Workbook

Sheet Итог-Модел CGE
A1: Модел CGE - SAM 2024-Баҳодиҳии пешакии нишондиҳандаҳои асосии макроиќтисодии Љумҳурии Тољикистон барои соли 2026 ва дурнамои он барои солҳои 2027-2029
A2: Нишондињандањо | B2: Воњиди ченак | C2: Соли 2022 | E2: Соли 2023 | G2: Соли 2024 | I2: Соли 2025 | K2: Соли 2026 | M2: Соли 2027 | O2: Соли 2028 | Q2: Соли 2029 | S2: Соли 2030 | U2: Соли 2031 | W2: Соли 2032 | Y2: 2024
C3: Воќеї | D3: нисбат ба соли 2021 (бо фоиз) | E3: Воќеї | F3: нисбат ба соли 2022 (бо фоиз) | G3: Воќеї | H3: нисбат ба соли 2023 (бо фоиз) | I3: Воќеї | J3: нисбат ба соли 2024 (бо фоиз) | K3: Бањодињї | L3: нисбат ба соли 2025 (бо фоиз) | M3: Дурнамо | N3: нисбат ба соли 2026 (бо фоиз) | O3: Дурнамо | P3: нисбат ба соли 2027 (бо фоиз) | Q3: Дурнамо | R3: нисбат ба соли 2027 (бо фоиз) | S3: Дурнамо | T3: нисбат ба соли 2027 (бо фоиз) | U3: Дурнамо | V3: нисбат ба соли 2027 (бо фоиз) | W3: Дурнамо | X3: нисбат ба соли 2027 (бо фоиз) | Z3: Соли 2023 | AB3: Соли 2024 | AD3: Соли 2025 | AF3: Соли 2026 | AH3: Соли 2027 | AJ3: Соли 2028 | AL3: Соли 2029 | AN3: Соли 2030 | AP3: Соли 2031 | AR3: Соли 2032
A4: Шумораи ањолї (ба њисоби миёнаи солона) | B4: Њазор нафар | C4: 9982.6 | D4: 101.8 | E4: 10183.3 | F4: =+E4/C4*100 -> 102.0105 | G4: 10398.4 | H4: =+G4/E4*100 -> 102.11228 | I4: 10614.691 | J4: =+I4/G4*100 -> 102.08004 | K4: =+I4*L4/100 -> 10837.6 | L4: 102.1 | M4: =+K4*N4/100 -> 11076.027 | N4: 102.2 | O4: =+M4*P4/100 -> 11319.699 | P4: 102.2 | Q4: =+O4*P4/100 -> 11568.733 | R4: 102.2 | S4: =+Q4*R4/100 -> 11823.245 | T4: 102.2 | U4: =+S4*T4/100 -> 12083.356 | V4: 102.2 | W4: =+U4*V4/100 -> 12349.19 | X4: 102.3 | Y4: 10382.1 | Z4: =C4*F4/100 -> 10183.3 | AA4: =E4/C4*100 -> 102.0105 | AB4: =E4*H4/100 -> 10398.4 | AC4: =G4/E4*100 -> 102.11228 | AD4: =G4*J4/100 -> 10614.691 | AE4: =I4/G4*100 -> 102.08004 | AF4: =I4*L4/100 -> 10837.6 | AG4: =K4/I4*100 -> 102.1 | AH4: =K4*N4/100 -> 11076.027 | AI4: =M4/K4*100 -> 102.2 | AJ4: =M4*P4/100 -> 11319.699 | AK4: =O4/M4*100 -> 102.2 | AL4: =O4*R4/100 -> 11568.733 | AM4: =Q4/O4*100 -> 102.2 | AN4: =Q4*T4/100 -> 11823.245 | AO4: =S4/Q4*100 -> 102.2 | AP4: =S4*V4/100 -> 12083.356 | AQ4: =U4/S4*100 -> 102.2 | AR4: =U4*X4/100 -> 12361.273 | AS4: =W4/U4*100 -> 102.2
A5: Маљмўи мањсулоти дохилї | B5: млн. сомонї | C5: 118181.7 | D5: 108.03592 | E5: 132781.9 | F5: 108.31977 | G5: 155783.9 | H5: 108.4 | I5: 176919 | J5: 108.4 | K5: =GDP!P19 -> 199898.14 | L5: =GDP!P36 -> 108.516 | M5: =GDP!Q19 -> 225457.17 | N5: =GDP!Q36 -> 108.37389 | O5: =GDP!R19 -> 254612 | P5: =GDP!R36 -> 108.6252 | Q5: =GDP!S19 -> 290957.14 | R5: =GDP!S36 -> 108.76495 | S5: =GDP!T19 -> 325987.62 | T5: =GDP!T36 -> 107.88215 | U5: =GDP!U19 -> 368330.85 | V5: =GDP!U36 -> 108.53792 | W5: =GDP!V19 -> 413970.34 | X5: =GDP!V36 -> 108.10939 | Y5: 153402.2 | Z5: =S5/I5*100 -> 184.25812
A6: Индекс-дефлятори ММД | B6: бо фоиз | D6: 108.22628 | F6: 103.7244 | H6: 108.2 | J6: 106.4 | L6: =GDP!P35 -> 104.12161 | N6: =GDP!Q35 -> 104.07122 | P6: =GDP!R35 -> 103.9643 | R6: =GDP!S35 -> 105.06575 | T6: =GDP!T35 -> 103.85382 | V6: =GDP!U35 -> 104.10115 | X6: =GDP!V35 -> 103.96034 | Z6: =S6/I6*100 -> #DIV/0!
A7: Таваррум | B7: бо фоиз | D7: 104.2 | F7: 103.8 | H7: 103.6 | J7: 103.5 | L7: ='6_Closures'!E20 -> 103.92894 | N7: ='6_Closures'!F20 -> 104.00219 | P7: ='6_Closures'!G20 -> 103.83918 | R7: ='6_Closures'!H20 -> 103.94069 | T7: ='6_Closures'!I20 -> 104.0531 | V7: ='6_Closures'!J20 -> 104.40046 | X7: ='6_Closures'!K20 -> 104.36099 | Z7: =S7/I7*100 -> #DIV/0!
A8: ММД ба њар нафар ањолї | B8: сомонї | C8: =+C5/C4*1000 -> 11838.769 | D8: =+C8/10312*100 -> 114.80576 | E8: =+E5/E4*1000 -> 13039.182 | F8: =+E8/C8*100 -> 110.13967 | G8: =+G5/G4*1000 -> 14981.526 | H8: =+G8/E8*100 -> 114.89621 | I8: =+I5/I4*1000 -> 16667.372 | J8: =+I8/G8*100 -> 111.25283 | K8: =+K5/K4*1000 -> 18444.873 | L8: =+K8/I8*100 -> 110.66455 | M8: =+M5/M4*1000 -> 20355.419 | N8: =+M8/K8*100 -> 110.35814 | O8: =+O5/O4*1000 -> 22492.824 | P8: =+O8/M8*100 -> 110.50042 | Q8: =+Q5/Q4*1000 -> 25150.304 | R8: =+Q8/O8*100 -> 111.81479 | S8: =+S5/S4*1000 -> 27571.756 | T8: =+S8/Q8*100 -> 109.62792 | U8: =+U5/U4*1000 -> 30482.496 | V8: =+U8/S8*100 -> 110.55696 | W8: =+W5/W4*1000 -> 33522.064 | X8: =+W8/U8*100 -> 109.97152 | Y8: =+Y5/Y4*1000 -> 14775.643 | Z8: =S8/I8*100 -> 165.42354
A9: Њаљми мањсулоти саноатї | B9: млн. сомонї | C9: 42221.4 | D9: 115.4 | E9: 46816 | F9: 112 | G9: 53819 | H9: 120 | I9: 66726.1 | J9: 122.1 | K9: ='GDP-total'!D30 -> 83491.033 | L9: ='2_Production_2'!X35 -> 125 | M9: ='GDP-total'!E30 -> 104885.61 | N9: ='2_Production_2'!Y35 -> 125 | O9: ='GDP-total'!F30 -> 131605.53 | P9: ='2_Production_2'!Z35 -> 125.1 | Q9: ='GDP-total'!G30 -> 164803.16 | R9: ='2_Production_2'!AA35 -> 125.1 | S9: ='GDP-total'!H30 -> 167868.34 | T9: ='2_Production_2'!AB35 -> 119.97633 | U9: ='GDP-total'!I30 -> 171881.64 | V9: ='2_Production_2'!AC35 -> 120.03604 | W9: ='GDP-total'!J30 -> 172763.33 | X9: ='2_Production_2'!AD35 -> 120.08717 | Z9: =S9/I9*100 -> 251.57824
A10: Њаљми мањсулоти кишоварзї | B10: млн. сомонї | C10: 61337.9 | D10: 108 | E10: 66907.2 | F10: 109 | G10: 73976.6 | H10: 110.6 | I10: 84653.8 | J10: 109.5 | K10: ='2_Production_2'!E21 -> 95155.45 | L10: ='2_Production_2'!X21 -> 108.92031 | M10: ='2_Production_2'!F21 -> 104590.97 | N10: ='2_Production_2'!Y21 -> 108.61255 | O10: ='2_Production_2'!G21 -> 114715.95 | P10: ='2_Production_2'!Z21 -> 108.27301 | Q10: ='2_Production_2'!H21 -> 125434.68 | R10: ='2_Production_2'!AA21 -> 108.15402 | S10: ='2_Production_2'!I21 -> 136949.67 | T10: ='2_Production_2'!AB21 -> 108.31356 | U10: ='2_Production_2'!J21 -> 148095.67 | V10: ='2_Production_2'!AC21 -> 107.60075 | W10: ='2_Production_2'!K21 -> 159589.19 | X10: ='2_Production_2'!AD21 -> 107.54578 | Z10: =S10/I10*100 -> 161.77616
A11: Маблаѓгузорї ба сармояи асосї аз њисоби њамаи манбаъњои маблаѓгузорї | B11: млн. сомонї | C11: 16279.5 | D11: 111.4 | E11: 19859 | F11: 121.98778 | G11: 22543 | H11: 108.4 | I11: 28736 | J11: 123 | K11: ='GDP-total'!D35 -> 32767.972 | L11: =+K11/I11*100 -> 114.03108 | M11: ='GDP-total'!E35 -> 38923.922 | N11: =+M11/K11*100 -> 118.78648 | O11: ='GDP-total'!F35 -> 44524.431 | P11: =+O11/M11*100 -> 114.38835 | Q11: ='GDP-total'!G35 -> 51375.484 | R11: =+Q11/O11*100 -> 115.38718 | S11: ='GDP-total'!H35 -> 55564.062 | T11: =+S11/Q11*100 -> 108.15287 | U11: ='GDP-total'!I35 -> 63254.949 | V11: =+U11/S11*100 -> 113.84148 | W11: ='GDP-total'!J35 -> 73256.893 | X11: =+W11/U11*100 -> 115.81211 | Z11: =S11/I11*100 -> 193.36046
A12: аз чумла аз њисоби буљети давлатї | B12: млн. сомонї | C12: 6736.9 | D12: 110.3 | E12: 7922.5 | F12: 117.5986 | G12: 9830.5 | H12: 118.5 | I12: 13280.5 | J12: 130.4 | K12: ='GDP-total'!D44 -> 14210.135 | L12: =+K12/I12*100 -> 107 | M12: ='GDP-total'!E44 -> 15631.149 | N12: =+M12/K12*100 -> 110 | O12: ='GDP-total'!F44 -> 16881.64 | P12: =+O12/M12*100 -> 108 | Q12: ='GDP-total'!G44 -> 18063.355 | R12: =+Q12/O12*100 -> 107 | S12: ='GDP-total'!H44 -> 18785.889 | T12: =+S12/Q12*100 -> 104 | U12: ='GDP-total'!I44 -> 19725.184 | V12: =+U12/S12*100 -> 105 | W12: ='GDP-total'!J44 -> 21697.702 | X12: =+W12/U12*100 -> 110 | Z12: =S12/I12*100 -> 141.45468
A13: Сармоягузории хориљї (қарз, грант, мустақим) | B13: млн. доллар | C13: 2577 | E13: 2690 | F13: 104.38494 | G13: 5126.6 | H13: =+G13/E13*100 -> 190.57993 | I13: =[1]OEA!$AF$34 -> 6925.3 | J13: =+I13/G13*100 -> 135.08563 | K13: =[1]OEA!$AG$34 -> 7624.7553 | L13: =+K13/I13*100 -> 110.1 | M13: =[1]OEA!$AH$34 -> 8562.6002 | N13: =+M13/K13*100 -> 112.3 | O13: =[1]OEA!$AI$34 -> 9598.6748 | P13: =+O13/M13*100 -> 112.1 | Q13: =[1]OEA!$AJ$34 -> 10769.713 | R13: =+Q13/O13*100 -> 112.2 | S13: =[1]OEA!$AK$34 -> 12094.388 | T13: =+S13/Q13*100 -> 112.3 | U13: =[1]OEA!$AL$34 -> 13545.714 | V13: =+U13/S13*100 -> 112 | W13: =[1]OEA!$AM$34 -> 15184.746 | X13: =+W13/U13*100 -> 112.1 | Z13: =S13/I13*100 -> 174.64063
A14: Њаљми умумии гардиши савдо дар њама соњањо | B14: млн. сомонї | C14: 47563.4 | D14: 111.2 | E14: 56124.4 | F14: 113.4 | G14: 65783.8 | H14: 113.6 | I14: 77307.1 | J14: 113.9 | K14: =[1]Household!$AG$81 -> 89946.541 | L14: =[1]Household!$AG$82 -> 114.15336 | M14: =[1]Household!$AH$81 -> 105319.77 | N14: =[1]Household!$AH$82 -> 114.4858 | O14: =[1]Household!$AI$81 -> 120054.47 | P14: =[1]Household!$AI$82 -> 113.559 | Q14: =[1]Household!$AJ$81 -> 138358.42 | R14: =[1]Household!$AJ$82 -> 113.89538 | S14: =[1]Household!$AK$81 -> 149157.72 | T14: =[1]Household!$AK$82 -> 108.35112 | U14: =[1]Household!$AL$81 -> 160879.07 | V14: =[1]Household!$AL$82 -> 109.75396 | W14: =[1]Household!$AM$81 -> 174656.34 | X14: =[1]Household!$AM$82 -> 109.31575 | Z14: =S14/I14*100 -> 192.94181 | AH14: =K13*L13/100 -> 8394.8556 | AI14: =M13/K13*100 -> 112.3
A15: аз он: гардиши савдои чакана | B15: млн. сомонї | C15: 39586.2 | D15: 110.2 | E15: 47540.5 | F15: 115.4 | G15: 55663 | H15: 113.5 | I15: 65705.6 | J15: 114.4 | K15: =[1]Household!$AG$84 -> 78696.141 | L15: =[1]Household!$AG$85 -> 114.0414 | M15: =[1]Household!$AH$84 -> 91582.412 | N15: =[1]Household!$AH$85 -> 114.2317 | O15: =[1]Household!$AI$84 -> 104395.19 | P15: =[1]Household!$AI$85 -> 113.33319 | Q15: =[1]Household!$AJ$84 -> 119274.5 | R15: =[1]Household!$AJ$85 -> 113.47425 | S15: =[1]Household!$AK$84 -> 129702.36 | T15: =[1]Household!$AK$85 -> 108.20577 | U15: =[1]Household!$AL$84 -> 139894.85 | V15: =[1]Household!$AL$85 -> 107.45769 | W15: =[1]Household!$AM$84 -> 151875.08 | X15: =[1]Household!$AM$85 -> 107.26362 | Z15: =S15/I15*100 -> 197.39925
A16: Њаљми хизматрасонињои пулакї дар њамаи соњањо | B16: млн. сомонї | C16: 18696.8 | D16: 116 | E16: 21760.3 | F16: 114.1 | G16: 25722.9 | H16: 113 | I16: 30470.2 | J16: 113.2 | K16: =[1]Household!$AG$88 -> 35439.755 | L16: =[1]Household!$AG$89 -> 114.93039 | M16: =[1]Household!$AH$88 -> 41254.485 | N16: =[1]Household!$AH$89 -> 113.90153 | O16: =[1]Household!$AI$88 -> 47612.182 | P16: =[1]Household!$AI$89 -> 113.70534 | Q16: =[1]Household!$AJ$88 -> 51548.635 | R16: =[1]Household!$AJ$89 -> 108.15958 | S16: =[1]Household!$AK$88 -> 56661.404 | T16: =[1]Household!$AK$89 -> 109.69894 | U16: =[1]Household!$AL$88 -> 62425.439 | V16: =[1]Household!$AL$89 -> 109.62465 | W16: =[1]Household!$AM$88 -> 64323.564 | X16: =[1]Household!$AM$89 -> 102.52799 | Z16: =S16/I16*100 -> 185.95678
A17: аз он: хизматрасонињои пулакї ба ањолї | B17: млн. сомонї | C17: 13866.9 | D17: 110.9 | E17: 16740.8 | F17: 118.4 | G17: 19094.9 | H17: 109 | I17: 22148.5 | J17: 110.9 | K17: =[1]Household!$AG$91 -> 25868.434 | L17: =[1]Household!$AG$92 -> 111.23374 | M17: =[1]Household!$AH$91 -> 29679.485 | N17: =[1]Household!$AH$92 -> 111.39072 | O17: =[1]Household!$AI$91 -> 33529.706 | P17: =[1]Household!$AI$92 -> 111.85412 | Q17: =[1]Household!$AJ$91 -> 37085.349 | R17: =[1]Household!$AJ$92 -> 110.49396 | S17: =[1]Household!$AK$91 -> 40763.6 | T17: =[1]Household!$AK$92 -> 108.83004 | U17: =[1]Household!$AL$91 -> 43351 | V17: =[1]Household!$AL$92 -> 105.81824 | W17: =[1]Household!$AM$91 -> 45945.403 | X17: =[1]Household!$AM$92 -> 103.90651 | Z17: =S17/I17*100 -> 184.04677
A18: Гардиши савдои хориљї | B18: млн. доллар | C18: 7309.5 | D18: 114.9 | E18: =+E19+E20 -> 8733.359 | F18: =+E18/C18*100 -> 119.47957 | G18: =+G19+G20 -> 8955.1 | H18: =+G18/E18*100 -> 102.53901 | I18: =+I19+I20 -> 10793.1 | J18: =+I18/G18*100 -> 120.52462 | K18: =+K19+K20 -> 11021.795 | L18: =+K18/I18*100 -> 102.1189 | M18: =+M19+M20 -> 11200.6 | N18: =+M18/K18*100 -> 101.62229 | O18: =+O19+O20 -> 11336.584 | P18: =+O18/M18*100 -> 101.21408 | Q18: =+Q19+Q20 -> 11664.552 | R18: =+Q18/O18*100 -> 102.89301 | S18: =+S19+S20 -> 11979.381 | T18: =+S18/Q18*100 -> 102.69902 | U18: =+U19+U20 -> 11976.135 | V18: =+U18/S18*100 -> 99.972908 | W18: =+W19+W20 -> 12300.515 | X18: =+W18/U18*100 -> 102.70855 | Z18: =S18/I18*100 -> 110.99111
A19: аз он: - содирот | C19: 2142 | D19: 99.6 | E19: =1861.478+243.5 -> 2104.978 | F19: =+E19/C19*100 -> 98.271615 | G19: 1947.5 | H19: =+G19/E19*100 -> 92.518782 | I19: 2487.9 | J19: =+I19/G19*100 -> 127.7484 | K19: ='5_IntTrade'!E74 -> 2672.7851 | L19: =+K19/I19*100 -> 107.43137 | M19: ='5_IntTrade'!F74 -> 2840.4586 | N19: =+M19/K19*100 -> 106.27336 | O19: ='5_IntTrade'!G74 -> 2973.4668 | P19: =+O19/M19*100 -> 104.68263 | Q19: ='5_IntTrade'!H74 -> 3140.6396 | R19: =+Q19/O19*100 -> 105.62215 | S19: ='5_IntTrade'!I74 -> 3298.4753 | T19: =+S19/Q19*100 -> 105.02559 | U19: ='5_IntTrade'!J74 -> 3051.7401 | V19: =+U19/S19*100 -> 92.51972 | W19: ='5_IntTrade'!K74 -> 3206.4144 | X19: =+W19/U19*100 -> 105.0684 | Z19: =S19/I19*100 -> 132.5807
A20: -воридот | C20: 5167.5 | D20: 122.8 | E20: =5880.1+748.281 -> 6628.381 | F20: =+E20/C20*100 -> 128.27056 | G20: 7007.6 | H20: =+G20/E20*100 -> 105.72114 | I20: 8305.2 | J20: =+I20/G20*100 -> 118.51704 | K20: ='5_IntTrade'!E75 -> 8349.0099 | L20: =+K20/I20*100 -> 100.5275 | M20: ='5_IntTrade'!F75 -> 8360.1413 | N20: =+M20/K20*100 -> 100.13333 | O20: ='5_IntTrade'!G75 -> 8363.1169 | P20: =+O20/M20*100 -> 100.03559 | Q20: ='5_IntTrade'!H75 -> 8523.9124 | R20: =+Q20/O20*100 -> 101.92268 | S20: ='5_IntTrade'!I75 -> 8680.9057 | T20: =+S20/Q20*100 -> 101.8418 | U20: ='5_IntTrade'!J75 -> 8924.3954 | V20: =+U20/S20*100 -> 102.80489 | W20: ='5_IntTrade'!K75 -> 9094.1011 | X20: =+W20/U20*100 -> 101.90159 | Z20: =S20/I20*100 -> 104.52374
G21: 2108.4 | J21: =I19/G21*100 -> 117.99943 | T21: =AVERAGE(L11,N11,P11,R11,T11) -> 114.14919
E22: =+G8-E8 -> 1942.3442 | F22: =+H8-F8 -> 4.7565408 | G22: =+I8-G8 -> 1685.8457 | H22: =+J8-H8 -> -3.6433823 | I22: =+K8-I8 -> 1777.501 | J22: =+L8-J8 -> -0.58827528 | K22: =+M8-K8 -> 1910.5465 | L22: =+N8-L8 -> -0.30641058 | ... N22: =+P8-N8 -> 0.14227548 | T22: =AVERAGE(L14,N14,P14,R14,T14) -> 112.88893
I23: =3119*109.8 -> 342466.2 | T23: =AVERAGE(L16,N16,P16,R16,T16) -> 112.07916
E24: =+E19/E18*100 -> 24.102731 | G24: =+G19/G18*100 -> 21.747384 | I24: =+I19/I18*100 -> 23.050838 | K24: =+K19/K18*100 -> 24.249998 | M24: =+M19/M18*100 -> 25.359879 | T24: =AVERAGE(L9,N9,P9,R9,T9) -> 124.03527
E25: =+E20/E18*100 -> 75.897269 | G25: =+G20/G18*100 -> 78.252616 | I25: =+I20/I18*100 -> 76.949162 | K25: =+K20/K18*100 -> 75.750002 | M25: =+M20/M18*100 -> 74.640121 | S25: =AVERAGE(K26,M26,O26,Q26,S26) -> 38.081699 | T25: =AVERAGE(L10,N10,P10,R10,T10) -> 108.45469
I26: =I12/I11*100 -> 46.215548 | K26: =K12/K11*100 -> 43.365928 | M26: =M12/M11*100 -> 40.158206 | O26: =O12/O11*100 -> 37.915455 | Q26: =Q12/Q11*100 -> 35.159484 | S26: =S12/S11*100 -> 33.809424 | T26: =S5/K5*100 -> 163.07686
C27: =C28+C29 -> 7013.824 | D27: =D28+D29 -> 0 | E27: =E28+E29 -> 8036.481 | F27: =F28+F29 -> 232.83271 | G27: =G28+G29 -> 9794.106 | H27: =H28+H29 -> 229.7365 | I27: =I28+I29 -> 10921.976 | J27: =J28+J29 -> 224.16668 | ... P27: =P28+P29 -> 214.68302 | T27: =S51/K51*100 -> 163.49721
A28: аз он: - содирот молњо ва хизматрасонї | C28: =[2]BoP!K14 -> 1752.9 | E28: =[2]BoP!L14 -> 2105 | F28: =+E28/C28*100 -> 120.08671 | G28: =[2]BoP!M14 -> 2108.405 | H28: =+G28/E28*100 -> 100.16176 | I28: =[2]BoP!N14 -> 2384.1837 | J28: =+I28/G28*100 -> 113.07997 | K28: =[2]BoP!O14 -> 2646.4817 | L28: =+K28/I28*100 -> 111.00158 | M28: =[2]BoP!P14 -> 2924.6196 | N28: =+M28/K28*100 -> 110.50973 | O28: =[2]BoP!Q14 -> 3161.1126 | P28: =+O28/M28*100 -> 108.08628 | T28: =S8/K8*100 -> 149.48195
A29: -воридот молњо ва хизматрасонї | C29: =[2]BoP!K15 -> 5260.924 | E29: =[2]BoP!L15 -> 5931.481 | F29: =+E29/C29*100 -> 112.74599 | G29: =[2]BoP!M15 -> 7685.701 | H29: =+G29/E29*100 -> 129.57474 | I29: =[2]BoP!N15 -> 8537.7923 | J29: =+I29/G29*100 -> 111.08671 | K29: =[2]BoP!O15 -> 11770.761 | L29: =+K29/I29*100 -> 137.86656 | M29: =[2]BoP!P15 -> 12569.072 | N29: =+M29/K29*100 -> 106.78216 | O29: =[2]BoP!Q15 -> 13398.221 | P29: =+O29/M29*100 -> 106.59674 | T29: =AVERAGE(L12,N12,P12,R12,T12) -> 107.2
A30: Ќурби миёнасолона (1 $ нисбат ба сомонї)* | C30: 11.0258 | D30: =+C30/11.3089*100 -> 97.496662 | E30: 10.8445 | F30: =+E30/C30*100 -> 98.355675 | G30: 10.7986 | H30: =+G30/E30*100 -> 99.576744 | I30: 10.0409 | J30: =+I30/G30*100 -> 92.98335 | K30: ='1_Prices'!E90 -> 9.176678 | L30: =+K30/I30*100 -> 91.392983 | M30: ='1_Prices'!F90 -> 9.414024 | N30: =+M30/K30*100 -> 102.5864 | O30: ='1_Prices'!G90 -> 9.692052 | P30: =+O30/M30*100 -> 102.95334 | Q30: ='1_Prices'!H90 -> 9.882669 | R30: =+Q30/O30*100 -> 101.96674 | S30: ='1_Prices'!I90 -> 10.01421 | T30: =+S30/Q30*100 -> 101.33103 | U30: ='1_Prices'!J90 -> 10.29836 | V30: =+U30/S30*100 -> 102.83747 | W30: ='1_Prices'!K90 -> 10.46302 | X30: =+W30/U30*100 -> 101.5989
E32: =E19/E18*100 -> 24.102731 | G32: =G19/G18*100 -> 21.747384 | I32: =I19/I18*100 -> 23.050838 | K32: =K19/K18*100 -> 24.249998 | M32: =M19/M18*100 -> 25.359879 | O32: =O19/O18*100 -> 26.22895
E33: =E20/E18*100 -> 75.897269 | G33: =G20/G18*100 -> 78.252616 | I33: =I20/I18*100 -> 76.949162 | K33: =K20/K18*100 -> 75.750002 | M33: =M20/M18*100 -> 74.640121 | O33: =O20/O18*100 -> 73.77105
I35: =I9/I5*1000 -> 377.15621 | K35: =K9/K5*1000 -> 417.66788 | M35: =M9/M5*1000 -> 465.21302 | O35: =O9/O5*1000 -> 516.88661 | Q35: =Q9/Q5*1000 -> 566.41731 | S35: =S9/S5*1000 -> 514.95314
L36: =L11+N11+P11+R11+T11 -> 570.74596
L37: =L36/5 -> 114.14919
L38: =L14+N14+P14+R14+T14 -> 564.44466
L39: =L38/5 -> 112.88893
L40: =L16+N16+P16+R16+T16 -> 560.39579
L41: =L40/5 -> 112.07916
L42: =L5+N5+P5+R5+T5 -> 542.1622
L43: =L42/5 -> 108.43244
K45: =S5/K5*100 -> 163.07686
K46: =S5-K5 -> 126089.47
K47: =K46/K5*100 -> 63.07686
K48: =K5/L6*100 -> 191985.26 | M48: =M5/N6*100 -> 216637.39 | S48: =S5/T6*100 -> 313890.82
K49: =S48/K48*100 -> 163.49735 | M49: =S48/M48*100 -> 144.89226
K50: =S8/K8*100 -> 149.48195
A51: реал.ВВП | I51: =G5*J5/100 -> 168869.75 | K51: =I5*L5/100 -> 191985.42 | M51: =K5*N5/100 -> 216637.39 | O51: =M5*P5/100 -> 244903.31 | Q51: =O5*R5/100 -> 276928.62 | S51: =Q5*T5/100 -> 313890.82 | Y51: =S51/I51*100 -> 185.87747
I52: 66.8 | K52: 66.2
I53: 33.2 | K53: =100-K52 -> 33.8
A54: -растанипарварї | I54: =I52*I10/100 -> 56548.738 | K54: =K52*K10/100 -> 62992.908
A55: чорвопарварї | I55: =I53*I10/100 -> 28105.062 | K55: =K53*K10/100 -> 32162.542
A56: ММД, млн.доллар бо курби расми | G56: =G5/G57 -> 14426.305 | I56: =I5/I57 -> 16247.423 | K56: =K5/K57 -> 18330.467 | M56: =M5/M57 -> 20536.32 | O56: =O5/O57 -> 22682.341 | Q56: =Q5/Q57 -> 28252.764 | S56: =S5/S57 -> 31156.169
A57: Ќурби миёнасолона (1 $ нисбат ба сомонї)* | G57: 10.7986 | H57: 99.576744 | I57: 10.88905 | J57: 100.83761 | K57: 10.90524 | L57: 100.14868 | M57: 10.97846 | N57: 100.67142 | O57: 11.22512 | P57: 102.24676 | Q57: ='1_Prices'!J90 -> 10.29836 | R57: =Q57/O57*100 -> 91.743874 | S57: ='1_Prices'!K90 -> 10.46302 | T57: =S57/Q57*100 -> 101.5989
A58: Ҳиссаи гардиши савдо дар ММД | C58: =C14/C5*100 -> 40.245994 | E58: =E14/E5*100 -> 42.26811 | G58: =G14/G5*100 -> 42.227599 | I58: =I14/I5*100 -> 43.696324 | K58: =K14/K5*100 -> 44.996187 | M58: =M14/M5*100 -> 46.713873 | O58: =O14/O5*100 -> 47.15193 | Q58: =Q14/Q5*100 -> 47.552853 | S58: =S14/S5*100 -> 45.755639
A59: Ҳиссаи содирот дар ММД | C59: =C19/C5*100 -> 1.8124634 | E59: =E19/E5*100 -> 1.5852899 | G59: =G19/G56*100 -> 13.499645 | I59: =I19/I56*100 -> 15.312582 | K59: =K19/K56*100 -> 14.581108 | M59: =M19/M56*100 -> 13.831391 | O59: =O19/O56*100 -> 13.109171 | Q59: =Q19/Q56*100 -> 11.11622 | S59: =S19/S56*100 -> 10.586909
A60: Ҳиссаи воридот дар ММД | C60: =C20/C5*100 -> 4.3725044 | E60: =E20/E5*100 -> 4.9919311 | G60: =G20/G56*100 -> 48.575154 | I60: =I20/I56*100 -> 51.11703 | K60: =K20/K56*100 -> 45.547175 | M60: =M20/M56*100 -> 40.709053 | O60: =O20/O56*100 -> 36.870607 | Q60: =Q20/Q56*100 -> 30.170189 | S60: =S20/S56*100 -> 27.862558
A63: Маљмўи мањсулоти дохилї | B63: млн.сомони | I63: 176919
A64: Шумораи ањолї (ба њисоби миёнаи солона) | I64: 10603.8 | J64: 10657 | K64: доими
A65: ММД ба њар нафар ањолї | B65: сомонї | I65: =I63/I64*1000 -> 16684.49
A66: Ќурби миёнасолона (1 $ нисбат ба сомонї)* | I66: 10.0409
A67: ММД ба њар нафар ањолї | B67: доллар | I67: =I65/I66 -> 1661.6529

Sheet посл.вар.
A1: Сенарияи шиддатнок-Нишондиҳандаҳои асосии макроиќтисодии Љумҳурии Тољикистон барои солҳои 2026-2030
A2: Нишондињандањо | B2: Воњиди ченак | C2: Соли 2022 | E2: Соли 2023 | G2: Соли 2024 | I2: Соли 2025 | K2: Соли 2026 | M2: Соли 2027 | O2: Соли 2028 | Q2: Соли 2029 | S2: Соли 2030 | U2: Соли 2031 | W2: Соли 2032 | Y2: 2024
C3: Воќеї | D3: нисбат ба соли 2021 (бо фоиз) | E3: Воќеї | F3: нисбат ба соли 2022 (бо фоиз) | G3: Воќеї | H3: нисбат ба соли 2023 (бо фоиз) | I3: Бањодињї | J3: нисбат ба соли 2024 (бо фоиз) | K3: Дурнамо | L3: нисбат ба соли 2025 (бо фоиз) | M3: Дурнамо | N3: нисбат ба соли 2026 (бо фоиз) | O3: Дурнамо | P3: нисбат ба соли 2027 (бо фоиз) | Q3: Дурнамо | R3: нисбат ба соли 2027 (бо фоиз) | S3: Дурнамо | T3: нисбат ба соли 2027 (бо фоиз) | U3: Дурнамо | V3: нисбат ба соли 2027 (бо фоиз) | W3: Дурнамо | X3: нисбат ба соли 2027 (бо фоиз) | Z3: Соли 2023 | AB3: Соли 2024 | AD3: Соли 2025 | AF3: Соли 2026 | AH3: Соли 2027 | AJ3: Соли 2028
A4: Шумораи ањолї (ба њисоби миёнаи солона) | B4: Њазор нафар | C4: 9982.6 | D4: 101.8 | E4: 10183.4 | F4: =+E4/C4*100 -> 102.0115 | G4: 10382.1 | H4: =+G4/E4*100 -> 101.95121 | I4: =+G4*J4/100 -> 10589.742 | J4: 102 | K4: =+I4*L4/100 -> 10812.127 | L4: 102.1 | M4: =+K4*N4/100 -> 11049.993 | N4: 102.2 | O4: =+M4*P4/100 -> 11304.143 | P4: 102.3 | Q4: =+O4*P4/100 -> 11564.139 | R4: 102.3 | S4: =+Q4*R4/100 -> 11830.114 | T4: 102.4 | U4: =+S4*T4/100 -> 12114.036 | V4: 102.4 | W4: =+U4*V4/100 -> 12404.773 | X4: 102.4 | Y4: 10382.1 | Z4: =C4*D4/100 -> 10162.287 | AA4: =E4/C4*100 -> 102.0115 | AB4: =E4*F4/100 -> 10388.239 | AC4: =G4/E4*100 -> 101.95121 | AD4: =G4*H4/100 -> 10584.677 | AE4: =I4/G4*100 -> 102 | AF4: =I4*J4/100 -> 10801.537 | AG4: =K4/I4*100 -> 102.1 | AH4: =K4*L4/100 -> 11039.181 | AI4: =M4/K4*100 -> 102.2 | AJ4: =M4*N4/100 -> 11293.093 | AK4: =O4/M4*100 -> 102.3
A5: Маљмўи мањсулоти дохилї | B5: млн. сомонї | C5: =+[2]GDP!K2 -> 118181.7 | D5: =+[2]GDP!K3 -> 108.03592 | E5: =+[2]GDP!L2 -> 132781.9 | F5: =+[2]GDP!L3 -> 108.31977 | G5: 153402.2 | H5: 108.4 | I5: ='Итог-Модел CGE'!I5 -> 176919 | J5: ='Итог-Модел CGE'!J5 -> 108.4 | K5: ='Итог-Модел CGE'!K5 -> 199898.14 | L5: ='Итог-Модел CGE'!L5 -> 108.516 | M5: ='Итог-Модел CGE'!M5 -> 225457.17 | N5: ='Итог-Модел CGE'!N5 -> 108.37389 | O5: ='Итог-Модел CGE'!O5 -> 254612 | P5: ='Итог-Модел CGE'!P5 -> 108.6252 | ... X5: ='Итог-Модел CGE'!X5 -> 108.10939 | Y5: 153402.2
A6: Индекс-дефлятори ММД | B6: бо фоиз | D6: =+[2]GDP!K4 -> 108.22628 | F6: =+[2]GDP!L4 -> 103.7244 | H6: 108.2 | J6: =GDP!Q35 -> 104.07122 | L6: =GDP!R35 -> 103.9643 | N6: =GDP!S35 -> 105.06575 | P6: =GDP!T35 -> 103.85382 | R6: =GDP!AN35 -> 104.10115 | T6: =GDP!AQ35 -> 103.96034 | V6: =GDP!AS35 -> 0 | X6: =GDP!AU35 -> 106.39305
A7: Таваррум | B7: бо фоиз | D7: =+[2]Monetary!K3 -> 106.6 | F7: 103.7 | H7: 103.6 | J7: ='Итог-Модел CGE'!J7 -> 103.5 | L7: ='Итог-Модел CGE'!L7 -> 103.92894 | N7: ='Итог-Модел CGE'!N7 -> 104.00219 | P7: ='Итог-Модел CGE'!P7 -> 103.83918 | R7: ='Итог-Модел CGE'!R7 -> 103.94069 | T7: ='Итог-Модел CGE'!T7 -> 104.0531 | V7: ='Итог-Модел CGE'!V7 -> 104.40046 | X7: ='Итог-Модел CGE'!X7 -> 104.36099
A8: ММД ба њар нафар ањолї | B8: сомонї | C8: =+C5/C4*1000 -> 11838.769 | D8: =+C8/10312*100 -> 114.80576 | E8: =+E5/E4*1000 -> 13039.054 | F8: =+E8/C8*100 -> 110.13859 | G8: =+G5/G4*1000 -> 14775.643 | H8: =+G8/E8*100 -> 113.31837 | I8: ='Итог-Модел CGE'!I8 -> 16667.372 | J8: ='Итог-Модел CGE'!J8 -> 111.25283 | K8: ='Итог-Модел CGE'!K8 -> 18444.873 | L8: ='Итог-Модел CGE'!L8 -> 110.66455 | M8: ='Итог-Модел CGE'!M8 -> 20355.419 | N8: ='Итог-Модел CGE'!N8 -> 110.35814 | O8: ='Итог-Модел CGE'!O8 -> 22492.824 | P8: ='Итог-Модел CGE'!P8 -> 110.50042 | ... X8: ='Итог-Модел CGE'!X8 -> 109.97152 | Y8: =+Y5/Y4*1000 -> 14775.643
A9: Њаљми мањсулоти саноатї | B9: млн. сомонї | C9: 42804.2 | D9: 115.4 | E9: =+[2]Industry!M4 -> 53819 | F9: =+[2]Industry!M18 -> 120 | G9: 53819 | H9: 120 | I9: ='Итог-Модел CGE'!I9 -> 66726.1 | J9: ='Итог-Модел CGE'!J9 -> 122.1 | K9: ='Итог-Модел CGE'!K9 -> 83491.033 | L9: ='Итог-Модел CGE'!L9 -> 125 | M9: ='Итог-Модел CGE'!M9 -> 104885.61 | N9: ='Итог-Модел CGE'!N9 -> 125 | O9: ='Итог-Модел CGE'!O9 -> 131605.53 | P9: ='Итог-Модел CGE'!P9 -> 125.1 | ... X9: ='Итог-Модел CGE'!X9 -> 120.08717
A10: Њаљми мањсулоти кишоварзї | B10: млн. сомонї | C10: 49272.4 | D10: 108 | E10: =+[2]Agriculture!L2 -> 63028.4 | F10: =+[2]Agriculture!L3 -> 109 | G10: 73981.3 | H10: 110.6 | I10: ='Итог-Модел CGE'!I10 -> 84653.8 | J10: ='Итог-Модел CGE'!J10 -> 109.5 | K10: ='Итог-Модел CGE'!K10 -> 95155.45 | L10: ='Итог-Модел CGE'!L10 -> 108.92031 | M10: ='Итог-Модел CGE'!M10 -> 104590.97 | N10: ='Итог-Модел CGE'!N10 -> 108.61255 | O10: ='Итог-Модел CGE'!O10 -> 114715.95 | P10: ='Итог-Модел CGE'!P10 -> 108.27301 | ... X10: ='Итог-Модел CGE'!X10 -> 107.54578
A11: Маблаѓгузорї ба сармояи асосї | B11: млн. сомонї | C11: 16279.5 | D11: 111.4 | E11: =+[2]OEA!L22 -> 19859 | F11: =+E11/C11*100 -> 121.98778 | G11: 22543 | H11: 108.4 | I11: ='Итог-Модел CGE'!I11 -> 28736 | J11: ='Итог-Модел CGE'!J11 -> 123 | K11: ='Итог-Модел CGE'!K11 -> 32767.972 | L11: ='Итог-Модел CGE'!L11 -> 114.03108 | M11: ='Итог-Модел CGE'!M11 -> 38923.922 | N11: ='Итог-Модел CGE'!N11 -> 118.78648 | O11: ='Итог-Модел CGE'!O11 -> 44524.431 | P11: ='Итог-Модел CGE'!P11 -> 114.38835 | ... X11: ='Итог-Модел CGE'!X11 -> 115.81211
A12: аз чумла аз њисоби буљети давлатї | B12: млн. сомонї | C12: 6736.9 | D12: 110.3 | E12: =+[2]OEA!L23 -> 7922.5 | F12: =+E12/C12*100 -> 117.5986 | G12: 9830.5 | H12: 118.5 | I12: ='GDP-total'!E44 -> 15631.149 | J12: =+I12/G12*100 -> 159.00665 | K12: ='GDP-total'!F44 -> 16881.64 | L12: =+K12/I12*100 -> 108 | M12: ='GDP-total'!G44 -> 18063.355 | N12: =+M12/K12*100 -> 107 | O12: ='GDP-total'!H44 -> 18785.889 | P12: =+O12/M12*100 -> 104 | Q12: ='GDP-total'!I44 -> 19725.184 | R12: =+Q12/O12*100 -> 105 | S12: ='GDP-total'!J44 -> 21697.702 | T12: =+S12/Q12*100 -> 110 | U12: ='GDP-total'!L44 -> 1421.0135 | V12: =+U12/S12*100 -> 6.5491428 | W12: ='GDP-total'!N44 -> 1181.7148 | X12: =+W12/U12*100 -> 83.16
A13: Сармоягузории хориљї (қарз, грант, мустақим) | B13: млн. доллар | C13: 2577 | E13: 2690 | F13: =+E13/C13*100 -> 104.38494 | G13: 4905.6 | H13: =+G13/E13*100 -> 182.36431 | I13: ='Итог-Модел CGE'!I13 -> 6925.3 | J13: ='Итог-Модел CGE'!J13 -> 135.08563 | K13: ='Итог-Модел CGE'!K13 -> 7624.7553 | L13: ='Итог-Модел CGE'!L13 -> 110.1 | M13: ='Итог-Модел CGE'!M13 -> 8562.6002 | N13: ='Итог-Модел CGE'!N13 -> 112.3 | O13: ='Итог-Модел CGE'!O13 -> 9598.6748 | P13: ='Итог-Модел CGE'!P13 -> 112.1 | ... X13: ='Итог-Модел CGE'!X13 -> 112.1
A14: Гардиши савдои дохилӣ | B14: млн. сомонї | C14: 47563.4 | D14: 111.2 | E14: =+[2]Household!L3 -> 56124.4 | F14: =+[2]Household!L4 -> 113.4 | G14: 65783.8 | H14: 113.6 | I14: ='Итог-Модел CGE'!I14 -> 77307.1 | J14: ='Итог-Модел CGE'!J14 -> 113.9 | K14: ='Итог-Модел CGE'!K14 -> 89946.541 | L14: ='Итог-Модел CGE'!L14 -> 114.15336 | M14: ='Итог-Модел CGE'!M14 -> 105319.77 | N14: ='Итог-Модел CGE'!N14 -> 114.4858 | O14: ='Итог-Модел CGE'!O14 -> 120054.47 | P14: ='Итог-Модел CGE'!P14 -> 113.559 | ... X14: ='Итог-Модел CGE'!X14 -> 109.31575 | AH14: =K13*L13/100 -> 8394.8556 | AI14: =M13/K13*100 -> 112.3
A15: аз он: гардиши савдои чакана | B15: млн. сомонї | C15: 39586.2 | D15: 110.2 | E15: =+[2]Household!L9 -> 47540.5 | F15: =+[2]Household!L11 -> 115.4 | G15: 55663 | H15: 113.5 | I15: =+[2]Household!N9 -> 63081.371 | J15: =+[2]Household!N11 -> 107.9169 | K15: =+[2]Household!O9 -> 71753.534 | L15: =+[2]Household!O11 -> 107.40849 | M15: =+[2]Household!P9 -> 79859.123 | N15: =+[2]Household!P11 -> 105.64028 | O15: =+[2]Household!Q9 -> 87893.051 | P15: =+[2]Household!Q11 -> 104.57593 | Q15: =[3]Household!$AJ$9 -> 96368.262 | R15: =+[4]Household!R11 -> 104.54414 | S15: =[3]Household!$AK$9 -> 111046.18 | T15: =[3]Household!$AK$11 -> 109.99728 | U15: =[3]Household!$AK$9 -> 111046.18 | V15: =[3]Household!$AK$11 -> 109.99728 | W15: =[3]Household!$AK$9 -> 111046.18 | X15: =[3]Household!$AK$11 -> 109.99728
A16: Хизматрасонии пулакї | B16: млн. сомонї | C16: 18696.8 | D16: 116 | E16: =+[2]Household!L15 -> 21760.3 | F16: =+[2]Household!L16 -> 114.1 | G16: 25722.9 | H16: 113 | I16: ='Итог-Модел CGE'!I16 -> 30470.2 | J16: ='Итог-Модел CGE'!J16 -> 113.2 | K16: ='Итог-Модел CGE'!K16 -> 35439.755 | L16: ='Итог-Модел CGE'!L16 -> 114.93039 | M16: ='Итог-Модел CGE'!M16 -> 41254.485 | N16: ='Итог-Модел CGE'!N16 -> 113.90153 | O16: ='Итог-Модел CGE'!O16 -> 47612.182 | P16: ='Итог-Модел CGE'!P16 -> 113.70534 | ... X16: ='Итог-Модел CGE'!X16 -> 102.52799
A17: аз он: хизматрасонињои пулакї ба ањолї | B17: млн. сомонї | C17: 13866.9 | D17: 110.9 | E17: =+[2]Household!L18 -> 16740.8 | F17: =+[2]Household!L20 -> 118.4 | G17: 19094.9 | H17: 109 | I17: =+[2]Household!N18 -> 20828.754 | J17: =+[2]Household!N20 -> 109.0802 | K17: =+[2]Household!O18 -> 23917.845 | L17: =+[2]Household!O20 -> 120.87462 | M17: =+[2]Household!P18 -> 26619.708 | N17: =+[2]Household!P20 -> 111.29643 | O17: =+[2]Household!Q18 -> 30111.508 | P17: =+[2]Household!Q20 -> 114.25995 | Q17: =+[4]Household!R18 -> 34438.528 | R17: =+[4]Household!R20 -> 105.42107 | S17: =+[4]Household!S18 -> 38378.647 | T17: =+[4]Household!S20 -> 107.15483 | U17: =+[4]Household!U18 -> 0 | V17: =+[4]Household!U20 -> 0 | W17: =+[4]Household!W18 -> 0 | X17: =+[4]Household!W20 -> 0
A18: Гардиши савдои хориљї | B18: млн. доллар | C18: 7309.5 | D18: 114.9 | E18: =+E19+E20 -> 8328.9 | F18: =+E18/C18*100 -> 113.94623 | G18: =+G19+G20 -> 8955 | H18: =+G18/E18*100 -> 107.5172 | I18: ='Итог-Модел CGE'!I18 -> 10793.1 | J18: ='Итог-Модел CGE'!J18 -> 120.52462 | K18: ='Итог-Модел CGE'!K18 -> 11021.795 | L18: ='Итог-Модел CGE'!L18 -> 102.1189 | M18: ='Итог-Модел CGE'!M18 -> 11200.6 | N18: ='Итог-Модел CGE'!N18 -> 101.62229 | O18: ='Итог-Модел CGE'!O18 -> 11336.584 | P18: ='Итог-Модел CGE'!P18 -> 101.21408 | ... X18: ='Итог-Модел CGE'!X18 -> 102.70855
A19: аз он: - содирот | C19: 2142 | D19: 99.6 | E19: =[2]Results!L31 -> 2448.8 | F19: =+E19/C19*100 -> 114.32306 | G19: 1947.4 | H19: =+G19/E19*100 -> 79.524665 | I19: ='5_IntTrade'!F74 -> 2840.4586 | J19: =+I19/G19*100 -> 145.85902 | K19: ='5_IntTrade'!G74 -> 2973.4668 | L19: =+K19/I19*100 -> 104.68263 | M19: ='5_IntTrade'!H74 -> 3140.6396 | N19: =+M19/K19*100 -> 105.62215 | O19: ='5_IntTrade'!I74 -> 3298.4753 | P19: =+O19/M19*100 -> 105.02559 | Q19: ='5_IntTrade'!J74 -> 3051.7401 | R19: =+Q19/O19*100 -> 92.51972 | S19: ='5_IntTrade'!K74 -> 3206.4144 | T19: =+S19/Q19*100 -> 105.0684
A20: -воридот | C20: 5167.5 | D20: 122.8 | E20: =[2]Results!L33 -> 5880.1 | F20: =+E20/C20*100 -> 113.79003 | G20: 7007.6 | H20: =+G20/E20*100 -> 119.17484 | I20: ='5_IntTrade'!F75 -> 8360.1413 | J20: =+I20/G20*100 -> 119.30106 | K20: ='5_IntTrade'!G75 -> 8363.1169 | L20: =+K20/I20*100 -> 100.03559 | M20: ='5_IntTrade'!H75 -> 8523.9124 | N20: =+M20/K20*100 -> 101.92268 | O20: ='5_IntTrade'!I75 -> 8680.9057 | P20: =+O20/M20*100 -> 101.8418 | Q20: ='5_IntTrade'!J75 -> 8924.3954 | R20: =+Q20/O20*100 -> 102.80489 | S20: ='5_IntTrade'!K75 -> 9094.1011 | T20: =+S20/Q20*100 -> 101.90159
G21: 2108.4 | J21: =I19/G21*100 -> 134.72105
E22: =+G8-E8 -> 1736.5889 | F22: =+H8-F8 -> 3.1797763 | G22: =+I8-G8 -> 1891.729 | H22: =+J8-H8 -> -2.0655362 | I22: =+K8-I8 -> 1777.501 | J22: =+L8-J8 -> -0.58827528 | K22: =+M8-K8 -> 1910.5465 | L22: =+N8-L8 -> -0.30641058 | ... N22: =+P8-N8 -> 0.14227548
I23: =3119*109.8 -> 342466.2
E24: =+E19/E18*100 -> 29.401241 | G24: =+G19/G18*100 -> 21.74651 | I24: =+I19/I18*100 -> 26.317357 | K24: =+K19/K18*100 -> 26.978063 | M24: =+M19/M18*100 -> 28.039923
E25: =+E20/E18*100 -> 70.598759 | G25: =+G20/G18*100 -> 78.25349 | I25: =+I20/I18*100 -> 77.458203 | K25: =+K20/K18*100 -> 75.877993 | M25: =+M20/M18*100 -> 76.102284
C27: =C28+C29 -> 7013.824 | D27: =D28+D29 -> 0 | E27: =E28+E29 -> 8036.481 | F27: =F28+F29 -> 232.83271 | G27: =G28+G29 -> 9794.106 | H27: =H28+H29 -> 229.7365 | I27: =I28+I29 -> 10921.976 | J27: =J28+J29 -> 224.16668 | ... P27: =P28+P29 -> 214.68302
A28: аз он: - содирот молњо ва хизматрасонї | C28: =[2]BoP!K14 -> 1752.9 | E28: =[2]BoP!L14 -> 2105 | F28: =+E28/C28*100 -> 120.08671 | G28: =[2]BoP!M14 -> 2108.405 | H28: =+G28/E28*100 -> 100.16176 | I28: =[2]BoP!N14 -> 2384.1837 | J28: =+I28/G28*100 -> 113.07997 | K28: =[2]BoP!O14 -> 2646.4817 | L28: =+K28/I28*100 -> 111.00158 | M28: =[2]BoP!P14 -> 2924.6196 | N28: =+M28/K28*100 -> 110.50973 | O28: =[2]BoP!Q14 -> 3161.1126 | P28: =+O28/M28*100 -> 108.08628
A29: -воридот молњо ва хизматрасонї | C29: =[2]BoP!K15 -> 5260.924 | E29: =[2]BoP!L15 -> 5931.481 | F29: =+E29/C29*100 -> 112.74599 | G29: =[2]BoP!M15 -> 7685.701 | H29: =+G29/E29*100 -> 129.57474 | I29: =[2]BoP!N15 -> 8537.7923 | J29: =+I29/G29*100 -> 111.08671 | K29: =[2]BoP!O15 -> 11770.761 | L29: =+K29/I29*100 -> 137.86656 | M29: =[2]BoP!P15 -> 12569.072 | N29: =+M29/K29*100 -> 106.78216 | O29: =[2]BoP!Q15 -> 13398.221 | P29: =+O29/M29*100 -> 106.59674
A30: Ќурби миёнасолона (1 $ нисбат ба сомонї)* | C30: 11.0258 | D30: =+C30/11.3089*100 -> 97.496662 | E30: 10.8445 | F30: =+E30/C30*100 -> 98.355675 | G30: 10.7986 | H30: =+G30/E30*100 -> 99.576744 | I30: ='1_Prices'!F90 -> 9.414024 | J30: =+I30/G30*100 -> 87.17819 | K30: ='1_Prices'!G90 -> 9.692052 | L30: =+K30/I30*100 -> 102.95334 | M30: ='1_Prices'!H90 -> 9.882669 | N30: =+M30/K30*100 -> 101.96674 | O30: ='1_Prices'!I90 -> 10.01421 | P30: =+O30/M30*100 -> 101.33103
E32: =E19/E18*100 -> 29.401241 | G32: =G19/G18*100 -> 21.74651 | I32: =I19/I18*100 -> 26.317357 | K32: =K19/K18*100 -> 26.978063 | M32: =M19/M18*100 -> 28.039923 | O32: =O19/O18*100 -> 29.095849
E33: =E20/E18*100 -> 70.598759 | G33: =G20/G18*100 -> 78.25349 | I33: =I20/I18*100 -> 77.458203 | K33: =K20/K18*100 -> 75.877993 | M33: =M20/M18*100 -> 76.102284 | O33: =O20/O18*100 -> 76.574266
I35: =I9/I5*1000 -> 377.15621 | K35: =K9/K5*1000 -> 417.66788 | M35: =M9/M5*1000 -> 465.21302 | O35: =O9/O5*1000 -> 516.88661 | Q35: =Q9/Q5*1000 -> 566.41731 | S35: =S9/S5*1000 -> 514.95314
L36: =L11+N11+P11+R11+T11 -> 570.74596
L37: =L36/5 -> 114.14919
L38: =L14+N14+P14+R14+T14 -> 564.44466
L39: =L38/5 -> 112.88893
L40: =L16+N16+P16+R16+T16 -> 560.39579
L41: =L40/5 -> 112.07916
L42: =L5+N5+P5+R5+T5 -> 542.1622
L43: =L42/5 -> 108.43244
K45: =S5/K5*100 -> 163.07686
K46: =S5-K5 -> 126089.47
K47: =K46/K5*100 -> 63.07686
K48: =K5/L6*100 -> 192275.76 | M48: =M5/N6*100 -> 214586.73 | S48: =S5/T6*100 -> 313569.21
K49: =S48/K48*100 -> 163.08307 | M49: =S48/M48*100 -> 146.12703
K50: =S8/K8*100 -> 149.48195
I52: 66.8 | K52: 66.2
I53: 33.2 | K53: =100-K52 -> 33.8
A54: -растанипарварї | I54: =I52*I10/100 -> 56548.738 | K54: =K52*K10/100 -> 62992.908
A55: чорвопарварї | I55: =I53*I10/100 -> 28105.062 | K55: =K53*K10/100 -> 32162.542

Sheet 2025-2029
A1: «Дар бораи дурнамои нишондиҳандаҳои асосии макроиќтисодии Љумҳурии Тољикистон барои солњои 2026-2029»
A2: Нишондињандањо | B2: Соли 2025 воќеї | D2: Соли 2026 баҳодиҳӣ | F2: Соли 2027 дурнамо | H2: Соли 2028 | J2: Соли 2029
B4: млрд. сомонї | C4: Рушд бо % | D4: млрд. сомонї | E4: Рушд бо % | F4: млрд. сомонї | G4: Рушд бо % | H4: млрд. сомонї | I4: Рушд бо % | J4: млрд. сомонї | K4: Рушд бо %
A5: Маљмўи мањсулоти дохилӣ | B5: ='Итог-Модел CGE'!I5/1000 -> 176.919 | C5: ='Итог-Модел CGE'!J5 -> 108.4 | D5: ='Итог-Модел CGE'!K5/1000 -> 199.89814 | E5: ='Итог-Модел CGE'!L5 -> 108.516 | F5: ='Итог-Модел CGE'!M5/1000 -> 225.45717 | G5: ='Итог-Модел CGE'!N5 -> 108.37389 | H5: ='Итог-Модел CGE'!O5/1000 -> 254.612 | I5: ='Итог-Модел CGE'!P5 -> 108.6252 | J5: ='Итог-Модел CGE'!Q5/1000 -> 290.95714 | K5: ='Итог-Модел CGE'!R5 -> 108.76495
A6: Маљмўи мањсулоти саноатї | B6: ='Итог-Модел CGE'!I9/1000 -> 66.7261 | C6: ='Итог-Модел CGE'!J9 -> 122.1 | D6: ='Итог-Модел CGE'!K9/1000 -> 83.491033 | E6: ='Итог-Модел CGE'!L9 -> 125 | F6: ='Итог-Модел CGE'!M9/1000 -> 104.88561 | G6: ='Итог-Модел CGE'!N9 -> 125 | H6: ='Итог-Модел CGE'!O9/1000 -> 131.60553 | I6: ='Итог-Модел CGE'!P9 -> 125.1 | J6: ='Итог-Модел CGE'!Q9/1000 -> 164.80316 | K6: ='Итог-Модел CGE'!R9 -> 125.1
A7: Маљмўи мањсулоти кишоварзї | B7: ='Итог-Модел CGE'!I10/1000 -> 84.6538 | C7: ='Итог-Модел CGE'!J10 -> 109.5 | D7: ='Итог-Модел CGE'!K10/1000 -> 95.15545 | E7: ='Итог-Модел CGE'!L10 -> 108.92031 | F7: ='Итог-Модел CGE'!M10/1000 -> 104.59097 | G7: ='Итог-Модел CGE'!N10 -> 108.61255 | H7: ='Итог-Модел CGE'!O10/1000 -> 114.71595 | I7: ='Итог-Модел CGE'!P10 -> 108.27301 | J7: ='Итог-Модел CGE'!Q10/1000 -> 125.43468 | K7: ='Итог-Модел CGE'!R10 -> 108.15402
A8: Маблаѓгузорї ба сармояи асосї | B8: ='Итог-Модел CGE'!I11/1000 -> 28.736 | C8: ='Итог-Модел CGE'!J11 -> 123 | D8: ='Итог-Модел CGE'!K11/1000 -> 32.767972 | E8: ='Итог-Модел CGE'!L11 -> 114.03108 | F8: ='Итог-Модел CGE'!M11/1000 -> 38.923922 | G8: ='Итог-Модел CGE'!N11 -> 118.78648 | H8: ='Итог-Модел CGE'!O11/1000 -> 44.524431 | I8: ='Итог-Модел CGE'!P11 -> 114.38835 | J8: ='Итог-Модел CGE'!Q11/1000 -> 51.375484 | K8: ='Итог-Модел CGE'!R11 -> 115.38718
A9: Сармоягузории хориҷӣ (қарз, грант, мустақим)
A10: Гардиши савдои дохилї | B10: ='Итог-Модел CGE'!I14/1000 -> 77.3071 | C10: ='Итог-Модел CGE'!J14 -> 113.9 | D10: ='Итог-Модел CGE'!K14/1000 -> 89.946541 | E10: ='Итог-Модел CGE'!L14 -> 114.15336 | F10: ='Итог-Модел CGE'!M14/1000 -> 105.31977 | G10: ='Итог-Модел CGE'!N14 -> 114.4858 | H10: ='Итог-Модел CGE'!O14/1000 -> 120.05447 | I10: ='Итог-Модел CGE'!P14 -> 113.559 | J10: ='Итог-Модел CGE'!Q14/1000 -> 138.35842 | K10: ='Итог-Модел CGE'!R14 -> 113.89538
A11: Хизматрасонии пулакї | B11: ='Итог-Модел CGE'!I16/1000 -> 30.4702 | C11: ='Итог-Модел CGE'!J16 -> 113.2 | D11: ='Итог-Модел CGE'!K16/1000 -> 35.439755 | E11: ='Итог-Модел CGE'!L16 -> 114.93039 | F11: ='Итог-Модел CGE'!M16/1000 -> 41.254485 | G11: ='Итог-Модел CGE'!N16 -> 113.90153 | H11: ='Итог-Модел CGE'!O16/1000 -> 47.612182 | I11: ='Итог-Модел CGE'!P16 -> 113.70534 | J11: ='Итог-Модел CGE'!Q16/1000 -> 51.548635 | K11: ='Итог-Модел CGE'!R16 -> 108.15958
A12: аз он: - ба ањолї | B12: ='Итог-Модел CGE'!I17/1000 -> 22.1485 | C12: ='Итог-Модел CGE'!J17 -> 110.9 | D12: ='Итог-Модел CGE'!K17/1000 -> 25.868434 | E12: ='Итог-Модел CGE'!L17 -> 111.23374 | F12: ='Итог-Модел CGE'!M17/1000 -> 29.679485 | G12: ='Итог-Модел CGE'!N17 -> 111.39072 | H12: ='Итог-Модел CGE'!O17/1000 -> 33.529706 | I12: ='Итог-Модел CGE'!P17 -> 111.85412 | J12: ='Итог-Модел CGE'!Q17/1000 -> 37.085349 | K12: ='Итог-Модел CGE'!R17 -> 110.49396
A13: Гардиши савдои хориљї (млн. доллар) | B13: ='Итог-Модел CGE'!I18 -> 10793.1 | C13: ='Итог-Модел CGE'!J18 -> 120.52462 | D13: ='Итог-Модел CGE'!K18 -> 11021.795 | E13: =+D13/B13*100 -> 102.1189 | F13: ='Итог-Модел CGE'!M18 -> 11200.6 | G13: =+F13/D13*100 -> 101.62229 | H13: ='Итог-Модел CGE'!O18 -> 11336.584 | I13: =+H13/F13*100 -> 101.21408 | J13: ='Итог-Модел CGE'!Q18 -> 11664.552 | K13: =+J13/H13*100 -> 102.89301
A14: аз он: - содирот | B14: ='Итог-Модел CGE'!I19 -> 2487.9 | C14: ='Итог-Модел CGE'!J19 -> 127.7484 | D14: ='Итог-Модел CGE'!K19 -> 2672.7851 | E14: =+D14/B14*100 -> 107.43137 | F14: ='Итог-Модел CGE'!M19 -> 2840.4586 | G14: =+F14/D14*100 -> 106.27336 | H14: ='Итог-Модел CGE'!O19 -> 2973.4668 | I14: =+H14/F14*100 -> 104.68263 | J14: ='Итог-Модел CGE'!Q19 -> 3140.6396 | K14: =+J14/H14*100 -> 105.62215
A15: -воридот | B15: ='Итог-Модел CGE'!I20 -> 8305.2 | C15: ='Итог-Модел CGE'!J20 -> 118.51704 | D15: ='Итог-Модел CGE'!K20 -> 8349.0099 | E15: =+D15/B15*100 -> 100.5275 | F15: ='Итог-Модел CGE'!M20 -> 8360.1413 | G15: =+F15/D15*100 -> 100.13333 | H15: ='Итог-Модел CGE'!O20 -> 8363.1169 | I15: =+H15/F15*100 -> 100.03559 | J15: ='Итог-Модел CGE'!Q20 -> 8523.9124 | K15: =+J15/H15*100 -> 101.92268
A16: Индекс-дефлятори ММД | B16: - | C16: ='Итог-Модел CGE'!J6 -> 106.4 | D16: - | E16: ='Итог-Модел CGE'!L6 -> 104.12161 | F16: - | G16: ='Итог-Модел CGE'!N6 -> 104.07122 | H16: - | I16: ='Итог-Модел CGE'!P6 -> 103.9643 | J16: - | K16: ='Итог-Модел CGE'!R6 -> 105.06575
A17: Сатњи таваррум* | B17: - | C17: ='Итог-Модел CGE'!J7-100 -> 3.5 | D17: - | E17: 4,0* | F17: - | G17: 3,5* | H17: - | I17: 3,7* | J17: - | K17: 4,2*
A18: Ќурби миёнасолона (1 $ нисбат ба сомонї)* | B18: ='Итог-Модел CGE'!I30 -> 10.0409 | C18: =+B18/10.7986*100 -> 92.98335 | D18: ='Итог-Модел CGE'!K30 -> 9.176678 | E18: =+D18/B18*100 -> 91.392983 | F18: ='Итог-Модел CGE'!M30 -> 9.414024 | G18: =+F18/D18*100 -> 102.5864 | H18: ='Итог-Модел CGE'!O30 -> 9.692052 | I18: =+H18/F18*100 -> 102.95334 | J18: ='Итог-Модел CGE'!Q30 -> 9.882669 | K18: =+J18/H18*100 -> 101.96674
A19: Ќурби миёнасолона (1 $ нисбат ба сомонї)* маълумоти Бонки миллии Тоҷикистон | B19: 10.0409 | C19: =+B19/10.7986*100 -> 92.98335 | E19: =+D19/B19*100 -> 0 | G19: =+F19/D19*100 -> #DIV/0! | I19: =+H19/F19*100 -> #DIV/0! | K19: =+J19/H19*100 -> #DIV/0!
A20: *-Нишондињандањои мазкур интишор карда намешаванд.
E22: ='6_Closures'!F20 -> 104.00219 | F22: ='6_Closures'!G20 -> 103.83918 | G22: ='6_Closures'!H20 -> 103.94069 | H22: ='6_Closures'!I20 -> 104.0531
E23: ='1_Prices'!F90 -> 9.414024 | F23: ='1_Prices'!G90 -> 9.692052 | G23: ='1_Prices'!H90 -> 9.882669 | H23: ='1_Prices'!I90 -> 10.01421
A24: ММД долл. | B24: =B5/B18 -> 17.619835 | D24: =D5/D18 -> 21.78328 | F24: =F5/F18 -> 23.949075 | H24: =H5/H18 -> 26.270185 | J24: =J5/J18 -> 29.44115
B25: =B14/B24 -> 141.19883
B28: 10793.1 | C28: 120.52462 | D28: 10621.795 | E28: 98.412829 | F28: 11030.6 | G28: 103.84874 | H28: 11336.584 | I28: 102.77395 | J28: 11664.552 | K28: 102.89301
B29: 2487.9 | C29: 127.7484 | D29: 2672.7851 | E29: 107.43137 | F29: 2840.4586 | G29: 106.27336 | H29: 2973.4668 | I29: 104.68263 | J29: 3140.6396 | K29: 105.62215
B30: 8305.2 | C30: 118.51704 | D30: 7949.0099 | E30: 95.71124 | F30: 8190.1413 | G30: 103.03348 | H30: 8363.1169 | I30: 102.112 | J30: 8523.9124 | K30: 101.92268

Sheet 1_Prices
B2: Block 1: Prices | E2: 0.923 | F2: 0.934 | G2: 0.9011 | H2: 0.90001 | I2: 0.88 | J2: 0.9301 | K2: 0.85
A3: 1 | B3: Source: p_grp | E3: 1.032 | F3: 1.012 | G3: 1.013 | H3: 1.011 | I3: 1.008 | J3: 1.005 | K3: 1.002
A4: Equation | B4: Gross Output prices | C4: 2024 | D4: =C4+1 -> 2025 | E4: =D4+1 -> 2026 | F4: =E4+1 -> 2027 | G4: =F4+1 -> 2028 | H4: =G4+1 -> 2029 | I4: =H4+1 -> 2030 | J4: =I4+1 -> 2031 | K4: =J4+1 -> 2032
A5: 1 | B5: Agriculture (p_a) | C5: 1.000879 | D5: 1.040396 | E5: 1.036174 | F5: 1.047091 | G5: 1.039209 | H5: 1.060155 | I5: 1.054533 | J5: 1.075063 | K5: 1.09542
A6: =A5+1 -> 2 | B6: Mining (p_mi) | C6: 1.009833 | D6: 1.031612 | E6: 1.041602 | F6: 0.905 | G6: 0.935 | H6: 0.935 | I6: 0.935 | J6: 0.905 | K6: 0.901
A7: =A6+1 -> 3 | B7: Manufacturing (p_m) | C7: 1.003147 | D7: 1.033837 | E7: 1.042326 | F7: 1.055848 | G7: 1.009 | H7: 1.009 | I7: 1.009 | J7: 0.91 | K7: 0.907
A8: =A7+1 -> 4 | B8: Energy and Water (p_e) | C8: 1.004254 | D8: 1.020014 | E8: 1.035124 | F8: 1.053312 | G8: 1.052226 | H8: 1.085796 | I8: 1.02 | J8: 1.076408 | K8: 1
A9: =A8+1 -> 5 | B9: Construction (p_c) | C9: 1 | D9: 1.06 | E9: 1.06 | F9: 1.07 | G9: 1.045 | H9: 1.021 | I9: 1.035 | J9: 1.045 | K9: 1.055
A10: =A9+1 -> 6 | B10: Transport (p_t) | C10: 1.004766 | D10: 1.025735 | E10: 1.049202 | F10: 1.088025 | G10: 1.094247 | H10: 1.146252 | I10: 1.088428 | J10: 1.1057 | K10: 1.12234
A11: =A10+1 -> 7 | B11: Trade (p_tr) | C11: 1.000093 | D11: 1.010111 | E11: 1.020294 | F11: 1.045241 | G11: 1.054977 | H11: 1.049495 | I11: 1.059468 | J11: 1.069699 | K11: 1.080588
A12: =A11+1 -> 8 | B12: Financial services (p_fs) | C12: 1.000483 | D12: 1.07119 | E12: 1.067118 | F12: 1.091531 | G12: 1.109512 | H12: 1.131571 | I12: 1.151267 | J12: 1.199551 | K12: 1.20014
A13: =A12+1 -> 9 | B13: Public Services (p_ps) | C13: 1.000129 | D13: 1.010253 | E13: 1.040199 | F13: 1.030356 | G13: 1.040031 | H13: 1.05068 | I13: 1.060781 | J13: 1.07104 | K13: 1.091057
A14: =A13+1 -> 10 | B14: Market Services (p_ms) | C14: 1.000181 | D14: 1.010285 | E14: 1.002134 | F14: 1.030502 | G14: 1.030043 | H14: 1.040947 | I14: 1.036071 | J14: 1.046373 | K14: 1.061275
B15: Source: pva_grp
B16: Value added prices | C16: 2024 | D16: =C16+1 -> 2025 | E16: =D16+1 -> 2026 | F16: =E16+1 -> 2027 | G16: =F16+1 -> 2028 | H16: =G16+1 -> 2029 | I16: =H16+1 -> 2030 | J16: =I16+1 -> 2031 | K16: =J16+1 -> 2032
A17: 11 | B17: Agriculture (pva_a) | C17: 0.9958141 | D17: 1.070785 | E17: 1.06048 | F17: 1.080147 | G17: 1.013892 | H17: 0.9705722 | I17: 0.939447 | J17: 0.8989173 | K17: 0.9359334
A18: =A17+1 -> 12 | B18: Mining (pva_mi) | C18: 1.020986 | D18: 1.224783 | E18: 1.251685 | F18: 1.285737 | G18: 0.9245005 | H18: 0.918577 | I18: 0.8939355 | J18: 0.8895337 | K18: 0.8938999
A19: =A18+1 -> 13 | B19: Manufacturing (pva_m) | C19: 0.9954861 | D19: 0.9831472 | E19: 1.049954 | F19: 0.9841733 | G19: 1.053318 | H19: 1.050349 | I19: 1.093903 | J19: 1.074273 | K19: 1.073668
A20: =A19+1 -> 14 | B20: Energy and Water (pva_e) | C20: 1.005361 | D20: 1.03293 | E20: 0.8565347 | F20: 0.8391973 | G20: 0.6327221 | H20: 0.6008687 | I20: 0.5893384 | J20: 0.5732561 | K20: 0.6060239
A21: =A20+1 -> 15 | B21: Construction (pva_c) | C21: 0.9369689 | D21: 1.068781 | E21: 1.147408 | F21: 1.190035 | G21: 1.191113 | H21: 1.180669 | I21: 1.21292 | J21: 1.254364 | K21: 1.285813
A22: =A21+1 -> 16 | B22: Transport (pva_t) | C22: 1.001906 | D22: 1.074133 | E22: 1.137099 | F22: 1.404508 | G22: 1.405637 | H22: 1.418685 | I22: 1.402125 | J22: 1.531533 | K22: 1.618333
A23: =A22+1 -> 17 | B23: Trade (pva_tr) | C23: 0.9921399 | D23: 0.9773986 | E23: 0.9218877 | F23: 0.9924737 | G23: 0.8944123 | H23: 0.8589714 | I23: 0.8436901 | J23: 0.8823803 | K23: 0.8588048
A24: =A23+1 -> 18 | B24: Financial services (pva_fs) | C24: 1.163395 | D24: 1.221282 | E24: 1.176507 | F24: 1.157249 | G24: 1.161612 | H24: 1.148914 | I24: 0.9496975 | J24: 0.9214652 | K24: 0.8862919
A25: =A24+1 -> 19 | B25: Public Services (pva_ps) | C25: 0.9988407 | D25: 0.913445 | E25: 0.9205453 | F25: 0.9186769 | G25: 0.9258954 | H25: 0.9460649 | I25: 0.959806 | J25: 0.9788029 | K25: 0.9945043
A26: =A25+1 -> 20 | B26: Market Services (pva_ms) | C26: 0.3277719 | D26: 0.2614986 | E26: 0.216421 | F26: 0.2325555 | G26: 0.1930372 | H26: 0.1889256 | I26: 0.1700383 | J26: 0.1637706 | K26: 0.171378
B27: Source: pc_grp
B28: Purchaser's price of commodity | C28: 2024 | D28: =C28+1 -> 2025 | E28: =D28+1 -> 2026 | F28: =E28+1 -> 2027 | G28: =F28+1 -> 2028 | H28: =G28+1 -> 2029 | I28: =H28+1 -> 2030 | J28: =I28+1 -> 2031 | K28: =J28+1 -> 2032
A29: 21 | B29: Agriculture (pc_a) | C29: 1.041787 | D29: 1.08291 | E29: 1.084011 | F29: 1.09741 | G29: 1.088556 | H29: 1.108769 | I29: 1.104173 | J29: 1.125941 | K29: 1.145297
A30: =A29+1 -> 22 | B30: Mining (pc_mi) | C30: 1.085293 | D30: 1.122346 | E30: 1.126317 | F30: 1.141462 | G30: 1.160984 | H30: 1.177234 | I30: 1.188016 | J30: 1.203188 | K30: 1.1988
A31: =A30+1 -> 23 | B31: Manufacturing (pc_m) | C31: 1.068337 | D31: 1.108502 | E31: 1.124811 | F31: 1.142457 | G31: 1.16831 | H31: 1.160557 | I31: 1.16397 | J31: 1.185302 | K31: 1.194204
A32: =A31+1 -> 24 | B32: Energy and Water (pc_e) | C32: 1.088096 | D32: 1.100802 | E32: 1.112357 | F32: 1.129743 | G32: 1.142269 | H32: 1.153639 | I32: 1.170466 | J32: 1.122482 | K32: 1.151509
A33: =A32+1 -> 25 | B33: Construction (pc_c) | C33: 1.049556 | D33: 1.114042 | E33: 1.114077 | F33: 1.133341 | G33: 1.099701 | H33: 1.077389 | I33: 1.092021 | J33: 1.103971 | K33: 1.114146
A34: =A33+1 -> 26 | B34: Transport (pc_t) | C34: 1.049271 | D34: 1.081324 | E34: 1.099591 | F34: 1.135001 | G34: 1.157018 | H34: 1.193628 | I34: 1.144873 | J34: 1.173816 | K34: 1.189199
A35: =A34+1 -> 27 | B35: Trade (pc_tr) | C35: 1.024319 | D35: 1.034606 | E35: 1.044913 | F35: 1.070499 | G35: 1.080781 | H35: 1.074683 | I35: 1.084934 | J35: 1.095225 | K35: 1.106508
A36: =A35+1 -> 28 | B36: Financial services (pc_fs) | C36: 1.122912 | D36: 1.187823 | E36: 1.218403 | F36: 1.233254 | G36: 1.262584 | H36: 1.290641 | I36: 1.307805 | J36: 1.362435 | K36: 1.364337
A37: =A36+1 -> 29 | B37: Public Services (pc_ps) | C37: 1.044415 | D37: 1.057326 | E37: 1.088405 | F37: 1.082075 | G37: 1.097818 | H37: 1.110595 | I37: 1.122551 | J37: 1.136072 | K37: 1.155637
A38: =A37+1 -> 30 | B38: Market Services (pc_ms) | C38: 1.031891 | D38: 1.063449 | E38: 1.089969 | F38: 1.122195 | G38: 1.155365 | H38: 1.170013 | I38: 1.190202 | J38: 1.227756 | K38: 1.249274
B39: Source: pe_grp
B40: Export prices | C40: 2024 | D40: =C40+1 -> 2025 | E40: =D40+1 -> 2026 | F40: =E40+1 -> 2027 | G40: =F40+1 -> 2028 | H40: =G40+1 -> 2029 | I40: =H40+1 -> 2030 | J40: =I40+1 -> 2031 | K40: =J40+1 -> 2032
A41: 31 | B41: Agriculture (pe_a) | C41: 1.029226 | D41: 1.053384 | E41: 1.07359 | F41: 1.111289 | G41: 1.158822 | H41: 1.202739 | I41: 1.205697 | J41: 1.238696 | K41: 1.267527
A42: =A41+1 -> 32 | B42: Mining (pe_mi) | C42: 1.029226 | D42: 1.054429 | E42: 1.07359 | F42: 1.09611 | G42: 1.138688 | H42: 1.161736 | I42: 1.182622 | J42: 1.226843 | K42: 1.237491
A43: =A42+1 -> 33 | B43: Manufacturing (pe_m) | C43: 1.029226 | D43: 1.065396 | E43: 1.100164 | F43: 1.138393 | G43: 1.180075 | H43: 1.178821 | I43: 1.194159 | J43: 1.226843 | K43: 1.249505
A44: =A43+1 -> 34 | B44: Energy and Water (pe_e) | C44: 1.029226 | D44: 1.075841 | E44: 1.116108 | F44: 1.149235 | G44: 1.202446 | H44: 1.230074 | I44: 1.246079 | J44: 1.303891 | K44: 1.285548
A45: =A44+1 -> 35 | B45: Construction (pe_c) | C45: 1.029226 | D45: 1.049728 | E45: 1.068275 | F45: 1.089605 | G45: 1.124147 | H45: 1.144652 | I45: 1.159546 | J45: 1.191282 | K45: 1.213462
A46: =A45+1 -> 36 | B46: Transport (pe_t) | C46: 1.029226 | D46: 1.054951 | E46: 1.094849 | F46: 1.132972 | G46: 1.174482 | H46: 1.2016 | I46: 1.194159 | J46: 1.238696 | K46: 1.26152
A47: =A46+1 -> 37 | B47: Trade (pe_tr) | C47: 1.029226 | D47: 1.044506 | E47: 1.105479 | F47: 1.11671 | G47: 1.152111 | H47: 1.184516 | I47: 1.18839 | J47: 1.25055 | K47: 1.237491
A48: =A47+1 -> 38 | B48: Financial services (pe_fs) | C48: 1.029226 | D48: 1.138511 | E48: 1.179886 | F48: 1.17634 | G48: 1.185667 | H48: 1.218684 | I48: 1.223004 | J48: 1.28611 | K48: 1.315585
A49: =A48+1 -> 39 | B49: Public Services (pe_ps) | C49: 1.029226 | D49: 1.065396 | E49: 1.084219 | F49: 1.105868 | G49: 1.152111 | H49: 1.184516 | I49: 1.211466 | J49: 1.262403 | K49: 1.285548
A50: =A49+1 -> 40 | B50: Market Services | C50: 1.029226 | D50: 1.054951 | E50: 1.094849 | F50: 1.105868 | G50: 1.140925 | H50: 1.173126 | I50: 1.182622 | J50: 1.226843 | K50: 1.231483
B51: Source: pm_grp
B52: Import prices | C52: 2024 | D52: =C52+1 -> 2025 | E52: =D52+1 -> 2026 | F52: =E52+1 -> 2027 | G52: =F52+1 -> 2028 | H52: =G52+1 -> 2029 | I52: =H52+1 -> 2030 | J52: =I52+1 -> 2031 | K52: =J52+1 -> 2032
A53: 41 | B53: Agriculture (pm_a) | C53: 1.121496 | D53: 1.155218 | E53: 1.285662 | F53: 1.358588 | G53: 1.383374 | H53: 1.389992 | I53: 1.421908 | J53: 1.465991 | K53: 1.453164
A54: =A53+1 -> 42 | B54: Mining (pm_mi) | C54: 1.111393 | D54: 1.195567 | E54: 1.193733 | F54: 1.223422 | G54: 1.268245 | H54: 1.303678 | I54: 1.314412 | J54: 1.375986 | K54: 1.375205
A55: =A54+1 -> 43 | B55: Manufacturing (pm_m) | C55: 1.109806 | D55: 1.162323 | E55: 1.194321 | F55: 1.222844 | G55: 1.266434 | H55: 1.283394 | I55: 1.275211 | J55: 1.316504 | K55: 1.327899
A56: =A55+1 -> 44 | B56: Energy and Water (pm_e) | C56: 1.173299 | D56: 1.22644 | E56: 1.254167 | F56: 1.297748 | G56: 1.35164 | H56: 1.376295 | I56: 1.407355 | J56: 1.445874 | K56: 1.465502
A57: =A56+1 -> 45 | B57: Construction (pm_c) | C57: 1.123951 | D57: 1.243294 | E57: 1.242045 | F57: 1.219486 | G57: 1.27036 | H57: 1.343284 | I57: 1.354462 | J57: 1.417422 | K57: 1.416984
A58: =A57+1 -> 46 | B58: Transport (pm_t) | C58: 1.094648 | D58: 1.166444 | E58: 1.175748 | F58: 1.193458 | G58: 1.219396 | H58: 1.253752 | I58: 1.286018 | J58: 1.333822 | K58: 1.348096
A59: =A58+1 -> 47 | B59: Trade (pm_tr) | C59: 1.099998 | D59: 1.138655 | E59: 1.192854 | F59: 1.205084 | G59: 1.243287 | H59: 1.272052 | I59: 1.288603 | J59: 1.33654 | K59: 1.361105
A60: =A59+1 -> 48 | B60: Financial services (pm_fs) | C60: 1.256466 | D60: 1.300622 | E60: 1.414437 | F60: 1.400325 | G60: 1.448813 | H60: 1.493316 | I60: 1.50007 | J60: 1.562832 | K60: 1.569382
A61: =A60+1 -> 49 | B61: Public Services (pm_ps) | C61: 1.107247 | D61: 1.134922 | E61: 1.166409 | F61: 1.183866 | G61: 1.23343 | H61: 1.262055 | I61: 1.284683 | J61: 1.319844 | K61: 1.331299
A62: =A61+1 -> 50 | B62: Market Services (pm_ms) | C62: 1.037126 | D62: 1.073574 | E62: 1.108608 | F62: 1.141669 | G62: 1.183497 | H62: 1.199346 | I62: 1.226578 | J62: 1.272093 | K62: 1.295416
B63: Source: pd_grp
B64: Domestic prices (including taxes) | C64: 2024 | D64: =C64+1 -> 2025 | E64: =D64+1 -> 2026 | F64: =E64+1 -> 2027 | G64: =F64+1 -> 2028 | H64: =G64+1 -> 2029 | I64: =H64+1 -> 2030 | J64: =I64+1 -> 2031 | K64: =J64+1 -> 2032
A65: 51 | B65: Agriculture (pd_a) | C65: 1.037499 | D65: 1.078999 | E65: 1.073811 | F65: 1.084186 | G65: 1.073811 | H65: 1.094561 | I65: 1.088336 | J65: 1.109086 | K65: 1.129836
A66: =A65+1 -> 52 | B66: Mining (pd_mi) | C66: 1.075938 | D66: 1.097457 | E66: 1.102837 | F66: 1.113596 | G66: 1.124355 | H66: 1.135115 | I66: 1.145874 | J66: 1.145874 | K66: 1.140494
A67: =A66+1 -> 53 | B67: Manufacturing (pd_m) | C67: 1.036027 | D67: 1.067108 | E67: 1.072288 | F67: 1.082648 | G67: 1.096117 | H67: 1.072288 | I67: 1.082648 | J67: 1.090936 | K67: 1.098189
A68: =A67+1 -> 54 | B68: Energy and Water (pd_e) | C68: 1.083838 | D68: 1.094676 | E68: 1.105514 | F68: 1.121772 | G68: 1.13261 | H68: 1.143449 | I68: 1.159706 | J68: 1.108766 | K68: 1.138029
A69: =A68+1 -> 55 | B69: Construction (pd_c) | C69: 1.047118 | D69: 1.109946 | E69: 1.109946 | F69: 1.120417 | G69: 1.094239 | H69: 1.069108 | I69: 1.083768 | J69: 1.094239 | K69: 1.10471
A70: =A69+1 -> 56 | B70: Transport (pd_t) | C70: 1.035189 | D70: 1.055893 | E70: 1.076596 | F70: 1.116969 | G70: 1.137672 | H70: 1.174939 | I70: 1.102476 | J70: 1.112828 | K70: 1.128356
A71: =A70+1 -> 57 | B71: Trade (pd_tr) | C71: 1.024192 | D71: 1.034433 | E71: 1.044675 | F71: 1.07028 | G71: 1.080522 | H71: 1.074377 | I71: 1.084619 | J71: 1.094861 | K71: 1.106127
A72: =A71+1 -> 58 | B72: Financial services (pd_fs) | C72: 1.061031 | D72: 1.135303 | E72: 1.129998 | F72: 1.156524 | G72: 1.177745 | H72: 1.198965 | I72: 1.220186 | J72: 1.271115 | K72: 1.271115
A73: =A72+1 -> 59 | B73: Public Services (pd_ps) | C73: 1.032773 | D73: 1.043101 | E73: 1.074084 | F73: 1.063756 | G73: 1.074084 | H73: 1.084412 | I73: 1.094739 | J73: 1.105067 | K73: 1.125722
A74: =A73+1 -> 60 | B74: Market Services (pd_ms) | C74: 1.007676 | D74: 1.017752 | E74: 1.009187 | F74: 1.037906 | G74: 1.037906 | H74: 1.047983 | I74: 1.042944 | J74: 1.053021 | K74: 1.068136
B75: Source: pci_grp
A76: 2 | B76: Intermediate Consumption price index | C76: 2024 | D76: =C76+1 -> 2025 | E76: =D76+1 -> 2026 | F76: =E76+1 -> 2027 | G76: =F76+1 -> 2028 | H76: =G76+1 -> 2029 | I76: =H76+1 -> 2030 | J76: =I76+1 -> 2031 | K76: =J76+1 -> 2032
A77: 61 | B77: Agriculture (pci_a) | C77: 1.055415 | D77: 1.095979 | E77: 1.103728 | F77: 1.119787 | G77: 1.123242 | H77: 1.135647 | I77: 1.134252 | J77: 1.153322 | K77: 1.169232
A78: =A77+1 -> 62 | B78: Mining (pci_mi) | C78: 1.072211 | D78: 1.112247 | E78: 1.125827 | F78: 1.14352 | G78: 1.164571 | H78: 1.163799 | I78: 1.168889 | J78: 1.187172 | K78: 1.194471
A79: =A78+1 -> 63 | B79: Manufacturing (pci_m) | C79: 1.06514 | D79: 1.104819 | E79: 1.116384 | F79: 1.133398 | G79: 1.148621 | H79: 1.153631 | I79: 1.15565 | J79: 1.174864 | K79: 1.185737
A80: =A79+1 -> 64 | B80: Energy and Water (pci_e) | C80: 1.074888 | D80: 1.112967 | E80: 1.123543 | F80: 1.141772 | G80: 1.155854 | H80: 1.161695 | I80: 1.168229 | J80: 1.177751 | K80: 1.186058
A81: =A80+1 -> 65 | B81: Construction (pci_c) | C81: 1.06742 | D81: 1.111093 | E81: 1.125362 | F81: 1.144051 | G81: 1.159625 | H81: 1.155119 | I81: 1.159175 | J81: 1.178863 | K81: 1.188643
A82: =A81+1 -> 66 | B82: Transport (pci_t) | C82: 1.07065 | D82: 1.110497 | E82: 1.127355 | F82: 1.148662 | G82: 1.168673 | H82: 1.176933 | I82: 1.172979 | J82: 1.193855 | K82: 1.204791
A83: =A82+1 -> 67 | B83: Trade (pci_tr) | C83: 1.072534 | D83: 1.114753 | E83: 1.131891 | F83: 1.151944 | G83: 1.170594 | H83: 1.17926 | I83: 1.179481 | J83: 1.204166 | K83: 1.21443
A84: =A83+1 -> 68 | B84: Financial services (pci_fs) | C84: 1.072667 | D84: 1.12537 | E84: 1.138248 | F84: 1.156538 | G84: 1.15908 | H84: 1.156344 | I84: 1.166231 | J84: 1.187783 | K84: 1.196892
A85: =A84+1 -> 69 | B85: Public Services (pci_ps) | C85: 1.07453 | D85: 1.118136 | E85: 1.135636 | F85: 1.153327 | G85: 1.17155 | H85: 1.175338 | I85: 1.180575 | J85: 1.20388 | K85: 1.213767
A86: =A85+1 -> 70 | B86: Market Services (pci_ms) | C86: 1.070244 | D86: 1.10854 | E86: 1.125184 | F86: 1.144532 | G86: 1.164623 | H86: 1.169772 | I86: 1.171932 | J86: 1.18952 | K86: 1.201825
B88: Nominal exchange rate | C88: 2024 | D88: =C88+1 -> 2025 | E88: =D88+1 -> 2026 | F88: =E88+1 -> 2027 | G88: =F88+1 -> 2028 | H88: =G88+1 -> 2029 | I88: =H88+1 -> 2030 | J88: =I88+1 -> 2031 | K88: =J88+1 -> 2032
A89: 71 | B89: e_1 | C89: 0.9327285 | D89: 0.9444087 | E89: 0.9629152 | F89: 0.98782 | G89: 1.016994 | H89: 1.036995 | I89: 1.050798 | J89: 1.080614 | K89: 1.097892
B90: e_TJS/USD | C90: 9.346694 | D90: 9.000309 | E90: 9.176678 | F90: 9.414024 | G90: 9.692052 | H90: 9.882669 | I90: 10.01421 | J90: 10.29836 | K90: 10.46302
B91: Source: w_1 | D91: 10.8445 | E91: =E90/D91*100 -> 84.620573 | F91: =F90/E90*100 -> 102.5864 | G91: =G90/F90*100 -> 102.95334 | H91: =H90/G90*100 -> 101.96674 | I91: =I90/H90*100 -> 101.33103 | J91: =J90/I90*100 -> 102.83747 | K91: =K90/J90*100 -> 101.5989
B92: Wages | C92: 2022 | D92: =C92+1 -> 2023 | E92: =D92+1 -> 2024 | F92: =E92+1 -> 2025 | G92: =F92+1 -> 2026 | H92: =G92+1 -> 2027 | I92: =H92+1 -> 2028 | J92: =I92+1 -> 2029 | K92: =J92+1 -> 2030
A93: 72 | B93: Total economy | C93: 1.007774 | D93: 1.007337 | E93: 1.006102 | F93: 1.004341 | G93: 1.003243 | H93: 1.002521 | I93: 1.001769 | J93: 1.000094 | K93: 0.9995255
B95: Prices determined exogenously
B96: Source: pl_grp
B97: Producer's prices | C97: 2024 | D97: =C97+1 -> 2025 | E97: =D97+1 -> 2026 | F97: =E97+1 -> 2027 | G97: =F97+1 -> 2028 | H97: =G97+1 -> 2029 | I97: =H97+1 -> 2030 | J97: =I97+1 -> 2031 | K97: =J97+1 -> 2032
A98: 73 | B98: Agriculture (pl_a) | C98: 1 | D98: 1.04 | E98: 1.035 | F98: 1.045 | G98: 1.035 | H98: 1.055 | I98: 1.049 | J98: 1.069 | K98: 1.089
A99: =A98+1 -> 74 | B99: Mining (pl_mi) | C99: 1 | D99: 1.02 | E99: 1.025 | F99: 1.035 | G99: 1.045 | H99: 1.055 | I99: 1.065 | J99: 1.065 | K99: 1.06
A100: =A99+1 -> 75 | B100: Manufacturing (pl_m) | C100: 1 | D100: 1.03 | E100: 1.035 | F100: 1.045 | G100: 1.058 | H100: 1.035 | I100: 1.045 | J100: 1.053 | K100: 1.06
A101: =A100+1 -> 76 | B101: Energy and Water (pl_e) | C101: 1 | D101: 1.01 | E101: 1.02 | F101: 1.035 | G101: 1.045 | H101: 1.055 | I101: 1.07 | J101: 1.023 | K101: 1.05
A102: =A101+1 -> 77 | B102: Construction (pl_c) | C102: 1 | D102: 1.06 | E102: 1.06 | F102: 1.07 | G102: 1.045 | H102: 1.021 | I102: 1.035 | J102: 1.045 | K102: 1.055
A103: =A102+1 -> 78 | B103: Transport (pl_t) | C103: 1 | D103: 1.02 | E103: 1.04 | F103: 1.079 | G103: 1.099 | H103: 1.135 | I103: 1.065 | J103: 1.075 | K103: 1.09
...

Sheet 2_Production_1
R1: 1-вар.
B2: Block 2: Production (1) | R2: Block 2: Production (1)
B4: Intermediate consumption of commodity i in industry j (in real terms) | R4: Intermediate consumption of commodity i in industry j (in real terms)
B5: Source: di_a_grp | R5: Source: di_a_grp
B6: Agriculture | C6: 2024 | D6: =C6+1 -> 2025 | E6: =D6+1 -> 2026 | F6: =E6+1 -> 2027 | G6: =F6+1 -> 2028 | H6: =G6+1 -> 2029 | I6: =H6+1 -> 2030 | J6: =I6+1 -> 2031 | K6: =J6+1 -> 2032 | L6: Description | R6: Agriculture | S6: 2024 | T6: =S6+1 -> 2025 | U6: =T6+1 -> 2026 | V6: =U6+1 -> 2027 | W6: =V6+1 -> 2028 | X6: =W6+1 -> 2029 | Y6: =X6+1 -> 2030 | Z6: =Y6+1 -> 2031 | AA6: =Z6+1 -> 2032 | AB6: Description
B7: di_a_a | C7: 22311.89 | D7: 23949.15 | E7: 25153.86 | F7: 26119.58 | G7: 26875.09 | H7: 27778.03 | I7: 28209.41 | J7: 28862.45 | K7: 30113.7 | L7: Intermediate consumption of agriculture paid for agr, Commodities | R7: di_a_a | S7: 16464.13 | T7: 17682.88 | U7: 18563.21 | V7: 19275.91 | W7: 19841.17 | X7: 20509.8 | Y7: 20831.11 | Z7: 21312.3 | AA7: 22235.73 | AB7: Intermediate consumption of agriculture paid for agr, Commodities
B8: di_mi_a | C8: 296.3033 | D8: 318.0463 | E8: 334.0449 | F8: 346.8697 | G8: 356.903 | H8: 368.8941 | I8: 374.6229 | J8: 383.2953 | K8: 399.9119 | L8: Intermediate consumption of agriculture paid for mining commodities | R8: di_mi_a | S8: 218.6448 | T8: 234.8299 | U8: 246.5207 | V8: 255.9854 | W8: 263.492 | X8: 272.3715 | Y8: 276.6386 | Z8: 283.0287 | AA8: 295.2919 | AB8: Intermediate consumption of agriculture paid for mining commodities
B9: di_m_a | C9: 9523.852 | D9: 10222.72 | E9: 10736.95 | F9: 11149.17 | G9: 11471.66 | H9: 11857.08 | I9: 12041.22 | J9: 12319.97 | K9: 12854.06 | L9: Intermediate consumption of agriculture paid for manufact, Commodities | R9: di_m_a | S9: 7027.731 | T9: 7547.957 | U9: 7923.725 | V9: 8227.944 | W9: 8469.223 | X9: 8754.629 | Y9: 8891.782 | Z9: 9097.176 | AA9: 9491.343 | AB9: Intermediate consumption of agriculture paid for manufact, Commodities
B10: di_e_a | C10: 2353.256 | D10: 2525.94 | E10: 2653.002 | F10: 2754.857 | G10: 2834.542 | H10: 2929.776 | I10: 2975.274 | J10: 3044.151 | K10: 3176.121 | L10: Intermediate consumption of agriculture paid for energy commodities | R10: di_e_a | S10: 1736.488 | T10: 1865.031 | U10: 1957.88 | V10: 2033.049 | W10: 2092.667 | X10: 2163.188 | Y10: 2197.078 | Z10: 2247.829 | AA10: 2345.224 | AB10: Intermediate consumption of agriculture paid for energy commodities
B11: di_c_a | C11: 1577.79 | D11: 1693.57 | E11: 1778.761 | F11: 1847.052 | G11: 1900.478 | H11: 1964.33 | I11: 1994.835 | J11: 2041.015 | K11: 2129.497 | L11: Intermediate consumption of agriculture paid for construct, Commodities | R11: di_c_a | S11: 1164.265 | T11: 1250.449 | U11: 1312.702 | V11: 1363.101 | W11: 1403.073 | X11: 1450.355 | Y11: 1473.077 | Z11: 1507.104 | AA11: 1572.405 | AB11: Intermediate consumption of agriculture paid for construct, Commodities
B12: di_t_a | C12: 1893.044 | D12: 2031.957 | E12: 2134.17 | F12: 2216.106 | G12: 2280.208 | H12: 2356.817 | I12: 2393.418 | J12: 2448.825 | K12: 2554.986 | L12: Intermediate consumption of agriculture paid for trans, Services | R12: di_t_a | S12: 1396.893 | T12: 1500.298 | U12: 1574.989 | V12: 1635.458 | W12: 1683.417 | X12: 1740.147 | Y12: 1767.408 | Z12: 1808.234 | AA12: 1886.583 | AB12: Intermediate consumption of agriculture paid for trans, Services
B13: di_tr_a | C13: 110.991 | D13: 119.1356 | E13: 125.1284 | F13: 129.9324 | G13: 133.6907 | H13: 138.1824 | I13: 140.3283 | J13: 143.5769 | K13: 149.8012 | L13: Intermediate consumption of agriculture paid for trade services | R13: di_tr_a | S13: 81.90118 | T13: 87.96389 | U13: 92.34309 | V13: 95.88845 | W13: 98.70032 | X13: 102.0264 | Y13: 103.6248 | Z13: 106.0185 | AA13: 110.6121 | AB13: Intermediate consumption of agriculture paid for trade services
B14: di_fs_a | C14: 1881.664 | D14: 2019.742 | E14: 2121.341 | F14: 2202.784 | G14: 2266.5 | H14: 2342.65 | I14: 2379.03 | J14: 2434.104 | K14: 2539.627 | L14: Intermediate consumption of agriculture paid for fin, services | R14: di_fs_a | S14: 1388.496 | T14: 1491.279 | U14: 1565.521 | V14: 1625.627 | W14: 1673.297 | X14: 1729.686 | Y14: 1756.784 | Z14: 1797.364 | AA14: 1875.241 | AB14: Intermediate consumption of agriculture paid for fin, services
B15: di_ps_a | C15: 140.9403 | D15: 151.2826 | E15: 158.8925 | F15: 164.9928 | G15: 169.7652 | H15: 175.4689 | I15: 178.1939 | J15: 182.319 | K15: 190.2229 | L15: Intermediate consumption of agriculture paid for public services | R15: di_ps_a | S15: 104.001 | T15: 111.6997 | U15: 117.2605 | V15: 121.7626 | W15: 125.3332 | X15: 129.5568 | Y15: 131.5865 | Z15: 134.626 | AA15: 140.4592 | AB15: Intermediate consumption of agriculture paid for public services
B16: di_ms_a | C16: 250.3777 | D16: 268.7507 | E16: 282.2696 | F16: 293.1066 | G16: 301.5847 | H16: 311.7173 | I16: 316.5581 | J16: 323.8863 | K16: 337.9274 | L16: Intermediate consumption of agriculture paid market services | R16: di_ms_a | S16: 184.7559 | T16: 198.4324 | U16: 208.3111 | V16: 216.3089 | W16: 222.652 | X16: 230.1552 | Y16: 233.7609 | Z16: 239.1606 | AA16: 249.5231 | AB16: Intermediate consumption of agriculture paid market services
B17: ci_a | C17: 40340.11 | D17: 43300.3 | E17: 45478.42 | F17: 47224.45 | G17: 48590.42 | H17: 50222.95 | I17: 51002.89 | J17: 52183.59 | K17: 54445.85 | L17: Total intermediate consumption in agricultural sector | N17: =C17/'2_Production_2'!AX21*100 -> 51.725265 | R17: ci_a | S17: 29767.31 | T17: 31970.83 | U17: 33562.46 | V17: 34851.04 | W17: 35873.03 | X17: 37081.92 | Y17: 37662.85 | Z17: 38532.84 | AA17: 40202.41 | AB17: Total intermediate consumption in agricultural sector | AD17: =S17/'2_Production_2'!AX21*100 -> 38.168513 | AE17: 51.66246
L18: = expenses of agriculture on the intermediate consumption | AB18: = expenses of agriculture on the intermediate consumption
B19: ci_a_im | C19: 5552.509 | D19: 5959.957 | E19: 6259.759 | F19: 6500.087 | G19: 6688.102 | H19: 6912.808 | I19: 7020.161 | J19: 7182.675 | K19: 7494.058 | L19: of which the intermediate consumption of imported goods | R19: ci_a_im | S19: 4097.244 | T19: 4400.541 | U19: 4619.618 | V19: 4796.981 | W19: 4937.649 | X19: 5104.044 | Y19: 5184.005 | Z19: 5303.753 | AA19: 5533.556 | AB19: of which the intermediate consumption of imported goods
B20: Source: di_mi_grp | R20: Source: di_mi_grp
B21: Mining | C21: 2024 | D21: =C21+1 -> 2025 | E21: =D21+1 -> 2026 | F21: =E21+1 -> 2027 | G21: =F21+1 -> 2028 | H21: =G21+1 -> 2029 | I21: =H21+1 -> 2030 | J21: =I21+1 -> 2031 | K21: =J21+1 -> 2032 | L21: Description | R21: Mining | S21: 2024 | T21: =S21+1 -> 2025 | U21: =T21+1 -> 2026 | V21: =U21+1 -> 2027 | W21: =V21+1 -> 2028 | X21: =W21+1 -> 2029 | Y21: =X21+1 -> 2030 | Z21: =Y21+1 -> 2031 | AA21: =Z21+1 -> 2032 | AB21: Description
B22: di_a_mi | C22: 0 | D22: 0 | E22: 0 | F22: 0 | G22: 0 | H22: 0 | I22: 0 | J22: 0 | K22: 0 | L22: Intermediate consumption of mining paid for agr. commodities | R22: di_a_mi | S22: 0 | T22: 0 | U22: 0 | V22: 0 | W22: 0 | X22: 0 | Y22: 0 | Z22: 0 | AA22: 0 | AB22: Intermediate consumption of mining paid for agr. commodities
B23: di_mi_mi | C23: 1160.229 | D23: 1444.166 | E23: 1537.133 | F23: 1630.58 | G23: 1692.322 | H23: 1757.118 | I23: 1831.811 | J23: 1926.386 | K23: 2015.434 | L23: Intermediate consumption of mining paid for mining commodities | R23: di_mi_mi | S23: 533.6855 | T23: 664.2057 | U23: 707.0685 | V23: 749.2703 | W23: 779.4724 | X23: 809.5709 | Y23: 844.9853 | Z23: 889.1173 | AA23: 930.2194 | AB23: Intermediate consumption of mining paid for mining commodities
B24: di_m_mi | C24: 4107.026 | D24: 5112.116 | E24: 5441.204 | F24: 5771.992 | G24: 5990.549 | H24: 6219.918 | I24: 6484.318 | J24: 6819.1 | K24: 7134.316 | L24: Intermediate consumption of mining paid for manufact, commodities | R24: di_m_mi | S24: 1889.162 | T24: 2351.182 | U24: 2502.91 | V24: 2652.297 | W24: 2759.208 | X24: 2865.752 | Y24: 2991.113 | Z24: 3147.333 | AA24: 3292.828 | AB24: Intermediate consumption of mining paid for manufact, commodities
B25: di_e_mi | C25: 249.9291 | D25: 311.0928 | E25: 331.1191 | F25: 351.2489 | G25: 364.549 | H25: 378.507 | I25: 394.5968 | J25: 414.9697 | K25: 434.1518 | L25: Intermediate consumption of mining paid for energy commodities | R25: di_e_mi | S25: 114.9631 | T25: 143.0789 | U25: 152.3121 | V25: 161.403 | W25: 167.9089 | X25: 174.3925 | Y25: 182.0213 | Z25: 191.5279 | AA25: 200.3818 | AB25: Intermediate consumption of mining paid for energy commodities
B26: di_c_mi | C26: 315.201 | D26: 392.3385 | E26: 417.5949 | F26: 442.9818 | G26: 459.7554 | H26: 477.3587 | I26: 497.6505 | J26: 523.344 | K26: 547.5358 | L26: Intermediate consumption of mining paid for construct, commodities | R26: di_c_mi | S26: 144.9871 | T26: 180.4457 | U26: 192.0903 | V26: 203.5553 | W26: 211.7603 | X26: 219.9372 | Y26: 229.5583 | Z26: 241.5477 | AA26: 252.714 | AB26: Intermediate consumption of mining paid for construct, commodities
B27: di_t_mi | C27: 166.0148 | D27: 206.6427 | E27: 219.9451 | F27: 233.3163 | G27: 242.1508 | H27: 251.4224 | I27: 262.11 | J27: 275.6426 | K27: 288.3843 | L27: Intermediate consumption of mining paid for trans, Services | R27: di_t_mi | S27: 76.36395 | T27: 95.03981 | U27: 101.173 | V27: 107.2115 | W27: 111.5331 | X27: 115.8398 | Y27: 120.9072 | Z27: 127.2219 | AA27: 133.1032 | AB27: Intermediate consumption of mining paid for trans, Services
B28: di_tr_mi | C28: 64.15786 | D28: 79.85887 | E28: 84.99971 | F28: 90.16711 | G28: 93.58129 | H28: 97.16438 | I28: 101.2947 | J28: 106.5245 | K28: 111.4486 | L28: Intermediate consumption of mining paid for trade services | R28: di_tr_mi | S28: 29.51152 | T28: 36.72897 | U28: 39.09917 | V28: 41.43283 | W28: 43.10294 | X28: 44.76731 | Y28: 46.72564 | Z28: 49.16603 | AA28: 51.43888 | AB28: Intermediate consumption of mining paid for trade services
B29: di_fs_mi | C29: 226.265 | D29: 281.6376 | E29: 299.7678 | F29: 317.9916 | G29: 330.0324 | H29: 342.6689 | I29: 357.2352 | J29: 375.6791 | K29: 393.045 | L29: Intermediate consumption of mining paid for fin, services | R29: di_fs_mi | S29: 104.078 | T29: 129.5318 | U29: 137.8907 | V29: 146.1208 | W29: 152.0108 | X29: 157.8805 | Y29: 164.7869 | Z29: 173.3934 | AA29: 181.4091 | AB29: Intermediate consumption of mining paid for fin, services
B30: di_ps_mi | C30: 9.354959 | D30: 11.64435 | E30: 12.39394 | F30: 13.14741 | G30: 13.64524 | H30: 14.16769 | I30: 14.76994 | J30: 15.53251 | K30: 16.2505 | L30: Intermediate consumption of mining paid for public services | R30: di_ps_mi | S30: 4.303121 | T30: 5.355508 | U30: 5.701112 | V30: 6.041387 | W30: 6.284907 | X30: 6.527592 | Y30: 6.813139 | Z30: 7.168976 | AA30: 7.500384 | AB30: Intermediate consumption of mining paid for public services
B31: di_ms_mi | C31: 10.54939 | D31: 13.13109 | E31: 13.97639 | F31: 14.82606 | G31: 15.38745 | H31: 15.97661 | I31: 16.65575 | J31: 17.51568 | K31: 18.32535 | L31: Intermediate consumption of mining paid for market services | R31: di_ms_mi | S31: 4.852539 | T31: 6.039294 | U31: 6.429024 | V31: 6.812745 | W31: 7.087357 | X31: 7.361028 | Y31: 7.683034 | Z31: 8.084304 | AA31: 8.458025 | AB31: Intermediate consumption of mining paid for market services
B32: ci_mi | C32: 6308.727 | D32: 7852.628 | E32: 8358.133 | F32: 8866.251 | G32: 9201.972 | H32: 9554.302 | I32: 9960.441 | J32: 10474.69 | K32: 10958.89 | L32: Total intermediate consumption in mining sector | N32: =C32/'2_Production_2'!AX23*100 -> 49.81371 | R32: ci_mi | S32: 2901.906 | T32: 3611.608 | U32: 3844.673 | V32: 4074.145 | W32: 4238.368 | X32: 4402.028 | Y32: 4594.594 | Z32: 4834.561 | AA32: 5058.053 | AB32: Total intermediate consumption in mining sector | AD32: =S32/'2_Production_2'!AX23*100 -> 22.91345 | AE32: 49.102771
L33: = expenses of mining on the intermediate consumption | AB33: = expenses of mining on the intermediate consumption
B34: ci_mi_im | C34: 2019.652 | D34: 2513.91 | E34: 2675.741 | F34: 2838.408 | G34: 2945.884 | H34: 3058.678 | I34: 3188.698 | J34: 3353.329 | K34: 3508.338 | L34: of which the intermediate consumption of imported goods | R34: ci_mi_im | S34: 929.0052 | T34: 1156.206 | U34: 1230.819 | V34: 1304.281 | W34: 1356.855 | X34: 1409.249 | Y34: 1470.896 | Z34: 1547.718 | AA34: 1619.266 | AB34: of which the intermediate consumption of imported goods
B35: Source: di_m_grp | R35: Source: di_m_grp
B36: Manufacturing | C36: 2024 | D36: =C36+1 -> 2025 | E36: =D36+1 -> 2026 | F36: =E36+1 -> 2027 | G36: =F36+1 -> 2028 | H36: =G36+1 -> 2029 | I36: =H36+1 -> 2030 | J36: =I36+1 -> 2031 | K36: =J36+1 -> 2032 | L36: Description | R36: Manufacturing | S36: 2024 | T36: =S36+1 -> 2025 | U36: =T36+1 -> 2026 | V36: =U36+1 -> 2027 | W36: =V36+1 -> 2028 | X36: =W36+1 -> 2029 | Y36: =X36+1 -> 2030 | Z36: =Y36+1 -> 2031 | AA36: =Z36+1 -> 2032 | AB36: Description
B37: di_a_m | C37: 8192.94 | D37: 8527.142 | E37: 9245.99 | F37: 10012.2 | G37: 10963.55 | H37: 12205.55 | I37: 12601.31 | J37: 12950.2 | K37: 13207.94 | L37: Intermediate consumption of manufacturing paid for agr, commodities | R37: di_a_m | S37: 6982.956 | T37: 7270.973 | U37: 7886.666 | V37: 8539.849 | W37: 9359.093 | X37: 10423.09 | Y37: 10764.93 | Z37: 11063.37 | AA37: 11284.21 | AB37: Intermediate consumption of manufacturing paid for agr, commodities
B38: di_mi_m | C38: 3804.83 | D38: 3960.035 | E38: 4293.87 | F38: 4649.699 | G38: 5091.512 | H38: 5668.3 | I38: 5852.091 | J38: 6014.118 | K38: 6133.816 | L38: Intermediate consumption of manufacturing paid for mining commodities | R38: di_mi_m | S38: 3242.909 | T38: 3376.665 | U38: 3662.595 | V38: 3965.936 | W38: 4346.396 | X38: 4840.518 | Y38: 4999.271 | Z38: 5137.866 | AA38: 5240.425 | AB38: Intermediate consumption of manufacturing paid for mining commodities
B39: di_m_m | C39: 17755.54 | D39: 18479.81 | E39: 20037.68 | F39: 21698.18 | G39: 23759.94 | H39: 26451.56 | I39: 27309.24 | J39: 28065.35 | K39: 28623.93 | L39: Intermediate consumption of manufacturing paid for manufact, commodities | R39: di_m_m | S39: 15133.29 | T39: 15757.47 | U39: 17091.79 | V39: 18507.35 | W39: 20282.79 | X39: 22588.66 | Y39: 23329.49 | Z39: 23976.25 | AA39: 24454.85 | AB39: Intermediate consumption of manufacturing paid for manufact, commodities
B40: di_e_m | C40: 1460.623 | D40: 1520.204 | E40: 1648.359 | F40: 1784.957 | G40: 1954.563 | H40: 2175.984 | I40: 2246.539 | J40: 2308.739 | K40: 2354.689 | L40: Intermediate consumption of manufacturing paid for energy commodities | R40: di_e_m | S40: 1244.909 | T40: 1296.256 | U40: 1406.021 | V40: 1522.469 | W40: 1668.523 | X40: 1858.21 | Y40: 1919.153 | Z40: 1972.358 | AA40: 2011.729 | AB40: Intermediate consumption of manufacturing paid for energy commodities
B41: di_c_m | C41: 697.7529 | D41: 726.2153 | E41: 787.4361 | F41: 852.6901 | G41: 933.7125 | H41: 1039.487 | I41: 1073.192 | J41: 1102.906 | K41: 1124.856 | L41: Intermediate consumption of manufacturing paid for construct, commodities | R41: di_c_m | S41: 594.7044 | T41: 619.2334 | U41: 671.669 | V41: 727.2975 | W41: 797.0685 | X41: 887.6837 | Y41: 916.7968 | Z41: 942.2132 | AA41: 961.0211 | AB41: Intermediate consumption of manufacturing paid for construct, commodities
B42: di_t_m | C42: 1218.081 | D42: 1267.769 | E42: 1374.643 | F42: 1488.558 | G42: 1630.001 | H42: 1814.654 | I42: 1873.493 | J42: 1925.364 | K42: 1963.684 | L42: Intermediate consumption of manufacturing paid for trans, Services | R42: di_t_m | S42: 1038.187 | T42: 1081.008 | U42: 1172.546 | V42: 1269.658 | W42: 1391.458 | X42: 1549.647 | Y42: 1600.471 | Z42: 1644.84 | AA42: 1677.674 | AB42: Intermediate consumption of manufacturing paid for trans, Services
B43: di_tr_m | C43: 248.4102 | D43: 258.5433 | E43: 280.3388 | F43: 303.5702 | G43: 332.4153 | H43: 370.0727 | I43: 382.072 | J43: 392.6505 | K43: 400.4654 | L43: Intermediate consumption of manufacturing paid for trade services | R43: di_tr_m | S43: 211.7235 | T43: 220.4562 | U43: 239.124 | V43: 258.9285 | W43: 283.768 | X43: 316.0284 | Y43: 326.3931 | Z43: 335.4417 | AA43: 342.1376 | AB43: Intermediate consumption of manufacturing paid for trade services
B44: di_fs_m | C44: 1305.012 | D44: 1358.245 | E44: 1472.747 | F44: 1594.792 | G44: 1746.328 | H44: 1944.16 | I44: 2007.198 | J44: 2062.771 | K44: 2103.826 | L44: Intermediate consumption of manufacturing paid for fin, services | R44: di_fs_m | S44: 1112.279 | T44: 1158.156 | U44: 1256.227 | V44: 1360.269 | W44: 1490.762 | X44: 1660.24 | Y44: 1714.691 | Z44: 1762.227 | AA44: 1797.404 | AB44: Intermediate consumption of manufacturing paid for fin, services
B45: di_ps_m | C45: 97.75437 | D45: 101.7419 | E45: 110.3189 | F45: 119.4609 | G45: 130.812 | H45: 145.631 | I45: 150.3529 | J45: 154.5158 | K45: 157.5911 | L45: Intermediate consumption of manufasturing paid for public services | R45: di_ps_m | S45: 83.3174 | T45: 86.75388 | U45: 94.10005 | V45: 101.8935 | W45: 111.6684 | X45: 124.3635 | Y45: 128.4422 | Z45: 132.003 | AA45: 134.6379 | AB45: Intermediate consumption of manufasturing paid for public services
B46: di_ms_m | C46: 260.3604 | D46: 270.9809 | E46: 293.8249 | F46: 318.1738 | G46: 348.4066 | H46: 387.8756 | I46: 400.4522 | J46: 411.5395 | K46: 419.7303 | L46: Intermediate consumption of manufacturing paid for market services | R46: di_ms_m | S46: 221.9087 | T46: 231.0615 | U46: 250.6274 | V46: 271.3847 | W46: 297.4191 | X46: 331.2314 | Y46: 342.0947 | Z46: 351.5786 | AA46: 358.5966 | AB46: Intermediate consumption of manufacturing paid for market services
B47: ci_m | C47: 35041.3 | D47: 36470.69 | E47: 39545.21 | F47: 42822.28 | G47: 46891.24 | H47: 52203.28 | I47: 53895.93 | J47: 55388.15 | K47: 56490.54 | L47: Total intermediate consumption in manufacturing sector | N47: =C47/'2_Production_2'!AX24*100 -> 61.458347 | R47: ci_m | S47: 29866.18 | T47: 31098.04 | U47: 33731.36 | V47: 36525.04 | W47: 40028.95 | X47: 44579.67 | Y47: 46041.73 | Z47: 47318.15 | AA47: 48262.69 | AB47: Total intermediate consumption in manufacturing sector | AD47: =S47/'2_Production_2'!AX24*100 -> 52.381791 | AE47: 61.187309
L48: = expenses of manufacturing on the intermediate consumption | AB48: = expenses of manufacturing on the intermediate consumption
B49: ci_m_im | C49: 6494.481 | D49: 6759.401 | E49: 7329.226 | F49: 7936.592 | G49: 8690.724 | H49: 9675.246 | I49: 9988.959 | J49: 10265.52 | K49: 10469.84 | L49: of which the intermediate consumption of imported goods | R49: ci_m_im | S49: 5535.336 | T49: 5763.645 | U49: 6251.7 | V49: 6769.474 | W49: 7418.882 | X49: 8262.302 | Y49: 8533.278 | Z49: 8769.847 | AA49: 8944.905 | AB49: of which the intermediate consumption of imported goods
B50: Source: di_e_grp | R50: Source: di_e_grp
B51: Energy & Water | C51: 2024 | D51: =C51+1 -> 2025 | E51: =D51+1 -> 2026 | F51: =E51+1 -> 2027 | G51: =F51+1 -> 2028 | H51: =G51+1 -> 2029 | I51: =H51+1 -> 2030 | J51: =I51+1 -> 2031 | K51: =J51+1 -> 2032 | L51: Description | R51: Energy & Water | S51: 2024 | T51: =S51+1 -> 2025 | U51: =T51+1 -> 2026 | V51: =U51+1 -> 2027 | W51: =V51+1 -> 2028 | X51: =W51+1 -> 2029 | Y51: =X51+1 -> 2030 | Z51: =Y51+1 -> 2031 | AA51: =Z51+1 -> 2032 | AB51: Description
B52: di_a_e | C52: 0.165966 | D52: 0.1912819 | E52: 0.2051123 | F52: 0.273372 | G52: 0.2767939 | H52: 0.2807769 | I52: 0.2886017 | J52: 0.3373524 | K52: 0.3837296 | L52: Intermediate consumption of energy paid for agr, commodities | R52: di_a_e | S52: 0.127253 | T52: 0.146851 | U52: 0.157546 | V52: 0.2099017 | W52: 0.2134196 | X52: 0.2164792 | Y52: 0.2224876 | Z52: 0.2601056 | AA52: 0.2954242 | AB52: Intermediate consumption of energy paid for agr, commodities
B53: di_mi_e | C53: 1323.582 | D53: 1525.477 | E53: 1635.775 | F53: 2180.147 | G53: 2207.437 | H53: 2239.202 | I53: 2301.605 | J53: 2690.393 | K53: 3060.252 | L53: Intermediate consumption of energy paid for mining commodities | R53: di_mi_e | S53: 1014.846 | T53: 1171.14 | U53: 1256.433 | V53: 1673.971 | W53: 1702.026 | X53: 1726.427 | Y53: 1774.344 | Z53: 2074.348 | AA53: 2356.014 | AB53: Intermediate consumption of energy paid for mining commodities
B54: di_m_e | C54: 1154.273 | D54: 1330.343 | E54: 1426.532 | F54: 1901.269 | G54: 1925.068 | H54: 1952.77 | I54: 2007.19 | J54: 2346.246 | K54: 2668.793 | L54: Intermediate consumption of energy paid for manufact, commodities | R54: di_m_e | S54: 885.0297 | T54: 1021.331 | U54: 1095.713 | V54: 1459.841 | W54: 1484.308 | X54: 1505.587 | Y54: 1547.375 | Z54: 1809.003 | AA54: 2054.64 | AB54: Intermediate consumption of energy paid for manufact, commodities
B55: di_e_e | C55: 670.0461 | D55: 772.2528 | E55: 828.0899 | F55: 1103.671 | G55: 1117.486 | H55: 1133.567 | I55: 1165.157 | J55: 1361.976 | K55: 1549.212 | L55: Intermediate consumption of energy paid for energy commodities | R55: di_e_e | S55: 513.7524 | T55: 592.8741 | U55: 636.0526 | V55: 847.4257 | W55: 861.6285 | X55: 873.9809 | Y55: 898.2383 | Z55: 1050.111 | AA55: 1192.701 | AB55: Intermediate consumption of energy paid for energy commodities
B56: di_c_e | C56: 534.3771 | D56: 615.8893 | E56: 660.4207 | F56: 880.203 | G56: 891.2209 | H56: 904.0453 | I56: 929.2396 | J56: 1086.207 | K56: 1235.532 | L56: Intermediate consumption of energy paid for construct, commodities | R56: di_c_e | S56: 409.7293 | T56: 472.8307 | U56: 507.2665 | V56: 675.8414 | W56: 687.1685 | X56: 697.0197 | Y56: 716.3656 | Z56: 837.4879 | AA56: 951.2066 | AB56: Intermediate consumption of energy paid for construct, commodities
B57: di_t_e | C57: 291.5961 | D57: 336.0753 | E57: 360.3749 | F57: 480.3046 | G57: 486.3168 | H57: 493.3147 | I57: 507.0627 | J57: 592.716 | K57: 674.1989 | L57: Intermediate consumption of energy paid for trans, Services | R57: di_t_e | S57: 223.579 | T57: 258.0118 | U57: 276.8025 | V57: 368.7896 | W57: 374.9705 | X57: 380.3461 | Y57: 390.9027 | Z57: 456.996 | AA57: 519.0495 | AB57: Intermediate consumption of energy paid for trans, Services
B58: di_tr_e | C58: 67.41827 | D58: 77.70203 | E58: 83.32022 | F58: 111.0485 | G58: 112.4385 | H58: 114.0565 | I58: 117.235 | J58: 137.0385 | K58: 155.8777 | L58: Intermediate consumption of energy paid for trade services | R58: di_tr_e | S58: 51.69241 | T58: 59.65342 | U58: 63.99792 | V58: 85.26573 | W58: 86.69478 | X58: 87.93764 | Y58: 90.37836 | Z58: 105.6594 | AA58: 120.0065 | AB58: Intermediate consumption of energy paid for trade services
B59: di_fs_e | C59: 218.2392 | D59: 251.5287 | E59: 269.7153 | F59: 359.4742 | G59: 363.9738 | H59: 369.2113 | I59: 379.5007 | J59: 443.6062 | K59: 504.5904 | L59: Intermediate consumption of energy paid for fin, services | R59: di_fs_e | S59: 167.3331 | T59: 193.1036 | U59: 207.1672 | V59: 276.0131 | W59: 280.639 | X59: 284.6623 | Y59: 292.5631 | Z59: 342.0293 | AA59: 388.472 | AB59: Intermediate consumption of energy paid for fin, services
B60: di_ps_e | C60: 10.50439 | D60: 12.1067 | E60: 12.98207 | F60: 17.30238 | G60: 17.51897 | H60: 17.77106 | I60: 18.26631 | J60: 21.35187 | K60: 24.28719 | L60: Intermediate consumption of energy paid for public services | R60: di_ps_e | S60: 8.054158 | T60: 9.294558 | U60: 9.971472 | V60: 13.28519 | W60: 13.50785 | X60: 13.7015 | Y60: 14.08179 | Z60: 16.46272 | AA60: 18.69812 | AB60: Intermediate consumption of energy paid for public services
B61: di_ms_e | C61: 18.60054 | D61: 21.4378 | E61: 22.98785 | F61: 30.63801 | G61: 31.02151 | H61: 31.46791 | I61: 32.34487 | J61: 37.80858 | K61: 43.00627 | L61: Intermediate consumption of energy paid for market services | R61: di_ms_e | S61: 14.26181 | T61: 16.45824 | U61: 17.65687 | V61: 23.52461 | W61: 23.91888 | X61: 24.26178 | Y61: 24.93517 | Z61: 29.15118 | AA61: 33.10949 | AB61: Intermediate consumption of energy paid for market services
B62: ci_e | C62: 4288.803 | D62: 4943.003 | E62: 5300.403 | F62: 7064.331 | G62: 7152.759 | H62: 7255.685 | I62: 7457.89 | J62: 8717.681 | K62: 9916.134 | L62: Total intermediate consumption in energy & water sector | R62: ci_e | S62: 3288.405 | T62: 3794.843 | U62: 4071.218 | V62: 5424.167 | W62: 5515.075 | X62: 5594.14 | Y62: 5749.406 | Z62: 6721.509 | AA62: 7634.193 | AB62: Total intermediate consumption in energy & water sector
L63: = expenses of energy & water on the intermediate consumption | N63: =C62/'2_Production_2'!AX25*100 -> 42.896794 | AB63: = expenses of energy & water on the intermediate consumption | AD63: =S62/'2_Production_2'!AX25*100 -> 32.89077 | AE63: 42.639266
B64: ci_e_im | C64: 1557.492 | D64: 1795.066 | E64: 1924.857 | F64: 2565.433 | G64: 2597.546 | H64: 2634.924 | I64: 2708.355 | J64: 3165.852 | K64: 3601.074 | L64: of which the intermediate consumption of imported goods | R64: ci_e_im | S64: 1194.194 | T64: 1378.109 | U64: 1478.475 | V64: 1969.802 | W64: 2002.816 | X64: 2031.529 | Y64: 2087.914 | Z64: 2440.936 | AA64: 2772.38 | AB64: of which the intermediate consumption of imported goods
B65: Source: di_c_grp | R65: Source: di_c_grp
B66: Construction | C66: 2024 | D66: =C66+1 -> 2025 | E66: =D66+1 -> 2026 | F66: =E66+1 -> 2027 | G66: =F66+1 -> 2028 | H66: =G66+1 -> 2029 | I66: =H66+1 -> 2030 | J66: =I66+1 -> 2031 | K66: =J66+1 -> 2032 | L66: Description | R66: Construction | S66: 2024 | T66: =S66+1 -> 2025 | U66: =T66+1 -> 2026 | V66: =U66+1 -> 2027 | W66: =V66+1 -> 2028 | X66: =W66+1 -> 2029 | Y66: =X66+1 -> 2030 | Z66: =Y66+1 -> 2031 | AA66: =Z66+1 -> 2032 | AB66: Description
B67: di_a_c | C67: 101.0709 | D67: 112.9256 | E67: 125.2296 | F67: 132.5467 | G67: 145.0874 | H67: 151.6437 | I67: 157.8436 | J67: 165.1368 | K67: 171.2409 | L67: Intermediate consumption of construction paid for agr, commodities | R67: di_a_c | S67: 94.22367 | T67: 105.2745 | U67: 116.7459 | V67: 123.5673 | W67: 135.2573 | X67: 141.3704 | Y67: 147.151 | Z67: 153.95 | AA67: 159.6407 | AB67: Intermediate consumption of construction paid for agr, commodities
B68: di_mi_c | C68: 170.8304 | D68: 190.8673 | E68: 211.6636 | F68: 224.031 | G68: 245.2272 | H68: 256.3088 | I68: 266.788 | J68: 279.1149 | K68: 289.432 | L68: Intermediate consumption of construction paid for mining commodities | R68: di_mi_c | S68: 159.2572 | T68: 177.9354 | U68: 197.3243 | V68: 208.854 | W68: 228.6125 | X68: 238.9448 | Y68: 248.7152 | Z68: 260.2069 | AA68: 269.8254 | AB68: Intermediate consumption of construction paid for mining commodities
B69: di_m_c | C69: 9400.841 | D69: 10503.48 | E69: 11647.91 | F69: 12328.49 | G69: 13494.92 | H69: 14104.74 | I69: 14681.41 | J69: 15359.77 | K69: 15927.52 | L69: Intermediate consumption of construction paid for manufact, commodities | R69: di_m_c | S69: 8763.969 | T69: 9791.833 | U69: 10858.81 | V69: 11493.29 | W69: 12580.61 | X69: 13149.2 | Y69: 13686.87 | Z69: 14319.25 | AA69: 14848.57 | AB69: Intermediate consumption of construction paid for manufact, commodities
B70: di_e_c | C70: 476.022 | D70: 531.8553 | E70: 589.8046 | F70: 624.2667 | G70: 683.3303 | H70: 714.2094 | I70: 743.4097 | J70: 777.7589 | K70: 806.5078 | L70: Intermediate consumption of construction paid for energy commodities | R70: di_e_c | S70: 443.7733 | T70: 495.8203 | U70: 549.848 | V70: 581.9755 | W70: 637.033 | X70: 665.8242 | Y70: 693.0497 | Z70: 725.0713 | AA70: 751.8736 | AB70: Intermediate consumption of construction paid for energy commodities
B71: di_c_c | C71: 2238.033 | D71: 2500.535 | E71: 2772.986 | F71: 2935.01 | G71: 3212.7 | H71: 3357.879 | I71: 3495.165 | J71: 3656.659 | K71: 3791.823 | L71: Intermediate consumption of construction paid for construct, commodities | R71: di_c_c | S71: 2086.415 | T71: 2331.116 | U71: 2585.128 | V71: 2736.177 | W71: 2995.031 | X71: 3130.395 | Y71: 3258.396 | Z71: 3408.947 | AA71: 3534.958 | AB71: Intermediate consumption of construction paid for construct, commodities
B72: di_t_c | C72: 699.9698 | D72: 782.0702 | E72: 867.2821 | F72: 917.9571 | G72: 1004.808 | H72: 1050.214 | I72: 1093.152 | J72: 1143.661 | K72: 1185.935 | L72: Intermediate consumption of construction paid for trans, Services | R72: di_t_c | S72: 652.5494 | T72: 729.0823 | U72: 808.5277 | V72: 855.7698 | W72: 936.7294 | X72: 979.0657 | Y72: 1019.1 | Z72: 1066.186 | AA72: 1105.598 | AB72: Intermediate consumption of construction paid for trans, Services
B73: di_tr_c | C73: 103.5584 | D73: 115.7049 | E73: 128.3117 | F73: 135.8089 | G73: 148.6582 | H73: 155.3759 | I73: 161.7284 | J73: 169.2011 | K73: 175.4554 | L73: Intermediate consumption of construction paid for trade services | R73: di_tr_c | S73: 96.54266 | T73: 107.8655 | U73: 119.6192 | V73: 126.6085 | W73: 138.5862 | X73: 144.8497 | Y73: 150.7726 | Z73: 157.7389 | AA73: 163.5697 | AB73: Intermediate consumption of construction paid for trade services
B74: di_fs_c | C74: 777.8719 | D74: 869.1096 | E74: 963.805 | F74: 1020.12 | G74: 1116.636 | H74: 1167.096 | I74: 1214.812 | J74: 1270.943 | K74: 1317.922 | L74: Intermediate consumption of construction paid for fin, services | R74: di_fs_c | S74: 725.1739 | T74: 810.2245 | U74: 898.5116 | V74: 951.0115 | W74: 1040.981 | X74: 1088.029 | Y74: 1132.519 | Z74: 1184.846 | AA74: 1228.643 | AB74: Intermediate consumption of construction paid for fin, services
B75: di_ps_c | C75: 30.89471 | D75: 34.5184 | E75: 38.27942 | F75: 40.51607 | G75: 44.34941 | H75: 46.35351 | I75: 48.24867 | J75: 50.478 | K75: 52.34386 | L75: Intermediate consumption of construction paid for public services | R75: di_ps_c | S75: 28.80171 | T75: 32.17966 | U75: 35.68616 | V75: 37.77129 | W75: 41.34463 | X75: 43.21323 | Y75: 44.98021 | Z75: 47.05848 | AA75: 48.79799 | AB75: Intermediate consumption of construction paid for public services
B76: di_ms_c | C76: 119.2365 | D76: 133.2219 | E76: 147.7373 | F76: 156.3696 | G76: 171.1642 | H76: 178.8989 | I76: 186.2131 | J76: 194.8171 | K76: 202.0183 | L76: Intermediate consumption of construction paid for market services | R76: di_ms_c | S76: 111.1586 | T76: 124.1957 | U76: 137.7288 | V76: 145.7763 | W76: 159.5674 | X76: 166.7791 | Y76: 173.5987 | Z76: 181.6197 | AA76: 188.3332 | AB76: Intermediate consumption of construction paid for market services
B77: ci_c | C77: 14118.33 | D77: 15774.29 | E77: 17493 | F77: 18515.11 | G77: 20266.88 | H77: 21182.72 | I77: 22048.77 | J77: 23067.54 | K77: 23920.2 | L77: Total intermediate consumption in construction sector | N77: =C77/'2_Production_2'!AX26*100 -> 44.571162 | R77: ci_c | S77: 13161.86 | T77: 14705.53 | U77: 16307.93 | V77: 17260.8 | W77: 18893.75 | X77: 19747.67 | Y77: 20555.15 | Z77: 21504.88 | AA77: 22299.8 | AB77: Total intermediate consumption in construction sector | AD77: =S77/'2_Production_2'!AX26*100 -> 41.551613
L78: = expenses of construction on the intermediate consumption | AB78: = expenses of construction on the intermediate consumption
B79: ci_c_im | C79: 3471.035 | D79: 3878.157 | E79: 4300.709 | F79: 4551.998 | G79: 4982.676 | H79: 5207.838 | I79: 5420.76 | J79: 5671.225 | K79: 5880.855 | L79: of which the intermediate consumption of imported goods | R79: ci_c_im | S79: 3235.885 | T79: 3615.399 | U79: 4009.356 | V79: 4243.622 | W79: 4645.087 | X79: 4855.026 | Y79: 5053.547 | Z79: 5287.041 | AA79: 5482.476 | AB79: of which the intermediate consumption of imported goods
B80: Source: di_t_grp | R80: Source: di_t_grp
B81: Transport | C81: 2024 | D81: =C81+1 -> 2025 | E81: =D81+1 -> 2026 | F81: =E81+1 -> 2027 | G81: =F81+1 -> 2028 | H81: =G81+1 -> 2029 | I81: =H81+1 -> 2030 | J81: =I81+1 -> 2031 | K81: =J81+1 -> 2032 | L81: Description | R81: Transport | S81: 2024 | T81: =S81+1 -> 2025 | U81: =T81+1 -> 2026 | V81: =U81+1 -> 2027 | W81: =V81+1 -> 2028 | X81: =W81+1 -> 2029 | Y81: =X81+1 -> 2030 | Z81: =Y81+1 -> 2031 | AA81: =Z81+1 -> 2032 | AB81: Description
B82: di_a_t | C82: 25.56347 | D82: 28.11759 | E82: 31.51396 | F82: 39.29899 | G82: 40.80405 | H82: 42.55906 | I82: 49.11696 | J82: 54.57476 | K82: 60.36127 | L82: Intermediate consumption of transport paid for agr, commodities | R82: di_a_t | S82: 15.57039 | T82: 17.13765 | U82: 19.21182 | V82: 23.93977 | W82: 24.88157 | X82: 25.94353 | Y82: 29.99873 | Z82: 33.34005 | AA82: 36.86923 | AB82: Intermediate consumption of transport paid for agr, commodities
B83: di_mi_t | C83: 228.6116 | D83: 251.4529 | E83: 281.8263 | F83: 351.4471 | G83: 364.9067 | H83: 380.6016 | I83: 439.2482 | J83: 488.0568 | K83: 539.8051 | L83: Intermediate consumption of transport paid for mining commodities | R83: di_mi_t | S83: 139.2445 | T83: 153.2604 | U83: 171.8095 | V83: 214.0911 | W83: 222.5135 | X83: 232.0105 | Y83: 268.2758 | Z83: 298.1569 | AA83: 329.7179 | AB83: Intermediate consumption of transport paid for mining commodities
B84: di_m_t | C84: 4131.27 | D84: 4544.038 | E84: 5092.919 | F84: 6351.045 | G84: 6594.275 | H84: 6877.9 | I84: 7937.711 | J84: 8819.738 | K84: 9754.887 | L84: Intermediate consumption of transport paid for manufact, commodities | R84: di_m_t | S84: 2516.305 | T84: 2769.588 | U84: 3104.791 | V84: 3868.867 | W84: 4021.07 | X84: 4192.692 | Y84: 4848.047 | Z84: 5388.031 | AA84: 5958.375 | AB84: Intermediate consumption of transport paid for manufact, commodities
B85: di_e_t | C85: 745.0666 | D85: 819.5086 | E85: 918.4982 | F85: 1145.399 | G85: 1189.265 | H85: 1240.416 | I85: 1431.551 | J85: 1590.623 | K85: 1759.275 | L85: Intermediate consumption of transport paid for energy commodities | R85: di_e_t | S85: 453.8108 | T85: 499.49 | U85: 559.9431 | V85: 697.7428 | W85: 725.1922 | X85: 756.144 | Y85: 874.3359 | Z85: 971.7212 | AA85: 1074.582 | AB85: Intermediate consumption of transport paid for energy commodities
B86: di_c_t | C86: 574.8125 | D86: 632.2439 | E86: 708.6135 | F86: 883.6654 | G86: 917.5077 | H86: 956.9704 | I86: 1104.429 | J86: 1227.152 | K86: 1357.266 | L86: Intermediate consumption of transport paid for construct, commodities | R86: di_c_t | S86: 350.1111 | T86: 385.3522 | U86: 431.9913 | V86: 538.3026 | W86: 559.4796 | X86: 583.3586 | Y86: 674.5427 | Z86: 749.6745 | AA86: 829.0305 | AB86: Intermediate consumption of transport paid for construct, commodities
B87: di_t_t | C87: 2050.999 | D87: 2255.921 | E87: 2528.417 | F87: 3153.023 | G87: 3273.777 | H87: 3414.584 | I87: 3940.735 | J87: 4378.624 | K87: 4842.886 | L87: Intermediate consumption of transport paid for trans, Services | R87: di_t_t | S87: 1249.238 | T87: 1374.983 | U87: 1541.396 | V87: 1920.728 | W87: 1996.29 | X87: 2081.493 | Y87: 2406.848 | Z87: 2674.928 | AA87: 2958.079 | AB87: Intermediate consumption of transport paid for trans, Services
B88: di_tr_t | C88: 282.6839 | D88: 310.9278 | E88: 348.4852 | F88: 434.573 | G88: 451.2161 | H88: 470.6233 | I88: 543.1413 | J88: 603.4943 | K88: 667.4823 | L88: Intermediate consumption of transport paid for trade services | R88: di_tr_t | S88: 172.1793 | T88: 189.5103 | U88: 212.4467 | V88: 264.7289 | W88: 275.1434 | X88: 286.8868 | Y88: 331.7297 | Z88: 368.6784 | AA88: 407.7044 | AB88: Intermediate consumption of transport paid for trade services
B89: di_fs_t | C89: 1251.874 | D89: 1376.952 | E89: 1543.276 | F89: 1924.519 | G89: 1998.223 | H89: 2084.168 | I89: 2405.316 | J89: 2672.591 | K89: 2955.964 | L89: Intermediate consumption of transport paid for fin, services | R89: di_fs_t | S89: 762.5006 | T89: 839.2515 | U89: 940.826 | V89: 1172.359 | W89: 1218.48 | X89: 1270.486 | Y89: 1469.074 | Z89: 1632.702 | AA89: 1805.53 | AB89: Intermediate consumption of transport paid for fin, services
B90: di_ps_t | C90: 54.34115 | D90: 59.77055 | E90: 66.99032 | F90: 83.53923 | G90: 86.73859 | H90: 90.46928 | I90: 104.4096 | J90: 116.0115 | K90: 128.3121 | L90: Intermediate consumption of transport paid for public services | R90: di_ps_t | S90: 33.09852 | T90: 36.43011 | U90: 40.83924 | V90: 50.8896 | W90: 52.89162 | X90: 55.14908 | Y90: 63.76936 | Z90: 70.87211 | AA90: 78.3742 | AB90: Intermediate consumption of transport paid for public services
B91: di_ms_t | C91: 25.41091 | D91: 27.9498 | E91: 31.32589 | F91: 39.06446 | G91: 40.56054 | H91: 42.30508 | I91: 48.82384 | J91: 54.24907 | K91: 60.00106 | L91: Intermediate consumption of transport paid for market services | R91: di_ms_t | S91: 15.47747 | T91: 17.03538 | U91: 19.09717 | V91: 23.79691 | W91: 24.73308 | X91: 25.78871 | Y91: 29.81971 | Z91: 33.14109 | AA91: 36.6492 | AB91: Intermediate consumption of transport paid for market services
B92: ci_t | C92: 9370.634 | D92: 10306.88 | E92: 11551.87 | F92: 14405.58 | G92: 14957.28 | H92: 15600.6 | I92: 18004.49 | J92: 20005.12 | K92: 22126.24 | L92: Total intermediate consumption in transport sector | N92: =C92/'2_Production_2'!AX27*100 -> 51.032308 | R92: ci_t | S92: 5707.536 | T92: 6282.039 | U92: 7042.353 | V92: 8775.447 | W92: 9120.676 | X92: 9509.953 | Y92: 10996.44 | Z92: 12221.25 | AA92: 13514.91 | AB92: Total intermediate consumption in transport sector | AD92: =S92/'2_Production_2'!AX27*100 -> 31.083141 | AE92: =T92/'2_Production_2'!AY27*100 -> 30.484503
L93: = expenses of transport on the intermediate consumption | AB93: = expenses of transport on the intermediate consumption
B94: ci_t_im | C94: 2781.697 | D94: 3059.625 | E94: 3429.202 | F94: 4276.333 | G94: 4440.106 | H94: 4631.078 | I94: 5344.678 | J94: 5938.571 | K94: 6568.232 | L94: of which the intermediate consumption of imported goods | R94: ci_t_im | S94: 1694.297 | T94: 1864.84 | U94: 2090.541 | V94: 2605.014 | W94: 2707.496 | X94: 2823.054 | Y94: 3264.322 | Z94: 3627.909 | AA94: 4011.937 | AB94: of which the intermediate consumption of imported goods
B95: Source: di_tr_grp | R95: Source: di_tr_grp
B96: Trade | C96: 2024 | D96: =C96+1 -> 2025 | E96: =D96+1 -> 2026 | F96: =E96+1 -> 2027 | G96: =F96+1 -> 2028 | H96: =G96+1 -> 2029 | I96: =H96+1 -> 2030 | J96: =I96+1 -> 2031 | K96: =J96+1 -> 2032 | L96: Description | R96: Trade | S96: 2024 | T96: =S96+1 -> 2025 | U96: =T96+1 -> 2026 | V96: =U96+1 -> 2027 | W96: =V96+1 -> 2028 | X96: =W96+1 -> 2029 | Y96: =X96+1 -> 2030 | Z96: =Y96+1 -> 2031 | AA96: =Z96+1 -> 2032 | AB96: Description
B97: di_a_tr | C97: 692.94 | D97: 722.8176 | E97: 732.4716 | F97: 804.3215 | G97: 855.3021 | H97: 883.3108 | I97: 917.4663 | J97: 1004.071 | K97: 1027.505 | L97: Intermediate consumption of trade paid for agr, commodities | R97: di_a_tr | S97: 536.5378 | T97: 559.6772 | U97: 567.1808 | V97: 622.801 | W97: 662.2874 | X97: 683.9911 | Y97: 710.4316 | Z97: 777.5195 | AA97: 795.6484 | AB97: Intermediate consumption of trade paid for agr, commodities
B98: di_mi_tr | C98: 74.25965 | D98: 77.46151 | E98: 78.49609 | F98: 86.19597 | G98: 91.65936 | H98: 94.66093 | I98: 98.32125 | J98: 107.6023 | K98: 110.1136 | L98: Intermediate consumption of trade paid for mining commodities | R98: di_mi_tr | S98: 57.49864 | T98: 59.9784 | U98: 60.78253 | V98: 66.74313 | W98: 70.97473 | X98: 73.30064 | Y98: 76.13415 | Z98: 83.3237 | AA98: 85.2665 | AB98: Intermediate consumption of trade paid for mining commodities
B99: di_m_tr | C99: 4558.563 | D99: 4755.115 | E99: 4818.625 | F99: 5291.296 | G99: 5626.676 | H99: 5810.933 | I99: 6035.628 | J99: 6605.362 | K99: 6759.526 | L99: Intermediate consumption of trade paid for manufact, commodities | R99: di_m_tr | S99: 3529.658 | T99: 3681.883 | U99: 3731.246 | V99: 4097.148 | W99: 4356.913 | X99: 4499.692 | Y99: 4673.633 | Z99: 5114.977 | AA99: 5234.239 | AB99: Intermediate consumption of trade paid for manufact, commodities
B100: di_e_tr | C100: 627.4979 | D100: 654.5537 | E100: 663.296 | F100: 728.3604 | G100: 774.5263 | H100: 799.8897 | I100: 830.8196 | J100: 909.2449 | K100: 930.4659 | L100: Intermediate consumption of trade paid for energy commodities | R100: di_e_tr | S100: 485.8665 | T100: 506.8206 | U100: 513.6155 | V100: 563.9828 | W100: 599.7401 | X100: 619.3941 | Y100: 643.3375 | Z100: 704.0896 | AA100: 720.5063 | AB100: Intermediate consumption of trade paid for energy commodities
B101: di_c_tr | C101: 710.2891 | D101: 740.9147 | E101: 750.8104 | F101: 824.4592 | G101: 876.7162 | H101: 905.4261 | I101: 940.4368 | J101: 1029.209 | K101: 1053.23 | L101: Intermediate consumption of trade paid for construct, commodities | R101: di_c_tr | S101: 549.971 | T101: 573.6898 | U101: 581.3812 | V101: 638.394 | W101: 678.869 | X101: 701.1162 | Y101: 728.2186 | Z101: 796.9862 | AA101: 815.5689 | AB101: Intermediate consumption of trade paid for construct, commodities
...

Sheet 2_Production_2
C1: =C18+C19 -> 157803.3 | D1: =D18+D19 -> 176918.85 | E1: =E18+E19 -> 199898.14 | F1: =F18+F19 -> 225457.17 | G1: =G18+G19 -> 254612 | H1: =H18+H19 -> 290957.14 | I1: =I18+I19 -> 325987.62 | J1: =J18+J19 -> 368330.85 | K1: =K18+K19 -> 413970.34 | V1: =V2+V3 -> 168506.33 | W1: =W2+W3 -> 191590.41 | X1: =X2+X3 -> 207987.41 | Y1: =Y2+Y3 -> 227590.86 | Z1: =Z2+Z3 -> 262764.28 | AA1: =AA2+AA3 -> 307293.09 | AB1: =AB2+AB3 -> 324567.17 | AC1: =AC2+AC3 -> 340824.59 | AD1: =AD2+AD3 -> 345054.52
B2: Block 2 : Production (2) | D2: =D1-C1 -> 19115.556 | E2: =E1-D1 -> 22979.288 | F2: =F1-E1 -> 25559.023 | G2: =G1-F1 -> 29154.833 | H2: =H1-G1 -> 36345.139 | I2: =I1-H1 -> 35030.477 | J2: =J1-I1 -> 42343.239 | K2: =K1-J1 -> 45639.483 | V2: =C19 -> 14524.861 | W2: =D19 -> 19301.09 | X2: =E19 -> 18610.317 | Y2: =F19 -> 20494.299 | Z2: =G19 -> 21611.493 | AA2: =H19 -> 21722.856 | AB2: =I19 -> 21977.798 | AC2: =J19 -> 22429.217 | AD2: =K19 -> 23764.345
E3: =E2-D2 -> 3863.7327 | F3: =F2-E2 -> 2579.7348 | G3: =G2-F2 -> 3595.8099 | H3: =H2-G2 -> 7190.3059 | I3: =I2-H2 -> -1314.6619 | J3: =J2-I2 -> 7312.7618 | K3: =K2-J2 -> 3296.2445 | V3: =C32-V17 -> 153981.47 | W3: =D32-W17 -> 172289.32 | X3: =E32-X17 -> 189377.09 | Y3: =F32-Y17 -> 207096.57 | Z3: =G32-Z17 -> 241152.79 | AA3: =H32-AA17 -> 285570.23 | AB3: =I32-AB17 -> 302589.37 | AC3: =J32-AC17 -> 318395.37 | AD3: =K32-AD17 -> 321290.17
B4: Total intermediate Demand for 10 commodities | U4: Total intermediate Demand for 10 commodities | AE4: удельный вес ПП | AQ4: Total intermediate Demand for 10 commodities
B5: Source: dit_grp | C5: =C17/C33*100 -> 50.254752 | D5: =D17/D33*100 -> 49.66774 | E5: =E17/E33*100 -> 47.314951 | F5: =F17/F33*100 -> 44.654897 | G5: =G17/G33*100 -> 46.164133 | H5: =H17/H33*100 -> 47.719164 | I5: =I17/I33*100 -> 43.094442 | J5: =J17/J33*100 -> 37.076026 | K5: =K17/K33*100 -> 29.933554 | U5: Source: dit_grp | V5: =V9/C24*100 -> 59.726686 | W5: =W9/D24*100 -> 55.944262 | X5: =X9/E24*100 -> 65.836807 | Y5: =Y9/F24*100 -> 70.968582 | Z5: =Z9/G24*100 -> 64.203789 | AA5: =AA9/H24*100 -> 54.848544 | AB5: =AB9/I24*100 -> 55.881753 | AC5: =AC9/J24*100 -> 56.902507 | AD5: =AD9/K24*100 -> 57.649987 | AQ5: Source: dit_grp
A6: 2 | C6: 2024 | D6: =C6+1 -> 2025 | E6: =D6+1 -> 2026 | F6: =E6+1 -> 2027 | G6: =F6+1 -> 2028 | H6: =G6+1 -> 2029 | I6: =H6+1 -> 2030 | J6: =I6+1 -> 2031 | K6: =J6+1 -> 2032 | T6: 2 | V6: 2024 | W6: =V6+1 -> 2025 | X6: =W6+1 -> 2026 | Y6: =X6+1 -> 2027 | Z6: =Y6+1 -> 2028 | AA6: =Z6+1 -> 2029 | AB6: =AA6+1 -> 2030 | AC6: =AB6+1 -> 2031 | AD6: =AC6+1 -> 2032 | AF6: 2024 | AG6: =AF6+1 -> 2025 | AH6: =AG6+1 -> 2026 | AI6: =AH6+1 -> 2027 | AJ6: =AI6+1 -> 2028 | AK6: =AJ6+1 -> 2029 | AL6: =AK6+1 -> 2030 | AM6: =AL6+1 -> 2031 | AN6: =AM6+1 -> 2032 | AS6: 2024 | AT6: =AS6+1 -> 2025 | AU6: =AT6+1 -> 2026 | AV6: =AU6+1 -> 2027 | AW6: =AV6+1 -> 2028 | AX6: =AW6+1 -> 2029 | AY6: =AX6+1 -> 2030 | AZ6: =AY6+1 -> 2031 | BA6: =AZ6+1 -> 2032
B7: Agriculture (DIT_a) | C7: =C21*AF7/100 -> 42982.911 | D7: =D21*AG7/100 -> 45882.216 | E7: =E21*AH7/100 -> 50270.624 | F7: =F21*AI7/100 -> 53550.575 | G7: =G21*AJ7/100 -> 50441.77 | H7: =H21*AK7/100 -> 58277.583 | I7: =I21*AL7/100 -> 67646.699 | J7: =J21*AM7/100 -> 60945.224 | K7: =K21*AN7/100 -> 71815.134 | L7: 26.724556 | U7: Agriculture (DIT_a) | V7: ='2_Production_1'!C17 -> 40340.11 | W7: ='2_Production_1'!D17 -> 43300.3 | X7: ='2_Production_1'!E17 -> 45478.42 | Y7: ='2_Production_1'!F17 -> 47224.45 | Z7: ='2_Production_1'!G17 -> 48590.42 | AA7: ='2_Production_1'!H17 -> 50222.95 | AB7: ='2_Production_1'!I17 -> 51002.89 | AC7: ='2_Production_1'!J17 -> 52183.59 | AD7: ='2_Production_1'!K17 -> 54445.85 | AE7: =V7/C21*100 -> 50.867517 | AF7: 54.2 | AG7: 54.2 | AH7: 52.83 | AI7: 51.2 | AJ7: 43.971016 | AK7: 46.460503 | AL7: 49.3953 | AM7: 41.152603 | AN7: 45 | AQ7: Agriculture (DIT_a) | AS7: 31573.43 | AT7: 33601.08 | AU7: 35597.88 | AV7: 37445.48 | AW7: 39259.39 | AX7: 41468.39 | AY7: 42359.66 | AZ7: 43511.28 | BA7: 45085.48
B8: Mining (DIT_mi) | C8: =C23*AF8/100 -> 7000.7758 | D8: =D23*AG8/100 -> 7778.9828 | E8: =E23*AH8/100 -> 16421.932 | F8: =F23*AI8/100 -> 14149.747 | G8: =G23*AJ8/100 -> 24731.767 | H8: =H23*AK8/100 -> 27517.377 | I8: =I23*AL8/100 -> 22437.651 | J8: =J23*AM8/100 -> 22936.391 | K8: =K23*AN8/100 -> 11648.734 | L8: 3.2720337 | U8: Mining (DIT_mi) | V8: ='2_Production_1'!C32 -> 6308.727 | W8: ='2_Production_1'!D32 -> 7852.628 | X8: ='2_Production_1'!E32 -> 8358.133 | Y8: ='2_Production_1'!F32 -> 8866.251 | Z8: ='2_Production_1'!G32 -> 9201.972 | AA8: ='2_Production_1'!H32 -> 9554.302 | AB8: ='2_Production_1'!I32 -> 9960.441 | AC8: ='2_Production_1'!J32 -> 10474.69 | AD8: ='2_Production_1'!K32 -> 10958.89 | AE8: =V8/C23*100 -> 46.589292 | AF8: 51.7 | AG8: 51.7 | AH8: 61.38 | AI8: 47.5 | AJ8: 60.7 | AK8: 57.271391 | AL8: 45.7 | AM8: 45 | AN8: 23 | AQ8: Mining (DIT_mi) | AS8: 7123.571 | AT8: 7834.645 | AU8: 8442.124 | AV8: 9543.081 | AW8: 10126.64 | AX8: 10846.91 | AY8: 11252.34 | AZ8: 11980.82 | BA8: 12645.92
B9: Manufacturing (DIT_m) | C9: =C24*AF9/100 -> 37783.106 | D9: =D24*AG9/100 -> 41983.08 | E9: =E24*AH9/100 -> 32735.7 | F9: =F24*AI9/100 -> 33247.214 | G9: =G24*AJ9/100 -> 40027.954 | H9: =H24*AK9/100 -> 58058.06 | I9: =I24*AL9/100 -> 50482.14 | J9: =J24*AM9/100 -> 44289.1 | K9: =K24*AN9/100 -> 29886.589 | L9: 27.822405 | U9: Manufacturing (DIT_m) | V9: ='2_Production_1'!C47 -> 35041.3 | W9: ='2_Production_1'!D47 -> 36470.69 | X9: ='2_Production_1'!E47 -> 39545.21 | Y9: ='2_Production_1'!F47 -> 42822.28 | Z9: ='2_Production_1'!G47 -> 46891.24 | AA9: ='2_Production_1'!H47 -> 52203.28 | AB9: ='2_Production_1'!I47 -> 53895.93 | AC9: ='2_Production_1'!J47 -> 55388.15 | AD9: ='2_Production_1'!K47 -> 56490.54 | AE9: =V9/C24*100 -> 59.726686 | AF9: 64.4 | AG9: 64.4 | AH9: 54.5 | AI9: 55.1 | AJ9: 54.806534 | AK9: 61 | AL9: 52.34218 | AM9: 45.5 | AN9: 30.5 | AQ9: Manufacturing (DIT_m) | AS9: 55650.79 | AT9: 60177.2 | AU9: 65000.41 | AV9: 70756.95 | AW9: 75654.78 | AX9: 80534.28 | AY9: 84153.63 | AZ9: 88649.81 | BA9: 92534.59
B10: Energy and Water (DIT_e) | C10: =C25*AF10/100 -> 4687.6181 | D10: =D25*AG10/100 -> 5208.6942 | E10: =E25*AH10/100 -> 5474.7842 | F10: =F25*AI10/100 -> 6053.3791 | G10: =G25*AJ10/100 -> 7290.9433 | H10: =H25*AK10/100 -> 8616.993 | I10: =I25*AL10/100 -> 8795.7572 | J10: =J25*AM10/100 -> 8250.6214 | K10: =K25*AN10/100 -> 4415.395 | L10: =2.8435571632284+0.0641141742494007 -> 2.9076713 | U10: Energy and Water (DIT_e) | V10: ='2_Production_1'!C62 -> 4288.803 | W10: ='2_Production_1'!D62 -> 4943.003 | X10: ='2_Production_1'!E62 -> 5300.403 | Y10: ='2_Production_1'!F62 -> 7064.331 | Z10: ='2_Production_1'!G62 -> 7152.759 | AA10: ='2_Production_1'!H62 -> 7255.685 | AB10: ='2_Production_1'!I62 -> 7457.89 | AC10: ='2_Production_1'!J62 -> 8717.681 | AD10: ='2_Production_1'!K62 -> 9916.134 | AE10: =V10/C25*100 -> 41.445948 | AF10: 45.3 | AG10: 45.3 | AH10: =X10/AZ25*100 -> 41.743871 | AI10: =Y10/BA25*100 -> 41.020678 | AJ10: 40.9 | AK10: =AA10/BC25*100 -> 39.932905 | AL10: 39.4 | AM10: 35 | AN10: 18.3 | AQ10: Energy and Water (DIT_e) | AS10: 7463.39 | AT10: 8060.131 | AU10: 8676.688 | AV10: 9615.347 | AW10: 10151.41 | AX10: 10678.61 | AY10: 11150.31 | AZ10: 11896.43 | BA10: 12581.55
B11: Construction (DIT_c) | C11: =C26*AF11/100 -> 16054.821 | D11: =D26*AG11/100 -> 17839.477 | E11: =E26*AH11/100 -> 18068.513 | F11: =F26*AI11/100 -> 19607.11 | G11: =G26*AJ11/100 -> 20312.507 | H11: =H26*AK11/100 -> 18074.895 | I11: =I26*AL11/100 -> 16680.326 | J11: =J26*AM11/100 -> 16187.19 | K11: =K26*AN11/100 -> 11244.509 | L11: 15.483318 | U11: Construction (DIT_c) | V11: ='2_Production_1'!C77 -> 14118.33 | W11: ='2_Production_1'!D77 -> 15774.29 | X11: ='2_Production_1'!E77 -> 17493 | Y11: ='2_Production_1'!F77 -> 18515.11 | Z11: ='2_Production_1'!G77 -> 20266.88 | AA11: ='2_Production_1'!H77 -> 21182.72 | AB11: ='2_Production_1'!I77 -> 22048.77 | AC11: ='2_Production_1'!J77 -> 23067.54 | AD11: ='2_Production_1'!K77 -> 23920.2 | AE11: =V11/C26*100 -> 41.330981 | AF11: 47 | AG11: 47 | AH11: =X11/AZ26*100 -> 42.048257 | AI11: =Y11/BA26*100 -> 41.655281 | AJ11: 41 | AK11: 34 | AL11: 30 | AM11: 27.1 | AN11: 19 | AQ11: Construction (DIT_c) | AS11: 9375.018 | AT11: 10154.97 | AU11: 10820.56 | AV11: 11752.68 | AW11: 12398.64 | AX11: 12944.09 | AY11: 13561.97 | AZ11: 14315.71 | BA11: 15046.98
B12: Transport (DIT_t) | C12: =C27*AF12/100 -> 10176.772 | D12: =D27*AG12/100 -> 11308.023 | E12: =E27*AH12/100 -> 11619.869 | F12: =F27*AI12/100 -> 11637.064 | G12: =G27*AJ12/100 -> 11048.283 | H12: =H27*AK12/100 -> 7924.2227 | I12: =I27*AL12/100 -> 8386.8571 | J12: =J27*AM12/100 -> 7746.6811 | K12: =K27*AN12/100 -> 4043.6176 | L12: 5.7927241 | U12: Transport (DIT_t) | V12: ='2_Production_1'!C92 -> 9370.634 | W12: ='2_Production_1'!D92 -> 10306.88 | X12: ='2_Production_1'!E92 -> 11551.87 | Y12: ='2_Production_1'!F92 -> 14405.58 | Z12: ='2_Production_1'!G92 -> 14957.28 | AA12: ='2_Production_1'!H92 -> 15600.6 | AB12: ='2_Production_1'!I92 -> 18004.49 | AC12: ='2_Production_1'!J92 -> 20005.12 | AD12: ='2_Production_1'!K92 -> 22126.24 | AE12: =V12/C27*100 -> 49.169997 | AF12: 53.4 | AG12: 53.4 | AH12: 50 | AI12: =Y12/BA27*100 -> 47.141563 | AJ12: =Z12/BB27*100 -> 46.184215 | AK12: 32 | AL12: 30.2 | AM12: 27.2 | AN12: 15 | AQ12: Transport (DIT_t) | AS12: 8819.603 | AT12: 9490.592 | AU12: 10225.34 | AV12: 11483.15 | AW12: 12135.79 | AX12: 12740.41 | AY12: 13568.97 | AZ12: 14596.29 | BA12: 15477.17
B13: Trade (DIT_tr) | C13: =C28*AF13/100 -> 12676.462 | D13: =D28*AG13/100 -> 14085.579 | E13: =E28*AH13/100 -> 12921.853 | F13: =F28*AI13/100 -> 14306.896 | G13: =G28*AJ13/100 -> 15819.406 | H13: =H28*AK13/100 -> 11697.912 | I13: =I28*AL13/100 -> 8383.2588 | J13: =J28*AM13/100 -> 7830.3565 | K13: =K28*AN13/100 -> 4418.1152 | L13: 8.3772737 | U13: Trade (DIT_tr) | V13: ='2_Production_1'!C107 -> 11835.09 | W13: ='2_Production_1'!D107 -> 12345.39 | X13: ='2_Production_1'!E107 -> 12510.27 | Y13: ='2_Production_1'!F107 -> 13737.44 | Z13: ='2_Production_1'!G107 -> 14608.16 | AA13: ='2_Production_1'!H107 -> 15086.54 | AB13: ='2_Production_1'!I107 -> 15669.9 | AC13: ='2_Production_1'!J107 -> 17149.06 | AD13: ='2_Production_1'!K107 -> 17549.31 | AE13: =V13/C28*100 -> 34.917659 | AF13: 37.4 | AG13: 37.4 | AH13: =X13/AZ28*100 -> 34.664493 | AI13: =Y13/BA28*100 -> 33.836001 | AJ13: =Z13/BB28*100 -> 33.513402 | AK13: 24 | AL13: 16.1 | AM13: 14.1 | AN13: 8 | AQ13: Trade (DIT_tr) | AS13: 1972.165 | AT13: 2104.14 | AU13: 2239.252 | AV13: 2504.341 | AW13: 2662.862 | AX13: 2795.668 | AY13: 2957.747 | AZ13: 3204.712 | BA13: 3368.733
B14: Financial services (DIT_fs) | C14: =C29*AF14/100 -> 8013.5878 | D14: =D29*AG14/100 -> 8904.3791 | E14: =E29*AH14/100 -> 9291.7983 | F14: =F29*AI14/100 -> 10896.998 | G14: =G29*AJ14/100 -> 9898.3674 | H14: =H29*AK14/100 -> 8362.5248 | I14: =I29*AL14/100 -> 7117.8672 | J14: =J29*AM14/100 -> 6812.5067 | K14: =K29*AN14/100 -> 5513.4254 | L14: 4.673192 | U14: Financial services (DIT_fs) | V14: ='2_Production_1'!C122 -> 5856.509 | W14: ='2_Production_1'!D122 -> 6158.721 | X14: ='2_Production_1'!E122 -> 6257.932 | Y14: ='2_Production_1'!F122 -> 6471.943 | Z14: ='2_Production_1'!G122 -> 6666.596 | AA14: ='2_Production_1'!H122 -> 6833.803 | AB14: ='2_Production_1'!I122 -> 7177.593 | AC14: ='2_Production_1'!J122 -> 7303.416 | AD14: ='2_Production_1'!K122 -> 7545.684 | AE14: =V14/C29*100 -> 39.025913 | AF14: 53.4 | AG14: 53.4 | AH14: 53.4 | AI14: 53.4 | AJ14: 52 | AK14: 37 | AL14: 33 | AM14: 28.5 | AN14: 23 | AQ14: Financial services (DIT_fs) | AS14: 10607.68 | AT14: 11310.79 | AU14: 12028.48 | AV14: 13228.64 | AW14: 13987.59 | AX14: 14708.05 | AY14: 15521.88 | AZ14: 16572.58 | BA14: 17416.56
B15: Public Services (DIT_ps) | C15: =C30*AF15/100 -> 3924.9603 | D15: =D30*AG15/100 -> 4361.2593 | E15: =E30*AH15/100 -> 4025.9504 | F15: =F30*AI15/100 -> 4422.2746 | G15: =G30*AJ15/100 -> 4789.9507 | H15: =H30*AK15/100 -> 4392.112 | I15: =I30*AL15/100 -> 2940.7222 | J15: =J30*AM15/100 -> 3025.0571 | K15: =K30*AN15/100 -> 3249.8143 | L15: 3.0868339 | U15: Public Services (DIT_ps) | V15: ='2_Production_1'!C137 -> 3656.114 | W15: ='2_Production_1'!D137 -> 3672.812 | X15: ='2_Production_1'!E137 -> 3897.717 | Y15: ='2_Production_1'!F137 -> 4398.493 | Z15: ='2_Production_1'!G137 -> 4581.257 | AA15: ='2_Production_1'!H137 -> 5184.905 | AB15: ='2_Production_1'!I137 -> 5736.568 | AC15: ='2_Production_1'!J137 -> 6209.787 | AD15: ='2_Production_1'!K137 -> 6756.221 | AE15: =V15/C30*100 -> 18.164317 | AF15: 19.5 | AG15: 19.5 | AH15: =X15/AZ30*100 -> 17.690986 | AI15: =Y15/BA30*100 -> 17.860479 | AJ15: 17.5 | AK15: 16 | AL15: 10.1 | AM15: 10 | AN15: 10.1 | AQ15: Public Services (DIT_ps) | AS15: 562.4446 | AT15: 595.4913 | AU15: 645.077 | AV15: 709.778 | AW15: 752.9944 | AX15: 807.0677 | AY15: 854.8023 | AZ15: 911.7216 | BA15: 966.6239
B16: Market Services | C16: =C31*AF16/100 -> 1444.9187 | D16: =D31*AG16/100 -> 1605.536 | E16: =E31*AH16/100 -> 1978.4434 | F16: =F31*AI16/100 -> 2428.4594 | G16: =G31*AJ16/100 -> 2135.1993 | H16: =H31*AK16/100 -> 2228.5927 | I16: =I31*AL16/100 -> 2424.425 | J16: =J31*AM16/100 -> 1521.2435 | K16: =K31*AN16/100 -> 1443.4027 | L16: 1.8599913 | U16: Market Services | V16: ='2_Production_1'!C152 -> 3227.287 | W16: ='2_Production_1'!D152 -> 3460.954 | X16: ='2_Production_1'!E152 -> 4327.249 | Y16: ='2_Production_1'!F152 -> 4660.14 | Z16: ='2_Production_1'!G152 -> 5427.298 | AA16: ='2_Production_1'!H152 -> 5689.536 | AB16: ='2_Production_1'!I152 -> 5761.674 | AC16: ='2_Production_1'!J152 -> 6551.6 | AD16: ='2_Production_1'!K152 -> 6885.488 | AE16: =V16/C31*100 -> 82.41771 | AF16: 36.9 | AG16: 36.9 | AH16: 36.9 | AI16: 36.9 | AJ16: 35 | AK16: 30 | AL16: 29 | AM16: 20.1 | AN16: 18 | AQ16: Market Services | AS16: 894.8115 | AT16: 956.627 | AU16: 1044.398 | AV16: 1126.558 | AW16: 1213.77 | AX16: 1290.827 | AY16: 1334.832 | AZ16: 1411.279 | BA16: 1470.94
C17: =SUM(C7:C16) -> 144745.93 | D17: =SUM(D7:D16) -> 158957.23 | E17: =SUM(E7:E16) -> 162809.47 | F17: =SUM(F7:F16) -> 170299.72 | G17: =SUM(G7:G16) -> 186496.15 | H17: =SUM(H7:H16) -> 205150.27 | I17: =SUM(I7:I16) -> 195295.7 | J17: =SUM(J7:J16) -> 179544.37 | ... L17: =SUM(L7:L16) -> 100 | V17: =SUM(V7:V16) -> 134042.9 | W17: =SUM(W7:W16) -> 144285.67 | X17: =SUM(X7:X16) -> 154720.2 | Y17: =SUM(Y7:Y16) -> 168166.02 | Z17: =SUM(Z7:Z16) -> 178343.86 | AA17: =SUM(AA7:AA16) -> 188814.32 | AB17: =SUM(AB7:AB16) -> 196716.15 | AC17: =SUM(AC7:AC16) -> 207050.63 | AD17: =SUM(AD7:AD16) -> 216594.56 | AS17: =SUM(AS7:AS16) -> 134042.9 | AT17: =SUM(AT7:AT16) -> 144285.67 | AU17: =SUM(AU7:AU16) -> 154720.21 | AV17: =SUM(AV7:AV16) -> 168166 | AW17: =SUM(AW7:AW16) -> 178343.87 | AX17: =SUM(AX7:AX16) -> 188814.3 | AY17: =SUM(AY7:AY16) -> 196716.14 | AZ17: =SUM(AZ7:AZ16) -> 207050.63 | BA17: =SUM(BA7:BA16) -> 216594.55
A18: 1 | B18: Gross Output (current prices) | C18: =C32-C17 -> 143278.44 | D18: =D32-D17 -> 157617.76 | E18: =E32-E17 -> 181287.83 | F18: =F32-F17 -> 204962.87 | G18: =G32-G17 -> 233000.51 | H18: =H32-H17 -> 269234.28 | I18: =I32-I17 -> 304009.82 | J18: =J32-J17 -> 345901.64 | K18: =K32-K17 -> 390205.99 | M18: Gross Output (%) | T18: Gross Output (%) | AW18: Gross Output (current prices)
B19: Source: xp_grp | C19: ='3_In & SA'!C68+689.2 -> 14524.861 | D19: ='3_In & SA'!D68+3879.8 -> 19301.09 | E19: ='3_In & SA'!E68+(16396.7555*13.5/100) -> 18610.317 | F19: ='3_In & SA'!F68+(18024.8889*13.7/100) -> 20494.299 | G19: ='3_In & SA'!G68+(19040.9628*13.5/100) -> 21611.493 | H19: ='3_In & SA'!H68+(20076.5768*8.2/100) -> 21722.856 | I19: ='3_In & SA'!I68+(21031.3856*4.5/100) -> 21977.798 | J19: ='3_In & SA'!J68 -> 22429.217 | K19: ='3_In & SA'!K68 -> 23764.345 | M19: Source: xp_grp | N19: Темпы роста ВВ к соответсвующему периоду прошлого года | X19: Темп роста ВВ метод дефлятирование | AW19: Source: xp_grp
C20: 2024 | D20: =C20+1 -> 2025 | E20: =D20+1 -> 2026 | F20: =E20+1 -> 2027 | G20: =F20+1 -> 2028 | H20: =G20+1 -> 2029 | I20: =H20+1 -> 2030 | J20: =I20+1 -> 2031 | K20: =J20+1 -> 2032 | N20: 2024 | O20: 2025 | P20: 2026 | Q20: 2027 | R20: 2028 | S20: 2029 | T20: 2030 | X20: 2026 | Y20: 2027 | Z20: 2028 | AA20: 2029 | AB20: 2030 | AC20: 2031 | AD20: 2032 | AO20: 2025 | AP20: 2026 | AQ20: 2027 | AR20: 2028 | AS20: 2029 | AT20: 2030 | AU20: 2031 | AV20: 2032 | AX20: 2024 | AY20: =AX20+1 -> 2025 | AZ20: =AY20+1 -> 2026 | BA20: =AZ20+1 -> 2027 | BB20: =BA20+1 -> 2028 | BC20: =BB20+1 -> 2029 | BD20: =BC20+1 -> 2030 | BE20: =BD20+1 -> 2031 | BF20: =BE20+1 -> 2032
B21: Agriculture (XP_a) | C21: =$L$21*C33/100 -> 79304.265 | D21: =($L$21*D33/100)-3466.2 -> 84653.535 | E21: =$AH$21*E33/100 -> 95155.45 | F21: =$AI$21*F33/100 -> 104590.97 | G21: =($AJ$21*G33/100)+2151.7 -> 114715.95 | H21: =($AK$21*H33/100)+5511.3 -> 125434.68 | I21: =($AL$21*I33/100)+9979.4 -> 136949.67 | J21: =($AM$21*J33/100)+14018.1 -> 148095.67 | K21: =($AN$21*K33/100)+17692.2 -> 159589.19 | L21: 27.533873 | M21: Agriculture (XP_a) | N21: =E21/D21*100 -> 112.40576 | O21: =F21/E21*100 -> 109.9159 | P21: =G21/F21*100 -> 109.68056 | Q21: =H21/G21*100 -> 109.34371 | R21: =I21/H21*100 -> 109.18007 | S21: =J21/I21*100 -> 108.13876 | T21: =K21/J21*100 -> 107.76087 | U21: Agriculture (XP_a) | X21: =E21/D21*100/'1_Prices'!E3 -> 108.92031 | Y21: =F21/E21*100/'1_Prices'!F3 -> 108.61255 | Z21: =G21/F21*100/'1_Prices'!G3 -> 108.27301 | AA21: =H21/G21*100/'1_Prices'!H3 -> 108.15402 | AB21: =I21/H21*100/'1_Prices'!I3 -> 108.31356 | AC21: =J21/I21*100/'1_Prices'!J3 -> 107.60075 | AD21: =K21/J21*100/'1_Prices'!K3 -> 107.54578 | AF21: 27.533873 | AG21: 27.533873 | AH21: =AZ21/AZ32*100+0.333 -> 27.653647 | AI21: =BA21/BA32*100+1.5 -> 27.425171 | AJ21: =BB21/BB32*100+2.5+0.43635 -> 27.863477 | AK21: =BC21/BC32*100+2.5+0.62436 -> 27.894886 | AL21: =BD21/BD32*100+3.5+0.63202 -> 28.01758 | AM21: =BE21/BE32*100+4.1+0.2876 -> 27.687103 | AN21: =BF21/BF32*100+5+0.43977 -> 28.76163 | AO21: =D21-C21 -> 5349.2706 | AP21: =E21-D21 -> 10501.915 | AQ21: =F21-E21 -> 9435.5161 | AR21: =G21-F21 -> 10124.987 | AS21: =H21-G21 -> 10718.727 | AT21: =I21-H21 -> 11514.988 | AU21: =J21-I21 -> 11146.002 | AW21: Agriculture (XP_a) | AX21: 77989.18 | AY21: 87034.98 | AZ21: 91015.24 | BA21: 95492.76 | BB21: 97449.91 | BC21: 102734.4 | BD21: 103766.2 | BE21: 108226.8 | BF21: 115059.6
B22: Industry | C22: =C23+C24+C25 -> 82558.514 | D22: =D23+D24+D25 -> 91735.728 | E22: =E23+E24+E25 -> 99935.217 | F22: =F23+F24+F25 -> 104885.61 | G22: =G23+G24+G25 -> 131605.53 | H22: =H23+H24+H25 -> 164803.16 | I22: =I23+I24+I25 -> 167868.34 | J22: =J23+J24+J25 -> 171881.64 | ... L22: =L23+L24+L25 -> 28.663725 | M22: Industry | N22: =E22/D22*100 -> 108.93816 | O22: =F22/E22*100 -> 104.9536 | P22: =G22/F22*100 -> 125.4753 | Q22: =H22/G22*100 -> 125.2251 | R22: =I22/H22*100 -> 101.85991 | S22: =J22/I22*100 -> 102.39074 | T22: =K22/J22*100 -> 100.51296 | U22: Industry + включая, досчеты ННЭ | X22: =E22/D22*100/'1_Prices'!E2 -> 118.02618 | Y22: =F22/E22*100/'1_Prices'!F2 -> 112.37002 | Z22: =G22/F22*100/'1_Prices'!G2 -> 139.24681 | AA22: =H22/G22*100/'1_Prices'!H2 -> 139.13745 | AB22: =I22/H22*100/'1_Prices'!I2 -> 115.74989 | AC22: =J22/I22*100/'1_Prices'!J2 -> 110.08573 | AD22: =K22/J22*100/'1_Prices'!K2 -> 118.25054 | AF22: =AF23+AF24+AF25 -> 28.663725 | AG22: =AG23+AG24+AG25 -> 28.663725 | AH22: =AH23+AH24+AH25 -> 29.042721 | AI22: =AI23+AI24+AI25 -> 29.131003 | AJ22: =AJ23+AJ24+AJ25 -> 29.295533 | AK22: =AK23+AK24+AK25 -> 29.300173 | AL22: =AL23+AL24+AL25 -> 29.109623 | AM22: =AM23+AM24+AM25 -> 29.928652 | AN22: =AN23+AN24+AN25 -> 29.55562 | AO22: =D22-C22 -> 9177.2133 | AP22: =E22-D22 -> 8199.489 | AQ22: =F22-E22 -> 4950.3931 | AR22: =G22-F22 -> 26719.924 | AS22: =H22-G22 -> 33197.627 | AT22: =I22-H22 -> 3065.1841 | AU22: =J22-I22 -> 4013.2985 | AW22: Industry | AX22: =AX23+AX24+AX25 -> 79678.937 | AY22: =AY23+AY24+AY25 -> 88903.85 | AZ22: =AZ23+AZ24+AZ25 -> 96752.11 | BA22: =BA23+BA24+BA25 -> 109039.15 | BB22: =BB23+BB24+BB25 -> 118703.06 | BC22: =BC23+BC24+BC25 -> 127673.28 | BD22: =BD23+BD24+BD25 -> 133393.61 | BE22: =BE23+BE24+BE25 -> 140971.18 | BF22: =BF23+BF24+BF25 -> 148230.7
B23: Mining (XP_mi) | C23: =$L$23*C33/100 -> 13541.152 | D23: =$L$23*D33/100 -> 15046.388 | E23: 26754.532 | F23: 29788.942 | G23: 40744.262 | H23: 48047.335 | I23: 49097.704 | J23: 50969.757 | K23: 50646.668 | L23: 4.7013912 | M23: Mining (XP_mi) | N23: =E23/D23*100 -> 177.81365 | O23: =F23/E23*100 -> 111.34167 | P23: =G23/F23*100 -> 136.77647 | Q23: =H23/G23*100 -> 117.92417 | R23: =I23/H23*100 -> 102.18611 | S23: =J23/I23*100 -> 103.81292 | T23: =K23/J23*100 -> 99.366116 | U23: Mining (XP_mi) | X23: =E23/D23*100/'1_Prices'!E6 -> 170.7117 | Y23: =F23/E23*100/'1_Prices'!F6 -> 123.02947 | Z23: =G23/F23*100/'1_Prices'!G6 -> 146.28499 | AA23: =H23/G23*100/'1_Prices'!H6 -> 126.12211 | AB23: =I23/H23*100/'1_Prices'!I6 -> 109.28996 | AC23: =J23/I23*100/'1_Prices'!J6 -> 114.7104 | AD23: =K23/J23*100/'1_Prices'!K6 -> 110.28426 | AF23: 4.7013912 | AG23: 4.7013912 | AH23: =AZ23/$AZ$32*100+0.7 -> 5.8862805 | AI23: =BA23/$AZ$32*100 -> 5.5822495 | AJ23: =BB23/$AZ$32*100-0.4 -> 5.4971377 | AK23: =BC23/$AZ$32*100-0.6 -> 5.6053801 | AL23: =BD23/$AZ$32*100-1 -> 5.5493435 | AM23: =BE23/$AZ$32*100-1.4 -> 5.5797727 | AN23: =BF23/$AZ$32*100-1.9 -> 5.4114199 | AO23: =D23-C23 -> 1505.236 | AP23: =E23-D23 -> 11708.143 | AQ23: =F23-E23 -> 3034.4099 | AR23: =G23-F23 -> 10955.32 | AS23: =H23-G23 -> 7303.0728 | AT23: =I23-H23 -> 1050.3691 | AU23: =J23-I23 -> 1872.0538 | AW23: Mining (XP_mi) | AX23: 12664.64 | AY23: 16086.69 | AZ23: 17277.43 | BA23: 18596.55 | BB23: 19645.56 | BC23: 20672.43 | BD23: 21818.3 | BE23: 23252.22 | BF23: 24357.06
B24: Manufacturing (XP_m) | C24: =$L$24*C33/100 -> 58669.419 | D24: =$L$24*D33/100 -> 65191.118 | E24: 60065.504 | F24: 60339.771 | G24: 73035.004 | H24: 95177.148 | I24: 96446.384 | J24: 97338.682 | K24: 97988.817 | L24: 20.369602 | M24: Manufacturing (XP_m) | N24: =E24/D24*100 -> 92.137558 | O24: =F24/E24*100 -> 100.45661 | P24: =G24/F24*100 -> 121.03958 | Q24: =H24/G24*100 -> 130.31717 | R24: =I24/H24*100 -> 101.33355 | S24: =J24/I24*100 -> 100.92517 | T24: =K24/J24*100 -> 100.66791 | U24: Manufacturing (XP_m) | X24: =E24/D24*100/'1_Prices'!E7 -> 88.396104 | Y24: =F24/E24*100/'1_Prices'!F7 -> 95.143064 | Z24: =G24/F24*100/'1_Prices'!G7 -> 119.95994 | AA24: =H24/G24*100/'1_Prices'!H7 -> 129.15477 | AB24: =I24/H24*100/'1_Prices'!I7 -> 100.42968 | AC24: =J24/I24*100/'1_Prices'!J7 -> 110.90679 | AD24: =K24/J24*100/'1_Prices'!K7 -> 110.98998 | AF24: 20.369602 | AG24: 20.369602 | AH24: =AZ24/$AZ$32*100-0.7 -> 19.344966 | AI24: =BA24/$AZ$32*100-2.3 -> 19.679295 | AJ24: =BB24/$AZ$32*100-4.6-0.43635 -> 19.385788 | AK24: =BC24/$AZ$32*100-6.9-0.62436 -> 19.140677 | AL24: =BD24/$AZ$32*100-8.1-0.63202 -> 19.075477 | AM24: =BE24/$AZ$32*100-9.1-0.2876 -> 19.480998 | AN24: =BF24/$AZ$32*100-9.7-0.3-0.43977 -> 19.253638 | AO24: =D24-C24 -> 6521.6989 | AP24: =E24-D24 -> -5125.614 | AQ24: =F24-E24 -> 274.26743 | AR24: =G24-F24 -> 12695.233 | AS24: =H24-G24 -> 22142.144 | AT24: =I24-H24 -> 1269.2363 | AU24: =J24-I24 -> 892.2976 | AW24: Manufacturing (XP_m) | AX24: 57016.34 | AY24: 61135.58 | AZ24: 66777.24 | BA24: 73221.21 | BB24: 81359.23 | BC24: 88831.16 | BD24: 92637.12 | BE24: 96172.04 | BF24: 98919.79
B25: Energy and Water (XP_e) | C25: =$L$25*C33/100 -> 10347.943 | D25: =$L$25*D33/100 -> 11498.221 | E25: =$AH$25*E33/100 -> 13115.181 | F25: =$AI$25*F33/100 -> 14756.897 | G25: =$AJ$25*G33/100 -> 17826.267 | H25: 21578.678 | I25: 22324.257 | J25: 23573.204 | K25: =$AN$25*K33/100 -> 24127.841 | L25: =3.48434345706365+0.108388206913228 -> 3.5927317 | M25: Energy and Water (XP_e) | N25: =E25/D25*100 -> 114.06269 | O25: =F25/E25*100 -> 112.51768 | P25: =G25/F25*100 -> 120.79957 | Q25: =H25/G25*100 -> 121.0499 | R25: =I25/H25*100 -> 103.45516 | S25: =J25/I25*100 -> 105.59457 | T25: =K25/J25*100 -> 102.35283 | U25: Energy and Water (XP_e) | X25: =E25/D25*100/'1_Prices'!E8 -> 110.1923 | Y25: =F25/E25*100/'1_Prices'!F8 -> 106.82274 | Z25: =G25/F25*100/'1_Prices'!G8 -> 114.80382 | AA25: =H25/G25*100/'1_Prices'!H8 -> 111.48494 | AB25: =I25/H25*100/'1_Prices'!I8 -> 101.42663 | AC25: =J25/I25*100/'1_Prices'!J8 -> 98.099024 | AD25: =K25/J25*100/'1_Prices'!K8 -> 102.35283 | AF25: =3.48434345706365+0.108388206913228 -> 3.5927317 | AG25: =3.48434345706365+0.108388206913228 -> 3.5927317 | AH25: =AZ25/$AZ$32*100 -> 3.8114746 | AI25: =BA25/$AZ$32*100-1.3 -> 3.8694586 | AJ25: =BB25/$AZ$32*100-0.9 -> 4.4126068 | AK25: =BC25/$AZ$32*100-0.9 -> 4.5541161 | AL25: =BD25/$AZ$32*100-1.2 -> 4.4848018 | AM25: =BE25/$AZ$32*100-1.9+0.3 -> 4.8678815 | AN25: =BF25/$AZ$32*100-2.6 -> 4.8905623 | AO25: =D25-C25 -> 1150.2784 | AP25: =E25-D25 -> 1616.9596 | AQ25: =F25-E25 -> 1641.7158 | AR25: =G25-F25 -> 3069.3707 | AS25: =H25-G25 -> 3752.411 | AT25: =I25-H25 -> 745.57864 | AU25: =J25-I25 -> 1248.947 | AW25: Energy and Water (XP_e) | AX25: 9997.957 | AY25: 11681.58 | AZ25: 12697.44 | BA25: 17221.39 | BB25: 17698.27 | BC25: 18169.69 | BD25: 18938.19 | BE25: 21546.92 | BF25: 24953.85
B26: Construction (XP_c) | C26: =$L$26*C33/100 -> 34159.194 | D26: =$L$26*D33/100 -> 37956.334 | E26: =$AH$26*E33/100 -> 42970.896 | F26: =$AI$26*F33/100 -> 47069.925 | G26: =$AJ$26*G33/100 -> 49542.699 | H26: =$AK$26*H33/100 -> 53161.455 | I26: =$AL$26*I33/100 -> 55601.086 | J26: =$AM$26*J33/100 -> 59731.328 | K26: =$AN$26*K33/100 -> 59181.627 | L26: 11.859828 | M26: Construction (XP_c) | N26: =E26/D26*100 -> 113.2114 | O26: =F26/E26*100 -> 109.53908 | P26: =G26/F26*100 -> 105.25341 | Q26: =H26/G26*100 -> 107.30432 | R26: =I26/H26*100 -> 104.5891 | S26: =J26/I26*100 -> 107.42835 | T26: =K26/J26*100 -> 99.079711 | U26: Construction (XP_c) | X26: =E26/D26*100/'1_Prices'!E9 -> 106.80321 | Y26: =F26/E26*100/'1_Prices'!F9 -> 102.37297 | Z26: =G26/F26*100/'1_Prices'!G9 -> 100.72096 | AA26: =H26/G26*100/'1_Prices'!H9 -> 105.09727 | AB26: =I26/H26*100/'1_Prices'!I9 -> 101.05227 | AC26: =J26/I26*100/'1_Prices'!J9 -> 102.80225 | AD26: =K26/J26*100/'1_Prices'!K9 -> 93.914418 | AF26: 11.859828 | AG26: 12.859828 | AH26: =AZ26/$AZ$32*100 -> 12.488008 | AI26: =BA26/$AZ$32*100-1 -> 12.342373 | AJ26: =BB26/$AZ$32*100-2 -> 12.263501 | AK26: =BC26/$AZ$32*100-2.2 -> 12.365668 | AL26: =BD26/$AZ$32*100-3.1 -> 12.269076 | AM26: =BE26/$AZ$32*100-3.9 -> 12.334557 | AN26: =BF26/$AZ$32*100-5 -> 11.995745 | AO26: =D26-C26 -> 3797.1397 | AP26: =E26-D26 -> 5014.5621 | AQ26: =F26-E26 -> 4099.0293 | AR26: =G26-F26 -> 2472.7738 | AS26: =H26-G26 -> 3618.7559 | AT26: =I26-H26 -> 2439.6304 | AU26: =J26-I26 -> 4130.2423 | AW26: Construction (XP_c) | AX26: 31675.93 | AY26: 37514.72 | AZ26: 41602.2 | BA26: 44448.41 | BB26: 47517.03 | BC26: 48523.66 | BD26: 51200.11 | BE26: 54083.35 | BF26: 56619.15
B27: Transport (XP_t) | C27: =$L$27*C33/100 -> 19057.626 | D27: =$L$27*D33/100 -> 21176.074 | E27: =$AH$27*E33/100 -> 23239.738 | F27: =$AI$27*F33/100 -> 24685.359 | G27: =$AJ$27*G33/100 -> 23922.207 | H27: =$AK$27*H33/100 -> 24763.196 | I27: =$AL$27*I33/100 -> 27771.05 | J27: =$AM$27*J33/100 -> 28480.445 | K27: =$AN$27*K33/100 -> 26957.451 | L27: =4.36947866818869+2.24719259080148 -> 6.6166713 | M27: Transport (XP_t) | N27: =E27/D27*100 -> 109.74527 | O27: =F27/E27*100 -> 106.22047 | P27: =G27/F27*100 -> 96.908484 | Q27: =H27/G27*100 -> 103.51552 | R27: =I27/H27*100 -> 112.14647 | S27: =J27/I27*100 -> 102.55444 | T27: =K27/J27*100 -> 94.65249 | U27: Transport (XP_t) | X27: =E27/D27*100/'1_Prices'!E10 -> 104.5988 | Y27: =F27/E27*100/'1_Prices'!F10 -> 97.626863 | Z27: =G27/F27*100/'1_Prices'!G10 -> 88.5618 | AA27: =H27/G27*100/'1_Prices'!H10 -> 90.307818 | AB27: =I27/H27*100/'1_Prices'!I10 -> 103.03527 | AC27: =J27/I27*100/'1_Prices'!J10 -> 92.750693 | AD27: =K27/J27*100/'1_Prices'!K10 -> 84.334952 | AF27: =4.36947866818869+2.24719259080148 -> 6.6166713 | AG27: =4.36947866818869+2.24719259080148 -> 6.6166713 | AH27: =AZ27/$AZ$32*100-0.333 -> 6.7538277 | AI27: =BA27/$AZ$32*100-2.3-0.4 -> 6.4728361 | AJ27: =BB27/$AZ$32*100-3.8 -> 5.9215589 | AK27: =BC27/$AZ$32*100-3.5-1.2 -> 5.7600655 | AL27: =BD27/$AZ$32*100-4.5-0.8 -> 6.12803 | AM27: =BE27/$AZ$32*100-7 -> 5.88123 | AN27: =BF27/$AZ$32*100-9 -> 5.4641063 | AO27: =D27-C27 -> 2118.4477 | AP27: =E27-D27 -> 2063.6648 | AQ27: =F27-E27 -> 1445.6203 | AR27: =G27-F27 -> -763.15185 | AS27: =H27-G27 -> 840.98917 | AT27: =I27-H27 -> 3007.8543 | AU27: =J27-I27 -> 709.39524 | AW27: Transport (XP_t) | AX27: 18362.16 | AY27: 20607.32 | AZ27: 23608.86 | BA27: 30558.13 | BB27: 32386.13 | BC27: 34846.37 | BD27: 38071.02 | BE27: 42912.17 | BF27: 48185.32
B28: Trade (XP_tr) | C28: =$L$28*C33/100 -> 33894.283 | D28: =$L$28*D33/100 -> 37661.975 | E28: =$AH$28*E33/100 -> 37276.913 | F28: =$AI$28*F33/100 -> 42283.058 | G28: =$AJ$28*G33/100 -> 47203.223 | H28: =$AK$28*H33/100 -> 48741.302 | I28: =$AL$28*I33/100 -> 52069.93 | J28: =$AM$28*J33/100 -> 55534.444 | K28: =$AN$28*K33/100 -> 55226.44 | L28: =8.84253063267223+2.92532179066877 -> 11.767852 | M28: Trade (XP_tr) | N28: =E28/D28*100 -> 98.977584 | O28: =F28/E28*100 -> 113.42961 | P28: =G28/F28*100 -> 111.63626 | Q28: =H28/G28*100 -> 103.25842 | R28: =I28/H28*100 -> 106.82917 | S28: =J28/I28*100 -> 106.65358 | T28: =K28/J28*100 -> 99.445383 | U28: Trade (XP_tr) | X28: =E28/D28*100/'1_Prices'!E11 -> 97.008886 | Y28: =F28/E28*100/'1_Prices'!F11 -> 108.52006 | Z28: =G28/F28*100/'1_Prices'!G11 -> 105.81867 | AA28: =H28/G28*100/'1_Prices'!H11 -> 98.388671 | AB28: =I28/H28*100/'1_Prices'!I11 -> 100.83285 | AC28: =J28/I28*100/'1_Prices'!J11 -> 99.704289 | AD28: =K28/J28*100/'1_Prices'!K11 -> 92.028954 | AF28: =8.84253063267223+2.92532179066877 -> 11.767852 | AG28: =8.84253063267223+2.92532179066877 -> 11.767852 | AH28: =AZ28/$AZ$32*100 -> 10.833248 | AI28: =BA28/$AZ$32*100-1.1 -> 11.087192 | AJ28: =BB28/$AZ$32*100-2+0.6 -> 11.684402 | AK28: =BC28/$AZ$32*100-2.1 -> 11.337514 | AL28: =BD28/$AZ$32*100-3.1+0.5 -> 11.489882 | AM28: =BE28/$AZ$32*100-4.1 -> 11.467898 | AN28: =BF28/$AZ$32*100-4.9 -> 11.194053 | AO28: =D28-C28 -> 3767.6921 | AP28: =E28-D28 -> -385.06197 | AQ28: =F28-E28 -> 5006.1446 | AR28: =G28-F28 -> 4920.1657 | AS28: =H28-G28 -> 1538.0782 | AT28: =I28-H28 -> 3328.6285 | AU28: =J28-I28 -> 3464.5134 | AW28: Trade (XP_tr) | AX28: 33468 | AY28: 35260.35 | AZ28: 36089.58 | BA28: 40600.07 | BB28: 43589.01 | BC28: 44765.36 | BD28: 46938.64 | BE28: 51862.46 | BF28: 53615.28
B29: Financial services (XP_fs) | C29: =$L$29*C33/100 -> 15006.719 | D29: =$L$29*D33/100 -> 16674.867 | E29: =$AH$29*E33/100 -> 17400.371 | F29: =$AI$29*F33/100 -> 20406.363 | G29: =$AJ$29*G33/100 -> 19035.322 | H29: =$AK$29*H33/100 -> 22601.418 | I29: =$AL$29*I33/100 -> 21569.295 | J29: =$AM$29*J33/100 -> 23903.532 | K29: =$AN$29*K33/100 -> 23971.415 | L29: =2.58276023010352+1.93584008592331+0.466027115327302+0.225597892404672 -> 5.2102253 | M29: Financial services (XP_fs) | N29: =E29/D29*100 -> 104.35088 | O29: =F29/E29*100 -> 117.27544 | P29: =G29/F29*100 -> 93.281307 | Q29: =H29/G29*100 -> 118.7341 | R29: =I29/H29*100 -> 95.433367 | S29: =J29/I29*100 -> 110.82204 | T29: =K29/J29*100 -> 100.28399 | U29: Financial services (XP_fs) | X29: =E29/D29*100/'1_Prices'!E12 -> 97.787578 | Y29: =F29/E29*100/'1_Prices'!F12 -> 107.44124 | Z29: =G29/F29*100/'1_Prices'!G12 -> 84.074176 | AA29: =H29/G29*100/'1_Prices'!H12 -> 104.92855 | AB29: =I29/H29*100/'1_Prices'!I12 -> 82.894209 | AC29: =J29/I29*100/'1_Prices'!J12 -> 92.386267 | AD29: =K29/J29*100/'1_Prices'!K12 -> 83.56024 | AF29: =2.58276023010352+1.93584008592331+0.466027115327302+0.225597892404672 -> 5.2102253 | AG29: =2.58276023010352+1.93584008592331+0.466027115327302+0.225597892404672 -> 5.2102253 | AH29: =AZ29/$AZ$32*100 -> 5.0568173 | AI29: =BA29/$AZ$32*100 -> 5.3508253 | AJ29: =BB29/$AZ$32*100-0.9 -> 4.7118889 | AK29: =BC29/$AZ$32*100-1.1+0.5 -> 5.2572232 | AL29: =BD29/$AZ$32*100-1.5 -> 4.759535 | AM29: =BE29/$AZ$32*100-1.7 -> 4.9360945 | AN29: =BF29/$AZ$32*100-2 -> 4.8588556 | AO29: =D29-C29 -> 1668.1485 | AP29: =E29-D29 -> 725.50424 | AQ29: =F29-E29 -> 3005.9913 | AR29: =G29-F29 -> -1371.0409 | AS29: =H29-G29 -> 3566.0965 | AT29: =I29-H29 -> -1032.1238 | AU29: =J29-I29 -> 2334.2375 | AW29: Financial services (XP_fs) | AX29: 14788.22 | AY29: 16646.49 | AZ29: 16846.14 | BA29: 17825.59 | BB29: 18695.29 | BC29: 19512.59 | BD29: 20852.84 | BE29: 22107.3 | BF29: 22849.4
B30: Public Services (XP_ps) | C30: =$L$30*C33/100 -> 20128.001 | D30: =$L$30*D33/100 -> 22365.432 | E30: =$AH$30*E33/100 -> 22757.071 | F30: =$AI$30*F33/100 -> 24760.112 | G30: =$AJ$30*G33/100 -> 27371.147 | H30: =$AK$30*H33/100 -> 27450.7 | I30: =$AL$30*I33/100 -> 29116.061 | J30: =$AM$30*J33/100 -> 30250.571 | K30: =$AN$30*K33/100 -> 32176.379 | L30: =1.79416924867713+3.24177036882918+1.51008952219217+0.442268870232184 -> 6.988298 | M30: Public Services (XP_ps) | N30: =E30/D30*100 -> 101.75109 | O30: =F30/E30*100 -> 108.80184 | P30: =G30/F30*100 -> 110.54533 | Q30: =H30/G30*100 -> 100.29065 | R30: =I30/H30*100 -> 106.06673 | S30: =J30/I30*100 -> 103.89651 | T30: =K30/J30*100 -> 106.36619 | U30: Public Services (XP_ps) | X30: =E30/D30*100/'1_Prices'!E13 -> 97.818871 | Y30: =F30/E30*100/'1_Prices'!F13 -> 105.59636 | Z30: =G30/F30*100/'1_Prices'!G13 -> 106.29041 | AA30: =H30/G30*100/'1_Prices'!H13 -> 95.453085 | AB30: =I30/H30*100/'1_Prices'!I13 -> 99.989285 | AC30: =J30/I30*100/'1_Prices'!J13 -> 97.005253 | AD30: =K30/J30*100/'1_Prices'!K13 -> 97.489122 | AF30: =1.79416924867713+3.24177036882918+1.51008952219217+0.442268870232184 -> 6.988298 | AG30: =1.79416924867713+3.24177036882918+1.51008952219217+0.442268870232184 -> 6.988298 | AH30: =AZ30/$AZ$32*100 -> 6.6135573 | AI30: =BA30/$AZ$32*100-0.9 -> 6.4924375 | AJ30: =BB30/$AZ$32*100-1 -> 6.7752888 | AK30: =BC30/$AZ$32*100-2.5 -> 6.3851948 | AL30: =BD30/$AZ$32*100-3.5 -> 6.4248235 | AM30: =BE30/$AZ$32*100-4.6 -> 6.246762 | AN30: =BF30/$AZ$32*100-5.5 -> 6.5219504 | AO30: =D30-C30 -> 2237.4308 | AP30: =E30-D30 -> 391.63925 | AQ30: =F30-E30 -> 2003.0409 | AR30: =G30-F30 -> 2611.0345 | AS30: =H30-G30 -> 79.553463 | AT30: =I30-H30 -> 1665.361 | AU30: =J30-I30 -> 1134.5093 | AW30: Public Services (XP_ps) | AX30: 19870.87 | AY30: 20162.73 | AZ30: 22032.22 | BA30: 24626.96 | BB30: 25902.38 | BC30: 29599.89 | BD30: 33063.28 | BE30: 36134.6 | BF30: 40049.59
B31: Market Services (XP_ms) | C31: =$L$31*C33/100 -> 3915.7688 | D31: =$L$31*D33/100 -> 4351.0461 | E31: =$AH$31*E33/100 -> 5361.6352 | F31: =$AI$31*F33/100 -> 6581.1908 | G31: =$AJ$31*G33/100 -> 6100.5694 | H31: =$AK$31*H33/100 -> 7428.6423 | I31: =$AL$31*I33/100 -> 8360.0863 | J31: =$AM$31*J33/100 -> 7568.3758 | K31: =$AN$31*K33/100 -> 8018.9041 | L31: =1.04574938284795+0.313777532853857 -> 1.3595269 | M31: Market Services (XP_ms) | N31: =E31/D31*100 -> 123.22635 | O31: =F31/E31*100 -> 122.74596 | P31: =G31/F31*100 -> 92.697045 | Q31: =H31/G31*100 -> 121.76966 | R31: =I31/H31*100 -> 112.53855 | S31: =J31/I31*100 -> 90.529877 | T31: =K31/J31*100 -> 105.95277 | U31: Market Services (XP_ms) | X31: =E31/D31*100/'1_Prices'!E14 -> 122.96394 | Y31: =F31/E31*100/'1_Prices'!F14 -> 119.11278 | Z31: =G31/F31*100/'1_Prices'!G14 -> 89.993374 | AA31: =H31/G31*100/'1_Prices'!H14 -> 116.97969 | AB31: =I31/H31*100/'1_Prices'!I14 -> 108.6205 | AC31: =J31/I31*100/'1_Prices'!J14 -> 86.517788 | AD31: =K31/J31*100/'1_Prices'!K14 -> 99.835362 | AF31: =1.04574938284795+0.313777532853857 -> 1.3595269 | AG31: =1.04574938284795+0.313777532853857 -> 1.3595269 | AH31: =AZ31/$AZ$32*100 -> 1.5581742 | AI31: =BA31/$AZ$32*100 -> 1.7256775 | AJ31: =BB31/$AZ$32*100-0.5 -> 1.5100982 | AK31: =BC31/$AZ$32*100-0.4 -> 1.727946 | AL31: =BD31/$AZ$32*100-0.3 -> 1.8447577 | AM31: =BE31/$AZ$32*100-0.9 -> 1.5628744 | AN31: =BF31/$AZ$32*100-1 -> 1.6253816 | AO31: =D31-C31 -> 435.27729 | AP31: =E31-D31 -> 1010.5891 | AQ31: =F31-E31 -> 1219.5556 | AR31: =G31-F31 -> -480.62138 | AS31: =H31-G31 -> 1328.0729 | AT31: =I31-H31 -> 931.44393 | AU31: =J31-I31 -> -791.71046 | AW31: Market Services (XP_ms) | AX31: 3864.399 | AY31: 4185.875 | AZ31: 5190.858 | BA31: 5748.874 | BB31: 6696.385 | BC31: 7088.98 | BD31: 7144.986 | BE31: 8204.751 | BF31: 8746.123
B32: =SUM('[5]2024-Final'!$AF$6:$AF$15) -> 284532.8 | C32: =C21+C23+C24+C25+C26+C27+C28+C29+C30+C31 -> 288024.37 | D32: =D21+D23+D24+D25+D26+D27+D28+D29+D30+D31 -> 316574.99 | E32: =E21+E23+E24+E25+E26+E27+E28+E29+E30+E31 -> 344097.29 | F32: =F21+F23+F24+F25+F26+F27+F28+F29+F30+F31 -> 375262.58 | G32: =G21+G23+G24+G25+G26+G27+G28+G29+G30+G31 -> 419496.65 | H32: =H21+H23+H24+H25+H26+H27+H28+H29+H30+H31 -> 474384.55 | I32: =I21+I23+I24+I25+I26+I27+I28+I29+I30+I31 -> 499305.52 | J32: =J21+J23+J24+J25+J26+J27+J28+J29+J30+J31 -> 525446.01 | ... L32: =L21+L23+L24+L25+L26+L27+L28+L29+L30+L31 -> 100 | M32: Gross Output | N32: =E32/D32*100 -> 108.69377 | O32: =F32/E32*100 -> 109.05712 | P32: =G32/F32*100 -> 111.7875 | Q32: =H32/G32*100 -> 113.08423 | R32: =I32/H32*100 -> 105.25333 | S32: =J32/I32*100 -> 105.23537 | T32: =K32/J32*100 -> 102.36727 | X32: =GDP!W32/'2_Production_2'!D32*100 -> 104.53926 | Y32: =GDP!Z32/'2_Production_2'!E32*100 -> 105.68779 | Z32: =GDP!AC32/'2_Production_2'!F32*100 -> 109.13871 | AA32: =GDP!AF32/'2_Production_2'!G32*100 -> 110.37276 | AB32: =GDP!AI32/'2_Production_2'!H32*100 -> 102.97158 | AC32: =GDP!AL32/I32*100 -> 104.70175 | AD32: =GDP!AO32/J32*100 -> 101.98767 | AF32: =AF21+AF23+AF24+AF25+AF26+AF27+AF28+AF29+AF30+AF31 -> 100 | AG32: =AG21+AG23+AG24+AG25+AG26+AG27+AG28+AG29+AG30+AG31 -> 101 | AH32: =AH21+AH23+AH24+AH25+AH26+AH27+AH28+AH29+AH30+AH31 -> 100 | AI32: =AI21+AI23+AI24+AI25+AI26+AI27+AI28+AI29+AI30+AI31 -> 100.02752 | AJ32: =AJ21+AJ23+AJ24+AJ25+AJ26+AJ27+AJ28+AJ29+AJ30+AJ31 -> 100.02575 | AK32: =AK21+AK23+AK24+AK25+AK26+AK27+AK28+AK29+AK30+AK31 -> 100.02867 | AL32: =AL21+AL23+AL24+AL25+AL26+AL27+AL28+AL29+AL30+AL31 -> 100.04331 | AM32: =AM21+AM23+AM24+AM25+AM26+AM27+AM28+AM29+AM30+AM31 -> 100.04517 | AN32: =AN21+AN23+AN24+AN25+AN26+AN27+AN28+AN29+AN30+AN31 -> 99.977342 | AO32: =D32-C32 -> 28550.62 | AP32: =E32-D32 -> 27522.301 | AQ32: =F32-E32 -> 31165.291 | AR32: =G32-F32 -> 44234.071 | AS32: =H32-G32 -> 54887.9 | AT32: =I32-H32 -> 24920.966 | AU32: =J32-I32 -> 26140.488 | AX32: =AX21+AX23+AX24+AX25+AX26+AX27+AX28+AX29+AX30+AX31 -> 279697.7 | AY32: =AY21+AY23+AY24+AY25+AY26+AY27+AY28+AY29+AY30+AY31 -> 310316.31 | AZ32: =AZ21+AZ23+AZ24+AZ25+AZ26+AZ27+AZ28+AZ29+AZ30+AZ31 -> 333137.21 | BA32: =BA21+BA23+BA24+BA25+BA26+BA27+BA28+BA29+BA30+BA31 -> 368339.94 | BB32: =BB21+BB23+BB24+BB25+BB26+BB27+BB28+BB29+BB30+BB31 -> 390939.2 | BC32: =BC21+BC23+BC24+BC25+BC26+BC27+BC28+BC29+BC30+BC31 -> 414744.53 | BD32: =BD21+BD23+BD24+BD25+BD26+BD27+BD28+BD29+BD30+BD31 -> 434430.69 | BE32: =BE21+BE23+BE24+BE25+BE26+BE27+BE28+BE29+BE30+BE31 -> 464502.61 | BF32: =BF21+BF23+BF24+BF25+BF26+BF27+BF28+BF29+BF30+BF31 -> 493355.16
B33: Gross Output (in real terms) | C33: 288024.37 | D33: 320041.19 | E33: 344097.29 | F33: 381368.51 | G33: 403984.95 | H33: 429911.71 | I33: 453180.72 | J33: 484260.02 | K33: 493355.16 | X33: 0.923 | Y33: 0.934 | Z33: 0.9011 | AA33: 0.90001 | AB33: 0.849 | AC33: 0.853 | AD33: 0.837 | AO33: =D33-C33 -> 32016.82 | AP33: =E33-D33 -> 24056.101 | AQ33: =F33-E33 -> 37271.219 | AR33: =G33-F33 -> 22616.436 | AS33: =H33-G33 -> 25926.763 | AT33: =I33-H33 -> 23269.006 | AU33: =J33-I33 -> 31079.3 | AW33: Gross Output (in real terms) | AX33: 279697.7 | AY33: 310316.31 | AZ33: 333137.21 | BA33: 368339.94 | BB33: 390939.2 | BC33: 414744.53 | BD33: 434430.69 | BE33: 464502.61 | BF33: 493355.16
B34: Source: xs_grp | C34: =C37+C38+C39 -> 80392.72 | D34: =D37+D38+D39 -> 87435.34 | E34: =E37+E38+E39 -> 94346.15 | F34: =F37+F38+F39 -> 104901.35 | G34: =G37+G38+G39 -> 112460.17 | H34: =H37+H38+H39 -> 122122.67 | I34: =I37+I38+I39 -> 126202.11 | J34: =J37+J38+J39 -> 132661.74 | K34: =K37+K38+K39 -> 138277.18 | U34: Industry - ННЭ | X34: =E22/D22*100/X33 -> 118.02618 | Y34: =F22/E22*100/Y33 -> 112.37002 | Z34: =G22/F22*100/Z33 -> 139.24681 | AA34: =H22/G22*100/AA33 -> 139.13745 | AB34: =I22/H22*100/AB33 -> 119.97633 | AC34: =J22/I22*100/AC33 -> 120.03604 | AD34: =K22/J22*100/AD33 -> 120.08717 | AW34: Source: xs_grp | AX34: =AX37+AX38+AX39 -> 80392.72 | AY34: =AY37+AY38+AY39 -> 87435.34 | AZ34: =AZ37+AZ38+AZ39 -> 94346.15 | BA34: =BA37+BA38+BA39 -> 104901.35 | BB34: =BB37+BB38+BB39 -> 112460.17 | BC34: =BC37+BC38+BC39 -> 122122.67 | BD34: =BD37+BD38+BD39 -> 126202.11 | BE34: =BE37+BE38+BE39 -> 132661.74 | BF34: =BF37+BF38+BF39 -> 138277.18 | BH34: Темп роста ВВ
C35: 2024 | D35: =C35+1 -> 2025 | E35: =D35+1 -> 2026 | F35: =E35+1 -> 2027 | G35: =F35+1 -> 2028 | H35: =G35+1 -> 2029 | I35: =H35+1 -> 2030 | J35: =I35+1 -> 2031 | K35: =J35+1 -> 2032 | N35: 2023 | O35: 2024 | P35: 2025 | Q35: 2026 | R35: 2027 | S35: 2028 | X35: ='GDP-total'!D30/'GDP-total'!C30*100/X36 -> 125 | Y35: ='GDP-total'!E68/'GDP-total'!D68*100/Y36 -> 125 | Z35: ='GDP-total'!F30/'GDP-total'!E30*100/Z36 -> 125.1 | AA35: ='GDP-total'!G30/'GDP-total'!F30*100/AA36 -> 125.1 | AB35: ='GDP-total'!H30/'GDP-total'!G30*100/AB36 -> 119.97633 | AC35: ='GDP-total'!I30/'GDP-total'!H30*100/AC36 -> 120.03604 | AD35: ='GDP-total'!J30/'GDP-total'!I30*100/AD36 -> 120.08717 | AX35: 2024 | AY35: =AX35+1 -> 2025 | AZ35: =AY35+1 -> 2026 | BA35: =AZ35+1 -> 2027 | BB35: =BA35+1 -> 2028 | BC35: =BB35+1 -> 2029 | BD35: =BC35+1 -> 2030 | BE35: =BD35+1 -> 2031 | BF35: =BE35+1 -> 2032 | BH35: 2025 | BI35: 2026 | BJ35: 2027 | BK35: 2028 | BL35: 2029 | BM35: 2030 | BN35: 2031 | BO35: 2032
B36: Agriculture (xs_a) | C36: 78126.15 | D36: 83859.11 | E36: 88077.45 | F36: 91458.96 | G36: 94104.42 | H36: 97266.12 | I36: 98776.62 | J36: 101063.3 | K36: 105444.6 | M36: Agriculture (xs_a) | N36: =D36/C21*100 -> 105.74351 | O36: =E36/D21*100 -> 104.04462 | P36: =F36/E21*100 -> 96.115315 | Q36: =G36/F21*100 -> 89.973756 | R36: =H36/G21*100 -> 84.78866 | S36: =I36/H21*100 -> 78.747457 | X36: 1.001 | Y36: 1.005 | Z36: 1.003 | AA36: 1.001 | AB36: 0.849 | AC36: 0.853 | AD36: 0.837 | AW36: Agriculture (xs_a) | AX36: 78126.15 | AY36: 83859.11 | AZ36: 88077.45 | BA36: 91458.96 | BB36: 94104.42 | BC36: 97266.12 | BD36: 98776.62 | BE36: 101063.3 | BF36: 105444.6 | BH36: =AY36/AX21*100 -> 107.5266 | BI36: =AZ36/AY21*100 -> 101.19776 | BJ36: =BA36/AZ21*100 -> 100.48752 | BK36: =BB36/BA21*100 -> 98.546131 | BL36: =BC36/BB21*100 -> 99.811401 | BM36: =BD36/BC21*100 -> 96.147561 | BN36: =BE36/BD21*100 -> 97.395202 | BO36: =BF36/BE21*100 -> 97.429287
B37: Mining (xs_mi) | C37: 12927.48 | D37: 16091.15 | E37: 17127 | F37: 18168.2 | G37: 18856.14 | H37: 19578.12 | I37: 20410.35 | J37: 21464.13 | K37: 22456.32 | M37: Mining (xs_mi) | N37: =D37/C22*100 -> 19.4906 | O37: =E37/D22*100 -> 18.669934 | P37: =F37/E22*100 -> 18.179978 | Q37: =G37/F22*100 -> 17.977814 | R37: =H37/G22*100 -> 14.876365 | S37: =I37/H22*100 -> 12.384684 | U37: Mining (XP_mi) | X37: 1.015 | Y37: 1.008 | Z37: 1.001 | AA37: 1.002 | AB37: 0.8 | AC37: 0.805 | AD37: 0.8 | AW37: Mining (xs_mi) | AX37: 12927.48 | AY37: 16091.15 | AZ37: 17127 | BA37: 18168.2 | BB37: 18856.14 | BC37: 19578.12 | BD37: 20410.35 | BE37: 21464.13 | BF37: 22456.32 | BH37: =AY37/AX23*100 -> 127.05572 | BI37: =AZ37/AY23*100 -> 106.4669 | BJ37: =BA37/AZ23*100 -> 105.15569 | BK37: =BB37/BA23*100 -> 101.3959 | BL37: =BC37/BB23*100 -> 99.656716 | BM37: =BD37/BC23*100 -> 98.732225 | BN37: =BE37/BD23*100 -> 98.37673 | BO37: =BF37/BE23*100 -> 96.577101
B38: Manufacturing (xs_m) | C38: 57380.35 | D38: 59720.98 | E38: 64755.53 | F38: 70121.75 | G38: 76784.7 | H38: 85483.19 | I38: 88254.93 | J38: 90698.45 | K38: 92503.6 | M38: Manufacturing (xs_m) | N38: =D38/C23*100 -> 441.03322 | O38: =E38/D23*100 -> 430.37258 | P38: =F38/E23*100 -> 262.09298 | Q38: =G38/F23*100 -> 257.76243 | R38: =H38/G23*100 -> 209.80424 | S38: =I38/H23*100 -> 183.6833 | X38: ='GDP-total'!D69/'GDP-total'!C69*100/X37 -> 175.18586 | Y38: ='GDP-total'!E69/'GDP-total'!D69*100/Y37 -> 110.458 | Z38: ='GDP-total'!F69/'GDP-total'!E69*100/Z37 -> 136.63983 | AA38: ='GDP-total'!G69/'GDP-total'!F69*100/AA37 -> 117.6888 | AB38: ='GDP-total'!H69/'GDP-total'!G69*100/AB37 -> 127.73264 | AC38: ='GDP-total'!I69/'GDP-total'!H69*100/AC37 -> 128.96014 | AD38: ='GDP-total'!J69/'GDP-total'!I69*100/AD37 -> 124.20765 | AW38: Manufacturing (xs_m) | AX38: 57380.35 | AY38: 59720.98 | AZ38: 64755.53 | BA38: 70121.75 | BB38: 76784.7 | BC38: 85483.19 | BD38: 88254.93 | BE38: 90698.45 | BF38: 92503.6 | BH38: =AY38/AX24*100 -> 104.74362 | BI38: =AZ38/AY24*100 -> 105.92118 | BJ38: =BA38/AZ24*100 -> 105.00846 | BK38: =BB38/BA24*100 -> 104.86675 | BL38: =BC38/BB24*100 -> 105.06883 | BM38: =BD38/BC24*100 -> 99.35132 | BN38: =BE38/BD24*100 -> 97.907243 | BO38: =BF38/BE24*100 -> 96.185544
B39: Energy and Water (xs_e) | C39: 10084.89 | D39: 11623.21 | E39: 12463.62 | F39: 16611.4 | G39: 16819.33 | H39: 17061.36 | I39: 17536.83 | J39: 20499.16 | K39: 23317.26 | M39: Energy and Water (xs_e) | N39: =D39/C24*100 -> 19.81136 | O39: =E39/D24*100 -> 19.118586 | P39: =F39/E24*100 -> 27.655474 | Q39: =G39/F24*100 -> 27.874368 | R39: =H39/G24*100 -> 23.360524 | S39: =I39/H24*100 -> 18.425463 | U39: Manufacturing (XP_m) | X39: 0.983 | Y39: 1.0026163 | Z39: 1.001 | AA39: 1.001 | AB39: 0.845 | AC39: 0.85 | AD39: 0.824 | AW39: Energy and Water (xs_e) | AX39: 10084.89 | AY39: 11623.21 | AZ39: 12463.62 | BA39: 16611.4 | BB39: 16819.33 | BC39: 17061.36 | BD39: 17536.83 | BE39: 20499.16 | BF39: 23317.26 | BH39: =AY39/AX25*100 -> 116.25585 | BI39: =AZ39/AY25*100 -> 106.69464 | BJ39: =BA39/AZ25*100 -> 130.8248 | BK39: =BB39/BA25*100 -> 97.665345 | BL39: =BC39/BB25*100 -> 96.401287 | BM39: =BD39/BC25*100 -> 96.516947 | BN39: =BE39/BD25*100 -> 108.24245 | BO39: =BF39/BE25*100 -> 108.21621
B40: Construction (xs_c) | C40: 31675.93 | D40: 35391.24 | E40: 39247.36 | F40: 41540.57 | G40: 45470.84 | H40: 47525.62 | I40: 49468.7 | J40: 51754.4 | K40: 53667.44 | M40: Construction (xs_c) | N40: =D40/C25*100 -> 342.01233 | O40: =E40/D25*100 -> 341.33419 | P40: =F40/E25*100 -> 316.73654 | Q40: =G40/F25*100 -> 308.13281 | R40: =H40/G25*100 -> 266.60444 | S40: =I40/H25*100 -> 229.24805 | X40: ='GDP-total'!D70/'GDP-total'!C70*100/X39 -> 110.43818 | Y40: ='GDP-total'!E70/'GDP-total'!D70*100/Y39 -> 137.96537 | Z40: ='GDP-total'!F70/'GDP-total'!E70*100/Z39 -> 120.91866 | AA40: ='GDP-total'!G70/'GDP-total'!F70*100/AA39 -> 130.18698 | AB40: ='GDP-total'!H70/'GDP-total'!G70*100/AB39 -> 119.92136 | AC40: ='GDP-total'!I70/'GDP-total'!H70*100/AC39 -> 118.7355 | AD40: ='GDP-total'!J70/'GDP-total'!I70*100/AD39 -> 122.16979 | AW40: Construction (xs_c) | AX40: 31675.93 | AY40: 35391.24 | AZ40: 39247.36 | BA40: 41540.57 | BB40: 45470.84 | BC40: 47525.62 | BD40: 49468.7 | BE40: 51754.4 | BF40: 53667.44 | BH40: =AY40/AX26*100 -> 111.72913 | BI40: =AZ40/AY26*100 -> 104.61856 | BJ40: =BA40/AZ26*100 -> 99.851859 | BK40: =BB40/BA26*100 -> 102.30026 | BL40: =BC40/BB26*100 -> 100.01808 | BM40: =BD40/BC26*100 -> 101.94759 | BN40: =BE40/BD26*100 -> 101.0826 | BO40: =BF40/BE26*100 -> 99.230983
B41: Transport (xs_t) | C41: 18541.68 | D41: 20394.23 | E41: 22857.68 | F41: 28504.31 | G41: 29595.96 | H41: 30868.91 | I41: 35625.48 | J41: 39584.12 | K41: 43781.2 | M41: Transport (xs_t) | N41: =D41/C26*100 -> 59.703487 | O41: =E41/D26*100 -> 60.22099 | P41: =F41/E26*100 -> 66.33399 | Q41: =G41/F26*100 -> 62.876581 | R41: =H41/G26*100 -> 62.307687 | S41: =I41/H26*100 -> 67.013741 | U41: Energy | X41: 1.035 | Y41: 1.009 | Z41: 1.015 | AA41: 1 | AB41: 1 | AC41: 1 | AD41: 1 | AW41: Transport (xs_t) | AX41: 18541.68 | AY41: 20394.23 | AZ41: 22857.68 | BA41: 28504.31 | BB41: 29595.96 | BC41: 30868.91 | BD41: 35625.48 | BE41: 39584.12 | BF41: 43781.2 | BH41: =AY41/AX27*100 -> 111.06662 | BI41: =AZ41/AY27*100 -> 110.9202 | BJ41: =BA41/AZ27*100 -> 120.73565 | BK41: =BB41/BA27*100 -> 96.851345 | BL41: =BC41/BB27*100 -> 95.315217 | BM41: =BD41/BC27*100 -> 102.23584 | BN41: =BE41/BD27*100 -> 103.97441 | BO41: =BF41/BE27*100 -> 102.02514
B42: Trade (xs_tr) | C42: 33474.18 | D42: 34917.49 | E42: 35383.85 | F42: 38854.74 | G42: 41317.48 | H42: 42670.51 | I42: 44320.48 | J42: 48504.11 | K42: 49636.16 | M42: Trade (xs_tr) | N42: =D42/C27*100 -> 183.22057 | O42: =E42/D27*100 -> 167.09354 | P42: =F42/E27*100 -> 167.19095 | Q42: =G42/F27*100 -> 167.37646 | R42: =H42/G27*100 -> 178.37196 | S42: =I42/H27*100 -> 178.97722 | X42: ='GDP-total'!D71/'GDP-total'!C71*100/X41 -> 110.2055 | Y42: ='GDP-total'!E71/'GDP-total'!D71*100/Y41 -> 111.76342 | Z42: ='GDP-total'!F71/'GDP-total'!E71*100/Z41 -> 119.50412 | AA42: ='GDP-total'!G71/'GDP-total'!F71*100/AA41 -> 121.19792 | AB42: ='GDP-total'!H71/'GDP-total'!G71*100/AB41 -> 103.45516 | AC42: ='GDP-total'!I71/'GDP-total'!H71*100/AC41 -> 105.59457 | AD42: ='GDP-total'!J71/'GDP-total'!I71*100/AD41 -> 102.35283 | AW42: Trade (xs_tr) | AX42: 33474.18 | AY42: 34917.49 | AZ42: 35383.85 | BA42: 38854.74 | BB42: 41317.48 | BC42: 42670.51 | BD42: 44320.48 | BE42: 48504.11 | BF42: 49636.16 | BH42: =AY42/AX28*100 -> 104.33097 | BI42: =AZ42/AY28*100 -> 100.35025 | BJ42: =BA42/AZ28*100 -> 107.66193 | BK42: =BB42/BA28*100 -> 101.76702 | BL42: =BC42/BB28*100 -> 97.892817 | BM42: =BD42/BC28*100 -> 99.006196 | BN42: =BE42/BD28*100 -> 103.33514 | BO42: =BF42/BE28*100 -> 95.7073
B43: Financial services (xs_fs) | C43: 14802.46 | D43: 15566.31 | E43: 15817.07 | F43: 16357.98 | G43: 16849.97 | H43: 17272.59 | I43: 18141.53 | J43: 18459.55 | K43: 19071.89 | M43: Financial services (xs_fs) | N43: =D43/C28*100 -> 45.926064 | O43: =E43/D28*100 -> 41.997452 | P43: =F43/E28*100 -> 43.882335 | Q43: =G43/F28*100 -> 39.850406 | R43: =H43/G28*100 -> 36.591971 | S43: =I43/H28*100 -> 37.220036 | U43: Water (XP_e) | X43: 1 | Y43: 1 | Z43: 1 | AA43: 1 | AB43: 1 | AC43: 1 | AD43: 1 | AW43: Financial services (xs_fs) | AX43: 14802.46 | AY43: 15566.31 | AZ43: 15817.07 | BA43: 16357.98 | BB43: 16849.97 | BC43: 17272.59 | BD43: 18141.53 | BE43: 18459.55 | BF43: 19071.89 | BH43: =AY43/AX29*100 -> 105.26155 | BI43: =AZ43/AY29*100 -> 95.017448 | BJ43: =BA43/AZ29*100 -> 97.102244 | BK43: =BB43/BA29*100 -> 94.526857 | BL43: =BC43/BB29*100 -> 92.390062 | BM43: =BD43/BC29*100 -> 92.97346 | BN43: =BE43/BD29*100 -> 88.522954 | BO43: =BF43/BE29*100 -> 86.269648
B44: Public Services | C44: 19875.96 | D44: 19966.73 | E44: 21189.39 | F44: 23911.8 | G44: 24905.37 | H44: 28187.01 | I44: 31186.05 | J44: 33758.64 | K44: 36729.25 | M44: Public Services | N44: =D44/C29*100 -> 133.05194 | O44: =E44/D29*100 -> 127.07382 | P44: =F44/E29*100 -> 137.4212 | Q44: =G44/F29*100 -> 122.04708 | R44: =H44/G29*100 -> 148.0774 | S44: =I44/H29*100 -> 137.98271 | X44: ='GDP-total'!D72/'GDP-total'!C72*100/X43 -> 114.06269 | Y44: ='GDP-total'!E72/'GDP-total'!D72*100/Y43 -> 104.4291 | Z44: ='GDP-total'!F72/'GDP-total'!E72*100/Z43 -> 103.54249 | AA44: ='GDP-total'!G72/'GDP-total'!F72*100/AA43 -> 115.03023 | AB44: ='GDP-total'!H72/'GDP-total'!G72*100/AB43 -> 103.45516 | AC44: ='GDP-total'!I72/'GDP-total'!H72*100/AC43 -> 105.59457 | AD44: ='GDP-total'!J72/'GDP-total'!I72*100/AD43 -> 102.35283 | AW44: Public Services | AX44: 19875.96 | AY44: 19966.73 | AZ44: 21189.39 | BA44: 23911.8 | BB44: 24905.37 | BC44: 28187.01 | BD44: 31186.05 | BE44: 33758.64 | BF44: 36729.25 | BH44: =AY44/AX30*100 -> 100.48241 | BI44: =AZ44/AY30*100 -> 105.09187 | BJ44: =BA44/AZ30*100 -> 108.53105 | BK44: =BB44/BA30*100 -> 101.13051 | BL44: =BC44/BB30*100 -> 108.82015 | BM44: =BD44/BC30*100 -> 105.35867 | BN44: =BE44/BD30*100 -> 102.10312 | BO44: =BF44/BE30*100 -> 101.64565
B45: Market Services | C45: 3865.793 | D45: 4145.689 | E45: 5183.378 | F45: 5582.13 | G45: 6501.067 | H45: 6815.188 | I45: 6901.598 | J45: 7847.808 | K45: 8247.754 | M45: Market Services | N45: =D45/C30*100 -> 20.596625 | O45: =E45/D30*100 -> 23.175845 | P45: =F45/E30*100 -> 24.529211 | Q45: =G45/F30*100 -> 26.25621 | R45: =H45/G30*100 -> 24.899169 | S45: =I45/H30*100 -> 25.141792 | AW45: Market Services | AX45: 3865.793 | AY45: 4145.689 | AZ45: 5183.378 | BA45: 5582.13 | BB45: 6501.067 | BC45: 6815.188 | BD45: 6901.598 | BE45: 7847.808 | BF45: 8247.754 | BH45: =AY45/AX31*100 -> 107.27901 | BI45: =AZ45/AY31*100 -> 123.83021 | BJ45: =BA45/AZ31*100 -> 107.53771 | BK45: =BB45/BA31*100 -> 113.08418 | BL45: =BC45/BB31*100 -> 101.77414 | BM45: =BD45/BC31*100 -> 97.356714 | BN45: =BE45/BD31*100 -> 109.83658 | BO45: =BF45/BE31*100 -> 100.52412
C46: =SUM(C36:C45) -> 280754.87 | D46: =SUM(D36:D45) -> 301676.14 | E46: =SUM(E36:E45) -> 322102.33 | F46: =SUM(F36:F45) -> 351111.84 | G46: =SUM(G36:G45) -> 371205.28 | H46: =SUM(H36:H45) -> 392728.62 | I46: =SUM(I36:I45) -> 410622.57 | J46: =SUM(J36:J45) -> 433633.67 | K46: =SUM(K36:K45) -> 454855.47 | M46: Industry | N46: =D34/C22*100 -> 105.90711 | O46: =E34/D22*100 -> 102.84559 | P46: =F34/E22*100 -> 104.96935 | Q46: =G34/F22*100 -> 107.22173 | R46: =H34/G22*100 -> 92.79448 | S46: =I34/H22*100 -> 76.577481 | AX46: =SUM(AX36:AX45) -> 280754.87 | AY46: =SUM(AY36:AY45) -> 301676.14 | AZ46: =SUM(AZ36:AZ45) -> 322102.33 | BA46: =SUM(BA36:BA45) -> 351111.84 | BB46: =SUM(BB36:BB45) -> 371205.28 | BC46: =SUM(BC36:BC45) -> 392728.62 | BD46: =SUM(BD36:BD45) -> 410622.57 | BE46: =SUM(BE36:BE45) -> 433633.67 | BF46: =SUM(BF36:BF45) -> 454855.47 | BH46: =AY46/AX32*100 -> 107.85793 | BI46: =AZ46/AY32*100 -> 103.79806 | BJ46: =BA46/AZ32*100 -> 105.39556 | BK46: =BB46/BA32*100 -> 100.7779 | BL46: =BC46/BB32*100 -> 100.45772 | BM46: =BD46/BC32*100 -> 99.006144 | BN46: =BE46/BD32*100 -> 99.816537 | BO46: =BF46/BE32*100 -> 97.923125
B47: Value Added (in real terms) | C47: ='2_Production_1'!C156 -> 134042.9 | D47: ='2_Production_1'!D156 -> 144285.67 | E47: ='2_Production_1'!E156 -> 154720.2 | F47: ='2_Production_1'!F156 -> 168166.02 | G47: ='2_Production_1'!G156 -> 178343.86 | H47: ='2_Production_1'!H156 -> 188814.32 | I47: ='2_Production_1'!I156 -> 196716.15 | J47: ='2_Production_1'!J156 -> 207050.63 | K47: ='2_Production_1'!K156 -> 216594.56 | N47: =D46/C32*100 -> 104.7398 | O47: =E46/D32*100 -> 101.74598 | P47: =F46/E32*100 -> 102.03854 | Q47: =G46/F32*100 -> 98.918809 | R47: =H46/G32*100 -> 93.619011 | S47: =I46/H32*100 -> 86.559009 | AY47: =AY46-AX46 -> 20921.266 | AZ47: =AZ46-AY46 -> 20426.189 | BA47: =BA46-AZ46 -> 29009.512 | BB47: =BB46-BA46 -> 20093.437 | BC47: =BC46-BB46 -> 21523.341 | BD47: =BD46-BC46 -> 17893.95 | BE47: =BE46-BD46 -> 23011.1 | BF47: =BF46-BE46 -> 21221.806
B48: Source: va_grp | D48: =D62/C18*100 -> 109.84938 | E48: =E62/D18*100 -> 106.19496 | F48: =F62/E18*100 -> 100.91457 | G48: =G62/F18*100 -> 94.095783 | H48: =H62/G18*100 -> 87.516675 | I48: =I62/H18*100 -> 79.44992 | J48: =J62/I18*100 -> 74.531486 | K48: =K62/J18*100 -> 68.881119
C49: 2024 | D49: =C49+1 -> 2025 | E49: =D49+1 -> 2026 | F49: =E49+1 -> 2027 | G49: =F49+1 -> 2028 | H49: =G49+1 -> 2029 | I49: =H49+1 -> 2030 | J49: =I49+1 -> 2031 | K49: =J49+1 -> 2032 | N49: 2023 | O49: 2024 | P49: 2025 | Q49: 2026 | R49: 2027 | S49: 2028 | T49: 2029 | U49: 2030
B50: Agriculture (va_a) | C50: 35764.63 | D50: 37198.76 | E50: 38722.26 | F50: 39698.61 | G50: 42643.57 | H50: 47509.86 | I50: 49333.46 | J50: 53956.4 | K50: 55435.45 | M50: Agriculture (va_a) | N50: =D50/GDP!C7*100 -> 94.137041 | O50: =E50/GDP!D7*100 -> 87.660332 | P50: =F50/GDP!E7*100 -> 87.128651 | Q50: =G50/GDP!F7*100 -> 89.673426 | R50: =H50/GDP!G7*100 -> 99.063864 | S50: =I50/GDP!H7*100 -> 96.671466 | T50: =J50/GDP!I7*100 -> 105.14964 | U50: =K50/GDP!J7*100 -> 103.30227
B51: Mining (va_mi) | C51: 6297.357 | D51: 6551.141 | E51: 6869.049 | F51: 7166.033 | G51: 10614.05 | H51: 11428.92 | I51: 12523.64 | J51: 13479.83 | K51: 13979.64 | M51: Mining (va_mi) | N51: =D51/GDP!C8*100 -> 86.070526 | O51: =E51/GDP!D8*100 -> 72.176689 | P51: =F51/GDP!E8*100 -> 70.346745 | Q51: =G51/GDP!F8*100 -> 97.086149 | R51: =H51/GDP!G8*100 -> 98.888674 | S51: =I51/GDP!H8*100 -> 101.79984 | T51: =J51/GDP!I8*100 -> 103.06453 | U51: =K51/GDP!J8*100 -> 100.12914
B52: Manufacturing (va_m) | C52: 18999.43 | D52: 20377.21 | E52: 20766.31 | F52: 24176.2 | G52: 25274.54 | H52: 26369.82 | I52: 26895.6 | J52: 28112.41 | K52: 28896.13 | M52: Manufacturing (va_m) | N52: =D52/GDP!C9*100 -> 77.487811 | O52: =E52/GDP!D9*100 -> 74.456518 | P52: =F52/GDP!E9*100 -> 80.033263 | Q52: =G52/GDP!F9*100 -> 77.000933 | R52: =H52/GDP!G9*100 -> 72.297285 | S52: =I52/GDP!H9*100 -> 70.287785 | T52: =J52/GDP!I9*100 -> 69.44719 | U52: =K52/GDP!J9*100 -> 69.441152
B53: Energy and Water (va_e) | C53: 4935.905 | D53: 5526.138 | E53: 7290.392 | F53: 10097.46 | G53: 13952.93 | H53: 15187.98 | I53: 16244.29 | J53: 18521.52 | K53: 20360.2 | M53: Energy and Water (va_e) | N53: =D53/GDP!C10*100 -> 86.345704 | O53: =E53/GDP!D10*100 -> 99.021035 | P53: =F53/GDP!E10*100 -> 125.88688 | Q53: =G53/GDP!F10*100 -> 128.3277 | R53: =H53/GDP!G10*100 -> 135.68389 | S53: =I53/GDP!H10*100 -> 140.74386 | T53: =J53/GDP!I10*100 -> 153.06523 | U53: =K53/GDP!J10*100 -> 151.96186
B54: Construction (va_c) | C54: 17239.47 | D54: 18199.37 | E54: 18580.7 | F54: 19011.36 | G54: 19589.96 | H54: 19784.71 | I54: 20534.69 | J54: 20817.97 | K54: 21286.66 | M54: Construction (va_c) | N54: =D54/GDP!C11*100 -> 96.700075 | O54: =E54/GDP!D11*100 -> 82.208066 | P54: =F54/GDP!E11*100 -> 76.653857 | Q54: =G54/GDP!F11*100 -> 74.678119 | R54: =H54/GDP!G11*100 -> 72.437926 | S54: =I54/GDP!H11*100 -> 74.881022 | T54: =J54/GDP!I11*100 -> 71.311782 | U54: =K54/GDP!J11*100 -> 69.474295
B55: Transport (va_t) | C55: 8324.458 | D55: 8552.57 | E55: 9348.06 | F55: 9987.864 | G55: 10652.15 | H55: 11652.76 | I55: 12210.75 | J55: 12591.75 | K55: 13469.96 | M55: Transport (va_t) | N55: =D55/GDP!C12*100 -> 88.376761 | O55: =E55/GDP!D12*100 -> 87.612655 | P55: =F55/GDP!E12*100 -> 81.185711 | Q55: =G55/GDP!F12*100 -> 65.767328 | R55: =H55/GDP!G12*100 -> 67.69909 | S55: =I55/GDP!H12*100 -> 64.464604 | T55: =J55/GDP!I12*100 -> 64.032707 | U55: =K55/GDP!J12*100 -> 60.378823
B56: Trade (va_tr) | C56: 19936.82 | D56: 20925.47 | E56: 22628.18 | F56: 23747.71 | G56: 28171.13 | H56: 29860.61 | I56: 32080.82 | J56: 33636.95 | K56: 35765.16 | M56: Trade (va_tr) | N56: =D56/GDP!C13*100 -> 95.274969 | O56: =E56/GDP!D13*100 -> 99.372581 | P56: =F56/GDP!E13*100 -> 102.27811 | Q56: =G56/GDP!F13*100 -> 107.53481 | R56: =H56/GDP!G13*100 -> 106.53698 | S56: =I56/GDP!H13*100 -> 112.364 | T56: =J56/GDP!I13*100 -> 111.72305 | U56: =K56/GDP!J13*100 -> 108.24525
B57: Financial services (va_fs) | C57: 6904.117 | D57: 7521.144 | E57: 7809.649 | F57: 8439.147 | G57: 8924.058 | H57: 9557.043 | I57: 12432.1 | J57: 13798.77 | K57: 14754.18 | M57: Financial services (va_fs) | N57: =D57/GDP!C14*100 -> 67.391106 | O57: =E57/GDP!D14*100 -> 61.172074 | P57: =F57/GDP!E14*100 -> 66.763079 | Q57: =G57/GDP!F14*100 -> 66.248014 | R57: =H57/GDP!G14*100 -> 67.17695 | S57: =I57/GDP!H14*100 -> 83.010384 | T57: =J57/GDP!I14*100 -> 85.66876 | U57: =K57/GDP!J14*100 -> 85.447121
B58: Public Services (va_ps) | C58: 15652.7 | D58: 17240.79 | E58: 18754.97 | F58: 20866.66 | G58: 21746.25 | H58: 24359.04 | I58: 26856.2 | J58: 28706.85 | K58: 31394.18 | M58: Public Services (va_ps) | N58: =D58/GDP!C15*100 -> 101.2898 | O58: =E58/GDP!D15*100 -> 109.33541 | P58: =F58/GDP!E15*100 -> 111.00456 | Q58: =G58/GDP!F15*100 -> 104.19651 | R58: =H58/GDP!G15*100 -> 111.16164 | S58: =I58/GDP!H15*100 -> 107.129 | T58: =J58/GDP!I15*100 -> 102.40399 | U58: =K58/GDP!J15*100 -> 102.75043
B59: Market Services (va_ms) | C59: 1223.318 | D59: 1299.781 | E59: 1423.178 | F59: 1706.571 | G59: 1836.584 | H59: 2172.833 | I59: 2171.223 | J59: 2342.437 | K59: 2565.305 | M59: Market Services (va_ms) | N59: =D59/GDP!C16*100 -> 185.01736 | O59: =E59/GDP!D16*100 -> 213.1908 | P59: =F59/GDP!E16*100 -> 241.38224 | Q59: =G59/GDP!F16*100 -> 221.74887 | R59: =H59/GDP!G16*100 -> 253.87973 | S59: =I59/GDP!H16*100 -> 232.29519 | T59: =J59/GDP!I16*100 -> 262.19151 | U59: =K59/GDP!J16*100 -> 262.06569
C60: =SUM(C50:C59) -> 135278.21 | D60: =SUM(D50:D59) -> 143392.37 | E60: =SUM(E50:E59) -> 152192.75 | F60: =SUM(F50:F59) -> 164897.62 | G60: =SUM(G50:G59) -> 183405.22 | H60: =SUM(H50:H59) -> 197883.58 | I60: =SUM(I50:I59) -> 211282.77 | J60: =SUM(J50:J59) -> 225964.89 | K60: =SUM(K50:K59) -> 237906.86 | M60: Industry | N60: =D61/GDP!C20*100 -> 80.514871 | O60: =E61/GDP!D20*100 -> 78.011542 | P60: =F61/GDP!E20*100 -> 85.591829 | Q60: =G61/GDP!F20*100 -> 91.236076 | R60: =H61/GDP!G20*100 -> 89.466571 | S60: =I61/GDP!H20*100 -> 89.622426 | T60: =J61/GDP!I20*100 -> 91.55351 | U60: =K61/GDP!J20*100 -> 91.683219
B61: Labor demand | D61: =D51+D52+D53 -> 32454.489 | E61: =E51+E52+E53 -> 34925.751 | F61: =F51+F52+F53 -> 41439.693 | G61: =G51+G52+G53 -> 49841.52 | H61: =H51+H52+H53 -> 52986.72 | I61: =I51+I52+I53 -> 55663.53 | J61: =J51+J52+J53 -> 60113.76 | K61: =K51+K52+K53 -> 63235.97 | N61: =D60/GDP!C18*100 -> 90.087843 | O61: =E60/GDP!D18*100 -> 86.683083 | P61: =F60/GDP!E18*100 -> 88.442101 | Q61: =G60/GDP!F18*100 -> 89.040618 | R61: =H60/GDP!G18*100 -> 91.302806 | S61: =I60/GDP!H18*100 -> 92.24833 | T61: =J60/GDP!I18*100 -> 93.772268 | U61: =K60/GDP!J18*100 -> 92.417981
B62: Source: ld_grp | C62: =C46-C47 -> 146711.97 | D62: =D46-D47 -> 157390.47 | E62: =E46-E47 -> 167382.12 | F62: =F46-F47 -> 182945.82 | G62: =G46-G47 -> 192861.41 | H62: =H46-H47 -> 203914.3 | I62: =I46-I47 -> 213906.42 | J62: =J46-J47 -> 226583.03 | K62: =K46-K47 -> 238260.92
C63: 2022 | D63: =C63+1 -> 2023 | E63: =D63+1 -> 2024 | F63: =E63+1 -> 2025 | G63: =F63+1 -> 2026 | H63: =G63+1 -> 2027 | I63: =H63+1 -> 2028 | J63: =I63+1 -> 2029 | K63: =J63+1 -> 2030
B64: Agriculture (ld_a) | C64: 550.6608 | D64: 615.6207 | E64: 634.7485 | F64: 661.9926 | G64: 666.7493 | H64: 710.0737 | I64: 713.6502 | J64: 746.5018 | K64: 798.028
B65: Mining (ld_mi) | C65: 721.1644 | D65: 900.0107 | E65: 962.2185 | F65: 1031.655 | G65: 1090.126 | H65: 1164.124 | I65: 1239.61 | J65: 1317.248 | K65: 1371.088
B66: Manufacturing (ld_m) | C66: 2326.538 | D66: 2464.22 | E66: 2671.299 | F66: 2903.366 | G66: 3238.838 | H66: 3363.436 | I66: 3569.997 | J66: 3654.872 | K66: 3747.139
B67: Energy and Water (ld_e) | C67: 942.9877 | D67: 1080.222 | E67: 1178.191 | F67: 1597.638 | G67: 1646.952 | H67: 1700.982 | I67: 1786.702 | J67: 1965.6 | K67: 2299.357
B68: Construction (ld_c) | C68: 1983.085 | D68: 2386.468 | E68: 2615.454 | F68: 2771.833 | G68: 2866.116 | H68: 2870.582 | I68: 3059.453 | J68: 3207.919 | K68: 3359.618
B69: Transport (ld_t) | C69: 1721.596 | D69: 1895.435 | E69: 2187.063 | F69: 2887.324 | G69: 3073.729 | H69: 3395.375 | I69: 3495.159 | J69: 3923.348 | K69: 4433.63
B70: Trade (ld_tr) | C70: 1408.874 | D70: 1458.488 | E70: 1486.626 | F70: 1677.78 | G70: 1794.462 | H70: 1826.48 | I70: 1927.098 | J70: 2113.467 | K70: 2186.187
B71: Financial services (ld_fs) | C71: 3640.948 | D71: 4161.544 | E71: 4160.79 | F71: 4421.928 | G71: 4693.834 | H71: 4969.5 | I71: 5343.796 | J71: 5752.661 | K71: 5914.484
B72: Public Services (ld_ps) | C72: 10192.73 | D72: 10268.28 | E72: 11255.42 | F72: 12496.1 | G72: 13125.51 | H72: 15021.2 | I72: 16801.26 | J72: 18313.81 | K72: 20347.53
B73: Market Services (ld_ms) | C73: 192.0916 | D73: 171.189 | E73: 166.1208 | F73: 203.0992 | G73: 195.2363 | H73: 218.9293 | I73: 203.4636 | J73: 217.4482 | K73: 241.8202
C74: =SUM(C64:C73) -> 23680.675 | D74: =SUM(D64:D73) -> 25401.477 | E74: =SUM(E64:E73) -> 27317.931 | F74: =SUM(F64:F73) -> 30652.716 | G74: =SUM(G64:G73) -> 32391.553 | H74: =SUM(H64:H73) -> 35240.682 | I74: =SUM(I64:I73) -> 38140.189 | J74: =SUM(J64:J73) -> 41212.875 | K74: =SUM(K64:K73) -> 44698.881
B75: Return to Capital
B76: Source: r_grp
C77: 2022 | D77: =C77+1 -> 2023 | E77: =D77+1 -> 2024 | F77: =E77+1 -> 2025 | G77: =F77+1 -> 2026 | H77: =G77+1 -> 2027 | I77: =H77+1 -> 2028 | J77: =I77+1 -> 2029 | K77: =J77+1 -> 2030
B78: Agriculture (r_a) | C78: 1.006719 | D78: 1.083302 | E78: 1.072856 | F78: 1.091676 | G78: 1.022564 | H78: 0.9767804 | I78: 0.9449327 | J78: 0.9031176 | K78: 0.9402747
B79: Mining (r_mi) | C79: 0.9515751 | D79: 1.170148 | E79: 1.196285 | F79: 1.234035 | G79: 0.8408871 | H79: 0.8330031 | I79: 0.8063373 | J79: 0.7946728 | K79: 0.7979769
B80: Manufacturing (r_m) | C80: 1.010599 | D80: 0.9963079 | E80: 1.068874 | F80: 0.9884517 | G80: 1.064242 | H80: 1.058596 | I80: 1.107722 | J80: 1.081867 | K80: 1.078714
B81: Energy and Water (r_e) | C81: 0.9855618 | D81: 1.01396 | E81: 0.8009312 | F81: 0.7801758 | G81: 0.5425627 | H81: 0.5083549 | I81: 0.4970934 | J81: 0.4755358 | K81: 0.5136417
B82: Construction (r_c) | C82: 0.9584125 | D82: 1.112111 | E82: 1.205338 | F82: 1.254435 | G82: 1.259386 | H82: 1.247522 | I82: 1.285656 | J82: 1.335789 | K82: 1.372605
B83: Transport (r_t) | C83: 0.9860229 | D83: 1.076134 | E83: 1.152433 | F83: 1.505896 | G83: 1.502416 | H83: 1.521036 | I83: 1.487168 | J83: 1.655576 | K83: 1.774478
B84: Trade (r_tr) | C84: 1.009386 | D84: 0.9945287 | E84: 0.9332707 | F84: 1.009128 | G84: 0.9027636 | H84: 0.8642384 | I84: 0.8475859 | J84: 0.889559 | K84: 0.8636201
B85: Financial services (r_fs) | C85: 1.334169 | D85: 1.455956 | E85: 1.359191 | F85: 1.318657 | G85: 1.327811 | H85: 1.300433 | I85: 0.9199093 | J85: 0.8701687 | K85: 0.810297
B86: Public Services (r_ps) | C86: 1.003617 | D86: 0.7775157 | E86: 0.7946241 | F86: 0.7898033 | G86: 0.8077437 | H86: 0.858832 | I86: 0.8949349 | J86: 0.9464333 | K86: 0.9902329
B87: Market Services (r_ms) | C87: 0.494533 | D87: 0.4989086 | E87: 0.4924613 | F87: 0.5169995 | G87: 0.4796547 | H87: 0.4582892 | I87: 0.4474788 | J87: 0.4597873 | K87: 0.4759768

Sheet 3_In & SA
B1: Доход и сбережения
B2: Block 3 : Income and Savings | M2: GDP by expenditure method
B3: Доход от рабочей силы
B4: Labor Income
B5: Source: ld_hh_1
C6: 2024 | D6: =C6+1 -> 2025 | E6: =D6+1 -> 2026 | F6: =E6+1 -> 2027 | G6: =F6+1 -> 2028 | H6: =G6+1 -> 2029 | I6: =H6+1 -> 2030 | J6: =I6+1 -> 2031 | K6: =J6+1 -> 2032 | N6: 2022 | O6: =N6+1 -> 2023 | P6: =O6+1 -> 2024 | Q6: =P6+1 -> 2025 | R6: =Q6+1 -> 2026 | S6: =R6+1 -> 2027 | T6: =S6+1 -> 2028 | U6: =T6+1 -> 2029 | V6: =U6+1 -> 2030
B7: Labor Income (ld_hh) | C7: 23680.68 | D7: 25401.47 | E7: 27317.93 | F7: 30652.71 | G7: 32391.55 | H7: 35240.68 | I7: 38140.19 | J7: 41212.87 | K7: 44698.88 | M7: Households Income (yh) | N7: =C12 -> 178198.9 | O7: =D12 -> 181254.7 | P7: =E12 -> 184455.1 | Q7: =F12 -> 190405.9 | R7: =G12 -> 188270.8 | S7: =H12 -> 197807.9 | T7: =I12 -> 210908.4 | U7: =J12 -> 217576.1 | V7: =K12 -> 225813.1
B8: Доход домохозяйств | M8: Investment demand by commodity inv_grp | N8: ='4_Demand'!C45 -> 75206.33 | O8: ='4_Demand'!D45 -> 77968.46 | P8: ='4_Demand'!E45 -> 82697.53 | Q8: ='4_Demand'!F45 -> 88077.81 | R8: ='4_Demand'!G45 -> 105031.3 | S8: ='4_Demand'!H45 -> 105712.3 | T8: ='4_Demand'!I45 -> 105665.1 | U8: ='4_Demand'!J45 -> 114942.5 | V8: ='4_Demand'!K45 -> 120227.9
B9: Households Income | M9: net exports of goods and services | N9: =N10-N11 -> -52160.384 | O9: =O10-O11 -> -52505.96 | P9: =P10-P11 -> -53379.375 | Q9: =Q10-Q11 -> -54582.933 | R9: =R10-R11 -> -56534.525 | S9: =S10-S11 -> -57766.388 | T9: =T10-T11 -> -58487.934 | U9: =U10-U11 -> -60478.718 | V9: =V10-V11 -> -61602.985
B10: Source: yh_1 | M10: Export by commodity ex_grp | N10: ='5_IntTrade'!C31 -> 15708.052 | O10: ='5_IntTrade'!D31 -> 17506.424 | P10: ='5_IntTrade'!E31 -> 19566.13 | Q10: ='5_IntTrade'!F31 -> 22519.254 | R10: ='5_IntTrade'!G31 -> 24521.239 | S10: ='5_IntTrade'!H31 -> 26472.617 | T10: ='5_IntTrade'!I31 -> 28444.479 | U10: ='5_IntTrade'!J31 -> 31427.918 | V10: ='5_IntTrade'!K31 -> 33548.778
C11: 2024 | D11: =C11+1 -> 2025 | E11: =D11+1 -> 2026 | F11: =E11+1 -> 2027 | G11: =F11+1 -> 2028 | H11: =G11+1 -> 2029 | I11: =H11+1 -> 2030 | J11: =I11+1 -> 2031 | K11: =J11+1 -> 2032 | M11: Import by commodity im_grp | N11: ='5_IntTrade'!C60 -> 67868.436 | O11: ='5_IntTrade'!D60 -> 70012.383 | P11: ='5_IntTrade'!E60 -> 72945.504 | Q11: ='5_IntTrade'!F60 -> 77102.187 | R11: ='5_IntTrade'!G60 -> 81055.764 | S11: ='5_IntTrade'!H60 -> 84239.005 | T11: ='5_IntTrade'!I60 -> 86932.413 | U11: ='5_IntTrade'!J60 -> 91906.636 | V11: ='5_IntTrade'!K60 -> 95151.762
A12: 1 | B12: Households Income (yh) | C12: 178198.9 | D12: 181254.7 | E12: 184455.1 | F12: 190405.9 | G12: 188270.8 | H12: 197807.9 | I12: 210908.4 | J12: 217576.1 | K12: 225813.1 | M12: statistical discrepancy | N12: =N14-N13 -> -46150.347 | O12: =O14-O13 -> -33678.146 | P12: =P14-P13 -> -16088.675 | Q12: =Q14-Q13 -> -913.02047 | R12: =R14-R13 -> 15273.894 | S12: =S14-S13 -> 43557.047 | T12: =T14-T13 -> 66955.637 | U12: =U14-U13 -> 96290.972 | V12: =V14-V13 -> 129532.32
B13: Располагаемый доход | M13: GDP by expenditure method | N13: =N7+N8+N10-N11 -> 201244.85 | O13: =O7+O8+O10-O11 -> 206717.2 | P13: =P7+P8+P10-P11 -> 213773.26 | Q13: =Q7+Q8+Q10-Q11 -> 223900.78 | R13: =R7+R8+R10-R11 -> 236767.58 | S13: =S7+S8+S10-S11 -> 245753.81 | T13: =T7+T8+T10-T11 -> 258085.57 | U13: =U7+U8+U10-U11 -> 272039.88 | V13: =V7+V8+V10-V11 -> 284438.02
B14: Disposable Income | M14: GDP by production method | N14: ='GDP-total'!B20 -> 155094.5 | O14: ='GDP-total'!C20 -> 173039.05 | P14: ='GDP-total'!D20 -> 197684.58 | Q14: ='GDP-total'!E20 -> 222987.76 | R14: ='GDP-total'!F20 -> 252041.47 | S14: ='GDP-total'!G20 -> 289310.86 | T14: ='GDP-total'!H20 -> 325041.2 | U14: ='GDP-total'!I20 -> 368330.85 | V14: ='GDP-total'!J20 -> 413970.34
B15: Source: ydh_1
C16: 2024 | D16: =C16+1 -> 2025 | E16: =D16+1 -> 2026 | F16: =E16+1 -> 2027 | G16: =F16+1 -> 2028 | H16: =G16+1 -> 2029 | I16: =H16+1 -> 2030 | J16: =I16+1 -> 2031 | K16: =J16+1 -> 2032
B17: Households Income (ydh) | C17: 165220 | D17: 168053.2 | E17: 171020.6 | F17: 176537.9 | G17: 174558.3 | H17: 183400.8 | I17: 195547.1 | J17: 201729.2 | K17: 209366.3
B18: Сбережения домохозяйств | C18: =[6]IEA2024!$P$23 -> 212972.6
B19: Savings of Households
B20: Source: sh_1
C21: 2024 | D21: =C21+1 -> 2025 | E21: =D21+1 -> 2026 | F21: =E21+1 -> 2027 | G21: =F21+1 -> 2028 | H21: =G21+1 -> 2029 | I21: =H21+1 -> 2030 | J21: =I21+1 -> 2031 | K21: =J21+1 -> 2032
B22: Savings of Households (sh) | C22: 15568.47 | D22: 15835.44 | E22: 16115.05 | F22: 16634.94 | G22: 16448.4 | H22: 17281.62 | I22: 18426.15 | J22: 19008.68 | K22: 19728.31
B23: Доход фирм | C23: ='[6]MacroSAM 2024'!$G$17 -> 15565.063
B24: Income of firms
B25: Source: sf_1
C26: 2024 | D26: =C26+1 -> 2025 | E26: =D26+1 -> 2026 | F26: =E26+1 -> 2027 | G26: =F26+1 -> 2028 | H26: =G26+1 -> 2029 | I26: =H26+1 -> 2030 | J26: =I26+1 -> 2031 | K26: =J26+1 -> 2032
B27: Savings of Firms (sf) | C27: 30478.01 | D27: 32299.64 | E27: 34204.16 | F27: 36798.7 | G27: 41452.82 | H27: 44682.92 | I27: 47543.05 | J27: 50773.95 | K27: 53106.65
B28: Сбережения правительства | C28: ='[6]MacroSAM 2024'!$L$15 -> 44182.986
B29: Savings of Government
B30: Source: sg_1
C31: 2024 | D31: =C31+1 -> 2025 | E31: =D31+1 -> 2026 | F31: =E31+1 -> 2027 | G31: =F31+1 -> 2028 | H31: =G31+1 -> 2029 | I31: =H31+1 -> 2030 | J31: =I31+1 -> 2031 | K31: =J31+1 -> 2032
B32: Savings of Government (sg) | C32: 15805.01 | D32: 15691.87 | E32: 16221.05 | F32: 15666.08 | G32: 24673.69 | H32: 18994.42 | I32: 13420.02 | J32: 15218.02 | K32: 15398.33
B33: Доходы правительства | C33: ='[6]MacroSAM 2024'!$I$17 -> 16354.2
B34: Government's Revenues
B35: Source: yg_1
C36: 2024 | D36: =C36+1 -> 2025 | E36: =D36+1 -> 2026 | F36: =E36+1 -> 2027 | G36: =F36+1 -> 2028 | H36: =G36+1 -> 2029 | I36: =H36+1 -> 2030 | J36: =I36+1 -> 2031 | K36: =J36+1 -> 2032
B37: Government's revenues (yg) | C37: 59317.95 | D37: 63914.72 | E37: 67197.62 | F37: 72636.77 | G37: 77828.42 | H37: 82925.37 | I37: 88058.96 | J37: 93957.18 | K37: 98974.21
C38: ='[6]MacroSAM 2024'!$L$16 -> 93530.106
B39: Taxes of production
B40: Source: tp_grp
C41: 2024 | D41: =C41+1 -> 2025 | E41: =D41+1 -> 2026 | F41: =E41+1 -> 2027 | G41: =F41+1 -> 2028 | H41: =G41+1 -> 2029 | I41: =H41+1 -> 2030 | J41: =I41+1 -> 2031 | K41: =J41+1 -> 2032
B42: Agriculture (tp_a) | C42: 154.3 | D42: 172.1956 | E42: 180.0704 | F42: 188.9284 | G42: 192.8 | H42: 203.2548 | I42: 205.2955 | J42: 214.1201 | K42: 227.6379
B43: Mining (tp_mi) | C43: 114.5565 | D43: 145.4979 | E43: 156.2666 | F43: 168.1922 | G43: 177.676 | H43: 186.96 | I43: 197.3191 | J43: 210.2786 | K43: 220.2655
B44: Manufacturing (tp_m) | C44: 1618.273 | D44: 1735.143 | E44: 1895.258 | F44: 2078.124 | G44: 2309.077 | H44: 2521.12 | I44: 2629.12 | J44: 2729.41 | K44: 2807.371
B45: Energy and Water (tp_e) | C45: 624.9335 | D45: 730.1422 | E45: 793.6334 | F45: 1076.379 | G45: 1106.161 | H45: 1135.615 | I45: 1183.638 | J45: 1346.645 | K45: 1559.578
B46: Construction (tp_c) | C46: 513.4607 | D46: 608.1064 | E46: 674.3637 | F46: 720.5002 | G46: 770.242 | H46: 786.5593 | I46: 829.9439 | J46: 876.6807 | K46: 917.7856
B47: Transport (tp_t) | C47: 406.7043 | D47: 456.4143 | E47: 522.891 | F47: 676.7949 | G47: 717.275 | H47: 771.7601 | I47: 843.1607 | J47: 950.3595 | K47: 1067.133
B48: Trade (tp_tr) | C48: 1036.504 | D48: 1092.013 | E48: 1117.694 | F48: 1257.383 | G48: 1349.95 | H48: 1386.382 | I48: 1453.688 | J48: 1606.177 | K48: 1660.462
B49: Financial services (tp_fs) | C49: 559.6082 | D49: 629.9252 | E49: 637.4798 | F49: 674.5428 | G49: 707.4529 | H49: 738.38 | I49: 789.0963 | J49: 836.5656 | K49: 864.6461
B50: Public Services (tp_ps) | C50: 394.7391 | D50: 400.5366 | E50: 437.6743 | F50: 489.2191 | G50: 514.5554 | H50: 588.007 | I50: 656.8075 | J50: 717.8194 | K50: 795.5911
B51: Market Services (tp_ms) | C51: 52.95066 | D51: 57.3555 | E51: 71.1259 | F51: 78.77188 | G51: 91.75477 | H51: 97.13412 | I51: 97.90147 | J51: 112.4224 | K51: 119.8403
B52: Total (tp_tot) | C52: 5476.03 | D52: 6027.33 | E52: 6486.457 | F52: 7408.836 | G52: 7936.945 | H52: 8415.172 | I52: 8885.97 | J52: 9600.479 | K52: 10240.31
B53: Косвенные налоги | C53: =SUM(C42:C51) -> 5476.03 | D53: =SUM(D42:D51) -> 6027.3297 | E53: =SUM(E42:E51) -> 6486.4571 | F53: =SUM(F42:F51) -> 7408.8355 | G53: =SUM(G42:G51) -> 7936.9441 | H53: =SUM(H42:H51) -> 8415.1723 | I53: =SUM(I42:I51) -> 8885.9705 | J53: =SUM(J42:J51) -> 9600.4783 | K53: =SUM(K42:K51) -> 10240.31
A54: 3 | B54: Indirect Taxes
B55: Source: ti_grp
C56: 2024 | D56: =C56+1 -> 2025 | E56: =D56+1 -> 2026 | F56: =E56+1 -> 2027 | G56: =F56+1 -> 2028 | H56: =G56+1 -> 2029 | I56: =H56+1 -> 2030 | J56: =I56+1 -> 2031 | K56: =J56+1 -> 2032
B57: Agriculture (ti_a) | C57: 3027.754 | D57: 3388.052 | E57: 3515.187 | F57: 3684.048 | G57: 3746.837 | H57: 3944.798 | I57: 3981.974 | J57: 4150.13 | K57: 4409.252
B58: Mining (ti_mi) | C58: 955.2161 | D58: 1192.187 | E58: 1264.267 | F58: 1340.48 | G58: 1384.092 | H58: 1437.073 | I58: 1506.07 | J58: 1592.127 | K58: 1642.896
B59: Manufacturing (ti_m) | C59: 3496.872 | D59: 3721.094 | E59: 4005.228 | F59: 4329.774 | G59: 4744.819 | H59: 5096.263 | I59: 5340.4 | J59: 5528.497 | K59: 5656.67
B60: Energy and Water (ti_e) | C60: 778.8238 | D60: 899.645 | E60: 967.9236 | F60: 1301.704 | G60: 1316.17 | H60: 1342.251 | I60: 1399.7 | J60: 1524.872 | K60: 1799.87
B61: Construction (ti_c) | C61: 1648.966 | D61: 1950.165 | E61: 2160.906 | F61: 2267.521 | G61: 2467.761 | H61: 2521.509 | I61: 2661.29 | J61: 2812.225 | K61: 2943.853
B62: Transport (ti_t) | C62: 752.0322 | D62: 834.4763 | E62: 952.0027 | F62: 1232.515 | G62: 1288.496 | H62: 1390.595 | I62: 1482.961 | J62: 1777.742 | K62: 1989.964
B63: Trade (ti_tr) | C63: 809.1038 | D63: 852.386 | E63: 872.0864 | F63: 981.1529 | G63: 1053.199 | H63: 1081.268 | I63: 1133.81 | J63: 1252.223 | K63: 1294.737
B64: Financial services (ti_fs) | C64: 1401.933 | D64: 1597.263 | E64: 1561.774 | F64: 1670.133 | G64: 1743.847 | H64: 1810.496 | I64: 1944.581 | J64: 2060.015 | K64: 2122.187
B65: Public Services (ti_ps) | C65: 784.8014 | D65: 794.4836 | E65: 868.2275 | F65: 965.2054 | G65: 1010 | H65: 1151.167 | I65: 1283.894 | J65: 1398.454 | K65: 1551.769
B66: Market Services (ti_ms) | C66: 180.1587 | D66: 191.5379 | E66: 229.1533 | F66: 252.3556 | G66: 285.7418 | H66: 301.1568 | I66: 296.7056 | J66: 332.9321 | K66: 353.1474
B67: Total (ti_tot) | C67: 13835.66 | D67: 15421.29 | E67: 16396.76 | F67: 18024.89 | G67: 19040.96 | H67: 20076.58 | I67: 21031.39 | J67: 22429.22 | K67: 23764.35
B68: ='[6]MacroSAM 2024'!$D$16 -> 14524.8 | C68: =SUM(C57:C66) -> 13835.661 | D68: =SUM(D57:D66) -> 15421.29 | E68: =SUM(E57:E66) -> 16396.756 | F68: =SUM(F57:F66) -> 18024.889 | G68: =SUM(G57:G66) -> 19040.963 | H68: =SUM(H57:H66) -> 20076.577 | I68: =SUM(I57:I66) -> 21031.386 | J68: =SUM(J57:J66) -> 22429.217 | K68: =SUM(K57:K66) -> 23764.345
B69: Налоги на капитал | C69: =14824.4-299.5 -> 14524.9
B70: Taxes on Capital
B71: Source: tax_c_1
C72: 2024 | D72: =C72+1 -> 2025 | E72: =D72+1 -> 2026 | F72: =E72+1 -> 2027 | G72: =F72+1 -> 2028 | H72: =G72+1 -> 2029 | I72: =H72+1 -> 2030 | J72: =I72+1 -> 2031 | K72: =J72+1 -> 2032
B73: tax_c | C73: 11818.91 | D73: 12525.3 | E73: 13263.85 | F73: 14269.97 | G73: 16074.77 | H73: 17327.35 | I73: 18436.47 | J73: 19689.36 | K73: 20593.95
B74: Налог на доходы домохозяйств | C74: ='[6]MacroSAM 2024'!$F$16 -> 11818.5
B75: Households Income Tax
B76: Source: dth_1
C77: 2024 | D77: =C77+1 -> 2025 | E77: =D77+1 -> 2026 | F77: =E77+1 -> 2027 | G77: =F77+1 -> 2028 | H77: =G77+1 -> 2029 | I77: =H77+1 -> 2030 | J77: =I77+1 -> 2031 | K77: =J77+1 -> 2032
B78: dth | C78: 12978.88 | D78: 13201.47 | E78: 13434.57 | F78: 13867.99 | G78: 13712.48 | H78: 14407.11 | I78: 15361.27 | J78: 15846.9 | K78: 16446.83
B79: Налог на доход фирм | C79: ='[6]MacroSAM 2024'!$G$16 -> 12976
B80: Firm's Income Tax
B81: Source: dtf_1
C82: 2024 | D82: =C82+1 -> 2025 | E82: =D82+1 -> 2026 | F82: =E82+1 -> 2027 | G82: =F82+1 -> 2028 | H82: =G82+1 -> 2029 | I82: =H82+1 -> 2030 | J82: =I82+1 -> 2031 | K82: =J82+1 -> 2032
B83: dtf | C83: 9229.674 | D83: 9781.318 | E83: 10358.07 | F83: 11143.77 | G83: 12553.18 | H83: 13531.35 | I83: 14397.49 | J83: 15375.91 | K83: 16082.32
B84: Таможенная пошлина | C84: ='[6]MacroSAM 2024'!$H$16 -> 15577.7
B85: Customs Duty
B86: Source: tim_grp
C87: 2024 | D87: =C87+1 -> 2025 | E87: =D87+1 -> 2026 | F87: =E87+1 -> 2027 | G87: =F87+1 -> 2028 | H87: =G87+1 -> 2029 | I87: =H87+1 -> 2030 | J87: =I87+1 -> 2031 | K87: =J87+1 -> 2032
B88: Agriculture (tim_a) | C88: 223.0015 | D88: 252.3769 | E88: 238.7786 | F88: 253.8722 | G88: 258.669 | H88: 273.2917 | I88: 276.2416 | J88: 288.0786 | K88: 305.7044
B89: Mining (tim_mi) | C89: 12.86548 | D89: 15.47927 | E89: 16.32992 | F89: 17.19542 | G89: 17.64266 | H89: 18.131 | I89: 19.00821 | J89: 21.44519 | K89: 22.09296
B90: Manufacturing (tim_m) | C90: 1768.13 | D90: 1866.209 | E90: 1989.446 | F90: 2133.088 | G90: 2314.212 | H90: 2454.225 | I90: 2590.775 | J90: 2692.724 | K90: 2752.17
B91: Energy and Water (tim_e) | C91: 24.65885 | D91: 27.63584 | E91: 29.33033 | F91: 38.50929 | G91: 37.88051 | H91: 38.26773 | I91: 39.58512 | J91: 40.23046 | K91: 47.95065
B92: Construction (tim_c) | C92: 51.46191 | D92: 58.54437 | E92: 63.40248 | F92: 31.755 | G92: 72.09045 | H92: 74.90025 | I92: 79.64359 | J92: 85.06172 | K92: 88.85065
B93: Transport (tim_t) | C93: 146.8808 | D93: 158.0347 | E93: 181.5918 | F93: 236.0371 | G93: 240.7881 | H93: 259.9879 | I93: 275.6107 | J93: 402.7462 | K93: 450.7444
B94: Trade (tim_tr) | C94: 2.659408 | D94: 2.740337 | E94: 2.697873 | F94: 3.060487 | G94: 3.221679 | H94: 3.210088 | I94: 3.353619 | J94: 3.601489 | K94: 3.685531
B95: Financial services (tim_fs) | C95: 1096.731 | D95: 1277.871 | E95: 1179.474 | F95: 1283.87 | G95: 1328.744 | H95: 1367.297 | I95: 1480.719 | J95: 1567.56 | K95: 1608.058
B96: Public Services (tim_ps) | C96: 165.8664 | D96: 166.2085 | E96: 181.6385 | F96: 196.9164 | G96: 201.0874 | H96: 226.3768 | I96: 250.6687 | J96: 268.8053 | K96: 300.1681
B97: Market Services (tim_ms) | C97: 0 | D97: 0 | E97: 0 | F97: 0 | G97: 0 | H97: 0 | I97: 0 | J97: 0 | K97: 0
B98: Total (tim_tot) | C98: 3492.255 | D98: 3825.1 | E98: 3882.69 | F98: 4194.304 | G98: 4474.336 | H98: 4715.688 | I98: 5015.606 | J98: 5370.252 | K98: 5579.425
A99: ='[5]D-SAM24'!$O$55 -> 2487.1354 | B99: =SUM('[5]D-SAM24'!$M$31:$V$31) -> 2487.1355 | C99: =SUM(C88:C97) -> 3492.2553 | D99: =SUM(D88:D97) -> 3825.0999 | E99: =SUM(E88:E97) -> 3882.6895 | F99: =SUM(F88:F97) -> 4194.3039 | G99: =SUM(G88:G97) -> 4474.3358 | H99: =SUM(H88:H97) -> 4715.6875 | I99: =SUM(I88:I97) -> 5015.6055 | J99: =SUM(J88:J97) -> 5370.253 | K99: =SUM(K88:K97) -> 5579.4247
B100: Export Taxes
...

Sheet 4_Demand
B1: Спрос
B2: Block 4: Demand
B3: Потребление домохозяйствами товаров (в реальном выражении) | G3: Расход д/х /индексы (реал.)
B4: Consumption of households by commodities (in real terms)
B5: Source: c_h_grp
C6: 2024 | D6: =C6+1 -> 2025 | E6: =D6+1 -> 2026 | F6: =E6+1 -> 2027 | G6: =F6+1 -> 2028 | H6: =G6+1 -> 2029 | I6: =H6+1 -> 2030 | J6: =I6+1 -> 2031 | K6: =J6+1 -> 2032
B7: Agriculture (c_a_h) | C7: 37782.84 | D7: 39456.02 | E7: 39116.14 | F7: 43366.77 | G7: 45793.73 | H7: 48770.47 | I7: 51415.1 | J7: 52097.89 | K7: 53279.83
B8: Mining (c_mi_h) | C8: 111.72 | D8: 117.2033 | E8: 115.9396 | F8: 128.1679 | G8: 132.0827 | H8: 141.1981 | I8: 146.8844 | J8: 149.794 | K8: 156.3146
B9: Manufacturing (c_m_h) | C9: 50064.83 | D9: 52399.95 | E9: 51203.33 | F9: 56418.04 | G9: 57823.66 | H9: 63083.71 | I9: 66054.73 | J9: 66980.14 | K9: 69093.19
B10: Energy and Water (c_e_h) | C10: 4661.131 | D10: 5000.151 | E10: 4912.103 | F10: 5426.916 | G10: 5621.184 | H10: 6037.309 | I10: 6246.942 | J10: 6728.726 | K10: 6823.745
B11: Construction (c_c_h) | C11: 337.5392 | D11: 345.108 | E11: 342.6295 | F11: 378.1667 | G11: 408.0255 | H11: 451.8151 | I11: 468.0029 | J11: 478.356 | K11: 493.0955
B12: Transport (c_t_h) | C12: 4623.427 | D12: 4868.126 | E12: 4751.822 | F12: 5161.874 | G12: 5305.504 | H12: 5577.231 | I12: 6104.938 | J12: 6158.765 | K12: 6320.834
B13: Trade (c_tr_h) | C13: 7746.785 | D13: 8323.986 | E13: 8182.948 | F13: 8965.73 | G13: 9300.568 | H13: 10146.73 | I13: 10552.03 | J13: 10800.97 | K13: 11122.77
B14: Financial services (c_fs_h) | C14: 10254.33 | D14: 10538.2 | E14: 10172.85 | F14: 11266.67 | G14: 11530.41 | H14: 12227.4 | I14: 12670.9 | J14: 12563.66 | K14: 13041.08
B15: Public Services (c_ps_h) | C15: 2736.163 | D15: 2933.918 | E15: 2828.948 | F15: 3189.945 | G15: 3292.804 | H15: 3529.662 | I15: 3665.664 | J15: 3741.316 | K15: 3825.612
B16: Market Services (c_ms_h) | C16: 22493.1 | D16: 23726.76 | E16: 22934.63 | F16: 24886.21 | G16: 25346.67 | H16: 27120.36 | I16: 27972.51 | J16: 27987.5 | K16: 28560.44
B17: ='[5]2024-Final'!$Y$48 -> 138104.44 | C17: =SUM(C7:C16) -> 140811.87 | D17: =SUM(D7:D16) -> 147709.42 | E17: =SUM(E7:E16) -> 144561.34 | F17: =SUM(F7:F16) -> 159188.49 | G17: =SUM(G7:G16) -> 164554.64 | H17: =SUM(H7:H16) -> 177085.89 | I17: =SUM(I7:I16) -> 185297.7 | J17: =SUM(J7:J16) -> 187687.12 | K17: =SUM(K7:K16) -> 192716.91
A18: гу /индексы (реал.) | B18: Consumption of government by commodities (in real terms)
B19: Source: c_g_grp
C20: 2024 | D20: =C20+1 -> 2025 | E20: =D20+1 -> 2026 | F20: =E20+1 -> 2027 | G20: =F20+1 -> 2028 | H20: =G20+1 -> 2029 | I20: =H20+1 -> 2030 | J20: =I20+1 -> 2031 | K20: =J20+1 -> 2032
B21: Agriculture (c_a_g) | C21: 4.63253 | D21: 4.53173 | E21: 4.794315 | F21: 4.984611 | G21: 5.098434 | H21: 5.334358 | I21: 5.447401 | J21: 5.379634 | K21: 5.81362
B22: Mining (c_mi_g) | C22: 0.00198779 | D22: 0.00231582 | E22: 0.00246594 | F22: 0.00282088 | G22: 0.00321213 | H22: 0.00354572 | I22: 0.0038644 | J22: 0.00408634 | K22: 0.00422242
B23: Manufacturing (c_m_g) | C23: 16.93616 | D23: 19.97698 | E23: 24.02716 | F23: 30.6351 | G23: 37.37377 | H23: 54.60988 | I23: 63.61188 | J23: 67.32927 | K23: 69.71959
B24: Energy and Water (c_e_g) | C24: 0.00193978 | D24: 0.00230684 | E24: 0.00263496 | F24: 0.00320092 | G24: 0.00355265 | H24: 0.00383331 | I24: 0.00400369 | J24: 0.0044096 | K24: 0.00455974
B25: Construction (c_c_g) | C25: 0.00200758 | D25: 0.00263265 | E25: 0.00367059 | F25: 0.00467291 | G25: 0.00573609 | H25: 0.00454462 | I25: 0.00480355 | J25: 0.00465041 | K25: 0.00478031
B26: Transport (c_t_g) | C26: 0.00205092 | D26: 0.00216792 | E26: 0.00251846 | F26: 0.00222623 | G26: 0.00257572 | H26: 0.00283784 | I26: 0.00261084 | J26: 0.00392244 | K26: 0.0041592
B27: Trade (c_tr_g) | C27: 0.00205051 | D27: 0.0021935 | E27: 0.00231829 | F27: 0.0024273 | G27: 0.00266054 | H27: 0.00276962 | I27: 0.00285776 | J27: 0.00296604 | K27: 0.0030795
B28: Financial services (c_fs_g) | C28: 52.58455 | D28: 71.453 | E28: 71.36864 | F28: 73.45783 | G28: 75.21046 | H28: 82.23511 | I28: 90.79238 | J28: 110.3016 | K28: 139.3246
B29: Public Services (c_ps_g) | C29: 20259.7 | D29: 23217.72 | E29: 23898.4 | F29: 27132.98 | G29: 26772.28 | H29: 30142.23 | I29: 30246.13 | J29: 30287.73 | K29: 29797.14
B30: Market Services (c_ms_g) | C30: 73.39699 | D30: 88.87646 | E30: 102.9374 | F30: 132.6763 | G30: 141.6491 | H30: 159.0753 | I30: 164.8847 | J30: 165.799 | K30: 170.3658
B31: ='[5]2024-Final'!$AF$48 -> 20393.052 | C31: =SUM(C21:C30) -> 20407.26 | D31: =SUM(D21:D30) -> 23402.57 | E31: =SUM(E21:E30) -> 24101.541 | F31: =SUM(F21:F30) -> 27374.749 | G31: =SUM(G21:G30) -> 27031.63 | H31: =SUM(H21:H30) -> 30443.502 | I31: =SUM(I21:I30) -> 30570.885 | J31: =SUM(J21:J30) -> 30636.56 | K31: =SUM(K21:K30) -> 30182.384
A32: ВНОК | B32: Investment demand by commodity (in real terms)
B33: Source: inv_grp
C34: 2024 | D34: =C34+1 -> 2025 | E34: =D34+1 -> 2026 | F34: =E34+1 -> 2027 | G34: =F34+1 -> 2028 | H34: =G34+1 -> 2029 | I34: =H34+1 -> 2030 | J34: =I34+1 -> 2031 | K34: =J34+1 -> 2032
B35: Agriculture (inv_a) | C35: 10967.88 | D35: 10940.99 | E35: 11587.37 | F35: 12189.18 | G35: 14655.49 | H35: 14480.92 | I35: 14534.58 | J35: 15504.29 | K35: 15941.01
B36: Mining (inv_mi) | C36: 5552.655 | D36: 5564.484 | E36: 5880.34 | F36: 6167.917 | G36: 7237.393 | H36: 7178.104 | I36: 7109.342 | J36: 7632.519 | K36: 8007.449
B37: Manufacturing (inv_m) | C37: 5972.077 | D37: 5970.884 | E37: 6232.923 | F37: 6516.283 | G37: 7604.394 | H37: 7696.992 | I37: 7673.268 | J37: 8191.104 | K37: 8494.791
B38: Energy and Water (inv_e) | C38: 9.10828 | D38: 9.333473 | E38: 9.795204 | F38: 10.26804 | G38: 12.10986 | H38: 12.06701 | I38: 11.88766 | J38: 13.47974 | K38: 13.74335
B39: Construction (inv_c) | C39: 24028.51 | D39: 23467.82 | E39: 24890.2 | F39: 26066.05 | G39: 32022.59 | H39: 32898.39 | I39: 32444.05 | J39: 34910.63 | K39: 36179.17
B40: Transport (inv_t) | C40: 7711.857 | D40: 7756.609 | E40: 8088.276 | F40: 8336.652 | G40: 9756.363 | H40: 9515.348 | I40: 9916.536 | J40: 10531.55 | K40: 10866.61
B41: Trade (inv_tr) | C41: 23412.99 | D41: 24031.56 | E41: 25237.49 | F41: 26236.77 | G41: 30989.27 | H41: 31366.96 | I41: 31056.69 | J41: 33465.85 | K41: 34647.59
B42: Financial services (inv_fs) | C42: 111.1083 | D42: 109.074 | E42: 112.4819 | F42: 118.2018 | G42: 137.7369 | H42: 135.5141 | I42: 133.6998 | J42: 139.5595 | K42: 145.639
B43: Public Services (inv_ps) | C43: 9.597084 | D43: 9.830154 | E43: 10.12566 | F43: 10.83352 | G43: 12.73296 | H43: 12.66314 | I43: 12.52085 | J43: 13.45319 | K43: 13.83003
B44: Market Services (inv_ms) | C44: 10.36875 | D44: 10.44794 | E44: 10.78872 | F44: 11.10773 | G44: 12.88144 | H44: 12.78744 | I44: 12.55718 | J44: 13.2265 | K44: 13.56959
A45: 2 | B45: Total | C45: 75206.33 | D45: 77968.46 | E45: 82697.53 | F45: 88077.81 | G45: 105031.3 | H45: 105712.3 | I45: 105665.1 | J45: 114942.5 | K45: 120227.9
B46: ='[5]2024-Final'!$AG$48 -> 78369.344 | C46: =SUM(C35:C44) -> 77786.151 | D46: =SUM(D35:D44) -> 77871.033 | E46: =SUM(E35:E44) -> 82059.79 | F46: =SUM(F35:F44) -> 85663.263 | G46: =SUM(G35:G44) -> 102440.96 | H46: =SUM(H35:H44) -> 103309.75 | I46: =SUM(I35:I44) -> 102905.13 | J46: =SUM(J35:J44) -> 110415.66 | K46: =SUM(K35:K44) -> 114323.4

Sheet 5_IntTrade
B2: Block 5: International trade
B4: Gorss Output forecasts using Constant Elasticity of transformation (CET)
B5: Source: xp_grp
C6: 2024 | D6: =C6+1 -> 2025 | E6: =D6+1 -> 2026 | F6: =E6+1 -> 2027 | G6: =F6+1 -> 2028 | H6: =G6+1 -> 2029 | I6: =H6+1 -> 2030 | J6: =I6+1 -> 2031 | K6: =J6+1 -> 2032
B7: Agriculture (XP_a) | C7: 77989.18 | D7: 87034.32 | E7: 91014.56 | F7: 95491.75 | G7: 97448.59 | H7: 102732.8 | I7: 103764.3 | J7: 108224.6 | K7: 115057
B8: Mining (XP_mi) | C8: 12664.64 | D8: 16085.33 | E8: 17275.85 | F8: 18594.27 | G8: 19642.75 | H8: 20669.12 | I8: 21814.36 | J8: 23247.08 | K8: 24351.17
B9: Manufacturing (XP_m) | C9: 57016.34 | D9: 61134 | E9: 66775.3 | F9: 73218.19 | G9: 81355.31 | H9: 88826.2 | I9: 92631.33 | J9: 96164.84 | K9: 98911.63
B10: Energy and Water (XP_e) | C10: 9997.957 | D10: 11681.13 | E10: 12696.89 | F10: 17220.38 | G10: 17696.85 | H10: 18168.07 | I10: 18936.36 | J10: 21544.21 | K10: 24950.81
B11: Construction (XP_c) | C11: 31675.93 | D11: 37514.72 | E11: 41602.2 | F11: 44448.41 | G11: 47517.03 | H11: 48523.66 | I11: 51200.11 | J11: 54083.35 | K11: 56619.15
B12: Transport (XP_t) | C12: 18362.16 | D12: 20606.51 | E12: 23607.84 | F12: 30556.4 | G12: 32384.02 | H12: 34843.95 | I12: 38067.6 | J12: 42907.48 | K12: 48179.63
B13: Trade (XP_tr) | C13: 33468 | D13: 35260.33 | E13: 36089.55 | F13: 40600.02 | G13: 43588.95 | H13: 44765.28 | I13: 46938.55 | J13: 51862.34 | K13: 53615.16
B14: Financial services (XP_fs) | C14: 14788.22 | D14: 16646.42 | E14: 16846.06 | F14: 17825.49 | G14: 18695.17 | H14: 19512.45 | I14: 20852.68 | J14: 22107.1 | K14: 22849.16
B15: Public Services (XP_ps) | C15: 19870.87 | D15: 20162.71 | E15: 22032.19 | F15: 24626.92 | G15: 25902.33 | H15: 29599.82 | I15: 33063.19 | J15: 36134.48 | K15: 40049.45
B16: Market Services (XP_ms) | C16: 3864.399 | D16: 4185.869 | E16: 5190.849 | F16: 5748.861 | G16: 6696.367 | H16: 7088.958 | I16: 7144.96 | J16: 8204.714 | K16: 8746.082
B17: =SUM('[5]2024-Final'!$AF$6:$AF$15) -> 284532.8 | C17: =SUM(C7:C16) -> 279697.7 | D17: =SUM(D7:D16) -> 310311.34 | E17: =SUM(E7:E16) -> 333131.29 | F17: =SUM(F7:F16) -> 368330.69 | G17: =SUM(G7:G16) -> 390927.37 | H17: =SUM(H7:H16) -> 414730.31 | I17: =SUM(I7:I16) -> 434413.44 | J17: =SUM(J7:J16) -> 464480.19 | K17: =SUM(K7:K16) -> 493329.24
B18: Export by commodity (in real terms)
B19: Source: ex_grp | L19: Source: pe_grp | V19: Экспорт по товарам (в реальном выражении)
C20: 2024 | D20: =C20+1 -> 2025 | E20: =D20+1 -> 2026 | F20: =E20+1 -> 2027 | G20: =F20+1 -> 2028 | H20: =G20+1 -> 2029 | I20: =H20+1 -> 2030 | J20: =I20+1 -> 2031 | K20: =J20+1 -> 2032 | L20: Export prices | M20: 2024 | N20: =M20+1 -> 2025 | O20: =N20+1 -> 2026 | P20: =O20+1 -> 2027 | Q20: =P20+1 -> 2028 | R20: =Q20+1 -> 2029 | S20: =R20+1 -> 2030 | T20: =S20+1 -> 2031 | U20: =T20+1 -> 2032 | V20: 2024 | W20: =V20+1 -> 2025 | X20: =W20+1 -> 2026 | Y20: =X20+1 -> 2027 | Z20: =Y20+1 -> 2028 | AA20: =Z20+1 -> 2029 | AB20: =AA20+1 -> 2030 | AC20: =AB20+1 -> 2031 | AD20: =AC20+1 -> 2032
B21: Agriculture (ex_a) | C21: 2035.83 | D21: 2037.524 | E21: 2319.693 | F21: 2519 | G21: 2785.262 | H21: 2961.366 | I21: 3044.408 | J21: 3156.124 | K21: 3325.744 | L21: Agriculture (pe_a) | M21: 0.9327285 | N21: 0.9523215 | O21: 0.9724226 | P21: 1.012351 | Q21: 1.053417 | R21: 1.094853 | S21: 1.097846 | T21: 1.128965 | U21: 1.157974 | V21: =C21/M21 -> 2182.6609 | W21: =D21/N21 -> 2139.5338 | X21: =E21/O21 -> 2385.4783 | Y21: =F21/P21 -> 2488.2674 | Z21: =G21/Q21 -> 2644.0261 | AA21: =H21/R21 -> 2704.8069 | AB21: =I21/S21 -> 2773.0738 | AC21: =J21/T21 -> 2795.5907 | AD21: =K21/U21 -> 2872.0369
B22: Mining (ex_mi) | C22: 3903.85 | D22: 4893.145 | E22: 5291.537 | F22: 5712.544 | G22: 6091.906 | H22: 6401.842 | I22: 6732.22 | J22: 7347.381 | K22: 7804.096 | L22: Mining (pe_mi) | M22: 0.9327285 | N22: 0.9532658 | O22: 0.9724226 | P22: 0.9985239 | Q22: 1.035114 | R22: 1.057529 | S22: 1.076835 | T22: 1.118162 | U22: 1.130534 | V22: =C22/M22 -> 4185.4087 | W22: =D22/N22 -> 5133.0332 | X22: =E22/O22 -> 5441.6022 | Y22: =F22/P22 -> 5720.9888 | Z22: =G22/Q22 -> 5885.2513 | AA22: =H22/R22 -> 6053.5853 | AB22: =I22/S22 -> 6251.8585 | AC22: =J22/T22 -> 6570.945 | AD22: =K22/U22 -> 6903.0175
B23: Manufacturing (ex_m) | C23: 5409.357 | D23: 5649.721 | E23: 6374.148 | F23: 7190.738 | G23: 8104.466 | H23: 9295.314 | I23: 9642.579 | J23: 10180.25 | K23: 10576.99 | L23: Manufacturing (pe_m) | M23: 0.9327285 | N23: 0.9631809 | O23: 0.9964924 | P23: 1.037043 | Q23: 1.072736 | R23: 1.073081 | S23: 1.087341 | T23: 1.118162 | U23: 1.14151 | V23: =C23/M23 -> 5799.4979 | W23: =D23/N23 -> 5865.6904 | X23: =E23/O23 -> 6396.5847 | Y23: =F23/P23 -> 6933.8861 | Z23: =G23/Q23 -> 7554.9492 | AA23: =H23/R23 -> 8662.2669 | AB23: =I23/S23 -> 8868.0359 | AC23: =J23/T23 -> 9104.45 | AD23: =K23/U23 -> 9265.7883
B24: Energy and Water (ex_e) | C24: 1291.76 | D24: 1552.499 | E24: 1728.207 | F24: 2364.622 | G24: 2527.607 | H24: 2614.615 | I24: 2677.228 | J24: 3468.924 | K24: 3767.285 | L24: Energy and Water (pe_e) | M24: 0.9327285 | N24: 0.9726239 | O24: 1.010934 | P24: 1.046919 | Q24: 1.093072 | R24: 1.119736 | S24: 1.134616 | T24: 1.188384 | U24: 1.174438 | V24: =C24/M24 -> 1384.9261 | W24: =D24/N24 -> 1596.1966 | X24: =E24/O24 -> 1709.5152 | Y24: =F24/P24 -> 2258.6485 | Z24: =G24/Q24 -> 2312.3884 | AA24: =H24/R24 -> 2335.0281 | AB24: =I24/S24 -> 2359.5895 | AC24: =J24/T24 -> 2919.0262 | AD24: =K24/U24 -> 3207.7343
B25: Construction (ex_c) | C25: 7.69011e-06 | D25: 8.08012e-06 | E25: 9.22511e-06 | F25: 1.00029e-05 | G25: 1.18506e-05 | H25: 1.32053e-05 | I25: 1.37365e-05 | J25: 1.4772e-05 | K25: 1.55795e-05 | L25: Construction (pe_c) | M25: 0.9327285 | N25: 0.9490165 | O25: 0.9676086 | P25: 0.9925979 | Q25: 1.021896 | R25: 1.041977 | S25: 1.055824 | T25: 1.085751 | U25: 1.108582 | V25: =C25/M25 -> 8.2447465e-06 | W25: =D25/N25 -> 8.5142039e-06 | X25: =E25/O25 -> 9.5339273e-06 | Y25: =F25/P25 -> 1.0077495e-05 | Z25: =G25/Q25 -> 1.1596679e-05 | AA25: =H25/R25 -> 1.2673312e-05 | AB25: =I25/S25 -> 1.3010218e-05 | AC25: =J25/T25 -> 1.3605329e-05 | AD25: =K25/U25 -> 1.4053539e-05
B26: Transport (ex_t) | C26: 2667.296 | D26: 2943.138 | E26: 3383.148 | F26: 4235.95 | G26: 4486.386 | H26: 4631.539 | I26: 5751.019 | J26: 6618.721 | K26: 7381.954 | L26: Transport (pe_t) | M26: 0.9327285 | N26: 0.953738 | O26: 0.9916785 | P26: 1.032104 | Q26: 1.067652 | R26: 1.093817 | S26: 1.087341 | T26: 1.128965 | U26: 1.152486 | V26: =C26/M26 -> 2859.6703 | W26: =D26/N26 -> 3085.8978 | X26: =E26/O26 -> 3411.5371 | Y26: =F26/P26 -> 4104.1891 | Z26: =G26/Q26 -> 4202.1052 | AA26: =H26/R26 -> 4234.2906 | AB26: =I26/S26 -> 5289.0666 | AC26: =J26/T26 -> 5862.645 | AD26: =K26/U26 -> 6405.244
B27: Trade (ex_tr) | C27: 91.88233 | D27: 96.18503 | E27: 104.8463 | F27: 113.6972 | G27: 124.4939 | H27: 135.4435 | I27: 139.4351 | J27: 162.6151 | K27: 161.9025 | L27: Trade (pe_tr) | M27: 0.9327285 | N27: 0.944295 | O27: 1.001306 | P27: 1.017289 | Q27: 1.047316 | R27: 1.078265 | S27: 1.082088 | T27: 1.139769 | U27: 1.130534 | V27: =C27/M27 -> 98.509191 | W27: =D27/N27 -> 101.85909 | X27: =E27/O27 -> 104.70955 | Y27: =F27/P27 -> 111.7649 | Z27: =G27/Q27 -> 118.86947 | AA27: =H27/R27 -> 125.61244 | AB27: =I27/S27 -> 128.85745 | AC27: =J27/T27 -> 142.67373 | AD27: =K27/U27 -> 143.20887
B28: Financial services (ex_fs) | C28: 211.6903 | D28: 233.0052 | E28: 252.0127 | F28: 252.8654 | G28: 255.7402 | H28: 266.4471 | I28: 274.2297 | J28: 283.3459 | K28: 303.764 | L28: Financial services (pe_fs) | M28: 0.9327285 | N28: 1.029282 | O28: 1.068702 | P28: 1.071611 | Q28: 1.07782 | R28: 1.109368 | S28: 1.113605 | T28: 1.172179 | U28: 1.201878 | V28: =C28/M28 -> 226.95811 | W28: =D28/N28 -> 226.37644 | X28: =E28/O28 -> 235.81195 | Y28: =F28/P28 -> 235.96753 | Z28: =G28/Q28 -> 237.27543 | AA28: =H28/R28 -> 240.17918 | AB28: =I28/S28 -> 246.25401 | AC28: =J28/T28 -> 241.72579 | AD28: =K28/U28 -> 252.74113
B29: Public Services (ex_ps) | C29: 75.66807 | D29: 78.5752 | E29: 82.16595 | F29: 97.72425 | G29: 106.3201 | H29: 123.8947 | I29: 139.8245 | J29: 158.9411 | K29: 173.4471 | L29: Public Services (pe_ps) | M29: 0.9327285 | N29: 0.9631809 | O29: 0.9820505 | P29: 1.007413 | Q29: 1.047316 | R29: 1.078265 | S29: 1.103099 | T29: 1.150572 | U29: 1.174438 | V29: =C29/M29 -> 81.125504 | W29: =D29/N29 -> 81.57886 | X29: =E29/O29 -> 83.667744 | Y29: =F29/P29 -> 97.005151 | Z29: =G29/Q29 -> 101.51673 | AA29: =H29/R29 -> 114.9019 | AB29: =I29/S29 -> 126.75608 | AC29: =J29/T29 -> 138.14094 | AD29: =K29/U29 -> 147.68519
B30: Market Services (ex_ms) | C30: 20.71859 | D30: 22.63111 | E30: 30.37184 | F30: 32.11289 | G30: 39.05738 | H30: 42.15567 | I30: 43.53531 | J30: 51.61611 | K30: 53.59491 | L30: Market Services | M30: 0.9327285 | N30: 0.953738 | O30: 0.9916785 | P30: 1.007413 | Q30: 1.037148 | R30: 1.067897 | S30: 1.076835 | T30: 1.118162 | U30: 1.125046 | V30: =C30/M30 -> 22.212884 | W30: =D30/N30 -> 23.728854 | X30: =E30/O30 -> 30.6267 | Y30: =F30/P30 -> 31.876589 | Z30: =G30/Q30 -> 37.658444 | AA30: =H30/R30 -> 39.475408 | AB30: =I30/S30 -> 40.428952 | AC30: =J30/T30 -> 46.161567 | AD30: =K30/U30 -> 47.637972
B31: Total (ex_tot) | C31: =SUM(C21:C30) -> 15708.052 | D31: =SUM(D21:D30) -> 17506.424 | E31: =SUM(E21:E30) -> 19566.13 | F31: =SUM(F21:F30) -> 22519.254 | G31: =SUM(G21:G30) -> 24521.239 | H31: =SUM(H21:H30) -> 26472.617 | I31: =SUM(I21:I30) -> 28444.479 | J31: =SUM(J21:J30) -> 31427.918 | K31: =SUM(K21:K30) -> 33548.778 | V31: =SUM(V21:V30) -> 16840.97 | W31: =SUM(W21:W30) -> 18253.895 | X31: =SUM(X21:X30) -> 19799.533 | Y31: =SUM(Y21:Y30) -> 21982.594 | Z31: =SUM(Z21:Z30) -> 23094.04 | AA31: =SUM(AA21:AA30) -> 24510.147 | AB31: =SUM(AB21:AB30) -> 26083.921 | AC31: =SUM(AC21:AC30) -> 27821.359 | AD31: =SUM(AD21:AD30) -> 29245.094
B32: =SUM('[5]2024-Final'!$AE$6:$AE$15) -> 17467.5 | C32: =C31/C63 -> 1680.5998 | D32: =D31/D63 -> 1945.0914 | E32: =E31/E63 -> 2132.1583 | F32: =F31/F63 -> 2392.0965 | G32: =G31/G63 -> 2530.0358 | H32: =H31/H63 -> 2678.691 | I32: =I31/I63 -> 2840.4116 | J32: =J31/J63 -> 3051.7401 | K32: =K31/K63 -> 3206.4144 | W32: =W31/C31*100 -> 116.20725 | X32: =X31/D31*100 -> 113.09868 | Y32: =Y31/E31*100 -> 112.35024 | Z32: =Z31/F31*100 -> 102.55242 | AA32: =AA31/G31*100 -> 99.954766 | AB32: =AB31/H31*100 -> 98.531705 | AC32: =AC31/I31*100 -> 97.809347 | AD32: =AD31/J31*100 -> 93.054506
B33: Composite Goods forecasts using Constant Elasticity of substitution (CES - Armington)
B34: Source: qq_grp | M34: проверка ВВ
C35: 2024 | D35: =C35+1 -> 2025 | E35: =D35+1 -> 2026 | F35: =E35+1 -> 2027 | G35: =F35+1 -> 2028 | H35: =G35+1 -> 2029 | I35: =H35+1 -> 2030 | J35: =I35+1 -> 2031 | K35: =J35+1 -> 2032 | M35: 2024 | N35: =M35+1 -> 2025 | O35: =N35+1 -> 2026 | P35: =O35+1 -> 2027 | Q35: =P35+1 -> 2028 | R35: =Q35+1 -> 2029 | S35: =R35+1 -> 2030 | T35: =S35+1 -> 2031 | U35: =T35+1 -> 2032
B36: Agriculture (qq_a) | C36: 80847.49 | D36: 87049.31 | E36: 90181.73 | F36: 93349.28 | G36: 95724.77 | H36: 98940.23 | I36: 100287.6 | J36: 102496.9 | K36: 107041.7 | M36: =C36-C50+C21 -> 79512.255 | N36: =D36-D50+D21 -> 85374.13 | O36: =E36-E50+E21 -> 89351.113 | P36: =F36-F50+F21 -> 92716.728 | Q36: =G36-G50+G21 -> 95349.774 | R36: =H36-H50+H21 -> 98583.179 | S36: =I36-I50+I21 -> 100053.96 | T36: =J36-J50+J21 -> 102340.45 | U36: =K36-K50+K21 -> 106829.53
B37: Mining (qq_mi) | C37: 12810.96 | D37: 15455.53 | E37: 16329.85 | F37: 17051.63 | G37: 17324.56 | H37: 17725.42 | I37: 18406.72 | J37: 19204.3 | K37: 19876.16 | M37: =C37-C51+C22 -> 14015.025 | N37: =D37-D51+D22 -> 17321.792 | O37: =E37-E51+E22 -> 18429.293 | P37: =F37-F51+F22 -> 19503.197 | Q37: =G37-G51+G22 -> 20182.073 | R37: =H37-H51+H22 -> 20898.155 | S37: =I37-I51+I22 -> 21782.168 | T37: =J37-J51+J22 -> 22937.452 | U37: =K37-K51+K22 -> 23963.533
B38: Manufacturing (qq_m) | C38: 98444.56 | D38: 101025.6 | E38: 107020.6 | F38: 113563.7 | G38: 121788.6 | H38: 131549.2 | I38: 137487.6 | J38: 139672.1 | K38: 141693.3 | M38: =C38-C52+C23 -> 70920.582 | N38: =D38-D52+D23 -> 73405.562 | O38: =E38-E52+E23 -> 78943.289 | P38: =F38-F52+F23 -> 84883.178 | Q38: =G38-G52+G23 -> 92235.683 | R38: =H38-H52+H23 -> 101491.06 | S38: =I38-I52+I23 -> 105332 | T38: =J38-J52+J23 -> 107811.92 | U38: =K38-K52+K23 -> 109770.98
B39: Energy and Water (qq_e) | C39: 9300.321 | D39: 10618.72 | E39: 11304.17 | F39: 14962.7 | G39: 14962.67 | H39: 15107.21 | I39: 15526.6 | J39: 17632.38 | K39: 20286.41 | M39: =C39-C53+C24 -> 10230.371 | N39: =D39-D53+D24 -> 11782.469 | O39: =E39-E53+E24 -> 12629.674 | P39: =F39-F53+F24 -> 16819.266 | Q39: =G39-G53+G24 -> 17009.424 | R39: =H39-H53+H24 -> 17245.419 | S39: =I39-I53+I24 -> 17722.03 | T39: =J39-J53+J24 -> 20625.148 | U39: =K39-K53+K24 -> 23495.087
B40: Construction (qq_c) | C40: 35032.31 | D40: 39031.01 | E40: 43247.05 | F40: 44621.56 | G40: 50029.42 | H40: 52178.8 | I40: 54335.08 | J40: 56795.22 | K40: 58905.25 | M40: =C40-C54+C25 -> 34120.704 | N40: =D40-D54+D25 -> 38091.228 | O40: =E40-E54+E25 -> 42230.181 | P40: =F40-F54+F25 -> 44105.805 | Q40: =G40-G54+G25 -> 48903.052 | R40: =H40-H54+H25 -> 51073.593 | S40: =I40-I54+I25 -> 53169.899 | T40: =J40-J54+J25 -> 55607.177 | U40: =K40-K54+K25 -> 57666.833
