Workbook

Sheet GDP
B1: Var. Name | C1: Наименование индикатора | D1: 1997 | E1: 1998 | F1: 1999 | G1: 2000 | H1: 2001 | I1: 2002 | J1: 2003 | K1: 2004 | L1: 2005 | M1: 2006 | N1: 2007 | O1: 2008 | P1: 2009 | Q1: 2010 | R1: 2011 | S1: 2012 | T1: 2013 | U1: 2014 | V1: 2015 | W1: 2016 | X1: 2017 | Y1: 2018 | Z1: 2019 | AA1: 2020 | AB1: 2021 | AC1: 2022 | AD1: 2023 | AE1: 2024
B2: GDPmp,t | C2: ВВП в рыночных ценах, млн. сомони | D2: 518.4 | E2: 1025.2 | F2: 1345 | G2: 1786.8 | H2: 2563.8 | I2: 3375.3 | J2: 4761.5 | K2: 6167.2 | L2: 7206.6 | M2: 9335.3 | N2: 12804.3 | O2: 17706.9 | P2: 20629 | Q2: 24707.1 | R2: 30071.1 | S2: 36163.1 | T2: 40525.2 | U2: 45606.6 | V2: =V13 -> 50977.4 | W2: =W13 -> 54790.3 | X2: =X13 -> 64434.3 | Y2: =Y13 -> 71059.2 | Z2: =Z13 -> 79109.8 | AA2: =AA13 -> 83958.3 | AB2: =AB13 -> 101076.3 | AC2: =AC13 -> 118181.7 | ... AE2: =AE13 -> 153402.2 | AG2: GDPmp,t = GDPmp,t
B3: gGDPt | C3: Реальный рост ВВП, % | D3: 101.7 | E3: 105.3 | F3: 103.7 | G3: 108.3 | H3: 109.6 | I3: 110.8 | J3: 111.1 | K3: 110.3 | L3: 106.7 | M3: 107 | N3: 107.8 | O3: 107.9 | P3: 103.9 | Q3: 106.5 | R3: 107.4 | S3: 107.5 | T3: 107.4 | U3: 106.7 | V3: =V30 -> 106 | W3: =W30 -> 106.9 | X3: =X30 -> 107.1 | Y3: =Y30 -> 107.56589 | Z3: =Z30 -> 107.42266 | AA3: =AA30 -> 104.44609 | AB3: =AB30 -> 109.41561 | AC3: =AC30 -> 108.03592 | ... AE3: =AE30 -> 108.35354 | AG3: gGDPt = gGDPmp,t
B4: defGDPt | C4: Дефлятор ВВП, % | D4: 165.2 | E4: 187.8 | F4: 123.5 | G4: 124.3 | H4: 130.9 | I4: 118.8 | J4: 127.1 | K4: 117.5 | L4: 109.5161 | M4: 121.06374 | N4: 127.23565 | O4: 128.16376 | P4: 112.12955 | Q4: 112.44802 | R4: 113.32436 | S4: 111.86852 | T4: 104.34106 | U4: 105.47223 | V4: =V64 -> 105.4494 | W4: =W64 -> 100.54218 | X4: =X64 -> 109.80547 | Y4: =Y64 -> 102.52473 | Z4: =Z64 -> 103.63682 | AA4: =AA64 -> 101.6111 | AB4: =AB64 -> 110.02881 | AC4: =AC64 -> 108.22628 | ... AE4: =AE64 -> 106.62268 | AG4: defGDPt = defGDPmp,t
B5: GDP2009mp,t | C5: ВВП в рыночных ценах 2009 года | D5: 8495.6919 | E5: 8945.9636 | F5: 9276.9643 | G5: 10046.952 | H5: 11011.46 | I5: 12200.697 | J5: 13554.975 | K5: 14951.137 | L5: 15952.863 | M5: 17069.564 | N5: 18400.99 | O5: 19854.668 | P5: 20629 | Q5: 21969.885 | R5: 23595.656 | S5: 25365.331 | T5: 27242.365 | U5: 29067.604 | V5: =V47 -> 30811.66 | W5: =W47 -> 32937.664 | X5: =X47 -> 35276.239 | Y5: =Y47 -> 37945.199 | Z5: =Z47 -> 40761.741 | AA5: =AA47 -> 42574.045 | AB5: =AB47 -> 46582.649 | AC5: =AC47 -> 50325.994 | ... AE5: =AE47 -> 59066.766 | AG5: GDP2009mp,t = GDP2009mp,t
B6: GDPPCUS,t | C6: ВВП на душу населения, долл. США | D6: 158.7 | E6: 221.8 | F6: 178.2 | G6: 158 | H6: 171.2 | I6: 190 | J6: 236.7 | K6: 309.7 | L6: 337.5 | M6: 410 | N6: 529 | O6: 719.8 | P6: 678.8 | Q6: 750.4 | R6: 845.64821 | S6: 961.47143 | T6: 1053.5032 | U6: 1119.3135 | V6: =V7/Assumptions!V12 -> 978.4573 | W6: =W7/Assumptions!W12 -> 808.65537 | X6: =X7/Assumptions!X12 -> 852.82525 | Y6: =Y7/Assumptions!Y12 -> 860.01836 | Z6: =Z7/Assumptions!Z12 -> 900.31584 | AA6: =AA7/Assumptions!AA12 -> 864.39922 | AB6: =AB7/Assumptions!AB12 -> 911.84819 | AC6: =AC7/Assumptions!AC12 -> 1073.7361 | ... AE6: =AE7/Assumptions!AE12 -> 1368.3056 | AG6: GDPPCUS,t = GDPmp,t/erUSDt/POPt
C7: ВВП на душу населения, в сомони | D7: 89.2 | E7: 172.9 | F7: 222.1 | G7: 288.4 | H7: 405.8 | I7: 525 | J7: 727.7 | K7: 926.2 | L7: 1062.8 | M7: 1352.2 | N7: 1821.1 | O7: 2468.3 | P7: 2812.7 | Q7: 3285.8 | R7: 3898.1 | S7: 4579.2 | T7: 5019.1 | U7: 5523.7 | V7: 6031.7 | W7: 6336.3 | X7: 7291.4 | Y7: 7870.2 | Z7: 8580.1 | AA7: 8922.2423 | AB7: 10312 | AC7: 11838.8 | AD7: =AD2/Assumptions!AD63 -> 13039.566 | AE7: =AE2/Assumptions!AE63 -> 14775.785
B8: =[1]Monetary!B15 -> ИПЦ, в том числе: (дек/дек), факт | C8: =[1]Monetary!C15 -> Inflation (dec/dec), fact, incl. | G8: 160.62781 | H8: 112.47905 | I8: 114.50567 | J8: 113.65265 | K8: 105.62006 | L8: 106.89379 | M8: 111.9 | N8: 121.5 | O8: 120.4 | P8: 106.4 | Q8: 106.5 | R8: 112.5 | S8: 105.8 | T8: 103.7 | U8: 107.4 | V8: =Monetary!V15 -> 105.1 | W8: =Monetary!W15 -> 106.1 | X8: =Monetary!X15 -> 106.7411 | Y8: =Monetary!Y15 -> 105.37889 | Z8: =Monetary!Z15 -> 108 | AA8: =Monetary!AA15 -> 109.4 | AB8: =Monetary!AB15 -> 108 | AC8: =Monetary!AC15 -> 104.2 | ... AE8: =Monetary!AE15 -> 103.6
C10: Среднегодовая численность населения , тысяч человек | D10: 5814.4 | E10: 5930.5 | F10: 6056 | G10: 6196.5 | H10: 6317.9 | I10: 6429.2 | J10: 6543 | K10: 6658.9 | L10: 6780.6 | M10: 6903.9 | N10: 7031.2 | O10: 7173.8 | P10: 7334.1 | Q10: 7519.3 | R10: 7714.2 | S10: 7897.3 | T10: 8074.3 | U10: 8256.6 | V10: 8451.6 | W10: 8647 | X10: 8837 | Y10: 9028.9 | Z10: 9220.2 | AA10: 9410 | AB10: 9801.812 | AC10: 9982.6 | AD10: 10183.3 | AE10: 10382.1
C13: ВВП в рыночных ценах, млн. сомони | D13: 518.4 | E13: 1025.2 | F13: 1345 | G13: 1786.8 | H13: 2563.8 | I13: 3375.3 | J13: 4761.5 | K13: 6167.2 | L13: 7206.6 | M13: 9335.3 | N13: 12804.3 | O13: 17706.9 | P13: 20629 | Q13: 24707.1 | R13: 30071.1 | S13: 36163.1 | T13: 40525.2 | U13: 45606.6 | V13: =V14+V15 -> 50977.4 | W13: =W14+W15 -> 54790.3 | X13: =X14+X15 -> 64434.3 | Y13: =Y14+Y15 -> 71059.2 | Z13: =Z14+Z15 -> 79109.8 | AA13: =AA14+AA15 -> 83958.3 | AB13: =AB14+AB15 -> 101076.3 | AC13: =AC14+AC15 -> 118181.7 | ... AE13: =AE14+AE15 -> 153402.2 | AG13: GDPmp,t = NITt+GDPfc,t
C14: Чистые косвенные налоги | D14: 49.8 | E14: 77.8 | F14: 98 | G14: 149.7 | H14: 230.3 | I14: 332.8 | J14: 508.4 | K14: 679.7 | L14: 831.2 | M14: 1059.7 | N14: 1603.5 | O14: 2235.9 | P14: 2286.6 | Q14: 2781.7 | R14: 3727.5 | S14: 4455.8 | T14: 5159.5 | U14: 6361.6 | V14: =5453.6-83.4 -> 5370.2 | W14: =5755.1-95 -> 5660.1 | X14: =6467.9-130.8 -> 6337.1 | Y14: =7131.5-112.4 -> 7019.1 | Z14: =7827.1-134.4 -> 7692.7 | AA14: =7718-175.3 -> 7542.7 | AB14: =9880.8-184.3 -> 9696.5 | AC14: 10687.4 | AD14: =13443.4-246.2 -> 13197.2 | AE14: 14425.9 | AG14: NITt = NITt
C15: ВВП в основных ценах | D15: 468.6 | E15: 947.4 | F15: 1247 | G15: 1637.1 | H15: 2333.5 | I15: 3042.5 | J15: 4253.1 | K15: 5487.5 | L15: 6375.4 | M15: 8275.6 | N15: 11200.8 | O15: 15471 | P15: 18342 | Q15: 21925.4 | R15: 26343.6 | S15: 31707.3 | T15: 35365.7 | U15: 39245 | V15: =SUM(V16:V22) -> 45607.2 | W15: =SUM(W16:W22) -> 49130.2 | X15: =SUM(X16:X22) -> 58097.2 | Y15: =SUM(Y16:Y22) -> 64040.1 | Z15: =SUM(Z16:Z22) -> 71417.1 | AA15: =SUM(AA16:AA22) -> 76415.6 | AB15: =SUM(AB16:AB22) -> 91379.8 | AC15: =SUM(AC16:AC22) -> 107494.3 | ... AE15: =SUM(AE16:AE22) -> 138976.3 | AG15: GDPfc,t = (VAAB,t+VACDE,t+VAF,t+VAGoodsO,t+VAGH,t+VAI,t+VAOther,t)
C16: Сельское хозяйство и рыболовство | D16: 165.9 | E16: 257.4 | F16: 341.4 | G16: 448.9 | H16: 610.4 | I16: 750.5 | J16: 1151.9 | K16: 1185.6 | L16: 1527.2 | M16: 2002.6 | N16: 2488.3 | O16: 3517.9 | P16: 3827 | Q16: 4839.3 | R16: 7167.6 | S16: 8435.7 | T16: 8279.6 | U16: 10692.6 | V16: 11006.4 | W16: =11399.2+28.4 -> 11427.6 | X16: =13069.4 -> 13069.4 | Y16: 14049.8 | Z16: 16507.9 | AA16: 19050.5 | AB16: 22690.7 | AC16: 27104.8 | AD16: 30352.5 | AE16: 34954.8 | AG16: VAAB,t = VAAB,t-1·gVAAB,t·defVAAB,t/10000
C17: Промышленность | D17: 114 | E17: 206.1 | F17: 291.6 | G17: 592.3 | H17: 858 | I17: 1117.2 | J17: 1440.2 | K17: 1644.4 | L17: 1645.1 | M17: 1987 | N17: 2349.4 | O17: 2515.8 | P17: 2957.4 | Q17: 3642.7 | R17: 4368.9 | S17: 4947.8 | T17: 5103.1 | U17: 5510.9 | V17: =811.2+5471.4+1443.7 -> 7726.3 | W17: =1550+6233.9+1483 -> 9266.9 | X17: =2463.1+8251+2074.6+51.2 -> 12839.9 | Y17: =2528.5+9400.4+3025.7+76.9 -> 15031.5 | Z17: =2642.3+10626.3+3505.5+99.7 -> 16873.8 | AA17: =2410.7+13119.2+3890.1+91.3 -> 19511.3 | AB17: =4669.7+15160.3+4189.5+119.5 -> 24139 | AC17: =5027.2+17893.5+4728.3+113 -> 27762 | AD17: =5407.1+19402.9+4817.5+115.2 -> 29742.7 | AE17: 25921 | AG17: VACDE,t = VACDE,t
C18: Строительство | D18: 14.3 | E18: 39.5 | F18: 73 | G18: 38 | H18: 69.7 | I18: 68.9 | J18: 136.6 | K18: 262.3 | L18: 327.1 | M18: 567.5 | N18: 1034.6 | O18: 1832.6 | P18: 2098.4 | Q18: 2528.2 | R18: 2387.5 | S18: 3023.5 | T18: 4200.8 | U18: 4660 | V18: 7679.3 | W18: 8382.9 | X18: 7680.4 | Y18: 9411.7 | Z18: 9281.6 | AA18: 8863.7 | AB18: 11417.3 | AC18: 13250.1 | AD18: 14923.6 | AE18: 12451.7 | AG18: VAF,t = 0,58·InvNAF,t
C19: Прочие товары | D19: 6 | E19: 10.2 | F19: 4.8 | G19: 5.9 | H19: 7.5 | I19: 13.4 | J19: 14.5 | K19: 24.2 | L19: 20.9 | M19: 20.8 | N19: 29.1 | O19: 34.9 | P19: 29.5 | Q19: 13.8 | AG19: VAGoodsO,t = VAGoodsO,t-1·VACDE,t/VACDE,t-1
C20: Розничная и оптовая торговля | D20: 108.6 | E20: 231.8 | F20: 270 | G20: 193.9 | H20: 274.9 | I20: 394.7 | J20: 544.1 | K20: 1017.5 | L20: 1191.6 | M20: 1593.8 | N20: 2119.7 | O20: 3577.3 | P20: 4345.8 | Q20: 4999.9 | R20: 3949.2 | S20: 5032.7 | T20: 5823.3 | U20: 6419.6 | V20: =4102.8+1331.1 -> 5433.9 | W20: =4625.3+1485.7 -> 6111 | X20: =6353.5 -> 6353.5 | Y20: =7359.6+1699.1 -> 9058.7 | Z20: =8764.1+1938.6 -> 10702.7 | AA20: =8978.4+1744.5 -> 10722.9 | AB20: =10956+2405.8 -> 13361.8 | AC20: =13042+3060.8 -> 16102.8 | AD20: =13851.7+3687.1 -> 17538.8 | AE20: 23332.7 | AG20: VAGH,t = RETt·0,447-750
C21: Транспорт и связь | D21: 15.1 | E21: 42.7 | F21: 99 | G21: 85 | H21: 127.6 | I21: 185.7 | J21: 260.2 | K21: 409 | L21: 533.3 | M21: 673.1 | N21: 1221.9 | O21: 1782.2 | P21: 2264.9 | Q21: 2758 | R21: 4356.3 | S21: 5535.2 | T21: 6172.2 | U21: 6523.8 | V21: 4859.2 | W21: 4875.2 | X21: 4870 | Y21: 4277.6 | Z21: 4829.2 | AA21: 3818.8 | AB21: =3735+1473.6 -> 5208.6 | AC21: =4401.1+1622.4 -> 6023.5 | AD21: =5272.4+1967.1 -> 7239.5 | AE21: 14321.1 | AG21: VAI,t = VAI,t-1+(RETt+SERt-RETt-1-SERt-1)·0,24
C22: Прочие услуги (остатком) | D22: 44.7 | E22: 159.7 | F22: 167.2 | G22: 273.2 | H22: 385.6 | I22: 512.2 | J22: 706.1 | K22: 945 | L22: 1130.7 | M22: 1431.2 | N22: 1958.1 | O22: 2214.2 | P22: 2823.8 | Q22: 3143.4 | R22: 4114.1 | S22: 4732.4 | T22: 5786.7 | U22: 5438.1 | V22: =2197.5+694+1492.8+2522.7+1152.2+1619.3-776.4 -> 8902.1 | W22: =1091.7+765.3+1708.6+2871.3+1292.1+1644.1-306.5 -> 9066.6 | X22: =1697.8+1533.8+1994.4+740.6+237.2+57.7+1874.8+3022.7+1359.1+296.7+736.4+275-542.2 -> 13284 | Y22: =1366.8+2078.9+791.4+237.7+60.1+2005.6+3256.3+1440.9+328.2+923.2+286-564.3 -> 12210.8 | Z22: =1424.1+1925.1+852.7+288.9+81.5+2139.9+3752.6+1651.2+366+972.3+347.6-580 -> 13221.9 | AA22: =1492.9+2157.1+1103.3+269.5+97.4+2247.4+4086.8+1842.9+408+888+462.1-607 -> 14448.4 | AB22: =2055.7+1228.9+568.4+207.9+2411.3+4778.7+2072.3+525.4+844.2+471.6-602 -> 14562.4 | AC22: =4066.6+1323+474.1+242.5+2620.7+5058.3+2146.1+571.5+1142.2+541.1-935 -> 17251.1 | AD22: =4831.1+1339.3+464.6+320.1+3473.8+6075.3+2451.3+559.2+1173.7+619.5-1520.3 -> 19787.6 | AE22: 27995 | AG22: VAOther,t = VAOther,t-1·(SERt/SERt-1)
C23: Справочно:
C24: Товары | D24: 300.2 | E24: 513.2 | F24: 710.8 | G24: 1085.1 | H24: 1545.6 | I24: 1950 | J24: 2743.2 | K24: 3116.5 | L24: 3520.3 | M24: 4577.9 | N24: 5901.4 | O24: 7901.2 | P24: 8912.3 | Q24: 11024 | R24: 13924 | S24: 16407 | T24: 17583.5 | U24: 20863.5 | V24: =V16+V17+V18+V19 -> 26412 | W24: =W16+W17+W18+W19 -> 29077.4 | X24: =X16+X17+X18+X19 -> 33589.7 | Y24: =Y16+Y17+Y18+Y19 -> 38493 | Z24: =Z16+Z17+Z18+Z19 -> 42663.3 | AA24: =AA16+AA17+AA18+AA19 -> 47425.5 | AB24: =AB16+AB17+AB18+AB19 -> 58247 | AC24: =AC16+AC17+AC18+AC19 -> 68116.9 | ... AE24: =AE16+AE17+AE18+AE19 -> 73327.5 | AG24: VAGoods,t = VAAB,t+VACDE,t+VAF,t+VAGoodsO,t
C25: Услуги | D25: 168.4 | E25: 434.2 | F25: 536.2 | G25: 552 | H25: 787.9 | I25: 1092.5 | J25: 1509.9 | K25: 2371 | L25: 2855.1 | M25: 3697.7 | N25: 5299.4 | O25: 7744.3 | P25: 9429.7 | Q25: 10901.3 | R25: 12419.6 | S25: 15300.3 | T25: 17782.2 | U25: 18381.5 | V25: =V20+V21+V22 -> 19195.2 | W25: =W20+W21+W22 -> 20052.8 | X25: =X20+X21+X22 -> 24507.5 | Y25: =Y20+Y21+Y22 -> 25547.1 | Z25: =Z15-Z24 -> 28753.8 | AA25: =AA15-AA24 -> 28990.1 | AB25: =AB15-AB24 -> 33132.8 | AC25: =AC15-AC24 -> 39377.4 | AD25: =AD15-AD24 -> 44565.9 | AE25: =AE15-AE24 -> 65648.8 | AG25: VAServces,t = GDPfc,t-VAGoods,t
V27: 5370.8 | W27: =W13-V13 -> 3812.9 | X27: =X13-W13 -> 9644 | Y27: =Y13-X13 -> 6624.9 | Z27: =Z13-Y13 -> 8050.6 | AA27: =AA13-Z13 -> 4848.5 | AB27: =AB13-AA13 -> 17118 | AC27: =AC13-AB13 -> 17105.4 | AD27: =AD13-AC13 -> 14600.2 | AE27: =AE13-AD13 -> 20620.3
C30: ВВП в рыночных ценах, % | D30: 101.7 | E30: 105.3 | F30: 103.7 | G30: 108.3 | H30: 109.6 | I30: 110.8 | J30: 111.1 | K30: 110.3 | L30: 106.7 | M30: 107 | N30: 107.8 | O30: 107.9 | P30: 103.9 | Q30: 106.5 | R30: 107.4 | S30: 107.5 | T30: 107.4 | U30: 106.7 | V30: 106 | W30: =(V14*W31+W32*V15)/(V14+V15) -> 106.9 | X30: =(W14*X31+X32*W15)/(W14+W15) -> 107.1 | Y30: =(X14*Y31+Y32*X15)/(X14+X15) -> 107.56589 | Z30: =(Y14*Z31+Z32*Y15)/(Y14+Y15) -> 107.42266 | AA30: =(Z14*AA31+AA32*Z15)/(Z14+Z15) -> 104.44609 | AB30: =(AA14*AB31+AB32*AA15)/(AA14+AA15) -> 109.41561 | AC30: =(AB14*AC31+AC32*AB15)/(AB14+AB15) -> 108.03592 | AD30: =(AC14*AD31+AD32*AC15)/(AC14+AC15) -> 108.31977 | AE30: =(AD14*AE31+AE32*AD15)/(AD14+AD15) -> 108.35354 | AG30: gGDPmp,t = (NITt-1·gNITt+gGDPfc,t·GDPfc,t-1)/(NITt-1+GDPfc,t-1)
C31: Чистые косвенные налоги | H31: 110 | I31: 111.8 | J31: 111.9 | K31: 111 | L31: 107.3 | M31: 107.4 | N31: 108.3 | O31: 107.9 | P31: 102 | Q31: 106.5 | R31: 107.4 | S31: 107.5 | T31: 107.4 | U31: 106.7 | V31: 106 | W31: 106.9 | X31: 107.1 | Y31: 104.8 | Z31: 103 | AA31: 100 | AB31: 100 | AC31: 100 | AD31: 100 | AE31: =(AE32/100)^1*100 -> 108.35354 | AG31: gNITt = (gGDPfc,t/100)^1,00·100
C32: ВВП в основных ценах | H32: 109.60139 | I32: 110.72988 | J32: 111.0332 | K32: 110.16366 | L32: 106.66415 | M32: 106.90176 | N32: 107.66178 | O32: 107.89471 | P32: 103.9 | Q32: 106.5 | R32: 107.4 | S32: 107.5 | T32: 107.4 | U32: 106.7 | V32: 106 | W32: 106.9 | X32: 107.1 | Y32: =SUMPRODUCT(Y33:Y39,X16:X22)/SUM(X16:X22) -> 107.86758 | Z32: =SUMPRODUCT(Z33:Z39,Y16:Y22)/SUM(Y16:Y22) -> 107.9074 | AA32: =SUMPRODUCT(AA33:AA39,Z16:Z22)/SUM(Z16:Z22) -> 104.925 | AB32: =SUMPRODUCT(AB33:AB39,AA16:AA22)/SUM(AA16:AA22) -> 110.34499 | AC32: =SUMPRODUCT(AC33:AC39,AB16:AB22)/SUM(AB16:AB22) -> 108.88863 | AD32: =SUMPRODUCT(AD33:AD39,AC16:AC22)/SUM(AC16:AC22) -> 109.14694 | AE32: =SUMPRODUCT(AE33:AE39,AD16:AD22)/SUM(AD16:AD22) -> 108.35354 | AG32: gGDPfc,t = (gVAAB,t·VAAB,t-1+gVACDE,t·VACDE,t-1+gVAF,t·VAF,t-1+gVAGoodsO,t·VAGoodsO,t-1+gVAGH,t·VAGH,t-1+gVAI,t·VAI,t-1+gVAOther,t·VAOther,t-1)/(VAAB,t-1+VACDE,t-1+VAF,t-1+VAGoodsO,t-1+VAGH,t-1+VAI,t-1+VAOther,t-1)
C33: Сельское хозяйство и рыболовство | L33: 101.4 | M33: 105.7 | N33: 103.5 | O33: 106.1 | P33: 110.5 | Q33: 106.8 | R33: 107.9 | S33: 110.4 | T33: 107.6 | U33: 104.5 | V33: =Agriculture!V3 -> 103.2 | W33: =Agriculture!W3 -> 105.2 | X33: =Agriculture!X3 -> 106.8 | Y33: =Agriculture!Y3 -> 107 | Z33: =Agriculture!Z3 -> 107 | AA33: =Agriculture!AA3 -> 107.9 | AB33: =Agriculture!AB3 -> 99.7 | AC33: =Agriculture!AC3 -> 108 | AD33: 112.2 | AE33: =Agriculture!AE3 -> 110.6 | AG33: gVAAB,t = (1+gVAAB,t/100)·100
C34: Промышленность | L34: 106.4 | M34: 105.5 | N34: 109.9 | O34: 96.5 | P34: 93.5 | Q34: 109.2 | R34: 105.7 | S34: 110.8 | T34: 103.8 | U34: 105 | V34: =Industry!V58 -> 111.3 | W34: =Industry!W58 -> 116 | X34: =Industry!X58 -> 121.3 | Y34: =Industry!Y58 -> 110.6 | Z34: =Industry!Z58 -> 113.2 | AA34: =Industry!AA58 -> 108.8 | AB34: =Industry!AB58 -> 120.8 | AC34: =Industry!AC58 -> 115.4 | AD34: 109.7 | AE34: =Industry!AE58 -> 120 | AG34: gVACDE,t = gVACDE,t
C35: Строительство | L35: 116.4 | M35: 107.2 | N35: 110.4 | O35: 121.2 | P35: 84.5 | Q35: 109.52934 | R35: 105.5 | S35: 75.6 | T35: 117.2 | U35: 125.3 | V35: =OEA!V39 -> 121.2 | W35: =OEA!W39 -> 120.3 | X35: =OEA!X39 -> 104.1 | Y35: =OEA!Y39 -> 110.2 | Z35: =OEA!Z39 -> 104.6 | AA35: =OEA!AA39 -> 104 | AB35: 132.1 | AC35: =OEA!AC39 -> 111.4 | AD35: =OEA!AD39 -> 112.3 | AE35: =OEA!AE39 -> 79.690833 | AG35: gVAF,t = gCONSTRt
C36: Прочие товары | L36: 100 | M36: 100 | N36: 110.2 | O36: 100 | P36: 100 | Q36: 109.2 | R36: 105.7 | S36: 110.8 | T36: 103.8 | U36: 105 | V36: =V34 -> 111.3 | W36: =W34 -> 116 | X36: =X34 -> 121.3 | Y36: =Y34 -> 110.6 | Z36: =Z34 -> 113.2 | AA36: =AA34 -> 108.8 | AB36: =AB34 -> 120.8 | AC36: =AC34 -> 115.4 | ... AE36: =AE34 -> 120 | AG36: gVAGoodsO,t = gVACDE,t
C37: Розничная и оптовая торговля | L37: 108.9 | M37: 110.8 | N37: 105.3 | O37: 112.4 | P37: 112.5 | Q37: 107.5 | R37: 109.1 | S37: 115.9 | T37: 118.8 | U37: 106.7 | V37: 105.6 | W37: 106 | X37: 106.6 | Y37: 112.2 | Z37: 109.6 | AA37: 94.1 | AB37: 110.2 | AC37: =Household!AC4 -> 111.2 | AD37: 98.6 | AE37: =Household!AE4 -> 113.6 | AG37: gVAGH,t = VAGH,t/VAGH,t-1/defVAGH,t·10000
C38: Транспорт и связь | L38: 130 | M38: 118.1 | N38: 183.8 | O38: 143.3 | P38: 153.5 | Q38: 119.39626 | R38: 150.89372 | S38: 124.05492 | T38: 110.30013 | U38: 105.11255 | V38: 102.1 | W38: =(W21/V21)^0.4*100 -> 100.13158 | X38: =(X21/W21)^3*100 -> 99.680354 | Y38: 93.3 | Z38: 115.7 | AA38: 79.4 | AB38: 95.3 | AC38: 96 | AD38: 121.7 | AE38: =(AE21/AD21)^0.82*100 -> 174.96033 | AG38: gVAI,t = (VAI,t/VAI,t-1)^0,9·100
C39: Прочие услуги (остатком) | L39: 97.001641 | M39: 96.376863 | N39: 78.00434 | O39: 92.627551 | P39: 73.250437 | Q39: 93 | R39: 97 | S39: 95 | T39: 95 | U39: 102 | V39: 97 | W39: 97 | X39: 101 | Y39: 108 | Z39: 101 | AA39: 115 | AB39: 101 | AC39: 100 | AD39: 106.5 | AE39: 80 | AG39: gVAOther,t = gVAOther,t
C40: Справочно:
C41: Товары | H41: 112.4 | I41: 111 | J41: 111.5 | K41: 105.3 | L41: 105.8 | M41: 105.2 | N41: 104.4 | O41: 103.4 | P41: 99 | Q41: 106.1 | R41: 106.9 | S41: 103.6 | T41: 105.9 | U41: 112.2 | V41: 109.7 | W41: 114.1 | X41: 107.4 | Y41: =SUMPRODUCT(Y33:Y36,X16:X19)/SUM(X16:X19) -> 109.10782 | Z41: =SUMPRODUCT(Z33:Z36,Y16:Y19)/SUM(Y16:Y19) -> 108.83429 | AA41: =SUMPRODUCT(AA33:AA36,Z16:Z19)/SUM(Z16:Z19) -> 107.4075 | AB41: =SUMPRODUCT(AB33:AB36,AA16:AA19)/SUM(AA16:AA19) -> 114.43621 | AC41: =SUMPRODUCT(AC33:AC36,AB16:AB19)/SUM(AB16:AB19) -> 111.7332 | AD41: =SUMPRODUCT(AD33:AD36,AC16:AC19)/SUM(AC16:AC19) -> 111.20054 | AE41: =SUMPRODUCT(AE33:AE36,AD16:AD19)/SUM(AD16:AD19) -> 108.17801 | AG41: gVAGoods,t = (gVAAB,t·VAAB,t-1+gVACDE,t·VACDE,t-1+gVAF,t·VAF,t-1+gVAGoodsO,t·VAGoodsO,t-1)/(VAAB,t-1+VACDE,t-1+VAF,t-1+VAGoodsO,t-1)
C42: Услуги | H42: 104.1 | I42: 110.2 | J42: 110.2 | K42: 119 | L42: 107.8 | M42: 109 | N42: 111.7 | O42: 112.9 | P42: 109.7 | Q42: 106.9 | R42: 107.7 | S42: 112 | T42: 109.1 | U42: 101.2 | V42: 101.7 | W42: 98.9 | X42: 106.6 | Y42: =(Y37*X20+X21*Y38+Y39*X22)/X25 -> 106.16773 | Z42: =(Z37*Y20+Y21*Z38+Z39*Y22)/Y25 -> 106.51082 | AA42: =(AA37*Z20+Z21*AA38+AA39*Z22)/Z25 -> 101.24161 | AB42: =(AB37*AA20+AA21*AB38+AB39*AA22)/AA25 -> 103.65206 | AC42: =(AC37*AB20+AB21*AC38+AC39*AB22)/AB25 -> 103.88792 | AD42: =(AD37*AC20+AC21*AD38+AD39*AC22)/AC25 -> 105.59453 | AE42: =(AE37*AD20+AD21*AE38+AE39*AD22)/AD25 -> 108.64901 | AG42: gVAServces,t = (gVAGH,t·VAGH,t-1+VAI,t-1·gVAI,t+gVAOther,t·VAOther,t-1)/VAServces,t-1
C46: В постоянных ценах 2009 года, млн. сомони
C47: ВВП в рыночных ценах 2009 года | G47: 10046.952 | H47: 11011.46 | I47: 12200.697 | J47: 13554.975 | K47: 14951.137 | L47: 15952.863 | M47: 17069.564 | N47: 18400.99 | O47: 19854.668 | P47: 20629 | Q47: 21969.885 | R47: 23595.656 | S47: 25365.331 | T47: 27242.365 | U47: 29067.604 | V47: 30811.66 | W47: =V47*W30/100 -> 32937.664 | X47: =W47*X30/100 -> 35276.239 | Y47: =X47*Y30/100 -> 37945.199 | Z47: =Y47*Z30/100 -> 40761.741 | AA47: =Z47*AA30/100 -> 42574.045 | AB47: =AA47*AB30/100 -> 46582.649 | AC47: =AB47*AC30/100 -> 50325.994 | AD47: =AC47*AD30/100 -> 54513 | AE47: =AD47*AE30/100 -> 59066.766 | AG47: GDP2009mp,t = GDP2009mp,t-1·gGDPmp,t/100
C48: Чистые косвенные налоги | H48: 1198.9946 | I48: 1340.4759 | J48: 1499.9926 | K48: 1664.9918 | L48: 1786.5362 | M48: 1918.7398 | N48: 2077.9952 | O48: 2242.1569 | P48: 2287 | Q48: 2435.655 | R48: 2615.8935 | S48: 2812.0855 | T48: 3020.1798 | U48: 3222.5319 | V48: 3415.8838 | W48: =V48*W31/100 -> 3651.5797 | X48: =W48*X31/100 -> 3910.8419 | Y48: =X48*Y31/100 -> 4098.5623 | Z48: =Y48*Z31/100 -> 4221.5192 | AA48: =Z48*AA31/100 -> 4221.5192 | AB48: =AA48*AB31/100 -> 4221.5192 | AC48: =AB48*AC31/100 -> 4221.5192 | AD48: =AC48*AD31/100 -> 4221.5192 | AE48: =AD48*AE31/100 -> 4574.1655 | AG48: NIT2009t = NIT2009t-1·gNITt/100
C49: ВВП в основных ценах | K49: 13293.54 | L49: 14180.584 | M49: 15155.605 | N49: 16320.036 | O49: 17598.221 | P49: 18342 | Q49: 19534.23 | R49: 20979.763 | S49: 22553.245 | T49: 24222.185 | U49: 25845.072 | V49: 27395.776 | W49: =V49*W32/100 -> 29286.085 | X49: =W49*X32/100 -> 31365.397 | Y49: =X49*Y32/100 -> 33833.095 | Z49: =Y49*Z32/100 -> 36508.414 | AA49: =Z49*AA32/100 -> 38306.454 | AB49: =AA49*AB32/100 -> 42269.251 | AC49: =AB49*AC32/100 -> 46026.408 | AD49: =AC49*AD32/100 -> 50236.418 | AE49: =AD49*AE32/100 -> 54432.938 | AG49: GDP2009fc,t = GDP2009fc,t-1·gGDPfc,t/100
C50: Сельское хозяйство и рыболовство | K50: 4438.6239 | L50: 4722.6959 | M50: 4921.0491 | N50: 4492.9178 | O50: 4093.0481 | P50: 3827 | Q50: 4087.236 | R50: 4410.1276 | S50: 4868.7809 | T50: 5238.8083 | U50: 5474.5546 | V50: 5649.7404 | W50: =V50*W33/100 -> 5943.5269 | X50: =W50*X33/100 -> 6347.6867 | Y50: =X50*Y33/100 -> 6792.0248 | Z50: =Y50*Z33/100 -> 7267.4665 | AA50: =Z50*AA33/100 -> 7841.5964 | AB50: =AA50*AB33/100 -> 7818.0716 | AC50: =AB50*AC33/100 -> 8443.5173 | AD50: =AC50*AD33/100 -> 9473.6264 | AE50: =AD50*AE33/100 -> 10477.831 | AG50: VA2009AB,t = VA2009AB,t-1·gVAAB,t/100
C51: Промышленность | K51: 2181.227 | L51: 2211.7641 | M51: 2331.1994 | N51: 2482.7274 | O51: 2676.3801 | P51: 2957.4 | Q51: 3229.4808 | R51: 3413.5612 | S51: 3782.2258 | T51: 3925.9504 | U51: 4122.2479 | V51: 4588.0619 | W51: =V51*W34/100 -> 5322.1518 | X51: =W51*X34/100 -> 6455.7702 | Y51: =X51*Y34/100 -> 7140.0818 | Z51: =Y51*Z34/100 -> 8082.5726 | AA51: =Z51*AA34/100 -> 8793.839 | AB51: =AA51*AB34/100 -> 10622.958 | AC51: =AB51*AC34/100 -> 12258.893 | AD51: =AC51*AD34/100 -> 13448.006 | AE51: =AD51*AE34/100 -> 16137.607 | AG51: VA2009CDE,t = VA2009CDE,t-1·gVACDE,t/100
C52: Строительство | K52: 1487.3463 | L52: 1731.2711 | M52: 1855.9227 | N52: 2048.9386 | O52: 2483.3136 | P52: 2098.4 | Q52: 2298.3636 | R52: 2424.7736 | S52: 1833.1289 | T52: 2148.427 | U52: 2691.9791 | V52: 3262.6786 | W52: =V52*W35/100 -> 3925.0024 | X52: =W52*X35/100 -> 4085.9275 | Y52: =X52*Y35/100 -> 4502.6921 | Z52: =Y52*Z35/100 -> 4709.8159 | AA52: =Z52*AA35/100 -> 4898.2086 | AB52: =AA52*AB35/100 -> 6470.5335 | AC52: =AB52*AC35/100 -> 7208.1744 | AD52: =AC52*AD35/100 -> 8094.7798 | AE52: =AD52*AE35/100 -> 6450.7975 | AG52: VA2009F,t = VA2009F,t-1·gVAF,t/100
C53: Прочие товары | AG53: VA2009GoodsO,t = VA2009GoodsO,t-1·gVAGoodsO,t/100
C54: Розничная и оптовая торговля | K54: 2430.5119 | L54: 2646.8275 | M54: 3094.1414 | N54: 3449.9676 | O54: 3936.413 | P54: 4345.8 | Q54: 4671.735 | R54: 5096.8629 | S54: 5907.2641 | T54: 7017.8297 | U54: 7488.0243 | V54: 7907.3537 | W54: =V54*W37/100 -> 8381.7949 | X54: =W54*X37/100 -> 8934.9934 | Y54: =X54*Y37/100 -> 10025.063 | Z54: =Y54*Z37/100 -> 10987.469 | AA54: =Z54*AA37/100 -> 10339.208 | AB54: =AA54*AB37/100 -> 11393.807 | AC54: =AB54*AC37/100 -> 12669.914 | AD54: =AC54*AD37/100 -> 12492.535 | AE54: =AD54*AE37/100 -> 14191.519 | AG54: VA2009GH,t = VA2009GH,t-1·gVAGH,t/100
C55: Транспорт и связь | K55: 364.88474 | L55: 474.35017 | M55: 560.20755 | N55: 1029.6615 | O55: 1475.5049 | P55: 2264.9 | Q55: 2704.2058 | R55: 4080.4767 | S55: 5062.032 | T55: 5583.4277 | U55: 5868.8834 | V55: 5992.1299 | W55: =V55*W38/100 -> 6000.0143 | X55: =W55*X38/100 -> 5980.8355 | Y55: =X55*Y38/100 -> 5580.1195 | Z55: =Y55*Z38/100 -> 6456.1983 | AA55: =Z55*AA38/100 -> 5126.2214 | AB55: =AA55*AB38/100 -> 4885.289 | AC55: =AB55*AC38/100 -> 4689.8775 | AD55: =AC55*AD38/100 -> 5707.5809 | AE55: =AD55*AE38/100 -> 9986.0026 | AG55: VA2009I,t = VA2009I,t-1·gVAI,t/100
C56: Прочие услуги (остатком) | K56: 5707.0661 | L56: 5535.9477 | M56: 5335.3727 | N56: 4161.8223 | O56: 3854.9941 | P56: 2823.8 | Q56: 2626.134 | R56: 2547.35 | S56: 2419.9825 | T56: 2298.9834 | U56: 2344.963 | V56: 2274.6141 | W56: =V56*W39/100 -> 2206.3757 | X56: =W56*X39/100 -> 2228.4395 | Y56: =X56*Y39/100 -> 2406.7146 | Z56: =Y56*Z39/100 -> 2430.7818 | AA56: =Z56*AA39/100 -> 2795.399 | AB56: =AA56*AB39/100 -> 2823.353 | AC56: =AB56*AC39/100 -> 2823.353 | AD56: =AC56*AD39/100 -> 3006.871 | AE56: =AD56*AE39/100 -> 2405.4968 | AG56: VA2009Other,t = VA2009Other,t-1·gVAOther,t/100
C57: Справочно:
C58: Товары | H58: 5749.1805 | I58: 6381.5903 | J58: 7115.4732 | K58: 7492.5933 | L58: 7927.1637 | M58: 8339.3762 | N58: 8706.3087 | O58: 9002.3232 | P58: 8912.3 | Q58: 9280.3927 | R58: 9920.7398 | S58: 10277.886 | T58: 10884.282 | U58: 12212.164 | V58: 13396.744 | W58: =V58*W41/100 -> 15285.685 | X58: =W58*X41/100 -> 16416.826 | Y58: =X58*Y41/100 -> 17912.04 | Z58: =Y58*Z41/100 -> 19494.441 | AA58: =Z58*AA41/100 -> 20938.491 | AB58: =AA58*AB41/100 -> 23961.216 | AC58: =AB58*AC41/100 -> 26772.633 | AD58: =AC58*AD41/100 -> 29771.313 | AE58: =AD58*AE41/100 -> 32206.014 | AG58: VA2009Goods,t = VA2009Goods,t-1·gVAGoods,t/100
C59: Услуги | H59: 4014.105 | I59: 4423.5437 | J59: 4874.7451 | K59: 5800.9467 | L59: 6253.4205 | M59: 6816.2284 | N59: 7613.7271 | O59: 8595.8979 | P59: 9429.7 | Q59: 10783.19 | R59: 11613.496 | S59: 13007.115 | T59: 14190.763 | U59: 14361.052 | V59: 14605.19 | W59: =V59*W42/100 -> 14444.533 | X59: =W59*X42/100 -> 15397.872 | Y59: =X59*Y42/100 -> 16347.571 | Z59: =Y59*Z42/100 -> 17411.933 | AA59: =Z59*AA42/100 -> 17628.121 | AB59: =AA59*AB42/100 -> 18271.911 | AC59: =AB59*AC42/100 -> 18982.309 | AD59: =AC59*AD42/100 -> 20044.28 | AE59: =AD59*AE42/100 -> 21777.913 | AG59: VA2009Services,t = VA2009Services,t-1·gVAServces,t/100
C63: Дефляторы, %
C64: ВВП в рыночных ценах, % | D64: 165.2 | E64: 187.8 | F64: 123.5 | G64: 124.3 | H64: 130.9 | I64: 118.8 | J64: 127.1 | K64: 117.5 | L64: 109.5161 | M64: 121.06374 | N64: 127.23565 | O64: 128.16376 | P64: 112.12955 | Q64: 112.45894 | R64: 113.32436 | S64: 111.86852 | T64: 104.34106 | U64: 105.47223 | V64: 105.4494 | W64: =W13/V13/W30*10000 -> 100.54218 | X64: =X13/W13/X30*10000 -> 109.80547 | Y64: =Y13/X13/Y30*10000 -> 102.52473 | Z64: =Z13/Y13/Z30*10000 -> 103.63682 | AA64: =AA13/Z13/AA30*10000 -> 101.6111 | AB64: =AB13/AA13/AB30*10000 -> 110.02881 | AC64: =AC13/AB13/AC30*10000 -> 108.22628 | AD64: =AD13/AC13/AD30*10000 -> 103.7244 | AE64: =AE13/AD13/AE30*10000 -> 106.62268 | AG64: defGDPmp,t = GDPmp,t/GDPmp,t-1/gGDPmp,t·10000
C65: Чистые косвенные налоги | L65: 113.96947 | M65: 118.70612 | N65: 139.71968 | O65: 129.22959 | P65: 100.2623 | Q65: 114.22745 | R65: 118.9 | S65: 111.19866 | T65: 107.81462 | U65: 115.55648 | V65: 79.637613 | W65: =W14/V14/W31*10000 -> 98.595238 | X65: =X14/W14/X31*10000 -> 104.53867 | Y65: 105.2 | Z65: 106.6 | AA65: 98.7 | AB65: =AB14/AA14/AB31*10000 -> 128.55476 | AC65: =AC14/AB14/AC31*10000 -> 110.21915 | AD65: =AD14/AC14/AD31*10000 -> 123.48373 | AE65: =AE14/AD14/AE31*10000 -> 100.88301 | AG65: defNITt = NITt/NITt-1/gNITt·10000
C66: ВВП в основных ценах | L66: 108.92171 | M66: 121.42475 | N66: 125.71526 | O66: 128.01746 | P66: 114.10712 | Q66: 112.24092 | R66: 111.87249 | S66: 111.9633 | T66: 103.85292 | U66: 104.00103 | V66: 109.63348 | W66: =W15/V15/W32*10000 -> 100.77143 | X66: =X15/W15/X32*10000 -> 110.41223 | Y66: =Y15/X15/Y32*10000 -> 102.1894 | Z66: =Z15/Y15/Z32*10000 -> 103.34726 | AA66: =AA15/Z15/AA32*10000 -> 101.97667 | AB66: =AB15/AA15/AB32*10000 -> 108.37162 | AC66: =AC15/AB15/AC32*10000 -> 108.03207 | AD66: =AD15/AC15/AD32*10000 -> 101.9245 | AE66: =AE15/AD15/AE32*10000 -> 107.2561 | AG66: defGDPfc,t = GDPfc,t/GDPfc,t-1/gGDPfc,t·10000
C67: Сельское хозяйство и рыболовство | L67: 127.03394 | M67: 124.05758 | N67: 120.05166 | O67: 133.24943 | P67: 98.449314 | Q67: 118.40031 | R67: 137.26815 | S67: 106.60518 | T67: 91.217036 | U67: 123.5827 | V67: 99.742965 | W67: =W16/V16/W33*10000 -> 98.694738 | X67: =X16/W16/X33*10000 -> 107.08518 | Y67: =Y16/X16/Y33*10000 -> 100.46868 | Z67: =Z16/Y16/Z33*10000 -> 109.80899 | AA67: =AA16/Z16/AA33*10000 -> 106.95303 | AB67: =AB16/AA16/AB33*10000 -> 119.46656 | AC67: =AC16/AB16/AC33*10000 -> 110.60495 | AD67: =AD16/AC16/AD33*10000 -> 99.805714 | AE67: =AE16/AD16/AE33*10000 -> 104.12553 | AG67: defVAAB,t = defVAAB,t+100
C68: Промышленность | L68: 94.024971 | M68: 114.48619 | N68: 107.5874 | O68: 110.96649 | P68: 125.7252 | Q68: 112.79522 | R68: 113.46808 | S68: 102.21162 | T68: 99.362976 | U68: 102.84878 | V68: 125.96615 | W68: =W17/V17/W34*10000 -> 103.39628 | X68: =X17/W17/X34*10000 -> 114.22637 | Y68: =Y17/X17/Y34*10000 -> 105.84871 | Z68: =Z17/Y17/Z34*10000 -> 99.166309 | AA68: =AA17/Z17/AA34*10000 -> 106.27825 | AB68: =AB17/AA17/AB34*10000 -> 102.4156 | AC68: =AC17/AB17/AC34*10000 -> 99.661098 | AD68: =AD17/AC17/AD34*10000 -> 97.661415 | AE68: =AE17/AD17/AE34*10000 -> 72.625664 | AG68: defVACDE,t = VACDE,t/VACDE,t-1/gVACDE,t·10000
C69: Строительство | L69: 107.13448 | M69: 161.84174 | N69: 165.13439 | O69: 146.1479 | P69: 135.50767 | Q69: 110 | R69: 89.511636 | S69: 167.51157 | T69: 118.54805 | U69: 88.532523 | V69: 135.96687 | W69: =W18/V18/W35*10000 -> 90.741724 | X69: =X18/W18/X35*10000 -> 88.011379 | Y69: =Y18/X18/Y35*10000 -> 111.19945 | Z69: =Z18/Y18/Z35*10000 -> 94.280763 | AA69: =AA18/Z18/AA35*10000 -> 91.824561 | AB69: =AB18/AA18/AB35*10000 -> 97.509189 | AC69: =AC18/AB18/AC35*10000 -> 104.17669 | AD69: =AD18/AC18/AD35*10000 -> 100.29394 | AE69: =AE18/AD18/AE35*10000 -> 104.7 | AG69: defVAF,t = VAF,t/VAF,t-1/gVAF,t·10000
C70: Прочие товары | L70: 86.363636 | M70: 99.521531 | AG70: defVAGoodsO,t = VAGoodsO,t/VAGoodsO,t-1/gVAGoodsO,t·10000
C71: Розничная и оптовая торговля | L71: 107.57262 | M71: 111.11833 | N71: 120.71607 | O71: 120.39902 | P71: 105.22753 | Q71: 101.6039 | R71: 113.18213 | S71: 105.78988 | T71: 97.398368 | U71: 103.31762 | V71: 80.156686 | W71: =W20/V20/W37*10000 -> 106.09497 | X71: =X20/W20/X37*10000 -> 97.531195 | Y71: =Y20/X20/Y37*10000 -> 127.07496 | Z71: =Z20/Y20/Z37*10000 -> 107.79954 | AA71: =AA20/Z20/AA37*10000 -> 106.4705 | AB71: =AB20/AA20/AB37*10000 -> 113.07618 | AC71: =AC20/AB20/AC37*10000 -> 108.37563 | AD71: =AD20/AC20/AD37*10000 -> 110.4642 | AE71: =AE20/AD20/AE37*10000 -> 117.10806 | AG71: defVAGH,t = defRETt
C72: Транспорт и связь | L72: 100.30092 | M72: 106.87057 | N72: 98.766705 | O72: 101.78284 | P72: 82.791207 | Q72: 101.98928 | R72: 104.67726 | S72: 102.42396 | T72: 101.09523 | U72: 100.55555 | V72: 72.9522 | W72: =W21/V21/W38*10000 -> 100.19743 | X72: =X21/W21/X38*10000 -> 100.21367 | Y72: =Y21/X21/Y38*10000 -> 94.143332 | Z72: =Z21/Y21/Z38*10000 -> 97.575697 | AA72: =AA21/Z21/AA38*10000 -> 99.593551 | AB72: =AB21/AA21/AB38*10000 -> 143.12028 | AC72: =AC21/AB21/AC38*10000 -> 120.46383 | AD72: =AD21/AC21/AD38*10000 -> 98.757271 | AE72: =AE21/AD21/AE38*10000 -> 113.065 | AG72: defVAI,t = VAI,t/VAI,t-1/gVAI,t·10000
C73: Прочие услуги (остатком) | L73: 123.34925 | M73: 131.3349 | N73: 175.39442 | O73: 122.07923 | P73: 174.10325 | Q73: 119.69686 | R73: 134.92843 | S73: 121.08295 | T73: 128.71404 | U73: 92.133178 | V73: 168.76157 | W73: =W22/V22/W39*10000 -> 104.99781 | X73: =X22/W22/X39*10000 -> 145.06513 | Y73: =Y22/X22/Y39*10000 -> 85.112137 | Z73: =Z22/Y22/Z39*10000 -> 107.20829 | AA73: =AA22/Z22/AA39*10000 -> 95.022849 | AB73: =AB22/AA22/AB39*10000 -> 99.791104 | AC73: =AC22/AB22/AC39*10000 -> 118.4633 | AD73: =AD22/AC22/AD39*10000 -> 107.70273 | AE73: =AE22/AD22/AE39*10000 -> 176.84686 | AG73: defVAOther,t = VAOther,t/VAOther,t-1/gVAOther,t·10000
C74: Справочно:
C75: Товары | L75: 106.7645 | M75: 123.61492 | N75: 123.47762 | O75: 129.4844 | P75: 113.93615 | Q75: 116.58268 | R75: 137.9 | S75: 113.73795 | T75: 101.19992 | U75: 105.7521 | V75: 115.40045 | W75: =W24/V24/W41*10000 -> 96.486963 | X75: =X24/W24/X41*10000 -> 107.55888 | Y75: =Y24/X24/Y41*10000 -> 105.03155 | Z75: =Z24/Y24/Z41*10000 -> 101.83732 | AA75: =AA24/Z24/AA41*10000 -> 103.49584 | AB75: =AB24/AA24/AB41*10000 -> 107.32432 | AC75: =AC24/AB24/AC41*10000 -> 104.66443 | AD75: =AD24/AC24/AD41*10000 -> 99.039476 | AE75: =AE24/AD24/AE41*10000 -> 90.356161 | AG75: defVAGoods,t = VAGoods,t/VAGoods,t-1/gVAGoods,t·10000
C76: Услуги | L76: 111.70459 | M76: 118.81844 | N76: 128.30449 | O76: 129.43792 | P76: 110.99645 | Q76: 108.14407 | R76: 102.8 | S76: 110 | T76: 106.52727 | U76: 102.14449 | V76: 102.68115 | W76: =W25/V25/W42*10000 -> 105.62971 | X76: =X25/W25/X42*10000 -> 114.64808 | Y76: =Y25/X25/Y42*10000 -> 98.18611 | Z76: =Z25/Y25/Z42*10000 -> 105.67199 | AA76: =AA25/Z25/AA42*10000 -> 99.585341 | AB76: =AB25/AA25/AB42*10000 -> 110.26317 | AC76: =AC25/AB25/AC42*10000 -> 114.39942 | AD76: =AD25/AC25/AD42*10000 -> 107.18011 | AE76: =AE25/AD25/AE42*10000 -> 135.58084 | AG76: defVAServces,t = VAServces,t/VAServces,t-1/gVAServces,t·10000
C77: структура ВВП | AG77: 2021 | AH77: 2022 | AI77: 2023 | AJ77: 2024 | AK77: 2025 | AL77: 2026
C78: ВВП в рыночных ценах, % | D78: 100.00694 | E78: 100.00694 | F78: 100.00694 | G78: 100.00694 | H78: 100.00694 | I78: 100.00694 | J78: 100.00694 | K78: 100.00694 | L78: 100.00694 | M78: 100.00428 | N78: 100.00234 | O78: 100.02203 | P78: 100.02133 | Q78: 99.999595 | R78: 100 | S78: 100 | T78: 100 | U78: 100 | V78: =V79+V80 -> 100 | W78: =W79+W80 -> 100 | X78: =X79+X80 -> 100 | Y78: =Y79+Y80 -> 100 | Z78: =Z79+Z80 -> 100 | AA78: =AA79+AA80 -> 100 | AB78: =AB79+AB80 -> 100 | AC78: =AC79+AC80 -> 100 | ... AE78: =AE79+AE80 -> 100 | AG78: =AG79+AG81+AG82+AG83+AG85+AG86+AG87 -> 0 | AH78: =AH79+AH81+AH82+AH83+AH85+AH86+AH87 -> 0 | AI78: =AI79+AI81+AI82+AI83+AI85+AI86+AI87 -> 0 | AJ78: =AJ79+AJ81+AJ82+AJ83+AJ85+AJ86+AJ87 -> 0 | AK78: =AK79+AK81+AK82+AK83+AK85+AK86+AK87 -> #REF! | AL78: =AL79+AL81+AL82+AL83+AL85+AL86+AL87 -> #REF!
C79: Чистые косвенные налоги | D79: =D14/D$13*100 -> 9.6064815 | E79: =E14/E$13*100 -> 7.5887632 | F79: =F14/F$13*100 -> 7.2862454 | G79: =G14/G$13*100 -> 8.3781061 | H79: =H14/H$13*100 -> 8.98276 | I79: =I14/I$13*100 -> 9.8598643 | J79: =J14/J$13*100 -> 10.677308 | K79: =K14/K$13*100 -> 11.021209 | L79: 11.533872 | M79: 11.351537 | N79: 12.523137 | O79: 12.627281 | P79: 11.084396 | Q79: 11.258707 | R79: 12.395622 | S79: 12.321399 | T79: 12.731584 | U79: 13.948858 | V79: =V14/V13*100 -> 10.534472 | W79: =W14/W13*100 -> 10.330478 | X79: =X14/X13*100 -> 9.8349792 | Y79: =Y14/Y13*100 -> 9.8778202 | Z79: =Z14/Z13*100 -> 9.7240797 | AA79: =AA14/AA13*100 -> 8.9838646 | AB79: =AB14/AB13*100 -> 9.5932479 | AC79: =AC14/AC13*100 -> 9.0431937 | ... AE79: =AE14/AE13*100 -> 9.403972 | AG79: =$AU$44*AB79/100 -> 0 | AH79: =$AV$44*AC79/100 -> 0 | AI79: =$AW$44*AD79/100 -> 0 | AJ79: =$AX$44*AE79/100 -> 0 | AK79: =$AY$44*#REF!/100 -> #REF! | AL79: =$AZ$44*#REF!/100 -> #REF!
C80: ВВП в основных ценах | D80: =D15/D$13*100 -> 90.393519 | E80: =E15/E$13*100 -> 92.411237 | F80: =F15/F$13*100 -> 92.713755 | G80: =G15/G$13*100 -> 91.621894 | H80: =H15/H$13*100 -> 91.01724 | I80: =I15/I$13*100 -> 90.140136 | J80: =J15/J$13*100 -> 89.322692 | K80: =K15/K$13*100 -> 88.978791 | L80: 88.473066 | M80: 88.652748 | N80: 87.479206 | O80: 87.394744 | P80: 88.936933 | Q80: 88.740888 | R80: 87.604378 | S80: 87.678601 | T80: 87.268416 | U80: 86.051142 | V80: =V81+V82+V83+V84+V85+V86+V87 -> 89.465528 | W80: =W81+W82+W83+W84+W85+W86+W87 -> 89.669522 | X80: =X81+X82+X83+X84+X85+X86+X87 -> 90.165021 | Y80: =Y81+Y82+Y83+Y84+Y85+Y86+Y87 -> 90.12218 | Z80: =Z81+Z82+Z83+Z84+Z85+Z86+Z87 -> 90.27592 | AA80: =AA81+AA82+AA83+AA84+AA85+AA86+AA87 -> 91.016135 | AB80: =AB81+AB82+AB83+AB84+AB85+AB86+AB87 -> 90.406752 | AC80: =AC81+AC82+AC83+AC84+AC85+AC86+AC87 -> 90.956806 | ... AE80: =AE81+AE82+AE83+AE84+AE85+AE86+AE87 -> 90.596028 | AG80: =AG81+AG82+AG83+AG85+AG86+AG87 -> 0 | AH80: =AH81+AH82+AH83+AH85+AH86+AH87 -> 0 | AI80: =AI81+AI82+AI83+AI85+AI86+AI87 -> 0 | AJ80: =AJ81+AJ82+AJ83+AJ85+AJ86+AJ87 -> 0 | AK80: =AK81+AK82+AK83+AK85+AK86+AK87 -> #REF! | AL80: =AL81+AL82+AL83+AL85+AL86+AL87 -> #REF!
C81: Сельское хозяйство и рыболовство | D81: =D16/D$13*100 -> 32.002315 | E81: =E16/E$13*100 -> 25.107296 | F81: =F16/F$13*100 -> 25.3829 | G81: =G16/G$13*100 -> 25.123125 | H81: =H16/H$13*100 -> 23.808409 | I81: =I16/I$13*100 -> 22.235061 | J81: =J16/J$13*100 -> 24.191956 | K81: =K16/K$13*100 -> 19.224283 | L81: 21.191685 | M81: 21.451908 | N81: 19.433315 | O81: 19.867396 | P81: 18.551554 | Q81: 19.586678 | R81: 23.83551 | S81: 23.326817 | T81: 20.430744 | U81: 23.445291 | V81: =V16/V13*100 -> 21.590744 | W81: =W16/W13*100 -> 20.856977 | X81: =X16/X13*100 -> 20.283296 | Y81: =Y16/Y13*100 -> 19.771965 | Z81: =Z16/Z13*100 -> 20.867073 | AA81: =AA16/AA13*100 -> 22.690431 | AB81: =AB16/AB13*100 -> 22.449081 | AC81: =AC16/AC13*100 -> 22.934854 | ... AE81: =AE16/AE13*100 -> 22.786375 | AG81: =$AU$44*AB81/100 -> 0 | AH81: =$AV$44*AC81/100 -> 0 | AI81: =$AW$44*AD81/100 -> 0 | AJ81: =$AX$44*AE81/100 -> 0 | AK81: =$AY$44*#REF!/100 -> #REF! | AL81: =$AZ$44*#REF!/100 -> #REF!
C82: Промышленность | D82: =D17/D$13*100 -> 21.990741 | E82: =E17/E$13*100 -> 20.103394 | F82: =F17/F$13*100 -> 21.680297 | G82: =G17/G$13*100 -> 33.148646 | H82: =H17/H$13*100 -> 33.465949 | I82: =I17/I$13*100 -> 33.09928 | J82: =J17/J$13*100 -> 30.246771 | K82: =K17/K$13*100 -> 26.66364 | L82: 22.827686 | M82: 21.284801 | N82: 18.348524 | O82: 14.208021 | P82: 14.336129 | Q82: 14.743535 | R82: 14.528567 | S82: 13.681902 | T82: 12.592412 | U82: 12.083558 | V82: =V17/V13*100 -> 15.156324 | W82: =W17/W13*100 -> 16.913395 | X82: =X17/X13*100 -> 19.92712 | Y82: =Y17/Y13*100 -> 21.153489 | Z82: =Z17/Z13*100 -> 21.329595 | AA82: =AA17/AA13*100 -> 23.239275 | AB82: =AB17/AB13*100 -> 23.881958 | AC82: =AC17/AC13*100 -> 23.490947 | ... AE82: =AE17/AE13*100 -> 16.897411 | AG82: =$AU$44*AB82/100 -> 0 | AH82: =$AV$44*AC82/100 -> 0 | AI82: =$AW$44*AD82/100 -> 0 | AJ82: =$AX$44*AE82/100 -> 0 | AK82: =$AY$44*#REF!/100 -> #REF! | AL82: =$AZ$44*#REF!/100 -> #REF!
C83: Строительство | D83: =D18/D$13*100 -> 2.7584877 | E83: =E18/E$13*100 -> 3.8529067 | F83: =F18/F$13*100 -> 5.4275093 | G83: =G18/G$13*100 -> 2.126707 | H83: =H18/H$13*100 -> 2.7186208 | I83: =I18/I$13*100 -> 2.0413 | J83: =J18/J$13*100 -> 2.8688439 | K83: =K18/K$13*100 -> 4.2531457 | L83: 4.5388949 | M83: 6.0790762 | N83: 8.0800981 | O83: 10.349638 | P83: 10.172088 | Q83: 10.232686 | R83: 7.9395167 | S83: 8.3607323 | T83: 10.365896 | U83: 10.217819 | V83: =V18/V13*100 -> 15.064126 | W83: =W18/W13*100 -> 15.299971 | X83: =X18/X13*100 -> 11.919738 | Y83: =Y18/Y13*100 -> 13.244872 | Z83: =Z18/Z13*100 -> 11.732554 | AA83: =AA18/AA13*100 -> 10.557265 | AB83: =AB18/AB13*100 -> 11.295724 | AC83: =AC18/AC13*100 -> 11.211634 | ... AE83: =AE18/AE13*100 -> 8.1170283 | AG83: =$AU$44*AB83/100 -> 0 | AH83: =$AV$44*AC83/100 -> 0 | AI83: =$AW$44*AD83/100 -> 0 | AJ83: =$AX$44*AE83/100 -> 0 | AK83: =$AY$44*#REF!/100 -> #REF! | AL83: =$AZ$44*#REF!/100 -> #REF!
C84: Прочие товары | D84: =D19/D$13*100 -> 1.1574074 | E84: =E19/E$13*100 -> 0.99492782 | F84: =F19/F$13*100 -> 0.35687732 | G84: =G19/G$13*100 -> 0.33019924 | H84: =H19/H$13*100 -> 0.29253452 | I84: =I19/I$13*100 -> 0.39700175 | J84: =J19/J$13*100 -> 0.30452588 | K84: =K19/K$13*100 -> 0.3923985 | L84: 0.29001193 | M84: 0.22281019 | N84: 0.2272674 | O84: 0.19709831 | P84: 0.14300257 | Q84: 0.05585439 | R84: 0 | S84: 0 | T84: 0 | U84: 0 | V84: =V19/V13*100 -> 0 | W84: =W19/W13*100 -> 0 | X84: =X19/X13*100 -> 0 | Y84: =Y19/Y13*100 -> 0 | Z84: =Z19/Z13*100 -> 0 | AA84: =AA19/AA13*100 -> 0 | AB84: =AB19/AB13*100 -> 0 | AC84: =AC19/AC13*100 -> 0 | ... AE84: =AE19/AE13*100 -> 0
C85: Розничная и оптовая торговля | D85: =D20/D$13*100 -> 20.949074 | E85: =E20/E$13*100 -> 22.610222 | F85: =F20/F$13*100 -> 20.074349 | G85: =G20/G$13*100 -> 10.851802 | H85: =H20/H$13*100 -> 10.722365 | I85: =I20/I$13*100 -> 11.693775 | J85: =J20/J$13*100 -> 11.427071 | K85: =K20/K$13*100 -> 16.498573 | L85: 16.534843 | M85: 17.072831 | N85: 16.554595 | O85: 20.202859 | P85: 21.06646 | Q85: 20.236693 | R85: 13.132875 | S85: 13.916672 | T85: 14.369577 | U85: 14.076033 | V85: =V20/V13*100 -> 10.659429 | W85: =W20/W13*100 -> 11.153434 | X85: =X20/X13*100 -> 9.8604315 | Y85: =Y20/Y13*100 -> 12.748103 | Z85: =Z20/Z13*100 -> 13.528918 | AA85: =AA20/AA13*100 -> 12.771697 | AB85: =AB20/AB13*100 -> 13.219518 | AC85: =AC20/AC13*100 -> 13.62546 | ... AE85: =AE20/AE13*100 -> 15.210147 | AG85: =$AU$44*AB85/100 -> 0 | AH85: =$AV$44*AC85/100 -> 0 | AI85: =$AW$44*AD85/100 -> 0 | AJ85: =$AX$44*AE85/100 -> 0 | AK85: =$AY$44*#REF!/100 -> #REF! | AL85: =$AZ$44*#REF!/100 -> #REF!
C86: Транспорт и связь | D86: =D21/D$13*100 -> 2.9128086 | E86: =E21/E$13*100 -> 4.165041 | F86: =F21/F$13*100 -> 7.3605948 | G86: =G21/G$13*100 -> 4.7571077 | H86: =H21/H$13*100 -> 4.9769873 | I86: =I21/I$13*100 -> 5.5017332 | J86: =J21/J$13*100 -> 5.4646645 | K86: =K21/K$13*100 -> 6.6318589 | L86: 7.400161 | M86: 7.2102664 | N86: 9.5428879 | O86: 10.065003 | P86: 10.979204 | Q86: 11.162783 | R86: 14.486667 | S86: 15.30621 | T86: 15.230523 | U86: 14.304509 | V86: =V21/V13*100 -> 9.5320672 | W86: =W21/W13*100 -> 8.8979254 | X86: =X21/X13*100 -> 7.5580863 | Y86: =Y21/Y13*100 -> 6.0197694 | Z86: =Z21/Z13*100 -> 6.104427 | AA86: =AA21/AA13*100 -> 4.5484485 | AB86: =AB21/AB13*100 -> 5.1531368 | AC86: =AC21/AC13*100 -> 5.0968128 | ... AE86: =AE21/AE13*100 -> 9.3356549 | AG86: =$AU$44*AB86/100 -> 0 | AH86: =$AV$44*AC86/100 -> 0 | AI86: =$AW$44*AD86/100 -> 0 | AJ86: =$AX$44*AE86/100 -> 0 | AK86: =$AY$44*#REF!/100 -> #REF! | AL86: =$AZ$44*#REF!/100 -> #REF!
C87: Прочие услуги (остатком) | D87: =D22/D$13*100 -> 8.6226852 | E87: =E22/E$13*100 -> 15.577448 | F87: =F22/F$13*100 -> 12.431227 | G87: =G22/G$13*100 -> 15.289904 | H87: =H22/H$13*100 -> 15.040175 | I87: =I22/I$13*100 -> 15.174947 | J87: =J22/J$13*100 -> 14.82936 | K87: =K22/K$13*100 -> 15.322999 | L87: 15.689784 | M87: 15.331055 | N87: 15.292519 | O87: 12.50473 | P87: 13.688497 | Q87: 12.722659 | R87: 13.681242 | S87: 13.086267 | T87: 14.279263 | U87: 11.923932 | V87: =V22/V13*100 -> 17.462836 | W87: =W22/W13*100 -> 16.54782 | X87: =X22/X13*100 -> 20.616349 | Y87: =Y22/Y13*100 -> 17.183982 | Z87: =Z22/Z13*100 -> 16.713353 | AA87: =AA22/AA13*100 -> 17.209019 | AB87: =AB22/AB13*100 -> 14.407334 | AC87: =AC22/AC13*100 -> 14.597099 | ... AE87: =AE22/AE13*100 -> 18.249412 | AG87: =$AU$44*AB87/100 -> 0 | AH87: =$AV$44*AC87/100 -> 0 | AI87: =$AW$44*AD87/100 -> 0 | AJ87: =$AX$44*AE87/100 -> 0 | AK87: =$AY$44*#REF!/100 -> #REF! | AL87: =$AZ$44*#REF!/100 -> #REF!
C88: Справочно: | D88: =D23/D$13*100 -> 0 | E88: =E23/E$13*100 -> 0 | F88: =F23/F$13*100 -> 0 | G88: =G23/G$13*100 -> 0 | H88: =H23/H$13*100 -> 0 | I88: =I23/I$13*100 -> 0 | J88: =J23/J$13*100 -> 0 | K88: =K23/K$13*100 -> 0
C89: Товары | D89: =D24/D$13*100 -> 57.908951 | E89: =E24/E$13*100 -> 50.058525 | F89: =F24/F$13*100 -> 52.847584 | G89: =G24/G$13*100 -> 60.728677 | H89: =H24/H$13*100 -> 60.285514 | I89: =I24/I$13*100 -> 57.772642 | J89: =J24/J$13*100 -> 57.612097 | K89: =K24/K$13*100 -> 50.533467 | L89: 48.848278 | M89: 49.038595 | N89: 46.089204 | O89: 44.622153 | P89: 43.202773 | Q89: 44.618753 | R89: 46.303594 | S89: 45.369451 | T89: 43.389052 | U89: 45.746668 | V89: =V81+V82+V83+V84 -> 51.811195 | W89: =W81+W82+W83+W84 -> 53.070343 | X89: =X81+X82+X83+X84 -> 52.130154 | Y89: =Y81+Y82+Y83+Y84 -> 54.170326 | Z89: =Z81+Z82+Z83+Z84 -> 53.929222 | AA89: =AA81+AA82+AA83+AA84 -> 56.48697 | AB89: =AB81+AB82+AB83+AB84 -> 57.626763 | AC89: =AC81+AC82+AC83+AC84 -> 57.637435 | ... AE89: =AE81+AE82+AE83+AE84 -> 47.800814 | AG89: =$AU$44*AB89/100 -> 0 | AH89: =$AV$44*AC89/100 -> 0 | AI89: =$AW$44*AD89/100 -> 0 | AJ89: =$AX$44*AE89/100 -> 0 | AK89: =$AY$44*#REF!/100 -> #REF! | AL89: =$AZ$44*#REF!/100 -> #REF!
C90: Услуги | D90: =D25/D$13*100 -> 32.484568 | E90: =E25/E$13*100 -> 42.352712 | F90: =F25/F$13*100 -> 39.866171 | G90: =G25/G$13*100 -> 30.893217 | H90: =H25/H$13*100 -> 30.731726 | I90: =I25/I$13*100 -> 32.367493 | J90: =J25/J$13*100 -> 31.710595 | K90: =K25/K$13*100 -> 38.445324 | L90: 39.624788 | M90: 39.614153 | N90: 41.390002 | O90: 42.772591 | P90: 45.734161 | Q90: 44.122135 | R90: 41.300784 | S90: 42.309149 | T90: 43.879364 | U90: 40.304473 | V90: =V85+V86+V87 -> 37.654333 | W90: =W85+W86+W87 -> 36.599179 | X90: =X85+X86+X87 -> 38.034867 | Y90: =Y85+Y86+Y87 -> 35.951854 | Z90: =Z85+Z86+Z87 -> 36.346698 | AA90: =AA85+AA86+AA87 -> 34.529165 | AB90: =AB85+AB86+AB87 -> 32.779989 | AC90: =AC85+AC86+AC87 -> 33.319372 | ... AE90: =AE85+AE86+AE87 -> 42.795214 | AG90: =$AU$44*AB90/100 -> 0 | AH90: =$AV$44*AC90/100 -> 0 | AI90: =$AW$44*AD90/100 -> 0 | AJ90: =$AX$44*AE90/100 -> 0 | AK90: =$AY$44*#REF!/100 -> #REF! | AL90: =$AZ$44*#REF!/100 -> #REF!
C93: ВВП по использованию | D93: 518.4 | E93: 1025.2 | F93: 1345 | G93: 1786.8 | H93: 2563.8 | I93: 3375.3 | J93: 4761.5 | K93: 6167.2 | L93: 7206.6 | M93: 9335.3 | N93: 12804.3 | O93: 17706.9 | P93: 20629 | Q93: 24707.1 | R93: 30071.1 | S93: 36163.1 | T93: 40525.2 | U93: 45606.6 | V93: =V13 -> 50977.4 | W93: =W13 -> 54790.3 | X93: =X13 -> 64434.3 | Y93: =Y13 -> 71059.2 | Z93: =Z13 -> 79109.8 | AA93: =AA13 -> 83958.3 | AB93: =AB13 -> 101076.3 | AC93: =AC13 -> 118181.7 | ... AE93: =AE13 -> 153402.2 | AG93: GDPmp,t = GDPmp,t
C94: Конечное потребление | D94: 366.3 | E94: 786.3 | F94: 1084.3 | G94: 1775.5 | H94: 2516.3 | I94: 3158.4 | J94: 4319.4 | K94: 5292.8 | L94: 6899.3 | M94: 8773.8 | N94: 11923.9 | O94: 17156.5 | P94: 20380.2 | Q94: 23726.2 | R94: 33314.9 | S94: 41047.7 | T94: 46141.6 | U94: 51376.3 | V94: =V98+V95+V99 -> 42206.3 | W94: =W98+W95+W99 -> 50109.6 | X94: =X98+X95+X99 -> 59167.4 | Y94: =Y98+Y95+Y99 -> 62273.4 | Z94: =Z98+Z95+Z99 -> 69139 | AA94: =AA98+AA95+AA99 -> 74861.6 | AB94: =AB98+AB95+AB99 -> 92235.3 | AC94: =AC98+AC95+AC99 -> 115547 | ... AE94: =AE98+AE95+AE99 -> 110815.29 | AG94: FC,t = G,t+CH,t
C95: - населения | D95: 301.2 | E95: 691.3 | F95: 944.8 | G95: 1556.5 | H95: 2149.5 | I95: 2711.8 | J95: 3692.9 | K95: 4507.2 | L95: 5753.4 | M95: 7630.5 | N95: 10486.7 | O95: 15145 | P95: 17605.3 | Q95: 20717.1 | R95: 28935.7 | S95: 27407.1 | T95: 41354.9 | U95: 44082 | V95: 36003 | W95: 43219.8 | X95: 51499.4 | Y95: 53938.7 | Z95: 59925 | AA95: 64584 | AB95: 80377.1 | AC95: 102715.8 | AD95: 118160.2 | AE95: =AD95*Household!AE43/Household!AD43 -> 94514.531 | AG95: CH,t = CH,t-1·DIHHt/DIHHt-1
C96: - в т.ч. рыночный | J96: 2191.3 | K96: 3010.9 | L96: 3679.6 | M96: 4597.9 | N96: 5864 | O96: 8712.6 | P96: 10201 | Q96: 6079.2 | R96: 7506.7 | S96: 9204.8 | T96: 23152.6 | U96: 25879.7 | V96: =Household!V3+Household!V15 -> 26479.6 | W96: =Household!W3+Household!W15 -> 28302.4 | X96: =Household!X3+Household!X15 -> 30958.4 | Y96: =Household!Y3+Household!Y15 -> 33119.8 | Z96: =Household!Z3+Household!Z15 -> 38440.4 | AA96: =Household!AA3+Household!AA15 -> 40710.1 | AB96: =Household!AB3+Household!AB15 -> 48909.7 | AC96: =Household!AC3+Household!AC15 -> 66260.2 | ... AE96: =Household!AE3+Household!AE15 -> 91506.7 | AG96: CMRKTt = RETt+SERt
C97: - в т.ч. натуральное | J97: 1981.5317 | K97: 2345.7019 | L97: 2969.2369 | M97: 4786.8438 | N97: 9536.3161 | O97: 6432.4 | P97: 7404.3 | Q97: 14637.9 | R97: 21429 | S97: 18202.3 | T97: 18202.3 | U97: 18202.3 | V97: =V95-V96 -> 9523.4 | W97: =W95-W96 -> 14917.4 | X97: =X95-X96 -> 20541 | Y97: =Y95-Y96 -> 20818.9 | Z97: =Z95-Z96 -> 21484.6 | AA97: =AA95-AA96 -> 23873.9 | AB97: =AB95-AB96 -> 31467.4 | AC97: =AC95-AC96 -> 36455.6 | ... AE97: =AE95-AE96 -> 3007.8308 | AG97: CNAt = CH,t-CMRKTt
C98: - государства | D98: 55.2 | E98: 80 | F98: 116.5 | G98: 207.7 | H98: 355.4 | I98: 431.1 | J98: 580.1 | K98: 726.8 | L98: 1052.3 | M98: 1036.6 | N98: 1140.1 | O98: 1652.7 | P98: 2570.8 | Q98: 2798.5 | R98: 4105.7 | S98: 4644 | T98: 5352.2 | U98: 6317.1 | V98: 5892.5 | W98: 6441.6 | X98: 7336.8 | Y98: 7973.6 | Z98: 8824.3 | AA98: 9712.3 | AB98: 11001.4 | AC98: 11977.8 | AD98: 14157.5 | AE98: =(AD98-AD100)*AE93/AD93+AE100 -> 16300.76 | AG98: G,t = (G,t-1-GNTrrt-1)·GDPmp,t/GDPmp,t-1+GNTrrt
C99: организации, обслуживающие домашние хозяйства | V99: 310.8 | W99: 448.2 | X99: 331.2 | Y99: 361.1 | Z99: 389.7 | AA99: 565.3 | AB99: 856.8 | AC99: 853.4 | AD99: 786.6
C100: - в т.ч. трансферты населению в натуральной форме | D100: 33.2 | E100: 52.2 | F100: 76.8 | G100: 188.7 | H100: 402.3 | I100: 439 | J100: 523 | K100: 631 | L100: 768.1 | M100: 662.5 | N100: 904 | O100: 1088.8 | P100: 2242 | Q100: 2267.4 | R100: 2898.8 | S100: 3838.8 | T100: 4525.3 | U100: 5399.5 | V100: =Household!V40 -> 4055.1 | W100: =Household!W40 -> 4817.9 | X100: =Household!X40 -> 5466.7 | Y100: =Household!Y40 -> 5744 | Z100: =Household!Z40 -> 6433.2 | AA100: =Household!AA40 -> 7283.3 | AB100: =Household!AB40 -> 8932.6 | AC100: =Household!AC40 -> 10146.4 | ... AE100: =Household!AE40 -> 12016.235 | AG100: GNTrrt = TrNATG,t
C101: Валовое накопление | D101: 102 | E101: 158.1 | F101: 233.1 | G101: 168.2 | H101: 249.2 | I101: 316.6 | J101: 475.6 | K101: 752.6 | L101: 839.4 | M101: 1490.5 | N101: 3154.1 | O101: 4693.9 | P101: 5125.1 | Q101: 5891.6 | R101: 8783.6 | S101: 8414.2 | T101: 10024.7 | U101: 11930.5 | V101: 22781.7 | W101: 22202.3 | X101: 19284.9 | Y101: 26479.1 | Z101: 27995.9 | AA101: 28105 | AB101: 35249.2 | AC101: 41916.1 | AD101: 42027.3 | AE101: =AE93-AE104-AE105-AE94 -> 95859.928 | AG101: InvNAt = GDPmp,t-ExNA,t-ImNA,t-FC,t
C102: - валовое накопление основного капитала | D102: 91.6 | E102: 137.6 | F102: 223.6 | G102: 132.6 | H102: 230.3 | I102: 212.5 | J102: 382.6 | K102: 640 | L102: 801.3 | M102: 1445.3 | N102: 2973.9 | O102: 4341.4 | P102: 5423.9 | Q102: 6050.6 | R102: 8598.2 | S102: 7855.8 | T102: 9736.3 | U102: 11781.5 | V102: 19736.9 | W102: 21954 | X102: 20133 | Y102: 25146.8 | Z102: 24926.6 | AA102: 23150.4 | AB102: 32314.3 | AC102: 37469.9 | AD102: 37577.8 | AE102: =AE101*0.94 -> 90108.332 | AG102: InvNAF,t = InvNAt·0,97
C103: - изменение запасов | D103: 10.4 | E103: 20.5 | F103: 9.5 | G103: 35.6 | H103: 18.9 | I103: 104.1 | J103: 93 | K103: 112.6 | L103: 38.1 | M103: 45.2 | N103: 180.2 | O103: 352.5 | P103: -298.8 | Q103: -158.9 | R103: 185.4 | S103: 558.4 | T103: 288.3 | U103: 149 | V103: 3044.8 | W103: 248.3 | X103: -848.1 | Y103: 1332.3 | Z103: 3069.3 | AA103: 4954.6 | AB103: 2934.9 | AC103: 4446.2 | AD103: 4449.5 | AE103: =AE101-AE102 -> 5751.5957 | AG103: CiIt = InvNAt-InvNAF,t
C104: Экспорт товаров и услуг | D104: 424.1 | E104: 509.6 | F104: 913.6 | G104: 1650.9 | H104: 1693.5 | I104: 2123.6 | J104: 3045.5486 | K104: 3624.0277 | L104: 3909.5709 | M104: 5243.2217 | N104: 5871.4189 | O104: 5782.4 | P104: 5048 | Q104: 6620.7 | R104: 5335 | S104: 7829.5 | T104: 7582.6 | U104: 5143.4 | V104: 4997.2 | W104: 7232.5 | X104: 9619.1 | Y104: 10215.1 | Z104: 11850.6 | AA104: 14545.2 | AB104: 24442.2 | AC104: 19326.4 | AD104: 22827.7 | AE104: =(Trade!AE5+Trade!AE4-Trade!AE6)*Assumptions!AE12+Industry!AE12 -> 28747.758 | AG104: ExNA,t = (EXUSt+EXUSServ,t)·erUSDt
C105: (-) Импорт товаров и услуг | D105: -442.8 | E105: -589.3 | F105: -893.6 | G105: -1790 | H105: -1981.7 | I105: -2564.9 | J105: -3512.5803 | K105: -4292.8296 | L105: -5243.5078 | M105: -7819.7656 | N105: -12761.635 | O105: -14004.9 | P105: -12686.7 | Q105: -14577.7 | R105: -22286.1 | S105: -25114 | T105: -26051.9 | U105: -26676.2 | V105: -20460 | W105: -23299.3 | X105: -25037.6 | Y105: -29468.7 | Z105: -32486.5 | AA105: -32260.8 | AB105: -48156.8 | AC105: -58006.4 | AD105: -64323.5 | AE105: =-(Trade!AE42+Trade!AE43-Trade!AE49)*Assumptions!AE12 -> -82020.777 | AG105: ImNA,t = -(IMUSServ,t+IMUSGoods,t)·erUSDt
C106: чистый экспорт товаров и услуг | D106: -18.7 | E106: -79.7 | F106: 20 | G106: -139.1 | H106: -288.2 | I106: -441.3 | J106: -466.9 | K106: -668.8 | L106: -1334.3 | M106: -2318.9 | N106: -4518.6 | O106: -8222.5 | P106: -7638.6 | Q106: -7957 | R106: -16951.1 | S106: -17284.5 | T106: -18469.3 | U106: -21532.8 | V106: =V105+V104 -> -15462.8 | W106: =W105+W104 -> -16066.8 | X106: =X105+X104 -> -15418.5 | Y106: =Y105+Y104 -> -19253.6 | Z106: =Z105+Z104 -> -20635.9 | AA106: =AA105+AA104 -> -17715.6 | AB106: =AB105+AB104 -> -23714.6 | AC106: =AC105+AC104 -> -38680 | ... AE106: =AE105+AE104 -> -53273.019
C107: статистическое расхождение | D107: 68.8 | E107: 160.4 | F107: 7.6 | G107: -17.9 | H107: 86.5 | I107: 341.6 | J107: 433.3 | K107: 790.6 | L107: 802.2 | M107: 1389.9 | N107: 2245.1 | O107: 4079 | P107: 2761.9 | Q107: 3046.4 | R107: 4923.7 | S107: 3985.6 | T107: 2828.6 | U107: 3832.6 | V107: 1452.6 | W107: -1454.8 | X107: 1400.6 | Y107: 1560.3 | Z107: 2610.8 | AA107: -1292.7 | AB107: -2963.6 | AC107: -601.4 | AD107: =AD93-AD94-AD101-AD104-AD105 -> -853.9 | AE107: =AE93-AE94-AE101-AE104-AE105 -> 0
AC108: =AC94+AC101+AC104+AC105 -> 118783.1 | AD108: =AD94+AD101+AD104+AD105 -> 133635.8 | AE108: =AE94+AE101+AE104+AE105 -> 153402.2
C110: ВВП по использованию, % | K110: 110.3 | L110: 106.7 | M110: 107 | N110: 110.55184 | O110: 116.24527 | P110: 105.79428 | Q110: 111.81258 | R110: 113.43717 | S110: 99.965562 | T110: 121.39968 | U110: 111.07095 | V110: 109.325 | W110: 111.5 | X110: 103.1 | Y110: 107.1 | Z110: 107.8 | AA110: 104.7 | AB110: 109.8 | AC110: 108.6 | AD110: 107.7 | AE110: =(AE116*AD104+AE117*AD105+AE115*AD101+AE113*AD97+AD96*AE112+AE114*AD98)/(AD104+AD105+AD101+AD98+AD96+AD97) -> 160.59263 | AG110: gGDPmp,t = (gExNA,t·ExNA,t-1+gImNA,t·ImNA,t-1+gInvNAt·InvNAt-1+gCNAt·CNAt-1+CMRKTt-1·gCMRKTt+gG,t·G,t-1)/(ExNA,t-1+ImNA,t-1+InvNAt-1+G,t-1+CMRKTt-1+CNAt-1)
C111: Конечное потребление населения | K111: 111.6 | L111: 107.7562 | M111: 107.71048 | N111: 105.0185 | O111: 113.73118 | P111: 107.9 | Q111: 110.6 | R111: 124.4 | S111: 115.2 | T111: 109.4 | U111: 101.8 | V111: 85 | W111: 113 | X111: 105 | Y111: 104 | Z111: 105 | AA111: 103.1 | AB111: 104.3 | AC111: 115.7 | AD111: 109.2 | AE111: =SUMPRODUCT(AE112:AE113,AD96:AD97)/SUM(AD96:AD97) -> 111.73904 | AG111: gCH,t = (gCMRKTt·CMRKTt-1+gCNAt·CNAt-1)/(CMRKTt-1+CNAt-1)
C112: - в т.ч. рыночный | L112: 112.70812 | M112: 109.57491 | N112: 103.47611 | O112: 123.37675 | P112: 107.16028 | Q112: 110.09 | R112: 113.5897 | S112: 113.80107 | T112: 114.05663 | U112: 101.66359 | V112: 99.818533 | W112: =(Household!V9*Household!W11+Household!V18*Household!W20)/(Household!V9+Household!V18) -> 103.63471 | X112: =(Household!W9*Household!X11+Household!W18*Household!X20)/(Household!W9+Household!W18) -> 104.76179 | Y112: =(Household!X9*Household!Y11+Household!X18*Household!Y20)/(Household!X9+Household!X18) -> 106.94157 | Z112: =(Household!Y9*Household!Z11+Household!Y18*Household!Z20)/(Household!Y9+Household!Y18) -> 107.10766 | AA112: =(Household!Z9*Household!AA11+Household!Z18*Household!AA20)/(Household!Z9+Household!Z18) -> 96.019416 | AB112: =(Household!AA9*Household!AB11+Household!AA18*Household!AB20)/(Household!AA9+Household!AA18) -> 109.71003 | AC112: =(Household!AB9*Household!AC11+Household!AB18*Household!AC20)/(Household!AB9+Household!AB18) -> 110.35767 | AD112: =(Household!AC9*Household!AD11+Household!AC18*Household!AD20)/(Household!AC9+Household!AC18) -> 116.17827 | AE112: =(Household!AD9*Household!AE11+Household!AD18*Household!AE20)/(Household!AD9+Household!AD18) -> 112.32806 | AG112: gCMRKTt = (RETt-1·gRETt+SERt-1·gSERt)/(RETt-1+SERt-1)
C113: - в т.ч. натуральное | L113: 101.4 | M113: 105.4 | N113: 106.5 | O113: 107.8 | P113: 110.5 | Q113: 106.8 | R113: 107.9 | S113: 110.4 | T113: 107.6 | U113: 104.5 | V113: =V33 -> 103.2 | W113: =W33 -> 105.2 | X113: =X33 -> 106.8 | Y113: =Y33 -> 107 | Z113: =Z33 -> 107 | AA113: =AA33 -> 107.9 | AB113: =AB33 -> 99.7 | AC113: =AC33 -> 108 | ... AE113: =AE33 -> 110.6 | AG113: gCNAt = gVAAB,t
C114: Конечное потребление государства | K114: 102.2 | L114: 133.529 | M114: 86.382114 | N114: 89.235446 | O114: 94.240434 | P114: 106.9 | Q114: 100.9 | R114: 107.8 | S114: 102.1 | T114: 102.3 | U114: 104.1 | V114: 103.3 | W114: 101.7 | X114: 105.7 | Y114: 104.5 | Z114: 100.7 | AA114: 102.3 | AB114: 104.6 | AC114: 99.3 | AD114: 90.9 | AE114: =AE98/AD98/(AE96/AD96/AE112) -> 110.0801 | AG114: gG,t = G,t/G,t-1/(CMRKTt/CMRKTt-1/gCMRKTt)
C115: Валовое накопление | K115: 96.8 | L115: 102.6 | M115: 163.97218 | N115: 187.05774 | O115: 132.71217 | P115: 76.8 | Q115: 107.5 | R115: 113.3 | S115: 78.1 | T115: 115.1 | U115: 117.6 | V115: 125.2 | W115: 93.4 | X115: 88 | Y115: 125.5 | Z115: 108.9 | AA115: 95.4 | AB115: 112 | AC115: 111.9 | AD115: 90.1 | AE115: =AE102/AD102/0.88*100 -> 272.49023 | AG115: gInvNAt = InvNAF,t/InvNAF,t-1/0,88·100
...

Sheet Agriculture
D1: 1997 | E1: 1998 | F1: 1999 | G1: 2000 | H1: 2001 | I1: 2002 | J1: 2003 | K1: 2004 | L1: 2005 | M1: 2006 | N1: 2007 | O1: 2008 | P1: 2009 | Q1: 2010 | R1: 2011 | S1: 2012 | T1: 2013 | U1: 2014 | V1: 2015 | W1: 2016 | X1: 2017 | Y1: 2018 | Z1: 2019 | AA1: 2020 | AB1: 2021 | AC1: 2022 | AD1: 2023 | AE1: 2024
B2: СЕЛЬСКОЕ ХОЗЯЙСТВО | C2: млн. Сомони | L2: 6855.9 | M2: 7246.7 | N2: 7500.4 | O2: 7957.9 | P2: 8793.5 | Q2: 9391.4 | R2: 14853.3 | S2: 16477.5 | T2: 16756.6 | U2: 21021.9 | V2: 21577.8 | W2: =W5+W8 -> 22907.672 | X2: =X5+X8 -> 24576 | Y2: =Y5+Y8 -> 26370.3 | Z2: =Z5+Z8 -> 27750.4 | AA2: =AA5+AA8 -> 37298.4 | AB2: =AB5+AB8 -> 39769.4 | AC2: =AC5+AC8 -> 49272.4 | AD2: =AD5+AD8 -> 63028.4 | AE2: =AE5+AE8 -> 73981.3
B3: темп роста | C3: % | L3: 101.6 | M3: 105.7 | N3: 103.5 | O3: 107.9 | P3: 110.5 | Q3: 106.8 | R3: 107.9 | S3: 110.4 | T3: 107.6 | U3: 104.5 | V3: 103.2 | W3: 105.2 | X3: 106.8 | Y3: 107 | Z3: 107 | AA3: 107.9 | AB3: 99.7 | AC3: 108 | AD3: 109 | AE3: 110.6
B4: дефлятор | C4: % | M4: 100.00019 | N4: 100.00087 | O4: 98.331487 | P4: 100.00023 | Q4: 99.999382 | R4: 146.5788 | S4: 100.48455 | T4: 94.51099 | U4: 120.0521 | V4: 99.461614 | W4: =W2/V2/W3*10000 -> 100.91554 | X4: =X2/W2/X3*10000 -> 100.45209 | Y4: =Y2/X2/Y3*10000 -> 100.28133 | Z4: =Z2/Y2/Z3*10000 -> 98.349102 | AA4: =AA2/Z2/AA3*10000 -> 124.566 | AB4: =AB2/AA2/AB3*10000 -> 106.94579 | AC4: =AC2/AB2/AC3*10000 -> 114.71783 | AD4: =AD2/AC2/AD3*10000 -> 117.35621 | AE4: =AE2/AD2/AE3*10000 -> 106.12814
B5: РАСТЕНИЕВОДСТВО | C5: млн. Сомони | L5: 4724.9 | M5: 5032 | N5: 5147.7 | O5: 5523.5 | P5: 6219.5 | Q5: 6617.5 | R5: 10894.7 | S5: 11836.3 | T5: 11502.5 | U5: 14532.8 | V5: 14623.7 | W5: 15066.6 | X5: 16977.8 | Y5: 18229.2 | Z5: 19279.7 | AA5: 27130 | AB5: 28743.9 | AC5: 33902 | AD5: 43365.7 | AE5: 50984.8
B6: темп роста | C6: % | L6: 98.6 | M6: 106.5 | N6: 102.3 | O6: 108.4 | P6: 112.6 | Q6: 106.4 | R6: 108.2 | S6: 110.6 | T6: 107.6 | U6: 104.5 | V6: 101.4 | W6: 105.1 | X6: 107.4 | Y6: 103.4 | Z6: 107.8 | AA6: 108.1 | AB6: 105.9 | AC6: 107.7 | AD6: 106.8 | AE6: 113.4
B7: дефлятор | C7: % | M7: 99.999632 | N7: 99.999301 | O7: 98.985561 | P7: 100.00063 | Q7: 99.999275 | R7: 152.15775 | S7: 98.230321 | T7: 90.315857 | U7: 120.90403 | V7: 99.236175 | W7: =W5/V5/W6*10000 -> 98.029158 | X7: =X5/W5/X6*10000 -> 104.92087 | Y7: =Y5/X5/Y6*10000 -> 103.84023 | Z7: =Z5/Y5/Z6*10000 -> 98.110141 | AA7: =AA5/Z5/AA6*10000 -> 130.17387 | AB7: =AB5/AA5/AB6*10000 -> 100.04605 | AC7: =AC5/AB5/AC6*10000 -> 109.51256 | AD7: =AD5/AC5/AD6*10000 -> 119.77048 | AE7: =AE5/AD5/AE6*10000 -> 103.67673
B8: ЖИВОТНОВОДСТВО | C8: млн. Сомони | L8: 2134.1 | M8: 2208.8 | N8: 2356.8 | O8: 2429.8 | P8: 2573.2 | Q8: 2773.9 | R8: 3958.6 | S8: 3958.6 | T8: 3958.6 | U8: 3958.6 | V8: 6954.1 | W8: 7841.0717 | X8: 7598.2 | Y8: 8141.1 | Z8: 8470.7 | AA8: 10168.4 | AB8: 11025.5 | AC8: 15370.4 | AD8: 19662.7 | AE8: 22996.5
B9: темп роста | C9: % | L9: 110.1 | M9: 103.5 | N9: 106.7 | O9: 106.7 | P9: 105.9 | Q9: 107.7 | R9: 107 | S9: 109.7 | T9: 107.5 | U9: 112.5 | V9: 107.2 | W9: 105.5 | X9: 105.6 | Y9: 105.3 | Z9: 105.7 | AA9: 110.7 | AB9: 108.4 | AC9: 108.7 | AD9: 114.1 | AE9: 104.9
B10: дефлятор | C10: % | M10: 100.00029 | N10: 100.00044 | O10: 96.623637 | P10: 100.00162 | Q10: 100.0925 | R10: 133.37273 | S10: 91.157703 | T10: 93.023256 | U10: 88.888889 | V10: 163.87191 | W10: =W8/V8/W9*10000 -> 106.87645 | X10: =X8/W8/X9*10000 -> 91.763797 | Y10: =Y8/X8/Y9*10000 -> 101.75224 | Z10: =Z8/Y8/Z9*10000 -> 98.437647 | AA10: =AA8/Z8/AA9*10000 -> 108.43905 | AB10: =AB8/AA8/AB9*10000 -> 100.0268 | AC10: =AC8/AB8/AC9*10000 -> 128.24999 | AD10: =AD8/AC8/AD9*10000 -> 112.11722 | AE10: =AE8/AD8/AE9*10000 -> 111.49184
W11: =W2-V2 -> 1329.8717 | X11: =X2-W2 -> 1668.3283 | Y11: =Y2-X2 -> 1794.3 | Z11: =Z2-Y2 -> 1380.1 | AA11: =AA2-Z2 -> 9548 | AB11: =AB2-AA2 -> 2471 | AC11: =AC2-AB2 -> 9503 | AD11: =AD2-AC2 -> 13756 | AE11: =AE2-AD2 -> 10952.9 | AF11: =AE2-U2 -> 52959.4
AB12: =AB8-AA8 -> 857.1 | AC12: =AC8-AB8 -> 4344.9 | AD12: =AD8-AC8 -> 4292.3 | AE12: =AE8-AD8 -> 3333.8
B13: Общая земельная площадь | C13: га | L13: 14255397 | M13: 14255397 | N13: 14255397 | O13: 14255397 | P13: 14255397 | Q13: 14255397 | R13: 14255397 | S13: 14255397 | T13: 14255397 | U13: 14137685 | V13: 14137685 | W13: 14137685 | X13: 14137685 | Y13: 14137900 | Z13: =Y13 -> 14137900 | AA13: 14137907 | AB13: 14137907 | AC13: =AB13 -> 14137907 | AD13: =AC13 -> 14137907 | AE13: =AD13 -> 14137907
B14: площадь орошаемых земель (оби) | C14: га | L14: 737694 | M14: 741539 | N14: 742051 | O14: 741626 | P14: 743621 | Q14: 743856 | R14: 748256 | S14: 749000 | T14: 749995 | U14: 753000 | V14: 753000 | W14: 753000 | X14: =W14 -> 753000 | Y14: 757842 | Z14: 762198 | AA14: 762198 | AB14: 762851 | AC14: 763930 | AD14: 763930 | AE14: 763930
B15: Всего СХ угодья | C15: га | L15: 4668470 | M15: 4728417 | N15: 4725644 | O15: 4719198 | P15: 4719486 | Q15: 4705044 | R15: 3695161 | S15: 3614663 | T15: 3617515 | U15: 3604616 | V15: 3611907 | W15: 3638485 | X15: 3658200 | Y15: 4702084 | Z15: 4706451 | AA15: 4704794 | AB15: =AA15 -> 4704794 | AC15: 4704410 | AD15: 4704410 | AE15: 4704410
B16: в том числе, | C16: га
B17: Пашня | C17: га | L17: 718560 | M17: 714162 | N17: 710493 | O17: 704823 | P17: 701856 | Q17: 685441 | R17: 666077 | S17: 662011 | T17: 658410 | U17: 655643 | V17: 653195 | W17: 650644 | X17: 657300 | Y17: 668267 | Z17: 674609 | AA17: 672404 | AB17: 672404 | AC17: 672609 | AD17: 672609 | AE17: 672609
B18: многолетние насождение | C18: га | L18: 101635 | M18: 103135 | N18: 105571 | O18: 105104 | P18: 109671 | Q18: 120662 | R18: 121000 | S18: 126500 | T18: 131800 | U18: 137000 | V18: 140400 | W18: 144400 | X18: 148200 | Y18: 154491 | Z18: 159112 | AA18: 160330 | AB18: =AA18 -> 160330 | AC18: 161231 | AD18: 161231 | AE18: 161231
B19: сенокосы | C19: га | L19: 20619 | M19: 21259 | N19: 21259 | O19: 21211 | P19: 21264 | Q19: 21269 | R19: 17200 | S19: 17300 | T19: 17300 | U19: 17500 | V19: 17600 | W19: 17400 | X19: 15800 | Y19: =X19 -> 15800 | Z19: 18514 | AA19: 18824 | AB19: =AA19 -> 18824 | AC19: =AB19 -> 18824 | AD19: =AC19 -> 18824 | AE19: =AD19 -> 18824
B20: пастбища | C20: га | L20: 3797566 | M20: 3857776 | N20: 3856246 | O20: 3856236 | P20: 3854742 | Q20: 3846564 | R20: 2857000 | S20: 2777900 | T20: 2780000 | U20: 2764800 | V20: 2771500 | W20: 2797500 | X20: 2809600 | Y20: =X20 -> 2809600 | Z20: 3832161 | AA20: 3831887 | AB20: =AA20 -> 3831887 | AC20: 3830626 | AD20: 3830627 | AE20: 3830628
B21: залежи | C21: га | L21: 30090 | M21: 32084 | N21: 32075 | O21: 31824 | P21: 31953 | Q21: 31108 | R21: 33800 | S21: 31000 | T21: 30000 | U21: 29700 | V21: 29300 | W21: 28500 | X21: 27100 | Y21: 28727 | Z21: 20686 | AA21: 20100 | AB21: =AA21 -> 20100 | AC21: =AB21 -> 20100 | AD21: =AC21 -> 20100 | AE21: =AD21 -> 20100
B23: РАСТЕНИЕВОДСТВО | AE23: =AE25*AE28/1000 -> 2920.1
B24: Зерновые | C24: пос. площадь -га | L24: 395565 | M24: 401912 | N24: 396880 | O24: 438152 | P24: 461741 | Q24: 459942 | R24: 427178 | S24: 424332 | T24: 437440 | U24: 412626 | V24: 422947 | W24: 423449 | X24: 411581.1 | Y24: 374941.2 | Z24: =Y24 -> 374941.2 | AA24: 391483.8 | AB24: 394442.5 | AC24: 390531 | AD24: 390922 | AE24: 390922
C25: тыс. тонн | L25: 934.9 | M25: 912.3 | N25: 931.2 | O25: 942.9 | P25: 1294.5 | Q25: 1261.1 | R25: 1098.2 | S25: 1232.6 | T25: 1392.6 | U25: 1317.8 | V25: 1392.6 | W25: 1435.8 | X25: 1447.6 | Y25: 1295.6 | Z25: 1414.8 | AA25: 1562.1 | AB25: 1586.6 | AC25: 1756.2 | AD25: 1754.9 | AE25: 1828.3
C26: Рост, %, тыс. тонн | U26: 94.628752 | V26: 105.67613 | W26: =W25/V25*100 -> 103.10211 | X26: =X25/W25*100 -> 100.82184 | Y26: 89.5 | Z26: 109.2 | AA26: 110.4 | AB26: =AB25/AA25*100 -> 101.5684 | AC26: =AC25/AB25*100 -> 110.68952 | AD26: =AD25/AC25*100 -> 99.925977 | AE26: =AE25/AD25*100 -> 104.18257
C27: млн. сомони | L27: х | M27: х | N27: х | O27: х | P27: 1344.6 | Q27: 1301.7 | R27: 2120.5 | S27: 2697 | T27: 2088.1 | U27: 2371.1 | V27: 2509.8 | W27: 2541.7 | X27: 2578.3 | Y27: 2307.5749 | Z27: 2519.8804 | AA27: 2782.2343 | AB27: 3527.8521 | AC27: 4674.9295 | AD27: 3851.8991 | AE27: 2920.1
C28: цена, сомони\тонну | R28: 1930.8869 | S28: 2188.0578 | T28: 1499.4255 | U28: 1799.2867 | V28: =V27/V25*1000 -> 1802.2404 | W28: =W27/W25*1000 -> 1770.2326 | X28: =X27/X25*1000 -> 1781.0859 | Y28: =Y27/Y25*1000 -> 1781.0859 | Z28: =Z27/Z25*1000 -> 1781.0859 | AA28: =AA27/AA25*1000 -> 1781.0859 | AB28: =AB27/AB25*1000 -> 2223.5296 | AC28: =AC27/AC25*1000 -> 2661.9574 | ... AE28: =AE27/AE25*1000 -> 1597.1668
C29: урожайность -ц/га | L29: 19.5 | M29: 20.6 | N29: 20.5 | O29: 20.9 | P29: 25.2 | Q29: 27.418675 | R29: 23.6 | S29: 25.3 | T29: 27.7 | U29: 28.1 | V29: 27.7 | W29: 28.4 | X29: =X25/X24*10000 -> 35.171683 | Y29: =Y25/Y24*10000 -> 34.554752 | Z29: =Z25/Z24*10000 -> 37.733917 | AA29: =AA25/AA24*10000 -> 39.902034 | AB29: =AB25/AB24*10000 -> 40.22386 | AC29: =AC25/AC24*10000 -> 44.969541 | AD29: =AD25/AD24*10000 -> 44.891308 | AE29: =AE25/AE24*10000 -> 46.768921
C30: урожайность стат.
B31: в том числе,
B32: пшеница | C32: пос. площадь -га | L32: 317738 | M32: 320694 | N32: 307961 | O32: 331766 | P32: 358766 | Q32: 342566 | R32: 311179 | S32: 303677 | T32: 318601 | U32: 292573 | V32: 295632 | W32: 297479 | X32: 285867 | Y32: 255548.8 | Z32: =Y32 -> 255548.8 | AA32: 269645.3 | AB32: 274747.7 | AC32: 271067 | AD32: 271338 | AE32: 271338
C33: тыс. тонн | L33: 618.5 | M33: 640.3 | N33: 649.3 | O33: 659.1 | P33: 938.4 | Q33: 857.5 | R33: 726.9 | S33: 812.6 | T33: 947.4 | U33: 868.4 | V33: 896.4 | W33: 917.1 | X33: 900.2 | Y33: 779 | Z33: 836.2 | AA33: 863.7 | AB33: 876.1 | AC33: 934.3 | AD33: 860.8 | AE33: 880.7
C34: млн. сомони | W34: 1336.4 | X34: 1295.97
C35: урожайность -ц/га | L35: 19.6 | M35: 19.9 | N35: 20.6 | O35: 20.6 | P35: 25.1 | Q35: 23.9 | R35: 23.359545 | S35: 26.758694 | T35: 29.736253 | U35: 29.681481 | V35: =V33/V32*10000 -> 30.321481 | W35: =W33/W32*10000 -> 30.829067 | X35: =X33/X32*10000 -> 31.490169 | Y35: =Y33/Y32*10000 -> 30.483415 | Z35: =Z33/Z32*10000 -> 32.721735 | AA35: =AA33/AA32*10000 -> 32.030968 | AB35: =AB33/AB32*10000 -> 31.887437 | AC35: =AC33/AC32*10000 -> 34.467493 | ... AE35: =AE33/AE32*10000 -> 32.457673
AE36: =AE38*AE41/1000 -> 1289.7
B37: Хлопок | C37: пос. площадь -га | L37: 288655 | M37: 262894 | N37: 254830 | O37: 237130 | P37: 168916 | Q37: 162428 | R37: 204110 | S37: 199254 | T37: 190925 | U37: 177637 | V37: 159492 | W37: 162558 | X37: 173979 | Y37: 185816.8 | Z37: 185435 | AA37: 185435 | AB37: 177048 | AC37: 181542 | AD37: 185540 | AE37: 185540
C38: тыс. тонн | L38: 447.9 | M38: 437.9 | N38: 419.7 | O38: 353.1 | P38: 296 | Q38: 310.9 | R38: 416.5 | S38: 418 | T38: 392.8 | U38: 372.7 | V38: 270 | W38: 284.7 | X38: 386.5 | Y38: 300.4 | Z38: 403 | AA38: 396 | AB38: 388.8 | AC38: 404.7 | AD38: 344.4 | AE38: 253.2
C39: млн. сомони | L39: 0 | M39: 0 | N39: 0 | O39: 0 | P39: 550.8 | Q39: 789.4 | R39: 1509.3 | S39: 1107.5 | T39: 1327.3 | U39: 1098.8 | V39: 807.5 | W39: 1276.2 | X39: 1744.98 | Y39: 1346.577 | Z39: 1806.4932 | AA39: 1775.1149 | AB39: 1742.84 | AC39: 1851.5953 | AD39: 1922.3224 | AE39: 1289.7
C40: урожайность -ц/га | L40: 15.6 | M40: 17 | N40: 16.6 | O40: 15.6 | P40: 17.8 | Q40: 19.3 | R40: 20.4 | S40: 21 | T40: 20.573524 | U40: 20.980989 | V40: 17.3 | W40: =W38/W37*10000 -> 17.513749 | X40: =22.4 -> 22.4 | Y40: =Y38/Y37*10000 -> 16.166461 | Z40: =Z38/Z37*10000 -> 21.732683 | AA40: =AA38/AA37*10000 -> 21.355192 | AB40: =AB38/AB37*10000 -> 21.960146 | AC40: =AC38/AC37*10000 -> 22.292362 | AD40: =AD38/AD37*10000 -> 18.562035 | AE40: =AE38/AE37*10000 -> 13.646653
C41: цена | V41: =V39/V38*1000 -> 2990.7407 | W41: =W39/W38*1000 -> 4482.6133 | X41: =X39/X38*1000 -> 4514.8254 | Y41: =Y39/Y38*1000 -> 4482.6133 | Z41: =Z39/Z38*1000 -> 4482.6133 | AA41: =AA39/AA38*1000 -> 4482.6133 | AB41: =AB39/AB38*1000 -> 4482.6133 | AC41: =AC39/AC38*1000 -> 4575.2293 | ... AE41: =AE39/AE38*1000 -> 5093.6019
B42: в том числе, | AE42: =AE48*AE51/1000 -> 1051.1
B43: хлопковолокно | C43: пос. площадь -га | L43: 17346 | M43: 25442 | N43: 14538 | O43: 8298 | P43: 897 | Q43: 775 | R43: 1943 | S43: 2023 | T43: 370 | U43: 135 | AD43: =AD44/1000 -> 5632.908 | AE43: =AE44/1000 -> 5776.48
C44: тонн | L44: 28463 | M44: 37099 | N44: 28320 | O44: 10753 | P44: 1988 | Q44: 1717 | R44: 4133 | S44: 3813 | T44: 615 | U44: 411 | AD44: =AD46*AD45 -> 5632908 | AE44: =AE46*AE45 -> 5776480
C45: млн. сомони | AC45: =AE48*AE43/1000 -> 7301.4707 | AD45: 4.92 | AE45: 4.57
C46: урожайность -ц/га | Q46: 22.2 | R46: 21.3 | S46: 18.8 | T46: 16.6 | U46: 17.2 | AC46: =AD48*AD43/1000 -> 6449.1164 | AD46: =AD48*1000 -> 1144900 | AE46: =AE48*1000 -> 1264000
B47: Картошка | C47: пос. площадь -га | L47: 27483 | M47: 27935 | N47: 29752 | O47: 28676 | P47: 29838 | Q47: 31764 | R47: 36720 | S47: 41738 | T47: 44380 | U47: 35543 | V47: 39782 | W47: 41577 | X47: 40615.1 | Y47: 50302.2 | Z47: 52730.8 | AA47: 52730.8 | AB47: 58238.6 | AC47: 56092 | AD47: 56148 | AE47: 56148
C48: тыс. тонн | L48: 555.1 | M48: 573.7 | N48: 662.1 | O48: 679.8 | P48: 690.8 | Q48: 760.1 | R48: 863.1 | S48: 991 | T48: 1115.7 | U48: 853.7 | V48: 887.4 | W48: 898.1 | X48: 782.9 | Y48: 964.6 | Z48: 994.4 | AA48: 1022.5 | AB48: 1041.3 | AC48: 1094.4 | AD48: 1144.9 | AE48: 1264
C49: млн. сомони | L49: х | M49: х | N49: х | O49: х | P49: 824.7 | Q49: 860.9 | R49: 1400.6 | S49: 1685.7 | T49: 1748.9 | U49: 1978.1 | V49: 2058.7 | W49: 1491 | X49: 1318.5 | Y49: 1318.5 | Z49: 1318.5 | AA49: 1318.5 | AB49: 1013.1988 | AC49: 1035.8012 | AD49: 928.85119 | AE49: 1051.1
C50: урожайность -ц/га | L50: 196.2 | M50: 198.5 | N50: 218.4 | O50: 226.9 | P50: 223.1 | Q50: 229.7 | R50: 228.3 | S50: 233.2 | T50: 247.3 | U50: 231 | V50: 221.7 | W50: 214.4 | X50: =X48/X47*10000 -> 192.76082 | Y50: =Y48/Y47*10000 -> 191.761 | Z50: =Z48/Z47*10000 -> 188.58049 | AA50: =AA48/AA47*10000 -> 193.90944 | AB50: =AB48/AB47*10000 -> 178.79894 | AC50: =AC48/AC47*10000 -> 195.10804 | AD50: =AD48/AD47*10000 -> 203.90753 | AE50: =AE48/AE47*10000 -> 225.11933
C51: цена | P51: 1193.8332 | Q51: 1132.6141 | R51: 1622.7552 | S51: 1701.0091 | T51: 1567.5361 | U51: 2317.0903 | V51: =V49/V48*1000 -> 2319.9234 | W51: =W49/W48*1000 -> 1660.1715 | X51: =X49/X48*1000 -> 1684.1231 | Y51: =Y49/Y48*1000 -> 1366.8878 | Z51: =Z49/Z48*1000 -> 1325.9252 | AA51: =AA49/AA48*1000 -> 1289.4866 | AB51: =AB49/AB48*1000 -> 973.01331 | AC51: =AC49/AC48*1000 -> 946.45577 | ... AE51: =AE49/AE48*1000 -> 831.56646
AE52: =AE54*AE57/1000 -> 7996.7
B53: Овощи | C53: пос. площадь -га | L53: 33429 | M53: 35768 | N53: 39110 | O53: 37162 | P53: 40803 | Q53: 44769 | R53: 46885 | S53: 48995 | T53: 50727 | U53: 48532 | V53: 55424 | W53: 58194 | X53: 59538 | Y53: 68298.2 | Z53: 70439.7 | AA53: 70439.7 | AB53: 71113.8 | AC53: 69992 | AD53: 70201 | AE53: 70201
C54: тыс. тонн | L54: 718.5 | M54: 759.7 | N54: 835.1 | O54: 908.2 | P54: 1046.8 | Q54: 1142.6 | R54: 1242 | S54: 1342.4 | T54: 1490.6 | U54: 1549.5 | V54: 1666.6 | W54: 1748.3 | X54: 1859.1 | Y54: 2119.4 | Z54: 2182.5 | AA54: 2480.6 | AB54: 2597.6 | AC54: 2714.8 | AD54: 3026.2 | AE54: 3289.2
C55: млн. сомони | L55: х | M55: х | N55: х | O55: х | P55: 1443.9 | Q55: 1736.3 | R55: 3218.3 | S55: 3275.7 | T55: 2869.1 | U55: 3812.2 | V55: 4002.9 | W55: 4752.2 | X55: 5012.2 | Y55: 5012.2 | Z55: 5012.2 | AA55: 5012.2 | AB55: 5676.6345 | AC55: 6157.9161 | AD55: 7110.4164 | AE55: 7996.7
C56: урожайность -ц/га | L56: 186.8 | M56: 186.9 | N56: 190.2 | O56: 198.8 | P56: 208 | Q56: 205.8 | R56: 216.5 | S56: 225.1 | T56: 240.3 | U56: 251.1 | V56: 247.9 | W56: 248.6 | X56: =256.8 -> 256.8 | Y56: =256.8 -> 256.8 | Z56: =256.8 -> 256.8 | AA56: =256.8 -> 256.8 | AB56: =AB54/AB53*10000 -> 365.27369 | AC56: =AC54/AC53*10000 -> 387.8729 | AD56: =AD54/AD53*10000 -> 431.07648 | AE56: =AE54/AE53*10000 -> 468.54033
C57: цена | P57: 1379.3466 | Q57: 1519.6044 | R57: 2591.2238 | S57: 2440.1818 | T57: 1924.7954 | U57: 2460.2775 | V57: =V55/V54*1000 -> 2401.8361 | W57: =W55/W54*1000 -> 2718.1834 | X57: =X55/X54*1000 -> 2696.0357 | Y57: =Y55/Y54*1000 -> 2364.9146 | Z57: =Z55/Z54*1000 -> 2296.5407 | AA57: =AA55/AA54*1000 -> 2020.5595 | AB57: =AB55/AB54*1000 -> 2185.3382 | AC57: =AC55/AC54*1000 -> 2268.2761 | ... AE57: =AE55/AE54*1000 -> 2431.1991
B58: в том числе,
B59: Лук | C59: пос. площадь -га | P59: 12478 | Q59: 14499 | R59: 15595 | S59: 16215 | T59: 17449 | U59: 15565
C60: тыс. тонн | L60: 201.4 | M60: 201.7 | N60: 251.6 | O60: 227.2 | P60: 268.5 | Q60: 302.3 | R60: 343.4 | S60: 368 | T60: 435.4 | U60: 420.8
C61: млн. сомони
C62: урожайность -ц/га | L62: 189.5 | M62: 194.5 | N62: 203.1 | O62: 212.2 | P62: 215 | Q62: 210.4 | R62: 221.3 | S62: 227.3 | T62: 248.7 | U62: 269.7 | AE62: =AE64*AE67/1000 -> 2129.2
B63: Бахчевые | C63: пос. площадь -га | L63: 9193 | M63: 9110 | N63: 11118 | O63: 11570 | P63: 19313 | Q63: 20951 | R63: 17218 | S63: 18409 | T63: 17353 | U63: 19399 | V63: 21358 | W63: 20069.2 | X63: 20296 | Y63: 19926.6 | Z63: 21900 | AA63: 22753.9 | AB63: 22270.7 | AC63: 20664 | AD63: 21490.6 | AE63: 21490.6
C64: тыс. тонн | L64: 170.2 | M64: 218.2 | N64: 254.2 | O64: 285.2 | P64: 424.6 | Q64: 482.4 | R64: 423.3 | S64: 465 | T64: 495.2 | U64: 545.7 | V64: 592.4 | W64: 594.2 | X64: 631.2 | Y64: 641.7 | Z64: 701.3 | AA64: 757 | AB64: 818.8 | AC64: 842.6 | AD64: 1009.9 | AE64: 1144.8
C65: млн. сомони | L65: х | M65: х | N65: х | O65: х | P65: 223.8 | Q65: 347.7 | R65: 507.7 | S65: 373.5 | T65: 585.1 | U65: 1055.2 | V65: 1132.3 | W65: 1093.5 | X65: 1170.1 | Y65: 1170.1 | Z65: 1170.1 | AA65: 1170.1 | AB65: 1368.8376 | AC65: 1462.0857 | AD65: 1815.2282 | AE65: 2129.2
C66: урожайность -ц/га | L66: 1145.7 | M66: 185.7 | N66: 189 | O66: 197.6 | P66: 202.9 | Q66: 230.25154 | R66: 245.84737 | S66: 252.59384 | T66: 285.36852 | U66: 281.30316 | V66: =V64/V63*10000 -> 277.36679 | W66: =W64/W63*10000 -> 296.07558 | X66: =263.3 -> 263.3 | Y66: =263.3 -> 263.3 | Z66: =263.3 -> 263.3 | AA66: =263.3 -> 263.3 | AB66: =AB64/AB63*10000 -> 367.65795 | AC66: =AC64/AC63*10000 -> 407.76229 | AD66: =AD64/AD63*10000 -> 469.92639 | AE66: =AE64/AE63*10000 -> 532.69802
C67: цена | P67: 527.08431 | Q67: 720.77114 | R67: 1199.3858 | S67: 803.22581 | T67: 1181.5428 | U67: 1933.6632 | V67: =V65/V64*1000 -> 1911.3774 | W67: =W65/W64*1000 -> 1840.2895 | X67: =X65/X64*1000 -> 1853.7706 | Y67: =Y65/Y64*1000 -> 1823.4377 | Z67: =Z65/Z64*1000 -> 1668.4728 | AA67: =AA65/AA64*1000 -> 1545.7067 | AB67: =AB65/AB64*1000 -> 1671.7607 | AC67: =AC65/AC64*1000 -> 1735.2073 | ... AE67: =AE65/AE64*1000 -> 1859.8882
Q68: 204.2 | R68: 205.9 | S68: 209.7 | T68: 223.8 | U68: 281.28866 | AE68: =AE70*AE73/1000 -> 3538.6
B69: Фрукты | C69: пос. площадь -га | L69: 60870 | M69: 67087 | N69: 69850 | O69: 73807 | P69: 73293 | Q69: 73850 | R69: 115423 | S69: 122009 | T69: 130682 | U69: 135430 | V69: 140344 | W69: 146565 | X69: 150312.8 | Y69: 158940.7 | Z69: 173700 | AA69: 176936 | AB69: =AA69+3000 -> 179936 | AC69: 116506 | AD69: 125006 | AE69: 125006
C70: тыс. тонн | L70: 148.3 | M70: 208.8 | N70: 157.2 | O70: 262.4 | P70: 213.9 | Q70: 224.7 | R70: 263.1 | S70: 313.2 | T70: 328.5 | U70: 341.3 | V70: 299.3 | W70: 364.1 | X70: 405 | Y70: 447.7 | Z70: 473.6 | AA70: 470.4 | AB70: 444.4 | AC70: 512.1 | AD70: 664.3 | AE70: 823
C71: млн. сомони | L71: х | M71: х | N71: х | O71: х | P71: 457.9 | Q71: 595.4 | R71: 1111.7 | S71: 1092.2 | T71: 1209.1 | U71: 1717.7 | V71: 1525.1 | W71: =V71*1.02 -> 1555.602 | X71: =W71*1.02 -> 1586.714 | Y71: =X71*1.02 -> 1618.4483 | Z71: =Y71*1.02 -> 1650.8173 | AA71: =Z71*1.02 -> 1683.8336 | AB71: =AA71*1.02 -> 1717.5103 | AC71: 2054.2692 | AD71: 2760.3764 | AE71: 3538.6
C72: урожайность -ц/га | L72: 24.3 | M72: 31.1 | N72: 22.5 | O72: 35.5 | P72: 29.2 | Q72: 30.4 | R72: 22.794417 | S72: 25.670237 | T72: 25.137356 | U72: 25.201211 | V72: =V70/V69*10000 -> 21.32617 | W72: =W70/W69*10000 -> 24.84222 | X72: =X70/X69*10000 -> 26.943813 | Y72: =Y70/Y69*10000 -> 28.167738 | Z72: =Z70/Z69*10000 -> 27.2654 | AA72: =AA70/AA69*10000 -> 26.585884 | AB72: =AB70/AB69*10000 -> 24.69767 | AC72: =AC70/AC69*10000 -> 43.954818 | ... AE72: =AE70/AE69*10000 -> 65.83684
C73: цена | P73: 2140.72 | Q73: 2649.7552 | R73: 4225.3896 | S73: 3487.2286 | T73: 3680.6697 | U73: 5032.8157 | V73: =V71/V70*1000 -> 5095.5563 | W73: =W71/W70*1000 -> 4272.4581 | X73: =X71/X70*1000 -> 3917.8124 | Y73: =Y71/Y70*1000 -> 3615.0286 | Z73: =Z71/Z70*1000 -> 3485.6784 | AA73: =AA71/AA70*1000 -> 3579.5783 | AB73: =AB71/AB70*1000 -> 3864.7847 | AC73: =AC71/AC70*1000 -> 4011.461 | ... AE73: =AE71/AE70*1000 -> 4299.6355
AE74: =AE76*AE79/1000 -> 1908.6
B75: Виноград | C75: пос. площадь -га | L75: 31452 | M75: 31745 | N75: 32838 | O75: 31944 | P75: 31419 | Q75: 30470 | R75: 36508 | S75: 36511 | T75: 37812 | U75: 36125 | V75: 38707 | W75: 37061 | X75: 33300 | Y75: 38106 | Z75: =Y75*1.02 -> 38868.12 | AA75: =Z75*1.02 -> 39645.482 | AB75: =AA75*1.02 -> 40438.392 | AC75: 35549 | AD75: 36486 | AE75: 36486
C76: тыс. тонн | L76: 90.7 | M76: 107.2 | N76: 116.9 | O76: 117.9 | P76: 138.7 | Q76: 124.3 | R76: 154.7 | S76: 167.1 | T76: 175.2 | U76: 188.8 | V76: 203.8 | W76: 214.8 | X76: 228.3 | Y76: 241.8 | Z76: 247.2 | AA76: 239.9 | AB76: 267.5 | AC76: 301.1 | AD76: 190.4 | AE76: 290
C77: млн. сомони | L77: х | M77: х | N77: х | O77: х | P77: 298.4 | Q77: 490.3 | R77: 492.3 | S77: 621.1 | T77: 793 | U77: 1130 | V77: 1212.5 | W77: 1279.1 | X77: 1419.2 | Y77: 1419.2 | Z77: 1419.2 | AA77: 1419.2 | AB77: 1582.476 | AC77: 1848.8487 | AD77: 1211.0416 | AE77: 1908.6
C78: урожайность -ц/га | L78: 28.8 | M78: 33.1 | N78: 35.6 | O78: 36.9 | P78: 44.1 | Q78: 40.8 | R78: 42.374274 | S78: 45.767029 | T78: 46.334497 | U78: 52.262976 | V78: =V76/V75*10000 -> 52.651975 | W78: =W76/W75*10000 -> 57.958501 | X78: =X76/X75*10000 -> 68.558559 | Y78: =Y76/Y75*10000 -> 63.454574 | Z78: =Z76/Z75*10000 -> 63.59968 | AA78: =AA76/AA75*10000 -> 60.511308 | AB78: =AB76/AB75*10000 -> 66.150009 | AC78: =AC76/AC75*10000 -> 84.699992 | ... AE78: =AE76/AE75*10000 -> 79.482541
C79: цена | P79: 2151.4059 | Q79: 3944.4891 | R79: 3182.2883 | S79: 3716.936 | T79: 4526.2557 | U79: 5985.1695 | V79: =V77/V76*1000 -> 5949.4603 | W79: =W77/W76*1000 -> 5954.8417 | X79: =X77/X76*1000 -> 6216.382 | Y79: =Y77/Y76*1000 -> 5869.3135 | Z79: =Z77/Z76*1000 -> 5741.1003 | AA79: =AA77/AA76*1000 -> 5915.7982 | AB79: =AB77/AB76*1000 -> 5915.7982 | AC79: =AC77/AC76*1000 -> 6140.3146 | ... AE79: =AE77/AE76*1000 -> 6581.3793
R80: 534.3 | S80: 983.6 | T80: 881.9 | U80: 1369.7
B81: Прочее | L81: 109912 | M81: 131368 | N81: 130315 | O81: 108238 | P81: 122587 | Q81: 87710 | R81: 86042 | S81: 94881 | T81: 91823 | U81: 104620 | V81: =V5-V27-V39-V49-V55-V65-V71-V77 -> 1374.9 | W81: =W5-W27-W39-W49-W55-W65-W71-W77 -> 1077.298 | X81: =X5-X27-X39-X49-X55-X65-X71-X77 -> 2147.806 | Y81: =Y5-Y27-Y39-Y49-Y55-Y65-Y71-Y77 -> 4036.5997 | Z81: =Z5-Z27-Z39-Z49-Z55-Z65-Z71-Z77 -> 4382.5092 | AA81: =AA5-AA27-AA39-AA49-AA55-AA65-AA71-AA77 -> 11968.817 | AB81: =AB5-AB27-AB39-AB49-AB55-AB65-AB71-AB77 -> 12114.551 | AC81: =AC5-AC27-AC39-AC49-AC55-AC65-AC71-AC77 -> 14816.554 | ... AE81: =AE5-AE27-AE39-AE49-AE55-AE65-AE71-AE77 -> 30150.8
B82: пос. площадь для корм животных | C82: (ГА) | Q82: 318.6 | R82: 349.1 | V82: =V27+V39+V49+V55+V65+V71+V77 -> 13248.8 | W82: =W27+W39+W49+W55+W65+W71+W77 -> 13989.302 | X82: =X27+X39+X49+X55+X65+X71+X77 -> 14829.994 | Y82: =Y27+Y39+Y49+Y55+Y65+Y71+Y77 -> 14192.6 | Z82: =Z27+Z39+Z49+Z55+Z65+Z71+Z77 -> 14897.191 | AA82: =AA27+AA39+AA49+AA55+AA65+AA71+AA77 -> 15161.183 | AB82: =AB27+AB39+AB49+AB55+AB65+AB71+AB77 -> 16629.349 | AC82: =AC27+AC39+AC49+AC55+AC65+AC71+AC77 -> 19085.446 | ... AE82: =AE27+AE39+AE49+AE55+AE65+AE71+AE77 -> 20834
C83: продуктивность | V83: =V5-V82 -> 1374.9 | W83: =W5-W82 -> 1077.298 | X83: =X5-X82 -> 2147.806 | Y83: =Y5-Y82 -> 4036.5997 | Z83: =Z5-Z82 -> 4382.5092 | AA83: =AA5-AA82 -> 11968.817 | AB83: =AB5-AB82 -> 12114.551 | AC83: =AC5-AC82 -> 14816.554 | ... AE83: =AE5-AE82 -> 30150.8
B84: 2. Животноводство | Q84: 2773.9 | R84: 3958.6 | S84: 3958.6 | T84: 3958.6 | U84: 3958.6 | V84: 6954.1 | W84: 7841.0717 | X84: 7598.2
B85: Мясо (в живом весе) | C85: тыс. тонн | L85: 107 | M85: 111.7 | N85: 119 | O85: 129.8 | P85: 134.3 | Q85: 143.2 | R85: 150.7 | S85: 162 | T85: 173 | U85: 198.7 | V85: 217.7 | W85: 233.3 | X85: =W85*1.2 -> 279.96 | Y85: =X85*1.2 -> 335.952 | Z85: =Y85*1.2 -> 403.1424 | AA85: =Z85*1.2 -> 483.77088 | AB85: =AA85*1.2 -> 580.52506 | AC85: =AB85*1.2 -> 696.63007 | AD85: =AC85*1.2 -> 835.95608 | AE85: =AD85*1.2 -> 1003.1473
C86: млн. сомони | L86: х | M86: х | N86: х | O86: х | P86: 1044.2 | Q86: 1289.4 | R86: 1906.6 | S86: 2197.1 | T86: 2457.1 | U86: 3457.6 | V86: 3819.6
C87: тыс. голов
B88: в том числе,
B89: крупный рогатый скот | C89: тыс. тонн
C90: млн. сомони
C91: тыс. голов | L91: 1371.9 | M91: 1422.6 | N91: 1702.5 | O91: 1799.5 | P91: 1830 | Q91: 1896.9 | R91: 2010.8 | S91: 2043.7 | T91: 2099.1 | U91: 2128.2
B92: в том числе,
B93: Яки | C93: тыс. тонн
C94: млн. сомони
C95: тыс.голов | L95: 14.5 | M95: 15.1 | N95: 15.2 | O95: 9.3 | P95: 19.8 | Q95: 21.5 | R95: 23.4 | S95: 23.1 | T95: 25.5 | U95: 26.1
B96: овцы и козы | C96: тыс. тонн
C97: млн. сомони
C98: тыс. поголовье | Q98: 4394.2 | R98: 4618.6 | S98: 4732.5 | T98: 4923.6 | U98: 5056.6
B99: птица всех видов | C99: тыс. тонн
C100: млн. сомони
C101: тыс. голов | L101: 2451.1 | M101: 2579.8 | N101: 3280.4 | O101: 3682.8 | P101: 3938.5 | Q101: 4402.7 | R101: 4655.9 | S101: 4851.1 | T101: 5020.5 | U101: 5248
...

Sheet Industry
B1: Var. Name | C1: Наименование индикатора | D1: 1997 | E1: 1998 | F1: 1999 | G1: 2000 | H1: 2001 | I1: 2002 | J1: 2003 | K1: 2004 | L1: 2005 | M1: 2006 | N1: 2007 | O1: 2008 | P1: 2009 | Q1: 2010 | R1: 2011 | S1: 2012 | T1: 2013 | U1: 2014 | V1: 2015 | W1: 2016 | X1: 2017 | Y1: 2018 | Z1: 2019 | AA1: 2020 | AB1: 2021 | AC1: 2022 | AD1: 2023 | AE1: 2024
C2: Промышленность | W2: =W4-V4 -> 2894 | X2: =X4-W4 -> 4938.512 | Y2: =Y4-X4 -> 3865.388 | Z2: =Z4-Y4 -> 3719.4 | AA2: =AA4-Z4 -> 3276.7 | AB2: =AB4-AA4 -> 7939 | AC2: =AC4-AB4 -> 3392.4 | AD2: =AD4-AC4 -> 4594.6 | AE2: =AE4-AD4 -> 7003
C3: Номиналы, млн. сомони
B4: INDCDE,t | C4: Промышленное производство | I4: 2418 | J4: 3205 | K4: 3952 | L4: 4278 | M4: 4663 | N4: 5571 | O4: 6106 | P4: 6501 | Q4: 6164.7 | R4: 7862 | S4: 9504 | T4: 9952 | U4: 10534.657 | V4: =V5+V8+V15 -> 12196 | W4: =W5+W8+W15 -> 15090 | X4: =X5+X8+X15 -> 20028.512 | Y4: =Y5+Y8+Y15 -> 23893.9 | Z4: =Z5+Z8+Z15 -> 27613.3 | AA4: =AA5+AA8+AA15 -> 30890 | AB4: =AB5+AB8+AB15 -> 38829 | AC4: =AC5+AC8+AC15 -> 42221.4 | AD4: =AD5+AD8+AD15 -> 46816 | AE4: =AE5+AE8+AE15+AE17 -> 53819
B5: INDC,t | C5: Добыча полезных ископаемых | Q5: 755 | R5: 975 | S5: 1227 | T5: 1117 | U5: 1402 | V5: =V6+V7 -> 1641 | W5: =W6+W7 -> 3004 | X5: =X6+X7 -> 4523.512 | Y5: =Y6+Y7 -> 4685.9 | Z5: =Z6+Z7 -> 4853.3 | AA5: =AA6+AA7 -> 4309 | AB5: =AB6+AB7 -> 8409 | AC5: =AC6+AC7 -> 8890.9 | ... AE5: =AE6+AE7 -> 13363.1
B6: INDC13,t | C6: Добыча неэнергетических материалов | Q6: 677 | R6: 900 | S6: 1115 | T6: 804 | U6: 1175 | V6: 1438 | W6: 2782 | X6: 4225.986 | Y6: 4355.2 | Z6: 4476.7 | AA6: 3880 | AB6: 7924 | AC6: 8309 | AD6: 8795 | AE6: 12653.6
B7: INDCOther,t | C7: Добыча энергетических материалов | Q7: 78 | R7: 75 | S7: 112 | T7: 313 | U7: 227 | V7: 203 | W7: 222 | X7: 297.526 | Y7: 330.7 | Z7: 376.6 | AA7: 429 | AB7: 485 | AC7: 581.9 | AD7: 578 | AE7: 709.5
B8: INDDJ, t | C8: Обрабатывающая промышленность | Q8: 3959.3 | R8: 5428 | S8: 6536 | T8: 6916 | U8: 6959 | V8: 8006 | W8: 9368 | X8: 11776 | Y8: 13520 | Z8: 15952 | AA8: 19054 | AB8: 22313 | AC8: 25708.7 | AD8: 28459.8 | AE8: 30275.6
B9: INDDA, t | C9: пищевые продукты и табак | I9: 432.822 | J9: 493.57 | K9: 624.416 | L9: 834.21 | M9: 918.611 | N9: 1169.91 | O9: 1263.942 | P9: 1358.709 | Q9: 3048 | R9: 2442 | S9: 3318 | T9: 3588 | U9: 3266 | V9: 3482 | W9: 3690 | X9: 4304 | Y9: 4900 | Z9: 5399 | AA9: 7089 | AB9: 7608 | AC9: 10099 | AD9: 11610 | AE9: 11445.7
B10: INDDB, t | C10: текстильное производство | I10: 431.7 | J10: 696 | K10: 708.9 | L10: 751.1 | M10: 647.3 | N10: 813.2 | O10: 732 | P10: 705.3 | Q10: 534.3 | R10: 1414 | S10: 1533 | T10: 1361 | U10: 1315 | V10: 1292 | W10: 1520 | X10: 2354 | Y10: 2479 | Z10: 2636 | AA10: 2870 | AB10: 4096 | AC10: 4438 | AD10: 4632 | AE10: 4062.5
B11: INDDJ, t | C11: металлургическое производство и готовые металлические изделия | I11: 1182 | J11: 1430 | K11: 1817 | L11: 1799 | M11: 2092 | N11: 2273 | O11: 2400 | P11: 2510 | Q11: 886.5 | R11: 786 | S11: 835 | T11: 1034 | U11: 915 | V11: 1450.2 | W11: 1850 | X11: 2187.3 | Y11: 2708.4 | Z11: 3873.5 | AA11: 4978 | AB11: 5967 | AC11: 6025 | AD11: 6442 | AE11: 8090.7
B12: INDD27, t | C12: металлургическое производство | Q12: 700 | R12: 727 | S12: 681.07801 | T12: 880.2 | U12: 724 | V12: =V11-V13 -> 1202.6249 | W12: =W11-W13 -> 1557.4819 | X12: =X11-X13 -> 1932.7978 | Y12: =Y11-Y13 -> 2455.2806 | Z12: =Z11-Z13 -> 3768.9349 | AA12: =AA11-AA13 -> 4883.6227 | AB12: =AB11-AB13 -> 5845.5362 | AC12: =AC11-AC13 -> 5903.6407 | ... AE12: =AE11-AE13 -> 7962.559
B13: INDD28, t | C13: готовые металлические изделия | Q13: 100 | R13: 92.2 | S13: 73.318359 | T13: 148.6 | U13: 179.1 | V13: 247.57509 | W13: 292.51809 | X13: 254.50217 | Y13: 253.11944 | Z13: 104.56511 | AA13: 94.377342 | AB13: 121.46379 | AC13: 121.35925 | AD13: 122.87853 | AE13: 128.14095
B14: INDDOther, t | C14: переработка прочие (d) | I14: =I4-I15-I11-I10-I9 -> 231.234 | J14: 345.055 | K14: 568.516 | L14: 619.898 | M14: 715.983 | N14: 930.491 | O14: 1062.822 | P14: 1029.853 | Q14: -509.5 | R14: 786 | S14: 850 | T14: 933 | U14: 1463 | V14: 1781.8 | W14: 2308 | X14: 2930.7 | Y14: 3432.6 | Z14: 4043.5 | AA14: 4117 | AB14: 4642 | AC14: 5146.7 | AD14: 5775.8 | AE14: =AE8-AE9-AE10-AE11-AE13 -> 6548.559
B15: INDE, t | C15: Производство и распределение электроэнергии, газа и воды | I15: 140.244 | J15: 240.375 | K15: 233.168 | L15: 273.792 | M15: 289.106 | N15: 384.399 | O15: 647.236 | P15: 897.138 | Q15: 1450.4 | R15: 1459 | S15: 1741 | T15: 1919 | U15: 2173.657 | V15: 2549 | W15: 2718 | X15: 3729 | Y15: 5688 | Z15: 6808 | AA15: 7527 | AB15: 8107 | AC15: 7621.8 | AD15: 8983.2 | AE15: 9872.2
Z16: =Z4-Y4 -> 3719.4 | AA16: =AA4-Z4 -> 3276.7 | AB16: =AB4-AA4 -> 7939 | AC16: =AC4-AB4 -> 3392.4 | AD16: =AD4-AC4 -> 4594.6 | AE16: =AE4-AD4 -> 7003
B17: Секция Е (36-39) | C17: Водоснабжение, очистка, обработка отходов и получение вторичного сырья | X17: 87.1 | Y17: 132.5 | Z17: 181.6 | AA17: 168.5 | AB17: 184.6 | AC17: 188.4 | AD17: 228.8 | AE17: 308.1
A18: Реальные темпы роста, % | B18: gINDCDE,t | C18: Все промышленность | I18: 108.4 | J18: 109.9 | K18: 115.1 | L18: 110.4 | M18: 105.5 | N18: 109.9 | O18: 96.5 | P18: 93.5 | Q18: 109.2 | R18: 105.7 | S18: 110.8 | T18: 103.8 | U18: 105 | V18: 111.3 | W18: 116 | X18: 121.3 | Y18: 110.6 | Z18: 113.2 | AA18: 108.8 | AB18: 120.8 | AC18: 115.4 | AD18: 112 | AE18: 120
A19: Т/Р | B19: gINDC,t | C19: Добыча полезных ископаемых | R19: 134.3 | S19: 121.2 | T19: 143.1 | U19: 124.5 | V19: 117.9 | W19: 153.3 | X19: 121.7 | Y19: 112 | Z19: 112.6 | AA19: 97.4 | AB19: 155.2 | AC19: 97.7 | AD19: 111.7 | AE19: 143
B20: gINDC13,t | C20: Добыча неэнергетических материалов | R20: 136.4 | S20: 120.6 | T20: 122.2 | U20: 145.7 | V20: 123 | W20: 156.7 | X20: 120.3 | Y20: 113 | Z20: 113.3 | AA20: 96.5 | AB20: 160.5 | AC20: 117.7 | AD20: 113.1 | AE20: 145.2
B21: gINDCOther,t | C21: Добыча энергетических материалов | R21: 113.5 | S21: 126.9 | T21: 255.1 | U21: 68.5 | V21: 90.9 | W21: 119 | X21: 137.1 | Y21: 108.2 | Z21: 103.1 | AA21: 103.6 | AB21: 106.8 | AC21: 100.1 | AD21: 99.2 | AE21: 116.5
B22: gINDD, t | C22: Обрабатывающая промышленность | R22: 103.3 | S22: 110.2 | T22: 99 | U22: 100.9 | V22: 110.1 | W22: 112.5 | X22: 122.9 | Y22: 112.1 | Z22: 115.3 | AA22: 114.1 | AB22: 115.3 | AC22: 116.4 | AD22: 112.4 | AE22: 107.6
B23: gINDDA, t | C23: пищевые продукты и табак | I23: 102.7 | J23: 102.9 | K23: 117.3 | L23: 129.1 | M23: 107.1 | N23: 121.6 | O23: 102.4 | P23: 94.4 | Q23: 116.1 | R23: 102.1 | S23: 106.6 | T23: 100.8 | U23: 92.9 | V23: 103.5 | W23: 105.4 | X23: 115.6 | Y23: 117.6 | Z23: 107.7 | AA23: 125.9 | AB23: 103.3 | AC23: 132 | AD23: 127 | AE23: 110
B24: gINDDB, t | C24: текстильное производство | I24: 124.9 | J24: 117.8 | K24: 113.2 | L24: 111.9 | M24: 91.7 | N24: 115.3 | O24: 86 | P24: 91.1 | Q24: 113 | R24: 116.3 | S24: 128.2 | T24: 90.1 | U24: 92.9 | V24: 94.4 | W24: 103.8 | X24: 130.9 | Y24: 92.1 | Z24: 118.8 | AA24: 113.5 | AB24: 109.5 | AC24: 107.3 | AD24: 110.4 | AE24: 93
B25: gINDDJ, t | C25: металлургическое производство и готовые металлические изделия | I25: 105.3 | J25: 104.1 | K25: 114.8 | L25: 105.1 | M25: 108.6 | N25: 101.3 | O25: 96.3 | P25: 92.4 | Q25: 103 | R25: 83.6 | S25: 102.7 | T25: 96 | U25: 86.8 | V25: 130.3 | W25: 104.7 | X25: 109.4 | Y25: 110.7 | Z25: 142.2 | AA25: 109.4 | AB25: 109.4 | AC25: 103.4 | AD25: 102.7 | AE25: 113.5
B26: gINDD27J, t | C26: металлургическое производство | R26: 80.7 | S26: 158321.32 | T26: 70.080396 | U26: 80.6 | V26: 139.49313 | W26: 81.716387 | X26: 81.734833 | Y26: 93.476349 | Z26: 102.18957 | AA26: 89.702999 | AB26: 64.107442 | AC26: 101.64246 | AD26: =(AC156*AD152/AC152+AD159*AD154/AC154)/(AC156+AC159)*100 -> 104.39341 | AE26: =(AD156*AE152/AD152+AE159*AE154/AD154)/(AD156+AD159)*100 -> 129.33687
B27: gINDD28, t | C27: готовые металлические изделия | R27: 127.9 | S27: 72.673905 | T27: 79.412844 | U27: 115.9 | V27: 110.6603 | W27: 92.954709 | X27: 79.737046 | Y27: 92.919496 | Z27: 105.15921 | AA27: 83.333333 | AB27: 72.039498 | AC27: 102.47934 | AD27: =(AC158*AD153/AC153+AC159*AD154/AC154)/(AC158+AC159)*100 -> 107.41935 | AE27: =(AD158*AE153/AD153+AD159*AE154/AD154)/(AD158+AD159)*100 -> 123.42342
B28: gINDDther, t | C28: переработка прочие (d) | R28: 75.477134 | S28: 96.503053 | T28: 110.97212 | U28: 158.96152 | V28: 126.31196 | W28: 139.03169 | X28: 140.12357 | Y28: 121.13205 | Z28: 102.39653 | AA28: 103.23784 | AB28: 147.13974 | AC28: =(AC22*AB8-SUMPRODUCT(AB9:AB11,AC23:AC25))/AB14 -> 115.57273 | AD28: =(AD22*AC8-SUMPRODUCT(AC9:AC11,AD23:AD25))/AC14 -> 96.831403 | AE28: =(AE22*AD8-SUMPRODUCT(AD9:AD11,AE23:AE25))/AD14 -> 107.90392
B29: gINDE, t | C29: Производство и распределение электроэнергии, газа и воды | I29: 107.6 | J29: 106.6 | K29: 98.1 | L29: 104.4 | M29: 105.5 | N29: 105.6 | O29: 93.4 | P29: 97.7 | Q29: 104.4 | R29: 100.5 | S29: 106.4 | T29: 105.6 | U29: 106.8 | V29: 111.5 | W29: 103.7 | X29: 116.5 | Y29: 107.5 | Z29: 105.6 | AA29: 100.1 | AB29: 112.7 | AC29: 117.5 | AD29: 107.1 | AE29: 105.7
AE30: 134.9
B31: gINDD27J, t | C31: металлургическое производство | V31: 139.49313 | W31: 81.716387 | X31: 81.734833 | Y31: 93.476349 | Z31: 102.18957 | AA31: 89.702999 | AB31: 64.107442 | AC31: 101.64246 | AD31: 104.4737 | AE31: 129.06373
C32: Дефлятор, %
B33: defINDCDE,t | C33: Все промышленность | J33: 120.60742 | K33: 107.13061 | L33: 98.051619 | M33: 103.31709 | N33: 108.71014 | O33: 113.57855 | P33: 113.87064 | Q33: 86.837866 | R33: 120.65522 | S33: 109.10223 | T33: 100.88035 | U33: 100.81397 | V33: 114.7 | W33: 101.7 | X33: 101.8 | Y33: 101.1 | Z33: 105.4 | AA33: 105.9 | AB33: =AB4/AA4/AB18*10000 -> 104.05701 | AC33: =AC4/AB4/AC18*10000 -> 94.22597 | AD33: =AD4/AC4/AD18*10000 -> 99.001928 | AE33: =AE4/AD4/AE18*10000 -> 95.798801
B34: defINDC,t | C34: Добыча полезных ископаемых | R34: 96.157165 | S34: 103.83346 | T34: 63.616384 | U34: 100.81508 | V34: 163.9 | W34: 84.9 | X34: 90.1 | Y34: 100.3 | Z34: 107.7 | AA34: 116.7 | AB34: =AB5/AA5/AB19*10000 -> 125.74078 | AC34: =AC5/AB5/AC19*10000 -> 108.21982 | AD34: =AD5/AC5/AD19*10000 -> 94.379945 | AE34: =AE5/AD5/AE19*10000 -> 99.699404
B35: defINDC13,t | C35: Добыча неэнергетических материалов | R35: 97.462932 | S35: 102.72711 | T35: 59.007875 | U35: 100.30493 | V35: 96.8 | W35: 96.6 | X35: 103.7 | Y35: 116 | Z35: 106.4 | AA35: 112.3 | AB35: =AB6/AA6/AB20*10000 -> 127.24411 | AC35: =AC6/AB6/AC20*10000 -> 89.089768 | AD35: =AD6/AC6/AD20*10000 -> 93.58893 | AE35: =AE6/AD6/AE20*10000 -> 99.08585
B36: defINDCOther,t | C36: Добыча энергетических материалов | R36: 84.717045 | S36: 117.67796 | T36: 109.55088 | U36: 105.8744 | V36: 173.6 | W36: 83.4 | X36: 89.2 | Y36: 99.2 | Z36: 108.3 | AA36: 117.5 | AB36: =AB7/AA7/AB21*10000 -> 105.85544 | AC36: =AC7/AB7/AC21*10000 -> 119.85952 | AD36: 115 | AE36: =AE7/AD7/AE21*10000 -> 105.36555
B37: defINDD,t | C37: Обрабатывающая промышленность | R37: 132.71533 | S37: 109.2674 | T37: 106.88278 | U37: 99.724229 | V37: 102.7 | W37: 102 | X37: 102.8 | Y37: 101.5 | Z37: 104.5 | AA37: 104.8 | AB37: =AB8/AA8/AB22*10000 -> 101.56463 | AC37: =AC8/AB8/AC22*10000 -> 98.984951 | AD37: =AD8/AC8/AD22*10000 -> 98.488476 | AE37: =AE8/AD8/AE22*10000 -> 98.866382
B38: defINDDA, t | C38: пищевые продукты и табак | J38: 136.86169 | K38: 89.976544 | L38: 94.68533 | M38: 93.980664 | N38: 108.95884 | O38: 104.66832 | P38: 105.7656 | Q38: 67.039821 | R38: 78.470235 | S38: 127.45988 | T38: 107.2792 | U38: 97.982391 | V38: 101.1 | W38: 100.5 | X38: 101.7 | Y38: 102.6 | Z38: 104.1 | AA38: 108.4 | AB38: 103.89274 | AC38: 100.56201 | AD38: =Monetary!AD5 -> 103.6 | AE38: =Monetary!AE5 -> 102.2
B39: defINDDB, t | C39: текстильное производство | J39: 110.82151 | K39: 107.85176 | L39: 103.48446 | M39: 102.81744 | N39: 104.73389 | O39: 105.50541 | P39: 113.87472 | Q39: 193.22187 | R39: 227.55402 | S39: 84.567739 | T39: 98.535149 | U39: 104.00445 | V39: 120.7 | W39: 111.6 | X39: 106.3 | Y39: 94.2 | Z39: 99.5 | AA39: 113.4 | AB39: =AB10/AA10/AB24*10000 -> 130.33586 | AC39: =AC10/AB10/AC24*10000 -> 100.9782 | AD39: =AD10/AC10/AD24*10000 -> 94.539256 | AE39: =AE10/AD10/AE24*10000 -> 94.306554
B40: defINDDJ, t | C40: металлургическое производство и готовые металлические изделия | J40: 116.21651 | K40: 110.682 | L40: 94.204906 | M40: 107.07811 | N40: 107.25766 | O40: 109.64416 | P40: 113.18543 | Q40: 34.290024 | R40: 106.05656 | S40: 103.44118 | T40: 128.99202 | U40: 101.9485 | V40: 111.4 | W40: 110.7 | X40: 105.9 | Y40: 100.4 | Z40: 131.3 | AA40: 99 | AB40: =AB11/AA11/AB25*10000 -> 109.56802 | AC40: =AC11/AB11/AC25*10000 -> 97.65185 | AD40: =AD11/AC11/AD25*10000 -> 104.11019 | AE40: =AE11/AD11/AE25*10000 -> 110.65461
B41: defINDD27, t | C41: металлургическое производство | R41: 128.69534 | S41: 0.059172927 | T41: 184.41148 | U41: 102.05215 | V41: 119.07999 | W41: =W12/V12/W31*10000 -> 158.48336 | X41: =X12/W12/X31*10000 -> 151.82953 | Y41: =Y12/X12/Y31*10000 -> 135.89797 | Z41: =Z12/Y12/Z31*10000 -> 150.21418 | AA41: =AA12/Z12/AA31*10000 -> 144.44965 | AB41: =AB12/AA12/AB31*10000 -> 186.71268 | AC41: =AC12/AB12/AC31*10000 -> 99.362016 | AD41: =AD12/AC12/AD31*10000 -> 102.45421 | AE41: =(Assumptions!AE7/Assumptions!AD7)*(Assumptions!AE12/Assumptions!AD12)*100 -> 106.37114
B42: defINDD28, t | C42: готовые металлические изделия | R42: 72.087568 | S42: 109.42167 | T42: 255.22036 | U42: 103.99042 | V42: 124.91641 | W42: =(Assumptions!W7/Assumptions!V7)*(Assumptions!W12/Assumptions!V12)*100 -> 122.48758 | X42: =(Assumptions!X7/Assumptions!W7)*(Assumptions!X12/Assumptions!W12)*100 -> 133.83937 | Y42: =(Assumptions!Y7/Assumptions!X7)*(Assumptions!Y12/Assumptions!X12)*100 -> 114.69431 | Z42: =(Assumptions!Z7/Assumptions!Y7)*(Assumptions!Z12/Assumptions!Y12)*100 -> 89.004639 | AA42: =(Assumptions!AA7/Assumptions!Z7)*(Assumptions!AA12/Assumptions!Z12)*100 -> 109.65171 | AB42: =(Assumptions!AB7/Assumptions!AA7)*(Assumptions!AB12/Assumptions!AA12)*100 -> 150.43482 | AC42: =(Assumptions!AC7/Assumptions!AB7)*(Assumptions!AC12/Assumptions!AB12)*100 -> 97.068533 | AD42: =(Assumptions!AD7/Assumptions!AC7)*(Assumptions!AD12/Assumptions!AC12)*100 -> 88.973632 | AE42: =(Assumptions!AE7/Assumptions!AD7)*(Assumptions!AE12/Assumptions!AD12)*100 -> 106.37114
B43: defINDDther, t | C43: переработка прочие (d) | Q43: 100.91109 | R43: -204.39156 | S43: 112.06121 | T43: 98.911968 | U43: 98.643999 | V43: 96.420671 | W43: =W14/V14/W28*10000 -> 93.167203 | X43: =X14/W14/X28*10000 -> 90.620064 | Y43: =Y14/X14/Y28*10000 -> 96.692497 | Z43: =Z14/Y14/Z28*10000 -> 115.04004 | AA43: =AA14/Z14/AA28*10000 -> 98.624432 | AB43: =AB14/AA14/AB28*10000 -> 76.6292 | AC43: =AC14/AB14/AC28*10000 -> 95.933073 | AD43: =AD14/AC14/AD28*10000 -> 115.89563 | AE43: =AE14/AD14/AE28*10000 -> 105.07427
B44: defINDE, t | C44: производство и распределение электроэнергии, газа и воды | J44: 160.78584 | K44: 98.880498 | L44: 112.47378 | M44: 100.08843 | N44: 125.91029 | O44: 180.27418 | P44: 141.87374 | Q44: 154.856 | R44: 100.09248 | S44: 112.15066 | T44: 104.3788 | U44: 106.05833 | V44: 116.5 | W44: 115 | X44: 115 | Y44: 102.5 | Z44: 105.7 | AA44: 100.2 | AB44: =AB15/AA15/AB29*10000 -> 95.568406 | AC44: =AC15/AB15/AC29*10000 -> 80.012807 | AD44: =AD15/AC15/AD29*10000 -> 110.04848 | AE44: =AE15/AD15/AE29*10000 -> 103.96996
AE45: 100
C48: Индекс 2003 = 100 | J48: 100 | K48: 115.1 | L48: 127.0704 | M48: 134.05927 | N48: 147.33114 | O48: 142.17455 | P48: 132.9332 | Q48: 145.16306 | R48: 153.43735 | S48: 170.00859 | T48: 176.46891 | U48: 185.29236
B49: idxIND2003t | C49: Все промышленность | J49: 100 | K49: 98.1 | L49: 102.4164 | M49: 108.0493 | N49: 114.10006 | O49: 106.56946 | P49: 104.11836 | Q49: 108.69957 | R49: 107.39663 | S49: 112.26447 | T49: 113.19703 | U49: 108.94428 | V49: 206.2304 | W49: =V49*W18/100 -> 239.22726 | X49: =W49*X18/100 -> 290.18267 | Y49: =X49*Y18/100 -> 320.94203 | Z49: =Y49*Z18/100 -> 363.30638 | AA49: =Z49*AA18/100 -> 395.27734 | AB49: =AA49*AB18/100 -> 477.49502 | AC49: =AB49*AC18/100 -> 551.02926 | AD49: =AC49*AD18/100 -> 617.15277 | AE49: =AD49*AE18/100 -> 740.58332
B50: idxIND2003E,,t | C50: Электроэнергетика | J50: 100 | K50: 114.8 | L50: 120.6548 | M50: 131.03111 | N50: 132.73452 | O50: 127.82334 | P50: 118.10877 | Q50: 121.65203 | R50: 101.7011 | S50: 104.44703 | T50: 100.26915 | U50: 87.033618 | V50: 113.50788 | W50: =V50*W70/V70 -> 113.97085 | X50: =W50*X70/W70 -> 120.00274 | Y50: =X50*Y70/X70 -> 130.57176 | Z50: =Y50*Z70/Y70 -> 136.75576 | AA50: =Z50*AA70/Z70 -> 130.76356 | AB50: =AA50*AB70/AA70 -> 136.4039 | AC50: =AB50*AC70/AB70 -> 141.53431 | AD50: =AC50*AD70/AC70 -> 144.58332 | AE50: =AD50*AE70/AD70 -> 148.33473
B51: idxIND2003DJ,,t | C51: Цветная металлургия | J51: 100 | K51: 113.2 | L51: 126.6708 | M51: 116.15712 | N51: 133.92916 | O51: 115.17908 | P51: 104.92814 | Q51: 118.5688 | R51: 137.89552 | S51: 176.78205 | T51: 159.28063 | U51: 147.9717 | V51: 113.4048 | W51: =V51*W25/100 -> 118.73483 | X51: =W51*X25/100 -> 129.8959 | Y51: =X51*Y25/100 -> 143.79477 | Z51: =Y51*Z25/100 -> 204.47616 | AA51: =Z51*AA25/100 -> 223.69692 | AB51: =AA51*AB25/100 -> 244.72443 | AC51: =AB51*AC25/100 -> 253.04506 | AD51: =AC51*AD25/100 -> 259.87727 | AE51: =AD51*AE25/100 -> 294.9607
B52: idxIND2003DBC,,t | C52: Легкая промышленность | J52: 100 | K52: 117.3 | L52: 151.4343 | M52: 162.18614 | N52: 197.21834 | O52: 201.95158 | P52: 190.64229 | Q52: 221.3357 | R52: 225.98375 | S52: 240.89868 | T52: 242.82587 | U52: 225.58523 | V52: 139.68529 | W52: =V52*W24/100 -> 144.99333 | X52: =W52*X24/100 -> 189.79627 | Y52: =X52*Y24/100 -> 174.80236 | Z52: =Y52*Z24/100 -> 207.66521 | AA52: =Z52*AA24/100 -> 235.70001 | AB52: =AA52*AB24/100 -> 258.09151 | AC52: =AB52*AC24/100 -> 276.93219 | AD52: =AC52*AD24/100 -> 305.73314 | AE52: =AD52*AE24/100 -> 284.33182
B53: idxIND2003DA,,t | C53: Пищевая промышленность | J53: 100 | K53: 128.87149 | L53: 138.39603 | M53: 153.71806 | N53: 179.65198 | O53: 179.7015 | P53: 168.93539 | Q53: 197.29381 | R53: 148.91171 | S53: 143.70435 | T53: 159.47176 | U53: 253.49874 | V53: 233.48071 | W53: =V53*W23/100 -> 246.08867 | X53: =W53*X23/100 -> 284.47851 | Y53: =X53*Y23/100 -> 334.54672 | Z53: =Y53*Z23/100 -> 360.30682 | AA53: =Z53*AA23/100 -> 453.62629 | AB53: =AA53*AB23/100 -> 468.59595 | AC53: =AB53*AC23/100 -> 618.54666 | AD53: =AC53*AD23/100 -> 785.55426 | AE53: =AD53*AE23/100 -> 864.10968
B54: idxIND2003Other,t | C54: Прочее | V54: 320.19923 | W54: =V54*W28/100 -> 445.17839 | X54: =W54*X28/100 -> 623.79986 | Y54: =X54*Y28/100 -> 755.62153 | Z54: =Y54*Z28/100 -> 773.73021 | AA54: =Z54*AA28/100 -> 798.78235 | AB54: =AA54*AB28/100 -> 1175.3262 | AC54: =AB54*AC28/100 -> 1358.3566 | AD54: =AC54*AD28/100 -> 1315.3157 | AE54: =AD54*AE28/100 -> 1419.2773
C56: Расчет доли ВДС в выпуске
B57: VACDE,t | C57: Промышленность, ВДС | H57: 858 | I57: 1117.2 | J57: 1440.2 | K57: 1644.4 | L57: 1645.1 | M57: 1987 | N57: 2349.4 | O57: 2515.8 | P57: 2957.4 | Q57: 3642.7 | R57: 4368.9 | S57: 4947.8 | T57: 5103.1 | U57: 5510.9 | V57: =GDP!V17 -> 7726.3 | W57: =GDP!W17 -> 9266.9 | X57: =GDP!X17 -> 12839.9 | Y57: =GDP!Y17 -> 15031.5 | Z57: =GDP!Z17 -> 16873.8 | AA57: =GDP!AA17 -> 19511.3 | AB57: =GDP!AB17 -> 24139 | AC57: =GDP!AC17 -> 27762 | ... AE57: =GDP!AE17 -> 25921
B58: gVACDE,t | C58: - рост | L58: 106.4 | M58: 105.5 | N58: 109.9 | O58: 96.5 | P58: 93.5 | Q58: 109.2 | R58: 105.7 | S58: 110.8 | T58: 103.8 | U58: 105 | V58: =V18 -> 111.3 | W58: =W18 -> 116 | X58: =X18 -> 121.3 | Y58: =Y18 -> 110.6 | Z58: =Z18 -> 113.2 | AA58: =AA18 -> 108.8 | AB58: =AB18 -> 120.8 | AC58: =AC18 -> 115.4 | ... AE58: =AE18 -> 120
B59: defVACDE,t /INDt | C59: - дефлятор | L59: 94.024971 | M59: 114.48619 | N59: 107.5874 | O59: 110.96649 | P59: 125.7252 | Q59: 112.79522 | R59: 113.46808 | S59: 102.21162 | T59: 99.362976 | U59: 102.84878 | V59: 125.96615 | W59: =W57/V57/W58*10000 -> 103.39628 | X59: =X57/W57/X58*10000 -> 114.22637 | Y59: =Y57/X57/Y58*10000 -> 105.84871 | Z59: =Z57/Y57/Z58*10000 -> 99.166309 | AA59: =AA57/Z57/AA58*10000 -> 106.27825 | AB59: =AB57/AA57/AB58*10000 -> 102.4156 | AC59: =AC57/AB57/AC58*10000 -> 99.661098 | AD59: =AD57/AC57/AD58*10000 -> 95.655868 | AE59: =AE57/AD57/AE58*10000 -> 72.625664
V60: =V23 -> 103.5 | W60: =W23 -> 105.4 | X60: =X23 -> 115.6 | Y60: =Y23 -> 117.6 | Z60: =Z23 -> 107.7 | AA60: =AA23 -> 125.9 | AB60: =AB23 -> 103.3 | AC60: =AC23 -> 132 | ... AE60: =AE23 -> 110
B61: VACDE,t | C61: Доля ВДС/выпуск | I61: 0.46203474 | J61: 0.44936037 | K61: 0.41609312 | L61: 0.38454885 | M61: 0.42612052 | N61: 0.42171962 | O61: 0.41202096 | P61: 0.45491463 | Q61: 0.59089656 | R61: 0.5556983 | S61: 0.52060185 | T61: 0.5127713 | U61: 0.52312097 | V61: 0.63351099 | W61: =W57/W4 -> 0.61410868 | X61: =X57/X4 -> 0.64108107 | Y61: =Y57/Y4 -> 0.62909362 | Z61: =Z57/Z4 -> 0.6110751 | AA61: =AA57/AA4 -> 0.63163807 | AB61: =AB57/AB4 -> 0.62167452 | AC61: =AC57/AC4 -> 0.65753386 | AD61: 0.66 | AE61: 0.4817072
B62: proxy1t | C62: Прокси (глинозем/дефлятор промпроизводства) | I62: 100 | J62: 107.09889 | K62: 130.07161 | L62: 136.02792 | M62: 141.62091 | N62: 132.88357 | O62: 119.74356 | P62: 123.7828 | Q62: 150.54186 | R62: 153.72024 | S62: 153.309 | T62: 150.59744 | U62: 154.59844 | V62: 168.41259 | W62: =V62*W163/V163*(Household!W2/Household!V2)/(W33/100) -> 209.34672 | X62: =W62*X163/W163*(Household!X2/Household!W2)/(X33/100) -> 225.4197 | Y62: =X62*Y163/X163*(Household!Y2/Household!X2)/(Y33/100) -> 244.85867 | Z62: =Y62*Z163/Y163*(Household!Z2/Household!Y2)/(Z33/100) -> 242.7149 | AA62: =Z62*AA163/Z163*(Household!AA2/Household!Z2)/(AA33/100) -> 241.10826 | AB62: =AA62*AB163/AA163*(Household!AB2/Household!AA2)/(AB33/100) -> 253.95128 | AC62: =AB62*AC163/AB163*(Household!AC2/Household!AB2)/(AC33/100) -> 322.34494 | AD62: =AC62*AD163/AC163*(Household!AD2/Household!AC2)/(AD33/100) -> 313.58724 | AE62: =AD62*AE163/AD163*(Household!AE2/Household!AD2)/(AE33/100) -> 294.33779
AD63: =AD57/AD4 -> 0.63531058 | AE63: =AE57/AE4 -> 0.48163288
C64: Предпосылки:
B65: INDDA, t /RETt | C65: доля пищевой промышленности к розничному товарооброту | J65: 0.34399916 | K65: 0.33410883 | L65: 0.37588879 | M65: 0.33616739 | N65: 0.33678105 | O65: 0.26883231 | P65: 0.24411747 | Q65: 0.50138176 | R65: 0.32886674 | S65: 0.36809816 | T65: 2.7353816 | U65: 0.25468071 | V65: =V9/Household!V9 -> 0.2421806 | W65: =W9/Household!W9 -> 0.22824695 | X65: =X9/Household!X9 -> 0.23346641 | Y65: =Y9/Household!Y9 -> 0.23926132 | Z65: =Z9/Household!Z9 -> 0.21640753 | AA65: =AA9/Household!AA9 -> 0.26231461 | AB65: =AB9/Household!AB9 -> 0.22874667 | AC65: =AC9/Household!AC9 -> 0.25511416 | ... AE65: =AE9/Household!AE9 -> 0.20562492
B66: INDDther, t /DDIND, t | C66: доля прочей в промышленности | J66: 0.44554791 | K66: 0.44375902 | L66: 0.38325129 | M66: 0.40775746 | N66: 0.40187863 | O66: 0.44942062 | P66: 0.36546307 | Q66: -0.23084661 | R66: 0.22830795 | S66: 0.18457947 | T66: 0.18642913 | U66: 0.26606517 | V66: =V14/(V9+V10+V14-(V186+V187+V188)*Assumptions!V11) -> 0.29392051 | W66: =W14/(W9+W10+W14-(W186+W187+W188)*Assumptions!W11) -> 0.32363118 | X66: =X14/(X9+X10+X14-(X186+X187+X188)*Assumptions!X11) -> 0.32141142 | Y66: =Y14/(Y9+Y10+Y14-(Y186+Y187+Y188)*Assumptions!Y11) -> 0.34006179 | Z66: =Z14/(Z9+Z10+Z14-(Z186+Z187+Z188)*Assumptions!Z11) -> 0.35311481 | AA66: =AA14/(AA9+AA10+AA14-(AA186+AA187+AA188)*Assumptions!AA11) -> 0.30576747 | AB66: =AB14/(AB9+AB10+AB14-(AB186+AB187+AB188)*Assumptions!AB11) -> 0.30686263 | AC66: =AC14/(AC9+AC10+AC14-(AC186+AC187+AC188)*Assumptions!AC11) -> 0.29457891 | ... AE66: =AE14/(AE9+AE10+AE14-(AE186+AE187+AE188)*Assumptions!AE11) -> 0.31572529
R67: 3513.7301 | S67: 3808.2863
C68: Подробное описание
C69: Электроэнергетика
B70: qYEl,t | C70: Производство, млн. кВт - час | G70: 14300 | H70: 14400 | I70: 15300 | J70: 16509 | K70: 16491 | L70: 17090 | M70: 16935 | N70: 17494 | O70: 16147 | P70: 16117 | Q70: 16435 | R70: 16238 | S70: 16974 | T70: 17115 | U70: 16472 | V70: 17162 | W70: 17232 | X70: 18144 | Y70: 19742 | Z70: 20677 | AA70: 19771 | AB70: 20623.8 | AC70: 21399.5 | AD70: 21860.5 | AE70: 22427.7
B71: qIMEl,t | C71: Импорт | G71: 5242.4 | H71: 5396.4 | I71: 4659.4 | J71: 4617.6 | K71: 4807.3 | L71: 4505.5 | M71: 4839.6 | N71: 4552 | O71: 6404 | P71: 6003 | Q71: 432 | R71: 172 | S71: 114 | T71: 117 | U71: 52 | V71: =Trade!V60 -> 63 | W71: =Trade!W60 -> 103 | X71: =Trade!X60 -> 110 | Y71: =Trade!Y60 -> 559.7 | Z71: =Trade!Z60 -> 294.4 | AA71: =Trade!AA60 -> 378.7 | AB71: =Trade!AB60 -> 883.4 | AC71: =Trade!AC60 -> 797.3 | ... AE71: =Trade!AE60 -> 1617.792
B72: qTCEl,t | C72: ИТОГО ПОТРЕБЛЕНИЕ | G72: 19542.4 | H72: 19796.4 | I72: 19959.4 | J72: 21126.6 | K72: 21298.3 | L72: 21595.5 | M72: 21774.6 | N72: 22046 | O72: 22551 | P72: 22120 | Q72: 16867 | R72: 16410 | S72: 17088 | T72: 17232 | U72: 16524 | V72: =V70+V71 -> 17225 | W72: =W70+W71 -> 17335 | X72: =X70+X71 -> 18254 | Y72: =Y70+Y71 -> 20301.7 | Z72: =Z70+Z71 -> 20971.4 | AA72: =AA70+AA71 -> 20149.7 | AB72: =AB70+AB71 -> 21507.2 | AC72: =AC70+AC71 -> 22196.8 | ... AE72: =AE70+AE71 -> 24045.492
B73: qEXEl,t | C73: Экспорт | G73: 3908.7 | H73: 4047 | I73: 3831.2 | J73: 4597.2 | K73: 4451 | L73: 4257.9 | M73: 4231.2 | N73: 4464 | O73: 5539 | P73: 5960 | Q73: 286 | R73: 297 | S73: 775 | T73: 1061 | U73: 1364 | V73: =Trade!V19 -> 1396 | W73: =Trade!W19 -> 1428 | X73: =Trade!X19 -> 1421 | Y73: =Trade!Y19 -> 2945 | Z73: =Trade!Z19 -> 3175 | AA73: =Trade!AA19 -> 1870.3 | AB73: =Trade!AB19 -> 3302.6 | AC73: =Trade!AC19 -> 3341 | ... AE73: =Trade!AE19 -> 3901.7
B74: qCEl,t | C74: Внутреннее потребление - всего (по секторам) | G74: 15633.7 | H74: 15749.4 | I74: 16128.2 | J74: 16529.4 | K74: 16847.3 | L74: 17337.6 | M74: 17543.4 | N74: 17582 | O74: 17012 | P74: 16160 | Q74: 16581 | R74: 16113 | S74: 16313 | T74: 16171 | U74: 15160 | V74: =V72-V73 -> 15829 | W74: =W72-W73 -> 15907 | X74: =X72-X73 -> 16833 | Y74: =Y72-Y73 -> 17356.7 | Z74: =Z72-Z73 -> 17796.4 | AA74: =AA72-AA73 -> 18279.4 | AB74: =AB72-AB73 -> 18204.6 | AC74: =AC72-AC73 -> 18855.8 | ... AE74: =AE72-AE73 -> 20143.792
C75: в том числе: | R75: * по внутреннему потреблению есть ограничение по мощности
B76: qCCDEEl,t | C76: Промышленность | G76: 5800 | H76: 6100 | I76: 6202 | J76: 6675 | K76: 7031 | L76: 7533 | M76: 8080 | N76: 8060 | O76: 7802 | P76: 7007 | Q76: 7344 | R76: 6335 | S76: 6150 | T76: 5251 | U76: 3935 | V76: 4242 | W76: 4114 | X76: 3790 | Y76: 3783 | Z76: 3990 | AA76: 2744 | AB76: 3934 | AC76: =AB76*AC102/AB102 -> 2545.6428 | AD76: =AC76*AD102/AC102 -> 2613.1513 | AE76: =AD76*AE102/AD102 -> 2959.5911
B77: qCFEl,t | C77: Строительство | G77: 20 | H77: 20 | I77: 30 | J77: 23 | K77: 21 | L77: 19 | M77: 25 | N77: 28 | O77: 59 | P77: 46 | Q77: 90 | R77: 115 | S77: 194 | T77: 245 | U77: 122 | V77: 45 | W77: 67 | X77: 227 | Y77: 39 | Z77: 46 | AA77: 57 | AB77: 43 | AC77: =AB77*GDP!AC52/GDP!AB52 -> 47.902 | AD77: =AC77*GDP!AD52/GDP!AC52 -> 53.793946 | AE77: =AD77*GDP!AE52/GDP!AD52 -> 42.868844
B78: qCABEl,t | C78: Сельское хозяйство | G78: 4300 | H78: 4500 | I78: 4200 | J78: 4257 | K78: 4309 | L78: 3919 | M78: 3908 | N78: 3612 | O78: 3144 | P78: 3722 | Q78: 3593 | R78: 3742 | S78: 3832 | T78: 2600 | U78: 2328 | V78: 2496 | W78: 2807 | X78: 2754 | Y78: 2241 | Z78: 2338 | AA78: 2619 | AB78: 2086 | AC78: =AC137 -> 2812.0431 | AD78: =AD137 -> 3155.1123 | AE78: =AE137 -> 3489.5542
B79: qCIEl,t | C79: Транспорт | G79: 40 | H79: 30 | I79: 20 | J79: 23 | K79: 38 | L79: 24 | M79: 44 | N79: 52 | O79: 44 | P79: 41 | Q79: 30 | R79: 161 | S79: 37 | T79: 38 | U79: 41 | V79: 45 | W79: 35 | X79: 30 | Y79: 7 | Z79: 8 | AA79: 8 | AB79: 9 | AC79: =AB79*(GDP!AC55/GDP!AB55) -> 8.64 | AD79: =AC79*(GDP!AD55/GDP!AC55) -> 10.51488 | AE79: =AD79*(GDP!AE55/GDP!AD55) -> 18.396869
B80: qCHHEl,t | C80: Население | G80: 2800 | H80: 2500 | I80: 2900 | J80: 2700 | K80: 2600 | L80: 2700 | M80: 2600 | N80: 2400 | O80: 2400 | P80: 2700 | Q80: 3031 | R80: 3046 | S80: 3061 | T80: 4503 | U80: 4692 | V80: 4914 | W80: 4845 | X80: 5424 | Y80: 5579 | Z80: 6019 | AA80: 6857 | AB80: 5410 | AC80: =AB80*1.02 -> 5518.2 | AD80: =AC80*1.02 -> 5628.564 | AE80: =AD80*1.02 -> 5741.1353
B81: qLEl,t | C81: Потери | G81: 2200 | H81: 2200 | I81: 2300 | J81: 2527 | K81: 2455 | L81: 2746 | M81: 2745 | N81: 2954 | O81: 2985 | P81: 2099 | Q81: 2330 | R81: 2271 | S81: 2445 | T81: 2528 | U81: 2804 | V81: 2670 | W81: 2746 | X81: 2884 | Y81: 2878 | Z81: 2429 | AA81: 2549 | AB81: 4897.3 | AC81: 4760.7 | AD81: 4642.8 | AE81: 6196.2191
B82: qCOthEl,t | C82: Прочее | G82: 473.7 | H82: 399.4 | I82: 476.2 | J82: 324.4 | K82: 393.3 | L82: 396.6 | M82: 141.4 | N82: 476 | O82: 578 | P82: 545 | Q82: 163 | R82: 443 | S82: 594 | T82: 1006 | U82: 1238 | V82: 1417 | W82: 1293 | X82: 1724 | Y82: 2625 | Z82: 2740 | AA82: 3445.7 | AB82: 1820.5 | AC82: =AC74-SUM(AC76:AC81) -> 3162.6722 | AD82: =AD74-SUM(AD76:AD81) -> 2947.2636 | AE82: =AE74-SUM(AE76:AE80) -> 7892.2457
B83: qLYEl,t | C83: потери к выпуску | G83: 0.12685672 | H83: 0.12502557 | I83: 0.13024225 | J83: 0.13586314 | K83: 0.13028503 | L83: 0.14568026 | M83: 0.14424896 | N83: 0.15472449 | O83: 0.15256056 | P83: 0.10483992 | Q83: 0.16028066 | R83: 0.16061956 | S83: 0.16697398 | T83: 0.17192601 | U83: 0.20437318 | V83: 0.18344212 | W83: 0.188224 | X83: 0.18763826 | Y83: 0.16518395 | Z83: 0.1310918 | AA83: 0.14482132 | AB83: 0.29484933 | AC83: =AC81/(AC72-AC81) -> 0.27303698 | AD83: =AD81/(AD72-AD81) -> 0.25771857 | AE83: =AE81/(AE72-AE81) -> 0.34714126
B84: qLYEl,t | C84: потери к выпуску | AC84: =AC81/(AC72-AC81) -> 0.27303698 | AD84: =AD81/(AD72-AD81) -> 0.25771857 | AE84: =AE81/(AE72-AE81) -> 0.34714126
AE85: =0.256*(SUM(AE76:AE80,AE82,AE73)) -> 6155.646
C86: Импорт, млн кВт | G86: 5242.4 | H86: 5389.4 | I86: 4539.1 | J86: 4617.6 | K86: 4810.2 | L86: 4505.5 | M86: 4839.5 | N86: 4360.6 | O86: 5145.5 | P86: 4276.1 | Q86: 338.9 | R86: 134.93241 | S86: 89.431944 | T86: 91.785417 | U86: 40.793519 | V86: 49.422917 | W86: =V86*W71/V71 -> 80.802546 | X86: =W86*X71/W71 -> 86.293981 | Y86: =X86*Y71/X71 -> 439.07947 | Z86: =Y86*Z71/Y71 -> 230.95407 | AA86: =Z86*AA71/Z71 -> 297.08664 | AB86: =AA86*AB71/AA71 -> 693.01912 | AC86: =AB86*AC71/AB71 -> 625.47447 | AD86: =AC86*AD71/AC71 -> 625.47447 | AE86: =AD86*AE71/AD71 -> 1269.1428
C87: Экспорт, млн кВт | G87: 3908.7 | H87: 4040.1 | I87: 3675.6 | J87: 4713.6 | K87: 4450.9 | L87: 4257.9 | M87: 4231.2 | N87: 4259 | O87: 4264.8 | P87: 4227.3 | Q87: 286 | R87: 297 | S87: 775 | T87: 1061 | U87: 1364 | V87: =V73 -> 1396 | W87: =W73 -> 1428 | X87: =X73 -> 1421 | Y87: =Y73 -> 2945 | Z87: =Z73 -> 3175 | AA87: =AA73 -> 1870.3 | AB87: =AB73 -> 3302.6 | AC87: =AC73 -> 3341 | ... AE87: =AE73 -> 3901.7
C88: Импорт, млн. долл. | G88: 131.1 | H88: 93.9 | I88: 76.9 | J88: 61.4 | K88: 65 | L88: 58.1 | M88: 66.8 | N88: 65.6 | O88: 87.5 | P88: 76.1 | Q88: 12.9
B89: EXUSEl,t | C89: Экспорт, млн. долл. | G89: 86.8 | H89: 80.1 | I89: 64.5 | J89: 54.9 | K89: 57.6 | L89: 52.5 | M89: 49 | N89: 59.5 | O89: 59.7484 | P89: 63.1881 | Q89: 3.4600192 | R89: 4.269 | S89: 21.335 | T89: 33.268 | U89: 44.1 | V89: =Trade!V10 -> 48.4 | W89: =Trade!W10 -> 51.7 | X89: =Trade!X10 -> 53.5 | Y89: =Trade!Y10 -> 56.4 | Z89: =Trade!Z10 -> 93.1 | AA89: =Trade!AA10 -> 56.4 | AB89: =Trade!AB10 -> 95.961 | AC89: =Trade!AC10 -> 106.2 | ... AE89: =Trade!AE10 -> 113
B93: qCAPEl,t | C93: Мощность, тыс. кВт | J93: 4420 | K93: 4396 | L93: 4404 | M93: 4389 | N93: 4386 | O93: 5069 | P93: 5078 | Q93: 5105 | R93: 5079 | S93: 6168 | T93: 6180 | U93: 6280 | V93: 6283 | W93: 6577 | X93: 5718 | Y93: 6197 | Z93: 6475 | AA93: 6356 | AB93: 6476 | AC93: =AB93*1.002 -> 6488.952 | AD93: =AC93*1.002 -> 6501.9299 | AE93: =AD93*1.002 -> 6514.9338
B94: UREl,t | C94: загрузка мощностей, % | J94: 0.42637761 | K94: 0.428238 | L94: 0.44298666 | M94: 0.44046917 | N94: 0.45531965 | O94: 0.36363481 | P94: 0.36231591 | Q94: 0.36751059 | R94: 0.36496416 | S94: 0.31414903 | T94: 0.31614355 | U94: 0.29942123 | V94: =V70/(V93*24*365)*1000 -> 0.31181481 | W94: =W70/(W93*24*365)*1000 -> 0.29909127 | X94: =X70/(X93*24*365)*1000 -> 0.3622303 | Y94: =Y70/(Y93*24*365)*1000 -> 0.36366838 | Z94: =Z70/(Z93*24*365)*1000 -> 0.36453871 | AA94: =AA70/(AA93*24*365)*1000 -> 0.3550918 | AB94: =AB70/(AB93*24*365)*1000 -> 0.36354464 | AC94: =AC70/(AC93*24*365)*1000 -> 0.37646531 | ... AE94: =AE70/(AE93*24*365)*1000 -> 0.39298016
B95: qEXP*El,t | C95: потенциал чистого экспорта э/э, млн. кВт-ч/год | J95: 1120.6124 | K95: 1042.886 | L95: 475.7948 | M95: 570.9658 | N95: 0 | O95: 4071.2139 | P95: 4137.1113 | Q95: 3926.8035 | R95: 4020.0999 | S95: 7627.6854 | T95: 7534.5486 | U95: 8576.4086 | V95: =(0.46-V94)*V93*24*365/1000 -> 8155.9768 | W95: =(0.46-W94)*W93*24*365/1000 -> 9270.6792 | X95: =(0.46-X94)*X93*24*365/1000 -> 4897.2528 | Y95: =(0.46-Y94)*Y93*24*365/1000 -> 5229.4312 | Z95: =(0.46-Z94)*Z93*24*365/1000 -> 5414.66 | AA95: =(0.46-AA94)*AA93*24*365/1000 -> 5841.1376 | AB95: =(0.46-AB94)*AB93*24*365/1000 -> 5471.8896 | AC95: =(0.46-AC94)*AC93*24*365/1000 -> 4748.381 | ... AE95: =(0.46-AE94)*AE93*24*365/1000 -> 3824.8771
B96: PUREl,t | C96: использование потенциала, % | O96: 0 | P96: 0 | Q96: 0 | R96: 0.031093755 | S96: 0.086658005 | T96: 0.12528952 | U96: 0.15297779 | V96: =MAX(V73-V71,0)/V95 -> 0.16343842 | W96: =MAX(W73-W71,0)/W95 -> 0.14292372 | X96: =MAX(X73-X71,0)/X95 -> 0.26770111 | Y96: =MAX(Y73-Y71,0)/Y95 -> 0.45612991 | Z96: =MAX(Z73-Z71,0)/Z95 -> 0.53200016 | AA96: =MAX(AA73-AA71,0)/AA95 -> 0.25536122 | AB96: =MAX(AB73-AB71,0)/AB95 -> 0.44211418 | AC96: =MAX(AC73-AC71,0)/AC95 -> 0.53569838 | ... AE96: =MAX(AE73-AE71,0)/AE95 -> 0.59711932
C99: Потребление электроэнергии
C100: Промышленность | J100: 6445 | K100: 6920 | L100: 7531 | M100: 7595 | N100: 7870 | O100: 7833 | P100: 7774
C101: - в т.ч. на двигательную силу | J101: 577 | K101: 607 | L101: 645 | M101: 680 | N101: 642 | O101: 682 | P101: 870 | T101: -251.49786 | U101: -1482.3595 | V101: 1741.6613 | W101: =W102-V102 -> 281.18947 | X101: =X102-W102 -> 678.28759 | Y101: =Y102-X102 -> 853.84426 | Z101: =Z102-Y102 -> 3873.7029 | AA101: =AA102-Z102 -> 1219.7413 | AB101: =AB102-AA102 -> 1339.4228 | AC101: =AC102-AB102 -> -5583.4802 | AD101: =AD102-AC102 -> 271.49522 | AE101: =AE102-AD102 -> 1393.2579
B102: qC*CDEEl,t | C102: - на технологические нужды и прочее | J102: 5868 | K102: 6313 | L102: 6886 | M102: 6915 | N102: 7228 | O102: 7151 | P102: 6904 | Q102: 8004.741 | R102: 6692.6315 | S102: 7567.1602 | T102: 7315.6624 | U102: 5833.3029 | V102: =V109+V116+V123+V130 -> 7574.9642 | W102: =W109+W116+W123+W130 -> 7856.1537 | X102: =X109+X116+X123+X130 -> 8534.4413 | Y102: =Y109+Y116+Y123+Y130 -> 9388.2855 | Z102: =Z109+Z116+Z123+Z130 -> 13261.988 | AA102: =AA109+AA116+AA123+AA130 -> 14481.73 | AB102: =AB109+AB116+AB123+AB130 -> 15821.153 | AC102: =AC109+AC116+AC123+AC130 -> 10237.672 | ... AE102: =AE109+AE116+AE123+AE130 -> 11902.425
C103: энергоемкость выпуска 1 | J103: 64.45 | K103: 60.121633 | L103: 59.266359 | M103: 56.654045 | N103: 53.417085 | O103: 55.094249 | P103: 58.480498
B104: efCDEEl,t | C104: энергоемкость выпуска 2 | J104: 58.68 | K104: 54.847958 | L104: 54.190433 | M104: 51.581662 | N104: 49.059554 | O104: 50.297328 | P104: 51.935858 | Q104: 55.143099 | R104: 43.618007 | S104: 44.510459 | T104: 41.455814 | U104: 31.481616 | V104: 25 | W104: 26.3 | X104: 25 | Y104: 26 | Z104: 25 | AA104: 25 | AB104: 26 | AC104: 26 | AD104: 26 | AE104: 26
C107: Цветные металлы | J107: 5709 | K107: 6248 | L107: 6671 | M107: 7195 | N107: 7291 | O107: 7174 | P107: 7422 | Q107: 7803.815 | R107: 6523.9893 | S107: 6700.137 | T107: 6432.1315 | U107: 5583.0902 | V107: =V108+V109 -> 7274.7665 | W107: =W108+W109 -> 7616.6805 | X107: =X108+X109 -> 8332.6485 | Y107: =Y108+Y109 -> 9224.2419 | Z107: =Z108+Z109 -> 13116.872 | AA107: =AA108+AA109 -> 14349.858 | AB107: =AB108+AB109 -> 15698.745 | AC107: =AC108+AC109 -> 10121.802 | ... AE107: =AE108+AE109 -> 11798.428
C108: - в т.ч. на двигательную силу | J108: 249 | K108: 284 | L108: 287 | M108: 428 | N108: 419 | O108: 413 | P108: 691
B109: qC*DlEl,t | C109: - на технологические нужды и прочее | J109: 5460 | K109: 5964 | L109: 6384 | M109: 6767 | N109: 6872 | O109: 6761 | P109: 6731 | Q109: 7803.815 | R109: 6523.9893 | S109: 6700.137 | T109: 6432.1315 | U109: 5583.0902 | V109: 7274.7665 | W109: =W111*W51 -> 7616.6805 | X109: =X111*X51 -> 8332.6485 | Y109: =Y111*Y51 -> 9224.2419 | Z109: =Z111*Z51 -> 13116.872 | AA109: =AA111*AA51 -> 14349.858 | AB109: =AB111*AB51 -> 15698.745 | AC109: =AC111*AC51 -> 10121.802 | AD109: =AD111*AD51 -> 10395.091 | AE109: =AE111*AE51 -> 11798.428
C110: энергоемкость выпуска 1 | J110: 57.09 | K110: 55.194346 | L110: 52.664071 | M110: 61.941961 | N110: 54.439226 | O110: 62.285616 | P110: 70.734122 | Q110: 65.816766 | R110: 47.311106 | S110: 37.90055 | T110: 40.382384 | U110: 37.730796 | V110: =V107/V52 -> 52.07969 | W110: =W107/W52 -> 52.531248 | X110: =X107/X52 -> 43.903121 | Y110: =Y107/Y52 -> 52.769549 | Z110: =Z107/Z52 -> 63.163552 | AA110: =AA107/AA52 -> 60.881873 | AB110: =AB107/AB52 -> 60.826273 | AC110: =AC107/AC52 -> 36.54975 | ... AE110: =AE107/AE52 -> 41.495279
...

Sheet OEA
B1: Var. Name | C1: Наименование индикатора | D1: 1997 | E1: 1998 | F1: 1999 | G1: 2000 | H1: 2001 | I1: 2002 | J1: 2003 | K1: 2004 | L1: 2005 | M1: 2006 | N1: 2007 | O1: 2008 | P1: 2009 | Q1: 2010 | R1: 2011 | S1: 2012 | T1: 2013 | U1: 2014 | V1: 2015 | W1: 2016 | X1: 2017 | Y1: 2018 | Z1: 2019 | AA1: 2020 | AB1: 2021 | AC1: 2022 | AD1: 2023 | AE1: 2024
C2: Транспорт
B3: TRANCt | C3: Перевозка грузов, млн.тонна | D3: 36 | E3: 34.6 | F3: 27.7 | G3: 27.6763 | H3: 30.0127 | I3: 35.6024 | J3: 32.9246 | K3: 35.7322 | L3: 38.5936 | M3: 39.541 | N3: 44.998 | O3: 47.732 | P3: 58.863 | Q3: 59.327 | R3: 61.657 | S3: 68.399 | T3: 72.2 | U3: 74.4 | V3: 74.4 | W3: 84.1 | X3: 84.1 | Y3: 89.6 | Z3: 85.4 | AA3: 79.9 | AB3: 82 | AC3: 103.4 | AD3: 120.6 | AE3: 134.4 | AH3: TRANCt = TRANCM, t+TRANCOther, t
B4: PROXYTRANIND,t | C4: Промышленное производство, превозимое автотранспортом | J4: 100 | K4: 118.04233 | L4: 137.16425 | M4: 141.23944 | N4: 167.12739 | O4: 162.22223 | P4: 151.63621 | Q4: 175.32456 | R4: 189.83791 | S4: 242.58339 | T4: 238.86549 | U4: 242.72656 | V4: 258.4009 | W4: =(Industry!V9*Industry!W23+Industry!W24*Industry!V10+Industry!V14*Industry!W28+Industry!V7*Industry!W21)/(Industry!V7+Industry!V9+Industry!V10+Industry!V14)*V4/100 -> 295.53009 | X4: =(Industry!W9*Industry!X23+Industry!X24*Industry!W10+Industry!W14*Industry!X28+Industry!W7*Industry!X21)/(Industry!W7+Industry!W9+Industry!W10+Industry!W14)*W4/100 -> 373.94614 | Y4: =(Industry!X9*Industry!Y23+Industry!Y24*Industry!X10+Industry!X14*Industry!Y28+Industry!X7*Industry!Y21)/(Industry!X7+Industry!X9+Industry!X10+Industry!X14)*X4/100 -> 419.913 | Z4: =(Industry!Y9*Industry!Z23+Industry!Z24*Industry!Y10+Industry!Y14*Industry!Z28+Industry!Y7*Industry!Z21)/(Industry!Y7+Industry!Y9+Industry!Y10+Industry!Y14)*Y4/100 -> 455.18244 | AA4: =(Industry!Z9*Industry!AA23+Industry!AA24*Industry!Z10+Industry!Z14*Industry!AA28+Industry!Z7*Industry!AA21)/(Industry!Z7+Industry!Z9+Industry!Z10+Industry!Z14)*Z4/100 -> 524.57137 | AB4: =(Industry!AA9*Industry!AB23+Industry!AB24*Industry!AA10+Industry!AA14*Industry!AB28+Industry!AA7*Industry!AB21)/(Industry!AA7+Industry!AA9+Industry!AA10+Industry!AA14)*AA4/100 -> 614.13373 | AC4: =(Industry!AB9*Industry!AC23+Industry!AC24*Industry!AB10+Industry!AB14*Industry!AC28+Industry!AB7*Industry!AC21)/(Industry!AB7+Industry!AB9+Industry!AB10+Industry!AB14)*AB4/100 -> 740.27139 | AD4: =(Industry!AC9*Industry!AD23+Industry!AD24*Industry!AC10+Industry!AC14*Industry!AD28+Industry!AC7*Industry!AD21)/(Industry!AC7+Industry!AC9+Industry!AC10+Industry!AC14)*AC4/100 -> 850.60741 | AE4: =(Industry!AD9*Industry!AE23+Industry!AE24*Industry!AD10+Industry!AD14*Industry!AE28+Industry!AD7*Industry!AE21)/(Industry!AD7+Industry!AD9+Industry!AD10+Industry!AD14)*AD4/100 -> 902.88224 | AH4: PROXYTRANIND,t = PROXYTRANIND,t-1·((INDDBC, t-1·gINDDBC, t+INDDA, t-1·gINDDA, t+INDDther, t-1·gINDDther, t)/(INDDBC, t-1+INDDA, t-1+INDDther, t-1))/100
B5: TRANCM, t | C5: - в т.ч. авто, млн.тонна | D5: 22.8 | E5: 21.9 | F5: 16.1 | G5: 14.5763 | H5: 17.2959 | I5: 23.8024 | J5: 21.2003 | K5: 23.4598 | L5: 26.4757 | M5: 25.6036 | N5: 30.4975 | O5: 33.1856 | P5: 42.3148 | Q5: 50.8 | R5: 52.397 | S5: 60.425602 | T5: 65.5 | U5: 67.6 | V5: 68.3 | W5: 78.6 | X5: 79.5 | Y5: 84.3 | Z5: 79.6 | AA5: 73.6 | AB5: 76.3 | AC5: 97.3 | AD5: 114.1 | AE5: 127.7 | AH5: TRANCM, t = TRANCM, t-1·(PROXYTRANIND,t/PROXYTRANIND,t-1)^0,1·(gRETt/100)^0,8
B6: TRANCOther, t | C6: - прочее | D6: 13.2 | E6: 12.7 | F6: 11.6 | G6: 13.1 | H6: 12.7168 | I6: 11.8 | J6: 11.7243 | K6: 12.2724 | L6: 12.1179 | M6: 13.9374 | N6: 14.5 | O6: 14.5467 | P6: 14.5482 | Q6: 10.4 | R6: 9.26 | S6: 7.9733984 | T6: 6.7 | U6: 6.8 | V6: =V3-V5 -> 6.1 | W6: =W3-W5 -> 5.5 | X6: =X3-X5 -> 4.6 | Y6: =Y3-Y5 -> 5.3 | Z6: =Z3-Z5 -> 5.8 | AA6: =AA3-AA5 -> 6.3 | AB6: =AB3-AB5 -> 5.7 | AC6: =AC3-AC5 -> 6.1 | ... AE6: =AE3-AE5 -> 6.7 | AH6: TRANCOther, t = TRANCOther, t-1·(qEXAl,t/qEXAl,t-1)
B7: gTRANC, t | C7: - темпы роста | D7: 31.551271 | E7: 96.111111 | F7: 80.057803 | G7: 99.91444 | H7: 108.44188 | I7: 118.62445 | J7: 92.478597 | K7: 108.52736 | L7: 108.0079 | M7: 102.45481 | N7: 113.7996 | O7: 106.07767 | P7: 119.12898 | Q7: 107.6271 | R7: 103.92739 | S7: 110.93469 | T7: 105.5 | U7: 103 | V7: 100 | W7: 113 | X7: 100.1 | Y7: =Y3/X3*100 -> 106.53983 | Z7: =Z3/Y3*100 -> 95.3125 | AA7: 99.7 | AB7: 103.8 | AC7: 126.1 | AD7: 116.6 | AE7: 111.5 | AH7: gTRANC, t = TRANCt/TRANCt-1·100
B12: TRANPt | C12: Перевозка пассажиров | D12: 124.5 | E12: 174.1 | F12: 187.6 | G12: 151.4 | H12: 171.6 | I12: 225.9 | J12: 265.5 | K12: 340.6 | L12: 398.4 | M12: 415.4 | N12: 429.2 | O12: 455 | P12: 514.6 | Q12: 539.5 | R12: 479.3 | S12: 512.8 | T12: 545 | U12: 556.9 | V12: 564.5 | W12: 572.9 | X12: 594.7 | Y12: 614.5 | Z12: 658.1 | AA12: 654.7 | AB12: 737.1 | AC12: 818.6 | AD12: 899.3 | AE12: 1020 | AH12: TRANPt = TRANPM, t+TRANPOther, t
B13: TRANPM, t | C13: - в т.ч. авто | D13: 93.6 | E13: 140.8 | F13: 145.8 | G13: 122.8 | H13: 147.1 | I13: 203.7 | J13: 243.5 | K13: 317.4 | L13: 380.7 | M13: 391.4 | N13: 406.5 | O13: 443 | P13: 502.9 | Q13: 526.8 | R13: 467.3 | S13: 500.8 | T13: 533.2 | U13: 545.2 | V13: 553.1 | W13: 560.7 | X13: 582.2 | Y13: 602.6 | Z13: 635.4 | AA13: 634.8 | AB13: 717.1 | AC13: 797.1 | AD13: 876.7 | AE13: 996.1 | AH13: TRANPM, t = TRANPM, t-1·gRETt/100
B14: TRANPOther, t | C14: - прочее | D14: 30.9 | E14: 33.3 | F14: 41.8 | G14: 28.6 | H14: 24.5 | I14: 22.2 | J14: 22 | K14: 23.2 | L14: 17.7 | M14: 24 | N14: 22.7 | O14: 12 | P14: 11.7 | Q14: 12.7 | R14: 12 | S14: 12 | T14: 11.8 | U14: 11.7 | V14: =V12-V13 -> 11.4 | W14: =W12-W13 -> 12.2 | X14: =X12-X13 -> 12.5 | Y14: =Y12-Y13 -> 11.9 | Z14: =Z12-Z13 -> 22.7 | AA14: =AA12-AA13 -> 19.9 | AB14: =AB12-AB13 -> 20 | AC14: =AC12-AC13 -> 21.5 | ... AE14: =AE12-AE13 -> 23.9 | AH14: TRANPOther, t = TRANPOther, t-1
B15: gTRANPt | C15: - темпы роста | D15: 105.06329 | E15: 139.83936 | F15: 107.75416 | G15: 80.703625 | H15: 113.34214 | I15: 131.64336 | J15: 117.52988 | K15: 128.28625 | L15: 116.97005 | M15: 104.26707 | N15: 103.3221 | O15: 106.01118 | P15: 113.0989 | Q15: 104.83871 | R15: 88.84152 | S15: 106.98936 | T15: 104.7 | U15: 102.2 | V15: 101.4 | W15: 101.5 | X15: 103.8 | Y15: 103.3 | Z15: 107.1 | AA15: 97.5 | AB15: 113 | AC15: =AC12/AB12*100 -> 111.05684 | AD15: =AD12/AC12*100 -> 109.85829 | AE15: =AE12/AD12*100 -> 113.42155 | AH15: gTRANPt = TRANPt/TRANPt-1·100
W20: =W22-V22 -> 1759.3 | X20: =X22-W22 -> 297.1 | Y20: =Y22-X22 -> 1554.7 | Z20: =Z22-Y22 -> -843.2 | AA20: =AA22-Z22 -> -900.9 | AB20: =AB22-AA22 -> 3140.3 | AC20: =AC22-AB22 -> 1522.3 | AD20: =AD22-AC22 -> 3579.5 | AE20: =AE22-AD22 -> 2684
W21: =W23-V23 -> 953.9 | X21: =X23-W23 -> 613.9 | Y21: =Y23-X23 -> 1455 | Z21: =Z23-Y23 -> -207.4 | AA21: =AA23-Z23 -> -574.5 | AB21: =AB23-AA23 -> 421.9 | AC21: =AC23-AB23 -> 628.1 | AD21: =AD23-AC23 -> 1185.6 | AE21: =AE23-AD23 -> 1908
B22: INVt | C22: Инвестиции в ОК | D22: 67.5 | E22: 68.3 | F22: 122.5 | G22: 108.6 | H22: 194.8 | I22: 206.9 | J22: 318.4 | K22: 592 | L22: 682.5 | M22: 1214.5 | N22: 2828.7 | O22: 4341.4 | P22: 3899.4 | Q22: 4413.5 | R22: 4848 | S22: 4540.2 | T22: 5796.8 | U22: 7495.2 | V22: 9749.9 | W22: =SUM(W23+W25+W26+W27) -> 11509.2 | X22: =SUM(X23+X25+X26+X27) -> 11806.3 | Y22: 13361 | Z22: 12517.8 | AA22: =SUM(AA23+AA25+AA26+AA27) -> 11616.9 | AB22: =SUM(AB23+AB25+AB26+AB27) -> 14757.2 | AC22: =SUM(AC23+AC25+AC26+AC27) -> 16279.5 | AD22: =SUM(AD23+AD25+AD26+AD27) -> 19859 | AE22: =SUM(AE23+AE25+AE26+AE27) -> 22543 | AH22: INVt = INVt-1·InvNAF,t/InvNAF,t-1
C23: за счет бюджета | D23: 47.6 | E23: 46.3 | F23: 95.2 | G23: 47.3 | H23: 100.5 | I23: 117.2 | J23: 180.2 | K23: 349 | L23: 319.2 | M23: 429.3 | N23: 547.5 | O23: 1015 | P23: 1219.3 | Q23: 1629.9 | R23: 2183.3169 | S23: 2018.5 | T23: 2426 | U23: 3104 | V23: 3446 | W23: 4399.9 | X23: 5013.8 | Y23: 6468.8 | Z23: 6261.4 | AA23: 5686.9 | AB23: 6108.8 | AC23: 6736.9 | AD23: 7922.5 | AE23: 9830.5
C24: в. том числе цент.кап.влож. | W24: 3375.4 | X24: 3174.2 | Y24: 3410.6
C25: частные | G25: 27.3 | H25: 48.9 | I25: 19.3 | J25: 48 | K25: 79.7 | L25: 143.9 | M25: 230.2 | N25: 587.3 | O25: 414.1 | P25: 787.9 | Q25: 744.7 | R25: 1058.2553 | S25: 1119.2 | T25: 1701.9 | U25: 2310 | V25: 2444.3 | W25: 1993.7 | X25: 1821 | Y25: 2256.3 | Z25: 3067.8 | AA25: 3095.2 | AB25: 4443.8 | AC25: 4620 | AD25: 5721.4 | AE25: 8295
C26: совместные | D26: 3.4 | E26: 3.9 | F26: 6.3 | G26: 4.9 | H26: 9.8 | I26: 42.3 | J26: 39 | K26: 58.6 | L26: 68.3 | M26: 115.2 | N26: 105.4 | O26: 211.3 | P26: 280.7 | Q26: 316.6 | R26: 449.90416 | S26: 367 | T26: 509.4 | U26: 509.4 | V26: 276.2 | W26: 509.4 | X26: 509.4 | Y26: 433.6 | Z26: 161.8 | AA26: 45.2 | AB26: 101.5 | AC26: 230.6 | AD26: 695.9 | AE26: 98.8
C27: иностранные инвестиции | G27: 29.1 | H27: 35.6 | I27: 28.1 | J27: 51.2 | K27: 104.7 | L27: 151.1 | M27: 439.8 | N27: 1588.5 | O27: 2701 | P27: 1611.5 | Q27: 1722.3 | R27: 1156.5236 | S27: 1035.5 | T27: 1159.5 | U27: 1571.8 | V27: 3583.4 | W27: 4606.2 | X27: 4462.1 | Y27: 4202.3 | Z27: 3026.8 | AA27: 2789.6 | AB27: 4103.1 | AC27: 4692 | AD27: 5519.2 | AE27: 4318.7
V28: =V27/Household!V2 -> 581.29613 | W28: =W27/Household!W2 -> 587.85543 | X28: =X27/Household!X2 -> 521.90135 | Y28: =Y27/Household!Y2 -> 459.20754 | Z28: =Z27/Household!Z2 -> 317.60422 | AA28: =AA27/Household!AA2 -> 270.26032 | AB28: =AB27/Household!AB2 -> 362.82043 | AC28: =AC27/Household!AC2 -> 425.54735 | ... AE28: =AE27/Household!AE2 -> 399.93147
C29: Инвестиции в ОК | M29: 0.77948718 | N29: 1.3291066 | O29: 0.53476862 | P29: -0.10181048 | Q29: 0.1318408 | R29: 0.098447944 | S29: -0.063490099 | T29: 0.27677195 | U29: 0.29298924 | V29: 0.30081919 | W29: =W22/V22-1 -> 0.18044288 | X29: =X22/W22-1 -> 0.025814131 | Y29: =Y22/X22-1 -> 0.13168393 | Z29: =Z22/Y22-1 -> -0.063109049 | AA29: =AA22/Z22-1 -> -0.071969515 | AB29: =AB22/AA22-1 -> 0.27032169 | AC29: =AC22/AB22-1 -> 0.10315643 | AD29: =AD22/AC22-1 -> 0.21987776 | AE29: =AE22/AD22-1 -> 0.13515283
C30: за счет бюджета | M30: 0.34492481 | N30: 0.27533194 | O30: 0.85388128 | P30: 0.20128079 | Q30: 0.33675059 | R30: 0.33954042 | S30: -0.075489239 | T30: 0.20188259 | U30: 0.27947238 | V30: 0.11018041 | W30: =W23/V23-1 -> 0.2768137 | X30: =X23/W23-1 -> 0.1395259 | Y30: =Y23/X23-1 -> 0.29019905 | Z30: =Z23/Y23-1 -> -0.032061588 | AA30: =AA23/Z23-1 -> -0.091752643 | AB30: =AB23/AA23-1 -> 0.074188046 | AC30: =AC23/AB23-1 -> 0.10281888 | AD30: =AD23/AC23-1 -> 0.17598599 | AE30: =AE23/AD23-1 -> 0.24083307
C31: частные | M31: 0.59972203 | N31: 1.5512598 | O31: -0.29490891 | P31: 0.90268051 | Q31: -0.054829293 | R31: 0.42104915 | S31: 0.057589786 | T31: 0.52063974 | U31: 0.35730654 | V31: 0.058138528 | W31: =W25/V25-1 -> -0.18434726 | X31: =X25/W25-1 -> -0.086622862 | Y31: =Y25/X25-1 -> 0.23904448 | Z31: =Z25/Y25-1 -> 0.35965962 | AA31: =AA25/Z25-1 -> 0.0089314818 | AB31: =AB25/AA25-1 -> 0.4357069 | AC31: =AC25/AB25-1 -> 0.039650749 | AD31: =AD25/AC25-1 -> 0.23839827 | AE31: =AE25/AD25-1 -> 0.44981997
C32: совместные | M32: 0.68667643 | N32: -0.085069444 | O32: 1.0047438 | P32: 0.32844297 | Q32: 0.12789455 | R32: 0.42104915 | S32: -0.18427072 | T32: 0.3880109 | U32: 0 | V32: -0.45779348 | W32: =W26/V26-1 -> 0.84431571 | X32: =X26/W26-1 -> -1.7763568e-15 | Y32: =Y26/X26-1 -> -0.14880251 | Z32: =Z26/Y26-1 -> -0.62684502 | AA32: =AA26/Z26-1 -> -0.72064277 | AB32: =AB26/AA26-1 -> 1.2455752 | AC32: =AC26/AB26-1 -> 1.2719212 | AD32: =AD26/AC26-1 -> 2.0177797 | AE32: =AE26/AD26-1 -> -0.85802558
C33: иностранные инвестиции | M33: 1.9106552 | N33: 2.611869 | O33: 0.70034624 | P33: -0.40336912 | Q33: 0.068755818 | R33: -0.32850049 | S33: -0.1046443 | T33: 0.11974891 | U33: 0.3555843 | V33: 1.2798066 | W33: =W27/V27-1 -> 0.28542725 | X33: =X27/W27-1 -> -0.031283922 | Y33: =Y27/X27-1 -> -0.058223706 | Z33: =Z27/Y27-1 -> -0.27972777 | AA33: =AA27/Z27-1 -> -0.078366592 | AB33: =AB27/AA27-1 -> 0.47085604 | AC33: =AC27/AB27-1 -> 0.14352563 | AD33: =AD27/AC27-1 -> 0.17630009 | AE33: =AE27/AD27-1 -> -0.21751341
C34: иностранные инвестиции | AC34: 2577 | AD34: 2690 | AE34: 4905.6
AD35: =AD34/AC34*100 -> 104.38494 | AE35: =AE34/AD34*100 -> 182.36431
AD36: =AD34-AC34 -> 113 | AE36: =AE34-AD34 -> 2215.6
B37: CONSTRt | C37: Строительство | G37: 38 | H37: 69.7 | I37: 68.9 | J37: 136.6 | K37: 262.3 | L37: 327.1 | M37: 567.5 | N37: 1034.6 | O37: 1832.6 | P37: 2098.4 | Q37: 2528.2 | R37: 2387.5 | S37: 3023.5 | T37: 4200.8 | U37: 4660 | V37: =GDP!V18 -> 7679.3 | W37: =GDP!W18 -> 8382.9 | X37: =GDP!X18 -> 7680.4 | Y37: =GDP!Y18 -> 9411.7 | Z37: =GDP!Z18 -> 9281.6 | AA37: =GDP!AA18 -> 8863.7 | AB37: =GDP!AB18 -> 11417.3 | AC37: =GDP!AC18 -> 13250.1 | ... AE37: =GDP!AE18 -> 12451.7 | AH37: CONSTRt = VAF,t
B38: defCONSTRt | C38: - дефлятор | L38: 107.13448 | M38: 161.84174 | N38: 165.13439 | O38: 146.1479 | P38: 135.50767 | Q38: 110 | R38: 89.511636 | S38: 167.51157 | T38: 118.54805 | U38: 88.532523 | V38: 135.96687 | W38: =W37/V37/W39*10000 -> 90.741724 | X38: =X37/W37/X39*10000 -> 88.011379 | Y38: =Y37/X37/Y39*10000 -> 111.19945 | Z38: =Z37/Y37/Z39*10000 -> 94.280763 | AA38: =AA37/Z37/AA39*10000 -> 91.824561 | AB38: =AB37/AA37/AB39*10000 -> 104.46848 | AC38: =AC37/AB37/AC39*10000 -> 104.17669 | AD38: =AD37/AC37/AD39*10000 -> 100.29394 | AE38: 104.7 | AH38: defCONSTRt = EXP(0,25+1,31·LN(erRURt/erRURt-1))·100
B39: gCONSTRt | C39: - темпы роста | L39: 116.4 | M39: 107.2 | N39: 110.4 | O39: 121.2 | P39: 84.5 | Q39: 109.52934 | R39: 105.5 | S39: 75.6 | T39: 117.2 | U39: 125.3 | V39: 121.2 | W39: 120.3 | X39: 104.1 | Y39: 110.2 | Z39: 104.6 | AA39: 104 | AB39: 123.3 | AC39: 111.4 | AD39: 112.3 | AE39: =AE37/AD37/AE38*10000 -> 79.690833 | AH39: gCONSTRt = CONSTRt/CONSTRt-1/defCONSTRt·10000
B41: соотношение строительство/инвестиции в ОК | G41: 0.34990792 | H41: 0.35780287 | I41: 0.33301112 | J41: 0.4290201 | K41: 0.44307432 | L41: 0.4792674 | M41: 0.46727048 | N41: 0.36575105 | O41: 0.4221219 | P41: 0.53813407 | Q41: 0.57283335 | R41: 0.49247112 | S41: 0.66593983 | T41: 0.72467568 | U41: 0.62173124 | V41: =V37/V22 -> 0.78762859 | W41: =W37/W22 -> 0.72836513 | X41: =X37/X22 -> 0.65053404 | Y41: =Y37/Y22 -> 0.70441584 | Z41: =Z37/Z22 -> 0.74147214 | AA41: =AA37/AA22 -> 0.76300046 | AB41: =AB37/AB22 -> 0.77367658 | AC41: =AC37/AC22 -> 0.8139132 | ... AE41: =AE37/AE22 -> 0.55235328
V43: =GDP!V2 -> 50977.4 | W43: =GDP!W2 -> 54790.3 | X43: =GDP!X2 -> 64434.3 | Y43: =GDP!Y2 -> 71059.2 | Z43: =GDP!Z2 -> 79109.8 | AA43: =GDP!AA2 -> 83958.3 | AB43: =GDP!AB2 -> 101076.3 | AC43: =GDP!AC2 -> 118181.7 | ... AE43: =GDP!AE2 -> 153402.2
V44: =V25+V26 -> 2720.5 | W44: =W25+W26 -> 2503.1 | X44: =X25+X26 -> 2330.4 | Y44: =Y25+Y26 -> 2689.9 | Z44: =Z25+Z26 -> 3229.6 | AA44: =AA25+AA26 -> 3140.4 | AB44: =AB25+AB26 -> 4545.3 | AC44: =AC25+AC26 -> 4850.6 | ... AE44: =AE25+AE26 -> 8393.8
V45: =V44/V43*100 -> 5.3366786 | W45: =W44/W43*100 -> 4.5685094 | X45: =X44/X43*100 -> 3.6167073 | Y45: =Y44/Y43*100 -> 3.7854352 | Z45: =Z44/Z43*100 -> 4.0824272 | AA45: =AA44/AA43*100 -> 3.7404283 | AB45: =AB44/AB43*100 -> 4.4968999 | AC45: =AC44/AC43*100 -> 4.104358 | ... AE45: =AE44/AE43*100 -> 5.4717599

Sheet Household
C1: Наименование индикатора | D1: 1997 | E1: 1998 | F1: 1999 | G1: 2000 | H1: 2001 | I1: 2002 | J1: 2003 | K1: 2004 | L1: 2005 | M1: 2006 | N1: 2007 | O1: 2008 | P1: 2009 | Q1: 2010 | R1: 2011 | S1: 2012 | T1: 2013 | U1: 2014 | V1: 2015 | W1: 2016 | X1: 2017 | Y1: 2018 | Z1: 2019 | AA1: 2020 | AB1: 2021 | AC1: 2022 | AD1: 2023 | AE1: 2024
C2: Курс доллара | G2: 1.9367939 | H2: 2.358832 | I2: 2.7677686 | J2: 3.0617 | K2: 2.9709 | L2: 3.1166 | M2: 3.2984 | N2: 3.4425 | O2: 3.43 | P2: 4.14 | Q2: 4.379 | R2: 4.6096 | S2: 4.7627 | T2: 4.7642 | U2: 4.9349 | V2: =Assumptions!V12 -> 6.1645 | W2: =Assumptions!W12 -> 7.8356 | X2: =Assumptions!X12 -> 8.5497 | Y2: =Assumptions!Y12 -> 9.1512 | Z2: =Assumptions!Z12 -> 9.5301 | AA2: =Assumptions!AA12 -> 10.3219 | AB2: =Assumptions!AB12 -> 11.3089 | AC2: =Assumptions!AC12 -> 11.0258 | ... AE2: =Assumptions!AE12 -> 10.7986
C3: Розничная и оптовая торговля | Q3: 6079.2 | R3: 7506.7 | S3: 9204.8 | T3: 11586.3 | U3: 13122.1 | V3: 14696.7 | W3: 16573.4 | X3: 18959.6 | Y3: 20989 | Z3: 25456.8 | AA3: 27599.7 | AB3: 33797.9 | AC3: =AC6+AC9 -> 47563.4 | AD3: =AD6+AD9 -> 56124.4 | AE3: =AE6+AE9 -> 65783.8
C4: - рост | Y4: 115.4 | Z4: 109 | AA4: 93.2 | AB4: 113 | AC4: 111.2 | AD4: 113.4 | AE4: 113.6
C5: - дефлятор | Y5: =Y3/X3/Y4*10000 -> 95.930513 | Z5: =Z3/Y3/Z4*10000 -> 111.27192 | AA5: =AA3/Z3/AA4*10000 -> 116.3281 | AB5: =AB3/AA3/AB4*10000 -> 108.36946 | AC5: =AC3/AB3/AC4*10000 -> 126.55473 | AD5: =AD3/AC3/AD4*10000 -> 104.05567 | AE5: =AE3/AD3/AE4*10000 -> 103.17843
C6: Оптовая торговля | Q6: 81.5 | R6: 81.2 | S6: 190.9 | T6: 10274.6 | U6: 298.2 | V6: 319 | W6: 406.7 | X6: 524.4 | Y6: 509.3 | Z6: 508.5 | AA6: 574.9 | AB6: 538.4 | AC6: 7977.2 | AD6: 8583.9 | AE6: 10120.8
C7: - рост | Y7: 95.992565 | Z7: 106.7 | AA7: 70.8 | AB7: 106.5 | AC7: 116.2 | AD7: 103.4 | AE7: 114.2
C8: - дефлятор | Y8: =Y12 -> 101.17504 | Z8: =Z12 -> 111.14932 | AA8: =AA12 -> 109.30698 | AB8: =AB12 -> 109.20168 | AC8: =AC12 -> 108.00566 | AD8: =AD12 -> 104.06726 | AE8: =AE12 -> 103.15897
C9: Розничная торговля, млн. сомони | J9: 1434.8 | K9: 1868.9 | L9: 2219.3 | M9: 2732.6 | N9: 3473.8 | O9: 4701.6 | P9: 5565.8 | Q9: 5997.7 | R9: 7425.5 | S9: 9013.9 | T9: 1311.7 | U9: 12823.9 | V9: 14377.7 | W9: 16166.7 | X9: 18435.2 | Y9: 20479.7 | Z9: 24948.3 | AA9: 27024.8 | AB9: 33259.5 | AC9: 39586.2 | AD9: 47540.5 | AE9: 55663
C10: 2003=100% | J10: 100 | K10: 123.2 | L10: 136 | M10: 150.7 | N10: 158.7 | O10: 178.4 | P10: 200.7 | Q10: 215.7525 | R10: 235.38598 | S10: 272.81235 | T10: 325.46513 | U10: 346.62036 | V10: 365.68448 | W10: =V10*W11/100 -> 389.08829 | X10: =W10*X11/100 -> 414.76812 | Y10: =X10*Y11/100 -> 455.41539 | Z10: =Y10*Z11/100 -> 499.13527 | AA10: =Z10*AA11/100 -> 494.64305 | AB10: =AA10*AB11/100 -> 557.46272 | AC10: =AB10*AC11/100 -> 614.32392 | AD10: =AC10*AD11/100 -> 708.9298 | AE10: =AD10*AE11/100 -> 804.63533
C11: - рост | K11: 123.2 | L11: 110.38961 | M11: 110.80882 | N11: 105.30856 | O11: 112.41336 | P11: 112.5 | Q11: 107.5 | R11: 109.1 | S11: 115.9 | T11: 119.3 | U11: 106.5 | V11: 105.5 | W11: 106.4 | X11: 106.6 | Y11: 109.8 | Z11: 109.6 | AA11: 99.1 | AB11: 112.7 | AC11: 110.2 | AD11: 115.4 | AE11: 113.5
C12: - дефлятор | K12: 105.72653 | L12: 107.57262 | M12: 111.11833 | N12: 120.71607 | O12: 120.39902 | P12: 105.22753 | Q12: 100.24176 | R12: 113.47919 | S12: 104.73784 | T12: 12.197795 | U12: 917.98587 | V12: 106.27151 | W12: =W9/V9/W11*10000 -> 105.6794 | X12: =X9/W9/X11*10000 -> 106.97179 | Y12: =Y9/X9/Y11*10000 -> 101.17504 | Z12: =Z9/Y9/Z11*10000 -> 111.14932 | AA12: =AA9/Z9/AA11*10000 -> 109.30698 | AB12: =AB9/AA9/AB11*10000 -> 109.20168 | AC12: =AC9/AB9/AC11*10000 -> 108.00566 | AD12: =AD9/AC9/AD11*10000 -> 104.06726 | AE12: =AE9/AD9/AE11*10000 -> 103.15897
W13: =W3-V3 -> 1876.7 | X13: =X3-W3 -> 2386.2 | Y13: =Y3-X3 -> 2029.4 | Z13: =Z3-Y3 -> 4467.8 | AA13: =AA3-Z3 -> 2142.9 | AB13: =AB3-AA3 -> 6198.2 | AC13: =AC3-AB3 -> 13765.5 | AD13: =AD3-AC3 -> 8561 | AE13: =AE3-AD3 -> 9659.4
J14: 544.1 | K14: 1017.5 | L14: 1191.6 | M14: 1593.8 | N14: 2119.7 | O14: 3577.3 | P14: 4345.8 | Q14: 5997.7 | R14: 7425.5 | S14: 9013.9 | T14: 11311.7 | U14: 12823.9 | W14: =W9-V9 -> 1789 | X14: =X9-W9 -> 2268.5 | Y14: =Y9-X9 -> 2044.5 | Z14: =Z9-Y9 -> 4468.6 | AA14: =AA9-Z9 -> 2076.5 | AB14: =AB9-AA9 -> 6234.7 | AC14: =AC9-AB9 -> 6326.7 | AD14: =AD9-AC9 -> 7954.3 | AE14: =AE9-AD9 -> 8122.5
C15: Платные услуги, млн. сомони | T15: 11566.3 | U15: 12757.6 | V15: 11782.9 | W15: 11729 | X15: 11998.8 | Y15: 12130.8 | Z15: 12983.6 | AA15: 13110.4 | AB15: 15111.8 | AC15: 18696.8 | AD15: 21760.3 | AE15: 25722.9
C16: - рост | U16: 106.082 | V16: 89.100849 | W16: =W15/V15/W21*10000 -> 94.919662 | X16: =X15/W15/X21*10000 -> 96.005737 | Y16: =Y15/X15/Y21*10000 -> 92.613961 | Z16: =Z15/Y15/Z21*10000 -> 102.9 | AA16: 97.4 | AB16: 107.9 | AC16: 116 | AD16: 114.1 | AE16: 113
C17: - дефлятор | U17: 103.97593 | V17: =V21 -> 103.65765 | W17: =W21 -> 104.87032 | X17: =X21 -> 106.55643 | Y17: =Y21 -> 109.16293 | Z17: =Z15/Y15/Z16*10000 -> 104.01364 | AA17: =AA15/Z15/AA16*10000 -> 103.67209 | AB17: =AB15/AA15/AB16*10000 -> 106.82645 | AC17: =AC15/AB15/AC16*10000 -> 106.65792 | AD17: =AD15/AC15/AD16*10000 -> 102.00277 | AE17: =AE15/AD15/AE16*10000 -> 104.61082
C18: Платные услуги населения, млн. сомони | J18: 756.5 | K18: 1142 | L18: 1460.3 | M18: 1865.3 | N18: 2390.2 | O18: 4011 | P18: 4635.2 | Q18: 5374.5 | R18: 6773.2 | S18: 8661.6 | T18: 9560 | U18: 10039.5 | V18: 9615.8 | W18: 10033.7 | X18: 10884 | Y18: 12130.8 | Z18: 12983.6 | AA18: 9723.6 | AB18: 9669.7 | AC18: 13866.9 | AD18: 16740.8 | AE18: 19094.9
C19: в ценах 2009 | J19: 2026 | K19: 2607.5 | L19: 3037.8 | M19: 3271.7 | N19: 3297.8736 | O19: 4132.2356 | P19: 4632.2361 | Q19: 5243.6913 | R19: 6219.0179 | S19: 6934.2049 | T19: 7530.5466 | U19: 7605.852 | V19: 7027.8073 | W19: =V19*W20/100 -> 6992.6682 | X19: =W19*X20/100 -> 7118.5363 | Y19: =X19*Y20/100 -> 7268.0255 | Z19: =Y19*Z20/100 -> 7478.7983 | AA19: =Z19*AA20/100 -> 6738.3972 | AB19: =AA19*AB20/100 -> 6832.7348 | AC19: =AB19*AC20/100 -> 7577.5029 | AD19: =AC19*AD20/100 -> 8971.7634 | AE19: =AD19*AE20/100 -> 9779.2221
C20: - рост | K20: 128.70188 | L20: 116.5024 | M20: 107.7 | N20: 100.8 | O20: 125.3 | P20: 112.1 | Q20: 113.2 | R20: 118.6 | S20: 111.5 | T20: 108.6 | U20: 101 | V20: 92.4 | W20: 99.5 | X20: 101.8 | Y20: 102.1 | Z20: 102.9 | AA20: 90.1 | AB20: 101.4 | AC20: 110.9 | AD20: 118.4 | AE20: 109
C21: - дефлятор | K21: 117.29305 | L21: 109.75925 | M21: 118.6017 | N21: 127.12326 | O21: 133.92676 | P21: 103.0885 | Q21: 102.42905 | R21: 106.26033 | S21: 114.691 | T21: 101.63188 | U21: 103.97593 | V21: 103.65765 | W21: =W18/V18/W20*10000 -> 104.87032 | X21: =X18/W18/X20*10000 -> 106.55643 | Y21: =Y18/X18/Y20*10000 -> 109.16293 | Z21: =Z18/Y18/Z20*10000 -> 104.01364 | AA21: =AA18/Z18/AA20*10000 -> 83.120312 | AB21: =AB18/AA18/AB20*10000 -> 98.072661 | AC21: =AC18/AB18/AC20*10000 -> 129.31081 | AD21: =AD18/AC18/AD20*10000 -> 101.96359 | AE21: =AE18/AD18/AE20*10000 -> 104.64408
W22: =W15-V15 -> -53.9 | X22: =X15-W15 -> 269.8 | Y22: =Y15-X15 -> 132 | Z22: =Z15-Y15 -> 852.8 | AA22: =AA15-Z15 -> 126.8 | AB22: =AB15-AA15 -> 2001.4 | AC22: =AC15-AB15 -> 3585 | AD22: =AD15-AC15 -> 3063.5 | AE22: =AE15-AD15 -> 3962.6
R23: 235.7 | S23: 301.41427 | T23: 332.67761 | U23: 349.36369 | W23: =W18-V18 -> 417.9 | X23: =X18-W18 -> 850.3 | Y23: =Y18-X18 -> 1246.8 | Z23: =Z18-Y18 -> 852.8 | AA23: =AA18-Z18 -> -3260 | AB23: =AB18-AA18 -> -53.9 | AC23: =AC18-AB18 -> 4197.2 | AD23: =AD18-AC18 -> 2873.9 | AE23: =AE18-AD18 -> 2354.1
AE24: 6063.0593
C25: Домашние хозяйства | AE25: =0.105*AE29 -> 8448.6486
C26: Выпуск | L26: 6051.8 | M26: 7950.9 | N26: 9889.2 | O26: 15299.7 | P26: 18535.5 | Q26: 22126 | R26: 29004.9 | S26: 35191.1 | T26: 38573.8 | U26: 41235.4 | V26: 44902.8 | W26: 48684.6 | X26: 58584.4 | Y26: 59770.5 | Z26: 67442.5 | AA26: 73948.5 | AB26: 88393.7 | AC26: 108414.8 | AD26: 117209.6 | AE26: =AD26*(Assumptions!AE56/100+1)*(Assumptions!AE57/100+1) -> 137577.96
C27: Промежуточное потребление | L27: 2953.7 | M27: 3865.2 | N27: 4833 | O27: 7952.5 | P27: 9126.9 | Q27: 10625.5 | R27: 14778.9 | S27: 16671.4 | T27: 19011 | U27: 19514.8 | V27: 23229.4 | W27: 25210.4 | X27: 30205 | Y27: 31589.3 | Z27: 35649.8 | AA27: 36157.3 | AB27: 47422.7 | AC27: 59476.9 | AD27: 62620 | AE27: =0.52*AE26 -> 71540.538
C28: Чистые налоги | L28: 354.1 | M28: 475.8 | N28: 676.7 | O28: 1017.3 | P28: 1122.7 | Q28: 1410.3 | R28: 2106 | S28: 2584.4 | T28: 3312.4 | U28: 3950.6 | V28: 2982.7 | W28: 3147.8 | X28: 3593.1 | Y28: 3652.6 | Z28: 4000.2 | AA28: 3922.2 | AB28: 5042.2 | AC28: 5557.4 | AD28: 6862.5 | AE28: 14425.9
C29: Валовая добавленная стоимость | L29: 3452.1 | M29: 4561.4 | N29: 5732.8 | O29: 8364.5 | P29: 10531.4 | Q29: 12910.8 | R29: 16332.1 | S29: 21104 | T29: 22875 | U29: 25671.2 | V29: =V26-V27+V28 -> 24656.1 | W29: =W26-W27+W28 -> 26622 | X29: =X26-X27+X28 -> 31972.5 | Y29: =Y26-Y27+Y28 -> 31833.8 | Z29: =Z26-Z27+Z28 -> 35792.9 | AA29: =AA26-AA27+AA28 -> 41713.4 | AB29: =AB26-AB27+AB28 -> 46013.2 | AC29: =AC26-AC27+AC28 -> 54495.3 | ... AE29: =AE26-AE27+AE28 -> 80463.32
C30: Чистые налоги на производство и импорт | L30: 446.7 | M30: 540.8 | N30: 779.7 | O30: 12846.8 | P30: 1537.3 | Q30: 1965.2 | R30: 2881.2 | S30: 3643.4 | T30: 4730 | U30: 5613.9 | V30: 4281.7 | W30: 4618.2 | X30: 3593.1 | Y30: 5527.2 | Z30: 6064.4 | AA30: 5995.1 | AB30: 8404.3 | AC30: 11075.3 | AD30: 12936.3 | AE30: =0.146*AE29 -> 11747.645
C31: Валовая прибыль (валовая смешенный доход) | L31: 3005.4 | M31: 4020.7 | N31: 4953.1 | O31: 7136.6 | P31: 8994 | Q31: 10945.6 | R31: 13450.9 | S31: 17460.6 | T31: 18145.1 | U31: 20057.3 | V31: 20374.4 | W31: =W29-W30 -> 22003.8 | X31: =X29-X30 -> 28379.4 | Y31: 26306.5 | Z31: =Z29-Z30 -> 29728.5 | AA31: =AA29-AA30 -> 35718.3 | AB31: =AB29-AB30 -> 37608.9 | AC31: =AC29-AC30 -> 43420 | AD31: =AD29-AD30 -> 48515.8 | AE31: =AE29-AE30 -> 68715.675
C32: - без чистых налогов | L32: 2651.3 | M32: 3544.9 | N32: 4276.4 | O32: 6119.3 | P32: 7871.4 | Q32: 9535.2 | R32: 11344.9 | S32: 14876.2 | T32: 14832.7 | U32: 16106.7 | V32: =V31-V28 -> 17391.7 | W32: =W31-W28 -> 18856 | X32: =X31-X28 -> 24786.3 | Y32: =Y31-Y28 -> 22653.9 | Z32: =Z31-Z28 -> 25728.3 | AA32: =AA31-AA28 -> 31796.1 | AB32: =AB31-AB28 -> 32566.7 | AC32: =AC31-AC28 -> 37862.6 | ... AE32: =AE31-AE28 -> 54289.775
C33: Заработная плата и транферты из-за рубежа, в том числе: | L33: 3147.6 | M33: 4762.6 | N33: 5980.2 | O33: 10135.1 | P33: 8094.3 | Q33: 10468.6 | R33: 10909.6 | S33: 15061.7 | T33: 23565 | U33: 23229.7 | V33: =SUM(V34:V36) -> 18463.5 | W33: =SUM(W34:W36) -> 19414.4 | X33: =SUM(X34:X36) -> 23755.1 | Y33: =SUM(Y34:Y36) -> 25470.3 | Z33: =SUM(Z34:Z36) -> 27904.7 | AA33: =SUM(AA34:AA36) -> 28507.5 | AB33: =SUM(AB34:AB36) -> 37625.9 | AC33: =SUM(AC34:AC36) -> 57778.6 | ... AE33: =SUM(AE34:AE36) -> 18338.56
C34: Государство и НКО | H34: 378.1 | I34: 437.4 | J34: 489.8 | K34: 831.8 | L34: 260.6 | M34: 365.7 | N34: 526.5 | O34: 652 | P34: 919.3 | Q34: 1138.2 | R34: 1328.9 | S34: 1744.4 | T34: 2401.2 | U34: 3177.3 | V34: 3403.7 | W34: 3915.2 | X34: 4496.9 | Y34: 4923.9 | Z34: 4980.3 | AA34: 5417.4 | AB34: 6169.5 | AC34: 7053.8 | AD34: 10667.5 | AE34: =Assumptions!AE53 -> 11211.542
C35: Нефинансовые и финансовые предприятия | L35: 752.4 | M35: 902.3 | N35: 1219.2 | O35: 1509.6 | P35: 1962 | Q35: 2412 | R35: 2942 | S35: 3531.3 | T35: 4167 | U35: 4481.1 | V35: 4935.3 | W35: 5187.6 | X35: 5650.1 | Y35: 6496.3 | Z35: 7364.3 | AA35: 7217.5 | AB35: 8221.7 | AC35: 9278.9 | AD35: 8177.8 | AE35: =AD35*(GDP!AE17/GDP!AD17) -> 7127.0178
C36: Из зарубежа | H36: 594.3 | I36: 710.7 | J36: 1251.3 | K36: 1975.4 | L36: 2134.6 | M36: 3494.6 | N36: 4234.5 | O36: 7973.5 | P36: 5213 | Q36: 6918.4 | R36: 6638.7 | S36: 9786 | T36: 16996.8 | U36: 15571.3 | V36: 10124.5 | W36: 10311.6 | X36: 13608.1 | Y36: 14050.1 | Z36: 15560.1 | AA36: 15872.6 | AB36: 23234.7 | AC36: 41445.9 | AD36: 35336.7 | AE36: =GDP!AE128 -> 0
C37: Итого: зарплата и прибыль | L37: 5798.9 | M37: 8307.5 | N37: 10256.6 | O37: 16254.4 | P37: 17644.408 | Q37: 22814.398 | R37: 22254.5 | S37: 29937.9 | T37: 38397.7 | U37: 39336.4 | V37: =V33+V32 -> 35855.2 | W37: =W33+W32 -> 38270.4 | X37: =X33+X32 -> 48541.4 | Y37: =Y33+Y32 -> 48124.2 | Z37: =Z33+Z32 -> 53633 | AA37: =AA33+AA32 -> 60303.6 | AB37: =AB33+AB32 -> 70192.6 | AC37: =AC33+AC32 -> 95641.2 | ... AE37: =AE33+AE32 -> 72628.336
C38: Доходы от собственности | L38: 16 | M38: 25 | N38: 45.1 | O38: 72.3 | P38: 101.4 | Q38: 152 | R38: 1097 | S38: 906.5 | T38: 1117 | U38: 2134.8 | V38: 1227.7 | W38: 1486.7 | X38: 982.3 | Y38: 1078.5 | Z38: 1253.5 | AA38: 643.1 | AB38: 845.6 | AC38: 1066.3 | AD38: 1087.7 | AE38: =AD38*GDP!AE93/GDP!AD93 -> 1256.6138
C39: Текущие трансферты | L39: 273.2 | M39: 357.6 | N39: 481.2 | O39: 773.5 | P39: 1157.1 | Q39: 1272.4 | R39: 1676.2 | S39: 2008.112 | T39: 1970.7 | U39: 2278.1 | V39: 1469.9 | W39: 2430.5 | X39: 2319 | Y39: 2836.5 | Z39: 2065 | AA39: 2035.1 | AB39: 2569.7 | AC39: 3200 | AD39: 3263.9 | AE39: =AD39*GDP!AE93/GDP!AD93 -> 3770.7657
C40: Социальные трансферты в натуральной форме | L40: 768.1 | M40: 662.5 | N40: 904 | O40: 1088.8 | P40: 2242.2 | Q40: 2267.4 | R40: 2898.8 | S40: 3838.8 | T40: 4525.3 | U40: 5399.5 | V40: 4055.1 | W40: 4817.9 | X40: 5466.7 | Y40: 5744 | Z40: 6433.2 | AA40: 7283.3 | AB40: 8932.6 | AC40: 10146.4 | AD40: 10448.9 | AE40: =Assumptions!AE52 -> 12016.235
C41: ИТОГО ДОХОДЫ | L41: 6856.2 | M41: 9352.6 | N41: 11686.9 | O41: 18189 | P41: 21144.908 | Q41: 26506.198 | R41: 27926.5 | S41: 36691.312 | T41: 46010.7 | U41: 49148.8 | V41: =SUM(V37:V40) -> 42607.9 | W41: =SUM(W37:W40) -> 47005.5 | X41: =SUM(X37:X40) -> 57309.4 | Y41: =SUM(Y37:Y40) -> 57783.2 | Z41: =SUM(Z37:Z40) -> 63384.7 | AA41: =SUM(AA37:AA40) -> 70265.1 | AB41: =SUM(AB37:AB40) -> 82540.5 | AC41: =SUM(AC37:AC40) -> 110053.9 | ... AE41: =SUM(AE37:AE40) -> 89671.95
C42: Налоги | L42: 40.5 | M42: 163.6 | N42: 327.2 | O42: 376.2 | P42: 468 | Q42: 559.5 | R42: 696.3 | S42: 871 | T42: 1021.2 | U42: 1153.2 | V42: 1248.5806 | W42: 1356.699 | X42: 1695.1362 | Y42: 1653.4436 | Z42: 1847.4851 | AA42: 2156.0115 | AB42: 2278.6292 | AC42: 2629.8236 | AD42: 2935.6908 | AE42: 3524.2855
C43: Располагаемые доходы (вкл. субсидии) | L43: 6815.7 | M43: 9189 | N43: 11359.7 | O43: 17812.8 | P43: 20676.908 | Q43: 25946.698 | R43: 27230.2 | S43: 35820.312 | T43: 44989.5 | U43: 47995.6 | V43: =V41-V42 -> 41359.319 | W43: =W41-W42 -> 45648.801 | X43: =X41-X42 -> 55614.264 | Y43: =Y41-Y42 -> 56129.756 | Z43: =Z41-Z42 -> 61537.215 | AA43: =AA41-AA42 -> 68109.088 | AB43: =AB41-AB42 -> 80261.871 | AC43: =AC41-AC42 -> 107424.08 | ... AE43: =AE41-AE42 -> 86147.665
C44: Располагаемые доходы денежные | L44: 3396.3 | M44: 4981.6 | N44: 6179.3 | O44: 10604.7 | P44: 10563.308 | Q44: 14144.098 | R44: 12986.5 | S44: 17105.312 | T44: 25631.5 | U44: 26489.4 | V44: =V43-V40-V32 -> 19912.519 | W44: =W43-W40-W32 -> 21974.901 | X44: =X43-X40-X32 -> 25361.264 | Y44: =Y43-Y40-Y32 -> 27731.856 | Z44: =Z43-Z40-Z32 -> 29375.715 | AA44: =AA43-AA40-AA32 -> 29029.688 | AB44: =AB43-AB40-AB32 -> 38762.571 | AC44: =AC43-AC40-AC32 -> 59415.076 | ... AE44: =AE43-AE40-AE32 -> 19841.654
C45: Фактическое конечное потребление | L45: 6432 | M45: 8186.2 | N45: 11093.6 | O45: 16233.8 | P45: 19532.8 | Q45: 22819 | R45: 31464 | S45: 39226.8 | T45: 44135.5 | U45: 49278.7 | V45: 47627 | W45: 47267 | X45: 56444.5 | Y45: 59307.7 | Z45: 65923.1 | AA45: 71467.8 | AB45: 88467.7 | AC45: 111546.8 | AD45: 126991.7 | AE45: =AD45*AE43/AD43 -> 101578.71
C46: Расходы на конечное потребление | L46: 6899.3 | M46: 8773.8 | N46: 11923.8 | O46: 17156.5 | P46: 20380.2 | Q46: 23726.2 | R46: 28932.7 | S46: 36067.9 | T46: 40396.6 | U46: 44710.8 | V46: 36003 | W46: 43219.8 | X46: 51499.4 | Y46: 53938.7 | Z46: 59925 | AA46: 64584 | AB46: 80377.1 | AC46: 102715.8 | AD46: 118160.2
C47: - в том числе рыночные | L47: 3679.6 | M47: 4597.9 | N47: 5864 | O47: 8712.6 | P47: 10201 | Q47: 11372.2 | R47: 14198.7 | S47: 17675.5 | T47: 10871.7 | U47: 22863.4 | V47: =V9+V18 -> 23993.5 | W47: =W9+W18 -> 26200.4 | X47: =X9+X18 -> 29319.2 | Y47: =Y9+Y18 -> 32610.5 | Z47: =Z9+Z18 -> 37931.9 | AA47: =AA9+AA18 -> 36748.4 | AB47: =AB9+AB18 -> 42929.2 | AC47: =AC9+AC18 -> 53453.1 | ... AE47: =AE9+AE18 -> 74757.9
C48: Склонность к потреблению розничной торговли | L48: 0.32561586 | M48: 0.2973773 | N48: 0.30580033 | O48: 0.26394503 | P48: 0.26917951 | Q48: 0.23115465 | R48: 0.27269355 | S48: 0.25164214 | T48: 0.029155692 | U48: 0.26718908 | V48: =V9/V43 -> 0.34762903 | W48: =W9/W43 -> 0.35415388 | X48: =X9/X43 -> 0.33148331 | Y48: =Y9/Y43 -> 0.36486351 | Z48: =Z9/Z43 -> 0.40541809 | AA48: =AA9/AA43 -> 0.39678699 | AB48: =AB9/AB43 -> 0.4143873 | AC48: =AC9/AC43 -> 0.36850398 | ... AE48: =AE9/AE43 -> 0.64613475
C49: Склонность к потреблению платных услуг | L49: 0.21425532 | M49: 0.20299271 | N49: 0.21041049 | O49: 0.22517515 | P49: 0.22417278 | Q49: 0.20713618 | R49: 0.24873853 | S49: 0.24180694 | T49: 0.21249403 | U49: 0.20917542 | V49: =V18/V43 -> 0.23249415 | W49: =W18/W43 -> 0.21980205 | X49: =X18/X43 -> 0.19570519 | Y49: =Y18/Y43 -> 0.21612066 | Z49: =Z18/Z43 -> 0.21098777 | AA49: =AA18/AA43 -> 0.14276509 | AB49: =AB18/AB43 -> 0.12047688 | AC49: =AC18/AC43 -> 0.12908559 | ... AE49: =AE18/AE43 -> 0.22165314
C50: - склонность к потреблению (полному доходу) | L50: 0.53987118 | M50: 0.50037001 | N50: 0.51621082 | O50: 0.48912018 | P50: 0.4933523 | Q50: 0.43829084 | R50: 0.52143209 | S50: 0.49344908 | T50: 0.24164972 | U50: 0.4763645 | V50: =V47/V43 -> 0.58012318 | W50: =W47/W43 -> 0.57395593 | X50: =X47/X43 -> 0.52718849 | Y50: =Y47/Y43 -> 0.58098417 | Z50: =Z47/Z43 -> 0.61640586 | AA50: =AA47/AA43 -> 0.53955207 | AB50: =AB47/AB43 -> 0.53486418 | AC50: =AC47/AC43 -> 0.49758957 | ... AE50: =AE47/AE43 -> 0.86778789
C51: - склонность к потреблению (без прибыли) | L51: 0.88358467 | M51: 0.81463829 | N51: 0.82786272 | O51: 0.7450806 | P51: 0.79661034 | Q51: 0.69294101 | R51: 0.89382637 | S51: 0.84393647 | T51: 0.36050576 | U51: 0.71697048 | V51: =V47/(V43-V32) -> 1.0010798 | W51: =W47/(W43-W32) -> 0.97788955 | X51: =X47/(X43-X32) -> 0.9510586 | Y51: =Y47/(Y43-Y32) -> 0.97414983 | Z51: =Z47/(Z43-Z32) -> 1.0592865 | AA51: =AA47/(AA43-AA32) -> 1.0119905 | AB51: =AB47/(AB43-AB32) -> 0.90007435 | AC51: =AC47/(AC43-AC32) -> 0.76842964 | ... AE51: =AE47/(AE43-AE32) -> 2.3466055
C52: - склонность к потреблению (без прибыли и соцтранфертов) | L52: 1.0834143 | M52: 0.92297655 | N52: 0.9489748 | O52: 0.82157911 | P52: 0.96570128 | Q52: 0.8040244 | R52: 1.0933431 | S52: 1.033334 | T52: 0.42415387 | U52: 0.86311506 | V52: =V47/V44 -> 1.2049455 | W52: =W47/W44 -> 1.1922875 | X52: =X47/X44 -> 1.1560623 | Y52: =Y47/Y44 -> 1.175922 | Z52: =Z47/Z44 -> 1.2912673 | AA52: =AA47/AA44 -> 1.2658903 | AB52: =AB47/AB44 -> 1.107491 | AC52: =AC47/AC44 -> 0.89965549 | ... AE52: =AE47/AE44 -> 3.7677251
C53: Валовое сбережение | L53: 6448.3 | M53: 1371.9 | N53: 777.5 | O53: 2684.5 | P53: 139.7 | Q53: 1527.1 | R53: -2843.5 | S53: -2438.6 | T53: 1900.5 | U53: -2058 | V53: 21178.8 | W53: 17673.5 | X53: 19551.1 | Y53: 24508.1 | Z53: 28757.5 | AA53: 30106.7 | AB53: 40454.8 | AC53: 59136 | AD53: 56178.8 | AE53: =AD53 -> 56178.8
C54: Валовое накопленое основного капитала | L54: 68.3 | M54: 407.6 | N54: 460.9 | O54: 712 | P54: 1676 | Q54: 1785.2 | R54: 2923.4 | S54: 1924.7 | T54: 2852.7 | U54: 3618.3 | V54: 19736.9 | W54: 21954 | X54: 20133 | Y54: 25146.8 | Z54: 24926.6 | AA54: 23150.4 | AB54: 32314.3 | AC54: 37469.9 | AD54: 37577.9
C55: Чистое кредитование и статистическое расхождение | L55: 581.6 | M55: 966 | N55: 318.5 | O55: 1975.8 | P55: 1974.4 | Q55: -254.6 | R55: -5763 | S55: -4358.1 | T55: -947.7 | U55: -5671.6 | V55: -650.8 | W55: -3375 | X55: 1527.6 | Y55: -293.7 | Z55: 2431 | AA55: 4128 | AB55: 8631.1 | AC55: 20574.2 | AD55: 18009.3
C57: Распологаемые доходы, реальные, % | M57: 22.921075 | N57: 2.1228099 | O57: 36.406958 | P57: 9.6789314 | Q57: 18.986355 | R57: -7.5533131 | S57: 25.746268 | T57: 21.897734 | U57: -0.7182187 | V57: -18.926852 | W57: =W43/V43*100-Monetary!W15 -> 4.2712577 | X57: =X43/W43*100-Monetary!X15 -> 15.089622 | Y57: =Y43/X43*100-Monetary!Y15 -> -4.4519796 | Z57: =Z43/Y43*100-Monetary!Z15 -> 1.6338535 | AA57: =AA43/Z43*100-Monetary!AA15 -> 1.2795109 | AB57: =AB43/AA43*100-Monetary!AB15 -> 9.843114 | AC57: =AC43/AB43*100-Monetary!AC15 -> 29.641979 | AD57: =AD43/AC43*100-Monetary!AD15 -> -3.5430439 | AE57: =AE43/AD43*100-Monetary!AE15 -> -23.611534
C58: Налоги | W58: =(W37-W36)/(V37-V36)*V42 -> 1356.699 | X58: =(X37-X36)/(W37-W36)*W42 -> 1695.1362 | Y58: =(Y37-Y36)/(X37-X36)*X42 -> 1653.4436 | Z58: =(Z37-Z36)/(Y37-Y36)*Y42 -> 1847.4851 | AA58: =(AA37-AA36)/(Z37-Z36)*Z42 -> 2156.0115 | AB58: =(AB37-AB36)/(AA37-AA36)*AA42 -> 2278.6292 | AC58: =(AC37-AC36)/(AB37-AB36)*AB42 -> 2629.8236 | AD58: =(AD37-AD36)/(AC37-AC36)*AC42 -> 2935.6908 | AE58: =(AE37-AE36)/(AD37-AD36)*AD42 -> 3524.2855
C59: Располагаемые доходы (вкл. субсидии) | O59: 49.077609 | P59: -26.535963 | Q59: 22.832987 | R59: -8.2874023 | S59: 32.259141 | T59: 52.756442 | U59: -8.8228729 | V59: =V41-V42 -> 41359.319 | W59: =W41-W42 -> 45648.801 | X59: =X41-X42 -> 55614.264 | Y59: =Y41-Y42 -> 56129.756 | Z59: =Z41-Z42 -> 61537.215 | AA59: =AA41-AA42 -> 68109.088 | AB59: =AB41-AB42 -> 80261.871 | AC59: =AC41-AC42 -> 107424.08 | ... AE59: =AE41-AE42 -> 86147.665

Sheet Assumptions
D1: 1997 | E1: 1998 | F1: 1999 | G1: 2000 | H1: 2001 | I1: 2002 | J1: 2003 | K1: 2004 | L1: 2005 | M1: 2006 | N1: 2007 | O1: 2008 | P1: 2009 | Q1: 2010 | R1: 2011 | S1: 2012 | T1: 2013 | U1: 2014 | V1: 2015 | W1: 2016 | X1: 2017 | Y1: 2018 | Z1: 2019 | AA1: 2020 | AB1: 2021 | AC1: 2022 | AD1: 2023 | AE1: 2024
A2: Var. Name | B2: Внешние сценарные условия | C2: External scenario conditions
A3: gGDPWt | B3: Темпы роста мировой экономики,% | C3: Global economic growth ,% NGDP_RPCH | G3: 4.821 | H3: 2.515 | I3: 2.96 | J3: 4.055 | K3: 5.185 | L3: 4.872 | M3: 5.544 | N3: 5.702 | O3: 3.064 | P3: 0.028 | Q3: 5.431 | R3: 4.225 | S3: 3.426 | T3: 3.308 | U3: 3.428 | V3: 3.2 | W3: 3.2 | X3: 3.8 | Y3: 3.5 | Z3: 2.8 | AA3: -3.2 | AB3: 6.1 | AC3: 3.4 | AD3: 3.3 | AE3: 3.2
A4: gGDPDEt | B4: Темпы роста экономики развивающихся стран, % | C4: Economic growth in developing countries , % NGDP_RPCH | G4: 5.834 | H4: 3.803 | I4: 4.527 | J4: 6.421 | K4: 7.504 | L4: 7.253 | M4: 8.166 | N4: 8.682 | O4: 5.825 | P4: 3.13 | Q4: 7.451 | R4: 6.323 | S4: 5.211 | T4: 4.976 | U4: 4.626 | V4: 3.965 | W4: 4.4 | X4: 4.7 | Y4: 4.5 | Z4: 1.6 | AA4: -4.5 | AB4: 6.6 | AC4: 3.7 | AD4: 4.4 | AE4: 4.2
A5: gTRADEWt | B5: Объем мировой торговл, рост, % | C5: Volume of world trade, growth rate, % TRADEPCH | G5: 12.092 | H5: 0.216 | I5: 3.771 | J5: 5.435 | K5: 11.016 | L5: 7.688 | M5: 9.242 | N5: 7.915 | O5: 2.903 | P5: -10.327 | Q5: 12.517 | R5: 6.666 | S5: 2.911 | T5: 3.331 | U5: 3.9 | V5: 2.7 | W5: 2.5 | X5: 5.7 | Y5: 3.6 | Z5: 1 | AA5: -8.2 | AB5: 10.1 | AC5: 4.1 | AD5: 0.8 | AE5: 3.1
A6: pOILWt | B6: Мировые цены на нефть (brent+dubai+wti), долл./барр. | C6: World oil prices (brent + dubai + wti) , USD/bar | G6: 28.234 | H6: 24.331 | I6: 24.95 | J6: 28.892 | K6: 37.76 | L6: 53.354 | M6: 64.273 | N6: 71.128 | O6: 97.035 | P6: 61.777 | Q6: 79.03 | R6: 104.008 | S6: 105.007 | T6: 104.069 | U6: 97.387119 | V6: 50.793042 | W6: 42.7 | X6: 54.4 | Y6: 71.07 | Z6: 64.03 | AA6: 42.8 | AB6: 71 | AC6: 96.7 | AD6: 80.6 | AE6: 81.29
A7: pALWt | B7: Мировые цены на алюминий, долл./тонн | C7: Worldwide aluminum prices , USD/t | G7: 1551.498 | H7: 1446.747 | I7: 1351.057 | J7: 1432.836 | K7: 1718.508 | L7: 1900.514 | M7: 2573.063 | N7: 2639.861 | O7: 2577.916 | P7: 1669.175 | Q7: 2173.005 | R7: 2400.643 | S7: 2022.795 | T7: 1846.677 | U7: 1867.4211 | V7: 1664.7 | W7: 1604.1819 | X7: 1967.7 | Y7: 2108.5 | Z7: 1802.05 | AA7: 1824.4 | AB7: 2505 | AC7: 2494 | AD7: 2256.1 | AE7: 2410.04
A8: pidxAGWt | B8: Индекс цен на сельхозсырье, 2005=100 | C8: The price index for agricultural raw, 2005=100 | G8: 98.406 | H8: 95.057 | I8: 94.859 | J8: 95.421 | K8: 99.291 | L8: 100 | M8: 108.728 | N8: 114.165 | O8: 113.367 | P8: 93.929 | Q8: 125.10798 | R8: 153.50408 | S8: 134.03217 | T8: 136.20047 | U8: 145.1 | V8: 166 | W8: 107.6 | X8: 111.8 | Y8: 104.4 | Z8: 86.6 | AA8: 153.6 | AB8: 112.2 | AC8: 114.4 | AD8: 101.2 | AE8: 106.06
A9: pCOTWt | B9: Мировые цены на хлопок, cents/pound | C9: World cotton prices, USD/tonn | G9: 59.048 | H9: 47.997 | I9: 46.26 | J9: 63.444 | K9: 62.006 | L9: 55.168 | M9: 58.052 | N9: 63.284 | O9: 71.4 | P9: 62.752 | Q9: 103.54455 | R9: 154.60834 | S9: 89.240967 | T9: 90.400613 | U9: 83.096741 | V9: 70.417182 | W9: 74.2 | X9: 83.6 | Y9: 91.4 | Z9: 77.9 | AA9: 71.2 | AB9: 72.6 | AC9: 74.1 | AD9: 95.01 | AE9: 86.7
A10: pWHWt | B10: Мировые цены на пшеницу, долл./тонн | C10: World wheat prices, USD/tonn | G10: 114.004 | H10: 126.805 | I10: 148.528 | J10: 146.142 | K10: 156.882 | L10: 152.439 | M10: 191.721 | N10: 255.206 | O10: 325.94 | P10: 190.11167 | Q10: 194.50038 | R10: 279.98907 | S10: 276.12152 | T10: 265.75129 | U10: 242.4956 | V10: 284.9 | W10: 204.4 | X10: 166.6 | Y10: 210 | Z10: 202 | AA10: 211 | AB10: 255 | AC10: 320 | AD10: 272.3 | AE10: 202.6
A11: dCPIWt | B11: Мировая инфляция, % средняя | C11: World inflationб CPI average, PCPIPCH | G11: 4.858 | H11: 4.645 | I11: 3.726 | J11: 3.944 | K11: 3.841 | L11: 4.084 | M11: 4.088 | N11: 4.34 | O11: 6.412 | P11: 2.768 | Q11: 3.786 | R11: 5.151 | S11: 4.18 | T11: 3.857 | U11: 3.2 | V11: 2.7 | W11: 2.6 | X11: 3.2 | Y11: 3.6 | Z11: 3.5 | AA11: 3.2 | AB11: 4.7 | AC11: 8.8 | AD11: 6.7 | AE11: 5.8
A12: erUSDt | B12: Средний обменный курс (TJS/USD) | C12: Average exchange rate (TJS/USD) | G12: 1.9367939 | H12: 2.358832 | I12: 2.7677686 | J12: 3.0617 | K12: 2.9709 | L12: 3.1166 | M12: 3.2984 | N12: 3.4425 | O12: 3.43 | P12: 4.14 | Q12: 4.379 | R12: 4.6096 | S12: 4.7627 | T12: 4.7642 | U12: 4.9349 | V12: 6.1645 | W12: 7.8356 | X12: 8.5497 | Y12: 9.1512 | Z12: 9.5301 | AA12: 10.3219 | AB12: 11.3089 | AC12: 11.0258 | AD12: 10.8445 | AE12: 10.7986
A13: erRURt | B13: Курс рубля , руб./сомони | C13: RUB/Somoni | G13: 0.6514 | H13: 0.8138 | I13: 0.8821 | J13: 0.997 | K13: 1.0304 | L13: 1.1027 | M13: 1.2145 | N13: 1.3466 | O13: 1.3854 | P13: 1.3227 | Q13: 1.4544 | R13: 1.58 | S13: 1.5324003 | T13: 1.4645558 | U13: 1.1102137 | V13: =V12/V19*10 -> 1.0105738 | W13: =W12/W19*10 -> 1.1689691 | X13: =X12/X19*10 -> 1.4015902 | Y13: =Y12/Y19*10 -> 1.4525714 | Z13: =Z12/Z19*10 -> 1.4572018 | AA13: =AA12/AA19*10 -> 1.4355911 | AB13: =AB12/AB19*10 -> 1.5365353 | AC13: =AC12/AC19*10 -> 1.6190602 | AD13: 1.3962366 | AE13: 1.1653933
A14: MIGRUSt | B14: Число мигрантов из Таджикистана в России, тыс.чел. | C14: The number of migrants from Tajikistan in Russia, thousand persons | O14: 646.298 | P14: 677.414 | Q14: 736.446 | R14: 750.07 | S14: 744.368 | T14: 799.698 | U14: 770.898 | V14: 706.898 | W14: =V14+(W17-V17) -> 571.898 | X14: =W14+(X17-W17) -> 610.898 | Y14: =X14+(Y17-X17) -> 776.898 | Z14: =Y14+(Z17-Y17) -> 1286.898 | AA14: =Z14+(AA17-Z17) -> 466.898 | AB14: =AA14+(AB17-AA17) -> 332.898 | AC14: =AB14+(AC17-AB17) -> 333.898 | AD14: 332.898 | AE14: 332.478
A15: InvFt | B15: Зарубежные инвестиции (по счету инвестиций), млн. долл. США | C15: Foreign investments (investment survey), mln USD | G15: 15.02483 | H15: 15.092215 | I15: 10.152583 | J15: 16.722736 | K15: 35.241846 | L15: 48.48232 | M15: 133.33738 | N15: 461.43791 | O15: 989.2501 | P15: 383.136 | Q15: 459.1736 | R15: 325.5185 | S15: 746.4113 | T15: 1011.8628 | U15: 909.2544 | V15: 977.8 | W15: 842.7 | X15: 1100.4 | Y15: 644.4 | Z15: 607.1 | AA15: 482 | AB15: 823.4 | AC15: 2577 | AD15: 2690 | AE15: 3222
A16: WRUS, USt | B16: Средняя зарплата в России, долл. | C16: The average salary in Russia, U.S. | G16: 141.6246 | H16: 182.51542 | I16: 217.82526 | J16: 290.20215 | K16: 380.98924 | L16: 481.49826 | M16: 650.24821 | N16: 864.91071 | O16: 634.49541 | P16: 632.65445 | Q16: 682.25334 | R16: 748.52659 | S16: 856.78893 | T16: 915.83154 | U16: 731.04612 | V16: =V18/V19 -> 557.86885 | W16: =W18/W19 -> 505.38565 | X16: =X18/X19 -> 642.08197 | Y16: =Y18/Y19 -> 694.03175 | Z16: =Z18/Z19 -> 731.91131 | AA16: =AA18/AA19 -> 714.2088 | AB16: =AB18/AB19 -> 777.76703 | AC16: =AC18/AC19 -> 938.14771 | AD16: 965.85806 | AE16: 904.22627
B17: Потребность России в мигрантах (высокий вар.), тыс.чел. | C17: Russia's need for Migrants, thousand | P17: 1983.695 | Q17: 2088.1 | R17: 2198 | S17: 2368 | T17: 2334 | U17: 2238 | V17: 2174 | W17: 2039 | X17: 2078 | Y17: 2244 | Z17: 2754 | AA17: 1934 | AB17: 1800 | AC17: 1801 | AD17: 1800 | AE17: 1799.58
A18: WRUS, RUBt | B18: Средняя зарплата в России, руб. | C18: The average salary in Russia, RUB | G18: 3983.9 | H18: 5325.8 | I18: 6831 | J18: 8900.5 | K18: 10976.3 | L18: 13819 | M18: 17290.1 | N18: 21311.4 | O18: 17290 | P18: 18638 | Q18: 20952 | R18: 23369 | S18: 26629 | T18: 29792 | U18: 32495 | V18: 34030 | W18: 33876 | X18: 39167 | Y18: 43724 | Z18: 47867 | AA18: 51351.613 | AB18: 57243.654 | AC18: 63887.859 | AD18: 74854 | AE18: 83656
A19: erRUR/USDt | B19: Курс доллара к рублю, руб./долл. | C19: Exhange rate, Rub/dollar | G19: 28.13 | H19: 29.18 | I19: 31.36 | J19: 30.67 | K19: 28.81 | L19: 28.7 | M19: 26.59 | N19: 24.64 | O19: 27.25 | P19: 29.46 | Q19: 30.71 | R19: 31.22 | S19: 31.08 | T19: 32.53 | U19: 44.45 | V19: 61 | W19: 67.03 | X19: 61 | Y19: 63 | Z19: 65.4 | AA19: 71.9 | AB19: 73.6 | AC19: 68.1 | AD19: 77.5 | AE19: 92.516667
A20: pFVRUBt | B20: Цены на плодоовощную продукцию в России, $/tn | C20: Prices for fruits and vegetables in Russia, $/tn | Q20: 320 | R20: 336.4832 | S20: 350.5482 | T20: 364.06884 | U20: 375.71904 | V20: 385.86346 | W20: =V20*(1+W11/100) -> 395.89591 | X20: =W20*(1+X11/100) -> 408.56458 | Y20: =X20*(1+Y11/100) -> 423.2729 | Z20: =Y20*(1+Z11/100) -> 438.08745 | AA20: =Z20*(1+AA11/100) -> 452.10625 | AB20: =AA20*(1+AB11/100) -> 473.35525 | AC20: =AB20*(1+AC11/100) -> 515.01051 | AD20: 549.51621 | AE20: 581.38815
A21: pGOLDWt | B21: Мировые цены на золото, долл./унция | C21: Worldwide gold prices , USD/onz | Q21: 1225 | R21: 1570 | S21: 1670 | T21: 1410 | U21: 1275 | V21: 1167.7 | W21: 1258.5 | X21: 1257.1 | Y21: 1269.1 | Z21: 1411.15 | AA21: 1786.6 | AB21: 1794.25 | AC21: 1809.45 | AD21: 1943 | AE21: 2388.11
B22: Предпосылки производственного блока | C22: Production block assumptions
B24: Пищевая промышленность | C24: Food industry
A25: INDDA, t /RETt | B25: доля пищевой промышленности к розничному товарооброту | C25: food industry ouput / retail sales | J25: 0.34399916 | K25: 0.33410883 | L25: 0.37588879 | M25: 0.33616739 | N25: 0.33678105 | O25: 0.26883231 | P25: 0.24411747 | Q25: 0.50138176 | R25: 0.32886674 | S25: 0.36809816 | T25: 2.7353816 | U25: 0.25468071 | V25: =Industry!V65 -> 0.2421806 | W25: =Industry!W65 -> 0.22824695 | X25: =Industry!X65 -> 0.23346641 | Y25: =Industry!Y65 -> 0.23926132 | Z25: =Industry!Z65 -> 0.21640753 | AA25: =Industry!AA65 -> 0.26231461 | AB25: =Industry!AB65 -> 0.22874667 | AC25: =Industry!AC65 -> 0.25511416 | ... AE25: =Industry!AE65 -> 0.20562492
B26: Прочая промышленность | C26: Other industrial production
A27: INDDther, t /DDIND, t | B27: доля прочей в промышленности | C27: other industry / domestic final demand industries | Q27: -0.23084661 | R27: 0.22830795 | S27: 0.18457947 | T27: 0.18642913 | U27: 0.26606517 | V27: =Industry!V66 -> 0.29392051 | W27: =Industry!W66 -> 0.32363118 | X27: =Industry!X66 -> 0.32141142 | Y27: =Industry!Y66 -> 0.34006179 | Z27: =Industry!Z66 -> 0.35311481 | AA27: =Industry!AA66 -> 0.30576747 | AB27: =Industry!AB66 -> 0.30686263 | AC27: =Industry!AC66 -> 0.29457891 | ... AE27: =Industry!AE66 -> 0.31572529
B28: Электроэнергетика | C28: Power generation
A29: qCHHEl,t | B29: Потребление населением, млн. Квт*ч | C29: Household consumption of energy, mln. kWt*h | I29: 2900 | J29: 2700 | K29: 2600 | L29: 2700 | M29: 2600 | N29: 2400 | O29: 2400 | P29: 2700 | Q29: 3031 | R29: 3046 | S29: 3061 | T29: 4503 | U29: 4692 | V29: =Industry!V80 -> 4914 | W29: =Industry!W80 -> 4845 | X29: =Industry!X80 -> 5424 | Y29: =Industry!Y80 -> 5579 | Z29: =Industry!Z80 -> 6019 | AA29: =Industry!AA80 -> 6857 | AB29: =Industry!AB80 -> 5410 | AC29: =Industry!AC80 -> 5518.2 | ... AE29: =Industry!AE80 -> 5741.1353
A30: qLYEl,t | B30: потери к выпуску | C30: Losses/consumption ratio | I30: 0.13024225 | J30: 0.13586314 | K30: 0.13028503 | L30: 0.14568026 | M30: 0.14424896 | N30: 0.15472449 | O30: 0.15256056 | P30: 0.10483992 | Q30: 0.16028066 | R30: 0.16061956 | S30: 0.16697398 | T30: 0.17192601 | U30: 0.20437318 | V30: =Industry!V83 -> 0.18344212 | W30: =Industry!W83 -> 0.188224 | X30: =Industry!X83 -> 0.18763826 | Y30: =Industry!Y83 -> 0.16518395 | Z30: =Industry!Z83 -> 0.1310918 | AA30: =Industry!AA83 -> 0.14482132 | AB30: =Industry!AB83 -> 0.29484933 | AC30: =Industry!AC83 -> 0.27303698 | ... AE30: =Industry!AE83 -> 0.34714126
A31: qCAPEl,t | B31: Мощность, тыс. кВт | C31: Production capacity, thousands kWt | J31: 4420 | K31: 4396 | L31: 4404 | M31: 4389 | N31: 4386 | O31: 5069 | P31: 5078 | Q31: 5105 | R31: 5079 | S31: 6168 | T31: 6180 | U31: 6280 | V31: =Industry!V93 -> 6283 | W31: =Industry!W93 -> 6577 | X31: =Industry!X93 -> 5718 | Y31: =Industry!Y93 -> 6197 | Z31: =Industry!Z93 -> 6475 | AA31: =Industry!AA93 -> 6356 | AB31: =Industry!AB93 -> 6476 | AC31: =Industry!AC93 -> 6488.952 | ... AE31: =Industry!AE93 -> 6514.9338
A32: PUREl,t | B32: использование потенциала, % от потенциала | C32: export utlization rate. % potential | O32: 0 | P32: 0 | Q32: 0 | R32: 0 | S32: 0.24 | T32: 0.3 | U32: 0.15 | V32: 0.15 | W32: 0.2 | X32: 0.22 | Y32: 0.22 | Z32: 0.23 | AA32: 0.23 | AB32: 0.23 | AC32: 0.23 | AD32: 0.23 | AE32: 0.24
A33: pEXUSEl,t | B33: Электричество, USD/кВт-ч | C33: Electricity, USD/kWt-hour | G33: 0.046460639 | H33: 0.019408945 | I33: 0.017596132 | J33: 0.011994453 | K33: 0.012936419 | L33: 0.012342939 | M33: 0.011584184 | N33: 0.013998356 | O33: 0.01400966 | P33: 0.014947626 | Q33: 0.012097969 | R33: 0.014373737 | S33: 0.027529032 | T33: 0.031355325 | U33: 0.032331378 | V33: =Trade!V28 -> 0.034670487 | W33: =Trade!W28 -> 0.036204482 | X33: =Trade!X28 -> 0.037649543 | Y33: =Trade!Y28 -> 0.019151104 | Z33: =Trade!Z28 -> 0.029322835 | AA33: =Trade!AA28 -> 0.03015559 | AB33: =Trade!AB28 -> 0.029056198 | AC33: =Trade!AC28 -> 0.03178689 | ... AE33: =Trade!AE28 -> 0.028961735
A35: efDIEl,t | B35: энергоемкость выпуска алюминия | C35: power consumption/aluminum output ratio | J35: 54.6 | K35: 52.685512 | L35: 50.398355 | M35: 58.257297 | N35: 51.310706 | O35: 58.699896 | P35: 64.148663 | Q35: 64.148663 | R35: 64.148663 | S35: 52 | T35: 52 | U35: 52 | V35: 48 | W35: =V35 -> 48 | X35: =W35 -> 48 | Y35: =X35 -> 48 | Z35: =Y35 -> 48 | AA35: =Z35 -> 48 | AB35: =AA35 -> 48 | AC35: =AB35 -> 48 | AD35: =AC35 -> 48 | AE35: =AD35 -> 48
A36: efDBCEl,t | B36: энергоемкость выпуска в легкой промышленности | C36: power consumption/light industry output ratio | J36: 0.38 | K36: 0.30035336 | L36: 0.41051292 | M36: 0.29270697 | N36: 0.40319822 | O36: 0.32992102 | P36: 0.20490213 | Q36: 0.20490213 | R36: 0.20490213 | S36: 0.20490213 | T36: 0.20490213 | U36: 0.20490213 | V36: =Industry!V118 -> 0.20490213 | W36: =Industry!W118 -> 0.20490213 | X36: =Industry!X118 -> 0.20490213 | Y36: =Industry!Y118 -> 0.20490213 | Z36: =Industry!Z118 -> 0.20490213 | AA36: =Industry!AA118 -> 0.20490213 | AB36: =Industry!AB118 -> 0.20490213 | AC36: =Industry!AC118 -> 0.20490213 | ... AE36: =Industry!AE118 -> 0.20490213
A37: efDAEl,t | B37: энергоемкость выпуска в пищевой промышленности | C37: power consumption/food industry output ratio | J37: 0.63 | K37: 0.54560955 | L37: 0.31696914 | M37: 0.11714935 | N37: 0.10141045 | O37: 0.17826055 | P37: 0.12064479 | Q37: 0.12 | R37: 0.12 | S37: 0.12 | T37: 0.12 | U37: 0.12 | V37: 0.12 | W37: =V37 -> 0.12 | X37: =W37 -> 0.12 | Y37: =X37 -> 0.12 | Z37: =Y37 -> 0.12 | AA37: =Z37 -> 0.12 | AB37: =AA37 -> 0.12 | AC37: =AB37 -> 0.12 | AD37: =AC37 -> 0.12 | AE37: =AD37 -> 0.12
A38: efOthEl,t | B38: энергоемкость выпуска прочих секторов | C38: power consumption/other insdustries output ratio | J38: 3.07 | K38: 1.9476767 | L38: 2.9047077 | M38: 0.61801458 | N38: 1.5697016 | O38: 1.7584717 | P38: 0.76064584 | Q38: 0.76064584 | R38: 0.76064584 | S38: 0.76064584 | T38: 0.76064584 | U38: 0.76064584 | V38: 0.76064584 | W38: =V38 -> 0.76064584 | X38: =W38 -> 0.76064584 | Y38: =X38 -> 0.76064584 | Z38: =Y38 -> 0.76064584 | AA38: =Z38 -> 0.76064584 | AB38: =AA38 -> 0.76064584 | AC38: =AB38 -> 0.76064584 | AD38: =AC38 -> 0.76064584 | AE38: =AD38 -> 0.76064584
A39: efABEl,t | B39: энергоемкость выпуска с/х | C39: power consumption/agriculture output ratio | K39: 43.09 | L39: 38.648915 | M39: 36.565877 | N39: 31.733616 | O39: 25.623332 | P39: 27.451568 | Q39: 27.451568 | R39: 27.451568 | S39: 26.63 | T39: 26.63 | U39: 25 | V39: 25 | W39: 25 | X39: 26 | Y39: 27 | Z39: 28 | AA39: 29 | AB39: 30 | AC39: 31 | AD39: 32 | AE39: 33
A40: PHHEl, t | B40: Цены на электроэнергию для населения, дирам/кВт*ч | C40: Elecricity prices for households, .01 somoni/kWt | P40: 7.5 | Q40: 9 | R40: 10.96875 | S40: 10.96875 | T40: 10.96875 | U40: 11.517188 | V40: 12.093047 | W40: =V40*1.05 -> 12.697699 | X40: =W40*1.05 -> 13.332584 | Y40: =X40*1.05 -> 13.999213 | Z40: =Y40*1.05 -> 14.699174 | AA40: =Z40*1.05 -> 15.434133 | AB40: =AA40*1.05 -> 16.205839 | AC40: =AB40*1.05 -> 17.016131 | AD40: =AC40*1.05 -> 17.866938 | AE40: =AD40*1.05 -> 18.760285
B41: Производства алюминия | C41: Aluminum production
B42: Производство алюминия тонн | C42: Aluminiun production, ton | M42: 439.82167 | N42: 419.15005 | O42: 399.45 | P42: 357.78974 | Q42: 348.845 | R42: 278.4 | S42: 272.5 | T42: 216.4 | U42: 125.7 | V42: 139.1 | W42: 129.3 | X42: 103.1 | Y42: 95.8 | Z42: 100.8 | AA42: 84 | AB42: 60.5 | AC42: 62 | AD42: 66.6 | AE42: 82.2
A43: efAlAm,t | B43: Норма потребления глинозема в производстве | C43: Alumina consumption per ton of aluminium | M43: 1.9094014 | N43: 1.9965554 | O43: 2.0456312 | P43: 1.798345 | Q43: 2.0301767 | R43: 1.9040948 | S43: 1.7431193 | T43: 1.7985213 | U43: 1.9984089 | V43: =Industry!V161 -> 1.8483106 | W43: =Industry!W161 -> 2.0216551 | X43: =Industry!X161 -> 1.9903007 | Y43: =Industry!Y161 -> 1.6670146 | Z43: =Industry!Z161 -> 1.9573413 | AA43: =Industry!AA161 -> 2.0380952 | AB43: =Industry!AB161 -> 1.7322314 | AC43: =Industry!AC161 -> 1.7748387 | ... AE43: =Industry!AE161 -> 1.9452555
B44: Добыча глинозема в РТ, тыс. тонн. | Q44: 0 | R44: 0 | S44: 0 | T44: 0 | U44: 0 | V44: =Industry!V148 -> 0 | W44: =Industry!W148 -> 0 | X44: =Industry!X148 -> 0 | Y44: =Industry!Y148 -> 0 | Z44: =Industry!Z148 -> 0 | AA44: =Industry!AA148 -> 0 | AB44: =Industry!AB148 -> 0 | AC44: =Industry!AC148 -> 0 | ... AE44: =Industry!AE148 -> 0
B45: Справочно: степень переработки, % | Q45: 1.969849 | R45: 3.7714788 | S45: 2.6290192 | T45: 2.6290192 | U45: 2.6290192 | V45: =Industry!V155 -> 2.6290192 | W45: =Industry!W155 -> 2.6290192 | X45: =Industry!X155 -> 2.6290192 | Y45: =Industry!Y155 -> 2.6290192 | Z45: =Industry!Z155 -> 2.6290192 | AA45: =Industry!AA155 -> 2.6290192 | AB45: =Industry!AB155 -> 2.6290192 | AC45: =Industry!AC155 -> 2.6290192 | ... AE45: =Industry!AE155 -> 2.6290192
B46: Производства хлопка | C46: Cotton production
B47: Урожай хлопка, тыс. тонн | Q47: 310.67961 | R47: 416 | S47: 418.1 | T47: 392.811 | U47: 372.65 | V47: 276.1 | W47: 284.7 | X47: 385.6 | Y47: 300.3 | Z47: 403 | AA47: 395.7 | AB47: 388.8 | AC47: 404.7 | AD47: 344.4 | AE47: 253.2
B48: Доля переработки, % | Q48: 10.348346 | R48: 48.842407 | S48: -1.1922985 | T48: 14.268005 | U48: 31.807957 | V48: =Industry!V201 -> -14.834779 | W48: =Industry!W201 -> 9.7398707 | X48: =Industry!X201 -> 42.10703 | Y48: =Industry!Y201 -> 8.9146148 | Z48: =Industry!Z201 -> 31.323894 | AA48: =Industry!AA201 -> 25.597229 | AB48: =Industry!AB201 -> 26.072898 | AC48: =Industry!AC201 -> 42.814783 | ... AE48: =Industry!AE201 -> -13.432408
B49: Доля внутреннего потребления в переработке, % | Q49: 56.811173 | R49: 92.297927 | S49: 92.297927 | T49: 92.297927 | U49: 92.297927 | V49: =Industry!V202 -> 92.297927 | W49: =Industry!W202 -> 85 | X49: =Industry!X202 -> 85 | Y49: =Industry!Y202 -> 85 | Z49: =Industry!Z202 -> 95 | AA49: =Industry!AA202 -> 95 | AB49: =Industry!AB202 -> 95 | AC49: =Industry!AC202 -> 86 | ... AE49: =Industry!AE202 -> 86
A50: gINDC13,t | B50: Темп роста добычи драгметаллов | V50: 120 | W50: =V50 -> 120 | X50: =W50 -> 120 | Y50: =X50 -> 120 | Z50: =Y50 -> 120 | AA50: =Z50 -> 120 | AB50: =AA50 -> 120 | AC50: =AB50 -> 120 | AD50: =AC50 -> 120 | AE50: =AD50 -> 120
B51: Домохозяйства | C51: Household
A52: TrNATG,t | B52: Социальные трансферты в натуральной форме, млн. сомони | C52: Social transferts in natural form, mil. TJS | L52: 768.1 | M52: 662.5 | N52: 904 | O52: 1088.8 | P52: 2242.2 | Q52: 2267.4 | R52: 2898.8 | S52: 3838.8 | T52: 4525.3 | U52: 5399.5 | V52: =Household!V40 -> 4055.1 | W52: =Household!W40 -> 4817.9 | X52: =Household!X40 -> 5466.7 | Y52: =Household!Y40 -> 5744 | Z52: =Household!Z40 -> 6433.2 | AA52: =Household!AA40 -> 7283.3 | AB52: =Household!AB40 -> 8932.6 | AC52: =Household!AC40 -> 10146.4 | AD52: =Household!AD40 -> 10448.9 | AE52: =AD52*1.15 -> 12016.235
A53: WG,t | B53: Зарплата в секторе "Государство и НКО", млн. сомони | C53: Wage in "Government and non-commercial organization" sector, mln. TJS | L53: 260.6 | M53: 365.7 | N53: 526.5 | O53: 652 | P53: 919.3 | Q53: 1138.2 | R53: 1328.9 | S53: 1744.4 | T53: 2401.2 | U53: 3177.3 | V53: =Household!V34 -> 3403.7 | W53: =Household!W34 -> 3915.2 | X53: =Household!X34 -> 4496.9 | Y53: =Household!Y34 -> 4923.9 | Z53: =Household!Z34 -> 4980.3 | AA53: =Household!AA34 -> 5417.4 | AB53: =Household!AB34 -> 6169.5 | AC53: =Household!AC34 -> 7053.8 | AD53: =Household!AD34 -> 10667.5 | AE53: =AD53*1.051 -> 11211.542
A54: mpcCDIt | B54: - склонность к потреблению (полному доходу) | C54: mpc to total income | L54: 0.53987118 | M54: 0.50037001 | N54: 0.51621082 | O54: 0.48912018 | P54: 0.4933523 | Q54: 0.43829084 | R54: 0.52143209 | S54: 0.49344908 | T54: 0.24164972 | U54: 0.4763645 | V54: =Household!V50 -> 0.58012318 | W54: =Household!W50 -> 0.57395593 | X54: =Household!X50 -> 0.52718849 | Y54: =Household!Y50 -> 0.58098417 | Z54: =Household!Z50 -> 0.61640586 | AA54: =Household!AA50 -> 0.53955207 | AB54: =Household!AB50 -> 0.53486418 | AC54: =Household!AC50 -> 0.49758957 | AD54: =Household!AD50 -> 0.59685455 | AE54: =AD54 -> 0.59685455
B55: Сельское хозяйство | C55: Agriculture
A56: gVAAB,t | B56: Темп роста сельское хозяйства и рыболовства, % | C56: Agriculture, real growth, % | L56: 1.4 | M56: 5.7 | N56: 3.5 | O56: 6.1 | P56: 10.5 | Q56: 6.8 | R56: 7.9 | S56: 10.4 | T56: 7.6 | U56: 4.5 | V56: =GDP!V33-100 -> 3.2 | W56: =GDP!W33-100 -> 5.2 | X56: =GDP!X33-100 -> 6.8 | Y56: =GDP!Y33-100 -> 7 | Z56: =GDP!Z33-100 -> 7 | AA56: =GDP!AA33-100 -> 7.9 | AB56: =GDP!AB33-100 -> -0.3 | AC56: =GDP!AC33-100 -> 8 | ... AE56: =GDP!AE33-100 -> 10.6
A57: defVAAB,t | B57: Дефлятор сельское хозяйства и рыболовства, % | C57: Agriculture, deflator, % | L57: 27.03394 | M57: 24.057581 | N57: 20.051662 | O57: 33.249432 | P57: -1.550686 | Q57: -0.00061758249 | R57: 46.578803 | S57: 0.4845505 | T57: -5.4890103 | U57: 20.052103 | V57: =Agriculture!V4-100 -> -0.53838649 | W57: =Agriculture!W4-100 -> 0.91553984 | X57: =Agriculture!X4-100 -> 0.45209406 | Y57: =Agriculture!Y4-100 -> 0.28133214 | Z57: =Agriculture!Z4-100 -> -1.6508979 | AA57: =Agriculture!AA4-100 -> 24.565997 | AB57: =Agriculture!AB4-100 -> 6.9457864 | AC57: =Agriculture!AC4-100 -> 14.71783 | ... AE57: =Agriculture!AE4-100 -> 6.128139
A58: qEXFV,t | B58: Экспорт Фрукты и овощи, тонн | C58: Export Fruit and vegetables, tn | P58: 194 | Q58: 257 | R58: 89.686 | S58: 103.324 | T58: 227 | U58: 179.3 | V58: =Trade!V18 -> 220.4 | W58: =Trade!W18 -> 170.4 | X58: =Trade!X18 -> 118.6 | Y58: =Trade!Y18 -> 136.9 | Z58: =Trade!Z18 -> 118.4 | AA58: =Trade!AA18 -> 129 | AB58: =Trade!AB18 -> 208 | AC58: =Trade!AC18 -> 189.3 | ... AE58: =Trade!AE18 -> 165.3
B59: ВВП по производству | C59: GDP by production
A60: gVAOther,t | B60: ВДС прочих отраслей (J-0), growth, % | C60: Value Added growth of J-O activities, growth, % | L60: 97.001641 | M60: 96.376863 | N60: 78.00434 | O60: 92.627551 | P60: 73.250437 | Q60: 93 | R60: 97 | S60: 95 | T60: 95 | U60: 102 | V60: 100 | W60: 100 | X60: 100 | Y60: 100 | Z60: 100 | AA60: 100 | AB60: 100 | AC60: 100 | AD60: 100 | AE60: 100
B61: CPI
A62: dCPIAVServices,t | B62: Services, % | C62: платные услуги, % | G62: 128.1 | H62: 127 | I62: 114.8 | J62: 140.8 | K62: 117.3 | L62: 109.8 | M62: 118.6 | N62: 127.1 | O62: 120.5 | P62: 114.5 | Q62: 110 | R62: 110.7 | S62: 110 | T62: 110 | U62: 104 | V62: 110 | W62: 110 | X62: 110 | Y62: 110 | Z62: 110 | AA62: 110 | AB62: 110 | AC62: 110 | AD62: 110 | AE62: 110
A63: POPt | B63: Население (млн.) | C63: Population (million) | P63: 7.417 | Q63: 7.621 | R63: 7.714 | S63: 7.89 | T63: 8.161 | U63: 8.352 | V63: 8.451 | W63: 8.647 | X63: 8.837 | Y63: 9.029 | Z63: 9.22 | AA63: 9.41 | AB63: 9.801 | AC63: 10.01 | AD63: 10.183 | AE63: 10.382
A64: Госбюджет
A65: sInvGt | B65: Доля гос. инвестиций в доходах бюджета, % | C65: Government investments to total revenue (invetment survey), % | G65: 18.971635 | H65: 26.401909 | I65: 21.158691 | J65: 22.258092 | K65: 32.887223 | L65: 23.107391 | M65: 23.853757 | N65: 22.688898 | O65: 29.321742 | P65: 31.588492 | Q65: 35.400636 | R65: 34.145617 | S65: 25.941614 | T65: 25.820047 | U65: 27.061193 | V65: =OEA!V23/'Revenue Model'!V15*100 -> 28.465696 | W65: =OEA!W23/'Revenue Model'!W15*100 -> 34.819332 | X65: =OEA!X23/'Revenue Model'!X15*100 -> 34.517742 | Y65: =OEA!Y23/'Revenue Model'!Y15*100 -> 39.006019 | Z65: =OEA!Z23/'Revenue Model'!Z15*100 -> 35.174749 | AA65: =OEA!AA23/'Revenue Model'!AA15*100 -> 32.944756 | AB65: =OEA!AB23/'Revenue Model'!AB15*100 -> 28.719221 | AC65: =OEA!AC23/'Revenue Model'!AC15*100 -> 27.7988 | ... AE65: =OEA!AE23/'Revenue Model'!AE15*100 -> 30.005532
B67: Реальные темпы роста добыча энергетических материалов | R67: 113.5 | S67: 126.9 | T67: 250 | U67: 68.3 | V67: 90 | W67: 100 | X67: 102 | Y67: 104 | Z67: 106 | AA67: 108 | AB67: 108 | AC67: 109 | AD67: 110 | AE67: 111

Sheet Trade
B1: Var. Name | C1: Наименование индикатора | D1: 1997 | E1: 1998 | F1: 1999 | G1: 2000 | H1: 2001 | I1: 2002 | J1: 2003 | K1: 2004 | L1: 2005 | M1: 2006 | N1: 2007 | O1: 2008 | P1: 2009 | Q1: 2010 | R1: 2011 | S1: 2012 | T1: 2013 | U1: 2014 | V1: 2015 | W1: 2016 | X1: 2017 | Y1: 2018 | Z1: 2019 | AA1: 2020 | AB1: 2021 | AC1: 2022 | AD1: 2023 | AE1: 2024
C2: Экспорт | W2: =W3-V3 -> -12.5 | X2: =X3-W3 -> 319.5 | Y2: =Y3-X3 -> -134.5 | Z2: =Z3-Y3 -> 101.25 | AA2: =AA3-Z3 -> 128.65 | AB2: =AB3-AA3 -> 751 | AC2: =AC3-AB3 -> -17 | AD2: =AD3-AC3 -> 412.9 | AE2: =AE3-AD3 -> -583.895
B3: EXUSt | C3: Экспорт ТОВАРОВ И УСЛУГ (млн. долл.) | G3: 901.5265 | H3: 713.7707 | I3: 768.1372 | J3: 994.7247 | K3: 1219.8417 | L3: 1254.4346 | M3: 1589.6258 | N3: 1705.5683 | O3: 1686.309 | P3: 600.148 | Q3: 791.24733 | R3: 1821.8 | S3: 1847.3 | T3: 1306.77 | U3: 1229.7 | V3: =V4+V5 -> 1143 | W3: =W4+W5 -> 1130.5 | X3: =X4+X5 -> 1450 | Y3: =Y4+Y5 -> 1315.5 | Z3: =Z4+Z5 -> 1416.75 | AA3: =AA4+AA5 -> 1545.4 | AB3: =AB4+AB5 -> 2296.4 | AC3: =AC4+AC5 -> 2279.4 | ... AE3: =AE4+AE5 -> 2108.405 | AH3: EXUSt = EXUSGoods,t+EXUSServ,t
B4: EXUSServ,t | C4: Экспорт услуг, млн.долл. | G4: 62.6 | H4: 62.2 | I4: 68.9892 | J4: 88.5265 | K4: 122.907 | L4: 146.342 | M4: 134.215 | N4: 148.692 | O4: 181.409 | P4: 179.748 | Q4: 333.74733 | R4: 564.5 | S4: 487.6 | T4: 363.37 | U4: 252.4 | V4: =BoP!V10 -> 252.4 | W4: =BoP!W10 -> 231.8 | X4: =BoP!X10 -> 252 | Y4: =BoP!Y10 -> 242.2 | Z4: =BoP!Z10 -> 242.35 | AA4: =BoP!AA10 -> 138.5 | AB4: =BoP!AB10 -> 146.8 | AC4: =BoP!AC10 -> 137.4 | ... AE4: =BoP!AE10 -> 161.005 | AH4: EXUSServ,t = EXUSServ,t-1·(0,0701742196128·EXUSGoods,t+ 0,0271620953584·IMUSGoods,t-1)/(0,0701742196128·EXUSGoods,t-1+ 0,0271620953584·IMUSGoods,t-2)
B5: EXUSGoods,t | C5: Экспорт товаров ФОБ, млн.долл. | G5: 838.9265 | H5: 651.5707 | I5: 699.148 | J5: 906.1982 | K5: 1096.9347 | L5: 1108.0926 | M5: 1455.4108 | N5: 1556.8763 | O5: 1504.9 | P5: 420.4 | Q5: 457.5 | R5: 1257.3 | S5: 1359.7 | T5: 943.4 | U5: 977.3 | V5: 890.6 | W5: 898.7 | X5: 1198 | Y5: 1073.3 | Z5: 1174.4 | AA5: 1406.9 | AB5: 2149.6 | AC5: 2142 | AD5: 2448.8 | AE5: 1947.4 | AH5: EXUSGoods,t = (EXUSAl,t+EXUSCot,t+EXUSFV,t+EXUSEl,t+EXUSoG,t)
B6: EXUSAl,t | C6: Алюминий первичный | G6: 433.5553 | H6: 398.3971 | I6: 398.5552 | J6: 429.5538 | K6: 563.3544 | L6: 563.016 | M6: 1049.5102 | N6: 1082.9825 | O6: 1012.9916 | P6: 589.4625 | Q6: 735.5 | R6: 664.6 | S6: 535.509 | T6: 369.5 | U6: 234.2 | V6: 216.2 | W6: 207.5 | X6: 200.7 | Y6: 199.3 | Z6: 173.2 | AA6: 136.2 | AB6: 135.1 | AC6: 139.9 | AD6: 132.3 | AE6: 183.6 | AH6: EXUSAl,t = qEXAl,t·pEXUSAl,t/1000000
C7: Готовые изделия из алюминия, включая отходы | Q7: 15.898 | R7: 16.799526 | S7: 10.488357 | T7: 3.2376873 | U7: 3.6650381 | V7: =Industry!V158+Industry!V159 -> 7.5795306 | W7: =Industry!W158+Industry!W159 -> 7.7895417 | X7: =Industry!X158+Industry!X159 -> 8.3729339 | Y7: =Industry!Y158+Industry!Y159 -> 8.2618057 | Z7: =Industry!Z158+Industry!Z159 -> 7.3984982 | AA7: =Industry!AA158+Industry!AA159 -> 5.3944559 | AB7: =Industry!AB158+Industry!AB159 -> 6.0304045 | AC7: =Industry!AC158+Industry!AC159 -> 6.2975477 | ... AE7: =Industry!AE158+Industry!AE159 -> 7.3690754
B8: EXUSCot,t | C8: Хлопок-волокно | G8: 91.8286 | H8: 71.5002 | I8: 127.9714 | J8: 192.7419 | K8: 161.5973 | L8: 143.912 | M8: 128.6668 | N8: 137.8451 | O8: 108.2178 | P8: 99.6828 | Q8: 201.1 | R8: 197.3 | S8: 223.865 | T8: 189.166 | U8: 132.1 | V8: 144.5 | W8: 122.6 | X8: 121 | Y8: 165.3 | Z8: 139.6 | AA8: 136 | AB8: 202.6 | AC8: 194.7 | AD8: 198.6 | AE8: 170.1 | AH8: EXUSCot,t = qEXCot,t·pEXUSCot,t/1000000
B9: EXUSFV,t | C9: Фрукты и овощи | P9: 52.4 | Q9: 56.797 | R9: 32.993 | S9: 33.575 | T9: 48.5 | U9: 36.6 | V9: 32.1 | W9: 21.8112 | X9: 17.3 | Y9: 16.3 | Z9: 18.2 | AA9: 19.5 | AB9: 36 | AC9: 51.5 | AD9: 46.3 | AE9: 50.3 | AH9: EXUSFV,t = qEXFV,t·pEXUSFV,t/1000
B10: EXUSEl,t | C10: Электричество | G10: 181.6007 | H10: 78.548 | I10: 67.4143 | J10: 55.1409 | K10: 57.58 | L10: 52.555 | M10: 49.015 | N10: 59.619 | O10: 59.7484 | P10: 63.1881 | Q10: 3.4600192 | R10: 4.269 | S10: 21.335 | T10: 33.268 | U10: 44.1 | V10: 48.4 | W10: 51.7 | X10: 53.5 | Y10: 56.4 | Z10: 93.1 | AA10: 56.4 | AB10: 95.961 | AC10: 106.2 | AD10: 110.4 | AE10: 113 | AH10: EXUSEl,t = qEXEl,t·pEXUSEl,t
B11: EXUSoG,t | C11: Прочие товары (вкл. неорг.торг.) | G11: 131.9419 | H11: 103.1254 | I11: 105.2071 | J11: 228.7616 | K11: 314.403 | L11: 348.6096 | M11: 228.2188 | N11: 276.4297 | O11: 323.9422 | P11: -384.3334 | Q11: -555.25502 | R11: 341.33847 | S11: 534.92764 | T11: 299.72831 | U11: 526.63496 | V11: =V5-SUM(V6:V10) -> 441.82047 | W11: =W5-SUM(W6:W10) -> 487.29926 | X11: =X5-SUM(X6:X10) -> 797.12707 | Y11: =Y5-SUM(Y6:Y10) -> 627.73819 | Z11: =Z5-SUM(Z6:Z10) -> 742.9015 | AA11: =AA5-SUM(AA6:AA10) -> 1053.4055 | AB11: =AB5-SUM(AB6:AB10) -> 1673.9086 | AC11: =AC5-SUM(AC6:AC10) -> 1643.4025 | ... AE11: =AE5-SUM(AE6:AE10) -> 1423.0309 | AH11: EXUSoG,t = EXUSoG,t-1·(gGDPDEt/100+1)·(1+dCPIWt/100)
V12: 91.12862 | W12: =W5/V5*100 -> 100.9095 | X12: =X5/W5*100 -> 133.30366 | Y12: =Y5/X5*100 -> 89.590985 | Z12: =Z5/Y5*100 -> 109.41955 | AA12: =AA5/Z5*100 -> 119.79734 | AB12: =AB5/AA5*100 -> 152.78982 | AC12: =AC5/AB5*100 -> 99.646446 | AD12: =AD5/AC5*100 -> 114.32306 | AE12: =AE5/AD5*100 -> 79.524665
M13: 2.0539847 | N13: 2.0353672 | O13: 2.0770625 | P13: 1.845271 | W13: =W5-V5 -> 8.1 | X13: =X5-W5 -> 299.3 | Y13: =Y5-X5 -> -124.7 | Z13: =Z5-Y5 -> 101.1 | AA13: =AA5-Z5 -> 232.5 | AB13: =AB5-AA5 -> 742.7 | AC13: =AC5-AB5 -> -7.6 | AD13: =AD5-AC5 -> 306.8 | AE13: =AE5-AD5 -> -501.4
C14: Экспорт товаров в физическом выражении | M14: 839796.1 | N14: 836856.3 | O14: 817127.4 | P14: 643429.4
B15: qEXAl,t | C15: Алюминий первичный, тонн | G15: 273541.2 | H15: 286993.8 | I15: 305430 | J15: 316676.1 | K15: 342633.8 | L15: 375281 | M15: 408861.9 | N15: 411157.4 | O15: 393405.3 | P15: 348691 | Q15: 339385.79 | R15: 277.65 | S15: 264798.9 | T15: 200200 | U15: 125700 | V15: 130900 | W15: 129700 | X15: 101400 | Y15: 94800 | Z15: 96800 | AA15: 87000 | AB15: 55600 | AC15: 56500 | AD15: 59100 | AE15: 76100 | AH15: qEXAl,t = qEXAl,t-1·EXP(0,057291+3,96444·LN((gGDPDEt+100)/(gGDPDEt-1+100)))
C16: Готовые изделия из алюминия, включая отходы | Q16: 10839 | R16: 14653.53 | S16: 11278.052 | T16: 8956.2219 | U16: 5202.3895 | V16: =(Industry!V153+Industry!V154)*1000 -> 5756.9799 | W16: =(Industry!W153+Industry!W154)*1000 -> 5351.3839 | X16: =(Industry!X153+Industry!X154)*1000 -> 4267.0355 | Y16: =(Industry!Y153+Industry!Y154)*1000 -> 3964.9078 | Z16: =(Industry!Z153+Industry!Z154)*1000 -> 4171.8446 | AA16: =(Industry!AA153+Industry!AA154)*1000 -> 3476.5371 | AB16: =(Industry!AB153+Industry!AB154)*1000 -> 2503.9345 | AC16: =(Industry!AC153+Industry!AC154)*1000 -> 2566.0155 | ... AE16: =(Industry!AE153+Industry!AE154)*1000 -> 3402.0399
B17: qEXCot,t | C17: Хлопок-волокно, тонн | G17: 78795.7 | H17: 75382.8 | I17: 140744.9 | J17: 149262.7 | K17: 133072.7 | L17: 132874 | M17: 120404.7 | N17: 119965.3 | O17: 83591.8 | P17: 86648.2 | Q17: 94700 | R17: 72357.3 | S17: 143848.9 | T17: 114500 | U17: 86400 | V17: =Industry!V182 -> 107800 | W17: =Industry!W182 -> 87370 | X17: =Industry!X182 -> 75900 | Y17: =Industry!Y182 -> 93000 | Z17: =Industry!Z182 -> 94100 | AA17: =Industry!AA182 -> 100100 | AB17: =Industry!AB182 -> 100600 | AC17: =Industry!AC182 -> 81000 | ... AE17: =Industry!AE182 -> 100523.8 | AH17: qEXCot,t = qEXCot,t
B18: qEXFV,t | C18: Фрукты и овощи, тонн | P18: 194 | Q18: 257 | R18: 89.686 | S18: 103.324 | T18: 227 | U18: 179.3 | V18: 220.4 | W18: 170.4 | X18: 118.6 | Y18: 136.9 | Z18: 118.4 | AA18: 129 | AB18: 208 | AC18: 189.3 | AD18: 177.1 | AE18: 165.3 | AH18: qEXFV,t = qEXFV,t
B19: qEXEl,t | C19: Электричество, млн. кВт-часов | G19: 3908.7 | H19: 4047 | I19: 3831.2 | J19: 4597.2 | K19: 4451 | L19: 4257.9 | M19: 4231.2 | N19: 4464 | O19: 5539 | P19: 5960 | Q19: 286 | R19: 297 | S19: 775 | T19: 1061 | U19: 1364 | V19: 1396 | W19: 1428 | X19: 1421 | Y19: 2945 | Z19: 3175 | AA19: 1870.3 | AB19: 3302.6 | AC19: 3341 | AD19: 3606.6 | AE19: 3901.7 | AH19: qEXEl,t = qEXEl,t
B20: idxqEX2003oG,t | C20: Имплицитный индекс объемов прочего экспорта товаров и услуг, 2003=100 | H20: 72.710054 | I20: 62.437624 | J20: 100 | K20: 156.47845 | L20: 138.73316 | M20: 279.94878 | N20: 594.05761 | O20: 303.99212 | P20: 712.05337 | Q20: 587.95219 | R20: 319.2751 | S20: 268951.82 | T20: 199892.72 | U20: 211160.56 | V20: 217540.62 | W20: =(V3*W33-SUM(V6:V10)*W34)/(V3-SUM(V6:V10))*V20/100 -> 220633.46 | X20: =(W3*X33-SUM(W6:W10)*X34)/(W3-SUM(W6:W10))*W20/100 -> 251293.23 | Y20: =(X3*Y33-SUM(X6:X10)*Y34)/(X3-SUM(X6:X10))*X20/100 -> 240295.23 | Z20: =(Y3*Z33-SUM(Y6:Y10)*Z34)/(Y3-SUM(Y6:Y10))*Y20/100 -> 276297.69 | AA20: =(Z3*AA33-SUM(Z6:Z10)*AA34)/(Z3-SUM(Z6:Z10))*Z20/100 -> 360225.42 | AB20: =(AA3*AB33-SUM(AA6:AA10)*AB34)/(AA3-SUM(AA6:AA10))*AA20/100 -> 415732.31 | AC20: =(AB3*AC33-SUM(AB6:AB10)*AC34)/(AB3-SUM(AB6:AB10))*AB20/100 -> 362052.04 | AD20: =(AC3*AD33-SUM(AC6:AC10)*AD34)/(AC3-SUM(AC6:AC10))*AC20/100 -> 485457.02 | AE20: =(AD3*AE33-SUM(AD6:AD10)*AE34)/(AD3-SUM(AD6:AD10))*AD20/100 -> 385055.64 | AH20: idxqEX2003oG,t = (EXUSt-1·gEXt-(EXUSAl,t-1+EXUSCot,t-1+EXUSFV,t-1+EXUSEl,t-1)·gEXGoods,t)/(EXUSt-1-(EXUSAl,t-1+EXUSCot,t-1+EXUSFV,t-1+EXUSEl,t-1))·idxqEX2003oG,t-1/100
C23: Экспортные цены на товары
B24: pEXUSAl,t | C24: Алюминий первичный, USD/тонн | G24: 1584.9726 | H24: 1388.1732 | I24: 1304.8987 | J24: 1356.4453 | K24: 1644.1881 | L24: 1500.2518 | M24: 2566.9063 | N24: 2633.9852 | O24: 2574.9312 | P24: 1690.501 | Q24: 2167.1502 | R24: 2393661.1 | S24: 2022.3234 | T24: 1845.6543 | U24: 1863.1663 | V24: =V6/V15*1000000 -> 1651.6425 | W24: =W6/W15*1000000 -> 1599.8458 | X24: =X6/X15*1000000 -> 1979.2899 | Y24: =Y6/Y15*1000000 -> 2102.3207 | Z24: =Z6/Z15*1000000 -> 1789.2562 | AA24: =AA6/AA15*1000000 -> 1565.5172 | AB24: =AB6/AB15*1000000 -> 2429.8561 | AC24: =AC6/AC15*1000000 -> 2476.1062 | ... AE24: =AE6/AE15*1000000 -> 2412.615 | AH24: pEXUSAl,t = pEXUSAl,t-1·pALWt/pALWt-1
C25: Готовые изделия из алюминия, включая отходы | Q25: 1466.7405 | R25: 1146.4491 | S25: 929.97948 | T25: 361.50146 | U25: 704.49129 | V25: =V7/V16*1000000 -> 1316.581 | W25: =W7/W16*1000000 -> 1455.6126 | X25: =X7/X16*1000000 -> 1962.2368 | Y25: =Y7/Y16*1000000 -> 2083.7321 | Z25: =Z7/Z16*1000000 -> 1773.4357 | AA25: =AA7/AA16*1000000 -> 1551.6751 | AB25: =AB7/AB16*1000000 -> 2408.3715 | AC25: =AC7/AC16*1000000 -> 2454.2126 | ... AE25: =AE7/AE16*1000000 -> 2166.0755
B26: pEXUSCot,t | C26: Хлопок-волокно, USD/тонн | G26: 1165.4012 | H26: 948.49488 | I26: 909.2436 | J26: 1291.2931 | K26: 1214.3535 | L26: 1083.0712 | M26: 1068.6194 | N26: 1149.0414 | O26: 1294.5983 | P26: 1150.4313 | Q26: 2123.548 | R26: 2726.7463 | S26: 1556.251 | T26: 1652.1048 | U26: 1528.9352 | V26: =V8/V17*1000000 -> 1340.4453 | W26: =W8/W17*1000000 -> 1403.2277 | X26: =X8/X17*1000000 -> 1594.2029 | Y26: =Y8/Y17*1000000 -> 1777.4194 | Z26: =Z8/Z17*1000000 -> 1483.5282 | AA26: =AA8/AA17*1000000 -> 1358.6414 | AB26: =AB8/AB17*1000000 -> 2013.9165 | AC26: =AC8/AC17*1000000 -> 2403.7037 | ... AE26: =AE8/AE17*1000000 -> 1692.1366 | AH26: pEXUSCot,t = pEXUSCot,t-1·pALWt/pALWt-1
B27: pEXUSFV,t | C27: Фрукты и овощи, USD/тонн | P27: 270.10309 | Q27: 221 | R27: 367.87235 | S27: 324.94871 | T27: 213.65639 | U27: 204.12716 | V27: =V9/V18*1000 -> 145.64428 | W27: =W9/W18*1000 -> 128 | X27: =X9/X18*1000 -> 145.86847 | Y27: =Y9/Y18*1000 -> 119.06501 | Z27: =Z9/Z18*1000 -> 153.71622 | AA27: =AA9/AA18*1000 -> 151.16279 | AB27: =AB9/AB18*1000 -> 173.07692 | AC27: =AC9/AC18*1000 -> 272.05494 | ... AE27: =AE9/AE18*1000 -> 304.29522 | AH27: pEXUSFV,t = pEXUSFV,t-1·pFVRUBt/pFVRUBt-1
B28: pEXUSEl,t | C28: Электричество, USD/кВт-ч | G28: 0.046460639 | H28: 0.019408945 | I28: 0.017596132 | J28: 0.011994453 | K28: 0.012936419 | L28: 0.012342939 | M28: 0.011584184 | N28: 0.013998356 | O28: 0.01400966 | P28: 0.014947626 | Q28: 0.012097969 | R28: 0.014373737 | S28: 0.027529032 | T28: 0.031355325 | U28: 0.032331378 | V28: =V10/V19 -> 0.034670487 | W28: =W10/W19 -> 0.036204482 | X28: =X10/X19 -> 0.037649543 | Y28: =Y10/Y19 -> 0.019151104 | Z28: =Z10/Z19 -> 0.029322835 | AA28: =AA10/AA19 -> 0.03015559 | AB28: =AB10/AB19 -> 0.029056198 | AC28: =AC10/AC19 -> 0.03178689 | ... AE28: =AE10/AE19 -> 0.028961735 | AH28: pEXUSEl,t = pEXUSEl,t
B29: idxdefEXUS,2003oG,t | C29: Имплицитный индекс цен экспорта прочих товаров и услуг, 2000=100 | H29: 71.662397 | I29: 87.930345 | J29: 100 | K29: 88.080767 | L29: 112.44203 | M29: 40.803397 | N29: 22.554382 | O29: 52.393474 | P29: -9.0554139 | Q29: -11.87389 | R29: 89.419437 | S29: 0.11982482 | T29: 0.10455075 | U29: 0.11627607 | V29: 111.04768 | W29: =V29*(W3-SUM(W6:W10))/(V3-SUM(V6:V10))/(W20/V20) -> 113.41485 | X29: =W29*(X3-SUM(X6:X10))/(W3-SUM(W6:W10))/(X20/W20) -> 145.27797 | Y29: =X29*(Y3-SUM(Y6:Y10))/(X3-SUM(X6:X10))/(Y20/X20) -> 125.97828 | Z29: =Y29*(Z3-SUM(Z6:Z10))/(Y3-SUM(Y6:Y10))/(Z20/Y20) -> 124.08586 | AA29: =Z29*(AA3-SUM(AA6:AA10))/(Z3-SUM(Z6:Z10))/(AA20/Z20) -> 115.13833 | AB29: =AA29*(AB3-SUM(AB6:AB10))/(AA3-SUM(AA6:AA10))/(AB20/AA20) -> 152.39795 | AC29: =AB29*(AC3-SUM(AC6:AC10))/(AB3-SUM(AB6:AB10))/(AC20/AB20) -> 171.158 | AD29: =AC29*(AD3-SUM(AD6:AD10))/(AC3-SUM(AC6:AC10))/(AD20/AC20) -> 157.6151 | AE29: =AD29*(AE3-SUM(AE6:AE10))/(AD3-SUM(AD6:AD10))/(AE20/AD20) -> 143.15087 | AH29: idxdefEXUS,2003oG,t = idxdefEXUS,2003oG,t-1·(EXUSt-(EXUSAl,t+EXUSCot,t+EXUSFV,t+EXUSEl,t))/(EXUSt-1-(EXUSAl,t-1+EXUSCot,t-1+EXUSFV,t-1+EXUSEl,t-1))/(idxqEX2003oG,t/idxqEX2003oG,t-1)
C32: Справочно:
B33: gEXt | C33: Темпы роста физобъема экспорта товаров и услуг, % | I33: 107.6 | J33: 129.5 | K33: 122.6 | L33: 102.9 | M33: 131.2 | N33: 127.9 | O33: 86 | P33: 98 | Q33: 82.571366 | R33: 54.302901 | S33: 84238.271 | T33: 74.322871 | U33: 105.63695 | V33: =V34 -> 103.02143 | W33: =W34 -> 101.42173 | X33: =X34 -> 113.89625 | Y33: =Y34 -> 95.623442 | Z33: =Z34 -> 114.98259 | AA33: =AA34 -> 130.37583 | AB33: =AB34 -> 115.40893 | AC33: =AC34 -> 87.087781 | ... AE33: =AE34 -> 79.318175 | AH33: gEXt = gEXGoods,t
B34: gEXGoods,t | C34: Темпы роста физобъема товаров, % | H34: 103.48465 | I34: 114.14975 | J34: 120.50781 | K34: 106.73249 | L34: 110.85811 | M34: 85.197221 | N34: 103.00252 | O34: 97.563208 | P34: 39.703171 | Q34: 82.571366 | R34: 54.302901 | S34: 84238.271 | T34: 74.322871 | U34: 105.63695 | V34: 103.02143 | W34: =W5/V5/W36*10000 -> 101.42173 | X34: =X5/W5/X36*10000 -> 113.89625 | Y34: =Y5/X5/Y36*10000 -> 95.623442 | Z34: =Z5/Y5/Z36*10000 -> 114.98259 | AA34: =AA5/Z5/AA36*10000 -> 130.37583 | AB34: =AB5/AA5/AB36*10000 -> 115.40893 | AC34: =AC5/AB5/AC36*10000 -> 87.087781 | AD34: =AD5/AC5/AD36*10000 -> 134.08487 | AE34: =AE5/AD5/AE36*10000 -> 79.318175 | AH34: gEXGoods,t = EXUSGoods,t/EXUSGoods,t-1/defEXUSGoods,t·10000
B35: defEXUSt | C35: Дефлятор экспорта товаров и услуг, % | I35: 100.01562 | J35: 99.998696 | K35: 100.02536 | L35: 99.937659 | M35: 96.585747 | N35: 83.888739 | O35: 114.96604 | P35: 36.315759 | Q35: 159.6704 | R35: 423.99956 | S35: 0.1203725 | T35: 95.178586 | U35: 89.080814 | V35: 90.223464 | W35: =(W3)/(V3)/W33*10000 -> 97.51992 | X35: =(X3)/(W3)/X33*10000 -> 112.61287 | Y35: =(Y3)/(X3)/Y33*10000 -> 94.876462 | Z35: =(Z3)/(Y3)/Z33*10000 -> 93.663475 | AA35: =(AA3)/(Z3)/AA33*10000 -> 83.666305 | AB35: =(AB3)/(AA3)/AB33*10000 -> 128.75592 | AC35: =(AC3)/(AB3)/AC33*10000 -> 113.97662 | AD35: =(AD3)/(AC3)/AD33*10000 -> 88.089293 | AE35: =(AE3)/(AD3)/AE33*10000 -> 98.731987 | AH35: defEXUSt = (EXUSt)/(EXUSt-1)/gEXt·10000
B36: defEXUSGoods,t | C36: Дефлятор экспорта товаров, % | H36: 75.051901 | I36: 94.001029 | J36: 107.55705 | K36: 113.4125 | L36: 91.122959 | M36: 154.16441 | N36: 103.85338 | O36: 99.075772 | P36: 70.360654 | Q36: 131.795 | R36: 506.08654 | S36: 0.12837922 | T36: 93.353434 | U36: 98.065486 | V36: 88.455987 | W36: =(W6+W8+W9+W10)/(W6/(W24/V24*100)+W8/(W26/V26*100)+W9/(W27/V27*100)+W10/(W28/V28*100)) -> 99.494953 | X36: =(X6+X8+X9+X10)/(X6/(X24/W24*100)+X8/(X26/W26*100)+X9/(X27/W27*100)+X10/(X28/W28*100)) -> 117.03955 | Y36: =(Y6+Y8+Y9+Y10)/(Y6/(Y24/X24*100)+Y8/(Y26/X26*100)+Y9/(Y27/X27*100)+Y10/(Y28/X28*100)) -> 93.691446 | Z36: =(Z6+Z8+Z9+Z10)/(Z6/(Z24/Y24*100)+Z8/(Z26/Y26*100)+Z9/(Z27/Y27*100)+Z10/(Z28/Y28*100)) -> 95.161835 | AA36: =(AA6+AA8+AA9+AA10)/(AA6/(AA24/Z24*100)+AA8/(AA26/Z26*100)+AA9/(AA27/Z27*100)+AA10/(AA28/Z28*100)) -> 91.886157 | AB36: =(AB6+AB8+AB9+AB10)/(AB6/(AB24/AA24*100)+AB8/(AB26/AA26*100)+AB9/(AB27/AA27*100)+AB10/(AB28/AA28*100)) -> 132.38995 | AC36: =(AC6+AC8+AC9+AC10)/(AC6/(AC24/AB24*100)+AC8/(AC26/AB26*100)+AC9/(AC27/AB27*100)+AC10/(AC28/AB28*100)) -> 114.4207 | AD36: =(AD6+AD8+AD9+AD10)/(AD6/(AD24/AC24*100)+AD8/(AD26/AC26*100)+AD9/(AD27/AC27*100)+AD10/(AD28/AC28*100)) -> 85.261715 | AE36: =(AE6+AE8+AE9+AE10)/(AE6/(AE24/AD24*100)+AE8/(AE26/AD26*100)+AE9/(AE27/AD27*100)+AE10/(AE28/AD28*100)) -> 100.26033 | AH36: defEXUSGoods,t = (EXUSAl,t+EXUSCot,t+EXUSFV,t+EXUSEl,t)/(EXUSAl,t/(pEXUSAl,t/pEXUSAl,t-1·100)+EXUSCot,t/(pEXUSCot,t/pEXUSCot,t-1·100)+EXUSFV,t/(pEXUSFV,t/pEXUSFV,t-1·100)+EXUSEl,t/(pEXUSEl,t/pEXUSEl,t-1·100))
R38: 1.0933919
C40: Импорт | W40: =W43-V43 -> -404.4 | X40: =X43-W43 -> -256.3 | Y40: =Y43-X43 -> 376.1 | Z40: =Z43-Y43 -> 198.3 | AA40: =AA43-Z43 -> -199.3 | AB40: =AB43-AA43 -> 1059.5 | AC40: =AC43-AB43 -> 958 | AD40: =AD43-AC43 -> 712.6 | AE40: =AE43-AD43 -> 1127.5
B41: IMUSt | C41: Импорт ТОВАРОВ И УСЛУГ (млн. долл.) | G41: 977.475 | H41: 835.2807 | I41: 927.7792 | J41: 1147.2647 | K41: 1444.9593 | L41: 1682.4449 | M41: 2370.7754 | N41: 3707.0835 | O41: 4084.524 | P41: 2833.901 | Q41: 3460.285 | R41: 3646.76 | S41: 4358.9 | T41: 4836.09 | U41: 4759.9 | V41: =V42+V43 -> 3898.14 | W41: =W42+W43 -> 3405.3 | X41: =X42+X43 -> 3149.08 | Y41: =Y42+Y43 -> 3608.8 | Z41: =Z42+Z43 -> 3837.1 | AA41: =AA42+AA43 -> 3560 | AB41: =AB42+AB43 -> 4741.1 | AC41: =AC42+AC43 -> 5852.824 | ... AE41: =AE42+AE43 -> 7685.701 | AH41: IMUSt = IMUSGoods,t+IMUSServ,t
B42: IMUSServ,t | C42: Импорт услуг, млн.долл. | G42: 57 | H42: 69.6 | I42: 104.878 | J42: 121.533 | K42: 212.526 | L42: 251.519 | M42: 240.8 | N42: 592.078 | O42: 455.524 | P42: 291.301 | Q42: 528.125 | R42: 440.76 | S42: 580.5 | T42: 790.69 | U42: 462.5 | V42: =BoP!V11 -> 462.54 | W42: =BoP!W11 -> 374.1 | X42: =BoP!X11 -> 374.18 | Y42: =BoP!Y11 -> 457.8 | Z42: =BoP!Z11 -> 487.8 | AA42: =BoP!AA11 -> 410 | AB42: =BoP!AB11 -> 531.6 | AC42: =BoP!AC11 -> 685.324 | ... AE42: =BoP!AE11 -> 678.101 | AH42: IMUSServ,t = IMUSServ,t-1·EXP(0,152474485921+0,843221616006·LN(EXUSAl,t/EXUSAl,t-1))
B43: IMUSGoods,t | C43: Импорт товаов ФОБ, млн.долл. | G43: 920.475 | H43: 765.6807 | I43: 822.9012 | J43: 1025.7317 | K43: 1232.4333 | L43: 1430.9259 | M43: 2129.9754 | N43: 3115.0055 | O43: 3629 | P43: 2542.6 | Q43: 2932.16 | R43: 3206 | S43: 3778.4 | T43: 4045.4 | U43: 4297.4 | V43: 3435.6 | W43: 3031.2 | X43: 2774.9 | Y43: 3151 | Z43: 3349.3 | AA43: 3150 | AB43: 4209.5 | AC43: 5167.5 | AD43: 5880.1 | AE43: 7007.6 | AH43: IMUSGoods,t = (IMUSWh,t+IMUSOil,t+IMUSEl,t+IMUSGas,t+IMUSAm,t+IMUSFl,t+IMUSoG,t)
B44: IMUSWh,t | C44: Пшеница | G44: 36.3229 | H44: 30.3712 | I44: 23.3321 | J44: 12.4162 | K44: 15.041 | L44: 30.69 | M44: 28.0255 | N44: 40.121 | O44: 58.8643 | P44: 73.566 | Q44: 81.805132 | R44: 116.2 | S44: 185.3 | T44: 208.4 | U44: 231.1 | V44: 244.5 | W44: 231.4 | X44: 197.5 | Y44: 172.6 | Z44: 222.8 | AA44: 243.2 | AB44: 265.9 | AC44: 329.1 | AD44: 288.8 | AE44: 274.5 | AH44: IMUSWh,t = qIMWh,t·pIMUSWh,t/1000000
B45: IMUSOil,t | C45: Нефтепродукты (c учетом бензина) | G45: 68.0087 | H45: 73.2182 | I45: 69.5751 | J45: 73.0093 | K45: 106.8338 | L45: 126.129 | M45: 191.3666 | N45: 275.2921 | O45: 412.5101 | P45: 322.6331 | Q45: 435.22792 | R45: 451.9 | S45: 415.4 | T45: 394 | U45: 507.7 | V45: 351.6 | W45: 256.6 | X45: 266 | Y45: 310.8 | Z45: 328.5 | AA45: 272.6 | AB45: 412.6 | AC45: 681.6 | AD45: 667 | AE45: 829.4 | AH45: IMUSOil,t = qIMOil,t·pIMUSOil,t/1000000
C46: Бензин | R46: 207.5 | S46: 166.8 | T46: 131.7 | U46: 196.3 | V46: 133.4 | W46: 94.2 | X46: 101.2 | Y46: 56.3 | Z46: 99.9 | AA46: 97.3 | AB46: 161.2 | AC46: 245.7 | AD46: 228.1 | AE46: 336.4
