Workbook

Sheet S-1 реалистичный сценарий
A1: Сенарияи 2. Воќеї-Баҳодиҳии пешакии нишондиҳандаҳои асосии макроиќтисодии Љумҳурии Тољикистон барои соли 2025 ва дурнамои он барои солҳои 2026-2028
A2: Нишондињандањо | B2: Воњиди ченак | C2: Соли 2022 | E2: Соли 2023 | G2: Соли 2024 | I2: Соли 2025 | K2: Соли 2026 | M2: Соли 2027 | O2: Соли 2028 | Q2: Соли 2029 | S2: Соли 2030 | U2: Соли 2031 | W2: Соли 2032 | Y2: Соли 2033 | AA2: Соли 2034 | AC2: Соли 2035 | AE2: 2024
C3: Воќеї | D3: нисбат ба соли 2021 (бо фоиз) | E3: Воќеї | F3: нисбат ба соли 2022 (бо фоиз) | G3: Воќеї | H3: нисбат ба соли 2023 (бо фоиз) | I3: Бањодињї | J3: нисбат ба соли 2024 (бо фоиз) | K3: Дурнамо | L3: нисбат ба соли 2025 (бо фоиз) | M3: Дурнамо | N3: нисбат ба соли 2026 (бо фоиз) | O3: Дурнамо | P3: нисбат ба соли 2027 (бо фоиз) | Q3: Дурнамо | R3: нисбат ба соли 2027 (бо фоиз) | S3: Дурнамо | T3: нисбат ба соли 2027 (бо фоиз) | U3: Дурнамо | V3: нисбат ба соли 2027 (бо фоиз) | W3: Дурнамо | X3: нисбат ба соли 2027 (бо фоиз) | Y3: Дурнамо | Z3: нисбат ба соли 2027 (бо фоиз) | AA3: Дурнамо | AB3: нисбат ба соли 2027 (бо фоиз) | AC3: Дурнамо | AD3: нисбат ба соли 2027 (бо фоиз) | AF3: Соли 2023 | AH3: Соли 2024 | AJ3: Соли 2025 | AL3: Соли 2026 | AN3: Соли 2027 | AP3: Соли 2028
A4: Шумораи ањолї (ба њисоби миёнаи солона) | B4: Њазор нафар | C4: 9982.6 | D4: 101.8 | E4: 10183.3 | F4: =+E4/C4*100 -> 102.0105 | G4: 10398.4 | H4: =+G4/E4*100 -> 102.11228 | I4: 10614.691 | J4: =+I4/G4*100 -> 102.08004 | K4: =+I4*L4/100 -> 10837.6 | L4: 102.1 | M4: =+K4*N4/100 -> 11076.027 | N4: 102.2 | O4: =+M4*N4/100 -> 11319.699 | P4: 102.2 | Q4: =+O4*P4/100 -> 11568.733 | R4: 102.2 | S4: =+Q4*R4/100 -> 11823.245 | T4: 102.2 | U4: =+S4*T4/100 -> 12083.356 | V4: 102.2 | W4: =+U4*V4/100 -> 12349.19 | X4: 102.3 | Y4: =+W4*X4/100 -> 12633.221 | Z4: 102.4 | AA4: =+Y4*Z4/100 -> 12936.419 | AB4: 102.3 | AC4: =+AA4*AB4/100 -> 13233.956 | AD4: 102.3 | AE4: 10382.1 | AF4: =C4*D4/100 -> 10162.287 | AG4: =E4/C4*100 -> 102.0105 | AH4: =E4*F4/100 -> 10388.035 | AI4: =G4/E4*100 -> 102.11228 | AJ4: =G4*H4/100 -> 10618.044 | AK4: =I4/G4*100 -> 102.08004 | AL4: =I4*J4/100 -> 10835.481 | AM4: =K4/I4*100 -> 102.1 | AN4: =K4*L4/100 -> 11065.189 | AO4: =M4/K4*100 -> 102.2 | AP4: =M4*N4/100 -> 11319.699 | AQ4: =O4/M4*100 -> 102.2
A5: Маљмўи мањсулоти дохилї | B5: млн. сомонї | C5: =+GDP!AC2 -> 118181.7 | D5: =+GDP!AC3 -> 108.03592 | E5: =+GDP!AD2 -> 132781.9 | F5: =+GDP!AD3 -> 108.31977 | G5: =+GDP!AE2 -> 155783.9 | H5: =+GDP!AE3 -> 108.42918 | I5: =+GDP!AF2 -> 176919 | J5: =+GDP!AF3 -> 108.43563 | K5: =+GDP!AG2 -> 199898.14 | L5: =+GDP!AG3 -> 108.49433 | M5: =+GDP!AH2 -> 225457.21 | N5: =+GDP!AH3 -> 108.43204 | O5: =+GDP!AI2 -> 254610.41 | P5: =+GDP!AI3 -> 108.58847 | Q5: =GDP!AJ2 -> 290955.28 | R5: =GDP!AJ3 -> 108.78201 | S5: =GDP!AK2 -> 325987.6 | T5: =GDP!AK3 -> 108.04844 | U5: =GDP!AL2 -> 368330.8 | V5: =+GDP!AL3 -> 108.54826 | W5: =GDP!AM2 -> 413970.29 | X5: =+GDP!AM3 -> 108.06837 | Y5: =GDP!AN2 -> 460417.18 | Z5: =+GDP!AN3 -> 108.10105 | AA5: =GDP!AO2 -> 511101.74 | AB5: =+GDP!AO3 -> 108.24891 | AC5: =GDP!AP2 -> 568732.06 | AD5: =+GDP!AP3 -> 108.60848 | AE5: 153402.2
A6: Индекс-дефлятори ММД | B6: бо фоиз | D6: =+GDP!AC4 -> 108.22628 | F6: =+GDP!AD4 -> 103.7244 | H6: =+GDP!AE4 -> 108.20255 | J6: =+GDP!AF4 -> 106.43212 | L6: =+GDP!AG4 -> 104.14231 | N6: =+GDP!AH4 -> 104.11542 | P6: =+GDP!AI4 -> 103.9988 | R6: =GDP!AJ4 -> 105.14926 | T6: =GDP!AK4 -> 103.99465 | V6: =+GDP!AL4 -> 104.09122 | X6: =+GDP!AM4 -> 103.9998 | Z6: =+GDP!AN4 -> 102.88509 | AB6: =+GDP!AO4 -> 102.54921 | AD6: =+GDP!AP4 -> 102.45581
A7: Таваррум | B7: бо фоиз | D7: =+Monetary!AC15 -> 104.2 | F7: =+Monetary!AD15 -> 103.8 | H7: =Monetary!AE15 -> 103.6 | J7: =Monetary!AF15 -> 103.5 | L7: =Monetary!AG3 -> 103.93407 | N7: =Monetary!AH3 -> 104.03272 | P7: =Monetary!AI3 -> 103.79573 | R7: =Monetary!AJ3 -> 103.90476 | T7: =Monetary!AK3 -> 104.06104 | V7: =Monetary!AL3 -> 104.427 | X7: =Monetary!AM3 -> 104.43909 | Z7: =Monetary!AN3 -> 104.16684 | AB7: =Monetary!AO3 -> 103.79413 | AD7: =Monetary!AP3 -> 104.06565
A8: ММД ба њар нафар ањолї | B8: сомонї | C8: =+C5/C4*1000 -> 11838.769 | D8: =+C8/10312*100 -> 114.80576 | E8: =+E5/E4*1000 -> 13039.182 | F8: =+E8/C8*100 -> 110.13967 | G8: =+G5/G4*1000 -> 14981.526 | H8: =+G8/E8*100 -> 114.89621 | I8: =+I5/I4*1000 -> 16667.372 | J8: =+I8/G8*100 -> 111.25283 | K8: =+K5/K4*1000 -> 18444.872 | L8: =+K8/I8*100 -> 110.66455 | M8: =+M5/M4*1000 -> 20355.423 | N8: =+M8/K8*100 -> 110.35817 | O8: =+O5/O4*1000 -> 22492.683 | P8: =+O8/M8*100 -> 110.49971 | Q8: =+Q5/Q4*1000 -> 25150.142 | R8: =+Q8/O8*100 -> 111.81477 | S8: =+S5/S4*1000 -> 27571.754 | T8: =+S8/Q8*100 -> 109.62862 | U8: =+U5/U4*1000 -> 30482.492 | V8: =+U8/S8*100 -> 110.55695 | W8: =+W5/W4*1000 -> 33522.06 | X8: =+W8/U8*100 -> 109.97152 | Y8: =+Y5/Y4*1000 -> 36444.955 | Z8: =+Y8/W8*100 -> 108.71932 | AA8: =+AA5/AA4*1000 -> 39508.75 | AB8: =+AA8/Y8*100 -> 108.40664 | AC8: =+AC5/AC4*1000 -> 42975.21 | AD8: =+AC8/AA8*100 -> 108.7739 | AE8: =+AE5/AE4*1000 -> 14775.643
A9: Њаљми мањсулоти саноатї | B9: млн. сомонї | C9: =Industry!AC4 -> 42221.4 | D9: =Industry!AC18 -> 115.4 | E9: =Industry!AD4 -> 46816 | F9: =Industry!AD18 -> 112 | G9: =Industry!AE4 -> 53819 | H9: =Industry!AE18 -> 120 | I9: =+Industry!AF4 -> 66726.1 | J9: =+Industry!AF18 -> 122.1 | K9: =+Industry!AG4 -> 83491.032 | L9: =+Industry!AG18 -> 125.02097 | M9: =+Industry!AH4 -> 104885.65 | N9: =+Industry!AH18 -> 125.0001 | O9: =+Industry!AI4 -> 131605.53 | P9: =+Industry!AI18 -> 125.10772 | Q9: =Industry!AJ4 -> 164803.16 | R9: =Industry!AJ18 -> 125.0738 | S9: =Industry!AK4 -> 167867.77 | T9: =Industry!AK18 -> 119.95581 | U9: =+Industry!AL4 -> 171881.25 | V9: =+Industry!AL18 -> 119.92603 | W9: =+Industry!AM4 -> 172762.85 | X9: =+Industry!AM18 -> 120.07027 | Y9: =+Industry!AN4 -> 196491.13 | Z9: =+Industry!AN18 -> 111.30175 | AA9: =+Industry!AO4 -> 216673.07 | AB9: =+Industry!AO18 -> 109.17267 | AC9: =+Industry!AP4 -> 241220.44 | AD9: =+Industry!AP18 -> 122.3396
A10: -саноати истихроҷи маъдан | B10: млн. сомонї | C10: =Industry!AC5 -> 8890.9 | D10: =Industry!AC19 -> 97.7 | E10: =Industry!AD5 -> 9373 | F10: =Industry!AD19 -> 111.7 | G10: =Industry!AE5 -> 13363.1 | H10: =Industry!AE19 -> 143 | I10: =Industry!AF5 -> 20000.2 | J10: =+Industry!AF19 -> 136.2 | K10: =Industry!AG5 -> 26754.532 | L10: =+Industry!AG19 -> 121.23928 | M10: =Industry!AH5 -> 29788.981 | N10: =+Industry!AH19 -> 127.31865 | O10: =Industry!AI5 -> 40744.262 | P10: =+Industry!AI19 -> 157.14609 | Q10: =Industry!AJ5 -> 48047.335 | R10: =Industry!AJ19 -> 118.05099 | S10: =Industry!AK5 -> 51160.518 | T10: =Industry!AK19 -> 77.11757 | U10: =Industry!AL5 -> 37883.054 | V10: =+Industry!AL19 -> 72.072546 | W10: =Industry!AM5 -> 26182.762 | X10: =+Industry!AM19 -> 67.986265 | Y10: =Industry!AN5 -> 30415.987 | Z10: =+Industry!AN19 -> 117.51327 | AA10: =Industry!AO5 -> 36342.377 | AB10: =+Industry!AO19 -> 119.45571 | AC10: =Industry!AP5 -> 43559.306 | AD10: =+Industry!AP19 -> 119.8637
A11: -саноати коркард | B11: млн. сомонї | C11: =Industry!AC8 -> 25708.7 | D11: =Industry!AC22 -> 116.4 | E11: =Industry!AD8 -> 28459.8 | F11: =Industry!AD22 -> 112.4 | G11: =Industry!AE8 -> 30275.6 | H11: =Industry!AE22 -> 107.6 | I11: =Industry!AF8 -> 34595.4 | J11: =+Industry!AF22 -> 110.5 | K11: =Industry!AG8 -> 43621.32 | L11: =+Industry!AG22 -> 132.91232 | M11: =Industry!AH8 -> 60339.771 | N11: =+Industry!AH22 -> 127.14443 | O11: =Industry!AI8 -> 73035.004 | P11: =+Industry!AI22 -> 110.19673 | Q11: =Industry!AJ8 -> 95177.148 | R11: =Industry!AJ22 -> 129.91494 | S11: =Industry!AK8 -> 93137.6 | T11: =Industry!AK22 -> 143.95848 | U11: =Industry!AL8 -> 108597.04 | V11: =+Industry!AL22 -> 149.21789 | W11: =Industry!AM8 -> 119233.48 | X11: =+Industry!AM22 -> 141.07614 | Y11: =Industry!AN8 -> 136686.93 | Z11: =+Industry!AN22 -> 110.7975 | AA11: =Industry!AO8 -> 148738.68 | AB11: =+Industry!AO22 -> 107.23612 | AC11: =Industry!AP8 -> 163710.02 | AD11: =+Industry!AP22 -> 126.03137
A12: -таъминоти нерўи барќ, газ, буѓ ва тозакунии њаво | B12: млн. сомонї | C12: =Industry!AC15 -> 7621.8 | D12: =Industry!AC29 -> 117.5 | E12: =Industry!AD15 -> 8983.2 | F12: =Industry!AD29 -> 107.1 | G12: =Industry!AE15+Industry!AE17 -> 10180.3 | H12: =Industry!AE29 -> 105.7 | I12: =Industry!AF15+Industry!AF17 -> 12130.5 | J12: =+Industry!AF29 -> 113 | K12: =Industry!AG15+Industry!AG17 -> 13115.18 | L12: =+Industry!AG29+2 -> 110.22722 | M12: =Industry!AH15+Industry!AH17 -> 14756.897 | N12: =+Industry!AH29 -> 112.76929 | O12: =Industry!AI15+Industry!AI17 -> 17826.267 | P12: =+Industry!AI29 -> 121.29669 | Q12: =Industry!AJ15+Industry!AJ17 -> 21578.678 | R12: =Industry!AJ29 -> 121.19792 | S12: =Industry!AK15+Industry!AK17 -> 23569.656 | T12: =Industry!AK29 -> 109.2266 | U12: =Industry!AL15+Industry!AL17 -> 25401.162 | V12: =+Industry!AL29 -> 107.77061 | W12: =Industry!AM15+Industry!AM17 -> 27346.612 | X12: =+Industry!AM29 -> 107.6589 | Y12: =Industry!AN15+Industry!AN17 -> 29388.222 | Z12: =+Industry!AN29 -> 107.46567 | AA12: =Industry!AO15+Industry!AO17 -> 31592.015 | AB12: =+Industry!AO29 -> 107.4989 | AC12: =Industry!AP15+Industry!AP17 -> 33951.116 | AD12: =+Industry!AP29 -> 107.46739
A13: Њаљми мањсулоти кишоварзї | B13: млн. сомонї | C13: =Agriculture!AC2 -> 61337.9 | D13: =Agriculture!AC3 -> 108 | E13: =+Agriculture!AD2 -> 66907.2 | F13: =+Agriculture!AD3 -> 109 | G13: =+Agriculture!AE2 -> 73976.6 | H13: =+Agriculture!AE3 -> 110.6 | I13: =+Agriculture!AF2 -> 84653.8 | J13: =+Agriculture!AF3 -> 109.5 | K13: =+Agriculture!AG2 -> 95155.365 | L13: =+Agriculture!AG3 -> 108.91987 | M13: =+Agriculture!AH2 -> 104591.34 | N13: =+Agriculture!AH3 -> 108.61303 | O13: =Agriculture!AI2 -> 114715.98 | P13: =+Agriculture!AI3 -> 108.27265 | Q13: =Agriculture!AJ2 -> 125434.67 | R13: =Agriculture!AJ3 -> 108.15398 | S13: =Agriculture!AK2 -> 136949.66 | T13: =+Agriculture!AK3 -> 108.31356 | U13: =Agriculture!AL2 -> 148095.75 | V13: =+Agriculture!AL3 -> 107.60081 | W13: =Agriculture!AM2 -> 159589.23 | X13: =+Agriculture!AM3 -> 107.54575 | Y13: =Agriculture!AN2 -> 172013.18 | Z13: =+Agriculture!AN3 -> 107.24871 | AA13: =Agriculture!AO2 -> 184982.77 | AB13: =+Agriculture!AO3 -> 107.00486 | AC13: =Agriculture!AP2 -> 199395.93 | AD13: =+Agriculture!AP3 -> 107.25535
A14: -растанипарварӣ | B14: млн. сомонї | C14: =Agriculture!AC5 -> 42115 | D14: =Agriculture!AC6 -> 107.7 | E14: =+Agriculture!AD5 -> 44976.1 | F14: =+Agriculture!AD6 -> 106.8 | G14: =+Agriculture!AE5 -> 50984.9 | H14: =+Agriculture!AE6 -> 113.4 | I14: =+Agriculture!AF5 -> 56588 | J14: =+Agriculture!AF6 -> 109.9 | K14: =+Agriculture!AG5 -> 61242.178 | L14: =+Agriculture!AG6 -> 107.25934 | M14: =+Agriculture!AH5 -> 66836.044 | N14: =+Agriculture!AH6 -> 106.99413 | O14: =Agriculture!AI5 -> 72556.838 | P14: =+Agriculture!AI6 -> 108.34276 | Q14: =Agriculture!AJ5 -> 78788.347 | R14: =Agriculture!AJ6 -> 107.51332 | S14: =Agriculture!AK5 -> 85058.32 | T14: =+Agriculture!AK6 -> 107.42089 | U14: =Agriculture!AL5 -> 90393.172 | V14: =+Agriculture!AL6 -> 105.74328 | W14: =Agriculture!AM5 -> 95752.602 | X14: =+Agriculture!AM6 -> 105.61219 | Y14: =Agriculture!AN5 -> 100785.75 | Z14: =+Agriculture!AN6 -> 104.94159 | AA14: =Agriculture!AO5 -> 105499.67 | AB14: =+Agriculture!AO6 -> 104.46823 | AC14: =Agriculture!AP5 -> 109860.02 | AD14: =+Agriculture!AP6 -> 101.29673
A15: -чорводорӣ | B15: млн. сомонї | C15: =Agriculture!AC8 -> 19222.9 | D15: =Agriculture!AC9 -> 108.7 | E15: =+Agriculture!AD8 -> 21931.1 | F15: =+Agriculture!AD9 -> 114.1 | G15: =+Agriculture!AE8 -> 22991.7 | H15: =+Agriculture!AE9 -> 104.8 | I15: =+Agriculture!AF8 -> 28065.8 | J15: =+Agriculture!AF9 -> 108.5 | K15: =+Agriculture!AG8 -> 33724.207 | L15: =+Agriculture!AG9 -> 107.4085 | M15: =+Agriculture!AH8 -> 37549.307 | N15: =+Agriculture!AH9 -> 106.622 | O15: =Agriculture!AI8 -> 41934.825 | P15: =+Agriculture!AI9 -> 104.4435 | Q15: =Agriculture!AJ8 -> 46401.587 | R15: =Agriculture!AJ9 -> 103.5132 | S15: =Agriculture!AK8 -> 51624.557 | T15: =+Agriculture!AK9 -> 105.0056 | U15: =Agriculture!AL8 -> 57411.246 | V15: =+Agriculture!AL9 -> 105.4467 | W15: =Agriculture!AM8 -> 63518.787 | X15: =+Agriculture!AM9 -> 105.897 | Y15: =Agriculture!AN8 -> 70880.981 | Z15: =+Agriculture!AN9 -> 107 | AA15: =Agriculture!AO8 -> 79106.511 | AB15: =+Agriculture!AO9 -> 107 | AC15: =Agriculture!AP8 -> 89127.317 | AD15: =+Agriculture!AP9 -> 108
A16: Маблаѓгузорї ба сармояи асосї аз њисоби њамаи манбаъњои маблаѓгузорї | B16: млн. сомонї | C16: 16279.5 | D16: 111.4 | E16: =+OEA!AD22 -> 19859 | F16: =+E16/C16*100 -> 121.98778 | G16: =OEA!AE22 -> 22543 | H16: 108.4 | I16: =OEA!AF22 -> 28736 | J16: 123 | K16: =OEA!AG22 -> 32767.972 | L16: =+K16/I16*100 -> 114.03108 | M16: =+OEA!AH22 -> 38923.922 | N16: =+M16/K16*100 -> 118.78648 | O16: =+OEA!AI22 -> 44524.431 | P16: =+O16/M16*100 -> 114.38835 | Q16: =OEA!AJ22 -> 51375.484 | R16: =+Q16/O16*100 -> 115.38718 | S16: =+OEA!AK22 -> 55564.062 | T16: =+S16/Q16*100 -> 108.15287 | U16: =+OEA!AL22 -> 63254.949 | V16: =+U16/S16*100 -> 113.84148 | W16: =+OEA!AM22 -> 73256.893 | X16: =+W16/U16*100 -> 115.81211 | Y16: =+OEA!AN22 -> 91342.986 | Z16: =+Y16/W16*100 -> 124.68859 | AA16: =+OEA!AO22 -> 114213.1 | AB16: =+AA16/W16*100 -> 155.90765 | AC16: =+OEA!AP22 -> 143190.44 | AD16: =+AC16/Y16*100 -> 156.76129
A17: аз чумла аз њисоби буљети давлатї | B17: млн. сомонї | C17: 6736.9 | D17: 110.3 | E17: =+OEA!AD23 -> 7922.5 | F17: =+E17/C17*100 -> 117.5986 | G17: =OEA!AE23 -> 9830.5 | H17: 118.5 | I17: =OEA!AF23 -> 13280.5 | J17: 130.4 | K17: =OEA!AG23 -> 14210.135 | L17: =+K17/I17*100 -> 107 | M17: =+OEA!AH23 -> 15631.149 | N17: =+M17/K17*100 -> 110 | O17: =+OEA!AI23 -> 16881.64 | P17: =+O17/M17*100 -> 108 | Q17: =OEA!AJ23 -> 18063.355 | R17: =+Q17/O17*100 -> 107 | S17: =+OEA!AK23 -> 18785.889 | T17: =+S17/Q17*100 -> 104 | U17: =+OEA!AL23 -> 19725.184 | V17: =+U17/S17*100 -> 105 | W17: =+OEA!AM23 -> 21697.702 | X17: =+W17/U17*100 -> 110 | Y17: =+OEA!AN23 -> 26037.243 | Z17: =+Y17/W17*100 -> 120 | AA17: =+OEA!AO23 -> 31244.691 | AB17: =+AA17/Y17*100 -> 120 | AC17: =+OEA!AP23 -> 37493.63 | AD17: =+AC17/AA17*100 -> 120
A18: Сармоягузории хориљї (қарз, грант, мустақим) | B18: млн. доллар | C18: 2577 | E18: 2690 | F18: =+E18/C18*100 -> 104.38494 | G18: =OEA!AE34 -> 5126.6 | H18: =+G18/E18*100 -> 190.57993 | I18: =OEA!AF34 -> 6925.3 | J18: =+I18/G18*100 -> 135.08563 | K18: =OEA!AG34 -> 7624.7553 | L18: =+K18/I18*100 -> 110.1 | M18: =OEA!AH34 -> 8562.6002 | N18: =+M18/K18*100 -> 112.3 | O18: =OEA!AI34 -> 9598.6748 | P18: =+O18/M18*100 -> 112.1 | Q18: =OEA!AJ34 -> 10769.713 | R18: =+Q18/O18*100 -> 112.2 | S18: =OEA!AK34 -> 12094.388 | T18: =+S18/Q18*100 -> 112.3 | U18: =OEA!AL34 -> 13545.714 | V18: =+U18/S18*100 -> 112 | W18: =OEA!AM34 -> 15184.746 | X18: =+W18/U18*100 -> 112.1 | Y18: =OEA!AN34 -> 17037.285 | Z18: =+Y18/W18*100 -> 112.2 | AA18: =OEA!AO34 -> 19132.871 | AB18: =+AA18/Y18*100 -> 112.3 | AC18: =OEA!AP34 -> 21428.815 | AD18: =+AC18/AA18*100 -> 112
A19: Њаљми умумии гардиши савдо дар њама соњањо | B19: млн. сомонї | C19: 47563.4 | D19: 111.2 | E19: =+Household!AD3 -> 56124.4 | F19: =+Household!AD4 -> 113.4 | G19: =+Household!AE3 -> 65783.8 | H19: =+Household!AE4 -> 113.6 | I19: =+Household!AF3 -> 77307.1 | J19: =+Household!AF4 -> 113.9 | K19: =+Household!AG3 -> 89946.541 | L19: =+Household!AG4 -> 114.32794 | M19: =+Household!AH3 -> 105319.77 | N19: =+Household!AH4 -> 114.46523 | O19: =+Household!AI3 -> 120054.47 | P19: =+Household!AI4 -> 113.63166 | Q19: =Household!AJ3 -> 138358.42 | R19: =+Household!AJ4 -> 113.89224 | S19: =+Household!AK3 -> 149157.72 | T19: =+Household!AK4 -> 108.36872 | U19: =+Household!AL3 -> 160879.07 | V19: =+Household!AL4 -> 109.84897 | W19: =+Household!AM3 -> 174656.34 | X19: =+Household!AM4 -> 109.32916 | Y19: =+Household!AN3 -> 194923.92 | Z19: =+Household!AN4 -> 109.35302 | AA19: =+Household!AO3 -> 210618.08 | AB19: =+Household!AO4 -> 106.10895 | AC19: =+Household!AP3 -> 228337.25 | AD19: =+Household!AP4 -> 106.39789 | AN19: =K18*L18/100 -> 8394.8556 | AO19: =M18/K18*100 -> 112.3
A20: аз он: гардиши савдои чакана | B20: млн. сомонї | C20: 39586.2 | D20: 110.2 | E20: =+Household!AD9 -> 47540.5 | F20: =+Household!AD11 -> 115.4 | G20: =+Household!AE9 -> 55663 | H20: =+Household!AE11 -> 113.5 | I20: =+Household!AF9 -> 65705.6 | J20: =+Household!AF11 -> 114.4 | K20: =+Household!AG9 -> 78696.141 | L20: =+Household!AG11 -> 113.99326 | M20: =+Household!AH9 -> 91582.412 | N20: =+Household!AH11 -> 114.2111 | O20: =+Household!AI9 -> 104395.19 | P20: =+Household!AI11 -> 113.29285 | Q20: =Household!AJ9 -> 119274.5 | R20: =+Household!AJ11 -> 113.4711 | S20: =+Household!AK9 -> 129702.36 | T20: =+Household!AK11 -> 108.22317 | U20: =+Household!AL9 -> 139894.85 | V20: =+Household!AL11 -> 107.54877 | W20: =+Household!AM9 -> 151875.08 | X20: =+Household!AM11 -> 107.27654 | Y20: =+Household!AN9 -> 163801.61 | Z20: =+Household!AN11 -> 103.74588 | AA20: =+Household!AO9 -> 176989.99 | AB20: =+Household!AO11 -> 104.16539 | AC20: =+Household!AP9 -> 191880.04 | AD20: =+Household!AP11 -> 104.45022
A21: Њаљми хизматрасонињои пулакї дар њамаи соњањо | B21: млн. сомонї | C21: 18696.8 | D21: 116 | E21: =+Household!AD15 -> 21760.3 | F21: =+Household!AD16 -> 114.1 | G21: =+Household!AE15 -> 25722.9 | H21: =+Household!AE16 -> 113 | I21: =+Household!AF15 -> 30470.2 | J21: =+Household!AF16 -> 113.2 | K21: =+Household!AG15 -> 35439.755 | L21: =+Household!AG16 -> 114.93039 | M21: =+Household!AH15 -> 41254.485 | N21: =+Household!AH16 -> 113.90153 | O21: =+Household!AI15 -> 47612.182 | P21: =+Household!AI16 -> 113.70534 | Q21: =Household!AJ15 -> 51548.635 | R21: =+Household!AJ16 -> 108.15958 | S21: =+Household!AK15 -> 56661.404 | T21: =+Household!AK16 -> 109.69894 | U21: =+Household!AL15 -> 62425.439 | V21: =+Household!AL16 -> 109.62465 | W21: =+Household!AM15 -> 64323.564 | X21: =+Household!AM16 -> 102.52799 | Y21: =+Household!AN15 -> 76394.869 | Z21: =+Household!AN16 -> 118.17566 | AA21: =+Household!AO15 -> 87007.682 | AB21: =+Household!AO16 -> 113.32542 | AC21: =+Household!AP15 -> 83427.507 | AD21: =+Household!AP16 -> 95.408178
A22: аз он: хизматрасонињои пулакї ба ањолї | B22: млн. сомонї | C22: 13866.9 | D22: 110.9 | E22: =+Household!AD18 -> 16740.8 | F22: =+Household!AD20 -> 118.4 | G22: =+Household!AE18 -> 19094.9 | H22: =+Household!AE20 -> 109 | I22: =+Household!AF18 -> 22148.5 | J22: =+Household!AF20 -> 110.9 | K22: =+Household!AG18 -> 25868.434 | L22: =+Household!AG20 -> 111.23374 | M22: =+Household!AH18 -> 29679.485 | N22: =+Household!AH20 -> 111.39072 | O22: =+Household!AI18 -> 33529.706 | P22: =+Household!AI20 -> 111.85412 | Q22: =+Household!AJ18 -> 37085.349 | R22: =+Household!AJ20 -> 110.49396 | S22: =+Household!AK18 -> 40763.6 | T22: =+Household!AK20 -> 108.83004 | U22: =+Household!AL18 -> 43351 | V22: =+Household!AL20 -> 105.81824 | W22: =+Household!AM18 -> 45945.403 | X22: =+Household!AM20 -> 103.90651 | Y22: =+Household!AN18 -> 50929.913 | Z22: =+Household!AN20 -> 108.67526 | AA22: =+Household!AO18 -> 58005.122 | AB22: =+Household!AO20 -> 108.26241 | AC22: =+Household!AP18 -> 64175.005 | AD22: =+Household!AP20 -> 109.54138
A23: Гардиши савдои хориљї | B23: млн. доллар | C23: 7309.5 | D23: 114.9 | E23: =+E24+E25 -> 8733.359 | F23: =+E23/C23*100 -> 119.47957 | G23: =+G24+G25 -> 8955.1 | H23: =+G23/E23*100 -> 102.53901 | I23: =+I24+I25 -> 10793.1 | J23: =+I23/G23*100 -> 120.52462 | K23: =+K24+K25 -> 11021.821 | L23: =+K23/I23*100 -> 102.11914 | M23: =+M24+M25 -> 11200.543 | N23: =+M23/K23*100 -> 101.62153 | O23: =+O24+O25 -> 11336.519 | P23: =+O23/M23*100 -> 101.21401 | Q23: =+Q24+Q25 -> 11664.519 | R23: =+Q23/O23*100 -> 102.8933 | S23: =+S24+S25 -> 11979.383 | T23: =+S23/Q23*100 -> 102.69934 | U23: =+U24+U25 -> 11976.167 | V23: =+U23/S23*100 -> 99.973148 | W23: =+W24+W25 -> 12300.476 | X23: =+W23/U23*100 -> 102.70796 | Y23: =+Y24+Y25 -> 11840.393 | Z23: =+Y23/W23*100 -> 96.25963 | AA23: =+AA24+AA25 -> 11378.757 | AB23: =+AA23/Y23*100 -> 96.101176 | AC23: =+AC24+AC25 -> 13564.672 | AD23: =+AC23/AA23*100 -> 119.2105
A24: аз он: - содирот | C24: 2142 | D24: 99.6 | E24: =Results!L31+Trade!AD4 -> 2104.978 | F24: =+E24/C24*100 -> 98.271615 | G24: =Results!M31 -> 1947.5 | H24: =+G24/E24*100 -> 92.518782 | I24: =Results!N31 -> 2487.9 | J24: =+I24/G24*100 -> 127.7484 | K24: =Results!O31 -> 2672.7851 | L24: =+K24/I24*100 -> 107.43137 | M24: =Results!P31 -> 2840.4586 | N24: =+M24/K24*100 -> 106.27336 | O24: =Results!Q31 -> 2973.4668 | P24: =+O24/M24*100 -> 104.68263 | Q24: =Results!R31 -> 3140.6396 | R24: =+Q24/O24*100 -> 105.62215 | S24: =Results!S31 -> 3298.4753 | T24: =+S24/Q24*100 -> 105.02559 | U24: =Results!T31 -> 3051.7187 | V24: =+U24/S24*100 -> 92.519072 | W24: =Results!U31 -> 3206.4233 | X24: =+W24/U24*100 -> 105.06942 | Y24: =Results!V31 -> 3486.8409 | Z24: =+Y24/W24*100 -> 108.7455 | AA24: =Results!W31 -> 3794.5847 | AB24: =+AA24/Y24*100 -> 108.82586 | AC24: =Results!X31 -> 4161.3641 | AD24: =+AC24/AA24*100 -> 109.66586
A25: -воридот | C25: 5167.5 | D25: 122.8 | E25: =Results!L33+Trade!AD42 -> 6628.381 | F25: =+E25/C25*100 -> 128.27056 | G25: =Results!M33 -> 7007.6 | H25: =+G25/E25*100 -> 105.72114 | I25: =Results!N33 -> 8305.2 | J25: =+I25/G25*100 -> 118.51704 | K25: =Results!O33 -> 8349.036 | L25: =+K25/I25*100 -> 100.52781 | M25: =Results!P33 -> 8360.0848 | N25: =+M25/K25*100 -> 100.13234 | O25: =Results!Q33 -> 8363.0527 | P25: =+O25/M25*100 -> 100.0355 | Q25: =Results!R33 -> 8523.8791 | R25: =+Q25/O25*100 -> 101.92306 | S25: =Results!S33 -> 8680.908 | T25: =+S25/Q25*100 -> 101.84222 | U25: =Results!T33 -> 8924.4479 | V25: =+U25/S25*100 -> 102.80546 | W25: =Results!U33 -> 9094.0526 | X25: =+W25/U25*100 -> 101.90045 | Y25: =Results!V33 -> 8353.5517 | Z25: =+Y25/W25*100 -> 91.857305 | AA25: =Results!W33 -> 7584.1718 | AB25: =+AA25/Y25*100 -> 90.789788 | AC25: =Results!X33 -> 9403.3084 | AD25: =+AC25/AA25*100 -> 123.98596
E27: =+G8-E8 -> 1942.3442 | F27: =+H8-F8 -> 4.7565408 | G27: =+I8-G8 -> 1685.8457 | H27: =+J8-H8 -> -3.6433823 | I27: =+K8-I8 -> 1777.5005 | J27: =+L8-J8 -> -0.58827826 | K27: =+M8-K8 -> 1910.5508 | L27: =+N8-L8 -> -0.30638389 | ... N27: =+P8-N8 -> 0.14154121
I28: =3119*109.8 -> 342466.2
E29: =+E24/E23*100 -> 24.102731 | G29: =+G24/G23*100 -> 21.747384 | I29: =+I24/I23*100 -> 23.050838 | K29: =+K24/K23*100 -> 24.249941 | M29: =+M24/M23*100 -> 25.360007
E30: =+E25/E23*100 -> 75.897269 | G30: =+G25/G23*100 -> 78.252616 | I30: =+I25/I23*100 -> 76.949162 | K30: =+K25/K23*100 -> 75.750059 | M30: =+M25/M23*100 -> 74.639993
C32: =C33+C34 -> 7013.824 | D32: =D33+D34 -> 0 | E32: =E33+E34 -> 8036.481 | F32: =F33+F34 -> 232.83271 | G32: =G33+G34 -> 8524.488 | H32: =H33+H34 -> 193.28926 | I32: =I33+I34 -> 11393.136 | J32: =J33+J34 -> 286.77984 | ... P32: =P33+P34 -> 207.58787
A33: аз он: - содирот молњо ва хизматрасонї | C33: =BoP!AC14 -> 1752.9 | E33: =BoP!AD14 -> 2105 | F33: =+E33/C33*100 -> 120.08671 | G33: =BoP!AE14 -> 1617.57 | H33: =+G33/E33*100 -> 76.844181 | I33: =BoP!AF14 -> 2573.297 | J33: =+I33/G33*100 -> 159.08412 | K33: =BoP!AG14 -> 2769.4661 | L33: =+K33/I33*100 -> 107.62326 | M33: =BoP!AH14 -> 2940.1717 | N33: =+M33/K33*100 -> 106.16385 | O33: =BoP!AI14 -> 3075.4343 | P33: =+O33/M33*100 -> 104.6005
A34: -воридот молњо ва хизматрасонї | C34: =BoP!AC15 -> 5260.924 | E34: =BoP!AD15 -> 5931.481 | F34: =+E34/C34*100 -> 112.74599 | G34: =BoP!AE15 -> 6906.918 | H34: =+G34/E34*100 -> 116.44508 | I34: =BoP!AF15 -> 8819.839 | J34: =+I34/G34*100 -> 127.69572 | K34: =BoP!AG15 -> 8896.2761 | L34: =+K34/I34*100 -> 100.86665 | M34: =BoP!AH15 -> 9176.3859 | N34: =+M34/K34*100 -> 103.14862 | O34: =BoP!AI15 -> 9450.5185 | P34: =+O34/M34*100 -> 102.98737

Sheet GDP
B1: Var. Name | C1: Наименование индикатора | D1: 1997 | E1: 1998 | F1: 1999 | G1: 2000 | H1: 2001 | I1: 2002 | J1: 2003 | K1: 2004 | L1: 2005 | M1: 2006 | N1: 2007 | O1: 2008 | P1: 2009 | Q1: 2010 | R1: 2011 | S1: 2012 | T1: 2013 | U1: 2014 | V1: 2015 | W1: 2016 | X1: 2017 | Y1: 2018 | Z1: 2019 | AA1: 2020 | AB1: 2021 | AC1: 2022 | AD1: 2023 | AE1: 2024 | AF1: 2025 | AG1: 2026 | AH1: 2027 | AI1: 2028 | AJ1: 2029 | AK1: 2030 | AL1: 2031 | AM1: 2032 | AN1: 2033 | AO1: 2034 | AP1: 2035
B2: GDPmp,t | C2: ВВП в рыночных ценах, млн. сомони | D2: 518.4 | E2: 1025.2 | F2: 1345 | G2: 1786.8 | H2: 2563.8 | I2: 3375.3 | J2: 4761.5 | K2: 6167.2 | L2: 7206.6 | M2: 9335.3 | N2: 12804.3 | O2: 17706.9 | P2: 20629 | Q2: 24707.1 | R2: 30071.1 | S2: 36163.1 | T2: 40525.2 | U2: 45606.6 | V2: =V13 -> 50977.4 | W2: =W13 -> 54790.3 | X2: =X13 -> 64434.3 | Y2: =Y13 -> 71059.2 | Z2: =Z13 -> 79109.8 | AA2: =AA13 -> 83958.3 | AB2: =AB13 -> 101076.3 | AC2: =AC13 -> 118181.7 | ... AP2: =AP13 -> 568732.06 | AS2: GDPmp,t = GDPmp,t
B3: gGDPt | C3: Реальный рост ВВП, % | D3: 101.7 | E3: 105.3 | F3: 103.7 | G3: 108.3 | H3: 109.6 | I3: 110.8 | J3: 111.1 | K3: 110.3 | L3: 106.7 | M3: 107 | N3: 107.8 | O3: 107.9 | P3: 103.9 | Q3: 106.5 | R3: 107.4 | S3: 107.5 | T3: 107.4 | U3: 106.7 | V3: =V30 -> 106 | W3: =W30 -> 106.9 | X3: =X30 -> 107.1 | Y3: =Y30 -> 106.95739 | Z3: =Z30 -> 107.44243 | AA3: =AA30 -> 104.63389 | AB3: =AB30 -> 110.98125 | AC3: =AC30 -> 108.03592 | ... AP3: =AP30 -> 108.60848 | AS3: gGDPt = gGDPmp,t
B4: defGDPt | C4: Дефлятор ВВП, % | D4: 165.22999 | E4: 187.8085 | F4: 126.51293 | G4: 122.66628 | H4: 130.91748 | I4: 118.81971 | J4: 126.97475 | K4: 117.42721 | L4: 109.5161 | M4: 121.06374 | N4: 127.23565 | O4: 128.16376 | P4: 112.12955 | Q4: 112.44802 | R4: 113.32436 | S4: 111.86852 | T4: 104.34106 | U4: 105.47223 | V4: =V64 -> 105.4494 | W4: =W64 -> 100.54218 | X4: =X64 -> 109.80547 | Y4: =Y64 -> 103.10801 | Z4: =Z64 -> 103.61775 | AA4: =AA64 -> 101.42872 | AB4: =AB64 -> 108.47661 | AC4: =AC64 -> 108.22628 | ... AP4: =AP64 -> 102.45581 | AS4: defGDPt = defGDPmp,t
B5: GDP2009mp,t | C5: ВВП в рыночных ценах 2009 года | D5: 8495.6919 | E5: 8945.9636 | F5: 9276.9643 | G5: 10046.952 | H5: 11011.46 | I5: 12200.697 | J5: 13554.975 | K5: 14951.137 | L5: 15952.863 | M5: 17069.564 | N5: 18400.99 | O5: 19854.668 | P5: 20629 | Q5: 21969.885 | R5: 23595.656 | S5: 25365.331 | T5: 27242.365 | U5: 29067.604 | V5: =V47 -> 30811.66 | W5: =W47 -> 32937.664 | X5: =X47 -> 35276.239 | Y5: =Y47 -> 37730.543 | Z5: =Z47 -> 40538.613 | AA5: =AA47 -> 42417.129 | AB5: =AB47 -> 47075.058 | AC5: =AC47 -> 50857.973 | ... AP5: =AP47 -> 144993.17 | AS5: GDP2009mp,t = GDP2009mp,t
B6: GDPPCUS,t | C6: ВВП на душу населения, долл. США | G6: 147.60889 | H6: 170.46641 | I6: 187.4139 | J6: 234.21412 | K6: 306.17541 | L6: 334.15138 | M6: 400.65841 | N6: 515.4486 | O6: 702.8013 | P6: 661.30182 | Q6: 750.4 | R6: 845.64821 | S6: 961.47143 | T6: 1053.5032 | U6: 1119.3135 | V6: =V7/Assumptions!V12 -> 978.4573 | W6: =W7/Assumptions!W12 -> 808.65537 | X6: =X7/Assumptions!X12 -> 852.82525 | Y6: =Y7/Assumptions!Y12 -> 860.01836 | Z6: =Z7/Assumptions!Z12 -> 900.31584 | AA6: =AA7/Assumptions!AA12 -> 864.39922 | AB6: =AB7/Assumptions!AB12 -> 911.84819 | AC6: =AC7/Assumptions!AC12 -> 1073.7361 | ... AP6: =AP7/Assumptions!AP12 -> 4458.2603 | AS6: GDPPCUS,t = GDPmp,t/erUSDt/POPt
C7: ВВП на душу населения, в сомони | Q7: 3285.8 | R7: 3898.1 | S7: 4579.2 | T7: 5019.1 | U7: 5523.7 | V7: 6031.7 | W7: 6336.3 | X7: 7291.4 | Y7: 7870.2 | Z7: 8580.1 | AA7: 8922.2423 | AB7: 10312 | AC7: 11838.8 | AD7: =AD2/Assumptions!AD63 -> 13039.182 | AE7: =AE2/Assumptions!AE63 -> 14981.526 | AF7: =AF2/Assumptions!AF63 -> 16684.49 | AG7: =AG2/Assumptions!AG63 -> 18464.635 | AH7: =AH2/Assumptions!AH63 -> 20375.708 | AI7: =AI2/Assumptions!AI63 -> 22515.954 | AJ7: =AJ2/Assumptions!AJ63 -> 25175.675 | AK7: =AK2/Assumptions!AK63 -> 27600.338 | ... AP7: =AP2/Assumptions!AP63 -> 46099.705
B8: ИПЦ, в том числе: (дек/дек), факт | C8: Inflation (dec/dec), fact, incl. | G8: 160.62781 | H8: 112.47905 | I8: 114.50567 | J8: 113.65265 | K8: 105.62006 | L8: 106.89379 | M8: 111.9 | N8: 121.5 | O8: 120.4 | P8: 106.4 | Q8: 106.5 | R8: 112.5 | S8: 105.8 | T8: 103.7 | U8: 107.4 | V8: =Monetary!V15 -> 105.1 | W8: =Monetary!W15 -> 106.1 | X8: =Monetary!X15 -> 106.7411 | Y8: =Monetary!Y15 -> 105.37889 | Z8: =Monetary!Z15 -> 108 | AA8: =Monetary!AA15 -> 109.4 | AB8: =Monetary!AB15 -> 108 | AC8: =Monetary!AC15 -> 104.2 | ... AP8: =Monetary!AP15 -> 104.91717
W9: =W2-V2 -> 3812.9 | X9: =X2-W2 -> 9644 | Y9: =Y2-X2 -> 6624.9 | Z9: =Z2-Y2 -> 8050.6 | AA9: =AA2-Z2 -> 4848.5 | AB9: =AB2-AA2 -> 17118 | AC9: =AC2-AB2 -> 17105.4 | AD9: =AD2-AC2 -> 14600.2 | ... AP9: =AP2-AO2 -> 57630.323
C13: ВВП в рыночных ценах, млн. сомони | D13: 518.4 | E13: 1025.2 | F13: 1345 | G13: 1786.8 | H13: 2563.8 | I13: 3375.3 | J13: 4761.5 | K13: 6167.2 | L13: 7206.6 | M13: 9335.3 | N13: 12804.3 | O13: 17706.9 | P13: 20629 | Q13: 24707.1 | R13: 30071.1 | S13: 36163.1 | T13: 40525.2 | U13: 45606.6 | V13: =V14+V15 -> 50977.4 | W13: =W14+W15 -> 54790.3 | X13: =X14+X15 -> 64434.3 | Y13: =Y14+Y15 -> 71059.2 | Z13: =Z14+Z15 -> 79109.8 | AA13: =AA14+AA15 -> 83958.3 | AB13: =AB14+AB15 -> 101076.3 | AC13: =AC14+AC15 -> 118181.7 | ... AP13: =AP14+AP15 -> 568732.06 | AS13: GDPmp,t = NITt+GDPfc,t
C14: Чистые косвенные налоги | D14: 49.8 | E14: 77.8 | F14: 98 | G14: 149.7 | H14: 230.3 | I14: 332.8 | J14: 508.4 | K14: 679.7 | L14: 831.2 | M14: 1059.7 | N14: 1603.5 | O14: 2235.9 | P14: 2286.6 | Q14: 2781.7 | R14: 3727.5 | S14: 4455.8 | T14: 5159.5 | U14: 6361.6 | V14: =5453.6-83.4 -> 5370.2 | W14: =5755.1-95 -> 5660.1 | X14: =6467.9-130.8 -> 6337.1 | Y14: =7131.5-112.4 -> 7019.1 | Z14: =7827.1-134.4 -> 7692.7 | AA14: =7718-175.3 -> 7542.7 | AB14: =9880.8-184.3 -> 9696.5 | AC14: 10687.4 | AD14: =13443.4-246.2 -> 13197.2 | AE14: =14824.4-299.5 -> 14524.9 | AF14: =18541.5-384.5 -> 18157 | AG14: =gateway!AG12 -> 18610.317 | AH14: =gateway!AH12 -> 20494.299 | AI14: =gateway!AI12 -> 21611.49 | AJ14: =gateway!AJ12 -> 21722.856 | AK14: =gateway!AK12 -> 21977.798 | AL14: =gateway!AL12 -> 22429.217 | AM14: =gateway!AM12 -> 23764.345 | AN14: =gateway!AN12 -> 26851.732 | ... AP14: =gateway!AP12 -> 34282.491 | AS14: NITt = NITt
C15: ВВП в основных ценах | D15: 468.6 | E15: 947.4 | F15: 1247 | G15: 1637.1 | H15: 2333.5 | I15: 3042.5 | J15: 4253.1 | K15: 5487.5 | L15: 6375.4 | M15: 8275.6 | N15: 11200.8 | O15: 15471 | P15: 18342 | Q15: 21925.4 | R15: 26343.6 | S15: 31707.3 | T15: 35365.7 | U15: 39245 | V15: =SUM(V16:V22) -> 45607.2 | W15: =SUM(W16:W22) -> 49130.2 | X15: =SUM(X16:X22) -> 58097.2 | Y15: =SUM(Y16:Y22) -> 64040.1 | Z15: =SUM(Z16:Z22) -> 71417.1 | AA15: =SUM(AA16:AA22) -> 76415.6 | AB15: =SUM(AB16:AB22) -> 91379.8 | AC15: =SUM(AC16:AC22) -> 107494.3 | ... AP15: =SUM(AP16:AP22) -> 534449.57 | AS15: GDPfc,t = (VAAB,t+VACDE,t+VAF,t+VAGoodsO,t+VAGH,t+VAI,t+VAOther,t)
C16: Сельское хозяйство и рыболовство | D16: 165.9 | E16: 257.4 | F16: 341.4 | G16: 448.9 | H16: 610.4 | I16: 750.5 | J16: 1151.9 | K16: 1185.6 | L16: 1527.2 | M16: 2002.6 | N16: 2488.3 | O16: 3517.9 | P16: 3827 | Q16: 4839.3 | R16: 7167.6 | S16: 8435.7 | T16: 8279.6 | U16: 10692.6 | V16: 11006.4 | W16: =11399.2+28.4 -> 11427.6 | X16: =13069.4 -> 13069.4 | Y16: 14049.8 | Z16: 16507.9 | AA16: 19050.5 | AB16: 22690.7 | AC16: 27104.8 | AD16: 30352.5 | AE16: 35915.7 | AF16: 38820.5 | AG16: =AF16*AG33*AG67/10000+1248.5 -> 44884.803 | AH16: =AG16*AH33*AH67/10000+1704.63810892211 -> 51040.391 | AI16: =AH16*AI33*AI67/10000+8291.37299199111 -> 64272.573 | AJ16: =AI16*AJ33*AJ67/10000-3122.74235819066 -> 67155.25 | AK16: =AJ16*AK33*AK67/10000-4017.1778005868 -> 69302.972 | AL16: =AK16*AL33*AL67/10000+12207.0045852159 -> 87150.42 | AM16: =AL16*AM33*AM67/10000-6139.99815483247 -> 87774.032 | AN16: =AM16*AN33*AN67/10000 -> 94607.201 | AO16: =AN16*AO33*AO67/10000 -> 101740.47 | AP16: =AO16*AP33*AP67/10000 -> 109667.71 | AS16: VAAB,t = VAAB,t-1·gVAAB,t·defVAAB,t/10000
C17: Промышленность | D17: 114 | E17: 206.1 | F17: 291.6 | G17: 592.3 | H17: 858 | I17: 1117.2 | J17: 1440.2 | K17: 1644.4 | L17: 1645.1 | M17: 1987 | N17: 2349.4 | O17: 2515.8 | P17: 2957.4 | Q17: 3642.7 | R17: 4368.9 | S17: 4947.8 | T17: 5103.1 | U17: 5510.9 | V17: =811.2+5471.4+1443.7 -> 7726.3 | W17: =1550+6233.9+1483 -> 9266.9 | X17: =2463.1+8251+2074.6+51.2 -> 12839.9 | Y17: =2528.5+9400.4+3025.7+76.9 -> 15031.5 | Z17: =2642.3+10626.3+3505.5+99.7 -> 16873.8 | AA17: =2410.7+13119.2+3890.1+91.3 -> 19511.3 | AB17: =4669.7+15160.3+4189.5+119.5 -> 24139 | AC17: =5027.2+17893.5+4728.3+113 -> 27762 | AD17: =5407.1+19402.9+4817.5+115.2 -> 29742.7 | AE17: =6456.6+20620.3+5452+137.8 -> 32666.7 | AF17: 28632 | AG17: =Industry!AG57-617.266632765852 -> 45302.801 | AH17: =Industry!AH57-4154.07814403639 -> 51435.316 | AI17: =Industry!AI57-8880.00859164027 -> 59554.869 | AJ17: =Industry!AJ57-14262.8971884416 -> 70610.731 | AK17: =Industry!AK57+2034.25522852303 -> 86152.797 | AL17: =Industry!AL57+7027.27848704623 -> 96405.531 | AM17: =Industry!AM57+35248.2981221771 -> 126812.61 | AN17: =Industry!AN57 -> 106105.21 | AO17: =Industry!AO57+1000 -> 118003.46 | AP17: =Industry!AP57+1000 -> 131259.04 | AS17: VACDE,t = VACDE,t
C18: Строительство | D18: 14.3 | E18: 39.5 | F18: 73 | G18: 38 | H18: 69.7 | I18: 68.9 | J18: 136.6 | K18: 262.3 | L18: 327.1 | M18: 567.5 | N18: 1034.6 | O18: 1832.6 | P18: 2098.4 | Q18: 2528.2 | R18: 2387.5 | S18: 3023.5 | T18: 4200.8 | U18: 4660 | V18: 7679.3 | W18: 8382.9 | X18: 7680.4 | Y18: 9411.7 | Z18: 9281.6 | AA18: 8863.7 | AB18: 11417.3 | AC18: 13250.1 | AD18: 14923.6 | AE18: 17873.3 | AF18: 12608.5 | AG18: =0.44*OEA!AG22+10484.5 -> 24902.408 | AH18: =0.49*OEA!AH22+8390.09 -> 27462.812 | AI18: =0.55*OEA!AI22+4741.75560268844 -> 29230.193 | AJ18: =0.69*OEA!AJ22-362.524 -> 35086.56 | AK18: =0.67*OEA!AK22+1692.83849206156 -> 38920.76 | AL18: =0.63*OEA!AL22+3693.52 -> 43544.138 | AM18: =0.602*OEA!AM22+3836.468 -> 47937.118 | AN18: =0.7*OEA!AN22 -> 63940.09 | AO18: =0.69*OEA!AO22 -> 78807.039 | AP18: =0.69*OEA!AP22 -> 98801.407 | AS18: VAF,t = 0,58·InvNAF,t
C19: Прочие товары | D19: 6 | E19: 10.2 | F19: 4.8 | G19: 5.9 | H19: 7.5 | I19: 13.4 | J19: 14.5 | K19: 24.2 | L19: 20.9 | M19: 20.8 | N19: 29.1 | O19: 34.9 | P19: 29.5 | Q19: 13.8 | AS19: VAGoodsO,t = VAGoodsO,t-1·VACDE,t/VACDE,t-1
C20: Розничная и оптовая торговля | D20: 108.6 | E20: 231.8 | F20: 270 | G20: 193.9 | H20: 274.9 | I20: 394.7 | J20: 544.1 | K20: 1017.5 | L20: 1191.6 | M20: 1593.8 | N20: 2119.7 | O20: 3577.3 | P20: 4345.8 | Q20: 4999.9 | R20: 3949.2 | S20: 5032.7 | T20: 5823.3 | U20: 6419.6 | V20: =4102.8+1331.1 -> 5433.9 | W20: =4625.3+1485.7 -> 6111 | X20: =6353.5 -> 6353.5 | Y20: =7359.6+1699.1 -> 9058.7 | Z20: =8764.1+1938.6 -> 10702.7 | AA20: =8978.4+1744.5 -> 10722.9 | AB20: =10956+2405.8 -> 13361.8 | AC20: =13042+3060.8 -> 16102.8 | AD20: =13851.7+3687.1 -> 17538.8 | AE20: =16467.3+4495.4 -> 20962.7 | AF20: 29189.2 | AG20: =(Household!AG3)*0.2718062-93 -> 24355.028 | AH20: =(Household!AH3-600)*0.31-4486.97 -> 27976.16 | AI20: =(Household!AI3-600)*0.29-3258 -> 31383.796 | AJ20: =(Household!AJ3)*0.29-3080.55 -> 37043.392 | AK20: =(Household!AK3)*0.31-2552.221 -> 43686.672 | AL20: =(Household!AL3-600)*0.31-1982.426 -> 47704.087 | AM20: =(Household!AM3-600)*0.31-3149.142 -> 50808.325 | AN20: =(Household!AN3-600)*0.4 -> 77729.567 | AO20: =(Household!AO3-600)*0.39 -> 81907.053 | AP20: =(Household!AP3-600)*0.38 -> 86540.154 | AS20: VAGH,t = RETt·0,447-750
C21: Транспорт и связь | D21: 15.1 | E21: 42.7 | F21: 99 | G21: 85 | H21: 127.6 | I21: 185.7 | J21: 260.2 | K21: 409 | L21: 533.3 | M21: 673.1 | N21: 1221.9 | O21: 1782.2 | P21: 2264.9 | Q21: 2758 | R21: 4356.3 | S21: 5535.2 | T21: 6172.2 | U21: 6523.8 | V21: 4859.2 | W21: 4875.2 | X21: 4870 | Y21: 4277.6 | Z21: 4829.2 | AA21: 3818.8 | AB21: =3735+1473.6 -> 5208.6 | AC21: =4401.1+1622.4 -> 6023.5 | AD21: =5272.4+1967.1 -> 7239.5 | AE21: =6358.5+2407.1 -> 8765.6 | AF21: 15892.7 | AG21: =AF21+(Household!AG9+Household!AG18-Household!AF9-Household!AF18)*0.001-4289.5 -> 11619.91 | AH21: =AG21+(Household!AH9+Household!AH18-Household!AG9-Household!AG18)*0.02+1094.44 -> 13048.297 | AI21: =AH21+(Household!AI9+Household!AI18-Household!AH9-Household!AH18)*0.02-507.6 -> 12873.957 | AJ21: =AI21+(Household!AJ9+Household!AJ18-Household!AI9-Household!AI18)*0.13+1568.47 -> 16838.971 | AK21: =AJ21+(Household!AK9+Household!AK18-Household!AJ9-Household!AJ18)*0.03+2122.039 -> 19384.193 | AL21: =AK21+(Household!AL9+Household!AL18-Household!AK9-Household!AK18)*0.09+199.3816 -> 20733.764 | AM21: =AL21+(Household!AM9+Household!AM18-Household!AL9-Household!AL18)*0.099+737.1796 -> 22913.833 | AN21: =AM21+(Household!AN9+Household!AN18-Household!AM9-Household!AM18)*0.5 -> 31369.352 | AO21: =AN21+(Household!AO9+Household!AO18-Household!AN9-Household!AN18)*0.04 -> 32179.896 | AP21: =AO21+(Household!AP9+Household!AP18-Household!AO9-Household!AO18)*0.03 -> 32811.694 | AS21: VAI,t = VAI,t-1+(RETt+SERt-RETt-1-SERt-1)·0,24
C22: Прочие услуги (остатком) | D22: 44.7 | E22: 159.7 | F22: 167.2 | G22: 273.2 | H22: 385.6 | I22: 512.2 | J22: 706.1 | K22: 945 | L22: 1130.7 | M22: 1431.2 | N22: 1958.1 | O22: 2214.2 | P22: 2823.8 | Q22: 3143.4 | R22: 4114.1 | S22: 4732.4 | T22: 5786.7 | U22: 5438.1 | V22: =2197.5+694+1492.8+2522.7+1152.2+1619.3-776.4 -> 8902.1 | W22: =1091.7+765.3+1708.6+2871.3+1292.1+1644.1-306.5 -> 9066.6 | X22: =1697.8+1533.8+1994.4+740.6+237.2+57.7+1874.8+3022.7+1359.1+296.7+736.4+275-542.2 -> 13284 | Y22: =1366.8+2078.9+791.4+237.7+60.1+2005.6+3256.3+1440.9+328.2+923.2+286-564.3 -> 12210.8 | Z22: =1424.1+1925.1+852.7+288.9+81.5+2139.9+3752.6+1651.2+366+972.3+347.6-580 -> 13221.9 | AA22: =1492.9+2157.1+1103.3+269.5+97.4+2247.4+4086.8+1842.9+408+888+462.1-607 -> 14448.4 | AB22: =2055.7+1228.9+568.4+207.9+2411.3+4778.7+2072.3+525.4+844.2+471.6-602 -> 14562.4 | AC22: =4066.6+1323+474.1+242.5+2620.7+5058.3+2146.1+571.5+1142.2+541.1-935 -> 17251.1 | AD22: =4831.1+1339.3+464.6+320.1+3473.8+6075.3+2451.3+559.2+1173.7+619.5-1520.3 -> 19787.6 | AE22: =5899.9+1692.9+665.1+351.4+4308.3+7589+3376.6+737.4+1725.8+714.2-1985.6 -> 25075 | AF22: 33619.1 | AG22: =AF22*(Household!AG18/Household!AF18)-9042.7 -> 30222.87 | AH22: =AG22*(Household!AH18/Household!AG18)-675.502 -> 33999.934 | AI22: =AH22*(Household!AI18/Household!AH18)-2727.1 -> 35683.531 | AJ22: =AI22*(Household!AJ18/Household!AI18)+3029.94 -> 42497.516 | AK22: =AJ22*(Household!AK18/Household!AJ18)-150.1586 -> 46562.406 | AL22: =AK22*(Household!AL18/Household!AK18)+845.7732 -> 50363.648 | AM22: =AL22*(Household!AM18/Household!AL18)+582.2976 -> 53960.031 | AN22: =AM22*(Household!AN18/Household!AM18) -> 59814.029 | AO22: =AN22*(Household!AO18/Household!AN18) -> 68123.424 | AP22: =AO22*(Household!AP18/Household!AO18) -> 75369.57 | AS22: VAOther,t = VAOther,t-1·(SERt/SERt-1)
C23: Справочно:
C24: Товары | D24: 300.2 | E24: 513.2 | F24: 710.8 | G24: 1085.1 | H24: 1545.6 | I24: 1950 | J24: 2743.2 | K24: 3116.5 | L24: 3520.3 | M24: 4577.9 | N24: 5901.4 | O24: 7901.2 | P24: 8912.3 | Q24: 11024 | R24: 13924 | S24: 16407 | T24: 17583.5 | U24: 20863.5 | V24: =V16+V17+V18+V19 -> 26412 | W24: =W16+W17+W18+W19 -> 29077.4 | X24: =X16+X17+X18+X19 -> 33589.7 | Y24: =Y16+Y17+Y18+Y19 -> 38493 | Z24: =Z16+Z17+Z18+Z19 -> 42663.3 | AA24: =AA16+AA17+AA18+AA19 -> 47425.5 | AB24: =AB16+AB17+AB18+AB19 -> 58247 | AC24: =AC16+AC17+AC18+AC19 -> 68116.9 | ... AP24: =AP16+AP17+AP18+AP19 -> 339728.15 | AS24: VAGoods,t = VAAB,t+VACDE,t+VAF,t+VAGoodsO,t
C25: Услуги | D25: 168.4 | E25: 434.2 | F25: 536.2 | G25: 552 | H25: 787.9 | I25: 1092.5 | J25: 1509.9 | K25: 2371 | L25: 2855.1 | M25: 3697.7 | N25: 5299.4 | O25: 7744.3 | P25: 9429.7 | Q25: 10901.3 | R25: 12419.6 | S25: 15300.3 | T25: 17782.2 | U25: 18381.5 | V25: =V20+V21+V22 -> 19195.2 | W25: =W20+W21+W22 -> 20052.8 | X25: =X20+X21+X22 -> 24507.5 | Y25: =Y20+Y21+Y22 -> 25547.1 | Z25: =Z15-Z24 -> 28753.8 | AA25: =AA15-AA24 -> 28990.1 | AB25: =AB15-AB24 -> 33132.8 | AC25: =AC15-AC24 -> 39377.4 | AD25: =AD15-AD24 -> 44565.9 | AE25: =AE15-AE24 -> 54803.3 | AF25: =AF15-AF24 -> 78701 | AG25: =AG15-AG24 -> 66197.808 | ... AP25: =AP15-AP24 -> 194721.42 | AS25: VAServces,t = GDPfc,t-VAGoods,t
V27: 5370.8 | W27: =W13-V13 -> 3812.9 | X27: =X13-W13 -> 9644 | Y27: =Y13-X13 -> 6624.9 | Z27: =Z13-Y13 -> 8050.6 | AA27: =AA13-Z13 -> 4848.5 | AB27: =AB13-AA13 -> 17118 | AC27: =AC13-AB13 -> 17105.4 | AD27: =AD13-AC13 -> 14600.2 | ... AP27: =AP13-AO13 -> 57630.323
C30: ВВП в рыночных ценах, % | D30: 101.7 | E30: 105.3 | F30: 103.7 | G30: 108.3 | H30: 109.6 | I30: 110.8 | J30: 111.1 | K30: 110.3 | L30: 106.7 | M30: 107 | N30: 107.8 | O30: 107.9 | P30: 103.9 | Q30: 106.5 | R30: 107.4 | S30: 107.5 | T30: 107.4 | U30: 106.7 | V30: 106 | W30: =(V14*W31+W32*V15)/(V14+V15) -> 106.9 | X30: =(W14*X31+X32*W15)/(W14+W15) -> 107.1 | Y30: =(X14*Y31+Y32*X15)/(X14+X15) -> 106.95739 | Z30: =(Y14*Z31+Z32*Y15)/(Y14+Y15) -> 107.44243 | AA30: =(Z14*AA31+AA32*Z15)/(Z14+Z15) -> 104.63389 | AB30: =(AA14*AB31+AB32*AA15)/(AA14+AA15) -> 110.98125 | AC30: =(AB14*AC31+AC32*AB15)/(AB14+AB15) -> 108.03592 | AD30: =(AC14*AD31+AD32*AC15)/(AC14+AC15) -> 108.31977 | ... AP30: =(AO14*AP31+AP32*AO15)/(AO14+AO15) -> 108.60848 | AS30: gGDPmp,t = (NITt-1·gNITt+gGDPfc,t·GDPfc,t-1)/(NITt-1+GDPfc,t-1)
C31: Чистые косвенные налоги | H31: 110 | I31: 111.8 | J31: 111.9 | K31: 111 | L31: 107.3 | M31: 107.4 | N31: 108.3 | O31: 107.9 | P31: 102 | Q31: 106.5 | R31: 107.4 | S31: 107.5 | T31: 107.4 | U31: 106.7 | V31: 106 | W31: 106.9 | X31: 107.1 | Y31: 104.8 | Z31: 103 | AA31: 100 | AB31: 100 | AC31: 100 | AD31: 100 | AE31: =(AE32/100)^1*100 -> 108.42918 | AF31: =(AF32/100)^1*100 -> 108.43563 | AG31: =(AG32/100)^1*100 -> 108.49433 | AH31: =(AH32/100)^1*100 -> 108.43204 | AI31: =(AI32/100)^1*100 -> 108.58847 | AJ31: =(AJ32/100)^1*100 -> 108.78201 | AK31: =(AK32/100)^1*100 -> 108.04844 | AL31: =(AL32/100)^1*100 -> 108.54826 | ... AP31: =(AP32/100)^1*100 -> 108.60848 | AS31: gNITt = (gGDPfc,t/100)^1,00·100
C32: ВВП в основных ценах | H32: 109.60139 | I32: 110.72988 | J32: 111.0332 | K32: 110.16366 | L32: 106.66415 | M32: 106.90176 | N32: 107.66178 | O32: 107.89471 | P32: 103.9 | Q32: 106.5 | R32: 107.4 | S32: 107.5 | T32: 107.4 | U32: 106.7 | V32: 106 | W32: 106.9 | X32: 107.1 | Y32: =SUMPRODUCT(Y33:Y39,X16:X22)/SUM(X16:X22) -> 107.19271 | Z32: =SUMPRODUCT(Z33:Z39,Y16:Y22)/SUM(Y16:Y22) -> 107.92934 | AA32: =SUMPRODUCT(AA33:AA39,Z16:Z22)/SUM(Z16:Z22) -> 105.13303 | AB32: =SUMPRODUCT(AB33:AB39,AA16:AA22)/SUM(AA16:AA22) -> 112.06516 | AC32: =SUMPRODUCT(AC33:AC39,AB16:AB22)/SUM(AB16:AB22) -> 108.88863 | AD32: =SUMPRODUCT(AD33:AD39,AC16:AC22)/SUM(AC16:AC22) -> 109.14694 | AE32: =SUMPRODUCT(AE33:AE39,AD16:AD22)/SUM(AD16:AD22) -> 108.42918 | AF32: =SUMPRODUCT(AF33:AF39,AE16:AE22)/SUM(AE16:AE22) -> 108.43563 | ... AP32: =SUMPRODUCT(AP33:AP39,AO16:AO22)/SUM(AO16:AO22) -> 108.60848 | AS32: gGDPfc,t = (gVAAB,t·VAAB,t-1+gVACDE,t·VACDE,t-1+gVAF,t·VAF,t-1+gVAGoodsO,t·VAGoodsO,t-1+gVAGH,t·VAGH,t-1+gVAI,t·VAI,t-1+gVAOther,t·VAOther,t-1)/(VAAB,t-1+VACDE,t-1+VAF,t-1+VAGoodsO,t-1+VAGH,t-1+VAI,t-1+VAOther,t-1)
C33: Сельское хозяйство и рыболовство | L33: 101.4 | M33: 105.7 | N33: 103.5 | O33: 106.1 | P33: 110.5 | Q33: 106.8 | R33: 107.9 | S33: 110.4 | T33: 107.6 | U33: 104.5 | V33: =Agriculture!V3 -> 103.2 | W33: =Agriculture!W3 -> 105.2 | X33: =Agriculture!X3 -> 106.8 | Y33: =Agriculture!Y3 -> 104 | Z33: =Agriculture!Z3 -> 107.1 | AA33: =Agriculture!AA3 -> 108.8 | AB33: =Agriculture!AB3 -> 106.6 | AC33: =Agriculture!AC3 -> 108 | AD33: 112.2 | AE33: =Agriculture!AE3 -> 110.6 | AF33: =Agriculture!AF3 -> 109.5 | AG33: =Agriculture!AG3 -> 108.91987 | AH33: =Agriculture!AH3 -> 108.61303 | AI33: =Agriculture!AI3 -> 108.27265 | AJ33: =Agriculture!AJ3 -> 108.15398 | AK33: =Agriculture!AK3 -> 108.31356 | AL33: =Agriculture!AL3 -> 107.60081 | ... AP33: =Agriculture!AP3 -> 107.25535 | AS33: gVAAB,t = (1+gVAAB,t/100)·100
C34: Промышленность | L34: 106.4 | M34: 105.5 | N34: 109.9 | O34: 96.5 | P34: 93.5 | Q34: 109.2 | R34: 105.7 | S34: 110.8 | T34: 103.8 | U34: 105 | V34: =Industry!V58 -> 111.3 | W34: =Industry!W58 -> 116 | X34: =Industry!X58 -> 121.3 | Y34: =Industry!Y58 -> 110.6 | Z34: =Industry!Z58 -> 113.2 | AA34: =Industry!AA58 -> 108.8 | AB34: =Industry!AB58 -> 120.8 | AC34: =Industry!AC58 -> 115.4 | AD34: 109.7 | AE34: =Industry!AE58 -> 120 | AF34: =Industry!AF58 -> 122.1 | AG34: =Industry!AG58 -> 125.02097 | AH34: =Industry!AH58 -> 125.0001 | AI34: =Industry!AI58 -> 125.10772 | AJ34: =Industry!AJ58 -> 125.0738 | AK34: =Industry!AK58 -> 119.95581 | AL34: =Industry!AL58 -> 119.92603 | ... AP34: =Industry!AP58 -> 122.3396 | AS34: gVACDE,t = gVACDE,t
C35: Строительство | L35: 116.4 | M35: 107.2 | N35: 110.4 | O35: 121.2 | P35: 84.5 | Q35: 109.52934 | R35: 105.5 | S35: 75.6 | T35: 117.2 | U35: 125.3 | V35: =OEA!V39 -> 121.2 | W35: =OEA!W39 -> 120.3 | X35: =OEA!X39 -> 104.1 | Y35: =OEA!Y39 -> 110.2 | Z35: =OEA!Z39 -> 104.6 | AA35: =OEA!AA39 -> 104 | AB35: 132.1 | AC35: =OEA!AC39 -> 111.4 | AD35: =OEA!AD39 -> 112.3 | AE35: =OEA!AE39 -> 114.38905 | AF35: =OEA!AF39 -> 68.092444 | AG35: =OEA!AG39 -> 173.24993 | AH35: =OEA!AH39 -> 116.08606 | AI35: =OEA!AI39 -> 110.87036 | AJ35: =OEA!AJ39 -> 125.03681 | ... AP35: =OEA!AP39 -> 130.5951 | AS35: gVAF,t = gCONSTRt
C36: Прочие товары | L36: 100 | M36: 100 | N36: 110.2 | O36: 100 | P36: 100 | Q36: 109.2 | R36: 105.7 | S36: 110.8 | T36: 103.8 | U36: 105 | V36: =V34 -> 111.3 | W36: =W34 -> 116 | X36: =X34 -> 121.3 | Y36: =Y34 -> 110.6 | Z36: =Z34 -> 113.2 | AA36: =AA34 -> 108.8 | AB36: =AB34 -> 120.8 | AC36: =AC34 -> 115.4 | ... AP36: =AP34 -> 122.3396 | AS36: gVAGoodsO,t = gVACDE,t
C37: Розничная и оптовая торговля | L37: 108.9 | M37: 110.8 | N37: 105.3 | O37: 112.4 | P37: 112.5 | Q37: 107.5 | R37: 109.1 | S37: 115.9 | T37: 118.8 | U37: 106.7 | V37: 105.6 | W37: 106 | X37: 106.6 | Y37: 112.2 | Z37: 109.6 | AA37: 94.1 | AB37: 110.2 | AC37: =Household!AC4 -> 111.2 | AD37: 98.6 | AE37: =Household!AE4 -> 113.6 | AF37: =Household!AF4 -> 113.9 | AG37: =Household!AG4 -> 114.32794 | AH37: =Household!AH4 -> 114.46523 | AI37: =Household!AI4 -> 113.63166 | AJ37: =Household!AJ4 -> 113.89224 | AK37: =Household!AK4 -> 108.36872 | AL37: =Household!AL4 -> 109.84897 | ... AP37: =Household!AP4 -> 106.39789 | AS37: gVAGH,t = VAGH,t/VAGH,t-1/defVAGH,t·10000
C38: Транспорт и связь | L38: 130 | M38: 118.1 | N38: 183.8 | O38: 143.3 | P38: 153.5 | Q38: 119.39626 | R38: 150.89372 | S38: 124.05492 | T38: 110.30013 | U38: 105.11255 | V38: 102.1 | W38: =(W21/V21)^0.4*100 -> 100.13158 | X38: =(X21/W21)^3*100 -> 99.680354 | Y38: 93.3 | Z38: 115.7 | AA38: 79.4 | AB38: 95.3 | AC38: 96 | AD38: 121.7 | AE38: =(AE21/AD21)^0.82*100 -> 116.98224 | AF38: =(AF21/AE21)^0.54*100 -> 137.89377 | AG38: =(AG21/AF21)^2.85*100 -> 40.965148 | AH38: =(AH21/AG21)^0.2*100 -> 102.34584 | AI38: =(AI21/AH21)^1.22*100 -> 98.372346 | AJ38: =(AJ21/AI21)^0.11*100 -> 102.99743 | AK38: =(AK21/AJ21)^0.1*100 -> 101.41757 | AL38: =(AL21/AK21)^0.2*100 -> 101.35521 | AM38: =(AM21/AL21)^0.1*100 -> 101.00479 | AN38: =(AN21/AM21)^1.22*100 -> 146.69575 | AO38: =(AO21/AN21)^1.22*100 -> 103.16122 | AP38: =(AP21/AO21)^1.22*100 -> 102.40041 | AS38: gVAI,t = (VAI,t/VAI,t-1)^0,9·100
C39: Прочие услуги (остатком) | L39: 97.001641 | M39: 96.376863 | N39: 78.00434 | O39: 92.627551 | P39: 73.250437 | Q39: 93 | R39: 97 | S39: 95 | T39: 95 | U39: 102 | V39: 97 | W39: 97 | X39: 101 | Y39: 108 | Z39: 101 | AA39: 115 | AB39: 101 | AC39: 100 | AD39: 106.5 | AE39: 75.5 | AF39: 103 | AG39: 96.5 | AH39: 74.5 | AI39: 82 | AJ39: 67 | AK39: 84 | AL39: 84 | AM39: 82 | AN39: 57 | AO39: 92.5 | AP39: 67 | AS39: gVAOther,t = gVAOther,t
C40: Справочно:
C41: Товары | H41: 112.4 | I41: 111 | J41: 111.5 | K41: 105.3 | L41: 105.8 | M41: 105.2 | N41: 104.4 | O41: 103.4 | P41: 99 | Q41: 106.1 | R41: 106.9 | S41: 103.6 | T41: 105.9 | U41: 112.2 | V41: 109.7 | W41: 114.1 | X41: 107.4 | Y41: =SUMPRODUCT(Y33:Y36,X16:X19)/SUM(X16:X19) -> 107.94055 | Z41: =SUMPRODUCT(Z33:Z36,Y16:Y19)/SUM(Y16:Y19) -> 108.87079 | AA41: =SUMPRODUCT(AA33:AA36,Z16:Z19)/SUM(Z16:Z19) -> 107.75574 | AB41: =SUMPRODUCT(AB33:AB36,AA16:AA19)/SUM(AA16:AA19) -> 117.2079 | AC41: =SUMPRODUCT(AC33:AC36,AB16:AB19)/SUM(AB16:AB19) -> 111.7332 | AD41: =SUMPRODUCT(AD33:AD36,AC16:AC19)/SUM(AC16:AC19) -> 111.20054 | AE41: =SUMPRODUCT(AE33:AE36,AD16:AD19)/SUM(AD16:AD19) -> 115.08058 | AF41: =SUMPRODUCT(AF33:AF36,AE16:AE19)/SUM(AE16:AE19) -> 105.70049 | ... AP41: =SUMPRODUCT(AP33:AP36,AO16:AO19)/SUM(AO16:AO19) -> 119.37834 | AS41: gVAGoods,t = (gVAAB,t·VAAB,t-1+gVACDE,t·VACDE,t-1+gVAF,t·VAF,t-1+gVAGoodsO,t·VAGoodsO,t-1)/(VAAB,t-1+VACDE,t-1+VAF,t-1+VAGoodsO,t-1)
C42: Услуги | H42: 104.1 | I42: 110.2 | J42: 110.2 | K42: 119 | L42: 107.8 | M42: 109 | N42: 111.7 | O42: 112.9 | P42: 109.7 | Q42: 106.9 | R42: 107.7 | S42: 112 | T42: 109.1 | U42: 101.2 | V42: 101.7 | W42: 98.9 | X42: 106.6 | Y42: =(Y37*X20+X21*Y38+Y39*X22)/X25 -> 106.16773 | Z42: =(Z37*Y20+Y21*Z38+Z39*Y22)/Y25 -> 106.51082 | AA42: =(AA37*Z20+Z21*AA38+AA39*Z22)/Z25 -> 101.24161 | AB42: =(AB37*AA20+AA21*AB38+AB39*AA22)/AA25 -> 103.65206 | AC42: =(AC37*AB20+AB21*AC38+AC39*AB22)/AB25 -> 103.88792 | AD42: =(AD37*AC20+AC21*AD38+AD39*AC22)/AC25 -> 105.59453 | AE42: =(AE37*AD20+AD21*AE38+AE39*AD22)/AD25 -> 97.232736 | AF42: =(AF37*AE20+AE21*AF38+AF39*AE22)/AE25 -> 112.75048 | ... AP42: =(AP37*AO20+AO21*AP38+AP39*AO22)/AO25 -> 90.962117 | AS42: gVAServces,t = (gVAGH,t·VAGH,t-1+VAI,t-1·gVAI,t+gVAOther,t·VAOther,t-1)/VAServces,t-1
C46: В постоянных ценах 2009 года, млн. сомони
C47: ВВП в рыночных ценах 2009 года | G47: 10046.952 | H47: 11011.46 | I47: 12200.697 | J47: 13554.975 | K47: 14951.137 | L47: 15952.863 | M47: 17069.564 | N47: 18400.99 | O47: 19854.668 | P47: 20629 | Q47: 21969.885 | R47: 23595.656 | S47: 25365.331 | T47: 27242.365 | U47: 29067.604 | V47: 30811.66 | W47: =V47*W30/100 -> 32937.664 | X47: =W47*X30/100 -> 35276.239 | Y47: =X47*Y30/100 -> 37730.543 | Z47: =Y47*Z30/100 -> 40538.613 | AA47: =Z47*AA30/100 -> 42417.129 | AB47: =AA47*AB30/100 -> 47075.058 | AC47: =AB47*AC30/100 -> 50857.973 | AD47: =AC47*AD30/100 -> 55089.238 | ... AP47: =AO47*AP30/100 -> 144993.17 | AS47: GDP2009mp,t = GDP2009mp,t-1·gGDPmp,t/100
C48: Чистые косвенные налоги | H48: 1198.9946 | I48: 1340.4759 | J48: 1499.9926 | K48: 1664.9918 | L48: 1786.5362 | M48: 1918.7398 | N48: 2077.9952 | O48: 2242.1569 | P48: 2287 | Q48: 2435.655 | R48: 2615.8935 | S48: 2812.0855 | T48: 3020.1798 | U48: 3222.5319 | V48: 3415.8838 | W48: =V48*W31/100 -> 3651.5797 | X48: =W48*X31/100 -> 3910.8419 | Y48: =X48*Y31/100 -> 4098.5623 | Z48: =Y48*Z31/100 -> 4221.5192 | AA48: =Z48*AA31/100 -> 4221.5192 | AB48: =AA48*AB31/100 -> 4221.5192 | AC48: =AB48*AC31/100 -> 4221.5192 | AD48: =AC48*AD31/100 -> 4221.5192 | ... AP48: =AO48*AP31/100 -> 11110.908 | AS48: NIT2009t = NIT2009t-1·gNITt/100
C49: ВВП в основных ценах | K49: 13293.54 | L49: 14180.584 | M49: 15155.605 | N49: 16320.036 | O49: 17598.221 | P49: 18342 | Q49: 19534.23 | R49: 20979.763 | S49: 22553.245 | T49: 24222.185 | U49: 25845.072 | V49: 27395.776 | W49: =V49*W32/100 -> 29286.085 | X49: =W49*X32/100 -> 31365.397 | Y49: =X49*Y32/100 -> 33621.419 | Z49: =Y49*Z32/100 -> 36287.376 | AA49: =Z49*AA32/100 -> 38150.019 | AB49: =AA49*AB32/100 -> 42752.882 | AC49: =AB49*AC32/100 -> 46553.027 | AD49: =AC49*AD32/100 -> 50811.206 | ... AP49: =AO49*AP32/100 -> 133733.53 | AS49: GDP2009fc,t = GDP2009fc,t-1·gGDPfc,t/100
C50: Сельское хозяйство и рыболовство | K50: 4438.6239 | L50: 4722.6959 | M50: 4921.0491 | N50: 4492.9178 | O50: 4093.0481 | P50: 3827 | Q50: 4087.236 | R50: 4410.1276 | S50: 4868.7809 | T50: 5238.8083 | U50: 5474.5546 | V50: 5649.7404 | W50: =V50*W33/100 -> 5943.5269 | X50: =W50*X33/100 -> 6347.6867 | Y50: =X50*Y33/100 -> 6601.5942 | Z50: =Y50*Z33/100 -> 7070.3074 | AA50: =Z50*AA33/100 -> 7692.4944 | AB50: =AA50*AB33/100 -> 8200.1991 | AC50: =AB50*AC33/100 -> 8856.215 | AD50: =AC50*AD33/100 -> 9936.6732 | ... AP50: =AO50*AP33/100 -> 25719.752 | AS50: VA2009AB,t = VA2009AB,t-1·gVAAB,t/100
C51: Промышленность | K51: 2181.227 | L51: 2211.7641 | M51: 2331.1994 | N51: 2482.7274 | O51: 2676.3801 | P51: 2957.4 | Q51: 3229.4808 | R51: 3413.5612 | S51: 3782.2258 | T51: 3925.9504 | U51: 4122.2479 | V51: 4588.0619 | W51: =V51*W34/100 -> 5322.1518 | X51: =W51*X34/100 -> 6455.7702 | Y51: =X51*Y34/100 -> 7140.0818 | Z51: =Y51*Z34/100 -> 8082.5726 | AA51: =Z51*AA34/100 -> 8793.839 | AB51: =AA51*AB34/100 -> 10622.958 | AC51: =AB51*AC34/100 -> 12258.893 | AD51: =AC51*AD34/100 -> 13448.006 | ... AP51: =AO51*AP34/100 -> 123723.36 | AS51: VA2009CDE,t = VA2009CDE,t-1·gVACDE,t/100
C52: Строительство | K52: 1487.3463 | L52: 1731.2711 | M52: 1855.9227 | N52: 2048.9386 | O52: 2483.3136 | P52: 2098.4 | Q52: 2298.3636 | R52: 2424.7736 | S52: 1833.1289 | T52: 2148.427 | U52: 2691.9791 | V52: 3262.6786 | W52: =V52*W35/100 -> 3925.0024 | X52: =W52*X35/100 -> 4085.9275 | Y52: =X52*Y35/100 -> 4502.6921 | Z52: =Y52*Z35/100 -> 4709.8159 | AA52: =Z52*AA35/100 -> 4898.2086 | AB52: =AA52*AB35/100 -> 6470.5335 | AC52: =AB52*AC35/100 -> 7208.1744 | AD52: =AC52*AD35/100 -> 8094.7798 | ... AP52: =AO52*AP35/100 -> 63239.701 | AS52: VA2009F,t = VA2009F,t-1·gVAF,t/100
C53: Прочие товары | AS53: VA2009GoodsO,t = VA2009GoodsO,t-1·gVAGoodsO,t/100
C54: Розничная и оптовая торговля | K54: 2430.5119 | L54: 2646.8275 | M54: 3094.1414 | N54: 3449.9676 | O54: 3936.413 | P54: 4345.8 | Q54: 4671.735 | R54: 5096.8629 | S54: 5907.2641 | T54: 7017.8297 | U54: 7488.0243 | V54: 7907.3537 | W54: =V54*W37/100 -> 8381.7949 | X54: =W54*X37/100 -> 8934.9934 | Y54: =X54*Y37/100 -> 10025.063 | Z54: =Y54*Z37/100 -> 10987.469 | AA54: =Z54*AA37/100 -> 10339.208 | AB54: =AA54*AB37/100 -> 11393.807 | AC54: =AB54*AC37/100 -> 12669.914 | AD54: =AC54*AD37/100 -> 12492.535 | ... AP54: =AO54*AP37/100 -> 43986.956 | AS54: VA2009GH,t = VA2009GH,t-1·gVAGH,t/100
C55: Транспорт и связь | K55: 364.88474 | L55: 474.35017 | M55: 560.20755 | N55: 1029.6615 | O55: 1475.5049 | P55: 2264.9 | Q55: 2704.2058 | R55: 4080.4767 | S55: 5062.032 | T55: 5583.4277 | U55: 5868.8834 | V55: 5992.1299 | W55: =V55*W38/100 -> 6000.0143 | X55: =W55*X38/100 -> 5980.8355 | Y55: =X55*Y38/100 -> 5580.1195 | Z55: =Y55*Z38/100 -> 6456.1983 | AA55: =Z55*AA38/100 -> 5126.2214 | AB55: =AA55*AB38/100 -> 4885.289 | AC55: =AB55*AC38/100 -> 4689.8775 | AD55: =AC55*AD38/100 -> 5707.5809 | ... AP55: =AO55*AP38/100 -> 6292.7108 | AS55: VA2009I,t = VA2009I,t-1·gVAI,t/100
C56: Прочие услуги (остатком) | K56: 5707.0661 | L56: 5535.9477 | M56: 5335.3727 | N56: 4161.8223 | O56: 3854.9941 | P56: 2823.8 | Q56: 2626.134 | R56: 2547.35 | S56: 2419.9825 | T56: 2298.9834 | U56: 2344.963 | V56: 2274.6141 | W56: =V56*W39/100 -> 2206.3757 | X56: =W56*X39/100 -> 2228.4395 | Y56: =X56*Y39/100 -> 2406.7146 | Z56: =Y56*Z39/100 -> 2430.7818 | AA56: =Z56*AA39/100 -> 2795.399 | AB56: =AA56*AB39/100 -> 2823.353 | AC56: =AB56*AC39/100 -> 2823.353 | AD56: =AC56*AD39/100 -> 3006.871 | ... AP56: =AO56*AP39/100 -> 188.77089 | AS56: VA2009Other,t = VA2009Other,t-1·gVAOther,t/100
C57: Справочно:
C58: Товары | H58: 5749.1805 | I58: 6381.5903 | J58: 7115.4732 | K58: 7492.5933 | L58: 7927.1637 | M58: 8339.3762 | N58: 8706.3087 | O58: 9002.3232 | P58: 8912.3 | Q58: 9280.3927 | R58: 9920.7398 | S58: 10277.886 | T58: 10884.282 | U58: 12212.164 | V58: 13396.744 | W58: =V58*W41/100 -> 15285.685 | X58: =W58*X41/100 -> 16416.826 | Y58: =X58*Y41/100 -> 17720.412 | Z58: =Y58*Z41/100 -> 19292.351 | AA58: =Z58*AA41/100 -> 20788.616 | AB58: =AA58*AB41/100 -> 24365.899 | AC58: =AB58*AC41/100 -> 27224.798 | AD58: =AC58*AD41/100 -> 30274.123 | ... AP58: =AO58*AP41/100 -> 170360.74 | AS58: VA2009Goods,t = VA2009Goods,t-1·gVAGoods,t/100
C59: Услуги | H59: 4014.105 | I59: 4423.5437 | J59: 4874.7451 | K59: 5800.9467 | L59: 6253.4205 | M59: 6816.2284 | N59: 7613.7271 | O59: 8595.8979 | P59: 9429.7 | Q59: 10783.19 | R59: 11613.496 | S59: 13007.115 | T59: 14190.763 | U59: 14361.052 | V59: 14605.19 | W59: =V59*W42/100 -> 14444.533 | X59: =W59*X42/100 -> 15397.872 | Y59: =X59*Y42/100 -> 16347.571 | Z59: =Y59*Z42/100 -> 17411.933 | AA59: =Z59*AA42/100 -> 17628.121 | AB59: =AA59*AB42/100 -> 18271.911 | AC59: =AB59*AC42/100 -> 18982.309 | AD59: =AC59*AD42/100 -> 20044.28 | ... AP59: =AO59*AP42/100 -> 13030.719 | AS59: VA2009Services,t = VA2009Services,t-1·gVAServces,t/100
C63: Дефляторы, %
C64: ВВП в рыночных ценах, % | H64: 130.91748 | I64: 118.81971 | J64: 126.97475 | K64: 117.42721 | L64: 109.5161 | M64: 121.06374 | N64: 127.23565 | O64: 128.16376 | P64: 112.12955 | Q64: 112.45894 | R64: 113.32436 | S64: 111.86852 | T64: 104.34106 | U64: 105.47223 | V64: 105.4494 | W64: =W13/V13/W30*10000 -> 100.54218 | X64: =X13/W13/X30*10000 -> 109.80547 | Y64: =Y13/X13/Y30*10000 -> 103.10801 | Z64: =Z13/Y13/Z30*10000 -> 103.61775 | AA64: =AA13/Z13/AA30*10000 -> 101.42872 | AB64: =AB13/AA13/AB30*10000 -> 108.47661 | AC64: =AC13/AB13/AC30*10000 -> 108.22628 | AD64: =AD13/AC13/AD30*10000 -> 103.7244 | AE64: =AE13/AD13/AE30*10000 -> 108.20255 | AF64: =AF13/AE13/AF30*10000+1.7 -> 106.43212 | AG64: =AG13/AF13/AG30*10000 -> 104.14231 | AH64: =AH13/AG13/AH30*10000+0.1 -> 104.11542 | AI64: =AI13/AH13/AI30*10000 -> 103.9988 | AJ64: =AJ13/AI13/AJ30*10000+0.1 -> 105.14926 | AK64: =AK13/AJ13/AK30*10000+0.3 -> 103.99465 | AL64: =AL13/AK13/AL30*10000 -> 104.09122 | AM64: =AM13/AL13/AM30*10000 -> 103.9998 | AN64: =AN13/AM13/AN30*10000 -> 102.88509 | AO64: =AO13/AN13/AO30*10000 -> 102.54921 | AP64: =AP13/AO13/AP30*10000 -> 102.45581 | AS64: defGDPmp,t = GDPmp,t/GDPmp,t-1/gGDPmp,t·10000
C65: Чистые косвенные налоги | L65: 113.96947 | M65: 118.70612 | N65: 139.71968 | O65: 129.22959 | P65: 100.2623 | Q65: 114.22745 | R65: 118.9 | S65: 111.19866 | T65: 107.81462 | U65: 115.55648 | V65: 79.637613 | W65: =W14/V14/W31*10000 -> 98.595238 | X65: =X14/W14/X31*10000 -> 104.53867 | Y65: 105.2 | Z65: 106.6 | AA65: 98.7 | AB65: =AB14/AA14/AB31*10000 -> 128.55476 | AC65: =AC14/AB14/AC31*10000 -> 110.21915 | AD65: =AD14/AC14/AD31*10000 -> 123.48373 | AE65: =AE14/AD14/AE31*10000 -> 101.50447 | AF65: =AF14/AE14/AF31*10000 -> 115.28132 | AG65: =AG14/AF14/AG31*10000 -> 94.471898 | AH65: =AH14/AG14/AH31*10000 -> 101.55975 | AI65: =AI14/AH14/AI31*10000 -> 97.11089 | ... AP65: =AP14/AO14/AP31*10000 -> 104.0369 | AS65: defNITt = NITt/NITt-1/gNITt·10000
C66: ВВП в основных ценах | L66: 108.92171 | M66: 121.42475 | N66: 125.71526 | O66: 128.01746 | P66: 114.10712 | Q66: 112.24092 | R66: 111.87249 | S66: 111.9633 | T66: 103.85292 | U66: 104.00103 | V66: 109.63348 | W66: =W15/V15/W32*10000 -> 100.77143 | X66: =X15/W15/X32*10000 -> 110.41223 | Y66: =Y15/X15/Y32*10000 -> 102.83277 | Z66: =Z15/Y15/Z32*10000 -> 103.32625 | AA66: =AA15/Z15/AA32*10000 -> 101.77488 | AB66: =AB15/AA15/AB32*10000 -> 106.70814 | AC66: =AC15/AB15/AC32*10000 -> 108.03207 | AD66: =AD15/AC15/AD32*10000 -> 101.9245 | ... AP66: =AP15/AO15/AP32*10000 -> 102.35603 | AS66: defGDPfc,t = GDPfc,t/GDPfc,t-1/gGDPfc,t·10000
C67: Сельское хозяйство и рыболовство | L67: 127.03394 | M67: 124.05758 | N67: 120.05166 | O67: 133.24943 | P67: 98.449314 | Q67: 118.40031 | R67: 137.26815 | S67: 106.60518 | T67: 91.217036 | U67: 123.5827 | V67: 99.742965 | W67: =W16/V16/W33*10000 -> 98.694738 | X67: =X16/W16/X33*10000 -> 107.08518 | Y67: =Y16/X16/Y33*10000 -> 103.36682 | Z67: =Z16/Y16/Z33*10000 -> 109.70646 | AA67: =AA16/Z16/AA33*10000 -> 106.06831 | AB67: =AB16/AA16/AB33*10000 -> 111.73373 | AC67: =AC16/AB16/AC33*10000 -> 110.60495 | AD67: =AD16/AC16/AD33*10000 -> 99.805714 | ... AF67: =AF16/AE16/AF33*10000 -> 98.710345 | AG67: =Assumptions!AG57+100 -> 103.2 | AH67: =Assumptions!AH57+100 -> 101.2 | AI67: =Assumptions!AI57+100 -> 101.3 | AJ67: =Assumptions!AJ57+100 -> 101.1 | AK67: =Assumptions!AK57+100 -> 100.8 | AL67: =Assumptions!AL57+100 -> 100.5 | AM67: =Assumptions!AM57+100 -> 100.2 | AN67: =Assumptions!AN57+100 -> 100.5 | ... AP67: =Assumptions!AP57+100 -> 100.5 | AS67: defVAAB,t = defVAAB,t+100
C68: Промышленность | L68: 94.024971 | M68: 114.48619 | N68: 107.5874 | O68: 110.96649 | P68: 125.7252 | Q68: 112.79522 | R68: 113.46808 | S68: 102.21162 | T68: 99.362976 | U68: 102.84878 | V68: 125.96615 | W68: =W17/V17/W34*10000 -> 103.39628 | X68: =X17/W17/X34*10000 -> 114.22637 | Y68: =Y17/X17/Y34*10000 -> 105.84871 | Z68: =Z17/Y17/Z34*10000 -> 99.166309 | AA68: =AA17/Z17/AA34*10000 -> 106.27825 | AB68: =AB17/AA17/AB34*10000 -> 102.4156 | AC68: =AC17/AB17/AC34*10000 -> 99.661098 | AD68: =AD17/AC17/AD34*10000 -> 97.661415 | ... AP68: =AP17/AO17/AP34*10000 -> 90.921668 | AS68: defVACDE,t = VACDE,t/VACDE,t-1/gVACDE,t·10000
C69: Строительство | L69: 107.13448 | M69: 161.84174 | N69: 165.13439 | O69: 146.1479 | P69: 135.50767 | Q69: 110 | R69: 89.511636 | S69: 167.51157 | T69: 118.54805 | U69: 88.532523 | V69: 135.96687 | W69: =W18/V18/W35*10000 -> 90.741724 | X69: =X18/W18/X35*10000 -> 88.011379 | Y69: =Y18/X18/Y35*10000 -> 111.19945 | Z69: =Z18/Y18/Z35*10000 -> 94.280763 | AA69: =AA18/Z18/AA35*10000 -> 91.824561 | AB69: =AB18/AA18/AB35*10000 -> 97.509189 | AC69: =AC18/AB18/AC35*10000 -> 104.17669 | AD69: =AD18/AC18/AD35*10000 -> 100.29394 | ... AP69: =AP18/AO18/AP35*10000 -> 96 | AS69: defVAF,t = VAF,t/VAF,t-1/gVAF,t·10000
C70: Прочие товары | L70: 86.363636 | M70: 99.521531 | AS70: defVAGoodsO,t = VAGoodsO,t/VAGoodsO,t-1/gVAGoodsO,t·10000
C71: Розничная и оптовая торговля | L71: 107.57262 | M71: 111.11833 | N71: 120.71607 | O71: 120.39902 | P71: 105.22753 | Q71: 101.6039 | R71: 113.18213 | S71: 105.78988 | T71: 97.398368 | U71: 103.31762 | V71: 80.156686 | W71: =W20/V20/W37*10000 -> 106.09497 | X71: =X20/W20/X37*10000 -> 97.531195 | Y71: =Y20/X20/Y37*10000 -> 127.07496 | Z71: =Z20/Y20/Z37*10000 -> 107.79954 | AA71: =AA20/Z20/AA37*10000 -> 106.4705 | AB71: =AB20/AA20/AB37*10000 -> 113.07618 | AC71: =AC20/AB20/AC37*10000 -> 108.37563 | AD71: =AD20/AC20/AD37*10000 -> 110.4642 | ... AF71: =AF20/AE20/AF37*10000 -> 122.25067 | AG71: =Household!AG12 -> 105.06834 | AH71: =Household!AH12 -> 101.8944 | AI71: =Household!AI12 -> 100.61574 | AJ71: =Household!AJ12 -> 100.68896 | AK71: =Household!AK12 -> 100.48009 | AL71: =Household!AL12 -> 100.28787 | AM71: =Household!AM12 -> 101.19989 | AN71: =Household!AN12 -> 103.95869 | ... AP71: =Household!AP12 -> 103.79388 | AS71: defVAGH,t = defRETt
C72: Транспорт и связь | L72: 100.30092 | M72: 106.87057 | N72: 98.766705 | O72: 101.78284 | P72: 82.791207 | Q72: 101.98928 | R72: 104.67726 | S72: 102.42396 | T72: 101.09523 | U72: 100.55555 | V72: 72.9522 | W72: =W21/V21/W38*10000 -> 100.19743 | X72: =X21/W21/X38*10000 -> 100.21367 | Y72: =Y21/X21/Y38*10000 -> 94.143332 | Z72: =Z21/Y21/Z38*10000 -> 97.575697 | AA72: =AA21/Z21/AA38*10000 -> 99.593551 | AB72: =AB21/AA21/AB38*10000 -> 143.12028 | AC72: =AC21/AB21/AC38*10000 -> 120.46383 | AD72: =AD21/AC21/AD38*10000 -> 98.757271 | ... AP72: =AP21/AO21/AP38*10000 -> 99.573166 | AS72: defVAI,t = VAI,t/VAI,t-1/gVAI,t·10000
C73: Прочие услуги (остатком) | L73: 123.34925 | M73: 131.3349 | N73: 175.39442 | O73: 122.07923 | P73: 174.10325 | Q73: 119.69686 | R73: 134.92843 | S73: 121.08295 | T73: 128.71404 | U73: 92.133178 | V73: 168.76157 | W73: =W22/V22/W39*10000 -> 104.99781 | X73: =X22/W22/X39*10000 -> 145.06513 | Y73: =Y22/X22/Y39*10000 -> 85.112137 | Z73: =Z22/Y22/Z39*10000 -> 107.20829 | AA73: =AA22/Z22/AA39*10000 -> 95.022849 | AB73: =AB22/AA22/AB39*10000 -> 99.791104 | AC73: =AC22/AB22/AC39*10000 -> 118.4633 | AD73: =AD22/AC22/AD39*10000 -> 107.70273 | ... AP73: =AP22/AO22/AP39*10000 -> 165.12954 | AS73: defVAOther,t = VAOther,t/VAOther,t-1/gVAOther,t·10000
C74: Справочно:
C75: Товары | L75: 106.7645 | M75: 123.61492 | N75: 123.47762 | O75: 129.4844 | P75: 113.93615 | Q75: 116.58268 | R75: 137.9 | S75: 113.73795 | T75: 101.19992 | U75: 105.7521 | V75: 115.40045 | W75: =W24/V24/W41*10000 -> 96.486963 | X75: =X24/W24/X41*10000 -> 107.55888 | Y75: =Y24/X24/Y41*10000 -> 106.16736 | Z75: =Z24/Y24/Z41*10000 -> 101.80318 | AA75: =AA24/Z24/AA41*10000 -> 103.16136 | AB75: =AB24/AA24/AB41*10000 -> 104.78636 | AC75: =AC24/AB24/AC41*10000 -> 104.66443 | AD75: =AD24/AC24/AD41*10000 -> 99.039476 | ... AP75: =AP24/AO24/AP41*10000 -> 95.320763 | AS75: defVAGoods,t = VAGoods,t/VAGoods,t-1/gVAGoods,t·10000
C76: Услуги | L76: 111.70459 | M76: 118.81844 | N76: 128.30449 | O76: 129.43792 | P76: 110.99645 | Q76: 108.14407 | R76: 102.8 | S76: 110 | T76: 106.52727 | U76: 102.14449 | V76: 102.68115 | W76: =W25/V25/W42*10000 -> 105.62971 | X76: =X25/W25/X42*10000 -> 114.64808 | Y76: =Y25/X25/Y42*10000 -> 98.18611 | Z76: =Z25/Y25/Z42*10000 -> 105.67199 | AA76: =AA25/Z25/AA42*10000 -> 99.585341 | AB76: =AB25/AA25/AB42*10000 -> 110.26317 | AC76: =AC25/AB25/AC42*10000 -> 114.39942 | AD76: =AD25/AC25/AD42*10000 -> 107.18011 | ... AP76: =AP25/AO25/AP42*10000 -> 117.48436 | AS76: defVAServces,t = VAServces,t/VAServces,t-1/gVAServces,t·10000
C77: структура ВВП | AS77: 2021 | AT77: 2022 | AU77: 2023 | AV77: 2024 | AW77: 2025 | AX77: 2026
C78: ВВП в рыночных ценах, % | L78: 100.00694 | M78: 100.00428 | N78: 100.00234 | O78: 100.02203 | P78: 100.02133 | Q78: 99.999595 | R78: 100 | S78: 100 | T78: 100 | U78: 100 | V78: =V79+V80 -> 100 | W78: =W79+W80 -> 100 | X78: =X79+X80 -> 100 | Y78: =Y79+Y80 -> 100 | Z78: =Z79+Z80 -> 100 | AA78: =AA79+AA80 -> 100 | AB78: =AB79+AB80 -> 100 | AC78: =AC79+AC80 -> 100 | ... AP78: =AP79+AP80 -> 100 | AS78: =AS79+AS81+AS82+AS83+AS85+AS86+AS87 -> 0 | AT78: =AT79+AT81+AT82+AT83+AT85+AT86+AT87 -> 0 | AU78: =AU79+AU81+AU82+AU83+AU85+AU86+AU87 -> 0 | AV78: =AV79+AV81+AV82+AV83+AV85+AV86+AV87 -> 0 | AW78: =AW79+AW81+AW82+AW83+AW85+AW86+AW87 -> 0 | AX78: =AX79+AX81+AX82+AX83+AX85+AX86+AX87 -> 0
C79: Чистые косвенные налоги | L79: 11.533872 | M79: 11.351537 | N79: 12.523137 | O79: 12.627281 | P79: 11.084396 | Q79: 11.258707 | R79: 12.395622 | S79: 12.321399 | T79: 12.731584 | U79: 13.948858 | V79: =V14/V13*100 -> 10.534472 | W79: =W14/W13*100 -> 10.330478 | X79: =X14/X13*100 -> 9.8349792 | Y79: =Y14/Y13*100 -> 9.8778202 | Z79: =Z14/Z13*100 -> 9.7240797 | AA79: =AA14/AA13*100 -> 8.9838646 | AB79: =AB14/AB13*100 -> 9.5932479 | AC79: =AC14/AC13*100 -> 9.0431937 | ... AP79: =AP14/AP13*100 -> 6.0278808 | AS79: =$BG$44*AB79/100 -> 0 | AT79: =$BH$44*AC79/100 -> 0 | AU79: =$BI$44*AD79/100 -> 0 | AV79: =$BJ$44*AE79/100 -> 0 | AW79: =$BK$44*AF79/100 -> 0 | AX79: =$BL$44*AG79/100 -> 0
C80: ВВП в основных ценах | L80: 88.473066 | M80: 88.652748 | N80: 87.479206 | O80: 87.394744 | P80: 88.936933 | Q80: 88.740888 | R80: 87.604378 | S80: 87.678601 | T80: 87.268416 | U80: 86.051142 | V80: =V81+V82+V83+V84+V85+V86+V87 -> 89.465528 | W80: =W81+W82+W83+W84+W85+W86+W87 -> 89.669522 | X80: =X81+X82+X83+X84+X85+X86+X87 -> 90.165021 | Y80: =Y81+Y82+Y83+Y84+Y85+Y86+Y87 -> 90.12218 | Z80: =Z81+Z82+Z83+Z84+Z85+Z86+Z87 -> 90.27592 | AA80: =AA81+AA82+AA83+AA84+AA85+AA86+AA87 -> 91.016135 | AB80: =AB81+AB82+AB83+AB84+AB85+AB86+AB87 -> 90.406752 | AC80: =AC81+AC82+AC83+AC84+AC85+AC86+AC87 -> 90.956806 | ... AP80: =AP81+AP82+AP83+AP84+AP85+AP86+AP87 -> 93.972119 | AS80: =AS81+AS82+AS83+AS85+AS86+AS87 -> 0 | AT80: =AT81+AT82+AT83+AT85+AT86+AT87 -> 0 | AU80: =AU81+AU82+AU83+AU85+AU86+AU87 -> 0 | AV80: =AV81+AV82+AV83+AV85+AV86+AV87 -> 0 | AW80: =AW81+AW82+AW83+AW85+AW86+AW87 -> 0 | AX80: =AX81+AX82+AX83+AX85+AX86+AX87 -> 0
C81: Сельское хозяйство и рыболовство | L81: 21.191685 | M81: 21.451908 | N81: 19.433315 | O81: 19.867396 | P81: 18.551554 | Q81: 19.586678 | R81: 23.83551 | S81: 23.326817 | T81: 20.430744 | U81: 23.445291 | V81: =V16/V13*100 -> 21.590744 | W81: =W16/W13*100 -> 20.856977 | X81: =X16/X13*100 -> 20.283296 | Y81: =Y16/Y13*100 -> 19.771965 | Z81: =Z16/Z13*100 -> 20.867073 | AA81: =AA16/AA13*100 -> 22.690431 | AB81: =AB16/AB13*100 -> 22.449081 | AC81: =AC16/AC13*100 -> 22.934854 | ... AP81: =AP16/AP13*100 -> 19.282842 | AS81: =$BG$44*AB81/100 -> 0 | AT81: =$BH$44*AC81/100 -> 0 | AU81: =$BI$44*AD81/100 -> 0 | AV81: =$BJ$44*AE81/100 -> 0 | AW81: =$BK$44*AF81/100 -> 0 | AX81: =$BL$44*AG81/100 -> 0
C82: Промышленность | L82: 22.827686 | M82: 21.284801 | N82: 18.348524 | O82: 14.208021 | P82: 14.336129 | Q82: 14.743535 | R82: 14.528567 | S82: 13.681902 | T82: 12.592412 | U82: 12.083558 | V82: =V17/V13*100 -> 15.156324 | W82: =W17/W13*100 -> 16.913395 | X82: =X17/X13*100 -> 19.92712 | Y82: =Y17/Y13*100 -> 21.153489 | Z82: =Z17/Z13*100 -> 21.329595 | AA82: =AA17/AA13*100 -> 23.239275 | AB82: =AB17/AB13*100 -> 23.881958 | AC82: =AC17/AC13*100 -> 23.490947 | ... AP82: =AP17/AP13*100 -> 23.07924 | AS82: =$BG$44*AB82/100 -> 0 | AT82: =$BH$44*AC82/100 -> 0 | AU82: =$BI$44*AD82/100 -> 0 | AV82: =$BJ$44*AE82/100 -> 0 | AW82: =$BK$44*AF82/100 -> 0 | AX82: =$BL$44*AG82/100 -> 0
C83: Строительство | L83: 4.5388949 | M83: 6.0790762 | N83: 8.0800981 | O83: 10.349638 | P83: 10.172088 | Q83: 10.232686 | R83: 7.9395167 | S83: 8.3607323 | T83: 10.365896 | U83: 10.217819 | V83: =V18/V13*100 -> 15.064126 | W83: =W18/W13*100 -> 15.299971 | X83: =X18/X13*100 -> 11.919738 | Y83: =Y18/Y13*100 -> 13.244872 | Z83: =Z18/Z13*100 -> 11.732554 | AA83: =AA18/AA13*100 -> 10.557265 | AB83: =AB18/AB13*100 -> 11.295724 | AC83: =AC18/AC13*100 -> 11.211634 | ... AP83: =AP18/AP13*100 -> 17.372224 | AS83: =$BG$44*AB83/100 -> 0 | AT83: =$BH$44*AC83/100 -> 0 | AU83: =$BI$44*AD83/100 -> 0 | AV83: =$BJ$44*AE83/100 -> 0 | AW83: =$BK$44*AF83/100 -> 0 | AX83: =$BL$44*AG83/100 -> 0
C84: Прочие товары | L84: 0.29001193 | M84: 0.22281019 | N84: 0.2272674 | O84: 0.19709831 | P84: 0.14300257 | Q84: 0.05585439 | R84: 0 | S84: 0 | T84: 0 | U84: 0 | V84: =V19/V13*100 -> 0 | W84: =W19/W13*100 -> 0 | X84: =X19/X13*100 -> 0 | Y84: =Y19/Y13*100 -> 0 | Z84: =Z19/Z13*100 -> 0 | AA84: =AA19/AA13*100 -> 0 | AB84: =AB19/AB13*100 -> 0 | AC84: =AC19/AC13*100 -> 0 | ... AP84: =AP19/AP13*100 -> 0
C85: Розничная и оптовая торговля | L85: 16.534843 | M85: 17.072831 | N85: 16.554595 | O85: 20.202859 | P85: 21.06646 | Q85: 20.236693 | R85: 13.132875 | S85: 13.916672 | T85: 14.369577 | U85: 14.076033 | V85: =V20/V13*100 -> 10.659429 | W85: =W20/W13*100 -> 11.153434 | X85: =X20/X13*100 -> 9.8604315 | Y85: =Y20/Y13*100 -> 12.748103 | Z85: =Z20/Z13*100 -> 13.528918 | AA85: =AA20/AA13*100 -> 12.771697 | AB85: =AB20/AB13*100 -> 13.219518 | AC85: =AC20/AC13*100 -> 13.62546 | ... AP85: =AP20/AP13*100 -> 15.216331 | AS85: =$BG$44*AB85/100 -> 0 | AT85: =$BH$44*AC85/100 -> 0 | AU85: =$BI$44*AD85/100 -> 0 | AV85: =$BJ$44*AE85/100 -> 0 | AW85: =$BK$44*AF85/100 -> 0 | AX85: =$BL$44*AG85/100 -> 0
C86: Транспорт и связь | L86: 7.400161 | M86: 7.2102664 | N86: 9.5428879 | O86: 10.065003 | P86: 10.979204 | Q86: 11.162783 | R86: 14.486667 | S86: 15.30621 | T86: 15.230523 | U86: 14.304509 | V86: =V21/V13*100 -> 9.5320672 | W86: =W21/W13*100 -> 8.8979254 | X86: =X21/X13*100 -> 7.5580863 | Y86: =Y21/Y13*100 -> 6.0197694 | Z86: =Z21/Z13*100 -> 6.104427 | AA86: =AA21/AA13*100 -> 4.5484485 | AB86: =AB21/AB13*100 -> 5.1531368 | AC86: =AC21/AC13*100 -> 5.0968128 | ... AP86: =AP21/AP13*100 -> 5.769271 | AS86: =$BG$44*AB86/100 -> 0 | AT86: =$BH$44*AC86/100 -> 0 | AU86: =$BI$44*AD86/100 -> 0 | AV86: =$BJ$44*AE86/100 -> 0 | AW86: =$BK$44*AF86/100 -> 0 | AX86: =$BL$44*AG86/100 -> 0
C87: Прочие услуги (остатком) | L87: 15.689784 | M87: 15.331055 | N87: 15.292519 | O87: 12.50473 | P87: 13.688497 | Q87: 12.722659 | R87: 13.681242 | S87: 13.086267 | T87: 14.279263 | U87: 11.923932 | V87: =V22/V13*100 -> 17.462836 | W87: =W22/W13*100 -> 16.54782 | X87: =X22/X13*100 -> 20.616349 | Y87: =Y22/Y13*100 -> 17.183982 | Z87: =Z22/Z13*100 -> 16.713353 | AA87: =AA22/AA13*100 -> 17.209019 | AB87: =AB22/AB13*100 -> 14.407334 | AC87: =AC22/AC13*100 -> 14.597099 | ... AP87: =AP22/AP13*100 -> 13.252211 | AS87: =$BG$44*AB87/100 -> 0 | AT87: =$BH$44*AC87/100 -> 0 | AU87: =$BI$44*AD87/100 -> 0 | AV87: =$BJ$44*AE87/100 -> 0 | AW87: =$BK$44*AF87/100 -> 0 | AX87: =$BL$44*AG87/100 -> 0
C88: Справочно:
C89: Товары | L89: 48.848278 | M89: 49.038595 | N89: 46.089204 | O89: 44.622153 | P89: 43.202773 | Q89: 44.618753 | R89: 46.303594 | S89: 45.369451 | T89: 43.389052 | U89: 45.746668 | V89: =V81+V82+V83+V84 -> 51.811195 | W89: =W81+W82+W83+W84 -> 53.070343 | X89: =X81+X82+X83+X84 -> 52.130154 | Y89: =Y81+Y82+Y83+Y84 -> 54.170326 | Z89: =Z81+Z82+Z83+Z84 -> 53.929222 | AA89: =AA81+AA82+AA83+AA84 -> 56.48697 | AB89: =AB81+AB82+AB83+AB84 -> 57.626763 | AC89: =AC81+AC82+AC83+AC84 -> 57.637435 | ... AP89: =AP81+AP82+AP83+AP84 -> 59.734306 | AS89: =$BG$44*AB89/100 -> 0 | AT89: =$BH$44*AC89/100 -> 0 | AU89: =$BI$44*AD89/100 -> 0 | AV89: =$BJ$44*AE89/100 -> 0 | AW89: =$BK$44*AF89/100 -> 0 | AX89: =$BL$44*AG89/100 -> 0
C90: Услуги | L90: 39.624788 | M90: 39.614153 | N90: 41.390002 | O90: 42.772591 | P90: 45.734161 | Q90: 44.122135 | R90: 41.300784 | S90: 42.309149 | T90: 43.879364 | U90: 40.304473 | V90: =V85+V86+V87 -> 37.654333 | W90: =W85+W86+W87 -> 36.599179 | X90: =X85+X86+X87 -> 38.034867 | Y90: =Y85+Y86+Y87 -> 35.951854 | Z90: =Z85+Z86+Z87 -> 36.346698 | AA90: =AA85+AA86+AA87 -> 34.529165 | AB90: =AB85+AB86+AB87 -> 32.779989 | AC90: =AC85+AC86+AC87 -> 33.319372 | ... AP90: =AP85+AP86+AP87 -> 34.237813 | AS90: =$BG$44*AB90/100 -> 0 | AT90: =$BH$44*AC90/100 -> 0 | AU90: =$BI$44*AD90/100 -> 0 | AV90: =$BJ$44*AE90/100 -> 0 | AW90: =$BK$44*AF90/100 -> 0 | AX90: =$BL$44*AG90/100 -> 0
C93: ВВП по использованию | J93: 4761.5 | K93: 6167.2 | L93: 7206.6 | M93: 9335.3 | N93: 12804.3 | O93: 17706.9 | P93: 20629 | Q93: 24707.1 | R93: 30071.1 | S93: 36163.1 | T93: 40525.2 | U93: 45606.6 | V93: =V13 -> 50977.4 | W93: =W13 -> 54790.3 | X93: =X13 -> 64434.3 | Y93: =Y13 -> 71059.2 | Z93: =Z13 -> 79109.8 | AA93: =AA13 -> 83958.3 | AB93: =AB13 -> 101076.3 | AC93: =AC13 -> 118181.7 | ... AP93: =AP13 -> 568732.06 | AS93: GDPmp,t = GDPmp,t
C94: Конечное потребление | J94: 4752.9317 | K94: 6083.4019 | L94: 7701.1369 | M94: 10421.344 | N94: 16540.416 | O94: 17156.5 | P94: 20380.2 | Q94: 23726.2 | R94: 33314.9 | S94: 41047.7 | T94: 46141.6 | U94: 51376.3 | V94: =V98+V95+V99 -> 42206.3 | W94: =W98+W95+W99 -> 50109.6 | X94: =X98+X95+X99 -> 59167.4 | Y94: =Y98+Y95+Y99 -> 62273.4 | Z94: =Z98+Z95+Z99 -> 69139 | AA94: =AA98+AA95+AA99 -> 74861.6 | AB94: =AB98+AB95+AB99 -> 92235.3 | AC94: =AC98+AC95+AC99 -> 115547 | ... AP94: =AP98+AP95+AP99 -> 400502.9 | AS94: FC,t = G,t+CH,t
C95: - населения | J95: 4172.8317 | K95: 5356.6019 | L95: 6648.8369 | M95: 9384.7438 | N95: 15400.316 | O95: 15145 | P95: 17605.3 | Q95: 20717.1 | R95: 28935.7 | S95: 27407.1 | T95: 41354.9 | U95: 44082 | V95: 36003 | W95: 43219.8 | X95: 51499.4 | Y95: 53938.7 | Z95: 59925 | AA95: 64584 | AB95: 80377.1 | AC95: 102715.8 | AD95: 118160.2 | AE95: 143478 | AF95: =AE95*Household!AF43/Household!AE43 -> 142970.5 | AG95: =AF95*Household!AG43/Household!AF43 -> 156795.45 | AH95: =AG95*Household!AH43/Household!AG43 -> 170643.49 | AI95: =AH95*Household!AI43/Household!AH43 -> 182359.93 | AJ95: =AI95*Household!AJ43/Household!AI43 -> 201698.21 | AK95: =AJ95*Household!AK43/Household!AJ43 -> 219332.17 | AL95: =AK95*Household!AL43/Household!AK43 -> 235775.56 | AM95: =AL95*Household!AM43/Household!AL43 -> 256827.17 | ... AP95: =AO95*Household!AP43/Household!AO43 -> 324477.24 | AS95: CH,t = CH,t-1·DIHHt/DIHHt-1
C96: - в т.ч. рыночный | J96: 2191.3 | K96: 3010.9 | L96: 3679.6 | M96: 4597.9 | N96: 5864 | O96: 8712.6 | P96: 10201 | Q96: 6079.2 | R96: 7506.7 | S96: 9204.8 | T96: 23152.6 | U96: 25879.7 | V96: =Household!V3+Household!V15 -> 26479.6 | W96: =Household!W3+Household!W15 -> 28302.4 | X96: =Household!X3+Household!X15 -> 30958.4 | Y96: =Household!Y3+Household!Y15 -> 33119.8 | Z96: =Household!Z3+Household!Z15 -> 38440.4 | AA96: =Household!AA3+Household!AA15 -> 40710.1 | AB96: =Household!AB3+Household!AB15 -> 48909.7 | AC96: =Household!AC3+Household!AC15 -> 66260.2 | ... AP96: =Household!AP3+Household!AP15 -> 311764.76 | AS96: CMRKTt = RETt+SERt
C97: - в т.ч. натуральное | J97: 1981.5317 | K97: 2345.7019 | L97: 2969.2369 | M97: 4786.8438 | N97: 9536.3161 | O97: 6432.4 | P97: 7404.3 | Q97: 14637.9 | R97: 21429 | S97: 18202.3 | T97: 18202.3 | U97: 18202.3 | V97: =V95-V96 -> 9523.4 | W97: =W95-W96 -> 14917.4 | X97: =X95-X96 -> 20541 | Y97: =Y95-Y96 -> 20818.9 | Z97: =Z95-Z96 -> 21484.6 | AA97: =AA95-AA96 -> 23873.9 | AB97: =AB95-AB96 -> 31467.4 | AC97: =AC95-AC96 -> 36455.6 | ... AP97: =AP95-AP96 -> 12712.488 | AS97: CNAt = CH,t-CMRKTt
C98: - государства | J98: 580.1 | K98: 726.8 | L98: 1052.3 | M98: 1036.6 | N98: 1140.1 | O98: 1652.7 | P98: 2570.8 | Q98: 2798.5 | R98: 4105.7 | S98: 4644 | T98: 5352.2 | U98: 6317.1 | V98: 5892.5 | W98: 6441.6 | X98: 7336.8 | Y98: 7973.6 | Z98: 8824.3 | AA98: 9712.3 | AB98: 11001.4 | AC98: 11977.8 | AD98: 14157.5 | AE98: 17602.5 | AF98: =(AE98-AE100)*AF93/AE93+AF100 -> 20158.917 | AG98: =(AF98-AF100)*AG93/AF93+AG100 -> 23048.922 | AH98: =(AG98-AG100)*AH93/AG93+AH100 -> 26339.824 | AI98: =(AH98-AH100)*AI93/AH93+AI100 -> 30115.345 | AJ98: =(AI98-AI100)*AJ93/AI93+AJ100 -> 34563.198 | AK98: =(AJ98-AJ100)*AK93/AJ93+AK100 -> 39423.843 | AL98: =(AK98-AK100)*AL93/AK93+AL100 -> 45090.906 | AM98: =(AL98-AL100)*AM93/AL93+AM100 -> 51493.132 | ... AP98: =(AO98-AO100)*AP93/AO93+AP100 -> 76025.653 | AS98: G,t = (G,t-1-GNTrrt-1)·GDPmp,t/GDPmp,t-1+GNTrrt
C99: организации, обслуживающие домашние хозяйства | V99: 310.8 | W99: 448.2 | X99: 331.2 | Y99: 361.1 | Z99: 389.7 | AA99: 565.3 | AB99: 856.8 | AC99: 853.4 | AD99: 786.6 | AE99: 874.7
C100: - в т.ч. трансферты населению в натуральной форме | L100: 768.1 | M100: 662.5 | N100: 904 | O100: 1088.8 | P100: 2242 | Q100: 2267.4 | R100: 2898.8 | S100: 3838.8 | T100: 4525.3 | U100: 5399.5 | V100: =Household!V40 -> 4055.1 | W100: =Household!W40 -> 4817.9 | X100: =Household!X40 -> 5466.7 | Y100: =Household!Y40 -> 5744 | Z100: =Household!Z40 -> 6433.2 | AA100: =Household!AA40 -> 7283.3 | AB100: =Household!AB40 -> 8932.6 | AC100: =Household!AC40 -> 10146.4 | ... AP100: =Household!AP40 -> 54637.219 | AS100: GNTrrt = TrNATG,t
C101: Валовое накопление | J101: 475.6 | K101: 752.6 | L101: 839.4 | M101: 1490.5 | N101: 3154.1 | O101: 4693.9 | P101: 5125.1 | Q101: 5891.6 | R101: 8783.6 | S101: 8414.2 | T101: 10024.7 | U101: 11930.5 | V101: 22781.7 | W101: 22202.3 | X101: 19284.9 | Y101: 26479.1 | Z101: 27995.9 | AA101: 28105 | AB101: 35249.2 | AC101: 41916.1 | AD101: 42027.3 | AE101: 50513.5 | AF101: =AF93-AF104-AF105-AF94 -> 67378.842 | AG101: =AG93-AG104-AG105-AG94 -> 65109.329 | AH101: =AH93-AH104-AH105-AH94 -> 74206.219 | AI101: =AI93-AI104-AI105-AI94 -> 88434.814 | AJ101: =AJ93-AJ104-AJ105-AJ94 -> 102847.46 | AK101: =AK93-AK104-AK105-AK94 -> 117794.22 | AL101: =AL93-AL104-AL105-AL94 -> 147556.67 | AM101: =AM93-AM104-AM105-AM94 -> 171355.69 | ... AP101: =AP93-AP104-AP105-AP94 -> 254856.99 | AS101: InvNAt = GDPmp,t-ExNA,t-ImNA,t-FC,t
C102: - валовое накопление основного капитала | J102: 382.6 | K102: 640 | L102: 801.3 | M102: 1445.3 | N102: 2973.9 | O102: 4341.4 | P102: 5423.9 | Q102: 6050.6 | R102: 8598.2 | S102: 7855.8 | T102: 9736.3 | U102: 11781.5 | V102: 19736.9 | W102: 21954 | X102: 20133 | Y102: 25146.8 | Z102: 24926.6 | AA102: 23150.4 | AB102: 32314.3 | AC102: 37469.9 | AD102: 37577.8 | AE102: 47110.6 | AF102: =AF101*0.94 -> 63336.111 | AG102: =AG101*0.94 -> 61202.769 | AH102: =AH101*0.94 -> 69753.846 | AI102: =AI101*0.94 -> 83128.725 | AJ102: =AJ101*0.94 -> 96676.611 | AK102: =AK101*0.94 -> 110726.57 | AL102: =AL101*0.94 -> 138703.27 | AM102: =AM101*0.94 -> 161074.35 | ... AP102: =AP101*0.94 -> 239565.57 | AS102: InvNAF,t = InvNAt·0,97
C103: - изменение запасов | J103: 93 | K103: 112.6 | L103: 38.1 | M103: 45.2 | N103: 180.2 | O103: 352.5 | P103: -298.8 | Q103: -158.9 | R103: 185.4 | S103: 558.4 | T103: 288.3 | U103: 149 | V103: 3044.8 | W103: 248.3 | X103: -848.1 | Y103: 1332.3 | Z103: 3069.3 | AA103: 4954.6 | AB103: 2934.9 | AC103: 4446.2 | AD103: 4449.5 | AE103: 3402.9 | AF103: =AF101-AF102 -> 4042.7305 | AG103: =AG101-AG102 -> 3906.5598 | AH103: =AH101-AH102 -> 4452.3732 | AI103: =AI101-AI102 -> 5306.0888 | AJ103: =AJ101-AJ102 -> 6170.8475 | AK103: =AK101-AK102 -> 7067.6534 | AL103: =AL101-AL102 -> 8853.4002 | AM103: =AM101-AM102 -> 10281.342 | ... AP103: =AP101-AP102 -> 15291.42 | AS103: CiIt = InvNAt-InvNAF,t
C104: Экспорт товаров и услуг | J104: 3045.5486 | K104: 3624.0277 | L104: 3909.5709 | M104: 5243.2217 | N104: 5871.4189 | O104: 5782.4 | P104: 5048 | Q104: 6620.7 | R104: 5335 | S104: 7829.5 | T104: 7582.6 | U104: 5143.4 | V104: 4997.2 | W104: 7232.5 | X104: 9619.1 | Y104: 10215.1 | Z104: 11850.6 | AA104: 14545.2 | AB104: 24442.2 | AC104: 19326.4 | AD104: 22827.7 | AE104: 17467.5 | AF104: =(Trade!AF5+Trade!AF4-Trade!AF6)*Assumptions!AF12+Industry!AF12 -> 33946.69 | AG104: =(Trade!AG5+Trade!AG4-Trade!AG6)*Assumptions!AG12+Industry!AG12 -> 35600.836 | AH104: =(Trade!AH5+Trade!AH4-Trade!AH6)*Assumptions!AH12+Industry!AH12 -> 39596.776 | AI104: =(Trade!AI5+Trade!AI4-Trade!AI6)*Assumptions!AI12+Industry!AI12 -> 44151.942 | AJ104: =(Trade!AJ5+Trade!AJ4-Trade!AJ6)*Assumptions!AJ12+Industry!AJ12 -> 49171.809 | AK104: =(Trade!AK5+Trade!AK4-Trade!AK6)*Assumptions!AK12+Industry!AK12 -> 54369.44 | AL104: =(Trade!AL5+Trade!AL4-Trade!AL6)*Assumptions!AL12+Industry!AL12 -> 56441.62 | AM104: =(Trade!AM5+Trade!AM4-Trade!AM6)*Assumptions!AM12+Industry!AM12 -> 62629.976 | ... AP104: =(Trade!AP5+Trade!AP4-Trade!AP6)*Assumptions!AP12+Industry!AP12 -> 86147.805 | AS104: ExNA,t = (EXUSt+EXUSServ,t)·erUSDt
C105: (-) Импорт товаров и услуг | J105: -3512.5803 | K105: -4292.8296 | L105: -5243.5078 | M105: -7819.7656 | N105: -12761.635 | O105: -14004.9 | P105: -12686.7 | Q105: -14577.7 | R105: -22286.1 | S105: -25114 | T105: -26051.9 | U105: -26676.2 | V105: -20460 | W105: -23299.3 | X105: -25037.6 | Y105: -29468.7 | Z105: -32486.5 | AA105: -32260.8 | AB105: -48156.8 | AC105: -58006.4 | AD105: -64323.5 | AE105: -74585.1 | AF105: =-(Trade!AF42+Trade!AF43-Trade!AF49)*Assumptions!AF12 -> -87535.954 | AG105: =-(Trade!AG42+Trade!AG43-Trade!AG49)*Assumptions!AG12 -> -80656.403 | AH105: =-(Trade!AH42+Trade!AH43-Trade!AH49)*Assumptions!AH12 -> -85329.101 | AI105: =-(Trade!AI42+Trade!AI43-Trade!AI49)*Assumptions!AI12 -> -90451.623 | AJ105: =-(Trade!AJ42+Trade!AJ43-Trade!AJ49)*Assumptions!AJ12 -> -97325.404 | AK105: =-(Trade!AK42+Trade!AK43-Trade!AK49)*Assumptions!AK12 -> -104932.08 | AL105: =-(Trade!AL42+Trade!AL43-Trade!AL49)*Assumptions!AL12 -> -116533.96 | AM105: =-(Trade!AM42+Trade!AM43-Trade!AM49)*Assumptions!AM12 -> -128335.68 | ... AP105: =-(Trade!AP42+Trade!AP43-Trade!AP49)*Assumptions!AP12 -> -172775.64 | AS105: ImNA,t = -(IMUSServ,t+IMUSGoods,t)·erUSDt
C106: чистый экспорт товаров и услуг | O106: -8222.5 | P106: -7638.6 | Q106: -7957 | R106: -16951.1 | S106: -17284.5 | T106: -18469.3 | U106: -21532.8 | V106: =V105+V104 -> -15462.8 | W106: =W105+W104 -> -16066.8 | X106: =X105+X104 -> -15418.5 | Y106: =Y105+Y104 -> -19253.6 | Z106: =Z105+Z104 -> -20635.9 | AA106: =AA105+AA104 -> -17715.6 | AB106: =AB105+AB104 -> -23714.6 | AC106: =AC105+AC104 -> -38680 | ... AP106: =AP105+AP104 -> -86627.833
C107: статистическое расхождение | O107: 4079 | P107: 2761.9 | Q107: 3046.4 | R107: 4923.7 | S107: 3985.6 | T107: 2828.6 | U107: 3832.6 | V107: 1452.6 | W107: -1454.8 | X107: 1400.6 | Y107: 1560.3 | Z107: 2610.8 | AA107: -1292.7 | AB107: -2963.6 | AC107: -601.4 | AD107: =AD93-AD94-AD101-AD104-AD105 -> -853.9 | AE107: =AE93-AE94-AE101-AE104-AE105 -> 432.8 | AF107: =AF93-AF94-AF101-AF104-AF105 -> 0 | AG107: =AG93-AG94-AG101-AG104-AG105 -> 0 | AH107: =AH93-AH94-AH101-AH104-AH105 -> 0 | AI107: =AI93-AI94-AI101-AI104-AI105 -> 0 | AJ107: =AJ93-AJ94-AJ101-AJ104-AJ105 -> 0 | AK107: =AK93-AK94-AK101-AK104-AK105 -> 0 | ... AP107: =AP93-AP94-AP101-AP104-AP105 -> 0
AC108: =AC94+AC101+AC104+AC105 -> 118783.1 | AD108: =AD94+AD101+AD104+AD105 -> 133635.8 | AE108: =AE94+AE101+AE104+AE105 -> 155351.1 | AF108: =AF94+AF101+AF104+AF105 -> 176919 | AG108: =AG94+AG101+AG104+AG105 -> 199898.14 | AH108: =AH94+AH101+AH104+AH105 -> 225457.21 | AI108: =AI94+AI101+AI104+AI105 -> 254610.41 | AJ108: =AJ94+AJ101+AJ104+AJ105 -> 290955.28 | ... AP108: =AP94+AP101+AP104+AP105 -> 568732.06
C110: ВВП по использованию, % | N110: 110.55184 | O110: 116.24527 | P110: 105.79428 | Q110: 111.81258 | R110: 113.43717 | S110: 99.965562 | T110: 121.39968 | U110: 111.07095 | V110: 109.325 | W110: 111.5 | X110: 103.1 | Y110: 107.1 | Z110: 107.8 | AA110: 104.7 | AB110: 109.8 | AC110: 108.6 | AD110: 107.7 | AE110: 107.6 | AF110: =(AF116*AE104+AF117*AE105+AF115*AE101+AF113*AE97+AE96*AF112+AF114*AE98)/(AE104+AE105+AE101+AE98+AE96+AE97) -> 129.06174 | AG110: =(AG116*AF104+AG117*AF105+AG115*AF101+AG113*AF97+AF96*AG112+AG114*AF98)/(AF104+AF105+AF101+AF98+AF96+AF97) -> 112.67963 | AH110: =(AH116*AG104+AH117*AG105+AH115*AG101+AH113*AG97+AG96*AH112+AH114*AG98)/(AG104+AG105+AG101+AG98+AG96+AG97) -> 118.96681 | AI110: =(AI116*AH104+AI117*AH105+AI115*AH101+AI113*AH97+AH96*AI112+AI114*AH98)/(AH104+AH105+AH101+AH98+AH96+AH97) -> 120.40685 | AJ110: =(AJ116*AI104+AJ117*AI105+AJ115*AI101+AJ113*AI97+AI96*AJ112+AJ114*AI98)/(AI104+AI105+AI101+AI98+AI96+AI97) -> 120.04094 | AK110: =(AK116*AJ104+AK117*AJ105+AK115*AJ101+AK113*AJ97+AJ96*AK112+AK114*AJ98)/(AJ104+AJ105+AJ101+AJ98+AJ96+AJ97) -> 116.39987 | AL110: =(AL116*AK104+AL117*AK105+AL115*AK101+AL113*AK97+AK96*AL112+AL114*AK98)/(AK104+AK105+AK101+AK98+AK96+AK97) -> 118.39567 | AM110: =(AM116*AL104+AM117*AL105+AM115*AL101+AM113*AL97+AL96*AM112+AM114*AL98)/(AL104+AL105+AL101+AL98+AL96+AL97) -> 117.4218 | ... AP110: =(AP116*AO104+AP117*AO105+AP115*AO101+AP113*AO97+AO96*AP112+AP114*AO98)/(AO104+AO105+AO101+AO98+AO96+AO97) -> 121.83308 | AS110: gGDPmp,t = (gExNA,t·ExNA,t-1+gImNA,t·ImNA,t-1+gInvNAt·InvNAt-1+gCNAt·CNAt-1+CMRKTt-1·gCMRKTt+gG,t·G,t-1)/(ExNA,t-1+ImNA,t-1+InvNAt-1+G,t-1+CMRKTt-1+CNAt-1)
C111: Конечное потребление населения | L111: 107.7562 | M111: 107.71048 | N111: 105.0185 | O111: 113.73118 | P111: 107.9 | Q111: 110.6 | R111: 124.4 | S111: 115.2 | T111: 109.4 | U111: 101.8 | V111: 85 | W111: 113 | X111: 105 | Y111: 104 | Z111: 105 | AA111: 103.1 | AB111: 104.3 | AC111: 115.7 | AD111: 109.2 | AE111: 115.5 | AF111: =SUMPRODUCT(AF112:AF113,AE96:AE97)/SUM(AE96:AE97) -> 112.05494 | AG111: =SUMPRODUCT(AG112:AG113,AF96:AF97)/SUM(AF96:AF97) -> 112.21997 | AH111: =SUMPRODUCT(AH112:AH113,AG96:AG97)/SUM(AG96:AG97) -> 112.53173 | AI111: =SUMPRODUCT(AI112:AI113,AH96:AH97)/SUM(AH96:AH97) -> 112.28229 | AJ111: =SUMPRODUCT(AJ112:AJ113,AI96:AI97)/SUM(AI96:AI97) -> 112.37725 | AK111: =SUMPRODUCT(AK112:AK113,AJ96:AJ97)/SUM(AJ96:AJ97) -> 108.36398 | AL111: =SUMPRODUCT(AL112:AL113,AK96:AK97)/SUM(AK96:AK97) -> 107.16365 | AM111: =SUMPRODUCT(AM112:AM113,AL96:AL97)/SUM(AL96:AL97) -> 106.53569 | ... AP111: =SUMPRODUCT(AP112:AP113,AO96:AO97)/SUM(AO96:AO97) -> 105.71555 | AS111: gCH,t = (gCMRKTt·CMRKTt-1+gCNAt·CNAt-1)/(CMRKTt-1+CNAt-1)
C112: - в т.ч. рыночный | L112: 112.70812 | M112: 109.57491 | N112: 103.47611 | O112: 123.37675 | P112: 107.16028 | Q112: 110.09 | R112: 113.5897 | S112: 113.80107 | T112: 114.05663 | U112: 101.66359 | V112: 99.818533 | W112: =(Household!V9*Household!W11+Household!V18*Household!W20)/(Household!V9+Household!V18) -> 103.63471 | X112: =(Household!W9*Household!X11+Household!W18*Household!X20)/(Household!W9+Household!W18) -> 104.76179 | Y112: =(Household!X9*Household!Y11+Household!X18*Household!Y20)/(Household!X9+Household!X18) -> 106.94157 | Z112: =(Household!Y9*Household!Z11+Household!Y18*Household!Z20)/(Household!Y9+Household!Y18) -> 107.10766 | AA112: =(Household!Z9*Household!AA11+Household!Z18*Household!AA20)/(Household!Z9+Household!Z18) -> 96.019416 | AB112: =(Household!AA9*Household!AB11+Household!AA18*Household!AB20)/(Household!AA9+Household!AA18) -> 109.71003 | AC112: =(Household!AB9*Household!AC11+Household!AB18*Household!AC20)/(Household!AB9+Household!AB18) -> 110.35767 | AD112: =(Household!AC9*Household!AD11+Household!AC18*Household!AD20)/(Household!AC9+Household!AC18) -> 116.17827 | ... AP112: =(Household!AO9*Household!AP11+Household!AO18*Household!AP20)/(Household!AO9+Household!AO18) -> 105.7069 | AS112: gCMRKTt = (RETt-1·gRETt+SERt-1·gSERt)/(RETt-1+SERt-1)
C113: - в т.ч. натуральное | L113: 101.4 | M113: 105.4 | N113: 106.5 | O113: 107.8 | P113: 110.5 | Q113: 106.8 | R113: 107.9 | S113: 110.4 | T113: 107.6 | U113: 104.5 | V113: =V33 -> 103.2 | W113: =W33 -> 105.2 | X113: =X33 -> 106.8 | Y113: =Y33 -> 104 | Z113: =Z33 -> 107.1 | AA113: =AA33 -> 108.8 | AB113: =AB33 -> 106.6 | AC113: =AC33 -> 108 | ... AP113: =AP33 -> 107.25535 | AS113: gCNAt = gVAAB,t
C114: Конечное потребление государства | L114: 133.529 | M114: 86.382114 | N114: 89.235446 | O114: 94.240434 | P114: 106.9 | Q114: 100.9 | R114: 107.8 | S114: 102.1 | T114: 102.3 | U114: 104.1 | V114: 103.3 | W114: 101.7 | X114: 105.7 | Y114: 104.5 | Z114: 100.7 | AA114: 102.3 | AB114: 104.6 | AC114: 99.3 | AD114: 90.9 | AE114: 76.9 | AF114: =AF98/AE98/(AF96/AE96/AF112) -> 110.36652 | AG114: =AG98/AF98/(AG96/AF96/AG112) -> 111.34769 | AH114: =AH98/AG98/(AH96/AG96/AH112) -> 110.96898 | AI114: =AI98/AH98/(AI96/AH96/AI112) -> 112.88508 | AJ114: =AJ98/AI98/(AJ96/AI96/AJ112) -> 114.24522 | AK114: =AK98/AJ98/(AK96/AJ96/AK112) -> 114.05069 | AL114: =AL98/AK98/(AL96/AK96/AL112) -> 112.94042 | AM114: =AM98/AL98/(AM96/AL96/AM112) -> 113.62177 | ... AP114: =AP98/AO98/(AP96/AO96/AP112) -> 114.96735 | AS114: gG,t = G,t/G,t-1/(CMRKTt/CMRKTt-1/gCMRKTt)
C115: Валовое накопление | M115: 163.97218 | N115: 187.05774 | O115: 132.71217 | P115: 76.8 | Q115: 107.5 | R115: 113.3 | S115: 78.1 | T115: 115.1 | U115: 117.6 | V115: 125.2 | W115: 93.4 | X115: 88 | Y115: 125.5 | Z115: 108.9 | AA115: 95.4 | AB115: 112 | AC115: 111.9 | AD115: 90.1 | AE115: 107.9 | AF115: =AF102/AE102/0.88*100 -> 152.77422 | AG115: =AG102/AF102/0.88*100 -> 109.80876 | AH115: =AH102/AG102/0.88*100 -> 129.51331 | AI115: =AI102/AH102/0.88*100 -> 135.42545 | AJ115: =AJ102/AI102/0.88*100 -> 132.15623 | AK115: =AK102/AJ102/0.88*100 -> 130.15107 | AL115: =AL102/AK102/0.88*100 -> 142.34827 | AM115: =AM102/AL102/0.88*100 -> 131.96447 | ... AP115: =AP102/AO102/0.88*100 -> 142.0391 | AS115: gInvNAt = InvNAF,t/InvNAF,t-1/0,88·100
...

Sheet Agriculture
D1: 1997 | E1: 1998 | F1: 1999 | G1: 2000 | H1: 2001 | I1: 2002 | J1: 2003 | K1: 2004 | L1: 2005 | M1: 2006 | N1: 2007 | O1: 2008 | P1: 2009 | Q1: 2010 | R1: 2011 | S1: 2012 | T1: 2013 | U1: 2014 | V1: 2015 | W1: 2016 | X1: 2017 | Y1: 2018 | Z1: 2019 | AA1: 2020 | AB1: 2021 | AC1: 2022 | AD1: 2023 | AE1: 2024 | AF1: 2025 | AG1: 2026 | AH1: 2027 | AI1: 2028 | AJ1: 2029 | AK1: 2030 | AL1: 2031 | AM1: 2032 | AN1: 2033 | AO1: 2034 | AP1: 2035
B2: СЕЛЬСКОЕ ХОЗЯЙСТВО | C2: млн. Сомони | L2: 6855.9 | M2: 7246.7 | N2: 7500.4 | O2: 7957.9 | P2: 8793.5 | Q2: 9391.4 | R2: 14853.3 | S2: 16477.5 | T2: 16756.6 | U2: 21021.9 | V2: 21577.8 | W2: =W5+W8 -> 22907.672 | X2: =X5+X8 -> 24576 | Y2: =Y5+Y8 -> 45645.8 | Z2: =Z5+Z8 -> 48889.8 | AA2: =AA5+AA8 -> 53235.2 | AB2: =AB5+AB8 -> 56806.7 | AC2: =AC5+AC8 -> 61337.9 | AD2: =AD5+AD8 -> 66907.2 | ... AF2: =AF5+AF8 -> 84653.8 | AG2: =AG5+AG8+AG125 -> 95155.365 | AH2: =AH5+AH8+AH125 -> 104591.34 | AI2: =AI5+AI8+AI125 -> 114715.98 | AJ2: =AJ5+AJ8+AJ125 -> 125434.67 | AK2: =AK5+AK8+AK125 -> 136949.66 | AL2: =AL5+AL8+AL125 -> 148095.75 | AM2: =AM5+AM8+AM125 -> 159589.23 | AN2: =AN5+AN8+AN125 -> 172013.18 | ... AP2: =AP5+AP8+AP125 -> 199395.93 | AQ2: N5+N8
B3: темп роста | C3: % | L3: 101.6 | M3: 105.7 | N3: 103.5 | O3: 107.9 | P3: 110.5 | Q3: 106.8 | R3: 107.9 | S3: 110.4 | T3: 107.6 | U3: 104.5 | V3: 103.2 | W3: 105.2 | X3: 106.8 | Y3: 104 | Z3: 107.1 | AA3: 108.8 | AB3: 106.6 | AC3: 108 | AD3: 109 | AE3: 110.6 | AF3: 109.5 | AG3: =AG2/AF2/AG4*10000 -> 108.91987 | AH3: =AH2/AG2/AH4*10000 -> 108.61303 | AI3: =AI2/AH2/AI4*10000 -> 108.27265 | AJ3: =AJ2/AI2/AJ4*10000 -> 108.15398 | AK3: =AK2/AJ2/AK4*10000 -> 108.31356 | AL3: =AL2/AK2/AL4*10000 -> 107.60081 | AM3: =AM2/AL2/AM4*10000 -> 107.54575 | AN3: =AN2/AM2/AN4*10000 -> 107.24871 | ... AP3: =AP2/AO2/AP4*10000 -> 107.25535 | AQ3: N2/M2/N4*10000
B4: дефлятор | C4: % | M4: 100.00019 | N4: 100.00087 | O4: 98.331487 | P4: 100.00023 | Q4: 99.999382 | R4: 146.5788 | S4: 100.48455 | T4: 94.51099 | U4: 120.0521 | V4: 99.461614 | W4: =W2/V2/W3*10000 -> 100.91554 | X4: =X2/W2/X3*10000 -> 100.45209 | Y4: =Y2/X2/Y3*10000 -> 178.58965 | Z4: =Z2/Y2/Z3*10000 -> 100.00644 | AA4: =AA2/Z2/AA3*10000 -> 100.08102 | AB4: =AB2/AA2/AB3*10000 -> 100.10216 | AC4: =AC2/AB2/AC3*10000 -> 99.978263 | AD4: =AD2/AC2/AD3*10000 -> 100.07312 | ... AF4: =AF2/AE2/AF3*10000 -> 104.50522 | AG4: 103.2 | AH4: 101.2 | AI4: 101.3 | AJ4: 101.1 | AK4: 100.8 | AL4: 100.5 | AM4: 100.2 | AN4: 100.5 | AO4: 100.5 | AP4: 100.5
B5: РАСТЕНИЕВОДСТВО | C5: млн. Сомони | L5: 4724.9 | M5: 5032 | N5: 5147.7 | O5: 5523.5 | P5: 6219.5 | Q5: 6617.5 | R5: 10894.7 | S5: 11836.3 | T5: 11502.5 | U5: 14532.8 | V5: 14623.7 | W5: 15066.6 | X5: 16977.8 | Y5: 31669.6 | Z5: 34124 | AA5: 36919.4 | AB5: 39115.6 | AC5: 42115 | AD5: 44976.1 | AE5: 50984.9 | AF5: 56588 | AG5: =AG28+AG40+AG50+AG56+AG66+AG72+AG78+AG82 -> 61242.178 | AH5: =AH28+AH40+AH50+AH56+AH66+AH72+AH78+AH82 -> 66836.044 | AI5: =AI28+AI40+AI50+AI56+AI66+AI72+AI78+AI82 -> 72556.838 | AJ5: =AJ28+AJ40+AJ50+AJ56+AJ66+AJ72+AJ78+AJ82 -> 78788.347 | AK5: =AK28+AK40+AK50+AK56+AK66+AK72+AK78+AK82 -> 85058.32 | AL5: =AL28+AL40+AL50+AL56+AL66+AL72+AL78+AL82 -> 90393.172 | AM5: =AM28+AM40+AM50+AM56+AM66+AM72+AM78+AM82 -> 95752.602 | AN5: =AN28+AN40+AN50+AN56+AN66+AN72+AN78+AN82 -> 100785.75 | ... AP5: =AP28+AP40+AP50+AP56+AP66+AP72+AP78+AP82 -> 109860.02 | AQ5: N27+N39+N49+N55+N65+N71+N77+N81
B6: темп роста | C6: % | L6: 98.6 | M6: 106.5 | N6: 102.3 | O6: 108.4 | P6: 112.6 | Q6: 106.4 | R6: 108.2 | S6: 110.6 | T6: 107.6 | U6: 104.5 | V6: 101.4 | W6: 105.1 | X6: 107.4 | Y6: 103.4 | Z6: 107.8 | AA6: 108.2 | AB6: 105.9 | AC6: 107.7 | AD6: 106.8 | AE6: 113.4 | AF6: 109.9 | AG6: =AG5/AF5/AG7*10000 -> 107.25934 | AH6: =AH5/AG5/AH7*10000 -> 106.99413 | AI6: =AI5/AH5/AI7*10000 -> 108.34276 | AJ6: =AJ5/AI5/AJ7*10000 -> 107.51332 | AK6: =AK5/AJ5/AK7*10000 -> 107.42089 | AL6: =AL5/AK5/AL7*10000 -> 105.74328 | AM6: =AM5/AL5/AM7*10000 -> 105.61219 | AN6: =AN5/AM5/AN7*10000 -> 104.94159 | ... AP6: =AP5/AO5/AP7*10000 -> 101.29673 | AQ6: N5/M5/N7*10000
B7: дефлятор | C7: % | M7: 99.999632 | N7: 99.999301 | O7: 98.985561 | P7: 100.00063 | Q7: 99.999275 | R7: 152.15775 | S7: 98.230321 | T7: 90.315857 | U7: 120.90403 | V7: 99.236175 | W7: =W5/V5/W6*10000 -> 98.029158 | X7: =X5/W5/X6*10000 -> 104.92087 | Y7: =Y5/X5/Y6*10000 -> 180.4017 | Z7: =Z5/Y5/Z6*10000 -> 99.953635 | AA7: =AA5/Z5/AA6*10000 -> 99.992503 | AB7: =AB5/AA5/AB6*10000 -> 100.04592 | AC7: =AC5/AB5/AC6*10000 -> 99.970325 | AD7: =AD5/AC5/AD6*10000 -> 99.993953 | ... AF7: =AF5/AE5/AF6*10000 -> 100.99156 | AG7: 100.9 | AH7: 102 | AI7: 100.2 | AJ7: 101 | AK7: 100.5 | AL7: 100.5 | AM7: 100.3 | AN7: 100.3 | AO7: 100.2 | AP7: 102.8
B8: ЖИВОТНОВОДСТВО | C8: млн. Сомони | L8: 2134.1 | M8: 2208.8 | N8: 2356.8 | O8: 2429.8 | P8: 2573.2 | Q8: 2773.9 | R8: 3958.6 | S8: 3958.6 | T8: 3958.6 | U8: 3958.6 | V8: 6954.1 | W8: 7841.0717 | X8: 7598.2 | Y8: 13976.2 | Z8: 14765.8 | AA8: 16315.8 | AB8: 17691.1 | AC8: 19222.9 | AD8: 21931.1 | AE8: 22991.7 | AF8: 28065.8 | AG8: =AF8*AG9*AG10/10000-AG125 -> 33724.207 | AH8: =AG8*AH9*AH10/10000-AH125 -> 37549.307 | AI8: =AH8*AI9*AI10/10000-AI125 -> 41934.825 | AJ8: =AI8*AJ9*AJ10/10000-AJ125 -> 46401.587 | AK8: =AJ8*AK9*AK10/10000-AK125 -> 51624.557 | AL8: =AK8*AL9*AL10/10000-AL125 -> 57411.246 | AM8: =AL8*AM9*AM10/10000-AM125 -> 63518.787 | AN8: =AM8*AN9*AN10/10000-AN125 -> 70880.981 | ... AP8: =AO8*AP9*AP10/10000-AP125 -> 89127.317
B9: темп роста | C9: % | L9: 110.1 | M9: 103.5 | N9: 106.7 | O9: 106.7 | P9: 105.9 | Q9: 107.7 | R9: 107 | S9: 109.7 | T9: 107.5 | U9: 112.5 | V9: 107.2 | W9: 105.5 | X9: 105.6 | Y9: 105.3 | Z9: 105.7 | AA9: 110.5 | AB9: 108.4 | AC9: 108.7 | AD9: 114.1 | AE9: 104.8 | AF9: 108.5 | AG9: 107.4085 | AH9: 106.622 | AI9: 104.4435 | AJ9: 103.5132 | AK9: 105.0056 | AL9: 105.4467 | AM9: 105.897 | AN9: 107 | AO9: 107 | AP9: 108
B10: дефлятор | C10: % | M10: 100.00029 | N10: 100.00044 | O10: 96.623637 | P10: 100.00162 | Q10: 100.0925 | R10: 133.37273 | S10: 91.157703 | T10: 93.023256 | U10: 88.888889 | V10: 163.87191 | W10: =W8/V8/W9*10000 -> 106.87645 | X10: =X8/W8/X9*10000 -> 91.763797 | Y10: =Y8/X8/Y9*10000 -> 174.68275 | Z10: =Z8/Y8/Z9*10000 -> 99.952322 | AA10: =AA8/Z8/AA9*10000 -> 99.997493 | AB10: =AB8/AA8/AB9*10000 -> 100.02699 | AC10: =AC8/AB8/AC9*10000 -> 99.961905 | AD10: =AD8/AC8/AD9*10000 -> 99.989838 | ... AF10: =AF8/AE8/AF9*10000 -> 112.50624 | AG10: 112.5 | AH10: 105 | AI10: 107.5 | AJ10: 107.46 | AK10: 106.5 | AL10: 106 | AM10: 105 | AN10: 104.8 | AO10: =AN10 -> 104.8 | AP10: =AO10 -> 104.8
W11: =W2-V2 -> 1329.8717 | X11: =X2-W2 -> 1668.3283 | Y11: =Y2-X2 -> 21069.8 | Z11: =Z2-Y2 -> 3244 | AA11: =AA2-Z2 -> 4345.4 | AB11: =AB2-AA2 -> 3571.5 | AC11: =AC2-AB2 -> 4531.2 | AD11: =AD2-AC2 -> 5569.3 | ... AP11: =AP2-AO2 -> 14413.161
V12: =V5-U5 -> 90.9 | W12: =W5-V5 -> 442.9 | X12: =X5-W5 -> 1911.2 | Y12: =Y5-X5 -> 14691.8 | Z12: =Z5-Y5 -> 2454.4 | AA12: =AA5-Z5 -> 2795.4 | AB12: =AB5-AA5 -> 2196.2 | AC12: =AC5-AB5 -> 2999.4 | ... AP12: =AP5-AO5 -> 4360.3453
AB13: =AB8-AA8 -> 1375.3 | AC13: =AC8-AB8 -> 1531.8 | AD13: =AD8-AC8 -> 2708.2 | AE13: =AE8-AD8 -> 1060.6 | AF13: =AF8-AE8 -> 5074.1 | AG13: =AG8-AF8 -> 5658.4066 | AH13: =AH8-AG8 -> 3825.0999 | AI13: =AI8-AH8 -> 4385.518 | ... AP13: =AP8-AO8 -> 10020.806
B14: Общая земельная площадь | C14: га | L14: 14255397 | M14: 14255397 | N14: 14255397 | O14: 14255397 | P14: 14255397 | Q14: 14255397 | R14: 14255397 | S14: 14255397 | T14: 14255397 | U14: 14137685 | V14: 14137685 | W14: 14137685 | X14: 14137685 | Y14: 14137900 | Z14: =Y14 -> 14137900 | AA14: 14137907 | AB14: 14137907 | AC14: =AB14 -> 14137907 | AD14: =AC14 -> 14137907 | AE14: =AD14 -> 14137907 | AF14: =AE14 -> 14137907 | AG14: =AF14 -> 14137907 | AH14: =AG14 -> 14137907 | AI14: =AH14 -> 14137907 | AJ14: =AI14 -> 14137907 | ... AP14: =AO14 -> 14137907
B15: площадь орошаемых земель (оби) | C15: га | L15: 737694 | M15: 741539 | N15: 742051 | O15: 741626 | P15: 743621 | Q15: 743856 | R15: 748256 | S15: 749000 | T15: 749995 | U15: 753000 | V15: 753000 | W15: 753000 | X15: 598522 | Y15: 602593 | Z15: 604142 | AA15: 604537 | AB15: 605065 | AC15: 604289 | AD15: 606920 | AE15: 608046 | AF15: =AE15 -> 608046 | AG15: =AF15 -> 608046 | AH15: =AG15 -> 608046 | AI15: =AH15 -> 608046 | AJ15: =AI15 -> 608046 | AK15: =AJ15 -> 608046 | AL15: =AK15 -> 608046 | AM15: =AL15 -> 608046 | ... AP15: =AO15 -> 608046
B16: Всего СХ угодья | C16: га | L16: 4668470 | M16: 4728417 | N16: 4725644 | O16: 4719198 | P16: 4719486 | Q16: 4705044 | R16: 3695161 | S16: 3614663 | T16: 3617515 | U16: 3604616 | V16: 3611907 | W16: 3638485 | X16: 3658200 | Y16: 3669400 | Z16: 3674067 | AA16: 3673662 | AB16: 3666434 | AC16: 3668881 | AD16: 3683519 | AE16: 3692335 | AF16: =AE16 -> 3692335 | AG16: =AF16 -> 3692335 | AH16: =AG16 -> 3692335 | AI16: =AH16 -> 3692335 | AJ16: =AI16 -> 3692335 | AK16: =AJ16 -> 3692335 | AL16: =AK16 -> 3692335 | AM16: =AL16 -> 3692335 | ... AP16: =AO16 -> 3692335
B17: в том числе, | C17: га | AF17: =AE17 -> 0 | AG17: =AF17 -> 0 | AH17: =AG17 -> 0 | AI17: =AH17 -> 0 | AJ17: =AI17 -> 0 | AK17: =AJ17 -> 0 | AL17: =AK17 -> 0 | AM17: =AL17 -> 0 | ... AP17: =AO17 -> 0
B18: Пашня | C18: га | L18: 718560 | M18: 714162 | N18: 710493 | O18: 704823 | P18: 701856 | Q18: 685441 | R18: 666077 | S18: 662011 | T18: 658410 | U18: 655643 | V18: 653195 | W18: 650644 | X18: 657345 | Y18: 659009 | Z18: 663960 | AA18: 661976 | AB18: 660884 | AC18: 660054 | AD18: 661713 | AE18: 663122 | AF18: =AE18 -> 663122 | AG18: =AF18 -> 663122 | AH18: =AG18 -> 663122 | AI18: =AH18 -> 663122 | AJ18: =AI18 -> 663122 | AK18: =AJ18 -> 663122 | AL18: =AK18 -> 663122 | AM18: =AL18 -> 663122 | ... AP18: =AO18 -> 663122
B19: многолетние насождение | C19: га | L19: 101635 | M19: 103135 | N19: 105571 | O19: 105104 | P19: 109671 | Q19: 120662 | R19: 121000 | S19: 126500 | T19: 131800 | U19: 137000 | V19: 140400 | W19: 144400 | X19: 148200 | Y19: 150900 | Z19: 152800 | AA19: 153800 | AB19: 154700 | AC19: 155400 | AD19: 156900 | AE19: 157100 | AF19: =AE19 -> 157100 | AG19: =AF19 -> 157100 | AH19: =AG19 -> 157100 | AI19: =AH19 -> 157100 | AJ19: =AI19 -> 157100 | AK19: =AJ19 -> 157100 | AL19: =AK19 -> 157100 | AM19: =AL19 -> 157100 | ... AP19: =AO19 -> 157100
B20: сенокосы | C20: га | L20: 20619 | M20: 21259 | N20: 21259 | O20: 21211 | P20: 21264 | Q20: 21269 | R20: 17200 | S20: 17300 | T20: 17300 | U20: 17500 | V20: 17600 | W20: 17400 | X20: 15800 | Y20: =X20 -> 15800 | Z20: =Y20 -> 15800 | AA20: 16200 | AB20: =AA20 -> 16200 | AC20: 16100 | AD20: 16200 | AE20: 16200 | AF20: =AE20 -> 16200 | AG20: =AF20 -> 16200 | AH20: =AG20 -> 16200 | AI20: =AH20 -> 16200 | AJ20: =AI20 -> 16200 | AK20: =AJ20 -> 16200 | AL20: =AK20 -> 16200 | AM20: =AL20 -> 16200 | ... AP20: =AO20 -> 16200
B21: пастбища | C21: га | L21: 3797566 | M21: 3857776 | N21: 3856246 | O21: 3856236 | P21: 3854742 | Q21: 3846564 | R21: 2857000 | S21: 2777900 | T21: 2780000 | U21: 2764800 | V21: 2771500 | W21: 2797500 | X21: 2809600 | Y21: 2818000 | Z21: 2820800 | AA21: 2821700 | AB21: 2814800 | AC21: 2818100 | AD21: 2829700 | AE21: 2837200 | AF21: =AE21 -> 2837200 | AG21: =AF21 -> 2837200 | AH21: =AG21 -> 2837200 | AI21: =AH21 -> 2837200 | AJ21: =AI21 -> 2837200 | AK21: =AJ21 -> 2837200 | AL21: =AK21 -> 2837200 | AM21: =AL21 -> 2837200 | ... AP21: =AO21 -> 2837200
B22: залежи | C22: га | L22: 30090 | M22: 32084 | N22: 32075 | O22: 31824 | P22: 31953 | Q22: 31108 | R22: 33800 | S22: 31000 | T22: 30000 | U22: 29700 | V22: 29300 | W22: 28500 | X22: 27100 | Y22: 25700 | Z22: 20686 | AA22: 20000 | AB22: 19800 | AC22: 19300 | AD22: 19000 | AE22: 18700 | AF22: =AE22 -> 18700 | AG22: =AF22 -> 18700 | AH22: =AG22 -> 18700 | AI22: =AH22 -> 18700 | AJ22: =AI22 -> 18700 | AK22: =AJ22 -> 18700 | AL22: =AK22 -> 18700 | AM22: =AL22 -> 18700 | ... AP22: =AO22 -> 18700
B24: РАСТЕНИЕВОДСТВО | AE24: =AE26*AE29/1000 -> 2920.1
B25: Зерновые | C25: пос. площадь -га | L25: 395565 | M25: 401912 | N25: 396880 | O25: 438152 | P25: 461741 | Q25: 459942 | R25: 427178 | S25: 424332 | T25: 437440 | U25: 412626 | V25: 422947 | W25: 423449 | X25: 411581.1 | Y25: 374941.2 | Z25: 383771 | AA25: 391483.8 | AB25: 394546 | AC25: 390531 | AD25: 398318 | AE25: 390228 | AF25: =AE25 -> 390228 | AG25: =AF25 -> 390228 | AH25: =AG25 -> 390228 | AI25: =AH25 -> 390228 | AJ25: =AI25 -> 390228 | AK25: =AJ25 -> 390228 | AL25: =AK25 -> 390228 | AM25: =AL25 -> 390228 | ... AP25: =AO25 -> 390228
C26: тыс. тонн | L26: 934.9 | M26: 912.3 | N26: 931.2 | O26: 942.9 | P26: 1294.5 | Q26: 1261.1 | R26: 1098.2 | S26: 1232.6 | T26: 1392.6 | U26: 1317.8 | V26: 1392.6 | W26: 1435.8 | X26: 1447.6 | Y26: 1296.2 | Z26: 1414.638 | AA26: 1561.356 | AB26: 1586.292 | AC26: 1756.364 | AD26: 1754.89 | AE26: 1828.321 | AF26: 1740.5 | AG26: =AF26*1.05 -> 1827.525 | AH26: =AG26*1.05 -> 1918.9013 | AI26: =AH26*1.05 -> 2014.8463 | AJ26: =AI26*1.05 -> 2115.5886 | AK26: =AJ26*1.05 -> 2221.3681 | AL26: =AK26*1.05 -> 2332.4365 | AM26: =AL26*1.05 -> 2449.0583 | AN26: =AM26*1.05 -> 2571.5112 | ... AP26: =AO26*1.05 -> 2835.0911
C27: Рост, %, тыс. тонн | U27: 94.628752 | V27: 105.67613 | W27: =W26/V26*100 -> 103.10211 | X27: =X26/W26*100 -> 100.82184 | Y27: =Y26/X26*100 -> 89.54131 | Z27: =Z26/Y26*100 -> 109.13732 | AA27: 110.4 | AB27: =AB26/AA26*100 -> 101.59707 | AC27: =AC26/AB26*100 -> 110.72136 | AD27: =AD26/AC26*100 -> 99.916077 | AE27: =AE26/AD26*100 -> 104.18436 | AF27: =AF26/AE26*100 -> 95.196631 | AG27: =AG26/AF26*100 -> 105 | AH27: =AH26/AG26*100 -> 105 | AI27: =AI26/AH26*100 -> 105 | ... AP27: =AP26/AO26*100 -> 105
C28: млн. сомони | L28: х | M28: х | N28: х | O28: х | P28: 1344.6 | Q28: 1301.7 | R28: 2120.5 | S28: 2697 | T28: 2088.1 | U28: 2371.1 | V28: 2509.8 | W28: 2541.7 | X28: 2578.3 | Y28: 2307.5749 | Z28: 2519.8804 | AA28: 2782.2343 | AB28: 3527.8521 | AC28: 4674.9295 | AD28: 3851.8991 | AE28: 2920.1 | AF28: 2392.0729 | AG28: =AG29*AG26/1000 -> 2552.3124 | AH28: =AH29*AH26/1000 -> 2775.5268 | AI28: =AI29*AI26/1000 -> 3031.9989 | AJ28: =AJ29*AJ26/1000 -> 4048.7721 | AK28: =AK29*AK26/1000 -> 4268.4865 | AL28: =AL29*AL26/1000 -> 4550.5949 | AM28: =AM29*AM26/1000 -> 4836.7393 | AN28: =AN29*AN26/1000 -> 5132.9687 | ... AP28: =AP29*AP26/1000 -> 5807.9489
C29: цена, сомони\тонну | R29: 1930.8869 | S29: 2188.0578 | T29: 1499.4255 | U29: 1799.2867 | V29: =V28/V26*1000 -> 1802.2404 | W29: =W28/W26*1000 -> 1770.2326 | X29: =X28/X26*1000 -> 1781.0859 | Y29: =Y28/Y26*1000 -> 1780.2615 | Z29: =Z28/Z26*1000 -> 1781.2899 | AA29: =AA28/AA26*1000 -> 1781.9346 | AB29: =AB28/AB26*1000 -> 2223.9614 | AC29: =AC28/AC26*1000 -> 2661.7088 | ... AF29: =AF28/AF26*1000 -> 1374.3596 | AG29: =AF29*Assumptions!AG10/Assumptions!AF10*(Monetary!AG15/100-Assumptions!AG11/100) -> 1396.5951 | AH29: =AG29*Assumptions!AH10/Assumptions!AG10*(Monetary!AH15/100-Assumptions!AH11/100) -> 1446.4146 | AI29: =AH29*Assumptions!AI10/Assumptions!AH10*(Monetary!AI15/100-Assumptions!AI11/100) -> 1504.8289 | AJ29: =AI29*Assumptions!AJ10/Assumptions!AI10*(Monetary!AJ15/100-Assumptions!AJ11/100) -> 1913.7804 | AK29: =AJ29*Assumptions!AK10/Assumptions!AJ10*(Monetary!AK15/100-Assumptions!AK11/100) -> 1921.5575 | AL29: =AK29*Assumptions!AL10/Assumptions!AK10*(Monetary!AL15/100-Assumptions!AL11/100) -> 1951.0049 | AM29: =AL29*Assumptions!AM10/Assumptions!AL10*(Monetary!AM15/100-Assumptions!AM11/100) -> 1974.9384 | AN29: =AM29*Assumptions!AN10/Assumptions!AM10*(Monetary!AN15/100-Assumptions!AN11/100) -> 1996.0904 | ... AP29: =AO29*Assumptions!AP10/Assumptions!AO10*(Monetary!AP15/100-Assumptions!AP11/100) -> 2048.5934 | AR29: N28*Assumptions!O10/Assumptions!N10*(Monetary!O15/100-Assumptions!O11/100)
C30: урожайность -ц/га | L30: 19.5 | M30: 20.6 | N30: 20.5 | O30: 20.9 | P30: 25.2 | Q30: 27.418675 | R30: 23.6 | S30: 25.3 | T30: 27.7 | U30: 28.1 | V30: 27.7 | W30: 28.4 | X30: =X26/X25*10000 -> 35.171683 | Y30: =Y26/Y25*10000 -> 34.570754 | Z30: =Z26/Z25*10000 -> 36.861514 | AA30: =AA26/AA25*10000 -> 39.88303 | AB30: =AB26/AB25*10000 -> 40.205502 | AC30: =AC26/AC25*10000 -> 44.973741 | AD30: =AD26/AD25*10000 -> 44.057512 | AE30: =AE26/AE25*10000 -> 46.852635 | ... AP30: =AP26/AP25*10000 -> 72.65217
C31: урожайность стат.
B32: в том числе,
B33: пшеница | C33: пос. площадь -га | L33: 317738 | M33: 320694 | N33: 307961 | O33: 331766 | P33: 358766 | Q33: 342566 | R33: 311179 | S33: 303677 | T33: 318601 | U33: 292573 | V33: 295632 | W33: 297479 | X33: 285867 | Y33: 255548.8 | Z33: 263960 | AA33: 269645.3 | AB33: 274796 | AC33: 271067 | AD33: 275037 | AE33: 263562 | AF33: =AE33 -> 263562 | AG33: =AF33 -> 263562 | AH33: =AG33 -> 263562 | AI33: =AH33 -> 263562 | AJ33: =AI33 -> 263562 | AK33: =AJ33 -> 263562 | AL33: =AK33 -> 263562 | AM33: =AL33 -> 263562 | ... AP33: =AO33 -> 263562
C34: тыс. тонн | L34: 618.5 | M34: 640.3 | N34: 649.3 | O34: 659.1 | P34: 938.4 | Q34: 857.5 | R34: 726.9 | S34: 812.6 | T34: 947.4 | U34: 868.4 | V34: 896.4 | W34: 917.1 | X34: 900.2 | Y34: 779 | Z34: 836.884 | AA34: 864.174 | AB34: 876.152 | AC34: 934.274 | AD34: 860.489 | AE34: 880.756 | AF34: 811.3 | AG34: =AF34*1.05 -> 851.865 | AH34: =AG34*1.05 -> 894.45825 | AI34: =AH34*1.05 -> 939.18116 | AJ34: =AI34*1.05 -> 986.14022 | AK34: =AJ34*1.05 -> 1035.4472 | AL34: =AK34*1.05 -> 1087.2196 | AM34: =AL34*1.05 -> 1141.5806 | AN34: =AM34*1.05 -> 1198.6596 | ... AP34: =AO34*1.05 -> 1321.5222
C35: млн. сомони | W35: 1336.4 | X35: 1295.97
C36: урожайность -ц/га | L36: 19.6 | M36: 19.9 | N36: 20.6 | O36: 20.6 | P36: 25.1 | Q36: 23.9 | R36: 23.359545 | S36: 26.758694 | T36: 29.736253 | U36: 29.681481 | V36: =V34/V33*10000 -> 30.321481 | W36: =W34/W33*10000 -> 30.829067 | X36: =X34/X33*10000 -> 31.490169 | Y36: =Y34/Y33*10000 -> 30.483415 | Z36: =Z34/Z33*10000 -> 31.704955 | AA36: =AA34/AA33*10000 -> 32.048547 | AB36: =AB34/AB33*10000 -> 31.883725 | AC36: =AC34/AC33*10000 -> 34.466534 | ... AP36: =AP34/AP33*10000 -> 50.140848
AE37: =AE39*AE42/1000 -> 1289.7
B38: Хлопок | C38: пос. площадь -га | L38: 288655 | M38: 262894 | N38: 254830 | O38: 237130 | P38: 168916 | Q38: 162428 | R38: 204110 | S38: 199254 | T38: 190925 | U38: 177637 | V38: 159492 | W38: 162558 | X38: 173979 | Y38: 185816.8 | Z38: 185671 | AA38: 185435 | AB38: 173770 | AC38: 181542 | AD38: 166326 | AE38: 170705 | AF38: =AE38 -> 170705 | AG38: =AF38 -> 170705 | AH38: =AG38 -> 170705 | AI38: =AH38 -> 170705 | AJ38: =AI38 -> 170705 | AK38: =AJ38 -> 170705 | AL38: =AK38 -> 170705 | AM38: =AL38 -> 170705 | ... AP38: =AO38 -> 170705
C39: тыс. тонн | L39: 447.9 | M39: 437.9 | N39: 419.7 | O39: 353.1 | P39: 296 | Q39: 310.9 | R39: 416.5 | S39: 418 | T39: 392.8 | U39: 372.7 | V39: 270 | W39: 284.7 | X39: 386.5 | Y39: 300.4 | Z39: 403.008 | AA39: 396.015 | AB39: 388.804 | AC39: 404.657 | AD39: 344.35 | AE39: 253.736 | AF39: 382.9 | AG39: =Assumptions!AG47 -> 387.4948 | AH39: =Assumptions!AH47 -> 392.14474 | AI39: =Assumptions!AI47 -> 396.85047 | AJ39: =Assumptions!AJ47 -> 401.61268 | AK39: =Assumptions!AK47 -> 406.43203 | AL39: =Assumptions!AL47 -> 411.30922 | AM39: =Assumptions!AM47 -> 416.24493 | AN39: =Assumptions!AN47 -> 421.23987 | ... AP39: =Assumptions!AP47 -> 431.41028
C40: млн. сомони | L40: 0 | M40: 0 | N40: 0 | O40: 0 | P40: 550.8 | Q40: 789.4 | R40: 1509.3 | S40: 1107.5 | T40: 1327.3 | U40: 1098.8 | V40: 807.5 | W40: 1276.2 | X40: 1744.98 | Y40: 1346.577 | Z40: 1806.4932 | AA40: 1775.1149 | AB40: 1742.84 | AC40: 1851.5953 | AD40: 1922.3224 | AE40: 1289.7 | AF40: 1755.6388 | AG40: =AG39*AG42/1000 -> 1794.653 | AH40: =AH39*AH42/1000 -> 1839.1785 | AI40: =AI39*AI42/1000 -> 1977.5767 | AJ40: =AJ39*AJ42/1000 -> 2119.0316 | AK40: =AK39*AK42/1000 -> 2318.3995 | AL40: =AL39*AL42/1000 -> 2346.2203 | AM40: =AM39*AM42/1000 -> 2374.375 | AN40: =AN39*AN42/1000 -> 2402.8675 | ... AP40: =AP39*AP42/1000 -> 2460.8823
C41: урожайность -ц/га | L41: 15.6 | M41: 17 | N41: 16.6 | O41: 15.6 | P41: 17.8 | Q41: 19.3 | R41: 20.4 | S41: 21 | T41: 20.573524 | U41: 20.980989 | V41: 17.3 | W41: =W39/W38*10000 -> 17.513749 | X41: =22.4 -> 22.4 | Y41: =Y39/Y38*10000 -> 16.166461 | Z41: =Z39/Z38*10000 -> 21.70549 | AA41: =AA39/AA38*10000 -> 21.356001 | AB41: =AB39/AB38*10000 -> 22.374633 | AC41: =AC39/AC38*10000 -> 22.289994 | AD41: =AD39/AD38*10000 -> 20.703318 | AE41: =AE39/AE38*10000 -> 14.864005 | AF41: =AF39/AF38*10000 -> 22.430509 | ... AP41: =AP39/AP38*10000 -> 25.27227
C42: цена | V42: =V40/V39*1000 -> 2990.7407 | W42: =W40/W39*1000 -> 4482.6133 | X42: =X40/X39*1000 -> 4514.8254 | Y42: =Y40/Y39*1000 -> 4482.6133 | Z42: =Z40/Z39*1000 -> 4482.5243 | AA42: =AA40/AA39*1000 -> 4482.4435 | AB42: =AB40/AB39*1000 -> 4482.5672 | AC42: =AC40/AC39*1000 -> 4575.7154 | ... AF42: =AF40/AF39*1000 -> 4585.1104 | AG42: =AF42*Assumptions!AG9/Assumptions!AF9 -> 4631.4247 | AH42: =AG42*Assumptions!AH9/Assumptions!AG9 -> 4690.0503 | AI42: =AH42*Assumptions!AI9/Assumptions!AH9 -> 4983.1784 | AJ42: =AI42*Assumptions!AJ9/Assumptions!AI9 -> 5276.3066 | AK42: =AJ42*Assumptions!AK9/Assumptions!AJ9 -> 5704.2737 | AL42: =AK42*Assumptions!AL9/Assumptions!AK9 -> 5704.2737 | AM42: =AL42*Assumptions!AM9/Assumptions!AL9 -> 5704.2737 | AN42: =AM42*Assumptions!AN9/Assumptions!AM9 -> 5704.2737 | ... AP42: =AO42*Assumptions!AP9/Assumptions!AO9 -> 5704.2737
B43: в том числе, | AE43: =AE49*AE52/1000 -> 1051.1
B44: хлопковолокно | C44: пос. площадь -га | L44: 17346 | M44: 25442 | N44: 14538 | O44: 8298 | P44: 897 | Q44: 775 | R44: 1943 | S44: 2023 | T44: 370 | U44: 135 | AD44: =AD45/1000 -> 5632.8244 | AE44: =AE45/1000 -> 5776.2469
C45: тонн | L45: 28463 | M45: 37099 | N45: 28320 | O45: 10753 | P45: 1988 | Q45: 1717 | R45: 4133 | S45: 3813 | T45: 615 | U45: 411 | AD45: =AD47*AD46 -> 5632824.4 | AE45: =AE47*AE46 -> 5776246.9
C46: млн. сомони | AC46: =AE49*AE44/1000 -> 7300.8815 | AD46: 4.92 | AE46: 4.57
C47: урожайность -ц/га | Q47: 22.2 | R47: 21.3 | S47: 18.8 | T47: 16.6 | U47: 17.2 | AC47: =AD49*AD44/1000 -> 6448.9249 | AD47: =AD49*1000 -> 1144883 | AE47: =AE49*1000 -> 1263949
B48: Картошка | C48: пос. площадь -га | L48: 27483 | M48: 27935 | N48: 29752 | O48: 28676 | P48: 29838 | Q48: 31764 | R48: 36720 | S48: 41738 | T48: 44380 | U48: 35543 | V48: 39782 | W48: 41577 | X48: 40615.1 | Y48: 49600 | Z48: 51756 | AA48: 52730.8 | AB48: 57204 | AC48: 56092 | AD48: 56577 | AE48: 64504 | AF48: =AE48 -> 64504 | AG48: =AF48 -> 64504 | AH48: =AG48 -> 64504 | AI48: =AH48 -> 64504 | AJ48: =AI48 -> 64504 | AK48: =AJ48 -> 64504 | AL48: =AK48 -> 64504 | AM48: =AL48 -> 64504 | ... AP48: =AO48 -> 64504
C49: тыс. тонн | L49: 555.1 | M49: 573.7 | N49: 662.1 | O49: 679.8 | P49: 690.8 | Q49: 760.1 | R49: 863.1 | S49: 991 | T49: 1115.7 | U49: 853.7 | V49: 887.4 | W49: 898.1 | X49: 782.9 | Y49: 964.6 | Z49: 994.433 | AA49: 1022.545 | AB49: 1041.316 | AC49: 1094.438 | AD49: 1144.883 | AE49: 1263.949 | AF49: 1332.5 | AG49: =AF49*1.02 -> 1359.15 | AH49: =AG49*1.02 -> 1386.333 | AI49: =AH49*1.02 -> 1414.0597 | AJ49: =AI49*1.02 -> 1442.3409 | AK49: =AJ49*1.02 -> 1471.1877 | AL49: =AK49*1.02 -> 1500.6114 | AM49: =AL49*1.02 -> 1530.6237 | AN49: =AM49*1.02 -> 1561.2361 | ... AP49: =AO49*1.02 -> 1624.3101
C50: млн. сомони | L50: х | M50: х | N50: х | O50: х | P50: 824.7 | Q50: 860.9 | R50: 1400.6 | S50: 1685.7 | T50: 1748.9 | U50: 1978.1 | V50: 2058.7 | W50: 1491 | X50: 1318.5 | Y50: 1318.5 | Z50: 1318.5 | AA50: 1318.5 | AB50: 1013.1988 | AC50: 1035.8012 | AD50: 928.85119 | AE50: 1051.1 | AF50: 1086.4756 | AG50: =AG49*AG52/1000 -> 1101.735 | AH50: =AH49*AH52/1000 -> 1143.1861 | AI50: =AI49*AI52/1000 -> 1192.3602 | AJ50: =AJ49*AJ52/1000 -> 1235.9331 | AK50: =AK49*AK52/1000 -> 1265.7747 | AL50: =AL49*AL52/1000 -> 1310.8758 | AM50: =AM49*AM52/1000 -> 1353.4959 | AN50: =AN49*AN52/1000 -> 1395.3519 | ... AP50: =AP49*AP52/1000 -> 1489.9087
C51: урожайность -ц/га | L51: 196.2 | M51: 198.5 | N51: 218.4 | O51: 226.9 | P51: 223.1 | Q51: 229.7 | R51: 228.3 | S51: 233.2 | T51: 247.3 | U51: 231 | V51: 221.7 | W51: 214.4 | X51: =X49/X48*10000 -> 192.76082 | Y51: =Y49/Y48*10000 -> 194.47581 | Z51: =Z49/Z48*10000 -> 192.13869 | AA51: =AA49/AA48*10000 -> 193.91798 | AB51: =AB49/AB48*10000 -> 182.03552 | AC51: =AC49/AC48*10000 -> 195.11481 | AD51: =AD49/AD48*10000 -> 202.35838 | AE51: =AE49/AE48*10000 -> 195.94893 | ... AP51: =AP49/AP48*10000 -> 251.8154
C52: цена | P52: 1193.8332 | Q52: 1132.6141 | R52: 1622.7552 | S52: 1701.0091 | T52: 1567.5361 | U52: 2317.0903 | V52: =V50/V49*1000 -> 2319.9234 | W52: =W50/W49*1000 -> 1660.1715 | X52: =X50/X49*1000 -> 1684.1231 | Y52: =Y50/Y49*1000 -> 1366.8878 | Z52: =Z50/Z49*1000 -> 1325.8812 | AA52: =AA50/AA49*1000 -> 1289.4298 | AB52: =AB50/AB49*1000 -> 972.99836 | AC52: =AC50/AC49*1000 -> 946.42291 | ... AF52: =AF50/AF49*1000 -> 815.36632 | AG52: =AF52*Assumptions!AG8/Assumptions!AF8*(Monetary!AG15/100-Assumptions!AG11/100) -> 810.60587 | AH52: =AG52*Assumptions!AH8/Assumptions!AG8*(Monetary!AH15/100-Assumptions!AH11/100) -> 824.61148 | AI52: =AH52*Assumptions!AI8/Assumptions!AH8*(Monetary!AI15/100-Assumptions!AI11/100) -> 843.21774 | AJ52: =AI52*Assumptions!AJ8/Assumptions!AI8*(Monetary!AJ15/100-Assumptions!AJ11/100) -> 856.89393 | AK52: =AJ52*Assumptions!AK8/Assumptions!AJ8*(Monetary!AK15/100-Assumptions!AK11/100) -> 860.37611 | AL52: =AK52*Assumptions!AL8/Assumptions!AK8*(Monetary!AL15/100-Assumptions!AL11/100) -> 873.56114 | AM52: =AL52*Assumptions!AM8/Assumptions!AL8*(Monetary!AM15/100-Assumptions!AM11/100) -> 884.27737 | AN52: =AM52*Assumptions!AN8/Assumptions!AM8*(Monetary!AN15/100-Assumptions!AN11/100) -> 893.74814 | ... AP52: =AO52*Assumptions!AP8/Assumptions!AO8*(Monetary!AP15/100-Assumptions!AP11/100) -> 917.25634
AE53: =AE55*AE58/1000 -> 7996.7
B54: Овощи | C54: пос. площадь -га | L54: 33429 | M54: 35768 | N54: 39110 | O54: 37162 | P54: 40803 | Q54: 44769 | R54: 46885 | S54: 48995 | T54: 50727 | U54: 48532 | V54: 55424 | W54: 58194 | X54: 59538 | Y54: 68298.2 | Z54: 67016 | AA54: 70439.7 | AB54: 71240 | AC54: 69992 | AD54: 73464 | AE54: 75227 | AF54: =AE54 -> 75227 | AG54: =AF54 -> 75227 | AH54: =AG54 -> 75227 | AI54: =AH54 -> 75227 | AJ54: =AI54 -> 75227 | AK54: =AJ54 -> 75227 | AL54: =AK54 -> 75227 | AM54: =AL54 -> 75227 | ... AP54: =AO54 -> 75227
C55: тыс. тонн | L55: 718.5 | M55: 759.7 | N55: 835.1 | O55: 908.2 | P55: 1046.8 | Q55: 1142.6 | R55: 1242 | S55: 1342.4 | T55: 1490.6 | U55: 1549.5 | V55: 1666.6 | W55: 1748.3 | X55: 1859.1 | Y55: 2119.4 | Z55: 2182.556 | AA55: 2479.36 | AB55: 2597.577 | AC55: 2714.825 | AD55: 3026.223 | AE55: 3298.693 | AF55: 3377.9 | AG55: =AF55*1.05 -> 3546.795 | AH55: =AG55*1.05 -> 3724.1348 | AI55: =AH55*1.05 -> 3910.3415 | AJ55: =AI55*1.05 -> 4105.8586 | AK55: =AJ55*1.05 -> 4311.1515 | AL55: =AK55*1.05 -> 4526.7091 | AM55: =AL55*1.05 -> 4753.0445 | AN55: =AM55*1.05 -> 4990.6967 | ... AP55: =AO55*1.05 -> 5502.2432
C56: млн. сомони | L56: х | M56: х | N56: х | O56: х | P56: 1443.9 | Q56: 1736.3 | R56: 3218.3 | S56: 3275.7 | T56: 2869.1 | U56: 3812.2 | V56: 4002.9 | W56: 4752.2 | X56: 5012.2 | Y56: 5012.2 | Z56: 5012.2 | AA56: 5012.2 | AB56: 5676.6345 | AC56: 6157.9161 | AD56: 7110.4164 | AE56: 7996.7 | AF56: 8471.6339 | AG56: =AG55*AG58/1000 -> 9108.1725 | AH56: =AH55*AH58/1000 -> 9974.289 | AI56: =AI55*AI58/1000 -> 11012.384 | AJ56: =AJ55*AJ58/1000 -> 11641.742 | AK56: =AK55*AK58/1000 -> 12273.504 | AL56: =AL55*AL58/1000 -> 13084.671 | AM56: =AM55*AM58/1000 -> 13907.444 | AN56: =AN55*AN58/1000 -> 14759.215 | ... AP56: =AP55*AP58/1000 -> 16700.037
C57: урожайность -ц/га | L57: 186.8 | M57: 186.9 | N57: 190.2 | O57: 198.8 | P57: 208 | Q57: 205.8 | R57: 216.5 | S57: 225.1 | T57: 240.3 | U57: 251.1 | V57: 247.9 | W57: 248.6 | X57: =256.8 -> 256.8 | Y57: =256.8 -> 256.8 | Z57: =256.8 -> 256.8 | AA57: =256.8 -> 256.8 | AB57: =AB55/AB54*10000 -> 364.62339 | AC57: =AC55/AC54*10000 -> 387.87647 | AD57: =AD55/AD54*10000 -> 411.93278 | AE57: =AE55/AE54*10000 -> 438.49854 | AF57: =AF55/AF54*10000 -> 449.02761 | AG57: =AG55/AG54*10000 -> 471.47899 | AH57: =AH55/AH54*10000 -> 495.05294 | AI57: =AI55/AI54*10000 -> 519.80559 | ... AP57: =AP55/AP54*10000 -> 731.41866
C58: цена | P58: 1379.3466 | Q58: 1519.6044 | R58: 2591.2238 | S58: 2440.1818 | T58: 1924.7954 | U58: 2460.2775 | V58: =V56/V55*1000 -> 2401.8361 | W58: =W56/W55*1000 -> 2718.1834 | X58: =X56/X55*1000 -> 2696.0357 | Y58: =Y56/Y55*1000 -> 2364.9146 | Z58: =Z56/Z55*1000 -> 2296.4817 | AA58: =AA56/AA55*1000 -> 2021.5701 | AB58: =AB56/AB55*1000 -> 2185.3575 | AC58: =AC56/AC55*1000 -> 2268.2553 | ... AF58: =AF56/AF55*1000 -> 2507.9588 | AG58: =AF58*Assumptions!AG20/Assumptions!AF20*(Monetary!AG15/100-Assumptions!AG11/100) -> 2568.0008 | AH58: =AG58*Assumptions!AH20/Assumptions!AG20*(Monetary!AH15/100-Assumptions!AH11/100) -> 2678.2836 | AI58: =AH58*Assumptions!AI20/Assumptions!AH20*(Monetary!AI15/100-Assumptions!AI11/100) -> 2816.2204 | AJ58: =AI58*Assumptions!AJ20/Assumptions!AI20*(Monetary!AJ15/100-Assumptions!AJ11/100) -> 2835.3978 | AK58: =AJ58*Assumptions!AK20/Assumptions!AJ20*(Monetary!AK15/100-Assumptions!AK11/100) -> 2846.9201 | AL58: =AK58*Assumptions!AL20/Assumptions!AK20*(Monetary!AL15/100-Assumptions!AL11/100) -> 2890.5484 | AM58: =AL58*Assumptions!AM20/Assumptions!AL20*(Monetary!AM15/100-Assumptions!AM11/100) -> 2926.0076 | AN58: =AM58*Assumptions!AN20/Assumptions!AM20*(Monetary!AN15/100-Assumptions!AN11/100) -> 2957.3456 | ... AP58: =AO58*Assumptions!AP20/Assumptions!AO20*(Monetary!AP15/100-Assumptions!AP11/100) -> 3035.1325
B59: в том числе,
B60: Лук | C60: пос. площадь -га | P60: 12478 | Q60: 14499 | R60: 15595 | S60: 16215 | T60: 17449 | U60: 15565
C61: тыс. тонн | L61: 201.4 | M61: 201.7 | N61: 251.6 | O61: 227.2 | P61: 268.5 | Q61: 302.3 | R61: 343.4 | S61: 368 | T61: 435.4 | U61: 420.8
C62: млн. сомони
C63: урожайность -ц/га | L63: 189.5 | M63: 194.5 | N63: 203.1 | O63: 212.2 | P63: 215 | Q63: 210.4 | R63: 221.3 | S63: 227.3 | T63: 248.7 | U63: 269.7 | AE63: =AE65*AE68/1000 -> 2129.2
B64: Бахчевые | C64: пос. площадь -га | L64: 9193 | M64: 9110 | N64: 11118 | O64: 11570 | P64: 19313 | Q64: 20951 | R64: 17218 | S64: 18409 | T64: 17353 | U64: 19399 | V64: 21358 | W64: 20069.2 | X64: 20296 | Y64: 19926.6 | Z64: 21883 | AA64: 22753.9 | AB64: 22595 | AC64: 20664 | AD64: 23801 | AE64: 25131 | AF64: =AE64 -> 25131 | AG64: =AF64 -> 25131 | AH64: =AG64 -> 25131 | AI64: =AH64 -> 25131 | AJ64: =AI64 -> 25131 | AK64: =AJ64 -> 25131 | AL64: =AK64 -> 25131 | AM64: =AL64 -> 25131 | ... AP64: =AO64 -> 25131
C65: тыс. тонн | L65: 170.2 | M65: 218.2 | N65: 254.2 | O65: 285.2 | P65: 424.6 | Q65: 482.4 | R65: 423.3 | S65: 465 | T65: 495.2 | U65: 545.7 | V65: 592.4 | W65: 594.2 | X65: 631.2 | Y65: 641.7 | Z65: 701.263 | AA65: 756.962 | AB65: 818.829 | AC65: 842.635 | AD65: 1009.915 | AE65: 1144.806 | AF65: 1254.4 | AG65: =AF65*1.005 -> 1260.672 | AH65: =AG65*1.005 -> 1266.9754 | AI65: =AH65*1.005 -> 1273.3102 | AJ65: =AI65*1.005 -> 1279.6768 | AK65: =AJ65*1.005 -> 1286.0752 | AL65: =AK65*1.005 -> 1292.5055 | AM65: =AL65*1.005 -> 1298.9681 | AN65: =AM65*1.005 -> 1305.4629 | ... AP65: =AO65*1.005 -> 1318.5502
C66: млн. сомони | L66: х | M66: х | N66: х | O66: х | P66: 223.8 | Q66: 347.7 | R66: 507.7 | S66: 373.5 | T66: 585.1 | U66: 1055.2 | V66: 1132.3 | W66: 1093.5 | X66: 1170.1 | Y66: 1170.1 | Z66: 1170.1 | AA66: 1170.1 | AB66: 1368.8376 | AC66: 1462.0857 | AD66: 1815.2282 | AE66: 2129.2 | AF66: 2413.6378 | AG66: =AG65*AG68/1000 -> 2483.7788 | AH66: =AH65*AH68/1000 -> 2603.3969 | AI66: =AI65*AI68/1000 -> 2751.1643 | AJ66: =AJ65*AJ68/1000 -> 2783.7482 | AK66: =AK65*AK68/1000 -> 2809.0359 | AL66: =AL65*AL68/1000 -> 2866.344 | AM66: =AM65*AM68/1000 -> 2916.0138 | AN66: =AN65*AN68/1000 -> 2961.9811 | ... AP66: =AP65*AP68/1000 -> 3070.3648
C67: урожайность -ц/га | L67: 1145.7 | M67: 185.7 | N67: 189 | O67: 197.6 | P67: 202.9 | Q67: 230.25154 | R67: 245.84737 | S67: 252.59384 | T67: 285.36852 | U67: 281.30316 | V67: =V65/V64*10000 -> 277.36679 | W67: =W65/W64*10000 -> 296.07558 | X67: =263.3 -> 263.3 | Y67: =263.3 -> 263.3 | Z67: =263.3 -> 263.3 | AA67: =263.3 -> 263.3 | AB67: =AB65/AB64*10000 -> 362.39389 | AC67: =AC65/AC64*10000 -> 407.77923 | AD67: =AD65/AD64*10000 -> 424.31621 | AE67: =AE65/AE64*10000 -> 455.53539 | AF67: =AF65/AF64*10000 -> 499.14448 | AG67: =AG65/AG64*10000 -> 501.64021 | AH67: =AH65/AH64*10000 -> 504.14841 | AI67: =AI65/AI64*10000 -> 506.66915 | ... AP67: =AP65/AP64*10000 -> 524.6708
C68: цена | P68: 527.08431 | Q68: 720.77114 | R68: 1199.3858 | S68: 803.22581 | T68: 1181.5428 | U68: 1933.6632 | V68: =V66/V65*1000 -> 1911.3774 | W68: =W66/W65*1000 -> 1840.2895 | X68: =X66/X65*1000 -> 1853.7706 | Y68: =Y66/Y65*1000 -> 1823.4377 | Z68: =Z66/Z65*1000 -> 1668.5609 | AA68: =AA66/AA65*1000 -> 1545.7843 | AB68: =AB66/AB65*1000 -> 1671.7015 | AC68: =AC66/AC65*1000 -> 1735.1353 | ... AF68: =AF66/AF65*1000 -> 1924.1372 | AG68: =AF68*Assumptions!AG20/Assumptions!AF20*(Monetary!AG15/100-Assumptions!AG11/100) -> 1970.2023 | AH68: =AG68*Assumptions!AH20/Assumptions!AG20*(Monetary!AH15/100-Assumptions!AH11/100) -> 2054.8126 | AI68: =AH68*Assumptions!AI20/Assumptions!AH20*(Monetary!AI15/100-Assumptions!AI11/100) -> 2160.6395 | AJ68: =AI68*Assumptions!AJ20/Assumptions!AI20*(Monetary!AJ15/100-Assumptions!AJ11/100) -> 2175.3526 | AK68: =AJ68*Assumptions!AK20/Assumptions!AJ20*(Monetary!AK15/100-Assumptions!AK11/100) -> 2184.1926 | AL68: =AK68*Assumptions!AL20/Assumptions!AK20*(Monetary!AL15/100-Assumptions!AL11/100) -> 2217.6648 | AM68: =AL68*Assumptions!AM20/Assumptions!AL20*(Monetary!AM15/100-Assumptions!AM11/100) -> 2244.8695 | AN68: =AM68*Assumptions!AN20/Assumptions!AM20*(Monetary!AN15/100-Assumptions!AN11/100) -> 2268.9125 | ... AP68: =AO68*Assumptions!AP20/Assumptions!AO20*(Monetary!AP15/100-Assumptions!AP11/100) -> 2328.5915
Q69: 204.2 | R69: 205.9 | S69: 209.7 | T69: 223.8 | U69: 281.28866 | AE69: =AE71*AE74/1000 -> 3538.6
B70: Фрукты | C70: пос. площадь -га | L70: 60870 | M70: 67087 | N70: 69850 | O70: 73807 | P70: 73293 | Q70: 73850 | R70: 115423 | S70: 122009 | T70: 130682 | U70: 135430 | V70: 140344 | W70: 146565 | X70: 150312.8 | Y70: 158940.7 | Z70: 160533 | AA70: 161837 | AB70: 160973 | AC70: 164394 | AD70: 166612 | AE70: 170090 | AF70: =AE70+3000 -> 173090 | AG70: =AF70+3000 -> 176090 | AH70: =AG70+3000 -> 179090 | AI70: =AH70+3000 -> 182090 | AJ70: =AI70+3000 -> 185090 | AK70: =AJ70+3000 -> 188090 | AL70: =AK70+3000 -> 191090 | AM70: =AL70+3000 -> 194090 | ... AP70: =AO70+3000 -> 203090
C71: тыс. тонн | L71: 148.3 | M71: 208.8 | N71: 157.2 | O71: 262.4 | P71: 213.9 | Q71: 224.7 | R71: 263.1 | S71: 313.2 | T71: 328.5 | U71: 341.3 | V71: 299.3 | W71: 364.1 | X71: 405 | Y71: 447.7 | Z71: 473.757 | AA71: 467.802 | AB71: 444.378 | AC71: 512.049 | AD71: 664.343 | AE71: 823.05 | AF71: 954.3 | AG71: =AF71*1.04 -> 992.472 | AH71: =AG71*1.04 -> 1032.1709 | AI71: =AH71*1.04 -> 1073.4577 | AJ71: =AI71*1.04 -> 1116.396 | AK71: =AJ71*1.04 -> 1161.0519 | AL71: =AK71*1.04 -> 1207.4939 | AM71: =AL71*1.04 -> 1255.7937 | AN71: =AM71*1.04 -> 1306.0254 | ... AP71: =AO71*1.04 -> 1412.5971
C72: млн. сомони | L72: х | M72: х | N72: х | O72: х | P72: 457.9 | Q72: 595.4 | R72: 1111.7 | S72: 1092.2 | T72: 1209.1 | U72: 1717.7 | V72: 1525.1 | W72: =V72*1.02 -> 1555.602 | X72: =W72*1.02 -> 1586.714 | Y72: =X72*1.02 -> 1618.4483 | Z72: =Y72*1.02 -> 1650.8173 | AA72: =Z72*1.02 -> 1683.8336 | AB72: =AA72*1.02 -> 1717.5103 | AC72: 2054.2692 | AD72: 2760.3764 | AE72: 3538.6 | AF72: 4244.6478 | AG72: =AG71*AG74/1000 -> 4520.118 | AH72: =AH71*AH74/1000 -> 4902.8038 | AI72: =AI71*AI74/1000 -> 5361.5201 | AJ72: =AJ71*AJ74/1000 -> 5613.9511 | AK72: =AK71*AK74/1000 -> 5862.2353 | AL72: =AL71*AL74/1000 -> 6190.1553 | AM72: =AM71*AM74/1000 -> 6516.7354 | AN72: =AN71*AN74/1000 -> 6849.9921 | ... AP72: =AP71*AP74/1000 -> 7603.8287
C73: урожайность -ц/га | L73: 24.3 | M73: 31.1 | N73: 22.5 | O73: 35.5 | P73: 29.2 | Q73: 30.4 | R73: 22.794417 | S73: 25.670237 | T73: 25.137356 | U73: 25.201211 | V73: =V71/V70*10000 -> 21.32617 | W73: =W71/W70*10000 -> 24.84222 | X73: =X71/X70*10000 -> 26.943813 | Y73: =Y71/Y70*10000 -> 28.167738 | Z73: =Z71/Z70*10000 -> 29.511502 | AA73: =AA71/AA70*10000 -> 28.905751 | AB73: =AB71/AB70*10000 -> 27.605748 | AC73: =AC71/AC70*10000 -> 31.14767 | ... AP73: =AP71/AP70*10000 -> 69.555228
C74: цена | P74: 2140.72 | Q74: 2649.7552 | R74: 4225.3896 | S74: 3487.2286 | T74: 3680.6697 | U74: 5032.8157 | V74: =V72/V71*1000 -> 5095.5563 | W74: =W72/W71*1000 -> 4272.4581 | X74: =X72/X71*1000 -> 3917.8124 | Y74: =Y72/Y71*1000 -> 3615.0286 | Z74: =Z72/Z71*1000 -> 3484.5233 | AA74: =AA72/AA71*1000 -> 3599.458 | AB74: =AB72/AB71*1000 -> 3864.976 | AC74: =AC72/AC71*1000 -> 4011.8605 | ... AF74: =AF72/AF71*1000 -> 4447.9177 | AG74: =AF74*Assumptions!AG20/Assumptions!AF20*(Monetary!AG15/100-Assumptions!AG11/100) -> 4554.4035 | AH74: =AG74*Assumptions!AH20/Assumptions!AG20*(Monetary!AH15/100-Assumptions!AH11/100) -> 4749.9924 | AI74: =AH74*Assumptions!AI20/Assumptions!AH20*(Monetary!AI15/100-Assumptions!AI11/100) -> 4994.6263 | AJ74: =AI74*Assumptions!AJ20/Assumptions!AI20*(Monetary!AJ15/100-Assumptions!AJ11/100) -> 5028.6377 | AK74: =AJ74*Assumptions!AK20/Assumptions!AJ20*(Monetary!AK15/100-Assumptions!AK11/100) -> 5049.0727 | AL74: =AK74*Assumptions!AL20/Assumptions!AK20*(Monetary!AL15/100-Assumptions!AL11/100) -> 5126.4484 | AM74: =AL74*Assumptions!AM20/Assumptions!AL20*(Monetary!AM15/100-Assumptions!AM11/100) -> 5189.336 | AN74: =AM74*Assumptions!AN20/Assumptions!AM20*(Monetary!AN15/100-Assumptions!AN11/100) -> 5244.9148 | ... AP74: =AO74*Assumptions!AP20/Assumptions!AO20*(Monetary!AP15/100-Assumptions!AP11/100) -> 5382.8714
AE75: =AE77*AE80/1000 -> 1908.6
B76: Виноград | C76: пос. площадь -га | L76: 31452 | M76: 31745 | N76: 32838 | O76: 31944 | P76: 31419 | Q76: 30470 | R76: 36508 | S76: 36511 | T76: 37812 | U76: 36125 | V76: 38707 | W76: 37061 | X76: 33300 | Y76: 38106 | Z76: 38570 | AA76: 39815 | AB76: 39449 | AC76: 39721 | AD76: 39923 | AE76: 38306 | AF76: =AE76*1.02 -> 39072.12 | AG76: =AF76*1.02 -> 39853.562 | AH76: =AG76*1.02 -> 40650.634 | AI76: =AH76*1.02 -> 41463.646 | AJ76: =AI76*1.02 -> 42292.919 | AK76: =AJ76*1.02 -> 43138.778 | AL76: =AK76*1.02 -> 44001.553 | AM76: =AL76*1.02 -> 44881.584 | ... AP76: =AO76*1.02 -> 47628.696
C77: тыс. тонн | L77: 90.7 | M77: 107.2 | N77: 116.9 | O77: 117.9 | P77: 138.7 | Q77: 124.3 | R77: 154.7 | S77: 167.1 | T77: 175.2 | U77: 188.8 | V77: 203.8 | W77: 214.8 | X77: 228.3 | Y77: 241.8 | Z77: 247.167 | AA77: 239.096 | AB77: 267.475 | AC77: 301.112 | AD77: 190.376 | AE77: 289.932 | AF77: 346.1 | AG77: =AF77*1.02 -> 353.022 | AH77: =AG77*1.02 -> 360.08244 | AI77: =AH77*1.02 -> 367.28409 | AJ77: =AI77*1.02 -> 374.62977 | AK77: =AJ77*1.02 -> 382.12237 | AL77: =AK77*1.02 -> 389.76481 | AM77: =AL77*1.02 -> 397.56011 | AN77: =AM77*1.02 -> 405.51131 | ... AP77: =AO77*1.02 -> 421.89397
C78: млн. сомони | L78: х | M78: х | N78: х | O78: х | P78: 298.4 | Q78: 490.3 | R78: 492.3 | S78: 621.1 | T78: 793 | U78: 1130 | V78: 1212.5 | W78: 1279.1 | X78: 1419.2 | Y78: 1419.2 | Z78: 1419.2 | AA78: 1419.2 | AB78: 1582.476 | AC78: 1848.8487 | AD78: 1211.0416 | AE78: 1908.6 | AF78: 2357.0666 | AG78: =AG77*AG80/1000 -> 2461.7661 | AH78: =AH77*AH80/1000 -> 2618.8364 | AI78: =AI77*AI80/1000 -> 2808.7858 | AJ78: =AJ77*AJ80/1000 -> 2884.4708 | AK78: =AK77*AK80/1000 -> 2954.1164 | AL78: =AL77*AL80/1000 -> 3059.3751 | AM78: =AM77*AM80/1000 -> 3158.8435 | AN78: =AN77*AN80/1000 -> 3256.5288 | ... AP78: =AP77*AP80/1000 -> 3477.2093
C79: урожайность -ц/га | L79: 28.8 | M79: 33.1 | N79: 35.6 | O79: 36.9 | P79: 44.1 | Q79: 40.8 | R79: 42.374274 | S79: 45.767029 | T79: 46.334497 | U79: 52.262976 | V79: =V77/V76*10000 -> 52.651975 | W79: =W77/W76*10000 -> 57.958501 | X79: =X77/X76*10000 -> 68.558559 | Y79: =Y77/Y76*10000 -> 63.454574 | Z79: =Z77/Z76*10000 -> 64.082707 | AA79: =AA77/AA76*10000 -> 60.051739 | AB79: =AB77/AB76*10000 -> 67.802733 | AC79: =AC77/AC76*10000 -> 75.806752 | ... AP79: =AP77/AP76*10000 -> 88.579785
C80: цена | P80: 2151.4059 | Q80: 3944.4891 | R80: 3182.2883 | S80: 3716.936 | T80: 4526.2557 | U80: 5985.1695 | V80: =V78/V77*1000 -> 5949.4603 | W80: =W78/W77*1000 -> 5954.8417 | X80: =X78/X77*1000 -> 6216.382 | Y80: =Y78/Y77*1000 -> 5869.3135 | Z80: =Z78/Z77*1000 -> 5741.8668 | AA80: =AA78/AA77*1000 -> 5935.6911 | AB80: =AB78/AB77*1000 -> 5916.3512 | AC80: =AC78/AC77*1000 -> 6140.0699 | ... AF80: =AF78/AF77*1000 -> 6810.3629 | AG80: =AF80*Assumptions!AG20/Assumptions!AF20*(Monetary!AG15/100-Assumptions!AG11/100) -> 6973.4071 | AH80: =AG80*Assumptions!AH20/Assumptions!AG20*(Monetary!AH15/100-Assumptions!AH11/100) -> 7272.8801 | AI80: =AH80*Assumptions!AI20/Assumptions!AH20*(Monetary!AI15/100-Assumptions!AI11/100) -> 7647.4476 | AJ80: =AI80*Assumptions!AJ20/Assumptions!AI20*(Monetary!AJ15/100-Assumptions!AJ11/100) -> 7699.5237 | AK80: =AJ80*Assumptions!AK20/Assumptions!AJ20*(Monetary!AK15/100-Assumptions!AK11/100) -> 7730.8125 | AL80: =AK80*Assumptions!AL20/Assumptions!AK20*(Monetary!AL15/100-Assumptions!AL11/100) -> 7849.2851 | AM80: =AL80*Assumptions!AM20/Assumptions!AL20*(Monetary!AM15/100-Assumptions!AM11/100) -> 7945.5745 | AN80: =AM80*Assumptions!AN20/Assumptions!AM20*(Monetary!AN15/100-Assumptions!AN11/100) -> 8030.6731 | ... AP80: =AO80*Assumptions!AP20/Assumptions!AO20*(Monetary!AP15/100-Assumptions!AP11/100) -> 8241.9034
R81: 534.3 | S81: 983.6 | T81: 881.9 | U81: 1369.7
B82: Прочее | L82: 109912 | M82: 131368 | N82: 130315 | O82: 108238 | P82: 122587 | Q82: 87710 | R82: 86042 | S82: 94881 | T82: 91823 | U82: 104620 | V82: =V5-V28-V40-V50-V56-V66-V72-V78 -> 1374.9 | W82: =W5-W28-W40-W50-W56-W66-W72-W78 -> 1077.298 | X82: =X5-X28-X40-X50-X56-X66-X72-X78 -> 2147.806 | Y82: =Y5-Y28-Y40-Y50-Y56-Y66-Y72-Y78 -> 17477 | Z82: =Z5-Z28-Z40-Z50-Z56-Z66-Z72-Z78 -> 19226.809 | AA82: =AA5-AA28-AA40-AA50-AA56-AA66-AA72-AA78 -> 21758.217 | AB82: =AB5-AB28-AB40-AB50-AB56-AB66-AB72-AB78 -> 22486.251 | AC82: =AC5-AC28-AC40-AC50-AC56-AC66-AC72-AC78 -> 23029.554 | ... AF82: =AF5-AF28-AF40-AF50-AF56-AF66-AF72-AF78 -> 33866.827 | AG82: =AF82*1.099 -> 37219.642 | AH82: =AG82*1.101 -> 40978.826 | AI82: =AH82*1.084 -> 44421.048 | AJ82: =AI82*1.09094 -> 48460.698 | AK82: =AJ82*1.1 -> 53306.768 | AL82: =AK82*1.069 -> 56984.935 | AM82: =AL82*1.065 -> 60688.955 | AN82: =AM82*1.055 -> 64026.848 | AO82: =AN82*1.045 -> 66908.056 | AP82: =AO82*1.035 -> 69249.838
B83: пос. площадь для корм животных | C83: (ГА) | Q83: 318.6 | R83: 349.1 | V83: =V28+V40+V50+V56+V66+V72+V78 -> 13248.8 | W83: =W28+W40+W50+W56+W66+W72+W78 -> 13989.302 | X83: =X28+X40+X50+X56+X66+X72+X78 -> 14829.994 | Y83: =Y28+Y40+Y50+Y56+Y66+Y72+Y78 -> 14192.6 | Z83: =Z28+Z40+Z50+Z56+Z66+Z72+Z78 -> 14897.191 | AA83: =AA28+AA40+AA50+AA56+AA66+AA72+AA78 -> 15161.183 | AB83: =AB28+AB40+AB50+AB56+AB66+AB72+AB78 -> 16629.349 | AC83: =AC28+AC40+AC50+AC56+AC66+AC72+AC78 -> 19085.446 | ... AP83: =AP28+AP40+AP50+AP56+AP66+AP72+AP78 -> 40610.18
C84: продуктивность | V84: =V5-V83 -> 1374.9 | W84: =W5-W83 -> 1077.298 | X84: =X5-X83 -> 2147.806 | Y84: =Y5-Y83 -> 17477 | Z84: =Z5-Z83 -> 19226.809 | AA84: =AA5-AA83 -> 21758.217 | AB84: =AB5-AB83 -> 22486.251 | AC84: =AC5-AC83 -> 23029.554 | ... AP84: =AP5-AP83 -> 69249.838
B85: 2. Животноводство | Q85: 2773.9 | R85: 3958.6 | S85: 3958.6 | T85: 3958.6 | U85: 3958.6 | V85: 6954.1 | W85: 7841.0717 | X85: 7598.2
B86: Мясо (в живом весе) | C86: тыс. тонн | L86: 107 | M86: 111.7 | N86: 119 | O86: 129.8 | P86: 134.3 | Q86: 143.2 | R86: 150.7 | S86: 162 | T86: 173 | U86: 198.7 | V86: 217.7 | W86: 233.3 | X86: =W86*1.2 -> 279.96 | Y86: =X86*1.2 -> 335.952 | Z86: 272.521 | AA86: 300.182 | AB86: 327.72 | AC86: 349.15 | AD86: 398.028 | AE86: 416.034 | AF86: 403.5 | AG86: =AF86*1.2 -> 484.2 | AH86: =AG86*1.2 -> 581.04 | AI86: =AH86*1.2 -> 697.248 | AJ86: =AI86*1.2 -> 836.6976 | AK86: =AJ86*1.2 -> 1004.0371 | AL86: =AK86*1.2 -> 1204.8445 | AM86: =AL86*1.2 -> 1445.8135 | AN86: =AM86*1.2 -> 1734.9761 | ... AP86: =AO86*1.2 -> 2498.3656
C87: млн. сомони | L87: х | M87: х | N87: х | O87: х | P87: 1044.2 | Q87: 1289.4 | R87: 1906.6 | S87: 2197.1 | T87: 2457.1 | U87: 3457.6 | V87: 3819.6
C88: тыс. голов
B89: в том числе,
B90: крупный рогатый скот | C90: тыс. тонн
C91: млн. сомони
C92: тыс. голов | L92: 1371.9 | M92: 1422.6 | N92: 1702.5 | O92: 1799.5 | P92: 1830 | Q92: 1896.9 | R92: 2010.8 | S92: 2043.7 | T92: 2099.1 | U92: 2128.2
B93: в том числе,
B94: Яки | C94: тыс. тонн
C95: млн. сомони
C96: тыс.голов | L96: 14.5 | M96: 15.1 | N96: 15.2 | O96: 9.3 | P96: 19.8 | Q96: 21.5 | R96: 23.4 | S96: 23.1 | T96: 25.5 | U96: 26.1
B97: овцы и козы | C97: тыс. тонн
C98: млн. сомони
C99: тыс. поголовье | Q99: 4394.2 | R99: 4618.6 | S99: 4732.5 | T99: 4923.6 | U99: 5056.6
B100: птица всех видов | C100: тыс. тонн
C101: млн. сомони
...

Sheet Industry
B1: Var. Name | C1: Наименование индикатора | D1: 1997 | E1: 1998 | F1: 1999 | G1: 2000 | H1: 2001 | I1: 2002 | J1: 2003 | K1: 2004 | L1: 2005 | M1: 2006 | N1: 2007 | O1: 2008 | P1: 2009 | Q1: 2010 | R1: 2011 | S1: 2012 | T1: 2013 | U1: 2014 | V1: 2015 | W1: 2016 | X1: 2017 | Y1: 2018 | Z1: 2019 | AA1: 2020 | AB1: 2021 | AC1: 2022 | AD1: 2023 | AE1: 2024 | AF1: 2025 | AG1: 2026 | AH1: 2027 | AI1: 2028 | AJ1: 2029 | AK1: 2030 | AL1: 2031 | AM1: 2032 | AN1: 2033 | AO1: 2034 | AP1: 2035 | AU1: 2015 | AV1: 2016 | AW1: 2017 | AX1: 2018 | AY1: 2019 | AZ1: 2020 | BA1: 2021 | BB1: 2022 | BC1: 2023 | BD1: 2024 | BE1: 2025
C2: Промышленность | W2: =W4-V4 -> 2894 | X2: =X4-W4 -> 4938.512 | Y2: =Y4-X4 -> 3865.388 | Z2: =Z4-Y4 -> 3719.4 | AA2: =AA4-Z4 -> 3276.7 | AB2: =AB4-AA4 -> 7939 | AC2: =AC4-AB4 -> 3392.4 | AD2: =AD4-AC4 -> 4594.6 | ... AP2: =AP4-AO4 -> 24547.362 | AV2: =AV4-AU4 -> 2894 | AW2: =AW4-AV4 -> 4939 | AX2: =AX4-AW4 -> 3865 | AY2: =AY4-AX4 -> 3719 | AZ2: =AZ4-AY4 -> 3277 | BA2: =BA4-AZ4 -> 7939 | BB2: =BB4-BA4 -> 4196 | BC2: =BC4-BB4 -> 3832 | ... BE2: =BE4-BD4 -> 12853.1
C3: Номинальный, млн. сомони | AF3: 66726.1 | AG3: 83491.044 | AH3: 104885.56 | AI3: 131605.45 | AJ3: 164803.23 | AK3: 167867.77 | AL3: 171881.25 | AM3: 172762.85 | AN3: 227714.43 | AO3: 257348.47 | AP3: 287067.01
B4: INDCDE,t | C4: Промышленное производство | I4: 2418 | J4: 3205 | K4: 3952 | L4: 4278 | M4: 4663 | N4: 5571 | O4: 6106 | P4: 6501 | Q4: 6164.7 | R4: 7862 | S4: 9504 | T4: 9952 | U4: 10534.657 | V4: =V5+V8+V15 -> 12196 | W4: =W5+W8+W15 -> 15090 | X4: =X5+X8+X15 -> 20028.512 | Y4: =Y5+Y8+Y15 -> 23893.9 | Z4: =Z5+Z8+Z15 -> 27613.3 | AA4: =AA5+AA8+AA15 -> 30890 | AB4: =AB5+AB8+AB15 -> 38829 | AC4: =AC5+AC8+AC15 -> 42221.4 | AD4: =AD5+AD8+AD15 -> 46816 | AE4: =AE5+AE8+AE15+AE17 -> 53819 | AF4: =AF5+AF8+AF15+AF17 -> 66726.1 | AG4: =AG5+AG8+AG15+AG17 -> 83491.032 | AH4: =AH5+AH8+AH15+AH17 -> 104885.65 | AI4: =AI5+AI8+AI15+AI17 -> 131605.53 | AJ4: =AJ5+AJ8+AJ15+AJ17 -> 164803.16 | AK4: =AK5+AK8+AK15+AK17 -> 167867.77 | AL4: =AL5+AL8+AL15+AL17 -> 171881.25 | ... AP4: =AP5+AP8+AP15+AP17 -> 241220.44 | AU4: 12196 | AV4: 15090 | AW4: 20029 | AX4: 23894 | AY4: 27613 | AZ4: 30890 | BA4: 38829 | BB4: 43025 | BC4: 46857 | BD4: 53873 | BE4: 66726.1
B5: INDC,t | C5: Добыча полезных ископаемых | Q5: 755 | R5: 975 | S5: 1227 | T5: 1117 | U5: 1402 | V5: =V6+V7 -> 1641 | W5: =W6+W7 -> 3004 | X5: =X6+X7 -> 4523.512 | Y5: =Y6+Y7 -> 4685.9 | Z5: =Z6+Z7 -> 4853.3 | AA5: =AA6+AA7 -> 4309 | AB5: =AB6+AB7 -> 8409 | AC5: =AC6+AC7 -> 8890.9 | ... AF5: =AF6+AF7 -> 20000.2 | AG5: =AG6+AG7+3705.63312143906 -> 26754.532 | AH5: =AH6+AH7 -> 29788.981 | AI5: =AI6+AI7-8127.28715318557 -> 40744.262 | AJ5: =AJ6+AJ7-14222.7044732146 -> 48047.335 | AK5: =AK6+AK7 -> 51160.518 | AL5: =AL6+AL7 -> 37883.054 | AM5: =AM6+AM7 -> 26182.762 | AN5: =AN6+AN7 -> 30415.987 | AO5: =AO6+AO7 -> 36342.377 | AP5: =AP6+AP7 -> 43559.306 | AU5: 1641 | AV5: 3004 | AW5: 4524 | AX5: 4686 | AY5: 4853 | AZ5: 4309 | BA5: 8409 | BB5: 8906 | BC5: 9336 | BD5: 13369 | BE5: 20000.2
B6: INDC13,t | C6: Добыча неэнергетических материалов | Q6: 677 | R6: 900 | S6: 1115 | T6: 804 | U6: 1175 | V6: 1438 | W6: 2782 | X6: 4225.986 | Y6: 4355.2 | Z6: 4476.7 | AA6: 3880 | AB6: 7924 | AC6: 8309 | AD6: 8795 | AE6: 12653.6 | AF6: 19179.5 | AG6: =AF6*AG20*AG35/10000 -> 21505.162 | AH6: =AG6*AH20*AH35/10000-2951.9660326175 -> 24390.347 | AI6: =AH6*AI20*AI35/10000 -> 38306.463 | AJ6: =AI6*AJ20*AJ35/10000 -> 39278.858 | AK6: =AJ6*AK20*AK35/10000 -> 39801.671 | AL6: =AK6*AL20*AL35/10000 -> 35159.755 | AM6: =AL6*AM20*AM35/10000 -> 25500.452 | AN6: =AM6*AN20*AN35/10000 -> 30241.601 | AO6: =AN6*AO20*AO35/10000 -> 36289.922 | AP6: =AO6*AP20*AP35/10000 -> 43547.906 | AU6: 1438 | AV6: 2782 | AW6: 4226 | AX6: 4355 | AY6: 4476 | AZ6: 3880 | BA6: 7924 | BB6: 8324 | BC6: 8758 | BD6: 12659 | BE6: 19179.4
B7: INDCOther,t | C7: Добыча энергетических материалов | Q7: 78 | R7: 75 | S7: 112 | T7: 313 | U7: 227 | V7: 203 | W7: 222 | X7: 297.526 | Y7: 330.7 | Z7: 376.6 | AA7: 429 | AB7: 485 | AC7: 581.9 | AD7: 578 | AE7: 709.5 | AF7: 820.7 | AG7: =AF7*AG21*AG36/10000 -> 1543.7367 | AH7: =AG7*AH21*AH36/10000 -> 5398.634 | AI7: =AH7*AI21*AI36/10000 -> 10565.086 | AJ7: =AI7*AJ21*AJ36/10000 -> 22991.181 | AK7: =AJ7*AK21*AK36/10000 -> 11358.848 | AL7: =AK7*AL21*AL36/10000 -> 2723.299 | AM7: =AL7*AM21*AM36/10000 -> 682.31056 | AN7: =AM7*AN21*AN36/10000 -> 174.38567 | ... AP7: =AO7*AP21*AP36/10000 -> 11.39993 | AU7: 203 | AV7: 222 | AW7: 298 | AX7: 331 | AY7: 377 | AZ7: 429 | BA7: 485 | BB7: 582 | BC7: 578 | BD7: 710 | BE7: 820.7
B8: INDDJ, t | C8: Обрабатывающая промышленность | Q8: 3959.3 | R8: 5428 | S8: 6536 | T8: 6916 | U8: 6959 | V8: 8006 | W8: 9368 | X8: 11776 | Y8: 13520 | Z8: 15952 | AA8: 19054 | AB8: 22313 | AC8: 25708.7 | AD8: 28459.8 | AE8: 30275.6 | AF8: 34595.4 | AG8: =SUM(AG9:AG11,AG14)+3721.66316443206 -> 43621.32 | AH8: =SUM(AH9:AH11,AH14)+8970.87546314397 -> 60339.771 | AI8: =SUM(AI9:AI11,AI14)+6251.91015231384 -> 73035.004 | AJ8: =SUM(AJ9:AJ11,AJ14)+11878.4774273042 -> 95177.148 | AK8: =SUM(AK9:AK11,AK14) -> 93137.6 | AL8: =SUM(AL9:AL11,AL14) -> 108597.04 | AM8: =SUM(AM9:AM11,AM14) -> 119233.48 | AN8: =SUM(AN9:AN11,AN14) -> 136686.93 | AO8: =SUM(AO9:AO11,AO14) -> 148738.68 | AP8: =SUM(AP9:AP11,AP14) -> 163710.02 | AU8: 8006 | AV8: 9368 | AW8: 11776 | AX8: 13520 | AY8: 15952 | AZ8: 19054 | BA8: 22313 | BB8: 26497 | BC8: 28537 | BD8: 30283 | BE8: 34595.4
B9: INDDA, t | C9: пищевые продукты и табак | I9: 432.822 | J9: 493.57 | K9: 624.416 | L9: 834.21 | M9: 918.611 | N9: 1169.91 | O9: 1263.942 | P9: 1358.709 | Q9: 3048 | R9: 2442 | S9: 3318 | T9: 3588 | U9: 3266 | V9: 3482 | W9: 3690 | X9: 4304 | Y9: 4900 | Z9: 5399 | AA9: 7089 | AB9: 7608 | AC9: 10099 | AD9: 11610 | AE9: 11445.7 | AF9: 12431.3 | AG9: =AG65*Household!AF3 -> 18708.318 | AH9: =AH65*Household!AH3 -> 25527.301 | AI9: =AI65*Household!AI3 -> 33391.89 | AJ9: =AJ65*Household!AJ3 -> 43813.961 | AK9: =AK65*Household!AK3 -> 46796.742 | AL9: =AL65*Household!AL3 -> 52823.518 | AM9: =AM65*Household!AM3 -> 57360.637 | AN9: =AN65*Household!AN3 -> 64129.969 | AO9: =AO65*Household!AO3 -> 68450.877 | AP9: =AP65*Household!AP3 -> 74666.28 | AU9: 3482 | AV9: 3690 | AW9: 4304 | AX9: 4900 | AY9: 5399 | AZ9: 7089 | BA9: 7608 | BB9: 10383 | BC9: 11621 | BD9: 11492 | BE9: 12431
B10: INDDB, t | C10: текстильное производство | I10: 431.7 | J10: 696 | K10: 708.9 | L10: 751.1 | M10: 647.3 | N10: 813.2 | O10: 732 | P10: 705.3 | Q10: 534.3 | R10: 1414 | S10: 1533 | T10: 1361 | U10: 1315 | V10: 1292 | W10: 1520 | X10: 2354 | Y10: 2479 | Z10: 2636 | AA10: 2870 | AB10: 4096 | AC10: 4438 | AD10: 4632 | AE10: 4062.5 | AF10: 4253.7 | AG10: =(AG198*AG197+(AG187+AG186)*Assumptions!AG12) -> 3183.4964 | AH10: =(AH198*AH197+(AH187+AH186)*Assumptions!AH12) -> 3488.3109 | AI10: =(AI198*AI197+(AI187+AI186)*Assumptions!AI12) -> 4395.0263 | AJ10: =(AJ198*AJ197+(AJ187+AJ186)*Assumptions!AJ12) -> 4086.8335 | AK10: =(AK198*AK197+(AK187+AK186)*Assumptions!AK12) -> 4341.3372 | AL10: =(AL198*AL197+(AL187+AL186)*Assumptions!AL12) -> 4454.2592 | AM10: =(AM198*AM197+(AM187+AM186)*Assumptions!AM12) -> 4541.2325 | AN10: =(AN198*AN197+(AN187+AN186)*Assumptions!AN12) -> 4561.9669 | ... AP10: =(AP198*AP197+(AP187+AP186)*Assumptions!AP12) -> 4231.9817 | AU10: 1292 | AV10: 1520 | AW10: 2354 | AX10: 2479 | AY10: 2636 | AZ10: 2870 | BA10: 4096 | BB10: 4720 | BC10: 4500 | BD10: 3896 | BE10: 4253.7
B11: INDDJ, t | C11: металлургическое производство и готовые металлические изделия | I11: 1182 | J11: 1430 | K11: 1817 | L11: 1799 | M11: 2092 | N11: 2273 | O11: 2400 | P11: 2510 | Q11: 886.5 | R11: 786 | S11: 835 | T11: 1034 | U11: 915 | V11: 1450.2 | W11: 1850 | X11: 2187.3 | Y11: 2708.4 | Z11: 3873.5 | AA11: 4978 | AB11: 5967 | AC11: 6025 | AD11: 6442 | AE11: 8090.7 | AF11: 10612.9 | AG11: =AG12+AG13 -> 12316.42 | AH11: =AH12+AH13 -> 14744.856 | AI11: =AI12+AI13 -> 17724.661 | AJ11: =AJ12+AJ13 -> 21103.898 | AK11: =AK12+AK13 -> 24971.255 | AL11: =AL12+AL13 -> 29491.137 | AM11: =AM12+AM13 -> 34415.781 | AN11: =AN12+AN13 -> 39073.095 | ... AP11: =AP12+AP13 -> 51586.437 | AU11: 1450 | AV11: 1850 | AW11: 2187 | AX11: 2708 | AY11: 3874 | AZ11: 4978 | BA11: 5967 | BB11: 6093 | BC11: 6486 | BD11: 8092 | BE11: 10621.9
B12: INDD27, t | C12: металлургическое производство | Q12: 700 | R12: 727 | S12: 681.07801 | T12: 880.2 | U12: 724 | V12: =V11-V13 -> 1202.6249 | W12: =W11-W13 -> 1557.4819 | X12: =X11-X13 -> 1932.7978 | Y12: =Y11-Y13 -> 2455.2806 | Z12: =Z11-Z13 -> 3768.9349 | AA12: =AA11-AA13 -> 4883.6227 | AB12: =AB11-AB13 -> 5845.5362 | AC12: =AC11-AC13 -> 5903.6407 | ... AF12: =AF11-AF13 -> 10194.971 | AG12: =AF12*AG26*AG41/10000 -> 11898.068 | AH12: =AG12*AH26*AH41/10000 -> 14272.747 | AI12: =AH12*AI26*AI41/10000 -> 17187.775 | AJ12: =AI12*AJ26*AJ41/10000 -> 20496.843 | AK12: =AJ12*AK26*AK41/10000 -> 24286.657 | AL12: =AK12*AL26*AL41/10000 -> 28704.965 | AM12: =AL12*AM26*AM41/10000 -> 33521.055 | AN12: =AM12*AN26*AN41/10000 -> 38079.78 | ... AP12: =AO12*AP26*AP41/10000 -> 50323.41
B13: INDD28, t | C13: готовые металлические изделия | Q13: 100 | R13: 92.2 | S13: 73.318359 | T13: 148.6 | U13: 179.1 | V13: 247.57509 | W13: 292.51809 | X13: 254.50217 | Y13: 253.11944 | Z13: 104.56511 | AA13: 94.377342 | AB13: 121.46379 | AC13: 121.35925 | AD13: 122.87853 | AE13: 128.14095 | AF13: 417.92925 | AG13: =AF13*(AG153+AG154)/(AF153+AF154)*(Assumptions!AG12/Assumptions!AF12) -> 418.35228 | AH13: =AG13*(AH153+AH154)/(AG153+AG154)*(Assumptions!AH12/Assumptions!AG12) -> 472.10847 | AI13: =AH13*(AI153+AI154)/(AH153+AH154)*(Assumptions!AI12/Assumptions!AH12) -> 536.88598 | AJ13: =AI13*(AJ153+AJ154)/(AI153+AI154)*(Assumptions!AJ12/Assumptions!AI12) -> 607.05459 | AK13: =AJ13*(AK153+AK154)/(AJ153+AJ154)*(Assumptions!AK12/Assumptions!AJ12) -> 684.59798 | AL13: =AK13*(AL153+AL154)/(AK153+AK154)*(Assumptions!AL12/Assumptions!AK12) -> 786.17271 | AM13: =AL13*(AM153+AM154)/(AL153+AL154)*(Assumptions!AM12/Assumptions!AL12) -> 894.7252 | AN13: =AM13*(AN153+AN154)/(AM153+AM154)*(Assumptions!AN12/Assumptions!AM12) -> 993.31521 | ... AP13: =AO13*(AP153+AP154)/(AO153+AO154)*(Assumptions!AP12/Assumptions!AO12) -> 1263.028
B14: INDDOther, t | C14: переработка прочие (d) | I14: =I4-I15-I11-I10-I9 -> 231.234 | J14: 345.055 | K14: 568.516 | L14: 619.898 | M14: 715.983 | N14: 930.491 | O14: 1062.822 | P14: 1029.853 | Q14: -509.5 | R14: 786 | S14: 850 | T14: 933 | U14: 1463 | V14: 1781.8 | W14: 2308 | X14: 2930.7 | Y14: 3432.6 | Z14: 4043.5 | AA14: 4117 | AB14: 4642 | AC14: 5146.7 | AD14: 5775.8 | AE14: =AE8-AE9-AE10-AE11-AE13 -> 6548.559 | AF14: =AF8-AF9-AF10-AF11-AF13 -> 6879.5708 | AG14: =(AG9+AG10-(AG186+AG187+AG188)*Assumptions!AG11)*AG66/(1-AG66) -> 5691.4224 | AH14: =(AH9+AH10-(AH186+AH187+AH188)*Assumptions!AH11)*AH66/(1-AH66) -> 7608.4281 | AI14: =(AI9+AI10-(AI186+AI187+AI188)*Assumptions!AI11)*AI66/(1-AI66) -> 11271.517 | AJ14: =(AJ9+AJ10-(AJ186+AJ187+AJ188)*Assumptions!AJ11)*AJ66/(1-AJ66) -> 14293.978 | AK14: =(AK9+AK10-(AK186+AK187+AK188)*Assumptions!AK11)*AK66/(1-AK66) -> 17028.266 | AL14: =(AL9+AL10-(AL186+AL187+AL188)*Assumptions!AL11)*AL66/(1-AL66) -> 21828.124 | AM14: =(AM9+AM10-(AM186+AM187+AM188)*Assumptions!AM11)*AM66/(1-AM66) -> 22915.825 | AN14: =(AN9+AN10-(AN186+AN187+AN188)*Assumptions!AN11)*AN66/(1-AN66) -> 28921.895 | ... AP14: =(AP9+AP10-(AP186+AP187+AP188)*Assumptions!AP11)*AP66/(1-AP66) -> 33225.316
B15: INDE, t | C15: Производство и распределение электроэнергии, газа и воды | I15: 140.244 | J15: 240.375 | K15: 233.168 | L15: 273.792 | M15: 289.106 | N15: 384.399 | O15: 647.236 | P15: 897.138 | Q15: 1450.4 | R15: 1459 | S15: 1741 | T15: 1919 | U15: 2173.657 | V15: 2549 | W15: 2718 | X15: 3729 | Y15: 5688 | Z15: 6808 | AA15: 7527 | AB15: 8107 | AC15: 7621.8 | AD15: 8983.2 | AE15: 9872.2 | AF15: 11752.6 | AG15: =AF15*AG141/AF141-7427.30787098423 -> 12719.512 | AH15: =AG15*AH141/AG141-569.511772338643 -> 14343.703 | AI15: =AH15*AI141/AH141+1894.25074976773 -> 17398.437 | AJ15: =AI15*AJ141/AI141+2313.65697865672 -> 21086.544 | AK15: =AJ15*AK141/AJ141 -> 23032.114 | AL15: =AK15*AL141/AK141 -> 24821.85 | AM15: =AL15*AM141/AL141 -> 26722.932 | AN15: =AM15*AN141/AM141 -> 28717.979 | AO15: =AN15*AO141/AN141 -> 30871.512 | AP15: =AO15*AP141/AO141 -> 33176.809 | AU15: 2549 | AV15: 2718 | AW15: 3729 | AX15: 5688 | AY15: 6808 | AZ15: 7527 | BA15: 8107 | BB15: 7622 | BC15: 8984 | BD15: 10221 | BE15: 11752.6
AY16: 3719 | AZ16: 3277 | BA16: 7939 | BB16: 4196 | BC16: 3832 | BD16: 7016 | BE16: 3184
B17: Секция Е (36-39) | C17: Водоснабжение, очистка, обработка отходов и получение вторичного сырья | X17: 87.1 | Y17: 132.5 | Z17: 181.6 | AA17: 168.5 | AB17: 184.6 | AC17: 188.4 | AD17: 228.8 | AE17: 308.1 | AF17: 377.9 | AG17: =AF17*AG141/AF141-252.14445 -> 395.66823 | AH17: =AG17*AH141/AG141-50.7150544781293 -> 413.1931 | AI17: =AH17*AI141/AH141-18.7922305996491 -> 427.83041 | AJ17: =AI17*AJ141/AI141+30.5059264694922 -> 492.1343 | AK17: =AJ17*AK141/AJ141 -> 537.54154 | AL17: =AK17*AL141/AK141 -> 579.31179 | AM17: =AL17*AM141/AL141 -> 623.68073 | AN17: =AM17*AN141/AM141 -> 670.2427 | AO17: =AN17*AO141/AN141 -> 720.50355 | AP17: =AO17*AP141/AO141 -> 774.30638 | BE17: 377.9
A18: Реальные темпы роста, % | B18: gINDCDE,t | C18: Все промышленность | I18: 108.4 | J18: 109.9 | K18: 115.1 | L18: 110.4 | M18: 105.5 | N18: 109.9 | O18: 96.5 | P18: 93.5 | Q18: 109.2 | R18: 105.7 | S18: 110.8 | T18: 103.8 | U18: 105 | V18: 111.3 | W18: 116 | X18: 121.3 | Y18: 110.6 | Z18: 113.2 | AA18: 108.8 | AB18: 120.8 | AC18: 115.4 | AD18: 112 | AE18: 120 | AF18: 122.1 | AG18: =(AG19*AF5+AF8*AG22+AG29*AF15)/(AF5+AF8+AF15) -> 125.02097 | AH18: =(AH19*AG5+AG8*AH22+AH29*AG15)/(AG5+AG8+AG15) -> 125.0001 | AI18: =(AI19*AH5+AH8*AI22+AI29*AH15)/(AH5+AH8+AH15) -> 125.10772 | AJ18: =(AJ19*AI5+AI8*AJ22+AJ29*AI15)/(AI5+AI8+AI15) -> 125.0738 | AK18: =(AK19*AJ5+AJ8*AK22+AK29*AJ15)/(AJ5+AJ8+AJ15) -> 119.95581 | AL18: =(AL19*AK5+AK8*AL22+AL29*AK15)/(AK5+AK8+AK15) -> 119.92603 | AM18: =(AM19*AL5+AL8*AM22+AM29*AL15)/(AL5+AL8+AL15) -> 120.07027 | AN18: =(AN19*AM5+AM8*AN22+AN29*AM15)/(AM5+AM8+AM15) -> 111.30175 | ... AP18: =(AP19*AO5+AO8*AP22+AP29*AO15)/(AO5+AO8+AO15) -> 122.3396 | AU18: 111.3 | AV18: 116 | AW18: 121.3 | AX18: 110.6 | AY18: 113.2 | AZ18: 108.8 | BA18: 120.8 | BB18: 109.7 | BC18: 109 | BD18: 120 | BE18: 122.1
A19: Т/Р | B19: gINDC,t | C19: Добыча полезных ископаемых | R19: 134.3 | S19: 121.2 | T19: 143.1 | U19: 124.5 | V19: 117.9 | W19: 153.3 | X19: 121.7 | Y19: 112 | Z19: 112.6 | AA19: 97.4 | AB19: 155.2 | AC19: 97.7 | AD19: 111.7 | AE19: 143 | AF19: 136.2 | AG19: =SUMPRODUCT(AG20:AG21,AF6:AF7)/SUM(AF6:AF7) -> 121.23928 | AH19: =SUMPRODUCT(AH20:AH21,AG6:AG7)/SUM(AG6:AG7) -> 127.31865 | AI19: =SUMPRODUCT(AI20:AI21,AH6:AH7)/SUM(AH6:AH7) -> 157.14609 | AJ19: =SUMPRODUCT(AJ20:AJ21,AI6:AI7)/SUM(AI6:AI7) -> 118.05099 | AK19: =SUMPRODUCT(AK20:AK21,AJ6:AJ7)/SUM(AJ6:AJ7) -> 77.11757 | AL19: =SUMPRODUCT(AL20:AL21,AK6:AK7)/SUM(AK6:AK7) -> 72.072546 | AM19: =SUMPRODUCT(AM20:AM21,AL6:AL7)/SUM(AL6:AL7) -> 67.986265 | AN19: =SUMPRODUCT(AN20:AN21,AM6:AM7)/SUM(AM6:AM7) -> 117.51327 | ... AP19: =SUMPRODUCT(AP20:AP21,AO6:AO7)/SUM(AO6:AO7) -> 119.8637 | AU19: 117.9 | AV19: 153.3 | AW19: 121.7 | AX19: 112 | AY19: 112.6 | AZ19: 97.4 | BA19: 155.2 | BB19: 97.3 | BC19: 111 | BD19: 143.1 | BE19: 136.2
B20: gINDC13,t | C20: Добыча неэнергетических материалов | R20: 136.4 | S20: 120.6 | T20: 122.2 | U20: 145.7 | V20: 123 | W20: 156.7 | X20: 120.3 | Y20: 113 | Z20: 113.3 | AA20: 96.5 | AB20: 160.5 | AC20: 117.7 | AD20: 113.1 | AE20: 145.2 | AF20: 136.2 | AG20: 119.11 | AH20: 123.9375 | AI20: 152.5505 | AJ20: 100.5607 | AK20: 100 | AL20: 85.9 | AM20: 71.386 | AN20: 120 | AO20: 120 | AP20: 120 | BE20: 136.2
B21: gINDCOther,t | C21: Добыча энергетических материалов | R21: 113.5 | S21: 126.9 | T21: 255.1 | U21: 68.5 | V21: 90.9 | W21: 119 | X21: 137.1 | Y21: 108.2 | Z21: 103.1 | AA21: 103.6 | AB21: 106.8 | AC21: 100.1 | AD21: 99.2 | AE21: 116.5 | AF21: 114 | AG21: =+AF21*1.5 -> 171 | AH21: =+AG21*1.02 -> 174.42 | AI21: =+AH21*1.02 -> 177.9084 | AJ21: =+AI21*1.02 -> 181.46657 | AK21: =+AJ21*0.20954 -> 38.024505 | AL21: =+AK21*0.6212 -> 23.620822 | AM21: =+AL21*1.02 -> 24.093239 | AN21: =+AM21*1.02 -> 24.575104 | AO21: =+AN21*1.02 -> 25.066606 | AP21: =+AO21*1.02 -> 25.567938 | BE21: 114
B22: gINDD, t | C22: Обрабатывающая промышленность | R22: 103.3 | S22: 110.2 | T22: 99 | U22: 100.9 | V22: 110.1 | W22: 112.5 | X22: 122.9 | Y22: 112.1 | Z22: 115.3 | AA22: 114.1 | AB22: 115.3 | AC22: 116.4 | AD22: 112.4 | AE22: 107.6 | AF22: 110.5 | AG22: =(AG23*AF9+AF10*AG24+AG25*AF11+AF14*AG28)/(AF8) -> 132.91232 | AH22: =(AH23*AG9+AG10*AH24+AH25*AG11+AG14*AH28)/(AG8) -> 127.14443 | AI22: =(AI23*AH9+AH10*AI24+AI25*AH11+AH14*AI28)/(AH8) -> 110.19673 | AJ22: =(AJ23*AI9+AI10*AJ24+AJ25*AI11+AI14*AJ28)/(AI8) -> 129.91494 | AK22: =(AK23*AJ9+AJ10*AK24+AK25*AJ11+AJ14*AK28)/(AJ8) -> 143.95848 | AL22: =(AL23*AK9+AK10*AL24+AL25*AK11+AK14*AL28)/(AK8) -> 149.21789 | AM22: =(AM23*AL9+AL10*AM24+AM25*AL11+AL14*AM28)/(AL8) -> 141.07614 | AN22: =(AN23*AM9+AM10*AN24+AN25*AM11+AM14*AN28)/(AM8) -> 110.7975 | ... AP22: =(AP23*AO9+AO10*AP24+AP25*AO11+AO14*AP28)/(AO8) -> 126.03137 | BE22: 110.5
B23: gINDDA, t | C23: пищевые продукты и табак | I23: 102.7 | J23: 102.9 | K23: 117.3 | L23: 129.1 | M23: 107.1 | N23: 121.6 | O23: 102.4 | P23: 94.4 | Q23: 116.1 | R23: 102.1 | S23: 106.6 | T23: 100.8 | U23: 92.9 | V23: 103.5 | W23: 105.4 | X23: 115.6 | Y23: 117.6 | Z23: 107.7 | AA23: 125.9 | AB23: 103.3 | AC23: 132 | AD23: 127 | AE23: 110 | AF23: 116.1 | AG23: 224.5 | AH23: 179 | AI23: 140.9 | AJ23: 176.7 | AK23: 215 | AL23: 180.5 | AM23: 150.5 | AN23: 110 | AO23: 110 | AP23: =AP9/AO9/AP38*10000 -> 104.49789 | BE23: 116.1
B24: gINDDB, t | C24: текстильное производство | I24: 124.9 | J24: 117.8 | K24: 113.2 | L24: 111.9 | M24: 91.7 | N24: 115.3 | O24: 86 | P24: 91.1 | Q24: 113 | R24: 116.3 | S24: 128.2 | T24: 90.1 | U24: 92.9 | V24: 94.4 | W24: 103.8 | X24: 130.9 | Y24: 92.1 | Z24: 118.8 | AA24: 113.5 | AB24: 109.5 | AC24: 107.3 | AD24: 110.4 | AE24: 93 | AF24: 114.4 | AG24: =(AG197/AF197*(AF198*AF197)+(AG182/AF182*AF186+AG184/AF184*AF188)*Assumptions!AG12)/Industry!AF10*100 -> 70.29376 | AH24: =(AH197/AG197*(AG198*AG197)+(AH182/AG182*AG186+AH184/AG184*AG188)*Assumptions!AH12)/Industry!AG10*100 -> 99.134406 | AI24: =(AI197/AH197*(AH198*AH197)+(AI182/AH182*AH186+AI184/AH184*AH188)*Assumptions!AI12)/Industry!AH10*100 -> 121.18995 | AJ24: =(AJ197/AI197*(AI198*AI197)+(AJ182/AI182*AI186+AJ184/AI184*AI188)*Assumptions!AJ12)/Industry!AI10*100 -> 82.801573 | AK24: =(AK197/AJ197*(AJ198*AJ197)+(AK182/AJ182*AJ186+AK184/AJ184*AJ188)*Assumptions!AK12)/Industry!AJ10*100 -> 107.93885 | AL24: =(AL197/AK197*(AK198*AK197)+(AL182/AK182*AK186+AL184/AK184*AK188)*Assumptions!AL12)/Industry!AK10*100 -> 97.598764 | AM24: =(AM197/AL197*(AL198*AL197)+(AM182/AL182*AL186+AM184/AL184*AL188)*Assumptions!AM12)/Industry!AL10*100 -> 96.999128 | AN24: =(AN197/AM197*(AM198*AM197)+(AN182/AM182*AM186+AN184/AM184*AM188)*Assumptions!AN12)/Industry!AM10*100 -> 95.654977 | ... AP24: =(AP197/AO197*(AO198*AO197)+(AP182/AO182*AO186+AP184/AO184*AO188)*Assumptions!AP12)/Industry!AO10*100 -> 85.696019 | BE24: 114.4
B25: gINDDJ, t | C25: металлургическое производство и готовые металлические изделия | I25: 105.3 | J25: 104.1 | K25: 114.8 | L25: 105.1 | M25: 108.6 | N25: 101.3 | O25: 96.3 | P25: 92.4 | Q25: 103 | R25: 83.6 | S25: 102.7 | T25: 96 | U25: 86.8 | V25: 130.3 | W25: 104.7 | X25: 109.4 | Y25: 110.7 | Z25: 142.2 | AA25: 109.4 | AB25: 109.4 | AC25: 103.4 | AD25: 102.7 | AE25: 113.5 | AF25: 106.5 | AG25: =(AG26*AF12+AF13*AG27)/(AF12+AF13) -> 120.67037 | AH25: =(AH26*AG12+AG13*AH27)/(AG12+AG13) -> 114.53937 | AI25: =(AI26*AH12+AH13*AI27)/(AH12+AH13) -> 114.64386 | AJ25: =(AJ26*AI12+AI13*AJ27)/(AI12+AI13) -> 114.69396 | AK25: =(AK26*AJ12+AJ13*AK27)/(AJ12+AJ13) -> 114.73737 | AL25: =(AL26*AK12+AK13*AL27)/(AK12+AK13) -> 114.77494 | AM25: =(AM26*AL12+AL13*AM27)/(AL12+AL13) -> 114.80096 | AN25: =(AN26*AM12+AM13*AN27)/(AM12+AM13) -> 114.82415 | ... AP25: =(AP26*AO12+AO13*AP27)/(AO12+AO13) -> 114.86317 | BE25: 106.5
B26: gINDD27J, t | C26: металлургическое производство | R26: 80.7 | S26: 158321.32 | T26: 70.080396 | U26: 80.6 | V26: 139.49313 | W26: 81.716387 | X26: 81.734833 | Y26: 93.476349 | Z26: 102.18957 | AA26: 89.702999 | AB26: 64.107442 | AC26: 101.64246 | AD26: =(AC156*AD152/AC152+AD159*AD154/AC154)/(AC156+AC159)*100 -> 104.39341 | AE26: =(AD156*AE152/AD152+AE159*AE154/AD154)/(AD156+AD159)*100 -> 129.33687 | AF26: =(AE156*AF152/AE152+AF159*AF154/AE154)/(AE156+AE159)*100 -> 105.64558 | AG26: =(AF156*AG152/AF152+AG159*AG154/AF154)/(AF156+AF159)*100 -> 121.26399 | AH26: =(AG156*AH152/AG152+AH159*AH154/AG154)/(AG156+AG159)*100 -> 114.80807 | AI26: =(AH156*AI152/AH152+AI159*AI154/AH154)/(AH156+AH159)*100 -> 114.8805 | AJ26: =(AI156*AJ152/AI152+AJ159*AJ154/AI154)/(AI156+AI159)*100 -> 114.90052 | AK26: =(AJ156*AK152/AJ152+AK159*AK154/AJ154)/(AJ156+AJ159)*100 -> 114.91724 | ... AP26: =(AO156*AP152/AO152+AP159*AP154/AO154)/(AO156+AO159)*100 -> 114.96058
B27: gINDD28, t | C27: готовые металлические изделия | R27: 127.9 | S27: 72.673905 | T27: 79.412844 | U27: 115.9 | V27: 110.6603 | W27: 92.954709 | X27: 79.737046 | Y27: 92.919496 | Z27: 105.15921 | AA27: 83.333333 | AB27: 72.039498 | AC27: 102.47934 | AD27: =(AC158*AD153/AC153+AC159*AD154/AC154)/(AC158+AC159)*100 -> 107.41935 | AE27: =(AD158*AE153/AD153+AD159*AE154/AD154)/(AD158+AD159)*100 -> 123.42342 | AF27: =(AE158*AF153/AE153+AE159*AF154/AE154)/(AE158+AE159)*100 -> 107.42092 | AG27: =(AF158*AG153/AF153+AF159*AG154/AF154)/(AF158+AF159)*100 -> 106.18966 | AH27: =(AG158*AH153/AG153+AG159*AH154/AG154)/(AG158+AG159)*100 -> 106.89746 | AI27: =(AH158*AI153/AH153+AH159*AI154/AH154)/(AH158+AH159)*100 -> 107.48987 | AJ27: =(AI158*AJ153/AI153+AI159*AJ154/AI154)/(AI158+AI159)*100 -> 108.08118 | AK27: =(AJ158*AK153/AJ153+AJ159*AK154/AJ154)/(AJ158+AJ159)*100 -> 108.66414 | ... AP27: =(AO158*AP153/AO153+AO159*AP154/AO154)/(AO158+AO159)*100 -> 111.05194
B28: gINDDther, t | C28: переработка прочие (d) | R28: 75.477134 | S28: 96.503053 | T28: 110.97212 | U28: 158.96152 | V28: 126.31196 | W28: 139.03169 | X28: 140.12357 | Y28: 121.13205 | Z28: 102.39653 | AA28: 103.23784 | AB28: 147.13974 | AC28: =(AC22*AB8-SUMPRODUCT(AB9:AB11,AC23:AC25))/AB14 -> 115.57273 | AD28: =(AD22*AC8-SUMPRODUCT(AC9:AC11,AD23:AD25))/AC14 -> 96.831403 | AE28: =(AE22*AD8-SUMPRODUCT(AD9:AD11,AE23:AE25))/AD14 -> 107.90392 | AF28: =(AF22*AE8-SUMPRODUCT(AE9:AE11,AF23:AF25))/AE14 -> 105.397 | AG28: =AG14/AF14/AG43*10000 -> 33.09173 | AH28: =AH14/AG14/AH43*10000 -> 82.775458 | AI28: =AI14/AH14/AI43*10000 -> 123.45429 | AJ28: =AJ14/AI14/AJ43*10000 -> 105.6792 | AK28: =AK14/AJ14/AK43*10000 -> 99.274126 | AL28: =AL14/AK14/AL43*10000 -> 126.91841 | AM28: =AM14/AL14/AM43*10000 -> 162.76438 | AN28: =AN14/AM14/AN43*10000 -> 109.74719 | ... AP28: =AP14/AO14/AP43*10000 -> 196.24564
B29: gINDE, t | C29: Производство и распределение электроэнергии, газа и воды | I29: 107.6 | J29: 106.6 | K29: 98.1 | L29: 104.4 | M29: 105.5 | N29: 105.6 | O29: 93.4 | P29: 97.7 | Q29: 104.4 | R29: 100.5 | S29: 106.4 | T29: 105.6 | U29: 106.8 | V29: 111.5 | W29: 103.7 | X29: 116.5 | Y29: 107.5 | Z29: 105.6 | AA29: 100.1 | AB29: 112.7 | AC29: 117.5 | AD29: 107.1 | AE29: 105.7 | AF29: 113 | AG29: =AG15/AF15*100 -> 108.22722 | AH29: =AH15/AG15*100 -> 112.76929 | AI29: =AI15/AH15*100 -> 121.29669 | AJ29: =AJ15/AI15*100 -> 121.19792 | AK29: =AK15/AJ15*100 -> 109.2266 | AL29: =AL15/AK15*100 -> 107.77061 | AM29: =AM15/AL15*100 -> 107.6589 | AN29: =AN15/AM15*100 -> 107.46567 | ... AP29: =AP15/AO15*100 -> 107.46739 | BE29: 112.9
AE30: 134.9 | AF30: 122.8 | AG30: =AG17/AF17*100 -> 104.70183 | AH30: =AH17/AG17*100 -> 104.42918 | AI30: =AI17/AH17*100 -> 103.54249 | AJ30: =AJ17/AI17*100 -> 115.03023 | AK30: =AK17/AJ17*100 -> 109.2266 | AL30: =AL17/AK17*100 -> 107.77061 | AM30: =AM17/AL17*100 -> 107.6589 | AN30: =AN17/AM17*100 -> 107.46567 | ... AP30: =AP17/AO17*100 -> 107.46739
B31: gINDD27J, t | C31: металлургическое производство | V31: 139.49313 | W31: 81.716387 | X31: 81.734833 | Y31: 93.476349 | Z31: 102.18957 | AA31: 89.702999 | AB31: 64.107442 | AC31: 101.64246 | AD31: 104.4737 | AE31: 129.06373 | AF31: 119.18394 | AG31: 121.26399 | AH31: 114.85655 | AI31: 114.8805 | AJ31: 114.90052 | AK31: 114.91724 | AL31: 114.93119 | AM31: 114.94013 | AN31: 114.94791 | AO31: 114.95469 | AP31: 114.96058
C32: Дефлятор, %
B33: defINDCDE,t | C33: Все промышленность | J33: 120.60742 | K33: 107.13061 | L33: 98.051619 | M33: 103.31709 | N33: 108.71014 | O33: 113.57855 | P33: 113.87064 | Q33: 86.837866 | R33: 120.65522 | S33: 109.10223 | T33: 100.88035 | U33: 100.81397 | V33: 114.7 | W33: 101.7 | X33: 101.8 | Y33: 101.1 | Z33: 105.4 | AA33: 105.9 | AB33: =AB4/AA4/AB18*10000 -> 104.05701 | AC33: =AC4/AB4/AC18*10000 -> 94.22597 | AD33: =AD4/AC4/AD18*10000 -> 99.001928 | AE33: =AE4/AD4/AE18*10000 -> 95.798801 | AF33: =AF4/AE4/AF18*10000 -> 101.54171 | AG33: =AG4/AF4/AG18*10000 -> 100.08321 | AH33: =AH4/AG4/AH18*10000 -> 100.49996 | AI33: =AI4/AH4/AI18*10000 -> 100.29377 | ... AP33: =AP4/AO4/AP18*10000 -> 91.000144 | BE33: 104.5
B34: defINDC,t | C34: Добыча полезных ископаемых | R34: 96.157165 | S34: 103.83346 | T34: 63.616384 | U34: 100.81508 | V34: 163.9 | W34: 84.9 | X34: 90.1 | Y34: 100.3 | Z34: 107.7 | AA34: 116.7 | AB34: =AB5/AA5/AB19*10000 -> 125.74078 | AC34: =AC5/AB5/AC19*10000 -> 108.21982 | AD34: =AD5/AC5/AD19*10000 -> 94.379945 | AE34: =AE5/AD5/AE19*10000 -> 99.699404 | AF34: =AF5/AE5/AF19*10000 -> 109.88794 | AG34: =AG5/AF5/AG19*10000 -> 110.33661 | AH34: =AH5/AG5/AH19*10000 -> 87.451304 | AI34: =AI5/AH5/AI19*10000 -> 87.037661 | ... AP34: =AP5/AO5/AP19*10000 -> 99.995382 | BE34: 109.9
B35: defINDC13,t | C35: Добыча неэнергетических материалов | R35: 97.462932 | S35: 102.72711 | T35: 59.007875 | U35: 100.30493 | V35: 96.8 | W35: 96.6 | X35: 103.7 | Y35: 116 | Z35: 106.4 | AA35: 112.3 | AB35: =AB6/AA6/AB20*10000 -> 127.24411 | AC35: =AC6/AB6/AC20*10000 -> 89.089768 | AD35: =AD6/AC6/AD20*10000 -> 93.58893 | AE35: =AE6/AD6/AE20*10000 -> 99.08585 | AF35: =AF6/AE6/AF20*10000 -> 111.28742 | AG35: =(Assumptions!AG21/Assumptions!AF21)*(Assumptions!AG12/Assumptions!AF12)*100 -> 94.136319 | AH35: =(Assumptions!AH21/Assumptions!AG21)*(Assumptions!AH12/Assumptions!AG12)*100 -> 102.5864 | AI35: =(Assumptions!AI21/Assumptions!AH21)*(Assumptions!AI12/Assumptions!AH12)*100 -> 102.95334 | AJ35: =(Assumptions!AJ21/Assumptions!AI21)*(Assumptions!AJ12/Assumptions!AI12)*100 -> 101.96674 | AK35: =(Assumptions!AK21/Assumptions!AJ21)*(Assumptions!AK12/Assumptions!AJ12)*100 -> 101.33103 | AL35: =(Assumptions!AL21/Assumptions!AK21)*(Assumptions!AL12/Assumptions!AK12)*100 -> 102.83747 | AM35: =(Assumptions!AM21/Assumptions!AL21)*(Assumptions!AM12/Assumptions!AL12)*100 -> 101.5989 | AN35: =(Assumptions!AN21/Assumptions!AM21)*(Assumptions!AN12/Assumptions!AM12)*100 -> 98.827012 | ... AP35: =(Assumptions!AP21/Assumptions!AO21)*(Assumptions!AP12/Assumptions!AO12)*100 -> 100 | BE35: 111.3
B36: defINDCOther,t | C36: Добыча энергетических материалов | R36: 84.717045 | S36: 117.67796 | T36: 109.55088 | U36: 105.8744 | V36: 173.6 | W36: 83.4 | X36: 89.2 | Y36: 99.2 | Z36: 108.3 | AA36: 117.5 | AB36: =AB7/AA7/AB21*10000 -> 105.85544 | AC36: =AC7/AB7/AC21*10000 -> 119.85952 | AD36: 115 | AE36: =AE7/AD7/AE21*10000 -> 105.36555 | AF36: =AF7/AE7/AF21*10000 -> 101.46755 | AG36: 110 | AH36: 200.5 | AI36: 110 | AJ36: 119.92 | AK36: 129.93 | AL36: 101.5 | AM36: 103.99 | AN36: 104 | AO36: 120 | AP36: 85 | BE36: 101.5
B37: defINDD,t | C37: Обрабатывающая промышленность | R37: 132.71533 | S37: 109.2674 | T37: 106.88278 | U37: 99.724229 | V37: 102.7 | W37: 102 | X37: 102.8 | Y37: 101.5 | Z37: 104.5 | AA37: 104.8 | AB37: =AB8/AA8/AB22*10000 -> 101.56463 | AC37: =AC8/AB8/AC22*10000 -> 98.984951 | AD37: =AD8/AC8/AD22*10000 -> 98.488476 | AE37: =AE8/AD8/AE22*10000 -> 98.866382 | AF37: =AF8/AE8/AF22*10000 -> 103.41019 | AG37: =AG8/AF8/AG22*10000 -> 94.867009 | AH37: =AH8/AG8/AH22*10000 -> 108.79464 | AI37: =AI8/AH8/AI22*10000 -> 109.83954 | ... AP37: =AP8/AO8/AP22*10000 -> 87.331853 | BE37: 104.1
B38: defINDDA, t | C38: пищевые продукты и табак | J38: 136.86169 | K38: 89.976544 | L38: 94.68533 | M38: 93.980664 | N38: 108.95884 | O38: 104.66832 | P38: 105.7656 | Q38: 67.039821 | R38: 78.470235 | S38: 127.45988 | T38: 107.2792 | U38: 97.982391 | V38: 101.1 | W38: 100.5 | X38: 101.7 | Y38: 102.6 | Z38: 104.1 | AA38: 108.4 | AB38: 103.89274 | AC38: 100.56201 | AD38: =Monetary!AD5 -> 103.6 | AE38: =Monetary!AE5 -> 102.2 | AF38: =Monetary!AF5 -> 103.9 | AG38: =Monetary!AG5 -> 111.69701 | AH38: =Monetary!AH5 -> 105.31013 | AI38: =Monetary!AI5 -> 105.1995 | AJ38: =Monetary!AJ5 -> 105.54148 | AK38: =Monetary!AK5 -> 106.04923 | ... AP38: =Monetary!AP5 -> 104.38497 | BE38: 99.6
B39: defINDDB, t | C39: текстильное производство | J39: 110.82151 | K39: 107.85176 | L39: 103.48446 | M39: 102.81744 | N39: 104.73389 | O39: 105.50541 | P39: 113.87472 | Q39: 193.22187 | R39: 227.55402 | S39: 84.567739 | T39: 98.535149 | U39: 104.00445 | V39: 120.7 | W39: 111.6 | X39: 106.3 | Y39: 94.2 | Z39: 99.5 | AA39: 113.4 | AB39: =AB10/AA10/AB24*10000 -> 130.33586 | AC39: =AC10/AB10/AC24*10000 -> 100.9782 | AD39: =AD10/AC10/AD24*10000 -> 94.539256 | AE39: =AE10/AD10/AE24*10000 -> 94.306554 | AF39: =AF10/AE10/AF24*10000 -> 91.526627 | AG39: =AG10/AF10/AG24*10000 -> 106.4684 | AH39: =AH10/AG10/AH24*10000 -> 110.53159 | AI39: =AI10/AH10/AI24*10000 -> 103.96321 | ... AP39: =AP10/AO10/AP24*10000 -> 107.07941 | BE39: 91.7
B40: defINDDJ, t | C40: металлургическое производство и готовые металлические изделия | J40: 116.21651 | K40: 110.682 | L40: 94.204906 | M40: 107.07811 | N40: 107.25766 | O40: 109.64416 | P40: 113.18543 | Q40: 34.290024 | R40: 106.05656 | S40: 103.44118 | T40: 128.99202 | U40: 101.9485 | V40: 111.4 | W40: 110.7 | X40: 105.9 | Y40: 100.4 | Z40: 131.3 | AA40: 99 | AB40: =AB11/AA11/AB25*10000 -> 109.56802 | AC40: =AC11/AB11/AC25*10000 -> 97.65185 | AD40: =AD11/AC11/AD25*10000 -> 104.11019 | AE40: =AE11/AD11/AE25*10000 -> 110.65461 | AF40: =AF11/AE11/AF25*10000 -> 123.16814 | AG40: =AG11/AF11/AG25*10000 -> 96.172247 | AH40: =AH11/AG11/AH25*10000 -> 104.52045 | AI40: =AI11/AH11/AI25*10000 -> 104.85439 | ... AP40: =AP11/AO11/AP25*10000 -> 100.03999 | BE40: 123.2
B41: defINDD27, t | C41: металлургическое производство | R41: 128.69534 | S41: 0.059172927 | T41: 184.41148 | U41: 102.05215 | V41: 119.07999 | W41: =W12/V12/W31*10000 -> 158.48336 | X41: =X12/W12/X31*10000 -> 151.82953 | Y41: =Y12/X12/Y31*10000 -> 135.89797 | Z41: =Z12/Y12/Z31*10000 -> 150.21418 | AA41: =AA12/Z12/AA31*10000 -> 144.44965 | AB41: =AB12/AA12/AB31*10000 -> 186.71268 | AC41: =AC12/AB12/AC31*10000 -> 99.362016 | AD41: =AD12/AC12/AD31*10000 -> 102.45421 | ... AF41: =AF12/AE12/AF31*10000 -> 107.42753 | AG41: =(Assumptions!AG7/Assumptions!AF7)*(Assumptions!AG12/Assumptions!AF12)*100 -> 96.24066 | AH41: =(Assumptions!AH7/Assumptions!AG7)*(Assumptions!AH12/Assumptions!AG12)*100 -> 104.48615 | AI41: =(Assumptions!AI7/Assumptions!AH7)*(Assumptions!AI12/Assumptions!AH12)*100 -> 104.82522 | AJ41: =(Assumptions!AJ7/Assumptions!AI7)*(Assumptions!AJ12/Assumptions!AI12)*100 -> 103.78757 | AK41: =(Assumptions!AK7/Assumptions!AJ7)*(Assumptions!AK12/Assumptions!AJ12)*100 -> 103.10876 | AL41: =(Assumptions!AL7/Assumptions!AK7)*(Assumptions!AL12/Assumptions!AK12)*100 -> 102.83747 | AM41: =(Assumptions!AM7/Assumptions!AL7)*(Assumptions!AM12/Assumptions!AL12)*100 -> 101.5989 | AN41: =(Assumptions!AN7/Assumptions!AM7)*(Assumptions!AN12/Assumptions!AM12)*100 -> 98.827012 | ... AP41: =(Assumptions!AP7/Assumptions!AO7)*(Assumptions!AP12/Assumptions!AO12)*100 -> 100
B42: defINDD28, t | C42: готовые металлические изделия | R42: 72.087568 | S42: 109.42167 | T42: 255.22036 | U42: 103.99042 | V42: 124.91641 | W42: =(Assumptions!W7/Assumptions!V7)*(Assumptions!W12/Assumptions!V12)*100 -> 122.48758 | X42: =(Assumptions!X7/Assumptions!W7)*(Assumptions!X12/Assumptions!W12)*100 -> 133.83937 | Y42: =(Assumptions!Y7/Assumptions!X7)*(Assumptions!Y12/Assumptions!X12)*100 -> 114.69431 | Z42: =(Assumptions!Z7/Assumptions!Y7)*(Assumptions!Z12/Assumptions!Y12)*100 -> 89.004639 | AA42: =(Assumptions!AA7/Assumptions!Z7)*(Assumptions!AA12/Assumptions!Z12)*100 -> 109.65171 | AB42: =(Assumptions!AB7/Assumptions!AA7)*(Assumptions!AB12/Assumptions!AA12)*100 -> 150.43482 | AC42: =(Assumptions!AC7/Assumptions!AB7)*(Assumptions!AC12/Assumptions!AB12)*100 -> 97.068533 | AD42: =(Assumptions!AD7/Assumptions!AC7)*(Assumptions!AD12/Assumptions!AC12)*100 -> 88.973632 | ... AP42: =(Assumptions!AP7/Assumptions!AO7)*(Assumptions!AP12/Assumptions!AO12)*100 -> 100
B43: defINDDther, t | C43: переработка прочие (d) | Q43: 100.91109 | R43: -204.39156 | S43: 112.06121 | T43: 98.911968 | U43: 98.643999 | V43: 96.420671 | W43: =W14/V14/W28*10000 -> 93.167203 | X43: =X14/W14/X28*10000 -> 90.620064 | Y43: =Y14/X14/Y28*10000 -> 96.692497 | Z43: =Z14/Y14/Z28*10000 -> 115.04004 | AA43: =AA14/Z14/AA28*10000 -> 98.624432 | AB43: =AB14/AA14/AB28*10000 -> 76.6292 | AC43: =AC14/AB14/AC28*10000 -> 95.933073 | AD43: =AD14/AC14/AD28*10000 -> 115.89563 | ... AF43: =AF14/AE14/AF28*10000 -> 99.675252 | AG43: 250 | AH43: 161.5 | AI43: 120 | AJ43: 120 | AK43: 120 | AL43: 101 | AM43: 64.5 | AN43: 115 | AO43: 115 | AP43: 55
B44: defINDE, t | C44: производство и распределение электроэнергии, газа и воды | J44: 160.78584 | K44: 98.880498 | L44: 112.47378 | M44: 100.08843 | N44: 125.91029 | O44: 180.27418 | P44: 141.87374 | Q44: 154.856 | R44: 100.09248 | S44: 112.15066 | T44: 104.3788 | U44: 106.05833 | V44: 116.5 | W44: 115 | X44: 115 | Y44: 102.5 | Z44: 105.7 | AA44: 100.2 | AB44: =AB15/AA15/AB29*10000 -> 95.568406 | AC44: =AC15/AB15/AC29*10000 -> 80.012807 | AD44: =AD15/AC15/AD29*10000 -> 110.04848 | AE44: =AE15/AD15/AE29*10000 -> 103.96996 | AF44: =AF15/AE15/AF29*10000 -> 105.3517 | AG44: =AG15/AF15/AG29*10000 -> 100 | AH44: =AH15/AG15/AH29*10000 -> 100 | AI44: =AI15/AH15/AI29*10000 -> 100 | ... AP44: =AP15/AO15/AP29*10000 -> 100 | BE44: 109.8
AE45: 100 | AF45: 100 | AG45: 100 | AH45: 100 | AI45: 100 | AJ45: 100 | AK45: 100 | AL45: 100 | AM45: 100 | AN45: 100 | AO45: 100 | AP45: 100
C48: Индекс 2003 = 100 | J48: 100 | K48: 115.1 | L48: 127.0704 | M48: 134.05927 | N48: 147.33114 | O48: 142.17455 | P48: 132.9332 | Q48: 145.16306 | R48: 153.43735 | S48: 170.00859 | T48: 176.46891 | U48: 185.29236
B49: idxIND2003t | C49: Все промышленность | J49: 100 | K49: 98.1 | L49: 102.4164 | M49: 108.0493 | N49: 114.10006 | O49: 106.56946 | P49: 104.11836 | Q49: 108.69957 | R49: 107.39663 | S49: 112.26447 | T49: 113.19703 | U49: 108.94428 | V49: 206.2304 | W49: =V49*W18/100 -> 239.22726 | X49: =W49*X18/100 -> 290.18267 | Y49: =X49*Y18/100 -> 320.94203 | Z49: =Y49*Z18/100 -> 363.30638 | AA49: =Z49*AA18/100 -> 395.27734 | AB49: =AA49*AB18/100 -> 477.49502 | AC49: =AB49*AC18/100 -> 551.02926 | AD49: =AC49*AD18/100 -> 617.15277 | ... AP49: =AO49*AP18/100 -> 5677.8839
B50: idxIND2003E,,t | C50: Электроэнергетика | J50: 100 | K50: 114.8 | L50: 120.6548 | M50: 131.03111 | N50: 132.73452 | O50: 127.82334 | P50: 118.10877 | Q50: 121.65203 | R50: 101.7011 | S50: 104.44703 | T50: 100.26915 | U50: 87.033618 | V50: 113.50788 | W50: =V50*W70/V70 -> 113.97085 | X50: =W50*X70/W70 -> 120.00274 | Y50: =X50*Y70/X70 -> 130.57176 | Z50: =Y50*Z70/Y70 -> 136.75576 | AA50: =Z50*AA70/Z70 -> 130.76356 | AB50: =AA50*AB70/AA70 -> 136.4039 | AC50: =AB50*AC70/AB70 -> 141.53431 | AD50: =AC50*AD70/AC70 -> 144.58332 | ... AP50: =AO50*AP70/AO70 -> 312.12196
B51: idxIND2003DJ,,t | C51: Цветная металлургия | J51: 100 | K51: 113.2 | L51: 126.6708 | M51: 116.15712 | N51: 133.92916 | O51: 115.17908 | P51: 104.92814 | Q51: 118.5688 | R51: 137.89552 | S51: 176.78205 | T51: 159.28063 | U51: 147.9717 | V51: 113.4048 | W51: =V51*W25/100 -> 118.73483 | X51: =W51*X25/100 -> 129.8959 | Y51: =X51*Y25/100 -> 143.79477 | Z51: =Y51*Z25/100 -> 204.47616 | AA51: =Z51*AA25/100 -> 223.69692 | AB51: =AA51*AB25/100 -> 244.72443 | AC51: =AB51*AC25/100 -> 253.04506 | AD51: =AC51*AD25/100 -> 259.87727 | ... AP51: =AO51*AP25/100 -> 1307.3244
B52: idxIND2003DBC,,t | C52: Легкая промышленность | J52: 100 | K52: 117.3 | L52: 151.4343 | M52: 162.18614 | N52: 197.21834 | O52: 201.95158 | P52: 190.64229 | Q52: 221.3357 | R52: 225.98375 | S52: 240.89868 | T52: 242.82587 | U52: 225.58523 | V52: 139.68529 | W52: =V52*W24/100 -> 144.99333 | X52: =W52*X24/100 -> 189.79627 | Y52: =X52*Y24/100 -> 174.80236 | Z52: =Y52*Z24/100 -> 207.66521 | AA52: =Z52*AA24/100 -> 235.70001 | AB52: =AA52*AB24/100 -> 258.09151 | AC52: =AB52*AC24/100 -> 276.93219 | AD52: =AC52*AD24/100 -> 305.73314 | ... AP52: =AO52*AP24/100 -> 183.50422
B53: idxIND2003DA,,t | C53: Пищевая промышленность | J53: 100 | K53: 128.87149 | L53: 138.39603 | M53: 153.71806 | N53: 179.65198 | O53: 179.7015 | P53: 168.93539 | Q53: 197.29381 | R53: 148.91171 | S53: 143.70435 | T53: 159.47176 | U53: 253.49874 | V53: 233.48071 | W53: =V53*W23/100 -> 246.08867 | X53: =W53*X23/100 -> 284.47851 | Y53: =X53*Y23/100 -> 334.54672 | Z53: =Y53*Z23/100 -> 360.30682 | AA53: =Z53*AA23/100 -> 453.62629 | AB53: =AA53*AB23/100 -> 468.59595 | AC53: =AB53*AC23/100 -> 618.54666 | AD53: =AC53*AD23/100 -> 785.55426 | ... AP53: =AO53*AP23/100 -> 74124.72
B54: idxIND2003Other,t | C54: Прочее | V54: 320.19923 | W54: =V54*W28/100 -> 445.17839 | X54: =W54*X28/100 -> 623.79986 | Y54: =X54*Y28/100 -> 755.62153 | Z54: =Y54*Z28/100 -> 773.73021 | AA54: =Z54*AA28/100 -> 798.78235 | AB54: =AA54*AB28/100 -> 1175.3262 | AC54: =AB54*AC28/100 -> 1358.3566 | AD54: =AC54*AD28/100 -> 1315.3157 | ... AP54: =AO54*AP28/100 -> 2185.2823
C56: Расчет доли ВДС в выпуске
B57: VACDE,t | C57: Промышленность, ВДС | H57: 858 | I57: 1117.2 | J57: 1440.2 | K57: 1644.4 | L57: 1645.1 | M57: 1987 | N57: 2349.4 | O57: 2515.8 | P57: 2957.4 | Q57: 3642.7 | R57: 4368.9 | S57: 4947.8 | T57: 5103.1 | U57: 5510.9 | V57: =GDP!V17 -> 7726.3 | W57: =GDP!W17 -> 9266.9 | X57: =GDP!X17 -> 12839.9 | Y57: =GDP!Y17 -> 15031.5 | Z57: =GDP!Z17 -> 16873.8 | AA57: =GDP!AA17 -> 19511.3 | AB57: =GDP!AB17 -> 24139 | AC57: =GDP!AC17 -> 27762 | ... AE57: =GDP!AE17 -> 32666.7 | AF57: =AF61*AF4 -> 34030.311 | AG57: =AG61*AG4 -> 45920.068 | AH57: =AH61*AH4 -> 55589.394 | AI57: =AI61*AI4 -> 68434.877 | AJ57: =AJ61*AJ4 -> 84873.628 | AK57: =AK61*AK4 -> 84118.542 | AL57: =AL61*AL4 -> 89378.252 | AM57: =AM61*AM4 -> 91564.311 | ... AP57: =AP61*AP4 -> 130259.04
B58: gVACDE,t | C58: - рост | L58: 106.4 | M58: 105.5 | N58: 109.9 | O58: 96.5 | P58: 93.5 | Q58: 109.2 | R58: 105.7 | S58: 110.8 | T58: 103.8 | U58: 105 | V58: =V18 -> 111.3 | W58: =W18 -> 116 | X58: =X18 -> 121.3 | Y58: =Y18 -> 110.6 | Z58: =Z18 -> 113.2 | AA58: =AA18 -> 108.8 | AB58: =AB18 -> 120.8 | AC58: =AC18 -> 115.4 | ... AP58: =AP18 -> 122.3396
B59: defVACDE,t /INDt | C59: - дефлятор | L59: 94.024971 | M59: 114.48619 | N59: 107.5874 | O59: 110.96649 | P59: 125.7252 | Q59: 112.79522 | R59: 113.46808 | S59: 102.21162 | T59: 99.362976 | U59: 102.84878 | V59: 125.96615 | W59: =W57/V57/W58*10000 -> 103.39628 | X59: =X57/W57/X58*10000 -> 114.22637 | Y59: =Y57/X57/Y58*10000 -> 105.84871 | Z59: =Z57/Y57/Z58*10000 -> 99.166309 | AA59: =AA57/Z57/AA58*10000 -> 106.27825 | AB59: =AB57/AA57/AB58*10000 -> 102.4156 | AC59: =AC57/AB57/AC58*10000 -> 99.661098 | AD59: =AD57/AC57/AD58*10000 -> 95.655868 | ... AP59: =AP57/AO57/AP58*10000 -> 91.000144
V60: =V23 -> 103.5 | W60: =W23 -> 105.4 | X60: =X23 -> 115.6 | Y60: =Y23 -> 117.6 | Z60: =Z23 -> 107.7 | AA60: =AA23 -> 125.9 | AB60: =AB23 -> 103.3 | AC60: =AC23 -> 132 | ... AP60: =AP23 -> 104.49789
B61: VACDE,t | C61: Доля ВДС/выпуск | I61: 0.46203474 | J61: 0.44936037 | K61: 0.41609312 | L61: 0.38454885 | M61: 0.42612052 | N61: 0.42171962 | O61: 0.41202096 | P61: 0.45491463 | Q61: 0.59089656 | R61: 0.5556983 | S61: 0.52060185 | T61: 0.5127713 | U61: 0.52312097 | V61: 0.63351099 | W61: =W57/W4 -> 0.61410868 | X61: =X57/X4 -> 0.64108107 | Y61: =Y57/Y4 -> 0.62909362 | Z61: =Z57/Z4 -> 0.6110751 | AA61: =AA57/AA4 -> 0.63163807 | AB61: =AB57/AB4 -> 0.62167452 | AC61: =AC57/AC4 -> 0.65753386 | AD61: 0.66 | AE61: 0.4817072 | AF61: 0.51 | AG61: 0.55 | AH61: 0.53 | AI61: 0.52 | AJ61: 0.515 | AK61: 0.5011 | AL61: 0.52 | AM61: 0.53 | AN61: 0.54 | AO61: 0.54 | AP61: 0.54
B62: proxy1t | C62: Прокси (глинозем/дефлятор промпроизводства) | I62: 100 | J62: 107.09889 | K62: 130.07161 | L62: 136.02792 | M62: 141.62091 | N62: 132.88357 | O62: 119.74356 | P62: 123.7828 | Q62: 150.54186 | R62: 153.72024 | S62: 153.309 | T62: 150.59744 | U62: 154.59844 | V62: 168.41259 | W62: =V62*W163/V163*(Household!W2/Household!V2)/(W33/100) -> 209.34672 | X62: =W62*X163/W163*(Household!X2/Household!W2)/(X33/100) -> 225.4197 | Y62: =X62*Y163/X163*(Household!Y2/Household!X2)/(Y33/100) -> 244.85867 | Z62: =Y62*Z163/Y163*(Household!Z2/Household!Y2)/(Z33/100) -> 242.7149 | AA62: =Z62*AA163/Z163*(Household!AA2/Household!Z2)/(AA33/100) -> 241.10826 | AB62: =AA62*AB163/AA163*(Household!AB2/Household!AA2)/(AB33/100) -> 253.95128 | AC62: =AB62*AC163/AB163*(Household!AC2/Household!AB2)/(AC33/100) -> 322.34494 | AD62: =AC62*AD163/AC163*(Household!AD2/Household!AC2)/(AD33/100) -> 313.58724 | ... AP62: =AO62*AP163/AO163*(Household!AP2/Household!AO2)/(AP33/100) -> 486.80066
AD63: =AD57/AD4 -> 0.63531058 | AE63: =AE57/AE4 -> 0.60697337 | AF63: =AF57/AF4 -> 0.51 | AG63: =AG57/AG4 -> 0.55 | AH63: =AH57/AH4 -> 0.53 | AI63: =AI57/AI4 -> 0.52 | AJ63: =AJ57/AJ4 -> 0.515 | AK63: =AK57/AK4 -> 0.5011 | ... AP63: =AP57/AP4 -> 0.54
C64: Предпосылки:
B65: INDDA, t /RETt | C65: доля пищевой промышленности к розничному товарооброту | J65: 0.34399916 | K65: 0.33410883 | L65: 0.37588879 | M65: 0.33616739 | N65: 0.33678105 | O65: 0.26883231 | P65: 0.24411747 | Q65: 0.50138176 | R65: 0.32886674 | S65: 0.36809816 | T65: 2.7353816 | U65: 0.25468071 | V65: =V9/Household!V9 -> 0.2421806 | W65: =W9/Household!W9 -> 0.22824695 | X65: =X9/Household!X9 -> 0.23346641 | Y65: =Y9/Household!Y9 -> 0.23926132 | Z65: =Z9/Household!Z9 -> 0.21640753 | AA65: =AA9/Household!AA9 -> 0.26231461 | AB65: =AB9/Household!AB9 -> 0.22874667 | AC65: =AC9/Household!AC9 -> 0.25511416 | ... AF65: =AF9/Household!AF9 -> 0.18919696 | AG65: 0.242 | AH65: 0.242379 | AI65: 0.2781395 | AJ65: 0.31667 | AK65: 0.31374 | AL65: 0.328343 | AM65: 0.32842 | AN65: 0.329 | AO65: 0.325 | AP65: 0.327
B66: INDDther, t /DDIND, t | C66: доля прочей в промышленности | J66: 0.44554791 | K66: 0.44375902 | L66: 0.38325129 | M66: 0.40775746 | N66: 0.40187863 | O66: 0.44942062 | P66: 0.36546307 | Q66: -0.23084661 | R66: 0.22830795 | S66: 0.18457947 | T66: 0.18642913 | U66: 0.26606517 | V66: =V14/(V9+V10+V14-(V186+V187+V188)*Assumptions!V11) -> 0.29392051 | W66: =W14/(W9+W10+W14-(W186+W187+W188)*Assumptions!W11) -> 0.32363118 | X66: =X14/(X9+X10+X14-(X186+X187+X188)*Assumptions!X11) -> 0.32141142 | Y66: =Y14/(Y9+Y10+Y14-(Y186+Y187+Y188)*Assumptions!Y11) -> 0.34006179 | Z66: =Z14/(Z9+Z10+Z14-(Z186+Z187+Z188)*Assumptions!Z11) -> 0.35311481 | AA66: =AA14/(AA9+AA10+AA14-(AA186+AA187+AA188)*Assumptions!AA11) -> 0.30576747 | AB66: =AB14/(AB9+AB10+AB14-(AB186+AB187+AB188)*Assumptions!AB11) -> 0.30686263 | AC66: =AC14/(AC9+AC10+AC14-(AC186+AC187+AC188)*Assumptions!AC11) -> 0.29457891 | ... AF66: =AF14/(AF9+AF10+AF14-(AF186+AF187+AF188)*Assumptions!AF11) -> 0.30346624 | AG66: 0.211 | AH66: 0.2122 | AI66: 0.233 | AJ66: 0.233 | AK66: 0.253 | AL66: 0.279 | AM66: 0.273 | AN66: 0.299 | AO66: 0.299 | AP66: 0.299
R67: 3513.7301 | S67: 3808.2863
C68: Подробное описание
C69: Электроэнергетика
B70: qYEl,t | C70: Производство, млн. кВт - час | G70: 14300 | H70: 14400 | I70: 15300 | J70: 16509 | K70: 16491 | L70: 17090 | M70: 16935 | N70: 17494 | O70: 16147 | P70: 16117 | Q70: 16435 | R70: 16238 | S70: 16974 | T70: 17115 | U70: 16472 | V70: 17162 | W70: 17232 | X70: 18144 | Y70: 19742 | Z70: 20677 | AA70: 19771 | AB70: 20623.8 | AC70: 21399.5 | AD70: 21860.5 | AE70: 22427.7 | AF70: 23989.9 | AG70: =AF70*1.07 -> 25669.193 | AH70: =AG70*1.07 -> 27466.037 | AI70: =AH70*1.07 -> 29388.659 | AJ70: =AI70*1.07 -> 31445.865 | AK70: =AJ70*1.07 -> 33647.076 | AL70: =AK70*1.07 -> 36002.371 | AM70: =AL70*1.07 -> 38522.537 | AN70: =AM70*1.07 -> 41219.115 | ... AP70: =AO70*1.07 -> 47191.764
B71: qIMEl,t | C71: Импорт | G71: 5242.4 | H71: 5396.4 | I71: 4659.4 | J71: 4617.6 | K71: 4807.3 | L71: 4505.5 | M71: 4839.6 | N71: 4552 | O71: 6404 | P71: 6003 | Q71: 432 | R71: 172 | S71: 114 | T71: 117 | U71: 52 | V71: =Trade!V60 -> 63 | W71: =Trade!W60 -> 103 | X71: =Trade!X60 -> 110 | Y71: =Trade!Y60 -> 559.7 | Z71: =Trade!Z60 -> 294.4 | AA71: =Trade!AA60 -> 378.7 | AB71: =Trade!AB60 -> 883.4 | AC71: =Trade!AC60 -> 797.3 | ... AP71: =Trade!AP60 -> 3293.6169
B72: qTCEl,t | C72: ИТОГО ПОТРЕБЛЕНИЕ | G72: 19542.4 | H72: 19796.4 | I72: 19959.4 | J72: 21126.6 | K72: 21298.3 | L72: 21595.5 | M72: 21774.6 | N72: 22046 | O72: 22551 | P72: 22120 | Q72: 16867 | R72: 16410 | S72: 17088 | T72: 17232 | U72: 16524 | V72: =V70+V71 -> 17225 | W72: =W70+W71 -> 17335 | X72: =X70+X71 -> 18254 | Y72: =Y70+Y71 -> 20301.7 | Z72: =Z70+Z71 -> 20971.4 | AA72: =AA70+AA71 -> 20149.7 | AB72: =AB70+AB71 -> 21507.2 | AC72: =AC70+AC71 -> 22196.8 | ... AP72: =AP70+AP71 -> 50485.381
B73: qEXEl,t | C73: Экспорт | G73: 3908.7 | H73: 4047 | I73: 3831.2 | J73: 4597.2 | K73: 4451 | L73: 4257.9 | M73: 4231.2 | N73: 4464 | O73: 5539 | P73: 5960 | Q73: 286 | R73: 297 | S73: 775 | T73: 1061 | U73: 1364 | V73: =Trade!V19 -> 1396 | W73: =Trade!W19 -> 1428 | X73: =Trade!X19 -> 1421 | Y73: =Trade!Y19 -> 2945 | Z73: =Trade!Z19 -> 3175 | AA73: =Trade!AA19 -> 1870.3 | AB73: =Trade!AB19 -> 3302.6 | AC73: =Trade!AC19 -> 3341 | ... AP73: =Trade!AP19 -> 4448.7655
B74: qCEl,t | C74: Внутреннее потребление - всего (по секторам) | G74: 15633.7 | H74: 15749.4 | I74: 16128.2 | J74: 16529.4 | K74: 16847.3 | L74: 17337.6 | M74: 17543.4 | N74: 17582 | O74: 17012 | P74: 16160 | Q74: 16581 | R74: 16113 | S74: 16313 | T74: 16171 | U74: 15160 | V74: =V72-V73 -> 15829 | W74: =W72-W73 -> 15907 | X74: =X72-X73 -> 16833 | Y74: =Y72-Y73 -> 17356.7 | Z74: =Z72-Z73 -> 17796.4 | AA74: =AA72-AA73 -> 18279.4 | AB74: =AB72-AB73 -> 18204.6 | AC74: =AC72-AC73 -> 18855.8 | ... AP74: =AP72-AP73 -> 46036.616
C75: в том числе: | R75: * по внутреннему потреблению есть ограничение по мощности
B76: qCCDEEl,t | C76: Промышленность | G76: 5800 | H76: 6100 | I76: 6202 | J76: 6675 | K76: 7031 | L76: 7533 | M76: 8080 | N76: 8060 | O76: 7802 | P76: 7007 | Q76: 7344 | R76: 6335 | S76: 6150 | T76: 5251 | U76: 3935 | V76: 4242 | W76: 4114 | X76: 3790 | Y76: 3783 | Z76: 3990 | AA76: 2744 | AB76: 3934 | AC76: =AB76*AC102/AB102 -> 2545.6428 | AD76: =AC76*AD102/AC102 -> 2613.1513 | AE76: =AD76*AE102/AD102 -> 2959.5911 | AF76: =AE76*AF102/AE102 -> 3151.322 | AG76: =AF76*AG102/AF102 -> 3791.4536 | AH76: =AG76*AH102/AG102 -> 4446.9107 | AI76: =AH76*AI102/AH102 -> 5097.1272 | AJ76: =AI76*AJ102/AI102 -> 5840.0626 | ... AP76: =AO76*AP102/AO102 -> 13344.793
B77: qCFEl,t | C77: Строительство | G77: 20 | H77: 20 | I77: 30 | J77: 23 | K77: 21 | L77: 19 | M77: 25 | N77: 28 | O77: 59 | P77: 46 | Q77: 90 | R77: 115 | S77: 194 | T77: 245 | U77: 122 | V77: 45 | W77: 67 | X77: 227 | Y77: 39 | Z77: 46 | AA77: 57 | AB77: 43 | AC77: =AB77*GDP!AC52/GDP!AB52 -> 47.902 | AD77: =AC77*GDP!AD52/GDP!AC52 -> 53.793946 | AE77: =AD77*GDP!AE52/GDP!AD52 -> 61.534385 | AF77: =AE77*GDP!AF52/GDP!AE52 -> 41.900267 | AG77: =AF77*GDP!AG52/GDP!AF52 -> 72.592182 | AH77: =AG77*GDP!AH52/GDP!AG52 -> 84.269401 | AI77: =AH77*GDP!AI52/GDP!AH52 -> 93.429786 | AJ77: =AI77*GDP!AJ52/GDP!AI52 -> 116.82162 | ... AP77: =AO77*GDP!AP52/GDP!AO52 -> 420.26011
B78: qCABEl,t | C78: Сельское хозяйство | G78: 4300 | H78: 4500 | I78: 4200 | J78: 4257 | K78: 4309 | L78: 3919 | M78: 3908 | N78: 3612 | O78: 3144 | P78: 3722 | Q78: 3593 | R78: 3742 | S78: 3832 | T78: 2600 | U78: 2328 | V78: 2496 | W78: 2807 | X78: 2754 | Y78: 2241 | Z78: 2338 | AA78: 2619 | AB78: 2086 | AC78: =AC137 -> 2949.4886 | AD78: =AD137 -> 3309.3262 | AE78: =AE137 -> 3660.1148 | AF78: =AF137 -> 4007.8257 | AG78: =AG137 -> 4810.7593 | AH78: =AH137 -> 5708.918 | AI78: =AI137 -> 6705.027 | AJ78: =AJ137 -> 7251.7535 | ... AP78: =AP137 -> 11187.917
B79: qCIEl,t | C79: Транспорт | G79: 40 | H79: 30 | I79: 20 | J79: 23 | K79: 38 | L79: 24 | M79: 44 | N79: 52 | O79: 44 | P79: 41 | Q79: 30 | R79: 161 | S79: 37 | T79: 38 | U79: 41 | V79: 45 | W79: 35 | X79: 30 | Y79: 7 | Z79: 8 | AA79: 8 | AB79: 9 | AC79: =AB79*(GDP!AC55/GDP!AB55) -> 8.64 | AD79: =AC79*(GDP!AD55/GDP!AC55) -> 10.51488 | AE79: =AD79*(GDP!AE55/GDP!AD55) -> 12.300542 | AF79: =AE79*(GDP!AF55/GDP!AE55) -> 16.961681 | AG79: =AF79*(GDP!AG55/GDP!AF55) -> 6.9483779 | AH79: =AG79*(GDP!AH55/GDP!AG55) -> 7.1113759 | AI79: =AH79*(GDP!AI55/GDP!AH55) -> 6.9956274 | AJ79: =AI79*(GDP!AJ55/GDP!AI55) -> 7.2053163 | ... AP79: =AO79*(GDP!AP55/GDP!AO55) -> 11.592845
B80: qCHHEl,t | C80: Население | G80: 2800 | H80: 2500 | I80: 2900 | J80: 2700 | K80: 2600 | L80: 2700 | M80: 2600 | N80: 2400 | O80: 2400 | P80: 2700 | Q80: 3031 | R80: 3046 | S80: 3061 | T80: 4503 | U80: 4692 | V80: 4914 | W80: 4845 | X80: 5424 | Y80: 5579 | Z80: 6019 | AA80: 6857 | AB80: 5410 | AC80: =AB80*1.02 -> 5518.2 | AD80: =AC80*1.02 -> 5628.564 | AE80: =AD80*1.02 -> 5741.1353 | AF80: =AE80*1.02 -> 5855.958 | AG80: =AF80*1.02 -> 5973.0771 | AH80: =AG80*1.02 -> 6092.5387 | AI80: =AH80*1.02 -> 6214.3895 | AJ80: =AI80*1.02 -> 6338.6773 | ... AP80: =AO80*1.02 -> 7138.3801
B81: qLEl,t | C81: Потери | G81: 2200 | H81: 2200 | I81: 2300 | J81: 2527 | K81: 2455 | L81: 2746 | M81: 2745 | N81: 2954 | O81: 2985 | P81: 2099 | Q81: 2330 | R81: 2271 | S81: 2445 | T81: 2528 | U81: 2804 | V81: 2670 | W81: 2746 | X81: 2884 | Y81: 2878 | Z81: 2429 | AA81: 2549 | AB81: 4897.3 | AC81: 4760.7 | AD81: 4642.8 | AE81: 6196.2191 | AF81: 8929.4622 | AG81: 11914.863 | AH81: 15630.529 | AI81: 16706.914 | AJ81: 17829.422 | AK81: 19652.584 | AL81: 20948.24 | AM81: 22332.992 | AN81: 23813.044 | AO81: 25395.035 | AP81: 27086.066
B82: qCOthEl,t | C82: Прочее | G82: 473.7 | H82: 399.4 | I82: 476.2 | J82: 324.4 | K82: 393.3 | L82: 396.6 | M82: 141.4 | N82: 476 | O82: 578 | P82: 545 | Q82: 163 | R82: 443 | S82: 594 | T82: 1006 | U82: 1238 | V82: 1417 | W82: 1293 | X82: 1724 | Y82: 2625 | Z82: 2740 | AA82: 3445.7 | AB82: 1820.5 | AC82: =AC74-SUM(AC76:AC81) -> 3025.2266 | AD82: =AD74-SUM(AD76:AD81) -> 2793.0497 | AE82: =AE74-SUM(AE76:AE81) -> 1512.8968 | AF82: =AF74-SUM(AF76:AF81) -> 739.86282 | AG82: =AG74-SUM(AG76:AG80) -> 9774.4111 | AH82: =AH74-SUM(AH76:AH80) -> 9893.5051 | AI82: =AI74-SUM(AI76:AI80) -> 10046.602 | AJ82: =AJ74-SUM(AJ76:AJ80) -> 10674.494 | AK82: =AK74-SUM(AK76:AK80) -> 11278.142 | AL82: =AL74-SUM(AL76:AL80) -> 11907.858 | AM82: =AM74-SUM(AM76:AM80) -> 12511.236 | AN82: =AN74-SUM(AN76:AN80) -> 13047.456 | ... AP82: =AP74-SUM(AP76:AP80) -> 13933.673
B83: qLYEl,t | C83: потери к выпуску | G83: 0.12685672 | H83: 0.12502557 | I83: 0.13024225 | J83: 0.13586314 | K83: 0.13028503 | L83: 0.14568026 | M83: 0.14424896 | N83: 0.15472449 | O83: 0.15256056 | P83: 0.10483992 | Q83: 0.16028066 | R83: 0.16061956 | S83: 0.16697398 | T83: 0.17192601 | U83: 0.20437318 | V83: 0.18344212 | W83: 0.188224 | X83: 0.18763826 | Y83: 0.16518395 | Z83: 0.1310918 | AA83: 0.14482132 | AB83: 0.29484933 | AC83: =AC81/(AC72-AC81) -> 0.27303698 | AD83: =AD81/(AD72-AD81) -> 0.25771857 | AE83: =AE81/(AE72-AE81) -> 0.34714126 | AF83: =AF81/(AF72-AF81) -> 0.50271849 | AG83: 0.43560665 | AH83: 0.53560665 | AI83: 0.53651306 | AJ83: 0.53651306 | AK83: 0.53651306 | AL83: 0.53651306 | AM83: 0.53651306 | AN83: 0.53651306 | AO83: 0.53651306 | AP83: 0.53651306
B84: qLYEl,t | C84: потери к выпуску | AC84: =AC81/(AC72-AC81) -> 0.27303698 | AD84: =AD81/(AD72-AD81) -> 0.25771857 | AE84: =AE81/(AE72-AE81) -> 0.34714126 | AF84: =AF81/(AF72-AF81) -> 0.50271849 | AG84: =AG81/(AG72-AG81) -> 0.72166322 | AH84: =AH81/(AH72-AH81) -> 1.0671796 | AI84: =AI81/(AI72-AI81) -> 1.0744662 | AJ84: =AJ81/(AJ72-AJ81) -> 1.0778874 | ... AP84: =AP81/(AP72-AP81) -> 1.1575581
AE85: =0.347*(SUM(AE76:AE80,AE82,AE73)) -> 6193.6977 | AF85: =0.534*(SUM(AF76:AF80,AF82,AF73)) -> 9485.0953 | AG85: =0.43561*(SUM(AG76:AG80,AG82,AG73)) -> 12382.277 | AH85: =0.53561*(SUM(AH76:AH80,AH82,AH73)) -> 16216.721 | AI85: =0.53561*(SUM(AI76:AI80,AI82,AI73)) -> 17276.61 | AJ85: =0.53561*(SUM(AJ76:AJ80,AJ82,AJ73)) -> 18409.185 | AK85: =0.53561*(SUM(AK76:AK80,AK82,AK73)) -> 19619.505 | AL85: =0.53561*(SUM(AL76:AL80,AL82,AL73)) -> 20912.98 | AM85: =0.53561*(SUM(AM76:AM80,AM82,AM73)) -> 22295.401 | AN85: =0.53561*(SUM(AN76:AN80,AN82,AN73)) -> 23772.962 | AO85: =0.53561*(SUM(AO76:AO80,AO82,AO73)) -> 25352.29 | AP85: =0.53561*(SUM(AP76:AP80,AP82,AP73)) -> 27040.475
C86: Импорт, млн кВт | G86: 5242.4 | H86: 5389.4 | I86: 4539.1 | J86: 4617.6 | K86: 4810.2 | L86: 4505.5 | M86: 4839.5 | N86: 4360.6 | O86: 5145.5 | P86: 4276.1 | Q86: 338.9 | R86: 134.93241 | S86: 89.431944 | T86: 91.785417 | U86: 40.793519 | V86: 49.422917 | W86: =V86*W71/V71 -> 80.802546 | X86: =W86*X71/W71 -> 86.293981 | Y86: =X86*Y71/X71 -> 439.07947 | Z86: =Y86*Z71/Y71 -> 230.95407 | AA86: =Z86*AA71/Z71 -> 297.08664 | AB86: =AA86*AB71/AA71 -> 693.01912 | AC86: =AB86*AC71/AB71 -> 625.47447 | AD86: =AC86*AD71/AC71 -> 625.47447 | ... AP86: =AO86*AP71/AO71 -> 2583.8119
C87: Экспорт, млн кВт | G87: 3908.7 | H87: 4040.1 | I87: 3675.6 | J87: 4713.6 | K87: 4450.9 | L87: 4257.9 | M87: 4231.2 | N87: 4259 | O87: 4264.8 | P87: 4227.3 | Q87: 286 | R87: 297 | S87: 775 | T87: 1061 | U87: 1364 | V87: =V73 -> 1396 | W87: =W73 -> 1428 | X87: =X73 -> 1421 | Y87: =Y73 -> 2945 | Z87: =Z73 -> 3175 | AA87: =AA73 -> 1870.3 | AB87: =AB73 -> 3302.6 | AC87: =AC73 -> 3341 | ... AP87: =AP73 -> 4448.7655
C88: Импорт, млн. долл. | G88: 131.1 | H88: 93.9 | I88: 76.9 | J88: 61.4 | K88: 65 | L88: 58.1 | M88: 66.8 | N88: 65.6 | O88: 87.5 | P88: 76.1 | Q88: 12.9
B89: EXUSEl,t | C89: Экспорт, млн. долл. | G89: 86.8 | H89: 80.1 | I89: 64.5 | J89: 54.9 | K89: 57.6 | L89: 52.5 | M89: 49 | N89: 59.5 | O89: 59.7484 | P89: 63.1881 | Q89: 3.4600192 | R89: 4.269 | S89: 21.335 | T89: 33.268 | U89: 44.1 | V89: =Trade!V10 -> 48.4 | W89: =Trade!W10 -> 51.7 | X89: =Trade!X10 -> 53.5 | Y89: =Trade!Y10 -> 56.4 | Z89: =Trade!Z10 -> 93.1 | AA89: =Trade!AA10 -> 56.4 | AB89: =Trade!AB10 -> 95.961 | AC89: =Trade!AC10 -> 106.2 | ... AP89: =Trade!AP10 -> 229.99992
AG90: =AG83*(SUM(AG76:AG80,AG82,AG73)) -> 12382.182 | AH90: =AH83*(SUM(AH76:AH80,AH82,AH73)) -> 16216.62 | AI90: =AI83*(SUM(AI76:AI80,AI82,AI73)) -> 17305.739 | AJ90: =AJ83*(SUM(AJ76:AJ80,AJ82,AJ73)) -> 18440.223 | AK90: =AK83*(SUM(AK76:AK80,AK82,AK73)) -> 19652.584 | AL90: =AL83*(SUM(AL76:AL80,AL82,AL73)) -> 20948.24 | AM90: =AM83*(SUM(AM76:AM80,AM82,AM73)) -> 22332.992 | AN90: =AN83*(SUM(AN76:AN80,AN82,AN73)) -> 23813.044 | ... AP90: =AP83*(SUM(AP76:AP80,AP82,AP73)) -> 27086.066
B93: qCAPEl,t | C93: Мощность, тыс. кВт | J93: 4420 | K93: 4396 | L93: 4404 | M93: 4389 | N93: 4386 | O93: 5069 | P93: 5078 | Q93: 5105 | R93: 5079 | S93: 6168 | T93: 6180 | U93: 6280 | V93: 6283 | W93: 6577 | X93: 5718 | Y93: 6197 | Z93: 6475 | AA93: 6356 | AB93: 6476 | AC93: =AB93*1.002 -> 6488.952 | AD93: =AC93*1.002 -> 6501.9299 | AE93: =AD93*1.002 -> 6514.9338 | AF93: =AE93*1.002 -> 6527.9636 | AG93: =AF93*1.002 -> 6541.0196 | AH93: =AG93*1.002 -> 6554.1016 | AI93: =AH93*1.002 -> 6567.2098 | AJ93: =AI93*1.002 -> 6580.3442 | ... AP93: =AO93*1.002 -> 6659.7042
B94: UREl,t | C94: загрузка мощностей, % | J94: 0.42637761 | K94: 0.428238 | L94: 0.44298666 | M94: 0.44046917 | N94: 0.45531965 | O94: 0.36363481 | P94: 0.36231591 | Q94: 0.36751059 | R94: 0.36496416 | S94: 0.31414903 | T94: 0.31614355 | U94: 0.29942123 | V94: =V70/(V93*24*365)*1000 -> 0.31181481 | W94: =W70/(W93*24*365)*1000 -> 0.29909127 | X94: =X70/(X93*24*365)*1000 -> 0.3622303 | Y94: =Y70/(Y93*24*365)*1000 -> 0.36366838 | Z94: =Z70/(Z93*24*365)*1000 -> 0.36453871 | AA94: =AA70/(AA93*24*365)*1000 -> 0.3550918 | AB94: =AB70/(AB93*24*365)*1000 -> 0.36354464 | AC94: =AC70/(AC93*24*365)*1000 -> 0.37646531 | ... AP94: =AP70/(AP93*24*365)*1000 -> 0.80892297
B95: qEXP*El,t | C95: потенциал чистого экспорта э/э, млн. кВт-ч/год | J95: 1120.6124 | K95: 1042.886 | L95: 475.7948 | M95: 570.9658 | N95: 0 | O95: 4071.2139 | P95: 4137.1113 | Q95: 3926.8035 | R95: 4020.0999 | S95: 7627.6854 | T95: 7534.5486 | U95: 8576.4086 | V95: =(0.46-V94)*V93*24*365/1000 -> 8155.9768 | W95: =(0.46-W94)*W93*24*365/1000 -> 9270.6792 | X95: =(0.46-X94)*X93*24*365/1000 -> 4897.2528 | Y95: =(0.46-Y94)*Y93*24*365/1000 -> 5229.4312 | Z95: =(0.46-Z94)*Z93*24*365/1000 -> 5414.66 | AA95: =(0.46-AA94)*AA93*24*365/1000 -> 5841.1376 | AB95: =(0.46-AB94)*AB93*24*365/1000 -> 5471.8896 | AC95: =(0.46-AC94)*AC93*24*365/1000 -> 4748.381 | ... AP95: =(0.46-AP94)*AP93*24*365/1000 -> -20355.82
B96: PUREl,t | C96: использование потенциала, % | O96: 0 | P96: 0 | Q96: 0 | R96: 0.031093755 | S96: 0.086658005 | T96: 0.12528952 | U96: 0.15297779 | V96: =MAX(V73-V71,0)/V95 -> 0.16343842 | W96: =MAX(W73-W71,0)/W95 -> 0.14292372 | X96: =MAX(X73-X71,0)/X95 -> 0.26770111 | Y96: =MAX(Y73-Y71,0)/Y95 -> 0.45612991 | Z96: =MAX(Z73-Z71,0)/Z95 -> 0.53200016 | AA96: =MAX(AA73-AA71,0)/AA95 -> 0.25536122 | AB96: =MAX(AB73-AB71,0)/AB95 -> 0.44211418 | AC96: =MAX(AC73-AC71,0)/AC95 -> 0.53569838 | ... AP96: =MAX(AP73-AP71,0)/AP95 -> -0.056747829
C99: Потребление электроэнергии
C100: Промышленность | J100: 6445 | K100: 6920 | L100: 7531 | M100: 7595 | N100: 7870 | O100: 7833 | P100: 7774
C101: - в т.ч. на двигательную силу | J101: 577 | K101: 607 | L101: 645 | M101: 680 | N101: 642 | O101: 682 | P101: 870 | T101: -251.49786 | U101: -1482.3595 | V101: 1741.6613 | W101: =W102-V102 -> 281.18947 | X101: =X102-W102 -> 678.28759 | Y101: =Y102-X102 -> 853.84426 | Z101: =Z102-Y102 -> 3873.7029 | AA101: =AA102-Z102 -> 1219.7413 | AB101: =AB102-AA102 -> 1339.4228 | AC101: =AC102-AB102 -> -5583.4802 | AD101: =AD102-AC102 -> 271.49522 | ... AP101: =AP102-AO102 -> 6929.3395
B102: qC*CDEEl,t | C102: - на технологические нужды и прочее | J102: 5868 | K102: 6313 | L102: 6886 | M102: 6915 | N102: 7228 | O102: 7151 | P102: 6904 | Q102: 8004.741 | R102: 6692.6315 | S102: 7567.1602 | T102: 7315.6624 | U102: 5833.3029 | V102: =V109+V116+V123+V130 -> 7574.9642 | W102: =W109+W116+W123+W130 -> 7856.1537 | X102: =X109+X116+X123+X130 -> 8534.4413 | Y102: =Y109+Y116+Y123+Y130 -> 9388.2855 | Z102: =Z109+Z116+Z123+Z130 -> 13261.988 | AA102: =AA109+AA116+AA123+AA130 -> 14481.73 | AB102: =AB109+AB116+AB123+AB130 -> 15821.153 | AC102: =AC109+AC116+AC123+AC130 -> 10237.672 | ... AP102: =AP109+AP116+AP123+AP130 -> 53668.023
C103: энергоемкость выпуска 1 | J103: 64.45 | K103: 60.121633 | L103: 59.266359 | M103: 56.654045 | N103: 53.417085 | O103: 55.094249 | P103: 58.480498
B104: efCDEEl,t | C104: энергоемкость выпуска 2 | J104: 58.68 | K104: 54.847958 | L104: 54.190433 | M104: 51.581662 | N104: 49.059554 | O104: 50.297328 | P104: 51.935858 | Q104: 55.143099 | R104: 43.618007 | S104: 44.510459 | T104: 41.455814 | U104: 31.481616 | V104: 25 | W104: 26.3 | X104: 25 | Y104: 26 | Z104: 25 | AA104: 25 | AB104: 26 | AC104: 26 | AD104: 26 | AE104: 26 | AF104: 26 | AG104: 26 | AH104: 26 | AI104: 26 | AJ104: 26 | AK104: 26 | AL104: 26 | AM104: 26 | AN104: 26 | AO104: 26 | AP104: 26
C107: Цветные металлы | J107: 5709 | K107: 6248 | L107: 6671 | M107: 7195 | N107: 7291 | O107: 7174 | P107: 7422 | Q107: 7803.815 | R107: 6523.9893 | S107: 6700.137 | T107: 6432.1315 | U107: 5583.0902 | V107: =V108+V109 -> 7274.7665 | W107: =W108+W109 -> 7616.6805 | X107: =X108+X109 -> 8332.6485 | Y107: =Y108+Y109 -> 9224.2419 | Z107: =Z108+Z109 -> 13116.872 | AA107: =AA108+AA109 -> 14349.858 | AB107: =AB108+AB109 -> 15698.745 | AC107: =AC108+AC109 -> 10121.802 | ... AP107: =AP108+AP109 -> 53600.301
C108: - в т.ч. на двигательную силу | J108: 249 | K108: 284 | L108: 287 | M108: 428 | N108: 419 | O108: 413 | P108: 691
B109: qC*DlEl,t | C109: - на технологические нужды и прочее | J109: 5460 | K109: 5964 | L109: 6384 | M109: 6767 | N109: 6872 | O109: 6761 | P109: 6731 | Q109: 7803.815 | R109: 6523.9893 | S109: 6700.137 | T109: 6432.1315 | U109: 5583.0902 | V109: 7274.7665 | W109: =W111*W51 -> 7616.6805 | X109: =X111*X51 -> 8332.6485 | Y109: =Y111*Y51 -> 9224.2419 | Z109: =Z111*Z51 -> 13116.872 | AA109: =AA111*AA51 -> 14349.858 | AB109: =AB111*AB51 -> 15698.745 | AC109: =AC111*AC51 -> 10121.802 | AD109: =AD111*AD51 -> 10395.091 | ... AP109: =AP111*AP51 -> 53600.301
...

Sheet Industry-2
B1: Var. Name | C1: Наименование индикатора | D1: 2015 | E1: 2016 | F1: 2017 | G1: 2018 | H1: 2019 | I1: 2020 | J1: 2021 | K1: 2022 | L1: 2023 | M1: 2024 | N1: 2025 | O1: 2026 | P1: 2027 | Q1: 2028 | R1: 2029 | S1: 2030 | T1: 2031 | U1: 2032 | V1: 2033 | W1: 2034 | X1: 2035
C2: Промышленность | E2: =E4-D4 -> 2894 | F2: =F4-E4 -> 4938.512 | G2: =G4-F4 -> 3865.388 | H2: =H4-G4 -> 3719.4 | I2: =I4-H4 -> 3276.7 | J2: =J4-I4 -> 7939 | K2: =K4-J4 -> 3392.4 | L2: =L4-K4 -> 4594.6 | ... X2: =X4-W4 -> 24808.445
C3: Номиналы, млн. сомони
B4: INDCDE,t | C4: Промышленное производство | D4: =D5+D8+D15 -> 12196 | E4: =E5+E8+E15 -> 15090 | F4: =F5+F8+F15 -> 20028.512 | G4: =G5+G8+G15 -> 23893.9 | H4: =H5+H8+H15 -> 27613.3 | I4: =I5+I8+I15 -> 30890 | J4: =J5+J8+J15 -> 38829 | K4: =K5+K8+K15 -> 42221.4 | L4: =L5+L8+L15 -> 46816 | M4: =M5+M8+M15+M17 -> 53819 | N4: =N5+N8+N15+N17 -> 66726.1 | O4: =O5+O8+O15+O17 -> 79702.285 | P4: =P5+P8+P15+P17 -> 93736.758 | Q4: =Q5+Q8+Q15+Q17 -> 107074.27 | R4: =R5+R8+R15+R17 -> 116280.77 | S4: =S5+S8+S15+S17 -> 125031.66 | T4: =T5+T8+T15+T17 -> 140359.14 | ... X4: =X5+X8+X15+X17 -> 214158.32
B5: INDC,t | C5: Добыча полезных ископаемых | D5: =D6+D7 -> 1641 | E5: =E6+E7 -> 3004 | F5: =F6+F7 -> 4523.512 | G5: =G6+G7 -> 4685.9 | H5: =H6+H7 -> 4853.3 | I5: =I6+I7 -> 4309 | J5: =J6+J7 -> 8409 | K5: =K6+K7 -> 8890.9 | ... X5: =X6+X7 -> 90328.822
B6: INDC13,t | C6: Добыча неэнергетических материалов | D6: 1438 | E6: 2782 | F6: 4225.986 | G6: 4355.2 | H6: 4476.7 | I6: 3880 | J6: 7924 | K6: 8309 | L6: 8795 | M6: 12653.6 | N6: 19179.5 | O6: 18957.619 | P6: 19739.659 | Q6: 22354.902 | R6: 25985.802 | S6: 30281.432 | T6: 31171.799 | U6: 36737.436 | V6: 42478.617 | W6: 48850.409 | X6: 58620.491
B7: INDCOther,t | C7: Добыча энергетических материалов | D7: 203 | E7: 222 | F7: 297.526 | G7: 330.7 | H7: 376.6 | I7: 429 | J7: 485 | K7: 581.9 | L7: 578 | M7: 709.5 | N7: 820.7 | O7: 1030.187 | P7: 2404.1941 | Q7: 3139.7964 | R7: 4559.6609 | S7: 7317.8179 | T7: 9358.0946 | U7: 12506.016 | V7: 17048.746 | W7: 27353.568 | X7: 31708.331
B8: INDDJ, t | C8: Обрабатывающая промышленность | D8: 8006 | E8: 9368 | F8: 11776 | G8: 13520 | H8: 15952 | I8: 19054 | J8: 22313 | K8: 25708.7 | L8: 28459.8 | M8: 30275.6 | N8: 34595.4 | O8: 38919.846 | P8: 47211.873 | Q8: 55225.987 | R8: 57299.824 | S8: 56373.305 | T8: 66356.653 | U8: 59586.671 | V8: 64537.103 | W8: 71515.254 | X8: 79090.129
B9: INDDA, t | C9: пищевые продукты и табак | D9: 3482 | E9: 3690 | F9: 4304 | G9: 4900 | H9: 5399 | I9: 7089 | J9: 7608 | K9: 10099 | L9: 11610 | M9: 11445.7 | N9: 12431.3 | O9: 17935.247 | P9: 22290.437 | Q9: 24269.859 | R9: 25392.84 | S9: 22113.054 | T9: 25931.865 | U9: 17228.505 | V9: 18198.359 | W9: 19179.974 | X9: 20356.537
B10: INDDB, t | C10: текстильное производство | D10: 1292 | E10: 1520 | F10: 2354 | G10: 2479 | H10: 2636 | I10: 2870 | J10: 4096 | K10: 4438 | L10: 4632 | M10: 4062.5 | N10: 4253.7 | O10: 3183.4964 | P10: 3488.3109 | Q10: 4395.0263 | R10: 4086.8335 | S10: 4341.3372 | T10: 4454.2592 | U10: 4541.2325 | V10: 4561.9669 | W10: 4611.8712 | X10: 4231.9817
B11: INDDJ, t | C11: металлургическое производство и готовые металлические изделия | D11: 1450.2 | E11: 1850 | F11: 2187.3 | G11: 2708.4 | H11: 3873.5 | I11: 4978 | J11: 5967 | K11: 6025 | L11: 6442 | M11: 8090.7 | N11: 10612.9 | O11: 12316.42 | P11: 14744.856 | Q11: 17724.661 | R11: 21103.898 | S11: 24971.255 | T11: 29491.137 | U11: 34415.781 | V11: 39073.095 | W11: 44893.255 | X11: 51586.437
B12: INDD27, t | C12: металлургическое производство | D12: =D11-D13 -> 1202.6249 | E12: =E11-E13 -> 1557.4819 | F12: =F11-F13 -> 1932.7978 | G12: =G11-G13 -> 2455.2806 | H12: =H11-H13 -> 3768.9349 | I12: =I11-I13 -> 4883.6227 | J12: =J11-J13 -> 5845.5362 | K12: =K11-K13 -> 5903.6407 | ... M12: =M11-M13 -> 7962.559 | N12: 10194.971 | O12: 11898.068 | P12: 14272.747 | Q12: 17187.775 | R12: 20496.843 | S12: 24286.657 | T12: 28704.965 | U12: 33521.055 | V12: 38079.78 | W12: 43774.492 | X12: 50323.41
B13: INDD28, t | C13: готовые металлические изделия | D13: 247.57509 | E13: 292.51809 | F13: 254.50217 | G13: 253.11944 | H13: 104.56511 | I13: 94.377342 | J13: 121.46379 | K13: 121.35925 | L13: 122.87853 | M13: 128.14095 | N13: 417.92925 | O13: 418.35228 | P13: 472.10847 | Q13: 536.88598 | R13: 607.05459 | S13: 684.59798 | T13: 786.17271 | U13: 894.7252 | V13: 993.31521 | W13: 1118.763 | X13: 1263.028
B14: INDDOther, t | C14: переработка прочие (d) | D14: 1781.8 | E14: 2308 | F14: 2930.7 | G14: 3432.6 | H14: 4043.5 | I14: 4117 | J14: 4642 | K14: 5146.7 | L14: 5775.8 | M14: =M8-M9-M10-M11-M13 -> 6548.559 | N14: 6879.5708 | O14: 5484.6823 | P14: 6688.2704 | Q14: 8836.4401 | R14: 6716.2526 | S14: 4947.6587 | T14: 6479.3914 | U14: 3401.1528 | V14: 2703.6816 | W14: 2830.1543 | X14: 2915.1728
B15: INDE, t | C15: Производство и распределение электроэнергии, газа и воды | D15: 2549 | E15: 2718 | F15: 3729 | G15: 5688 | H15: 6808 | I15: 7527 | J15: 8107 | K15: 7621.8 | L15: 8983.2 | M15: 9872.2 | N15: 11752.6 | O15: 20146.82 | P15: 23621.493 | Q15: 25532.598 | R15: 27549.635 | S15: 30091.528 | T15: 32429.824 | U15: 34913.593 | V15: 37520.128 | W15: 40333.726 | X15: 43345.604
H16: =H4-G4 -> 3719.4 | I16: =I4-H4 -> 3276.7 | J16: =J4-I4 -> 7939 | K16: =K4-J4 -> 3392.4 | L16: =L4-K4 -> 4594.6 | M16: =M4-L4 -> 7003 | N16: 12907.1 | O16: 12976.185 | P16: 14034.474 | Q16: 13337.515 | R16: 9206.4956 | S16: 8750.8954 | T16: 15327.473 | U16: 4507.21 | V16: 17924.69 | W16: 26558.833 | X16: 24808.445
